Workbook

Sheet 12月以降の契約について
B2: 《12月以降の契約について》
C4: ■目的
D5: 現在実施している要件定義について、11月末での完了を予定しております。12月以降の契約をどのような方針でプロジェクト進めることが両社として可能なのか検討することが目的となります。
D6: 当初の予定では、10月18日時点で「検索・表示」のみの見積提示を予定しておりましたが、早期に全体の金額感をお伝えすることで、12月以降の契約方針を決定するための材料にしたいと考えております。
D7: 当社都合で恐縮ですが、12月以降体制を維持するかどうか判断するために、10月末までに契約方針を決定させていただきたく思います。
D8: もし10月末までに確定できない場合、体制の維持が保証できなくなる可能性がありますので、ご了承くださいますようお願い申し上げます。
D9: また、契約方針が確定した場合は、契約締結日についても認識合わせをさせていただきたいです。1日での契約が難しい場合は先行着手依頼書などの対応も可能となりますので検討したいです。
C11: ■開発範囲(プロジェクト開始時)
C37: ■見積案
D38: 別シート「見積案」参照
C40: ■前提条件
D41: 12月1日の契約締結
D42: 遅くとも初旬での契約締結する必要がある。
D43: ※先行着手依頼書による対応も可能
C45: ■作業内容
D46: ・基本設計
D47: 要件定義のアウトプットをもとに成果物記載のドキュメントの作成を実施
D48: ・詳細設計
D49: 基本設計のアウトプットをもとに成果物記載のドキュメントの作成を実施
D50: ・製造
D51: 基本設計、詳細設計のアウトプットをもとにWebアプリケーション作成を実施
D52: Webアプリケーションの単体テストの実施
D53: ・結合テスト
D54: 結合テスト仕様書の作成
D55: 作成した仕様書をもとにWebアプリケーションのテストを実施
D56: ・総合テスト
D57: 総合テスト仕様書の作成
... D60: 出光様の受入テストの支援を実施"
C66: ■成果物
D67: 基本設計
D68: ・画面一覧
D69: ・帳票一覧
D70: ・バッチ一覧
D71: ・外部IF一覧
D72: ・メール一覧
D73: ・テーブル定義/ER図
D74: ・画面項目定義書
D75: ・帳票項目定義書
D76: 詳細設計
D77: ・API詳細設計書
D78: ・バッチ詳細設計書
... D84: ・総合テスト仕様書兼報告書

Sheet パターン① .NET＋VB6
H2: 0.125 | I2: 0.18 | J2: 0.275 | K2: 0.21 | L2: 0.125 | M2: 0.0625 | N2: =SUM(H2:M2) -> 0.9775
B3: 大分類 | C3: 中分類 | D3: 小分類 | F3: 行数 | G3: 画面機能 作業内容 | H3: 工程 | N3: 合計 （人日） | O3: 合計 （人月）
H4: 要件定義 | I4: 設計 | J4: 開発 | K4: 結合テスト | L4: システムテスト | M4: 受入テスト支援
B7: 機能 | C7: .NET | D7: S1_北海道製 | E7: ZZZY002.exe | F7: 3261 | H7: =$N7 * H$2 -> 1.5 | I7: =$N7 * I$2 -> 2.16 | J7: =$N7 * J$2 -> 3.3 | K7: =$N7 * K$2 -> 2.52 | L7: =$N7 * L$2 -> 1.5 | M7: =$N7 * M$2 -> 0.75 | N7: {=_xlfn.IFS( F7=0,0, F7<=1000,3, F7<=2300,6, F7<=4500,12, F7<=8200,24, F7<=16000,48, F7>16001,96 )} -> 12 | O7: =ROUNDUP(N7/20,2) -> 0.6
D8: ∟各所比較情報／品質管理 | E8: zbfz001.exe | F8: 1845 | H8: =$N8 * H$2 -> 0.75 | I8: =$N8 * I$2 -> 1.08 | J8: =$N8 * J$2 -> 1.65 | K8: =$N8 * K$2 -> 1.26 | L8: =$N8 * L$2 -> 0.75 | M8: =$N8 * M$2 -> 0.375 | N8: {=_xlfn.IFS( F8=0,0, F8<=1000,3, F8<=2300,6, F8<=4500,12, F8<=8200,24, F8<=16000,48, F8>16001,96 )} -> 6 | O8: =ROUNDUP(N8/20,2) -> 0.3
D9: ∟製油所情報／品質管理 | E9: bcfz001.exe | F9: 1882 | H9: =$N9 * H$2 -> 0.75 | I9: =$N9 * I$2 -> 1.08 | J9: =$N9 * J$2 -> 1.65 | K9: =$N9 * K$2 -> 1.26 | L9: =$N9 * L$2 -> 0.75 | M9: =$N9 * M$2 -> 0.375 | N9: {=_xlfn.IFS( F9=0,0, F9<=1000,3, F9<=2300,6, F9<=4500,12, F9<=8200,24, F9<=16000,48, F9>16001,96 )} -> 6 | O9: =ROUNDUP(N9/20,2) -> 0.3
D10: ∟製油所情報／データ検索 | E10: bciz001.exe | F10: 1897 | H10: =$N10 * H$2 -> 0.75 | I10: =$N10 * I$2 -> 1.08 | J10: =$N10 * J$2 -> 1.65 | K10: =$N10 * K$2 -> 1.26 | L10: =$N10 * L$2 -> 0.75 | M10: =$N10 * M$2 -> 0.375 | N10: {=_xlfn.IFS( F10=0,0, F10<=1000,3, F10<=2300,6, F10<=4500,12, F10<=8200,24, F10<=16000,48, F10>16001,96 )} -> 6 | O10: =ROUNDUP(N10/20,2) -> 0.3
D11: ∟品質情報検索／燃料油 | E11: zbfz0021.exe | F11: 4300 | H11: =$N11 * H$2 -> 1.5 | I11: =$N11 * I$2 -> 2.16 | J11: =$N11 * J$2 -> 3.3 | K11: =$N11 * K$2 -> 2.52 | L11: =$N11 * L$2 -> 1.5 | M11: =$N11 * M$2 -> 0.75 | N11: {=_xlfn.IFS( F11=0,0, F11<=1000,3, F11<=2300,6, F11<=4500,12, F11<=8200,24, F11<=16000,48, F11>16001,96 )} -> 12 | O11: =ROUNDUP(N11/20,2) -> 0.6
D12: ∟品質情報検索／工程 | E12: zbfz0022.exe | F12: 4400 | H12: =$N12 * H$2 -> 1.5 | I12: =$N12 * I$2 -> 2.16 | J12: =$N12 * J$2 -> 3.3 | K12: =$N12 * K$2 -> 2.52 | L12: =$N12 * L$2 -> 1.5 | M12: =$N12 * M$2 -> 0.75 | N12: {=_xlfn.IFS( F12=0,0, F12<=1000,3, F12<=2300,6, F12<=4500,12, F12<=8200,24, F12<=16000,48, F12>16001,96 )} -> 12 | O12: =ROUNDUP(N12/20,2) -> 0.6
D13: ∟品質情報検索／品質関連 | E13: zbfz0023.exe | F13: 3936 | H13: =$N13 * H$2 -> 1.5 | I13: =$N13 * I$2 -> 2.16 | J13: =$N13 * J$2 -> 3.3 | K13: =$N13 * K$2 -> 2.52 | L13: =$N13 * L$2 -> 1.5 | M13: =$N13 * M$2 -> 0.75 | N13: {=_xlfn.IFS( F13=0,0, F13<=1000,3, F13<=2300,6, F13<=4500,12, F13<=8200,24, F13<=16000,48, F13>16001,96 )} -> 12 | O13: =ROUNDUP(N13/20,2) -> 0.6
D14: ∟ローカルシステム | E14: bllz001.exe | F14: 1685 | H14: =$N14 * H$2 -> 0.75 | I14: =$N14 * I$2 -> 1.08 | J14: =$N14 * J$2 -> 1.65 | K14: =$N14 * K$2 -> 1.26 | L14: =$N14 * L$2 -> 0.75 | M14: =$N14 * M$2 -> 0.375 | N14: {=_xlfn.IFS( F14=0,0, F14<=1000,3, F14<=2300,6, F14<=4500,12, F14<=8200,24, F14<=16000,48, F14>16001,96 )} -> 6 | O14: =ROUNDUP(N14/20,2) -> 0.3
D15: ∟個別業務情報／運転管理 | E15: bedz001.exe | F15: 2275 | H15: =$N15 * H$2 -> 0.75 | I15: =$N15 * I$2 -> 1.08 | J15: =$N15 * J$2 -> 1.65 | K15: =$N15 * K$2 -> 1.26 | L15: =$N15 * L$2 -> 0.75 | M15: =$N15 * M$2 -> 0.375 | N15: {=_xlfn.IFS( F15=0,0, F15<=1000,3, F15<=2300,6, F15<=4500,12, F15<=8200,24, F15<=16000,48, F15>16001,96 )} -> 6 | O15: =ROUNDUP(N15/20,2) -> 0.3
D16: ∟個別業務情報／品質管理 | E16: zefz001.exe | F16: 998 | H16: =$N16 * H$2 -> 0.375 | I16: =$N16 * I$2 -> 0.54 | J16: =$N16 * J$2 -> 0.825 | K16: =$N16 * K$2 -> 0.63 | L16: =$N16 * L$2 -> 0.375 | M16: =$N16 * M$2 -> 0.1875 | N16: {=_xlfn.IFS( F16=0,0, F16<=1000,3, F16<=2300,6, F16<=4500,12, F16<=8200,24, F16<=16000,48, F16>16001,96 )} -> 3 | O16: =ROUNDUP(N16/20,2) -> 0.15
D17: S2_千葉（石） | E17: ZZZY002.exe | F17: 3261 | H17: =$N17 * H$2 -> 1.5 | I17: =$N17 * I$2 -> 2.16 | J17: =$N17 * J$2 -> 3.3 | K17: =$N17 * K$2 -> 2.52 | L17: =$N17 * L$2 -> 1.5 | M17: =$N17 * M$2 -> 0.75 | N17: {=_xlfn.IFS( F17=0,0, F17<=1000,3, F17<=2300,6, F17<=4500,12, F17<=8200,24, F17<=16000,48, F17>16001,96 )} -> 12 | O17: =ROUNDUP(N17/20,2) -> 0.6
D18: ∟各所比較情報／品質管理 | E18: zbfz001.exe | F18: 1845 | H18: =$N18 * H$2 -> 0.75 | I18: =$N18 * I$2 -> 1.08 | J18: =$N18 * J$2 -> 1.65 | K18: =$N18 * K$2 -> 1.26 | L18: =$N18 * L$2 -> 0.75 | M18: =$N18 * M$2 -> 0.375 | N18: {=_xlfn.IFS( F18=0,0, F18<=1000,3, F18<=2300,6, F18<=4500,12, F18<=8200,24, F18<=16000,48, F18>16001,96 )} -> 6 | O18: =ROUNDUP(N18/20,2) -> 0.3
D19: ∟製油所情報／品質管理 | E19: ccfz001.exe | F19: 1898 | H19: =$N19 * H$2 -> 0.75 | I19: =$N19 * I$2 -> 1.08 | J19: =$N19 * J$2 -> 1.65 | K19: =$N19 * K$2 -> 1.26 | L19: =$N19 * L$2 -> 0.75 | M19: =$N19 * M$2 -> 0.375 | N19: {=_xlfn.IFS( F19=0,0, F19<=1000,3, F19<=2300,6, F19<=4500,12, F19<=8200,24, F19<=16000,48, F19>16001,96 )} -> 6 | O19: =ROUNDUP(N19/20,2) -> 0.3
... D56: 6 徳山東（ログオン画面有り） | E56: ZZZY001.exe | F56: 7516 | H56: =$N56 * H$2 -> 3 | I56: =$N56 * I$2 -> 4.32 | J56: =$N56 * J$2 -> 6.6 | K56: =$N56 * K$2 -> 5.04 | L56: =$N56 * L$2 -> 3 | M56: =$N56 * M$2 -> 1.5 | N56: {=_xlfn.IFS( F56=0,0, F56<=1000,3, F56<=2300,6, F56<=4500,12, F56<=8200,24, F56<=16000,48, F56>16001,96 )} -> 24 | O56: =ROUNDUP(N56/20,2) -> 1.2
D57: 新IRISマスタメンテツール | E57: AuthMnt.exe | F57: 18982 | H57: =$N57 * H$2 -> 10 | I57: =$N57 * I$2 -> 14.4 | J57: =$N57 * J$2 -> 22 | K57: =$N57 * K$2 -> 16.8 | L57: =$N57 * L$2 -> 10 | M57: =$N57 * M$2 -> 5 | N57: 80 | O57: =ROUNDUP(N57/20,2) -> 4
C58: VB6 | D58: ET_MENU_NEW | E58: ET_MENU_NEW.exe | F58: 708 | H58: =$N58 * H$2 -> 0.375 | I58: =$N58 * I$2 -> 0.54 | J58: =$N58 * J$2 -> 0.825 | K58: =$N58 * K$2 -> 0.63 | L58: =$N58 * L$2 -> 0.375 | M58: =$N58 * M$2 -> 0.1875 | N58: {=_xlfn.IFS( F58=0,0, F58<=1000,3, F58<=2300,6, F58<=4500,12, F58<=8200,24, F58<=16000,48, F58>16001,96 )} -> 3 | O58: =ROUNDUP(N58/20,2) -> 0.15
D59: GT_ELE_COST | E59: GT_ELE_COST.exe | F59: 2324 | H59: =$N59 * H$2 -> 1.5 | I59: =$N59 * I$2 -> 2.16 | J59: =$N59 * J$2 -> 3.3 | K59: =$N59 * K$2 -> 2.52 | L59: =$N59 * L$2 -> 1.5 | M59: =$N59 * M$2 -> 0.75 | N59: {=_xlfn.IFS( F59=0,0, F59<=1000,3, F59<=2300,6, F59<=4500,12, F59<=8200,24, F59<=16000,48, F59>16001,96 )} -> 12 | O59: =ROUNDUP(N59/20,2) -> 0.6
D60: ｶｳﾝﾀｰ照合 | E60: ｶｳﾝﾀｰ照合.exe | F60: 52 | H60: =$N60 * H$2 -> 0.375 | I60: =$N60 * I$2 -> 0.54 | J60: =$N60 * J$2 -> 0.825 | K60: =$N60 * K$2 -> 0.63 | L60: =$N60 * L$2 -> 0.375 | M60: =$N60 * M$2 -> 0.1875 | N60: {=_xlfn.IFS( F60=0,0, F60<=1000,3, F60<=2300,6, F60<=4500,12, F60<=8200,24, F60<=16000,48, F60>16001,96 )} -> 3 | O60: =ROUNDUP(N60/20,2) -> 0.15
D61: ケミカル管理2_目標値入力画面 | E61: ケミカル管理2_目標値入力画面.exe | F61: 12972 | H61: =$N61 * H$2 -> 6 | I61: =$N61 * I$2 -> 8.64 | J61: =$N61 * J$2 -> 13.2 | K61: =$N61 * K$2 -> 10.08 | L61: =$N61 * L$2 -> 6 | M61: =$N61 * M$2 -> 3 | N61: {=_xlfn.IFS( F61=0,0, F61<=1000,3, F61<=2300,6, F61<=4500,12, F61<=8200,24, F61<=16000,48, F61>16001,96 )} -> 48 | O61: =ROUNDUP(N61/20,2) -> 2.4
D62: TPHC Tools | E62: TPHCtools.exe | F62: 6408 | H62: =$N62 * H$2 -> 3 | I62: =$N62 * I$2 -> 4.32 | J62: =$N62 * J$2 -> 6.6 | K62: =$N62 * K$2 -> 5.04 | L62: =$N62 * L$2 -> 3 | M62: =$N62 * M$2 -> 1.5 | N62: {=_xlfn.IFS( F62=0,0, F62<=1000,3, F62<=2300,6, F62<=4500,12, F62<=8200,24, F62<=16000,48, F62>16001,96 )} -> 24 | O62: =ROUNDUP(N62/20,2) -> 1.2
D63: Labman | E63: Labman.exe | F63: 15986 | H63: =$N63 * H$2 -> 6 | I63: =$N63 * I$2 -> 8.64 | J63: =$N63 * J$2 -> 13.2 | K63: =$N63 * K$2 -> 10.08 | L63: =$N63 * L$2 -> 6 | M63: =$N63 * M$2 -> 3 | N63: {=_xlfn.IFS( F63=0,0, F63<=1000,3, F63<=2300,6, F63<=4500,12, F63<=8200,24, F63<=16000,48, F63>16001,96 )} -> 48 | O63: =ROUNDUP(N63/20,2) -> 2.4
C64: 共通 | D64: メニュー作成 | H64: =$N64 * H$2 -> 0.625 | I64: =$N64 * I$2 -> 0.9 | J64: =$N64 * J$2 -> 1.375 | K64: =$N64 * K$2 -> 1.05 | L64: =$N64 * L$2 -> 0.625 | M64: =$N64 * M$2 -> 0.3125 | N64: 5 | O64: =ROUNDUP(N64/20,2) -> 0.25
D65: ログ取得 | H65: =$N65 * H$2 -> 0.625 | I65: =$N65 * I$2 -> 0.9 | J65: =$N65 * J$2 -> 1.375 | K65: =$N65 * K$2 -> 1.05 | L65: =$N65 * L$2 -> 0.625 | M65: =$N65 * M$2 -> 0.3125 | N65: 5 | O65: =ROUNDUP(N65/20,2) -> 0.25
D66: メール送信部品作成 | H66: =$N66 * H$2 -> 0.625 | I66: =$N66 * I$2 -> 0.9 | J66: =$N66 * J$2 -> 1.375 | K66: =$N66 * K$2 -> 1.05 | L66: =$N66 * L$2 -> 0.625 | M66: =$N66 * M$2 -> 0.3125 | N66: 5 | O66: =ROUNDUP(N66/20,2) -> 0.25
B67: 非機能要件 | C67: 環境構築 | E67: 環境構築(検証・本番) | H67: =$N67 * H$2 -> 1.25 | I67: =$N67 * I$2 -> 1.8 | J67: =$N67 * J$2 -> 2.75 | K67: =$N67 * K$2 -> 2.1 | L67: =$N67 * L$2 -> 1.25 | M67: =$N67 * M$2 -> 0.625 | N67: 10 | O67: =ROUNDUP(N67/20,2) -> 0.5
B68: 全体 | C68: リリース | E68: リリース・リリース計画・準備 | H68: =$N68 * H$2 -> 1.25 | I68: =$N68 * I$2 -> 1.8 | J68: =$N68 * J$2 -> 2.75 | K68: =$N68 * K$2 -> 2.1 | L68: =$N68 * L$2 -> 1.25 | M68: =$N68 * M$2 -> 0.625 | N68: 10 | O68: =ROUNDUP(N68/20,2) -> 0.5
B69: 合計（人日） | H69: =SUBTOTAL(9,H7:H68) -> 90.875 | I69: =SUBTOTAL(9,I7:I68) -> 130.86 | J69: =SUBTOTAL(9,J7:J68) -> 199.925 | K69: =SUBTOTAL(9,K7:K68) -> 152.67 | L69: =SUBTOTAL(9,L7:L68) -> 90.875 | M69: =SUBTOTAL(9,M7:M68) -> 45.4375 | N69: =SUM(H69:M69) -> 710.6425
B70: 合計（人月） | H70: =ROUNDUP(SUM(H69:H69)/20,1) -> 4.6 | I70: =ROUNDUP(SUM(I69:I69)/20,1) -> 6.6 | J70: =ROUNDUP(SUM(J69:J69)/20,1) -> 10 | K70: =ROUNDUP(SUM(K69:K69)/20,1) -> 7.7 | L70: =ROUNDUP(SUM(L69:L69)/20,1) -> 4.6 | M70: =ROUNDUP(SUM(M69:M69)/20,1) -> 2.3 | N70: =SUM(H70:M70) -> 35.8
B71: プロジェクト管理 | H71: =ROUNDUP(H70*0.2,1) -> 1 | I71: =ROUNDUP(I70*0.2,1) -> 1.4 | J71: =ROUNDUP(J70*0.2,1) -> 2 | K71: =ROUNDUP(K70*0.2,1) -> 1.6 | L71: =ROUNDUP(L70*0.2,1) -> 1 | M71: =ROUNDUP(M70*0.2,1) -> 0.5 | N71: =SUM(H71:M71) -> 7.5
B72: 金額 | H72: =H70*1100000 -> 5060000 | I72: =I70*1100000 -> 7260000 | J72: =J70*1100000 -> 11000000 | K72: =K70*1100000 -> 8470000 | L72: =L70*1100000 -> 5060000 | M72: =M70*1100000 -> 2530000 | N72: =SUM(H72:M72,N71*1400000) -> 49880000
H73: =H71*1400000 -> 1400000 | I73: =I71*1400000 -> 1960000 | J73: =J71*1400000 -> 2800000 | K73: =K71*1400000 -> 2240000 | L73: =L71*1400000 -> 1400000 | M73: =M71*1400000 -> 700000

Sheet パターン② VB6
H2: 0.125 | I2: 0.18 | J2: 0.275 | K2: 0.21 | L2: 0.125 | M2: 0.0625 | N2: =SUM(H2:M2) -> 0.9775
B3: 大分類 | C3: 中分類 | D3: 小分類 | F3: 行数 | G3: 画面機能 作業内容 | H3: 工程 | N3: 合計 （人日） | O3: 合計 （人月）
H4: 要件定義 | I4: 設計 | J4: 開発 | K4: 結合テスト | L4: システムテスト | M4: 受入テスト支援
B7: 機能 | C7: VB6 | D7: ET_MENU_NEW | E7: ET_MENU_NEW.exe | F7: 708 | H7: =$N7 * H$2 -> 0.375 | I7: =$N7 * I$2 -> 0.54 | J7: =$N7 * J$2 -> 0.825 | K7: =$N7 * K$2 -> 0.63 | L7: =$N7 * L$2 -> 0.375 | M7: =$N7 * M$2 -> 0.1875 | N7: {=_xlfn.IFS( F7=0,0, F7<=1000,3, F7<=2300,6, F7<=4500,12, F7<=8200,24, F7<=16000,48, F7>16001,96 )} -> 3 | O7: =ROUNDUP(N7/20,2) -> 0.15
D8: GT_ELE_COST | E8: GT_ELE_COST.exe | F8: 2324 | H8: =$N8 * H$2 -> 1.5 | I8: =$N8 * I$2 -> 2.16 | J8: =$N8 * J$2 -> 3.3 | K8: =$N8 * K$2 -> 2.52 | L8: =$N8 * L$2 -> 1.5 | M8: =$N8 * M$2 -> 0.75 | N8: {=_xlfn.IFS( F8=0,0, F8<=1000,3, F8<=2300,6, F8<=4500,12, F8<=8200,24, F8<=16000,48, F8>16001,96 )} -> 12 | O8: =ROUNDUP(N8/20,2) -> 0.6
D9: ｶｳﾝﾀｰ照合 | E9: ｶｳﾝﾀｰ照合.exe | F9: 52 | H9: =$N9 * H$2 -> 0.375 | I9: =$N9 * I$2 -> 0.54 | J9: =$N9 * J$2 -> 0.825 | K9: =$N9 * K$2 -> 0.63 | L9: =$N9 * L$2 -> 0.375 | M9: =$N9 * M$2 -> 0.1875 | N9: {=_xlfn.IFS( F9=0,0, F9<=1000,3, F9<=2300,6, F9<=4500,12, F9<=8200,24, F9<=16000,48, F9>16001,96 )} -> 3 | O9: =ROUNDUP(N9/20,2) -> 0.15
D10: ケミカル管理2_目標値入力画面 | E10: ケミカル管理2_目標値入力画面.exe | F10: 12972 | H10: =$N10 * H$2 -> 6 | I10: =$N10 * I$2 -> 8.64 | J10: =$N10 * J$2 -> 13.2 | K10: =$N10 * K$2 -> 10.08 | L10: =$N10 * L$2 -> 6 | M10: =$N10 * M$2 -> 3 | N10: {=_xlfn.IFS( F10=0,0, F10<=1000,3, F10<=2300,6, F10<=4500,12, F10<=8200,24, F10<=16000,48, F10>16001,96 )} -> 48 | O10: =ROUNDUP(N10/20,2) -> 2.4
D11: TPHC Tools | E11: TPHCtools.exe | F11: 6408 | H11: =$N11 * H$2 -> 3 | I11: =$N11 * I$2 -> 4.32 | J11: =$N11 * J$2 -> 6.6 | K11: =$N11 * K$2 -> 5.04 | L11: =$N11 * L$2 -> 3 | M11: =$N11 * M$2 -> 1.5 | N11: {=_xlfn.IFS( F11=0,0, F11<=1000,3, F11<=2300,6, F11<=4500,12, F11<=8200,24, F11<=16000,48, F11>16001,96 )} -> 24 | O11: =ROUNDUP(N11/20,2) -> 1.2
D12: Labman | E12: Labman.exe | F12: 15986 | H12: =$N12 * H$2 -> 6 | I12: =$N12 * I$2 -> 8.64 | J12: =$N12 * J$2 -> 13.2 | K12: =$N12 * K$2 -> 10.08 | L12: =$N12 * L$2 -> 6 | M12: =$N12 * M$2 -> 3 | N12: {=_xlfn.IFS( F12=0,0, F12<=1000,3, F12<=2300,6, F12<=4500,12, F12<=8200,24, F12<=16000,48, F12>16001,96 )} -> 48 | O12: =ROUNDUP(N12/20,2) -> 2.4
C13: 共通 | D13: メニュー作成 | H13: =$N13 * H$2 -> 0.625 | I13: =$N13 * I$2 -> 0.9 | J13: =$N13 * J$2 -> 1.375 | K13: =$N13 * K$2 -> 1.05 | L13: =$N13 * L$2 -> 0.625 | M13: =$N13 * M$2 -> 0.3125 | N13: 5 | O13: =ROUNDUP(N13/20,2) -> 0.25
D14: ログ取得 | H14: =$N14 * H$2 -> 0.625 | I14: =$N14 * I$2 -> 0.9 | J14: =$N14 * J$2 -> 1.375 | K14: =$N14 * K$2 -> 1.05 | L14: =$N14 * L$2 -> 0.625 | M14: =$N14 * M$2 -> 0.3125 | N14: 5 | O14: =ROUNDUP(N14/20,2) -> 0.25
D15: メール送信部品作成 | H15: =$N15 * H$2 -> 0.625 | I15: =$N15 * I$2 -> 0.9 | J15: =$N15 * J$2 -> 1.375 | K15: =$N15 * K$2 -> 1.05 | L15: =$N15 * L$2 -> 0.625 | M15: =$N15 * M$2 -> 0.3125 | N15: 5 | O15: =ROUNDUP(N15/20,2) -> 0.25
B16: 非機能要件 | C16: 環境構築 | E16: 環境構築(検証・本番) | H16: =$N16 * H$2 -> 1.25 | I16: =$N16 * I$2 -> 1.8 | J16: =$N16 * J$2 -> 2.75 | K16: =$N16 * K$2 -> 2.1 | L16: =$N16 * L$2 -> 1.25 | M16: =$N16 * M$2 -> 0.625 | N16: 10 | O16: =ROUNDUP(N16/20,2) -> 0.5
B17: 全体 | C17: リリース | E17: リリース・リリース計画・準備 | H17: =$N17 * H$2 -> 1.25 | I17: =$N17 * I$2 -> 1.8 | J17: =$N17 * J$2 -> 2.75 | K17: =$N17 * K$2 -> 2.1 | L17: =$N17 * L$2 -> 1.25 | M17: =$N17 * M$2 -> 0.625 | N17: 10 | O17: =ROUNDUP(N17/20,2) -> 0.5
B18: 合計（人日） | H18: =SUBTOTAL(9,H7:H17) -> 21.625 | I18: =SUBTOTAL(9,I7:I17) -> 31.14 | J18: =SUBTOTAL(9,J7:J17) -> 47.575 | K18: =SUBTOTAL(9,K7:K17) -> 36.33 | L18: =SUBTOTAL(9,L7:L17) -> 21.625 | M18: =SUBTOTAL(9,M7:M17) -> 10.8125 | N18: =SUM(H18:M18) -> 169.1075
B19: 合計（人月） | H19: =ROUNDUP(SUM(H18:H18)/20,1) -> 1.1 | I19: =ROUNDUP(SUM(I18:I18)/20,1) -> 1.6 | J19: =ROUNDUP(SUM(J18:J18)/20,1) -> 2.4 | K19: =ROUNDUP(SUM(K18:K18)/20,1) -> 1.9 | L19: =ROUNDUP(SUM(L18:L18)/20,1) -> 1.1 | M19: =ROUNDUP(SUM(M18:M18)/20,1) -> 0.6 | N19: =SUM(H19:M19) -> 8.7
B20: プロジェクト管理 | H20: =ROUNDUP(H19*0.2,1) -> 0.3 | I20: =ROUNDUP(I19*0.2,1) -> 0.4 | J20: =ROUNDUP(J19*0.2,1) -> 0.5 | K20: =ROUNDUP(K19*0.2,1) -> 0.4 | L20: =ROUNDUP(L19*0.2,1) -> 0.3 | M20: =ROUNDUP(M19*0.2,1) -> 0.2 | N20: =SUM(H20:M20) -> 2.1
B21: 金額 | H21: =H19*1100000 -> 1210000 | I21: =I19*1100000 -> 1760000 | J21: =J19*1100000 -> 2640000 | K21: =K19*1100000 -> 2090000 | L21: =L19*1100000 -> 1210000 | M21: =M19*1100000 -> 660000 | N21: =SUM(H21:M21,N20*1400000) -> 12510000
H22: =H20*1400000 -> 420000 | I22: =I20*1400000 -> 560000 | J22: =J20*1400000 -> 700000 | K22: =K20*1400000 -> 560000 | L22: =L20*1400000 -> 420000 | M22: =M20*1400000 -> 280000

Sheet 体制見積
A3: ■パターン①
F4: 2026年
F5: 4月 | G5: 5月 | H5: 6月 | I5: 7月 | J5: 8月 | K5: 9月 | L5: 10月 | M5: 11月 | N5: 12月 | O5: 1月
B6: 工程 | F6: 要件定義 | G6: 要件定義 | H6: 詳細設計 | J6: 実装 | L6: 結合テスト | N6: システムテスト | O6: 受入テスト | P6: 工数合計
B7: PM | C7: 1400000 | D7: 356240 | E7: PM | F7: 1 | G7: 1 | H7: 1 | I7: 1 | J7: 1 | K7: 1 | L7: 1 | M7: 1 | N7: 1 | O7: 1 | P7: =SUM(F7:O7) -> 10 | R7: =D7*COUNT(F7:O7) -> 3562400
B8: SE | C8: 1100000 | D8: 900000 | E8: SE | F8: 2 | G8: 2 | H8: 3 | I8: 3 | J8: 2 | K8: 2 | L8: 2 | M8: 2 | N8: 2 | O8: 1 | P8: =SUM(F8:O8) -> 21 | R8: =D8*COUNT(F8:O8) -> 9000000
B9: ブリッジ | C9: 1000000 | D9: 88256 | E9: BrSE | J9: 1 | K9: 1 | L9: 1 | M9: 1 | N9: 1 | O9: 0.5 | P9: =SUM(F9:O9) -> 5.5 | R9: =D9*COUNT(F9:O9) -> 529536
B10: PG① | C10: 700000 | D10: 350000 | E10: PG | J10: 1 | K10: 1 | L10: 1 | M10: 1 | N10: 1 | O10: 1 | P10: =SUM(F10:O10) -> 6 | R10: =D10*COUNT(F10:O10) -> 2100000
B11: PG② | C11: 700000 | D11: 350000 | E11: PG | J11: 1 | K11: 1 | L11: 1 | M11: 1 | N11: 1 | P11: =SUM(F11:O11) -> 5 | R11: =D11*COUNT(F11:O11) -> 1750000
C12: 700000 | D12: 350000 | E12: PG | J12: 1 | K12: 1 | P12: =SUM(F12:O12) -> 2 | R12: =D12*COUNT(F12:O12) -> 700000
C13: 700000 | D13: 350000 | E13: PG | J13: 1 | K13: 1 | P13: =SUM(F13:O13) -> 2 | R13: =D13*COUNT(F13:O13) -> 700000
B14: 工数合計（人月） | F14: =SUM(F7:F13) -> 3 | G14: =SUM(G7:G13) -> 3 | H14: =SUM(H7:H13) -> 4 | I14: =SUM(I7:I13) -> 4 | J14: =SUM(J7:J13) -> 8 | K14: =SUM(K7:K13) -> 8 | L14: =SUM(L7:L13) -> 6 | M14: =SUM(M7:M13) -> 6 | ... O14: =SUM(O7:O13) -> 3.5 | P14: =SUM(F14:O14) -> 51.5
B16: PM | F16: =$C7*F7 -> 1400000 | G16: =$C7*G7 -> 1400000 | H16: =$C7*H7 -> 1400000 | I16: =$C7*I7 -> 1400000 | J16: =$C7*J7 -> 1400000 | K16: =$C7*K7 -> 1400000 | L16: =$C7*L7 -> 1400000 | M16: =$C7*M7 -> 1400000 | ... O16: =$C7*O7 -> 1400000 | P16: =SUM(F16:O16) -> 14000000
B17: SE | G17: =$C8*G8 -> 2200000 | H17: =$C8*H8 -> 3300000 | I17: =$C8*I8 -> 3300000 | J17: =$C8*J8 -> 2200000 | K17: =$C8*K8 -> 2200000 | L17: =$C8*L8 -> 2200000 | M17: =$C8*M8 -> 2200000 | N17: =$C8*N8 -> 2200000 | O17: =$C8*O8 -> 1100000 | P17: =SUM(F17:O17) -> 20900000
B18: ブリッジ | G18: =$C9*G9 -> 0 | H18: =$C9*H9 -> 0 | I18: =$C9*I9 -> 0 | J18: =$C9*J9 -> 1000000 | K18: =$C9*K9 -> 1000000 | L18: =$C9*L9 -> 1000000 | M18: =$C9*M9 -> 1000000 | N18: =$C9*N9 -> 1000000 | O18: =$C9*O9 -> 500000 | P18: =SUM(F18:O18) -> 5500000
B19: PG① | G19: =$C10*G10 -> 0 | H19: =$C10*H10 -> 0 | I19: =$C10*I10 -> 0 | J19: =$C10*J10 -> 700000 | K19: =$C10*K10 -> 700000 | L19: =$C10*L10 -> 700000 | M19: =$C10*M10 -> 700000 | N19: =$C10*N10 -> 700000 | O19: =$C10*O10 -> 700000 | P19: =SUM(F19:O19) -> 4200000
B20: PG② | G20: =$C11*G11 -> 0 | H20: =$C11*H11 -> 0 | I20: =$C11*I11 -> 0 | J20: =$C11*J11 -> 700000 | K20: =$C11*K11 -> 700000 | L20: =$C11*L11 -> 700000 | M20: =$C11*M11 -> 700000 | N20: =$C11*N11 -> 700000 | O20: =$C11*O11 -> 0 | P20: =SUM(F20:O20) -> 3500000
F21: =SUM(F16:F20) -> 1400000 | G21: =SUM(G16:G20) -> 3600000 | H21: =SUM(H16:H20) -> 4700000 | I21: =SUM(I16:I20) -> 4700000 | J21: =SUM(J16:J20) -> 6000000 | K21: =SUM(K16:K20) -> 6000000 | L21: =SUM(L16:L20) -> 6000000 | M21: =SUM(M16:M20) -> 6000000 | ... O21: =SUM(O16:O20) -> 3700000 | P21: =SUM(F21:O21) -> 48100000 | R21: =SUM(R7:R13) -> 18341936 | S21: =P22-R21 -> 31538064 | T21: =S21/P22 -> 0.63227875
O22: 工数見積金額 | P22: 49880000
A25: ■パターン②
F26: 2026年
F27: 4月 | G27: 5月 | H27: 6月 | I27: 7月 | J27: 8月 | K27: 9月
B28: 工程 | F28: 要件定義 | G28: 詳細設計 | H28: 実装 | I28: 結合テスト | J28: システムテスト | K28: 受入テスト | L28: 工数合計
B29: PM | C29: 1400000 | D29: 356240 | E29: PM | F29: 0.5 | G29: 1 | H29: 0.5 | I29: 0.5 | J29: 0.5 | K29: 0.5 | L29: =SUM(F29:K29) -> 3.5 | N29: =D29*COUNT(F29:K29) -> 2137440
B30: SE | C30: 1100000 | D30: 900000 | E30: SE | F30: 1 | G30: 1 | H30: 1 | I30: 1 | J30: 1 | K30: 0.5 | L30: =SUM(F30:K30) -> 5.5 | N30: =D30*COUNT(F30:K30) -> 5400000
B31: ブリッジ | C31: 1000000 | D31: 88256 | E31: BrSE | H31: 0.5 | I31: 0.5 | L31: =SUM(F31:K31) -> 1 | N31: =D31*COUNT(F31:K31) -> 176512
B32: PG① | C32: 700000 | D32: 350000 | E32: PG | H32: 1 | I32: 1 | L32: =SUM(F32:K32) -> 2 | N32: =D32*COUNT(F32:K32) -> 700000
B33: 工数合計（人月） | F33: =SUM(F29:F32) -> 1.5 | G33: =SUM(G29:G32) -> 2 | H33: =SUM(H29:H32) -> 3 | I33: =SUM(I29:I32) -> 3 | J33: =SUM(J29:J32) -> 1.5 | K33: =SUM(K29:K32) -> 1 | L33: =SUM(F33:K33) -> 12
B35: PM | F35: =$C29*F29 -> 700000 | G35: =$C29*G29 -> 1400000 | H35: =$C29*H29 -> 700000 | I35: =$C29*I29 -> 700000 | J35: =$C29*J29 -> 700000 | K35: =$C29*K29 -> 700000 | L35: =SUM(F35:K35) -> 4900000
B36: SE | G36: =$C30*G30 -> 1100000 | H36: =$C30*H30 -> 1100000 | I36: =$C30*I30 -> 1100000 | J36: =$C30*J30 -> 1100000 | K36: =$C30*K30 -> 550000 | L36: =SUM(F36:K36) -> 4950000
B37: ブリッジ | G37: =$C31*G31 -> 0 | H37: =$C31*H31 -> 500000 | I37: =$C31*I31 -> 500000 | J37: =$C31*J31 -> 0 | K37: =$C31*K31 -> 0 | L37: =SUM(F37:K37) -> 1000000
B38: PG① | G38: =$C32*G32 -> 0 | H38: =$C32*H32 -> 700000 | I38: =$C32*I32 -> 700000 | J38: =$C32*J32 -> 0 | K38: =$C32*K32 -> 0 | L38: =SUM(F38:K38) -> 1400000
F39: =SUM(F35:F38) -> 700000 | G39: =SUM(G35:G38) -> 2500000 | H39: =SUM(H35:H38) -> 3000000 | I39: =SUM(I35:I38) -> 3000000 | J39: =SUM(J35:J38) -> 1800000 | K39: =SUM(K35:K38) -> 1250000 | L39: =SUM(F39:K39) -> 12250000 | N39: =SUM(N29:N32) -> 8413952 | O39: =P40-N39 -> 4096048 | P39: =O39/P40 -> 0.3274219
O40: 工数見積金額 | P40: 12510000

Sheet 工数見積り（バッチあり）
H2: 0.125 | I2: 0.18 | J2: 0.275 | K2: 0.21 | L2: 0.125 | M2: 0.0625 | N2: =SUM(H2:M2) -> 0.9775
B3: 大分類 | C3: 中分類 | D3: 小分類 | F3: 行数 | G3: 画面機能 作業内容 | H3: 工程 | N3: 合計 （人日） | O3: 合計 （人月）
H4: 要件定義 | I4: 設計 | J4: 開発 | K4: 結合テスト | L4: システムテスト | M4: 受入テスト支援
B7: 機能 | C7: .NET | D7: S1_北海道製 | E7: ZZZY002.exe | F7: 3261 | H7: =$N7 * H$2 -> 1.5 | I7: =$N7 * I$2 -> 2.16 | J7: =$N7 * J$2 -> 3.3 | K7: =$N7 * K$2 -> 2.52 | L7: =$N7 * L$2 -> 1.5 | M7: =$N7 * M$2 -> 0.75 | N7: {=_xlfn.IFS( F7=0,0, F7<=1000,3, F7<=2300,6, F7<=4500,12, F7<=8200,24, F7<=16000,48, F7>16001,96 )} -> 12 | O7: =ROUNDUP(N7/20,2) -> 0.6
D8: ∟各所比較情報／品質管理 | E8: zbfz001.exe | F8: 1845 | H8: =$N8 * H$2 -> 0.75 | I8: =$N8 * I$2 -> 1.08 | J8: =$N8 * J$2 -> 1.65 | K8: =$N8 * K$2 -> 1.26 | L8: =$N8 * L$2 -> 0.75 | M8: =$N8 * M$2 -> 0.375 | N8: {=_xlfn.IFS( F8=0,0, F8<=1000,3, F8<=2300,6, F8<=4500,12, F8<=8200,24, F8<=16000,48, F8>16001,96 )} -> 6 | O8: =ROUNDUP(N8/20,2) -> 0.3
D9: ∟製油所情報／品質管理 | E9: bcfz001.exe | F9: 1882 | H9: =$N9 * H$2 -> 0.75 | I9: =$N9 * I$2 -> 1.08 | J9: =$N9 * J$2 -> 1.65 | K9: =$N9 * K$2 -> 1.26 | L9: =$N9 * L$2 -> 0.75 | M9: =$N9 * M$2 -> 0.375 | N9: {=_xlfn.IFS( F9=0,0, F9<=1000,3, F9<=2300,6, F9<=4500,12, F9<=8200,24, F9<=16000,48, F9>16001,96 )} -> 6 | O9: =ROUNDUP(N9/20,2) -> 0.3
D10: ∟製油所情報／データ検索 | E10: bciz001.exe | F10: 1897 | H10: =$N10 * H$2 -> 0.75 | I10: =$N10 * I$2 -> 1.08 | J10: =$N10 * J$2 -> 1.65 | K10: =$N10 * K$2 -> 1.26 | L10: =$N10 * L$2 -> 0.75 | M10: =$N10 * M$2 -> 0.375 | N10: {=_xlfn.IFS( F10=0,0, F10<=1000,3, F10<=2300,6, F10<=4500,12, F10<=8200,24, F10<=16000,48, F10>16001,96 )} -> 6 | O10: =ROUNDUP(N10/20,2) -> 0.3
D11: ∟品質情報検索／燃料油 | E11: zbfz0021.exe | F11: 4300 | H11: =$N11 * H$2 -> 1.5 | I11: =$N11 * I$2 -> 2.16 | J11: =$N11 * J$2 -> 3.3 | K11: =$N11 * K$2 -> 2.52 | L11: =$N11 * L$2 -> 1.5 | M11: =$N11 * M$2 -> 0.75 | N11: {=_xlfn.IFS( F11=0,0, F11<=1000,3, F11<=2300,6, F11<=4500,12, F11<=8200,24, F11<=16000,48, F11>16001,96 )} -> 12 | O11: =ROUNDUP(N11/20,2) -> 0.6
D12: ∟品質情報検索／工程 | E12: zbfz0022.exe | F12: 4400 | H12: =$N12 * H$2 -> 1.5 | I12: =$N12 * I$2 -> 2.16 | J12: =$N12 * J$2 -> 3.3 | K12: =$N12 * K$2 -> 2.52 | L12: =$N12 * L$2 -> 1.5 | M12: =$N12 * M$2 -> 0.75 | N12: {=_xlfn.IFS( F12=0,0, F12<=1000,3, F12<=2300,6, F12<=4500,12, F12<=8200,24, F12<=16000,48, F12>16001,96 )} -> 12 | O12: =ROUNDUP(N12/20,2) -> 0.6
D13: ∟品質情報検索／品質関連 | E13: zbfz0023.exe | F13: 3936 | H13: =$N13 * H$2 -> 1.5 | I13: =$N13 * I$2 -> 2.16 | J13: =$N13 * J$2 -> 3.3 | K13: =$N13 * K$2 -> 2.52 | L13: =$N13 * L$2 -> 1.5 | M13: =$N13 * M$2 -> 0.75 | N13: {=_xlfn.IFS( F13=0,0, F13<=1000,3, F13<=2300,6, F13<=4500,12, F13<=8200,24, F13<=16000,48, F13>16001,96 )} -> 12 | O13: =ROUNDUP(N13/20,2) -> 0.6
D14: ∟ローカルシステム | E14: bllz001.exe | F14: 1685 | H14: =$N14 * H$2 -> 0.75 | I14: =$N14 * I$2 -> 1.08 | J14: =$N14 * J$2 -> 1.65 | K14: =$N14 * K$2 -> 1.26 | L14: =$N14 * L$2 -> 0.75 | M14: =$N14 * M$2 -> 0.375 | N14: {=_xlfn.IFS( F14=0,0, F14<=1000,3, F14<=2300,6, F14<=4500,12, F14<=8200,24, F14<=16000,48, F14>16001,96 )} -> 6 | O14: =ROUNDUP(N14/20,2) -> 0.3
D15: ∟個別業務情報／運転管理 | E15: bedz001.exe | F15: 2275 | H15: =$N15 * H$2 -> 0.75 | I15: =$N15 * I$2 -> 1.08 | J15: =$N15 * J$2 -> 1.65 | K15: =$N15 * K$2 -> 1.26 | L15: =$N15 * L$2 -> 0.75 | M15: =$N15 * M$2 -> 0.375 | N15: {=_xlfn.IFS( F15=0,0, F15<=1000,3, F15<=2300,6, F15<=4500,12, F15<=8200,24, F15<=16000,48, F15>16001,96 )} -> 6 | O15: =ROUNDUP(N15/20,2) -> 0.3
D16: ∟個別業務情報／品質管理 | E16: zefz001.exe | F16: 998 | H16: =$N16 * H$2 -> 0.375 | I16: =$N16 * I$2 -> 0.54 | J16: =$N16 * J$2 -> 0.825 | K16: =$N16 * K$2 -> 0.63 | L16: =$N16 * L$2 -> 0.375 | M16: =$N16 * M$2 -> 0.1875 | N16: {=_xlfn.IFS( F16=0,0, F16<=1000,3, F16<=2300,6, F16<=4500,12, F16<=8200,24, F16<=16000,48, F16>16001,96 )} -> 3 | O16: =ROUNDUP(N16/20,2) -> 0.15
D17: S2_千葉（石） | E17: ZZZY002.exe | F17: 3261 | H17: =$N17 * H$2 -> 1.5 | I17: =$N17 * I$2 -> 2.16 | J17: =$N17 * J$2 -> 3.3 | K17: =$N17 * K$2 -> 2.52 | L17: =$N17 * L$2 -> 1.5 | M17: =$N17 * M$2 -> 0.75 | N17: {=_xlfn.IFS( F17=0,0, F17<=1000,3, F17<=2300,6, F17<=4500,12, F17<=8200,24, F17<=16000,48, F17>16001,96 )} -> 12 | O17: =ROUNDUP(N17/20,2) -> 0.6
D18: ∟各所比較情報／品質管理 | E18: zbfz001.exe | F18: 1845 | H18: =$N18 * H$2 -> 0.75 | I18: =$N18 * I$2 -> 1.08 | J18: =$N18 * J$2 -> 1.65 | K18: =$N18 * K$2 -> 1.26 | L18: =$N18 * L$2 -> 0.75 | M18: =$N18 * M$2 -> 0.375 | N18: {=_xlfn.IFS( F18=0,0, F18<=1000,3, F18<=2300,6, F18<=4500,12, F18<=8200,24, F18<=16000,48, F18>16001,96 )} -> 6 | O18: =ROUNDUP(N18/20,2) -> 0.3
D19: ∟製油所情報／品質管理 | E19: ccfz001.exe | F19: 1898 | H19: =$N19 * H$2 -> 0.75 | I19: =$N19 * I$2 -> 1.08 | J19: =$N19 * J$2 -> 1.65 | K19: =$N19 * K$2 -> 1.26 | L19: =$N19 * L$2 -> 0.75 | M19: =$N19 * M$2 -> 0.375 | N19: {=_xlfn.IFS( F19=0,0, F19<=1000,3, F19<=2300,6, F19<=4500,12, F19<=8200,24, F19<=16000,48, F19>16001,96 )} -> 6 | O19: =ROUNDUP(N19/20,2) -> 0.3
... D57: 新IRISマスタメンテツール | E57: AuthMnt.exe | F57: 18982 | H57: =$N57 * H$2 -> 12 | I57: =$N57 * I$2 -> 17.28 | J57: =$N57 * J$2 -> 26.4 | K57: =$N57 * K$2 -> 20.16 | L57: =$N57 * L$2 -> 12 | M57: =$N57 * M$2 -> 6 | N57: {=_xlfn.IFS( F57=0,0, F57<=1000,3, F57<=2300,6, F57<=4500,12, F57<=8200,24, F57<=16000,48, F57>16001,96 )} -> 96 | O57: =ROUNDUP(N57/20,2) -> 4.8
C58: VB6 | D58: ET_MENU_NEW | E58: ET_MENU_NEW.exe | F58: 708 | H58: =$N58 * H$2 -> 0.375 | I58: =$N58 * I$2 -> 0.54 | J58: =$N58 * J$2 -> 0.825 | K58: =$N58 * K$2 -> 0.63 | L58: =$N58 * L$2 -> 0.375 | M58: =$N58 * M$2 -> 0.1875 | N58: {=_xlfn.IFS( F58=0,0, F58<=1000,3, F58<=2300,6, F58<=4500,12, F58<=8200,24, F58<=16000,48, F58>16001,96 )} -> 3 | O58: =ROUNDUP(N58/20,2) -> 0.15
D59: GT_ELE_COST | E59: GT_ELE_COST.exe | F59: 2324 | H59: =$N59 * H$2 -> 1.5 | I59: =$N59 * I$2 -> 2.16 | J59: =$N59 * J$2 -> 3.3 | K59: =$N59 * K$2 -> 2.52 | L59: =$N59 * L$2 -> 1.5 | M59: =$N59 * M$2 -> 0.75 | N59: {=_xlfn.IFS( F59=0,0, F59<=1000,3, F59<=2300,6, F59<=4500,12, F59<=8200,24, F59<=16000,48, F59>16001,96 )} -> 12 | O59: =ROUNDUP(N59/20,2) -> 0.6
D60: ｶｳﾝﾀｰ照合 | E60: ｶｳﾝﾀｰ照合.exe | F60: 52 | H60: =$N60 * H$2 -> 0.375 | I60: =$N60 * I$2 -> 0.54 | J60: =$N60 * J$2 -> 0.825 | K60: =$N60 * K$2 -> 0.63 | L60: =$N60 * L$2 -> 0.375 | M60: =$N60 * M$2 -> 0.1875 | N60: {=_xlfn.IFS( F60=0,0, F60<=1000,3, F60<=2300,6, F60<=4500,12, F60<=8200,24, F60<=16000,48, F60>16001,96 )} -> 3 | O60: =ROUNDUP(N60/20,2) -> 0.15
D61: ケミカル管理2_目標値入力画面 | E61: ケミカル管理2_目標値入力画面.exe | F61: 12972 | H61: =$N61 * H$2 -> 6 | I61: =$N61 * I$2 -> 8.64 | J61: =$N61 * J$2 -> 13.2 | K61: =$N61 * K$2 -> 10.08 | L61: =$N61 * L$2 -> 6 | M61: =$N61 * M$2 -> 3 | N61: {=_xlfn.IFS( F61=0,0, F61<=1000,3, F61<=2300,6, F61<=4500,12, F61<=8200,24, F61<=16000,48, F61>16001,96 )} -> 48 | O61: =ROUNDUP(N61/20,2) -> 2.4
D62: TPHC Tools | E62: TPHCtools.exe | F62: 6408 | H62: =$N62 * H$2 -> 3 | I62: =$N62 * I$2 -> 4.32 | J62: =$N62 * J$2 -> 6.6 | K62: =$N62 * K$2 -> 5.04 | L62: =$N62 * L$2 -> 3 | M62: =$N62 * M$2 -> 1.5 | N62: {=_xlfn.IFS( F62=0,0, F62<=1000,3, F62<=2300,6, F62<=4500,12, F62<=8200,24, F62<=16000,48, F62>16001,96 )} -> 24 | O62: =ROUNDUP(N62/20,2) -> 1.2
D63: Labman | E63: Labman.exe | F63: 15986 | H63: =$N63 * H$2 -> 6 | I63: =$N63 * I$2 -> 8.64 | J63: =$N63 * J$2 -> 13.2 | K63: =$N63 * K$2 -> 10.08 | L63: =$N63 * L$2 -> 6 | M63: =$N63 * M$2 -> 3 | N63: {=_xlfn.IFS( F63=0,0, F63<=1000,3, F63<=2300,6, F63<=4500,12, F63<=8200,24, F63<=16000,48, F63>16001,96 )} -> 48 | O63: =ROUNDUP(N63/20,2) -> 2.4
C64: バッチ | D64: 自家燃タンク在庫連携 | F64: 設計書から算出 | H64: =$N64 * H$2 -> 1 | I64: =$N64 * I$2 -> 1.44 | J64: =$N64 * J$2 -> 2.2 | K64: =$N64 * K$2 -> 1.68 | L64: =$N64 * L$2 -> 1 | M64: =$N64 * M$2 -> 0.5 | N64: 8 | O64: =ROUNDUP(N64/20,2) -> 0.4
D65: 自家燃使用量連携 | H65: =$N65 * H$2 -> 2 | I65: =$N65 * I$2 -> 2.88 | J65: =$N65 * J$2 -> 4.4 | K65: =$N65 * K$2 -> 3.36 | L65: =$N65 * L$2 -> 2 | M65: =$N65 * M$2 -> 1 | N65: 16 | O65: =ROUNDUP(N65/20,2) -> 0.8
D66: 潤滑油一課タンク在庫連携 | H66: =$N66 * H$2 -> 1.125 | I66: =$N66 * I$2 -> 1.62 | J66: =$N66 * J$2 -> 2.475 | K66: =$N66 * K$2 -> 1.89 | L66: =$N66 * L$2 -> 1.125 | M66: =$N66 * M$2 -> 0.5625 | N66: 9 | O66: =ROUNDUP(N66/20,2) -> 0.45
D67: 日別装置稼働連携 | H67: =$N67 * H$2 -> 1 | I67: =$N67 * I$2 -> 1.44 | J67: =$N67 * J$2 -> 2.2 | K67: =$N67 * K$2 -> 1.68 | L67: =$N67 * L$2 -> 1 | M67: =$N67 * M$2 -> 0.5 | N67: 8 | O67: =ROUNDUP(N67/20,2) -> 0.4
C68: 共通 | D68: メニュー作成 | H68: =$N68 * H$2 -> 0.625 | I68: =$N68 * I$2 -> 0.9 | J68: =$N68 * J$2 -> 1.375 | K68: =$N68 * K$2 -> 1.05 | L68: =$N68 * L$2 -> 0.625 | M68: =$N68 * M$2 -> 0.3125 | N68: 5 | O68: =ROUNDUP(N68/20,2) -> 0.25
D69: ログ取得 | H69: =$N69 * H$2 -> 0.625 | I69: =$N69 * I$2 -> 0.9 | J69: =$N69 * J$2 -> 1.375 | K69: =$N69 * K$2 -> 1.05 | L69: =$N69 * L$2 -> 0.625 | M69: =$N69 * M$2 -> 0.3125 | N69: 5 | O69: =ROUNDUP(N69/20,2) -> 0.25
D70: メール送信部品作成 | H70: =$N70 * H$2 -> 0.625 | I70: =$N70 * I$2 -> 0.9 | J70: =$N70 * J$2 -> 1.375 | K70: =$N70 * K$2 -> 1.05 | L70: =$N70 * L$2 -> 0.625 | M70: =$N70 * M$2 -> 0.3125 | N70: 5 | O70: =ROUNDUP(N70/20,2) -> 0.25
B71: 非機能要件 | C71: 環境構築 | E71: 環境構築(検証・本番) | H71: =$N71 * H$2 -> 1.25 | I71: =$N71 * I$2 -> 1.8 | J71: =$N71 * J$2 -> 2.75 | K71: =$N71 * K$2 -> 2.1 | L71: =$N71 * L$2 -> 1.25 | M71: =$N71 * M$2 -> 0.625 | N71: 10 | O71: =ROUNDUP(N71/20,2) -> 0.5
B72: 全体 | C72: リリース | E72: リリース・リリース計画・準備 | H72: =$N72 * H$2 -> 1.25 | I72: =$N72 * I$2 -> 1.8 | J72: =$N72 * J$2 -> 2.75 | K72: =$N72 * K$2 -> 2.1 | L72: =$N72 * L$2 -> 1.25 | M72: =$N72 * M$2 -> 0.625 | N72: 10 | O72: =ROUNDUP(N72/20,2) -> 0.5
B73: 合計（人日） | H73: =SUBTOTAL(9,H7:H72) -> 98 | I73: =SUBTOTAL(9,I7:I72) -> 141.12 | J73: =SUBTOTAL(9,J7:J72) -> 215.6 | K73: =SUBTOTAL(9,K7:K72) -> 164.64 | L73: =SUBTOTAL(9,L7:L72) -> 98 | M73: =SUBTOTAL(9,M7:M72) -> 49 | N73: =SUM(H73:M73) -> 766.36
B74: 合計（人月） | H74: =ROUNDUP(SUM(H73:H73)/20,1) -> 4.9 | I74: =ROUNDUP(SUM(I73:I73)/20,1) -> 7.1 | J74: =ROUNDUP(SUM(J73:J73)/20,1) -> 10.8 | K74: =ROUNDUP(SUM(K73:K73)/20,1) -> 8.3 | L74: =ROUNDUP(SUM(L73:L73)/20,1) -> 4.9 | M74: =ROUNDUP(SUM(M73:M73)/20,1) -> 2.5 | N74: =SUM(H74:M74) -> 38.5
B75: プロジェクト管理 | H75: =ROUNDUP(H74*0.2,1) -> 1 | I75: =ROUNDUP(I74*0.2,1) -> 1.5 | J75: =ROUNDUP(J74*0.2,1) -> 2.2 | K75: =ROUNDUP(K74*0.2,1) -> 1.7 | L75: =ROUNDUP(L74*0.2,1) -> 1 | M75: =ROUNDUP(M74*0.2,1) -> 0.5 | N75: =SUM(H75:M75) -> 7.9
B76: 金額 | H76: =H74*1100000 -> 5390000 | I76: =I74*1100000 -> 7810000 | J76: =J74*1100000 -> 11880000 | K76: =K74*1100000 -> 9130000 | L76: =L74*1100000 -> 5390000 | M76: =M74*1100000 -> 2750000 | N76: =SUM(H76:M76,N75*1400000) -> 53410000
H77: =H75*1400000 -> 1400000 | I77: =I75*1400000 -> 2100000 | J77: =J75*1400000 -> 3080000 | K77: =K75*1400000 -> 2380000 | L77: =L75*1400000 -> 1400000 | M77: =M75*1400000 -> 700000

Sheet 見積案_20241128
E2: phase1 | H2: phase2 | K2: phase3 | N2: phase4
E3: 構築 | F3: 初期流動 | G3: 初期流動 | H3: 構築 | I3: 初期流動 | J3: 初期流動 | K3: 構築 | L3: 初期流動 | M3: 初期流動 | N3: 構築 | O3: 初期流動 | P3: 初期流動 | Q3: 開発 | R3: 合計 | S3: 合計
E4: =SUMIF(工数見積り_20241115!G7:G66,"〇",工数見積り_20241115!Y7:Y66)+SUMIF(工数見積り_20241115!G7:G66,"〇",工数見積り_20241115!X7:X66)*0.2*1400000 -> 19635200 | H4: =SUMIF(工数見積り_20241115!H7:H66,"〇",工数見積り_20241115!Y7:Y66)+SUMIF(工数見積り_20241115!H7:H66,"〇",工数見積り_20241115!X7:X66)*0.2*1400000 -> 12992000 | K4: =SUMIF(工数見積り_20241115!I7:I66,"〇",工数見積り_20241115!Y7:Y66)+SUMIF(工数見積り_20241115!I7:I66,"〇",工数見積り_20241115!X7:X66)*0.2*1400000 -> 35328000 | N4: =SUMIF(工数見積り_20241115!J7:J66,"〇",工数見積り_20241115!Y7:Y66)+SUMIF(工数見積り_20241115!J7:J66,"〇",工数見積り_20241115!X7:X66)*0.2*1400000 -> 7564800
A9: ■見積案
B10: 案 | C10: 方針 | D10: 期間(案) | E10: 概算見積 | T10: メリット | U10: デメリット(リスク・課題)
E11: phase1 | H11: phase2 | K11: phase3 | N11: phase4 | Q11: 合計
E12: 構築 | F12: 初期流動 | G12: 保守 | H12: 構築 | I12: 初期流動 | J12: 保守 | K12: 構築 | L12: 初期流動 | M12: 保守 | N12: 構築 | O12: 初期流動 | P12: 保守 | Q12: 構築 | R12: 初期流動 | S12: 保守
B13: 案① | C13: ・要件定義で確定した内容に基づき、設計からリリースまでを一括で実施します。 このプロセスは、ウォーターフォール開発手法を想定しています | D13: 2024年12月～2025年11月 （契約意思表示：2024年10月末） | E13: ー | F13: - | G13: - | H13: ー | I13: - | J13: - | K13: ー | L13: - | M13: - | N13: ー | O13: - | P13: - | Q13: =工数見積り_20241115!Y69+工数見積り_20241115!Y70 -> 75520000 | R13: 5400000 | S13: 見直し有 （未定） | T13: ・すべての内容を一括で実行するため、他の案よりも少ない総工数での構築が可能です。 ・全体を見通して開発を進めることで、共通化が容易になり、手戻りも少なくなります。 | U13: 《課題》 ・すべての内容を一括で行うため、1つの契約あたりの費用が大きい。 ・2024年度に予定している予算計画を大幅に超えてしまう。 《リスク》 ・一括契約のため、要件定義に変更が生じた場合の手戻りリスクが高い。
B14: 案② | C14: 《全体方針》 ・もともとのDI部様の切り分け案を活かした案となります。 ・4つのphaseで開発を行います。 ・開発手法として、要件定義の内容を分散しウォーターフォールモデルを用いて開発を進めることを想定しています。 《phase1：国内企業検索》 ・国内企業検索のシステムを構築します。 ・現在のシステムでは、tsrv-van2で購入・参照をしていますが、リリース後は国内企業情報検索で可能になります。 ※マクロのインプットは現行通り、TSRから納品されたCSVを使用する想定 《phase2：海外企業検索》 ・Direct+の移行を行います。 ・現在のDirect+では、出力されたCSVファイルをマクロで取り込んでいますが、リリース後は、海外出光グループ購入済み企業一覧から出力されるCSVファイルを取り込むようにします。 ・初期化業務は、新業務フローに従い実施できるようにシステムを更新します。 ・現行のDirect+はシステムを廃止します。 《phase3：等級・基準限度額算出／限度額申請》 ・等級算出マクロ(一次、二次)の移行を行います。 ・リリース後はWebシステム内で等級・基準限度額算出が行えるようになります。 《phase4：リスク残額(エクスポージャー)／売掛以外の債権》 ・リスク残額、売掛以外の債権を参照できるようにします。 ・SAPから売掛金などの情報を連携できるようにします。 | D14: 《契約期間》 ■phase1 2024年12月～2025年3月 （契約意思表示：2024年10月末） 保守契約変更有 ■phase2 2025年4月～2025年6月 （契約締結希望：2025年2月末） 保守契約変更無 ■phase3 2025年7月～2025年12月 （契約締結希望：2025年5月末） ■phase4 2021年1月～2026年2月 （契約締結希望：2025年11月末） | E14: =E$4 -> 19635200 | F14: 1100000 | G14: 見直し有 (月75万) | H14: =H$4*1.1 -> 14291200 | I14: 1100000 | J14: 見直し無 | K14: =K$4*1.1 -> 38860800 | L14: 2100000 | M14: 見直し無 | N14: =N$4*1.1 -> 8321280 | O14: 1100000 | P14: 見直し有 （未定） | Q14: =SUM(E14,H14,K14,N14) -> 81108480 | R14: =SUM(F14,I14,L14,O14) -> 5400000 | T14: ・部分的に機能を構築するため、開発対象外の機能については手戻りなく変更が行えます。 ※変更により見積金額が変動する可能性があります。 ・phase2が対応完了(2025年6月)することで対応期限が決まっている「現行のDirect+の基盤移行」が完了できます。 | U14: 《課題》 ・phase2移行案件においても、契約の狭間なく継続を行い為同様の問題が再度生じる。 ・保守内容の変更に伴い、保守契約の見直しが必要となる。 ※初期流動を含めて検討が必要 ・phase3の対応完了(2025年12月)するまでの間は等級、基準限度額などの算出項目についてはマクロに機能が残るため非表示となります。 《リスク》 ・総額として、一括よりもリリース回数が増えるとリスクが大きくなり、金額が高くなる。 ・全体を俯瞰しながら開発ができないため、後から構築する機能での仕様変更や考慮漏れが発生した場合、影響が大きくなる可能性がある。
B16: 案③ | C16: 《全体方針》 ・2つのphaseで開発を行います。 ・開発手法として、要件定義の内容を分散しウォーターフォールモデルを用いて開発を進めることを想定しています。 《phase1：国内企業検索／海外企業検索》 ・国内企業検索のシステムを構築します。 ・現在のシステムでは、tsrv-van2で購入・参照をしていますが、リリース後は国内企業情報検索で可能になります。 ※マクロのインプットは現行通り、TSRから納品されたCSVを使用する想定 ・Direct+の移行を行います。 ・現在のDirect+では、出力されたCSVファイルをマクロで取り込んでいますが、リリース後は、海外出光グループ購入済み企業一覧から出力されるCSVファイルを取り込むようにします。 ・初期化業務は、新業務フローに従い実施できるようにシステムを更新します。 ・現行のDirect+はシステムを廃止します。 《phase2：等級・基準限度額算出／限度額申請／リスク残額(エクスポージャー)／売掛以外の債権》 ・等級算出マクロ(一次、二次)の移行を行います。 ・リリース後はWebシステム内で等級・基準限度額算出が行えるようになります。 ・リスク残額、売掛以外の債権を参照できるようにします。 ・SAPから売掛金などの情報を連携できるようにします。 | D16: ■phase1 2024年12月～2024年5月 （契約意思表示：2024年10月末） ■phase2 2025年6月～2025年12月 （契約締結希望：2025年4月末） | E16: =E$4+H$4 -> 32627200 | F16: 1200000 | G16: 見直し有 (月75万) | H16: =(K$4+N$4)*1.06 -> 45466368 | I16: 3200000 | J16: 見直し有 （未定） | K16: - | L16: - | M16: - | N16: - | O16: - | P16: - | Q16: =E16+H16 -> 78093568 | R16: 5400000 | T16: ・部分的に機能を構築するため、開発対象外の機能については手戻りなく変更が行えます。 ※変更により見積金額が変動する可能性があります。 ・phase1が対応完了(2025年5月)することで対応期限が決まっている「現行のDirect+の基盤移行」が完了できます。 | U16: 《課題》 ・phase2移行案件においても、契約の狭間なく継続を行い為同様の問題が再度生じる。 ・保守内容の変更に伴い、保守契約の見直しが必要となる。 ※初期流動を含めて検討が必要 ・phase2の対応完了(2025年12月)するまでの間は等級、基準限度額などの算出項目についてはマクロに機能が残るため非表示となります。 《リスク》 ・総額として、一括よりもリリース回数が増えるとリスクが大きくなり、金額が高くなる。 ・全体を俯瞰しながら開発ができないため、後から構築する機能での仕様変更や考慮漏れが発生した場合、影響が大きくなる可能性がある。
B18: 案④ | C18: 《全体方針》 ・3つのphaseで開発を行います。 ・開発手法として、要件定義の内容を分散しウォーターフォールモデルを用いて開発を進めることを想定しています。 《phase1：国内企業検索》 ・国内企業検索のシステムを構築します。 ・現在のシステムでは、tsrv-van2で購入・参照をしていますが、リリース後は国内企業情報検索で可能になります。 ※マクロのインプットは現行通り、TSRから納品されたCSVを使用する想定 《phase2：海外企業検索/等級・基準限度額算出／限度額申請》 ・Direct+の移行を行います。 ・現在のDirect+では、出力されたCSVファイルをマクロで取り込んでいますが、リリース後は、海外出光グループ購入済み企業一覧から出力されるCSVファイルを取り込むようにします。 ・初期化業務は、新業務フローに従い実施できるようにシステムを更新します。 ・現行のDirect+はシステムを廃止します。 ・等級算出マクロ(一次、二次)の移行を行います。 ・リリース後はWebシステム内で等級・基準限度額算出が行えるようになります。 《phase3：リスク残額(エクスポージャー)／売掛以外の債権》 ・リスク残額、売掛以外の債権を参照できるようにします。 ・SAPから売掛金などの情報を連携できるようにします。 | D18: ■phase1 2024年12月～2025年3月 （契約意思表示：2024年10月末） ■phase2 2025年4月～2025年11月 （契約締結希望：2025年2月末） ■phase3 2025年12月～2026年1月 （契約締結希望：2025年10月末） | E18: =E$4 -> 19635200 | F18: 1100000 | G18: 見直し有 (月75万) | H18: =(H4+K4)*1.08 -> 52185600 | I18: 3200000 | J18: 見直し無 | K18: =N$4*1.08 -> 8169984 | L18: 1100000 | M18: 見直し有 （未定） | N18: - | O18: - | P18: - | Q18: =E18+H18+K18 -> 79990784 | R18: =SUM(F18,I18,L18,O18) -> 5400000 | T18: ・部分的に機能を構築するため、開発対象外の機能については手戻りなく変更が行えます。 ※変更により見積金額が変動する可能性があります。 ・phase2が対応完了(2025年11月)することで対応期限が決まっている「現行のDirect+の基盤移行」が完了できます。 | U18: 《課題》 ・phase2移行案件においても、契約の狭間なく継続を行い為同様の問題が再度生じる。 ・保守内容の変更に伴い、保守契約の見直しが必要となる。 ※初期流動を含めて検討が必要 ・phase2の対応完了(2025年11月)するまでの間は等級、基準限度額などの算出項目についてはマクロに機能が残るため非表示となります。 《リスク》 ・総額として、一括よりもリリース回数が増えるとリスクが大きくなり、金額が高くなる。 ・全体を俯瞰しながら開発ができないため、後から構築する機能での仕様変更や考慮漏れが発生した場合、影響が大きくなる可能性がある。

Sheet 見積案_old
E2: phase1 | G2: phase2 | I2: phase3 | K2: phase4
E3: 構築 | F3: 初期流動 | G3: 構築 | H3: 初期流動 | I3: 構築 | J3: 初期流動 | K3: 構築 | L3: 初期流動 | M3: 開発 | N3: 合計
E4: =SUMIF(工数見積り_20241115!G7:G66,"〇",工数見積り_20241115!Y7:Y66)+SUMIF(工数見積り_20241115!G7:G66,"〇",工数見積り_20241115!X7:X66)*0.2*1400000 -> 19635200 | G4: =SUMIF(工数見積り_20241115!H7:H66,"〇",工数見積り_20241115!Y7:Y66)+SUMIF(工数見積り_20241115!H7:H66,"〇",工数見積り_20241115!X7:X66)*0.2*1400000 -> 12992000 | I4: =SUMIF(工数見積り_20241115!I7:I66,"〇",工数見積り_20241115!Y7:Y66)+SUMIF(工数見積り_20241115!I7:I66,"〇",工数見積り_20241115!X7:X66)*0.2*1400000 -> 35328000 | K4: =SUMIF(工数見積り_20241115!J7:J66,"〇",工数見積り_20241115!Y7:Y66)+SUMIF(工数見積り_20241115!J7:J66,"〇",工数見積り_20241115!X7:X66)*0.2*1400000 -> 7564800
A9: ■見積案
B10: 案 | C10: 方針 | D10: 期間(案) | E10: 概算見積 | O10: メリット | P10: デメリット(リスク・課題)
E11: phase1 | G11: phase2 | I11: phase3 | K11: phase4 | M11: 合計
E12: 構築 | F12: 初期流動 | G12: 構築 | H12: 初期流動 | I12: 構築 | J12: 初期流動 | K12: 構築 | L12: 初期流動 | M12: 構築 | N12: 初期流動
B13: 案① | C13: ・要件定義で確定した内容に基づき、設計からリリースまでを一括で実施します。 このプロセスは、ウォーターフォール開発手法を想定しています | D13: 2024年12月～2025年11月 （契約意思表示：2024年10月末） | E13: ー | F13: - | G13: ー | H13: - | I13: ー | J13: - | K13: ー | L13: - | M13: =工数見積り_20241115!Y69+工数見積り_20241115!Y70 -> 75520000 | N13: 5400000 | O13: ・すべての内容を一括で実行するため、他の案よりも少ない総工数での構築が可能です。 ・全体を見通して開発を進めることで、共通化が容易になり、手戻りも少なくなります。 | P13: 《課題》 ・すべての内容を一括で行うため、1つの契約あたりの費用が大きい。 ・2024年度に予定している予算計画を大幅に超えてしまう。 《リスク》 ・一括契約のため、要件定義に変更が生じた場合の手戻りリスクが高い。
B14: 案② | C14: 《全体方針》 ・もともとのDI部様の切り分け案を活かした案となります。 ・4つのphaseで開発を行います。 ・開発手法として、要件定義の内容を分散しウォーターフォールモデルを用いて開発を進めることを想定しています。 《phase1：国内企業検索》 ・国内企業検索のシステムを構築します。 ・現在のシステムでは、tsrv-van2で購入・参照をしていますが、リリース後は国内企業情報検索で可能になります。 ※マクロのインプットは現行通り、TSRから納品されたCSVを使用する想定 《phase2：海外企業検索》 ・Direct+の移行を行います。 ・現在のDirect+では、出力されたCSVファイルをマクロで取り込んでいますが、リリース後は、海外出光グループ購入済み企業一覧から出力されるCSVファイルを取り込むようにします。 ・初期化業務は、新業務フローに従い実施できるようにシステムを更新します。 ・現行のDirect+はシステムを廃止します。 《phase3：等級・基準限度額算出／限度額申請》 ・等級算出マクロ(一次、二次)の移行を行います。 ・リリース後はWebシステム内で等級・基準限度額算出が行えるようになります。 《phase4：リスク残額(エクスポージャー)／売掛以外の債権》 ・リスク残額、売掛以外の債権を参照できるようにします。 ・SAPから売掛金などの情報を連携できるようにします。 | D14: 《契約期間》 ■phase1 2024年12月～2025年3月 （契約意思表示：2024年10月末） 保守契約変更有 ■phase2 2025年4月～2025年6月 （契約締結希望：2025年2月末） 保守契約変更無 ■phase3 2025年7月～2025年12月 （契約締結希望：2025年5月末） ■phase4 2021年1月～2026年2月 （契約締結希望：2025年11月末） | E14: =E$4 -> 19635200 | F14: 1100000 | G14: =G$4*1.1 -> 14291200 | H14: 1100000 | I14: =I$4*1.1 -> 38860800 | J14: 2100000 | K14: =K$4*1.1 -> 8321280 | L14: 1100000 | M14: =SUM(E14,G14,I14,K14) -> 81108480 | N14: =SUM(F14,H14,J14,L14) -> 5400000 | O14: ・部分的に機能を構築するため、開発対象外の機能については手戻りなく変更が行えます。 ※変更により見積金額が変動する可能性があります。 ・phase2が対応完了(2025年6月)することで対応期限が決まっている「現行のDirect+の基盤移行」が完了できます。 | P14: 《課題》 ・phase2移行案件においても、契約の狭間なく継続を行い為同様の問題が再度生じる。 ・保守内容の変更に伴い、保守契約の見直しが必要となる。 ※初期流動を含めて検討が必要 ・phase3の対応完了(2025年12月)するまでの間は等級、基準限度額などの算出項目についてはマクロに機能が残るため非表示となります。 《リスク》 ・総額として、一括よりもリリース回数が増えるとリスクが大きくなり、金額が高くなる。 ・全体を俯瞰しながら開発ができないため、後から構築する機能での仕様変更や考慮漏れが発生した場合、影響が大きくなる可能性がある。
B16: 案③ | C16: 《全体方針》 ・2つのphaseで開発を行います。 ・開発手法として、要件定義の内容を分散しウォーターフォールモデルを用いて開発を進めることを想定しています。 《phase1：国内企業検索／海外企業検索》 ・国内企業検索のシステムを構築します。 ・現在のシステムでは、tsrv-van2で購入・参照をしていますが、リリース後は国内企業情報検索で可能になります。 ※マクロのインプットは現行通り、TSRから納品されたCSVを使用する想定 ・Direct+の移行を行います。 ・現在のDirect+では、出力されたCSVファイルをマクロで取り込んでいますが、リリース後は、海外出光グループ購入済み企業一覧から出力されるCSVファイルを取り込むようにします。 ・初期化業務は、新業務フローに従い実施できるようにシステムを更新します。 ・現行のDirect+はシステムを廃止します。 《phase2：等級・基準限度額算出／限度額申請／リスク残額(エクスポージャー)／売掛以外の債権》 ・等級算出マクロ(一次、二次)の移行を行います。 ・リリース後はWebシステム内で等級・基準限度額算出が行えるようになります。 ・リスク残額、売掛以外の債権を参照できるようにします。 ・SAPから売掛金などの情報を連携できるようにします。 | D16: ■phase1 2024年12月～2024年5月 （契約意思表示：2024年10月末） ■phase2 2025年6月～2025年12月 （契約締結希望：2025年4月末） | E16: =E$4+G$4 -> 32627200 | F16: 1200000 | G16: =(I$4+K$4)*1.06 -> 45466368 | H16: 3200000 | J16: - | K16: - | L16: - | M16: =E16+G16 -> 78093568 | N16: 5400000 | O16: ・部分的に機能を構築するため、開発対象外の機能については手戻りなく変更が行えます。 ※変更により見積金額が変動する可能性があります。 ・phase1が対応完了(2025年5月)することで対応期限が決まっている「現行のDirect+の基盤移行」が完了できます。 | P16: 《課題》 ・phase2移行案件においても、契約の狭間なく継続を行い為同様の問題が再度生じる。 ・保守内容の変更に伴い、保守契約の見直しが必要となる。 ※初期流動を含めて検討が必要 ・phase2の対応完了(2025年12月)するまでの間は等級、基準限度額などの算出項目についてはマクロに機能が残るため非表示となります。 《リスク》 ・総額として、一括よりもリリース回数が増えるとリスクが大きくなり、金額が高くなる。 ・全体を俯瞰しながら開発ができないため、後から構築する機能での仕様変更や考慮漏れが発生した場合、影響が大きくなる可能性がある。
B18: 案④ | C18: 《全体方針》 ・3つのphaseで開発を行います。 ・開発手法として、要件定義の内容を分散しウォーターフォールモデルを用いて開発を進めることを想定しています。 《phase1：国内企業検索》 ・国内企業検索のシステムを構築します。 ・現在のシステムでは、tsrv-van2で購入・参照をしていますが、リリース後は国内企業情報検索で可能になります。 ※マクロのインプットは現行通り、TSRから納品されたCSVを使用する想定 《phase2：海外企業検索/等級・基準限度額算出／限度額申請》 ・Direct+の移行を行います。 ・現在のDirect+では、出力されたCSVファイルをマクロで取り込んでいますが、リリース後は、海外出光グループ購入済み企業一覧から出力されるCSVファイルを取り込むようにします。 ・初期化業務は、新業務フローに従い実施できるようにシステムを更新します。 ・現行のDirect+はシステムを廃止します。 ・等級算出マクロ(一次、二次)の移行を行います。 ・リリース後はWebシステム内で等級・基準限度額算出が行えるようになります。 《phase3：リスク残額(エクスポージャー)／売掛以外の債権》 ・リスク残額、売掛以外の債権を参照できるようにします。 ・SAPから売掛金などの情報を連携できるようにします。 | D18: ■phase1 2024年12月～2025年3月 （契約意思表示：2024年10月末） ■phase2 2025年4月～2025年11月 （契約締結希望：2025年2月末） ■phase3 2025年12月～2026年1月 （契約締結希望：2025年10月末） | E18: =E$4 -> 19635200 | F18: 1100000 | G18: =(G4+I4)*1.08 -> 52185600 | H18: 3200000 | I18: =K$4*1.08 -> 8169984 | J18: 1100000 | K18: - | L18: - | M18: =E18+G18+I18 -> 79990784 | N18: =SUM(F18,H18,J18,L18) -> 5400000 | O18: ・部分的に機能を構築するため、開発対象外の機能については手戻りなく変更が行えます。 ※変更により見積金額が変動する可能性があります。 ・phase2が対応完了(2025年11月)することで対応期限が決まっている「現行のDirect+の基盤移行」が完了できます。 | P18: 《課題》 ・phase2移行案件においても、契約の狭間なく継続を行い為同様の問題が再度生じる。 ・保守内容の変更に伴い、保守契約の見直しが必要となる。 ※初期流動を含めて検討が必要 ・phase2の対応完了(2025年11月)するまでの間は等級、基準限度額などの算出項目についてはマクロに機能が残るため非表示となります。 《リスク》 ・総額として、一括よりもリリース回数が増えるとリスクが大きくなり、金額が高くなる。 ・全体を俯瞰しながら開発ができないため、後から構築する機能での仕様変更や考慮漏れが発生した場合、影響が大きくなる可能性がある。
B20: ※保守に関して全ての案で現行から変更となる想定です。

Sheet 工数見積り_20241128
A1: 【債権管理統合システム】詳細工数（2024/11/28） | AB1: 特高 | AC1: 高 | AD1: 中 | AE1: 低 | AF1: 特低
AB2: 10 | AC2: 7 | AD2: 5 | AE2: 3 | AF2: 2
B3: 大分類 | C3: 中分類 | D3: 小分類 | F3: 画面機能 作業内容 | G3: パターン | P3: 難易度 | Q3: 工程 | W3: 合計 （人日） | X3: 合計 （人月） | Y3: 合計 （金額）
Q4: 設計 | R4: 製造 | S4: 単体テスト | T4: 結合テスト | U4: 総合テスト | V4: 受入テスト支援
G5: 案② | K5: 案③ | M5: 案④
G6: phase1 | H6: phase2 | I6: phase3 | J6: phase4 | K6: phase1 | L6: phase2 | M6: phase1 | N6: phase2 | O6: phase3
B7: 機能要件 | C7: 画面 | D7: 共通 | E7: ログイン | F7: ・EntraID認証 | G7: 〇 | K7: 〇 | M7: 〇 | P7: 中 | Q7: =IFERROR(HLOOKUP(P7,AB$1:AF$2,2,FALSE),0) -> 5 | R7: =Q7*0.8 -> 4 | S7: =Q7*0.6 -> 3 | T7: =Q7*1.2 -> 6 | U7: =Q7*0.8 -> 4 | V7: =Q7*0.3 -> 1.5 | W7: =SUM(Q7:V7) -> 23.5 | X7: =ROUNDUP(W7/20,2) -> 1.18 | Y7: =Z7 -> 1180000 | Z7: =X7*1000000 -> 1180000
D8: 共通 | E8: ダッシュボード | F8: ・ログイン後に遷移する画面 ・各画面へ遷移する画面 | G8: 〇 | K8: 〇 | M8: 〇 | P8: 低 | Q8: =IFERROR(HLOOKUP(P8,AB$1:AF$2,2,FALSE),0) -> 3 | R8: =Q8*0.8 -> 2.4 | S8: =Q8*0.6 -> 1.8 | T8: =Q8*1.2 -> 3.6 | U8: =Q8*0.8 -> 2.4 | V8: =Q8*0.3 -> 0.9 | W8: =SUM(Q8:V8) -> 14.1 | X8: =ROUNDUP(W8/20,2) -> 0.71 | Y8: =Z8 -> 710000 | Z8: =X8*1000000 -> 710000
D9: 共通 | E9: 企業選択 | F9: ・新規取引先限度額申請の企業選択時に使用 ・親会社評価の親会社選択で使用 | I9: 〇 | L9: 〇 | N9: 〇 | P9: 中 | Q9: =IFERROR(HLOOKUP(P9,AB$1:AF$2,2,FALSE),0) -> 5 | R9: =Q9*0.8 -> 4 | S9: =Q9*0.6 -> 3 | T9: =Q9*1.2 -> 6 | U9: =Q9*0.8 -> 4 | V9: =Q9*0.3 -> 1.5 | W9: =SUM(Q9:V9) -> 23.5 | X9: =ROUNDUP(W9/20,2) -> 1.18 | Y9: =Z9 -> 1180000 | Z9: =X9*1000000 -> 1180000
D10: 共通 | E10: 所在地選択 | F10: ・国内取引先一覧の検索で使用するモーダル ・所在地の検索が可能 | G10: 〇 | K10: 〇 | M10: 〇 | P10: 低 | Q10: =IFERROR(HLOOKUP(P10,AB$1:AF$2,2,FALSE),0) -> 3 | R10: =Q10*0.8 -> 2.4 | S10: =Q10*0.6 -> 1.8 | T10: =Q10*1.2 -> 3.6 | U10: =Q10*0.8 -> 2.4 | V10: =Q10*0.3 -> 0.9 | W10: =SUM(Q10:V10) -> 14.1 | X10: =ROUNDUP(W10/20,2) -> 0.71 | Y10: =Z10 -> 710000 | Z10: =X10*1000000 -> 710000
D11: 共通 | E11: 業種選択 | F11: ・国内取引先一覧の検索で使用するモーダル ・業種の検索が可能 | G11: 〇 | K11: 〇 | M11: 〇 | P11: 低 | Q11: =IFERROR(HLOOKUP(P11,AB$1:AF$2,2,FALSE),0) -> 3 | R11: =Q11*0.8 -> 2.4 | S11: =Q11*0.6 -> 1.8 | T11: =Q11*1.2 -> 3.6 | U11: =Q11*0.8 -> 2.4 | V11: =Q11*0.3 -> 0.9 | W11: =SUM(Q11:V11) -> 14.1 | X11: =ROUNDUP(W11/20,2) -> 0.71 | Y11: =Z11 -> 710000 | Z11: =X11*1000000 -> 710000
D12: 共通 | E12: 品目選択 | F12: ・国内取引先一覧の検索で使用するモーダル ・品目の検索が可能 | G12: 〇 | K12: 〇 | M12: 〇 | P12: 低 | Q12: =IFERROR(HLOOKUP(P12,AB$1:AF$2,2,FALSE),0) -> 3 | R12: =Q12*0.8 -> 2.4 | S12: =Q12*0.6 -> 1.8 | T12: =Q12*1.2 -> 3.6 | U12: =Q12*0.8 -> 2.4 | V12: =Q12*0.3 -> 0.9 | W12: =SUM(Q12:V12) -> 14.1 | X12: =ROUNDUP(W12/20,2) -> 0.71 | Y12: =Z12 -> 710000 | Z12: =X12*1000000 -> 710000
D13: 共通 | E13: 取引先一覧へ表示 | F13: ・下記の画面で利用する画面 海外企業詳細 海外出光グループ購入済み企業一覧 国内企業詳細 国内出光グループ取得済み企業一覧 ※項目としては記載するが工数は上記の画面に含まれる | I13: 〇 | L13: 〇 | N13: 〇 | Z13: =X13*1000000 -> 0
D14: 検索 | E14: 海外企業情報検索 | F14: ・D&B APIを使用して海外企業検索をする画面 | H14: 〇 | K14: 〇 | N14: 〇 | P14: 中 | Q14: =IFERROR(HLOOKUP(P14,AB$1:AF$2,2,FALSE),0) -> 5 | R14: =Q14*0.8 -> 4 | S14: =Q14*0.6 -> 3 | T14: =Q14*1.2 -> 6 | U14: =Q14*0.8 -> 4 | V14: =Q14*0.3 -> 1.5 | W14: =SUM(Q14:V14) -> 23.5 | X14: =ROUNDUP(W14/20,2) -> 1.18 | Y14: =Z14 -> 1180000 | Z14: =X14*1000000 -> 1180000
D15: 検索 | E15: 海外出光グループ購入済み企業一覧 | F15: ・D&B APIを使用して購入した企業を検索する画面 ・取引先の設定ができる | H15: 〇 | K15: 〇 | N15: 〇 | P15: 中 | Q15: =IFERROR(HLOOKUP(P15,AB$1:AF$2,2,FALSE),0) -> 5 | R15: =Q15*0.8 -> 4 | S15: =Q15*0.6 -> 3 | T15: =Q15*1.2 -> 6 | U15: =Q15*0.8 -> 4 | V15: =Q15*0.3 -> 1.5 | W15: =SUM(Q15:V15) -> 23.5 | X15: =ROUNDUP(W15/20,2) -> 1.18 | Y15: =Z15 -> 1180000 | Z15: =X15*1000000 -> 1180000
D16: 検索 | E16: 海外企業詳細 | F16: ・海外企業情報を表示する画面 ・購入・未購入で表示できる範囲は異なる ・D&B APIで企業情報の購入ができる ・新規限度額申請をできる ・取引先の設定ができる ・モニタリング設定ができる | H16: 〇 | K16: 〇 | N16: 〇 | P16: 中 | Q16: =IFERROR(HLOOKUP(P16,AB$1:AF$2,2,FALSE),0) -> 5 | R16: =Q16*0.8 -> 4 | S16: =Q16*0.6 -> 3 | T16: =Q16*1.2 -> 6 | U16: =Q16*0.8 -> 4 | V16: =Q16*0.3 -> 1.5 | W16: =SUM(Q16:V16) -> 23.5 | X16: =ROUNDUP(W16/20,2) -> 1.18 | Y16: =Z16 -> 1180000 | Z16: =X16*1000000 -> 1180000
D17: 検索 | E17: 国内企業情報検索 | F17: ・TSR APIを使用して国内企業検索をする画面 | G17: 〇 | K17: 〇 | M17: 〇 | P17: 中 | Q17: =IFERROR(HLOOKUP(P17,AB$1:AF$2,2,FALSE),0) -> 5 | R17: =Q17*0.8 -> 4 | S17: =Q17*0.6 -> 3 | T17: =Q17*1.2 -> 6 | U17: =Q17*0.8 -> 4 | V17: =Q17*0.3 -> 1.5 | W17: =SUM(Q17:V17) -> 23.5 | X17: =ROUNDUP(W17/20,2) -> 1.18 | Y17: =Z17 -> 1180000 | Z17: =X17*1000000 -> 1180000
D18: 検索 | E18: 国内出光グループ取得済み企業一覧 | F18: ・TSR APIを使用して取得した企業を検索する画面 ・取引先の設定ができる | G18: 〇 | K18: 〇 | M18: 〇 | P18: 中 | Q18: =IFERROR(HLOOKUP(P18,AB$1:AF$2,2,FALSE),0) -> 5 | R18: =Q18*0.8 -> 4 | S18: =Q18*0.6 -> 3 | T18: =Q18*1.2 -> 6 | U18: =Q18*0.8 -> 4 | V18: =Q18*0.3 -> 1.5 | W18: =SUM(Q18:V18) -> 23.5 | X18: =ROUNDUP(W18/20,2) -> 1.18 | Y18: =Z18 -> 1180000 | Z18: =X18*1000000 -> 1180000
D19: 検索 | E19: 国内企業詳細 | F19: ・国内企業情報を表示する画面 ・新規限度額申請をできる ・TSR APIで企業情報の購入ができる ・取引先の設定ができる | G19: 〇 | K19: 〇 | M19: 〇 | P19: 中 | Q19: =IFERROR(HLOOKUP(P19,AB$1:AF$2,2,FALSE),0) -> 5 | R19: =Q19*0.8 -> 4 | S19: =Q19*0.6 -> 3 | T19: =Q19*1.2 -> 6 | U19: =Q19*0.8 -> 4 | V19: =Q19*0.3 -> 1.5 | W19: =SUM(Q19:V19) -> 23.5 | X19: =ROUNDUP(W19/20,2) -> 1.18 | Y19: =Z19 -> 1180000 | Z19: =X19*1000000 -> 1180000
D20: 表示 | E20: 海外取引先一覧 | F20: ・取引設定された海外企業を検索する画面 ・既存限度額申請をできる | I20: 〇 | L20: 〇 | N20: 〇 | P20: 中 | Q20: =IFERROR(HLOOKUP(P20,AB$1:AF$2,2,FALSE),0) -> 5 | R20: =Q20*0.8 -> 4 | S20: =Q20*0.6 -> 3 | T20: =Q20*1.2 -> 6 | U20: =Q20*0.8 -> 4 | V20: =Q20*0.3 -> 1.5 | W20: =SUM(Q20:V20) -> 23.5 | X20: =ROUNDUP(W20/20,2) -> 1.18 | Y20: =Z20 -> 1180000 | Z20: =X20*1000000 -> 1180000
D21: 表示 | E21: 国内取引先一覧 | F21: ・取引設定された国内企業を検索する画面 ・既存限度額申請をできる | I21: 〇 | L21: 〇 | N21: 〇 | P21: 中 | Q21: =IFERROR(HLOOKUP(P21,AB$1:AF$2,2,FALSE),0) -> 5 | R21: =Q21*0.8 -> 4 | S21: =Q21*0.6 -> 3 | T21: =Q21*1.2 -> 6 | U21: =Q21*0.8 -> 4 | V21: =Q21*0.3 -> 1.5 | W21: =SUM(Q21:V21) -> 23.5 | X21: =ROUNDUP(W21/20,2) -> 1.18 | Y21: =Z21 -> 1180000 | Z21: =X21*1000000 -> 1180000
D22: 申請 | E22: 新規取引先限度額申請 | F22: ・新規の限度額申請書を作成する画面 ・評価方法を選択して等級及び基準限度額を算出する | I22: 〇 | L22: 〇 | N22: 〇 | P22: 高 | Q22: =IFERROR(HLOOKUP(P22,AB$1:AF$2,2,FALSE),0) -> 7 | R22: =Q22*0.8 -> 5.6 | S22: =Q22*0.6 -> 4.2 | T22: =Q22*1.2 -> 8.4 | U22: =Q22*0.8 -> 5.6 | V22: =Q22*0.3 -> 2.1 | W22: =SUM(Q22:V22) -> 32.9 | X22: =ROUNDUP(W22/20,2) -> 1.65 | Y22: =Z22 -> 1650000 | Z22: =X22*1000000 -> 1650000
D23: 申請 | E23: 既存取引先限度額申請 | F23: <要件定義未実施> ・既存の限度額申請書を作成する画面 ・取引先一覧で選択した企業の限度額申請書を作成する ・評価方法を選択して等級及び基準限度額を再算出することも可能 | I23: 〇 | L23: 〇 | N23: 〇 | P23: 特高 | Q23: =IFERROR(HLOOKUP(P23,AB$1:AF$2,2,FALSE),0) -> 10 | R23: =Q23*0.8 -> 8 | S23: =Q23*0.6 -> 6 | T23: =Q23*1.2 -> 12 | U23: =Q23*0.8 -> 8 | V23: =Q23*0.3 -> 3 | W23: =SUM(Q23:V23) -> 47 | X23: =ROUNDUP(W23/20,2) -> 2.35 | Y23: =Z23 -> 2350000 | Z23: =X23*1000000 -> 2350000
D24: 申請 | E24: 取引先限度額申請一覧 | F24: ・取引先限度額申請を一覧で表示する。 ・現在の申請の状況を確認する。 | I24: 〇 | L24: 〇 | N24: 〇 | P24: 低 | Q24: =IFERROR(HLOOKUP(P24,AB$1:AF$2,2,FALSE),0) -> 3 | R24: =Q24*0.8 -> 2.4 | S24: =Q24*0.6 -> 1.8 | T24: =Q24*1.2 -> 3.6 | U24: =Q24*0.8 -> 2.4 | V24: =Q24*0.3 -> 0.9 | W24: =SUM(Q24:V24) -> 14.1 | X24: =ROUNDUP(W24/20,2) -> 0.71 | Y24: =Z24 -> 710000 | Z24: =X24*1000000 -> 710000
D25: 計算 | E25: Moody’s/S&P評価 | F25: ・取引先限度額申請時に「Moody’s/S&P評価」を入力する画面 | I25: 〇 | L25: 〇 | N25: 〇 | P25: 低 | Q25: =IFERROR(HLOOKUP(P25,AB$1:AF$2,2,FALSE),0) -> 3 | R25: =Q25*0.8 -> 2.4 | S25: =Q25*0.6 -> 1.8 | T25: =Q25*1.2 -> 3.6 | U25: =Q25*0.8 -> 2.4 | V25: =Q25*0.3 -> 0.9 | W25: =SUM(Q25:V25) -> 14.1 | X25: =ROUNDUP(W25/20,2) -> 0.71 | Y25: =Z25 -> 710000 | Z25: =X25*1000000 -> 710000
D26: 計算 | E26: TDB評価 | F26: ・取引先限度額申請時に「TDB情報」を入力する画面 | I26: 〇 | L26: 〇 | N26: 〇 | P26: 低 | Q26: =IFERROR(HLOOKUP(P26,AB$1:AF$2,2,FALSE),0) -> 3 | R26: =Q26*0.8 -> 2.4 | S26: =Q26*0.6 -> 1.8 | T26: =Q26*1.2 -> 3.6 | U26: =Q26*0.8 -> 2.4 | V26: =Q26*0.3 -> 0.9 | W26: =SUM(Q26:V26) -> 14.1 | X26: =ROUNDUP(W26/20,2) -> 0.71 | Y26: =Z26 -> 710000 | Z26: =X26*1000000 -> 710000
D27: 計算 | E27: 決算書分析 | F27: ・決算情報を入力して決算分析をする画面 ・算出結果は新規および既存取引先限度額申請で表示する | I27: 〇 | L27: 〇 | N27: 〇 | P27: 低 | Q27: =IFERROR(HLOOKUP(P27,AB$1:AF$2,2,FALSE),0) -> 3 | R27: =Q27*0.8 -> 2.4 | S27: =Q27*0.6 -> 1.8 | T27: =Q27*1.2 -> 3.6 | U27: =Q27*0.8 -> 2.4 | V27: =Q27*0.3 -> 0.9 | W27: =SUM(Q27:V27) -> 14.1 | X27: =ROUNDUP(W27/20,2) -> 0.71 | Y27: =Z27 -> 710000 | Z27: =X27*1000000 -> 710000
D28: 計算 | E28: リスク残額 | F28: <要件定義未実施> ・各企業の売掛金、倒産リスクからエクスポージャーを算出して表示する画面 ・部署や取引先、全社などドリルダウンしながら参照ができる ・前提条件としてSAPから売掛金情報を取得してグルーピングできること | J28: 〇 | L28: 〇 | O28: 〇 | P28: 特高 | Z28: =X28*1000000 -> 0
D29: 計算 | E29: 債権リスク一覧 | F29: ・SAPから取得した債権情報を事業部・課・取引先・国別に表示する画面。 ・対象は取引先一覧に評されている企業 | J29: 〇 | L29: 〇 | O29: 〇 | P29: 低 | Q29: =IFERROR(HLOOKUP(P29,AB$1:AF$2,2,FALSE),0) -> 3 | R29: =Q29*0.8 -> 2.4 | S29: =Q29*0.6 -> 1.8 | T29: =Q29*1.2 -> 3.6 | U29: =Q29*0.8 -> 2.4 | V29: =Q29*0.3 -> 0.9 | W29: =SUM(Q29:V29) -> 14.1 | X29: =ROUNDUP(W29/20,2) -> 0.71 | Y29: =Z29 -> 710000 | Z29: =X29*1000000 -> 710000
D30: 計算 | E30: 債権管理等級別リスク分析 | F30: ・SAPから取得した債権情報を債権等級別に表示する画面 ・対象は取引先一覧に評されている企業 | J30: 〇 | L30: 〇 | O30: 〇 | P30: 低 | Q30: =IFERROR(HLOOKUP(P30,AB$1:AF$2,2,FALSE),0) -> 3 | R30: =Q30*0.8 -> 2.4 | S30: =Q30*0.6 -> 1.8 | T30: =Q30*1.2 -> 3.6 | U30: =Q30*0.8 -> 2.4 | V30: =Q30*0.3 -> 0.9 | W30: =SUM(Q30:V30) -> 14.1 | X30: =ROUNDUP(W30/20,2) -> 0.71 | Y30: =Z30 -> 710000 | Z30: =X30*1000000 -> 710000
D31: 計算 | E31: 債権リスク推移 | F31: ・SAPから取得した債権情報をグラフで表示する画面 | J31: 〇 | L31: 〇 | O31: 〇 | P31: 中 | Q31: =IFERROR(HLOOKUP(P31,AB$1:AF$2,2,FALSE),0) -> 5 | R31: =Q31*0.8 -> 4 | S31: =Q31*0.6 -> 3 | T31: =Q31*1.2 -> 6 | U31: =Q31*0.8 -> 4 | V31: =Q31*0.3 -> 1.5 | W31: =SUM(Q31:V31) -> 23.5 | X31: =ROUNDUP(W31/20,2) -> 1.18 | Y31: =Z31 -> 1180000 | Z31: =X31*1000000 -> 1180000
D32: 計算 | E32: 売掛以外の債権 | F32: <要件定義未実施> ・売掛以外の債権を部署ごとなどで確認出来る画面 ・前提条件としてSAPから売掛以外の債権情報を取得できること | J32: 〇 | L32: 〇 | O32: 〇 | P32: 特高 | Z32: =X32*1000000 -> 0
D33: 共通 | E33: SAP情報アップロード | F33: <要件定義未実施> ・SAPからの情報を債権管理統合システムに取り込む画面 ※取込バッチになる可能性あり。 | J33: 〇 | L33: 〇 | O33: 〇 | P33: 特高 | Z33: =X33*1000000 -> 0
D34: 共通 | E34: 帝国データバンク企業情報 | F34: <要件定義未実施> ・帝国データバンクの情報をアップロードする画面 ※取込バッチになる可能性あり。 | I34: 〇 | L34: 〇 | N34: 〇 | P34: 低 | Q34: =IFERROR(HLOOKUP(P34,AB$1:AF$2,2,FALSE),0) -> 3 | R34: =Q34*0.8 -> 2.4 | S34: =Q34*0.6 -> 1.8 | T34: =Q34*1.2 -> 3.6 | U34: =Q34*0.8 -> 2.4 | V34: =Q34*0.3 -> 0.9 | W34: =SUM(Q34:V34) -> 14.1 | X34: =ROUNDUP(W34/20,2) -> 0.71 | Y34: =Z34 -> 710000 | Z34: =X34*1000000 -> 710000
D35: 共通 | E35: 為替 | F35: <要件定義未実施> ・為替情報をアップロードする画面 | I35: 〇 | L35: 〇 | N35: 〇 | P35: 低 | Q35: =IFERROR(HLOOKUP(P35,AB$1:AF$2,2,FALSE),0) -> 3 | R35: =Q35*0.8 -> 2.4 | S35: =Q35*0.6 -> 1.8 | T35: =Q35*1.2 -> 3.6 | U35: =Q35*0.8 -> 2.4 | V35: =Q35*0.3 -> 0.9 | W35: =SUM(Q35:V35) -> 14.1 | X35: =ROUNDUP(W35/20,2) -> 0.71 | Y35: =Z35 -> 710000 | Z35: =X35*1000000 -> 710000
D36: 共通 | E36: S&P , Moody's | F36: <要件定義未実施> ・S&P , Moody's情報を編集する画面 ・新規限度額申請で入力した情報を管理 | I36: 〇 | L36: 〇 | N36: 〇 | P36: 低 | Q36: =IFERROR(HLOOKUP(P36,AB$1:AF$2,2,FALSE),0) -> 3 | R36: =Q36*0.8 -> 2.4 | S36: =Q36*0.6 -> 1.8 | T36: =Q36*1.2 -> 3.6 | U36: =Q36*0.8 -> 2.4 | V36: =Q36*0.3 -> 0.9 | W36: =SUM(Q36:V36) -> 14.1 | X36: =ROUNDUP(W36/20,2) -> 0.71 | Y36: =Z36 -> 710000 | Z36: =X36*1000000 -> 710000
D37: 共通 | E37: S&Pソブリン格付け | F37: <要件定義未実施> ・S&Pソブリン格付け情報をアップロードする画面 | I37: 〇 | L37: 〇 | N37: 〇 | P37: 低 | Q37: =IFERROR(HLOOKUP(P37,AB$1:AF$2,2,FALSE),0) -> 3 | R37: =Q37*0.8 -> 2.4 | S37: =Q37*0.6 -> 1.8 | T37: =Q37*1.2 -> 3.6 | U37: =Q37*0.8 -> 2.4 | V37: =Q37*0.3 -> 0.9 | W37: =SUM(Q37:V37) -> 14.1 | X37: =ROUNDUP(W37/20,2) -> 0.71 | Y37: =Z37 -> 710000 | Z37: =X37*1000000 -> 710000
D38: 共通 | E38: 海外企業情報初期化 | F38: ・海外企業情報の初期化対象をアップロードする画面 ・アップロードした企業で初期化をいつ実施するかスケジュールすることができる | H38: 〇 | K38: 〇 | N38: 〇 | P38: 高 | Q38: =IFERROR(HLOOKUP(P38,AB$1:AF$2,2,FALSE),0) -> 7 | R38: =Q38*0.8 -> 5.6 | S38: =Q38*0.6 -> 4.2 | T38: =Q38*1.2 -> 8.4 | U38: =Q38*0.8 -> 5.6 | V38: =Q38*0.3 -> 2.1 | W38: =SUM(Q38:V38) -> 32.9 | X38: =ROUNDUP(W38/20,2) -> 1.65 | Y38: =Z38 -> 1650000 | Z38: =X38*1000000 -> 1650000
D39: 共通 | E39: 販売組織/利益センター/所属課管理 | F39: ・販売組織、利益センター、所属課をアップロードして管理する画面 ・アップロードした情報のマッピングを行う | I39: 〇 | L39: 〇 | N39: 〇 | P39: 中 | Q39: =IFERROR(HLOOKUP(P39,AB$1:AF$2,2,FALSE),0) -> 5 | R39: =Q39*0.8 -> 4 | S39: =Q39*0.6 -> 3 | T39: =Q39*1.2 -> 6 | U39: =Q39*0.8 -> 4 | V39: =Q39*0.3 -> 1.5 | W39: =SUM(Q39:V39) -> 23.5 | X39: =ROUNDUP(W39/20,2) -> 1.18 | Y39: =Z39 -> 1180000 | Z39: =X39*1000000 -> 1180000
D40: 共通 | E40: TSR納品情報管理 | F40: ・TSRから納品した企業情報、リスクスコア情報をアップロードする画面 ・アップロードした情報は「国内企業情報更新」バッチで使用 | I40: 〇 | L40: 〇 | N40: 〇 | P40: 低 | Q40: =IFERROR(HLOOKUP(P40,AB$1:AF$2,2,FALSE),0) -> 3 | R40: =Q40*0.8 -> 2.4 | S40: =Q40*0.6 -> 1.8 | T40: =Q40*1.2 -> 3.6 | U40: =Q40*0.8 -> 2.4 | V40: =Q40*0.3 -> 0.9 | W40: =SUM(Q40:V40) -> 14.1 | X40: =ROUNDUP(W40/20,2) -> 0.71 | Y40: =Z40 -> 710000 | Z40: =X40*1000000 -> 710000
C41: 帳票 | D41: 検索 | E41: 国内取得済企業一覧 | F41: ・国内出光グループ取得済み企業一覧で出力するCSV | G41: 〇 | K41: 〇 | M41: 〇 | P41: 低 | Q41: =IFERROR(HLOOKUP(P41,AB$1:AF$2,2,FALSE),0) -> 3 | R41: =Q41*0.8 -> 2.4 | S41: =Q41*0.6 -> 1.8 | T41: =Q41*1.2 -> 3.6 | U41: =Q41*0.8 -> 2.4 | V41: =Q41*0.3 -> 0.9 | W41: =SUM(Q41:V41) -> 14.1 | X41: =ROUNDUP(W41/20,2) -> 0.71 | Y41: =Z41 -> 710000 | Z41: =X41*1000000 -> 710000
D42: 検索 | E42: 海外購入済企業一覧 | F42: ・海外出光グループ購入済み企業一覧で出力するCSV ・海外企業情報初期化で使用する | H42: 〇 | K42: 〇 | N42: 〇 | P42: 低 | Q42: =IFERROR(HLOOKUP(P42,AB$1:AF$2,2,FALSE),0) -> 3 | R42: =Q42*0.8 -> 2.4 | S42: =Q42*0.6 -> 1.8 | T42: =Q42*1.2 -> 3.6 | U42: =Q42*0.8 -> 2.4 | V42: =Q42*0.3 -> 0.9 | W42: =SUM(Q42:V42) -> 14.1 | X42: =ROUNDUP(W42/20,2) -> 0.71 | Y42: =Z42 -> 710000 | Z42: =X42*1000000 -> 710000
D43: 検索 | E43: 国内企業情報 | F43: ・国内企業詳細で出力するPDF | G43: 〇 | K43: 〇 | M43: 〇 | P43: 中 | Q43: =IFERROR(HLOOKUP(P43,AB$1:AF$2,2,FALSE),0) -> 5 | R43: =Q43*0.8 -> 4 | S43: =Q43*0.6 -> 3 | T43: =Q43*1.2 -> 6 | U43: =Q43*0.8 -> 4 | V43: =Q43*0.3 -> 1.5 | W43: =SUM(Q43:V43) -> 23.5 | X43: =ROUNDUP(W43/20,2) -> 1.18 | Y43: =Z43 -> 1180000 | Z43: =X43*1000000 -> 1180000
D44: 検索 | E44: 海外企業情報 | F44: ・海外企業詳細で出力するPDF | H44: 〇 | K44: 〇 | N44: 〇 | P44: 中 | Q44: =IFERROR(HLOOKUP(P44,AB$1:AF$2,2,FALSE),0) -> 5 | R44: =Q44*0.8 -> 4 | S44: =Q44*0.6 -> 3 | T44: =Q44*1.2 -> 6 | U44: =Q44*0.8 -> 4 | V44: =Q44*0.3 -> 1.5 | W44: =SUM(Q44:V44) -> 23.5 | X44: =ROUNDUP(W44/20,2) -> 1.18 | Y44: =Z44 -> 1180000 | Z44: =X44*1000000 -> 1180000
D45: 表示 | E45: 国内取引先企業一覧 | F45: ・国内取引先一覧で出力するExcel | I45: 〇 | L45: 〇 | N45: 〇 | P45: 中 | Q45: =IFERROR(HLOOKUP(P45,AB$1:AF$2,2,FALSE),0) -> 5 | R45: =Q45*0.8 -> 4 | S45: =Q45*0.6 -> 3 | T45: =Q45*1.2 -> 6 | U45: =Q45*0.8 -> 4 | V45: =Q45*0.3 -> 1.5 | W45: =SUM(Q45:V45) -> 23.5 | X45: =ROUNDUP(W45/20,2) -> 1.18 | Y45: =Z45 -> 1180000 | Z45: =X45*1000000 -> 1180000
D46: 表示 | E46: 海外取引先企業一覧 | F46: ・海外取引先一覧で出力するExcel | I46: 〇 | L46: 〇 | N46: 〇 | P46: 中 | Q46: =IFERROR(HLOOKUP(P46,AB$1:AF$2,2,FALSE),0) -> 5 | R46: =Q46*0.8 -> 4 | S46: =Q46*0.6 -> 3 | T46: =Q46*1.2 -> 6 | U46: =Q46*0.8 -> 4 | V46: =Q46*0.3 -> 1.5 | W46: =SUM(Q46:V46) -> 23.5 | X46: =ROUNDUP(W46/20,2) -> 1.18 | Y46: =Z46 -> 1180000 | Z46: =X46*1000000 -> 1180000
D47: 申請・承認 | E47: 新規限度申請書 | F47: ・新規取引先限度額申請で出力するExcel ・出力したExcelは汎用WFで添付する | I47: 〇 | L47: 〇 | N47: 〇 | P47: 高 | Q47: =IFERROR(HLOOKUP(P47,AB$1:AF$2,2,FALSE),0) -> 7 | R47: =Q47*0.8 -> 5.6 | S47: =Q47*0.6 -> 4.2 | T47: =Q47*1.2 -> 8.4 | U47: =Q47*0.8 -> 5.6 | V47: =Q47*0.3 -> 2.1 | W47: =SUM(Q47:V47) -> 32.9 | X47: =ROUNDUP(W47/20,2) -> 1.65 | Y47: =Z47 -> 1650000 | Z47: =X47*1000000 -> 1650000
D48: 申請・承認 | E48: 既存限度申請書 | F48: <要件定義未実施> ・既存取引先限度額申請で出力するExcel ・出力したExcelは汎用WFで添付する | I48: 〇 | L48: 〇 | N48: 〇 | P48: 高 | Q48: =IFERROR(HLOOKUP(P48,AB$1:AF$2,2,FALSE),0) -> 7 | R48: =Q48*0.8 -> 5.6 | S48: =Q48*0.6 -> 4.2 | T48: =Q48*1.2 -> 8.4 | U48: =Q48*0.8 -> 5.6 | V48: =Q48*0.3 -> 2.1 | W48: =SUM(Q48:V48) -> 32.9 | X48: =ROUNDUP(W48/20,2) -> 1.65 | Y48: =Z48 -> 1650000 | Z48: =X48*1000000 -> 1650000
D49: 計算 | E49: 債権リスク分析 | F49: <要件定義未実施> ・リスク残額で出力するPDF | J49: 〇 | L49: 〇 | O49: 〇 | P49: 中 | Z49: =X49*1000000 -> 0
D50: 計算 | E50: 債権リスク分析 | F50: <要件定義未実施> ・リスク残額で出力するCSV | J50: 〇 | L50: 〇 | O50: 〇 | P50: 低 | Z50: =X50*1000000 -> 0
D51: 計算 | E51: 債権リスク一覧 | F51: ・債権リスク一覧に表示している内容をExcelに出力する ※リスク残額から分割 | J51: 〇 | L51: 〇 | O51: 〇 | P51: 低 | Q51: =IFERROR(HLOOKUP(P51,AB$1:AF$2,2,FALSE),0) -> 3 | R51: =Q51*0.8 -> 2.4 | S51: =Q51*0.6 -> 1.8 | T51: =Q51*1.2 -> 3.6 | U51: =Q51*0.8 -> 2.4 | V51: =Q51*0.3 -> 0.9 | W51: =SUM(Q51:V51) -> 14.1 | X51: =ROUNDUP(W51/20,2) -> 0.71 | Y51: =Z51 -> 710000 | Z51: =X51*1000000 -> 710000
D52: 計算 | E52: 債権管理等級別リスク分析 | F52: ・債権管理等級別リスク分析に表示している内容をExcelに出力する ※リスク残額から分割 | J52: 〇 | L52: 〇 | O52: 〇 | P52: 低 | Q52: =IFERROR(HLOOKUP(P52,AB$1:AF$2,2,FALSE),0) -> 3 | R52: =Q52*0.8 -> 2.4 | S52: =Q52*0.6 -> 1.8 | T52: =Q52*1.2 -> 3.6 | U52: =Q52*0.8 -> 2.4 | V52: =Q52*0.3 -> 0.9 | W52: =SUM(Q52:V52) -> 14.1 | X52: =ROUNDUP(W52/20,2) -> 0.71 | Y52: =Z52 -> 710000 | Z52: =X52*1000000 -> 710000
D53: 計算 | E53: 債権リスク推移 | F53: ・債権リスク推移に表示している内容をExcelに出力する ※グラフは対象外 ※リスク残額から分割 | J53: 〇 | L53: 〇 | O53: 〇 | P53: 低 | Q53: =IFERROR(HLOOKUP(P53,AB$1:AF$2,2,FALSE),0) -> 3 | R53: =Q53*0.8 -> 2.4 | S53: =Q53*0.6 -> 1.8 | T53: =Q53*1.2 -> 3.6 | U53: =Q53*0.8 -> 2.4 | V53: =Q53*0.3 -> 0.9 | W53: =SUM(Q53:V53) -> 14.1 | X53: =ROUNDUP(W53/20,2) -> 0.71 | Y53: =Z53 -> 710000 | Z53: =X53*1000000 -> 710000
C54: バッチ | D54: 共通 | E54: 海外企業情報更新 | F54: ・海外企業情報を日次で最新化するバッチ ・モニタリング対象の海外企業情報をD&B APIを使用して最新の情報を取得する | H54: 〇 | K54: 〇 | N54: 〇 | P54: 中 | Q54: =IFERROR(HLOOKUP(P54,AB$1:AF$2,2,FALSE),0) -> 5 | R54: =Q54*0.8 -> 4 | S54: =Q54*0.6 -> 3 | T54: =Q54*1.2 -> 6 | U54: =Q54*0.8 -> 4 | V54: =Q54*0.3 -> 1.5 | W54: =SUM(Q54:V54) -> 23.5 | X54: =ROUNDUP(W54/20,2) -> 1.18 | Y54: =Z54 -> 1180000 | Z54: =X54*1000000 -> 1180000
D55: 共通 | E55: 国内企業情報更新 | F55: ・国内企業情報を日次で最新化するバッチ ・対象の国内企業情報をTSR APIを使用して最新情報を取得する | G55: 〇 | K55: 〇 | M55: 〇 | P55: 中 | Q55: =IFERROR(HLOOKUP(P55,AB$1:AF$2,2,FALSE),0) -> 5 | R55: =Q55*0.8 -> 4 | S55: =Q55*0.6 -> 3 | T55: =Q55*1.2 -> 6 | U55: =Q55*0.8 -> 4 | V55: =Q55*0.3 -> 1.5 | W55: =SUM(Q55:V55) -> 23.5 | X55: =ROUNDUP(W55/20,2) -> 1.18 | Y55: =Z55 -> 1180000 | Z55: =X55*1000000 -> 1180000
D56: 共通 | E56: 海外企業購入情報初期化 | F56: ・海外企業情報初期化でスケジュールされた海外企業一覧でシステム内の購入情報を初期化するバッチ | H56: 〇 | K56: 〇 | N56: 〇 | P56: 中 | Q56: =IFERROR(HLOOKUP(P56,AB$1:AF$2,2,FALSE),0) -> 5 | R56: =Q56*0.8 -> 4 | S56: =Q56*0.6 -> 3 | T56: =Q56*1.2 -> 6 | U56: =Q56*0.8 -> 4 | V56: =Q56*0.3 -> 1.5 | W56: =SUM(Q56:V56) -> 23.5 | X56: =ROUNDUP(W56/20,2) -> 1.18 | Y56: =Z56 -> 1180000 | Z56: =X56*1000000 -> 1180000
D57: 共通 | E57: 海外企業購入情報初期化（リカバリ用） | F57: ・海外企業情報初期化リカバリ用のバッチ ・処理は海外企業情報初期化と合わせて行うため工数はなし | H57: 〇 | K57: 〇 | N57: 〇
D58: 計算 | E58: 等級算出 | F58: <要件定義未実施> ・毎月月初に最新の企業情報で等級を算出するバッチ | I58: 〇 | L58: 〇 | N58: 〇 | P58: 特高 | Q58: =IFERROR(HLOOKUP(P58,AB$1:AF$2,2,FALSE),0) -> 10 | R58: =Q58*0.8 -> 8 | S58: =Q58*0.6 -> 6 | T58: =Q58*1.2 -> 12 | U58: =Q58*0.8 -> 8 | V58: =Q58*0.3 -> 3 | W58: =SUM(Q58:V58) -> 47 | X58: =ROUNDUP(W58/20,2) -> 2.35 | Y58: =Z58 -> 2350000 | Z58: =X58*1000000 -> 2350000
D59: 申請・承認 | E59: Box監視 | F59: <要件定義未実施> ・汎用WFで出力されたExcelを監視するバッチ | I59: 〇 | L59: 〇 | N59: 〇 | P59: 高 | Q59: =IFERROR(HLOOKUP(P59,AB$1:AF$2,2,FALSE),0) -> 7 | R59: =Q59*0.8 -> 5.6 | S59: =Q59*0.6 -> 4.2 | T59: =Q59*1.2 -> 8.4 | U59: =Q59*0.8 -> 5.6 | V59: =Q59*0.3 -> 2.1 | W59: =SUM(Q59:V59) -> 32.9 | X59: =ROUNDUP(W59/20,2) -> 1.65 | Y59: =Z59 -> 1650000 | Z59: =X59*1000000 -> 1650000
D60: 計算 | E60: SAP得意先情報取込 | F60: ・SAPの得意先情報をBoxから取り込むバッチ | I60: 〇 | L60: 〇 | N60: 〇 | P60: 中 | Q60: =IFERROR(HLOOKUP(P60,AB$1:AF$2,2,FALSE),0) -> 5 | R60: =Q60*0.8 -> 4 | S60: =Q60*0.6 -> 3 | T60: =Q60*1.2 -> 6 | U60: =Q60*0.8 -> 4 | V60: =Q60*0.3 -> 1.5 | W60: =SUM(Q60:V60) -> 23.5 | X60: =ROUNDUP(W60/20,2) -> 1.18 | Y60: =Z60 -> 1180000 | Z60: =X60*1000000 -> 1180000
D61: 計算 | E61: SAP債権情報取込 | F61: ・SAPの債権情報をBoxから取り込むバッチ | J61: 〇 | L61: 〇 | O61: 〇 | P61: 中 | Q61: =IFERROR(HLOOKUP(P61,AB$1:AF$2,2,FALSE),0) -> 5 | R61: =Q61*0.8 -> 4 | S61: =Q61*0.6 -> 3 | T61: =Q61*1.2 -> 6 | U61: =Q61*0.8 -> 4 | V61: =Q61*0.3 -> 1.5 | W61: =SUM(Q61:V61) -> 23.5 | X61: =ROUNDUP(W61/20,2) -> 1.18 | Y61: =Z61 -> 1180000 | Z61: =X61*1000000 -> 1180000
B62: 非機能要件 | D62: 共通 | E62: データ移行(国内企業情報) | F62: 既存システムからのデータ移行 tsrvan2からのデータ登録 | G62: 〇 | K62: 〇 | M62: 〇 | P62: 低 | Q62: =IFERROR(HLOOKUP(P62,AB$1:AF$2,2,FALSE),0) -> 3 | R62: =Q62*0.8 -> 2.4 | S62: =Q62*0.6 -> 1.8 | T62: =Q62*1.2 -> 3.6 | U62: =Q62*0.8 -> 2.4 | V62: =Q62*0.3 -> 0.9 | W62: =SUM(Q62:V62) -> 14.1 | X62: =ROUNDUP(W62/20,2) -> 0.71 | Y62: =Z62 -> 710000 | Z62: =X62*1000000 -> 710000
D63: 共通 | E63: データ移行(海外企業情報) | F63: 既存システムからのデータ移行 MySQLからのデータ登録 | H63: 〇 | K63: 〇 | N63: 〇 | P63: 低 | Q63: =IFERROR(HLOOKUP(P63,AB$1:AF$2,2,FALSE),0) -> 3 | R63: =Q63*0.8 -> 2.4 | S63: =Q63*0.6 -> 1.8 | T63: =Q63*1.2 -> 3.6 | U63: =Q63*0.8 -> 2.4 | V63: =Q63*0.3 -> 0.9 | W63: =SUM(Q63:V63) -> 14.1 | X63: =ROUNDUP(W63/20,2) -> 0.71 | Y63: =Z63 -> 710000 | Z63: =X63*1000000 -> 710000
D64: 共通 | E64: データ移行(マクロ) | F64: 既存システムからのデータ移行 Excelからのデータ登録 | I64: 〇 | L64: 〇 | N64: 〇 | P64: 高 | Q64: =IFERROR(HLOOKUP(P64,AB$1:AF$2,2,FALSE),0) -> 7 | R64: =Q64*0.8 -> 5.6 | S64: =Q64*0.6 -> 4.2 | T64: =Q64*1.2 -> 8.4 | U64: =Q64*0.8 -> 5.6 | V64: =Q64*0.3 -> 2.1 | W64: =SUM(Q64:V64) -> 32.9 | X64: =ROUNDUP(W64/20,2) -> 1.65 | Y64: =Z64 -> 1650000 | Z64: =X64*1000000 -> 1650000
D65: 共通 | E65: システム構成 | F65: Azure環境の設定 運用設計 | G65: 〇 | K65: 〇 | M65: 〇 | P65: 特高 | Q65: =IFERROR(HLOOKUP(P65,AB$1:AF$2,2,FALSE),0) -> 10 | R65: =Q65*0.8 -> 8 | S65: =Q65*0.6 -> 6 | T65: =Q65*1.2 -> 12 | U65: =Q65*0.8 -> 8 | V65: =Q65*0.3 -> 3 | W65: =SUM(Q65:V65) -> 47 | X65: =ROUNDUP(W65/20,2) -> 2.35 | Y65: =Z65 -> 2350000 | Z65: =X65*1000000 -> 2350000
D66: 共通 | E66: 共通部品作成 | F66: Webアプリケーションの共通部品を作成 多言語対応 画面の解像度対応 | G66: 〇 | K66: 〇 | M66: 〇 | P66: 高 | Q66: =IFERROR(HLOOKUP(P66,AB$1:AF$2,2,FALSE),0) -> 7 | R66: =Q66*0.8 -> 5.6 | S66: =Q66*0.6 -> 4.2 | T66: =Q66*1.2 -> 8.4 | U66: =Q66*0.8 -> 5.6 | V66: =Q66*0.3 -> 2.1 | W66: =SUM(Q66:V66) -> 32.9 | X66: =ROUNDUP(W66/20,2) -> 1.65 | Y66: =Z66 -> 1650000 | Z66: =X66*1000000 -> 1650000
B67: 小計(人日) | P67: - | Q67: =SUM(Q6:Q66) -> 250 | R67: =SUM(R6:R66) -> 200 | S67: =SUM(S6:S66) -> 150 | T67: =SUM(T6:T66) -> 300 | U67: =SUM(U6:U66) -> 200 | V67: =SUM(V6:V66) -> 75 | W67: =SUM(Q67:V67) -> 1175
B68: 小計(人月) | P68: - | Q68: =Q67/20 -> 12.5 | R68: =R67/20 -> 10 | S68: =S67/20 -> 7.5 | T68: =T67/20 -> 15 | U68: =U67/20 -> 10 | V68: =V67/20 -> 3.75 | W68: =W67/20 -> 58.75 | X68: =SUM(X7:X66) -> 59
B69: 開発費用 | Y69: =SUM(Y7:Y66) -> 59000000
B70: 管理費用 | Y70: =X68*0.2*1400000 -> 16520000
B71: 初期流動(2か月) | Y71: 5400000
B72: 構築費用（管理費用+開発費用） | Y72: =Y69+Y70 -> 75520000
B73: 合計 | Y73: =Y71+Y72 -> 80920000

Sheet 工数見積り_20241115
A1: 【債権管理統合システム】詳細工数（2024/11/15） | AB1: 特高 | AC1: 高 | AD1: 中 | AE1: 低 | AF1: 特低
AB2: 10 | AC2: 7 | AD2: 5 | AE2: 3 | AF2: 2
B3: 大分類 | C3: 中分類 | D3: 小分類 | F3: 画面機能 作業内容 | G3: パターン | P3: 難易度 | Q3: 工程 | W3: 合計 （人日） | X3: 合計 （人月） | Y3: 合計 （金額）
Q4: 設計 | R4: 製造 | S4: 単体テスト | T4: 結合テスト | U4: 総合テスト | V4: 受入テスト支援
G5: 案② | K5: 案③ | M5: 案④
G6: phase1 | H6: phase2 | I6: phase3 | J6: phase4 | K6: phase1 | L6: phase2 | M6: phase1 | N6: phase2 | O6: phase3
B7: 機能要件 | C7: 画面 | D7: 共通 | E7: ログイン | F7: ・EntraID認証 | G7: 〇 | K7: 〇 | M7: 〇 | P7: 中 | Q7: =IFERROR(HLOOKUP(P7,AB$1:AF$2,2,FALSE),0) -> 5 | R7: =Q7*0.8 -> 4 | S7: =Q7*0.6 -> 3 | T7: =Q7*1.2 -> 6 | U7: =Q7*0.8 -> 4 | V7: =Q7*0.3 -> 1.5 | W7: =SUM(Q7:V7) -> 23.5 | X7: =ROUNDUP(W7/20,2) -> 1.18 | Y7: =Z7 -> 1180000 | Z7: =X7*1000000 -> 1180000
D8: 共通 | E8: ダッシュボード | F8: ・ログイン後に遷移する画面 ・各画面へ遷移する画面 | G8: 〇 | K8: 〇 | M8: 〇 | P8: 低 | Q8: =IFERROR(HLOOKUP(P8,AB$1:AF$2,2,FALSE),0) -> 3 | R8: =Q8*0.8 -> 2.4 | S8: =Q8*0.6 -> 1.8 | T8: =Q8*1.2 -> 3.6 | U8: =Q8*0.8 -> 2.4 | V8: =Q8*0.3 -> 0.9 | W8: =SUM(Q8:V8) -> 14.1 | X8: =ROUNDUP(W8/20,2) -> 0.71 | Y8: =Z8 -> 710000 | Z8: =X8*1000000 -> 710000
D9: 共通 | E9: 企業選択 | F9: ・新規取引先限度額申請の企業選択時に使用 ・親会社評価の親会社選択で使用 | I9: 〇 | L9: 〇 | N9: 〇 | P9: 中 | Q9: =IFERROR(HLOOKUP(P9,AB$1:AF$2,2,FALSE),0) -> 5 | R9: =Q9*0.8 -> 4 | S9: =Q9*0.6 -> 3 | T9: =Q9*1.2 -> 6 | U9: =Q9*0.8 -> 4 | V9: =Q9*0.3 -> 1.5 | W9: =SUM(Q9:V9) -> 23.5 | X9: =ROUNDUP(W9/20,2) -> 1.18 | Y9: =Z9 -> 1180000 | Z9: =X9*1000000 -> 1180000
D10: 共通 | E10: 所在地選択 | F10: ・国内取引先一覧の検索で使用するモーダル ・所在地の検索が可能 | G10: 〇 | K10: 〇 | M10: 〇 | P10: 低 | Q10: =IFERROR(HLOOKUP(P10,AB$1:AF$2,2,FALSE),0) -> 3 | R10: =Q10*0.8 -> 2.4 | S10: =Q10*0.6 -> 1.8 | T10: =Q10*1.2 -> 3.6 | U10: =Q10*0.8 -> 2.4 | V10: =Q10*0.3 -> 0.9 | W10: =SUM(Q10:V10) -> 14.1 | X10: =ROUNDUP(W10/20,2) -> 0.71 | Y10: =Z10 -> 710000 | Z10: =X10*1000000 -> 710000
D11: 共通 | E11: 業種選択 | F11: ・国内取引先一覧の検索で使用するモーダル ・業種の検索が可能 | G11: 〇 | K11: 〇 | M11: 〇 | P11: 低 | Q11: =IFERROR(HLOOKUP(P11,AB$1:AF$2,2,FALSE),0) -> 3 | R11: =Q11*0.8 -> 2.4 | S11: =Q11*0.6 -> 1.8 | T11: =Q11*1.2 -> 3.6 | U11: =Q11*0.8 -> 2.4 | V11: =Q11*0.3 -> 0.9 | W11: =SUM(Q11:V11) -> 14.1 | X11: =ROUNDUP(W11/20,2) -> 0.71 | Y11: =Z11 -> 710000 | Z11: =X11*1000000 -> 710000
D12: 共通 | E12: 品目選択 | F12: ・国内取引先一覧の検索で使用するモーダル ・品目の検索が可能 | G12: 〇 | K12: 〇 | M12: 〇 | P12: 低 | Q12: =IFERROR(HLOOKUP(P12,AB$1:AF$2,2,FALSE),0) -> 3 | R12: =Q12*0.8 -> 2.4 | S12: =Q12*0.6 -> 1.8 | T12: =Q12*1.2 -> 3.6 | U12: =Q12*0.8 -> 2.4 | V12: =Q12*0.3 -> 0.9 | W12: =SUM(Q12:V12) -> 14.1 | X12: =ROUNDUP(W12/20,2) -> 0.71 | Y12: =Z12 -> 710000 | Z12: =X12*1000000 -> 710000
A13: 追加 | D13: 共通 | E13: 取引先一覧へ表示 | F13: ・下記の画面で利用する画面 海外企業詳細 海外出光グループ購入済み企業一覧 国内企業詳細 国内出光グループ取得済み企業一覧 ※項目としては記載するが工数は上記の画面に含まれる | I13: 〇 | L13: 〇 | N13: 〇 | Z13: =X13*1000000 -> 0
D14: 検索 | E14: 海外企業情報検索 | F14: ・D&B APIを使用して海外企業検索をする画面 | H14: 〇 | K14: 〇 | N14: 〇 | P14: 中 | Q14: =IFERROR(HLOOKUP(P14,AB$1:AF$2,2,FALSE),0) -> 5 | R14: =Q14*0.8 -> 4 | S14: =Q14*0.6 -> 3 | T14: =Q14*1.2 -> 6 | U14: =Q14*0.8 -> 4 | V14: =Q14*0.3 -> 1.5 | W14: =SUM(Q14:V14) -> 23.5 | X14: =ROUNDUP(W14/20,2) -> 1.18 | Y14: =Z14 -> 1180000 | Z14: =X14*1000000 -> 1180000
D15: 検索 | E15: 海外出光グループ購入済み企業一覧 | F15: ・D&B APIを使用して購入した企業を検索する画面 ・取引先の設定ができる | H15: 〇 | K15: 〇 | N15: 〇 | P15: 中 | Q15: =IFERROR(HLOOKUP(P15,AB$1:AF$2,2,FALSE),0) -> 5 | R15: =Q15*0.8 -> 4 | S15: =Q15*0.6 -> 3 | T15: =Q15*1.2 -> 6 | U15: =Q15*0.8 -> 4 | V15: =Q15*0.3 -> 1.5 | W15: =SUM(Q15:V15) -> 23.5 | X15: =ROUNDUP(W15/20,2) -> 1.18 | Y15: =Z15 -> 1180000 | Z15: =X15*1000000 -> 1180000
D16: 検索 | E16: 海外企業詳細 | F16: ・海外企業情報を表示する画面 ・購入・未購入で表示できる範囲は異なる ・D&B APIで企業情報の購入ができる ・新規限度額申請をできる ・取引先の設定ができる ・モニタリング設定ができる | H16: 〇 | K16: 〇 | N16: 〇 | P16: 中 | Q16: =IFERROR(HLOOKUP(P16,AB$1:AF$2,2,FALSE),0) -> 5 | R16: =Q16*0.8 -> 4 | S16: =Q16*0.6 -> 3 | T16: =Q16*1.2 -> 6 | U16: =Q16*0.8 -> 4 | V16: =Q16*0.3 -> 1.5 | W16: =SUM(Q16:V16) -> 23.5 | X16: =ROUNDUP(W16/20,2) -> 1.18 | Y16: =Z16 -> 1180000 | Z16: =X16*1000000 -> 1180000
D17: 検索 | E17: 国内企業情報検索 | F17: ・TSR APIを使用して国内企業検索をする画面 | G17: 〇 | K17: 〇 | M17: 〇 | P17: 中 | Q17: =IFERROR(HLOOKUP(P17,AB$1:AF$2,2,FALSE),0) -> 5 | R17: =Q17*0.8 -> 4 | S17: =Q17*0.6 -> 3 | T17: =Q17*1.2 -> 6 | U17: =Q17*0.8 -> 4 | V17: =Q17*0.3 -> 1.5 | W17: =SUM(Q17:V17) -> 23.5 | X17: =ROUNDUP(W17/20,2) -> 1.18 | Y17: =Z17 -> 1180000 | Z17: =X17*1000000 -> 1180000
D18: 検索 | E18: 国内出光グループ取得済み企業一覧 | F18: ・TSR APIを使用して取得した企業を検索する画面 ・取引先の設定ができる | G18: 〇 | K18: 〇 | M18: 〇 | P18: 中 | Q18: =IFERROR(HLOOKUP(P18,AB$1:AF$2,2,FALSE),0) -> 5 | R18: =Q18*0.8 -> 4 | S18: =Q18*0.6 -> 3 | T18: =Q18*1.2 -> 6 | U18: =Q18*0.8 -> 4 | V18: =Q18*0.3 -> 1.5 | W18: =SUM(Q18:V18) -> 23.5 | X18: =ROUNDUP(W18/20,2) -> 1.18 | Y18: =Z18 -> 1180000 | Z18: =X18*1000000 -> 1180000
D19: 検索 | E19: 国内企業詳細 | F19: ・国内企業情報を表示する画面 ・新規限度額申請をできる ・TSR APIで企業情報の購入ができる ・取引先の設定ができる | G19: 〇 | K19: 〇 | M19: 〇 | P19: 中 | Q19: =IFERROR(HLOOKUP(P19,AB$1:AF$2,2,FALSE),0) -> 5 | R19: =Q19*0.8 -> 4 | S19: =Q19*0.6 -> 3 | T19: =Q19*1.2 -> 6 | U19: =Q19*0.8 -> 4 | V19: =Q19*0.3 -> 1.5 | W19: =SUM(Q19:V19) -> 23.5 | X19: =ROUNDUP(W19/20,2) -> 1.18 | Y19: =Z19 -> 1180000 | Z19: =X19*1000000 -> 1180000
D20: 表示 | E20: 海外取引先一覧 | F20: ・取引設定された海外企業を検索する画面 ・既存限度額申請をできる | I20: 〇 | L20: 〇 | N20: 〇 | P20: 中 | Q20: =IFERROR(HLOOKUP(P20,AB$1:AF$2,2,FALSE),0) -> 5 | R20: =Q20*0.8 -> 4 | S20: =Q20*0.6 -> 3 | T20: =Q20*1.2 -> 6 | U20: =Q20*0.8 -> 4 | V20: =Q20*0.3 -> 1.5 | W20: =SUM(Q20:V20) -> 23.5 | X20: =ROUNDUP(W20/20,2) -> 1.18 | Y20: =Z20 -> 1180000 | Z20: =X20*1000000 -> 1180000
D21: 表示 | E21: 国内取引先一覧 | F21: ・取引設定された国内企業を検索する画面 ・既存限度額申請をできる | I21: 〇 | L21: 〇 | N21: 〇 | P21: 中 | Q21: =IFERROR(HLOOKUP(P21,AB$1:AF$2,2,FALSE),0) -> 5 | R21: =Q21*0.8 -> 4 | S21: =Q21*0.6 -> 3 | T21: =Q21*1.2 -> 6 | U21: =Q21*0.8 -> 4 | V21: =Q21*0.3 -> 1.5 | W21: =SUM(Q21:V21) -> 23.5 | X21: =ROUNDUP(W21/20,2) -> 1.18 | Y21: =Z21 -> 1180000 | Z21: =X21*1000000 -> 1180000
A22: 変更 （金額変動あり） | D22: 申請 | E22: 新規取引先限度額申請 | F22: ・新規の限度額申請書を作成する画面 ・評価方法を選択して等級及び基準限度額を算出する | I22: 〇 | L22: 〇 | N22: 〇 | P22: 高 | Q22: =IFERROR(HLOOKUP(P22,AB$1:AF$2,2,FALSE),0) -> 7 | R22: =Q22*0.8 -> 5.6 | S22: =Q22*0.6 -> 4.2 | T22: =Q22*1.2 -> 8.4 | U22: =Q22*0.8 -> 5.6 | V22: =Q22*0.3 -> 2.1 | W22: =SUM(Q22:V22) -> 32.9 | X22: =ROUNDUP(W22/20,2) -> 1.65 | Y22: =Z22 -> 1650000 | Z22: =X22*1000000 -> 1650000
A23: 変更 (金額変動なし) | D23: 申請 | E23: 既存取引先限度額申請 | F23: <要件定義未実施> ・既存の限度額申請書を作成する画面 ・取引先一覧で選択した企業の限度額申請書を作成する ・評価方法を選択して等級及び基準限度額を再算出することも可能 | I23: 〇 | L23: 〇 | N23: 〇 | P23: 特高 | Q23: =IFERROR(HLOOKUP(P23,AB$1:AF$2,2,FALSE),0) -> 10 | R23: =Q23*0.8 -> 8 | S23: =Q23*0.6 -> 6 | T23: =Q23*1.2 -> 12 | U23: =Q23*0.8 -> 8 | V23: =Q23*0.3 -> 3 | W23: =SUM(Q23:V23) -> 47 | X23: =ROUNDUP(W23/20,2) -> 2.35 | Y23: =Z23 -> 2350000 | Z23: =X23*1000000 -> 2350000
A24: 追加 | D24: 申請 | E24: 取引先限度額申請一覧 | F24: ・取引先限度額申請を一覧で表示する。 ・現在の申請の状況を確認する。 | I24: 〇 | L24: 〇 | N24: 〇 | P24: 低 | Q24: =IFERROR(HLOOKUP(P24,AB$1:AF$2,2,FALSE),0) -> 3 | R24: =Q24*0.8 -> 2.4 | S24: =Q24*0.6 -> 1.8 | T24: =Q24*1.2 -> 3.6 | U24: =Q24*0.8 -> 2.4 | V24: =Q24*0.3 -> 0.9 | W24: =SUM(Q24:V24) -> 14.1 | X24: =ROUNDUP(W24/20,2) -> 0.71 | Y24: =Z24 -> 710000 | Z24: =X24*1000000 -> 710000
A25: 追加 | D25: 計算 | E25: Moody’s/S&P評価 | F25: ・取引先限度額申請時に「Moody’s/S&P評価」を入力する画面 | I25: 〇 | L25: 〇 | N25: 〇 | P25: 低 | Q25: =IFERROR(HLOOKUP(P25,AB$1:AF$2,2,FALSE),0) -> 3 | R25: =Q25*0.8 -> 2.4 | S25: =Q25*0.6 -> 1.8 | T25: =Q25*1.2 -> 3.6 | U25: =Q25*0.8 -> 2.4 | V25: =Q25*0.3 -> 0.9 | W25: =SUM(Q25:V25) -> 14.1 | X25: =ROUNDUP(W25/20,2) -> 0.71 | Y25: =Z25 -> 710000 | Z25: =X25*1000000 -> 710000
A26: 追加 | D26: 計算 | E26: TDB評価 | F26: ・取引先限度額申請時に「TDB情報」を入力する画面 | I26: 〇 | L26: 〇 | N26: 〇 | P26: 低 | Q26: =IFERROR(HLOOKUP(P26,AB$1:AF$2,2,FALSE),0) -> 3 | R26: =Q26*0.8 -> 2.4 | S26: =Q26*0.6 -> 1.8 | T26: =Q26*1.2 -> 3.6 | U26: =Q26*0.8 -> 2.4 | V26: =Q26*0.3 -> 0.9 | W26: =SUM(Q26:V26) -> 14.1 | X26: =ROUNDUP(W26/20,2) -> 0.71 | Y26: =Z26 -> 710000 | Z26: =X26*1000000 -> 710000
A27: 変更 （金額変動あり） | D27: 計算 | E27: 決算書分析 | F27: ・決算情報を入力して決算分析をする画面 ・算出結果は新規および既存取引先限度額申請で表示する | I27: 〇 | L27: 〇 | N27: 〇 | P27: 低 | Q27: =IFERROR(HLOOKUP(P27,AB$1:AF$2,2,FALSE),0) -> 3 | R27: =Q27*0.8 -> 2.4 | S27: =Q27*0.6 -> 1.8 | T27: =Q27*1.2 -> 3.6 | U27: =Q27*0.8 -> 2.4 | V27: =Q27*0.3 -> 0.9 | W27: =SUM(Q27:V27) -> 14.1 | X27: =ROUNDUP(W27/20,2) -> 0.71 | Y27: =Z27 -> 710000 | Z27: =X27*1000000 -> 710000
A28: 削減 | D28: 計算 | E28: リスク残額 | F28: <要件定義未実施> ・各企業の売掛金、倒産リスクからエクスポージャーを算出して表示する画面 ・部署や取引先、全社などドリルダウンしながら参照ができる ・前提条件としてSAPから売掛金情報を取得してグルーピングできること | J28: 〇 | L28: 〇 | O28: 〇 | P28: 特高 | Z28: =X28*1000000 -> 0
A29: 追加 | D29: 計算 | E29: 債権リスク一覧 | F29: ・SAPから取得した債権情報を事業部・課・取引先・国別に表示する画面。 ・対象は取引先一覧に評されている企業 | J29: 〇 | L29: 〇 | O29: 〇 | P29: 低 | Q29: =IFERROR(HLOOKUP(P29,AB$1:AF$2,2,FALSE),0) -> 3 | R29: =Q29*0.8 -> 2.4 | S29: =Q29*0.6 -> 1.8 | T29: =Q29*1.2 -> 3.6 | U29: =Q29*0.8 -> 2.4 | V29: =Q29*0.3 -> 0.9 | W29: =SUM(Q29:V29) -> 14.1 | X29: =ROUNDUP(W29/20,2) -> 0.71 | Y29: =Z29 -> 710000 | Z29: =X29*1000000 -> 710000
A30: 追加 | D30: 計算 | E30: 債権管理等級別リスク分析 | F30: ・SAPから取得した債権情報を債権等級別に表示する画面 ・対象は取引先一覧に評されている企業 | J30: 〇 | L30: 〇 | O30: 〇 | P30: 低 | Q30: =IFERROR(HLOOKUP(P30,AB$1:AF$2,2,FALSE),0) -> 3 | R30: =Q30*0.8 -> 2.4 | S30: =Q30*0.6 -> 1.8 | T30: =Q30*1.2 -> 3.6 | U30: =Q30*0.8 -> 2.4 | V30: =Q30*0.3 -> 0.9 | W30: =SUM(Q30:V30) -> 14.1 | X30: =ROUNDUP(W30/20,2) -> 0.71 | Y30: =Z30 -> 710000 | Z30: =X30*1000000 -> 710000
A31: 追加 | D31: 計算 | E31: 債権リスク推移 | F31: ・SAPから取得した債権情報をグラフで表示する画面 | J31: 〇 | L31: 〇 | O31: 〇 | P31: 中 | Q31: =IFERROR(HLOOKUP(P31,AB$1:AF$2,2,FALSE),0) -> 5 | R31: =Q31*0.8 -> 4 | S31: =Q31*0.6 -> 3 | T31: =Q31*1.2 -> 6 | U31: =Q31*0.8 -> 4 | V31: =Q31*0.3 -> 1.5 | W31: =SUM(Q31:V31) -> 23.5 | X31: =ROUNDUP(W31/20,2) -> 1.18 | Y31: =Z31 -> 1180000 | Z31: =X31*1000000 -> 1180000
A32: 削減 | D32: 計算 | E32: 売掛以外の債権 | F32: <要件定義未実施> ・売掛以外の債権を部署ごとなどで確認出来る画面 ・前提条件としてSAPから売掛以外の債権情報を取得できること | J32: 〇 | L32: 〇 | O32: 〇 | P32: 特高 | Z32: =X32*1000000 -> 0
A33: 削減 | D33: 共通 | E33: SAP情報アップロード | F33: <要件定義未実施> ・SAPからの情報を債権管理統合システムに取り込む画面 ※取込バッチになる可能性あり。 | J33: 〇 | L33: 〇 | O33: 〇 | P33: 特高 | Z33: =X33*1000000 -> 0
A34: 変更 (金額変動なし) | D34: 共通 | E34: 帝国データバンク企業情報 | F34: <要件定義未実施> ・帝国データバンクの情報をアップロードする画面 ※取込バッチになる可能性あり。 | I34: 〇 | L34: 〇 | N34: 〇 | P34: 低 | Q34: =IFERROR(HLOOKUP(P34,AB$1:AF$2,2,FALSE),0) -> 3 | R34: =Q34*0.8 -> 2.4 | S34: =Q34*0.6 -> 1.8 | T34: =Q34*1.2 -> 3.6 | U34: =Q34*0.8 -> 2.4 | V34: =Q34*0.3 -> 0.9 | W34: =SUM(Q34:V34) -> 14.1 | X34: =ROUNDUP(W34/20,2) -> 0.71 | Y34: =Z34 -> 710000 | Z34: =X34*1000000 -> 710000
A35: 変更 (金額変動なし) | D35: 共通 | E35: 為替 | F35: <要件定義未実施> ・為替情報をアップロードする画面 | I35: 〇 | L35: 〇 | N35: 〇 | P35: 低 | Q35: =IFERROR(HLOOKUP(P35,AB$1:AF$2,2,FALSE),0) -> 3 | R35: =Q35*0.8 -> 2.4 | S35: =Q35*0.6 -> 1.8 | T35: =Q35*1.2 -> 3.6 | U35: =Q35*0.8 -> 2.4 | V35: =Q35*0.3 -> 0.9 | W35: =SUM(Q35:V35) -> 14.1 | X35: =ROUNDUP(W35/20,2) -> 0.71 | Y35: =Z35 -> 710000 | Z35: =X35*1000000 -> 710000
A36: 変更 (金額変動なし) | D36: 共通 | E36: S&P , Moody's | F36: <要件定義未実施> ・S&P , Moody's情報を編集する画面 ・新規限度額申請で入力した情報を管理 | I36: 〇 | L36: 〇 | N36: 〇 | P36: 低 | Q36: =IFERROR(HLOOKUP(P36,AB$1:AF$2,2,FALSE),0) -> 3 | R36: =Q36*0.8 -> 2.4 | S36: =Q36*0.6 -> 1.8 | T36: =Q36*1.2 -> 3.6 | U36: =Q36*0.8 -> 2.4 | V36: =Q36*0.3 -> 0.9 | W36: =SUM(Q36:V36) -> 14.1 | X36: =ROUNDUP(W36/20,2) -> 0.71 | Y36: =Z36 -> 710000 | Z36: =X36*1000000 -> 710000
A37: 変更 (金額変動なし) | D37: 共通 | E37: S&Pソブリン格付け | F37: <要件定義未実施> ・S&Pソブリン格付け情報をアップロードする画面 | I37: 〇 | L37: 〇 | N37: 〇 | P37: 低 | Q37: =IFERROR(HLOOKUP(P37,AB$1:AF$2,2,FALSE),0) -> 3 | R37: =Q37*0.8 -> 2.4 | S37: =Q37*0.6 -> 1.8 | T37: =Q37*1.2 -> 3.6 | U37: =Q37*0.8 -> 2.4 | V37: =Q37*0.3 -> 0.9 | W37: =SUM(Q37:V37) -> 14.1 | X37: =ROUNDUP(W37/20,2) -> 0.71 | Y37: =Z37 -> 710000 | Z37: =X37*1000000 -> 710000
D38: 共通 | E38: 海外企業情報初期化 | F38: ・海外企業情報の初期化対象をアップロードする画面 ・アップロードした企業で初期化をいつ実施するかスケジュールすることができる | H38: 〇 | K38: 〇 | N38: 〇 | P38: 高 | Q38: =IFERROR(HLOOKUP(P38,AB$1:AF$2,2,FALSE),0) -> 7 | R38: =Q38*0.8 -> 5.6 | S38: =Q38*0.6 -> 4.2 | T38: =Q38*1.2 -> 8.4 | U38: =Q38*0.8 -> 5.6 | V38: =Q38*0.3 -> 2.1 | W38: =SUM(Q38:V38) -> 32.9 | X38: =ROUNDUP(W38/20,2) -> 1.65 | Y38: =Z38 -> 1650000 | Z38: =X38*1000000 -> 1650000
A39: 追加 | D39: 共通 | E39: 販売組織/利益センター/所属課管理 | F39: ・販売組織、利益センター、所属課をアップロードして管理する画面 ・アップロードした情報のマッピングを行う | I39: 〇 | L39: 〇 | N39: 〇 | P39: 中 | Q39: =IFERROR(HLOOKUP(P39,AB$1:AF$2,2,FALSE),0) -> 5 | R39: =Q39*0.8 -> 4 | S39: =Q39*0.6 -> 3 | T39: =Q39*1.2 -> 6 | U39: =Q39*0.8 -> 4 | V39: =Q39*0.3 -> 1.5 | W39: =SUM(Q39:V39) -> 23.5 | X39: =ROUNDUP(W39/20,2) -> 1.18 | Y39: =Z39 -> 1180000 | Z39: =X39*1000000 -> 1180000
A40: 追加 | D40: 共通 | E40: TSR納品情報管理 | F40: ・TSRから納品した企業情報、リスクスコア情報をアップロードする画面 ・アップロードした情報は「国内企業情報更新」バッチで使用 | I40: 〇 | L40: 〇 | N40: 〇 | P40: 低 | Q40: =IFERROR(HLOOKUP(P40,AB$1:AF$2,2,FALSE),0) -> 3 | R40: =Q40*0.8 -> 2.4 | S40: =Q40*0.6 -> 1.8 | T40: =Q40*1.2 -> 3.6 | U40: =Q40*0.8 -> 2.4 | V40: =Q40*0.3 -> 0.9 | W40: =SUM(Q40:V40) -> 14.1 | X40: =ROUNDUP(W40/20,2) -> 0.71 | Y40: =Z40 -> 710000 | Z40: =X40*1000000 -> 710000
C41: 帳票 | D41: 検索 | E41: 国内取得済企業一覧 | F41: ・国内出光グループ取得済み企業一覧で出力するCSV | G41: 〇 | K41: 〇 | M41: 〇 | P41: 低 | Q41: =IFERROR(HLOOKUP(P41,AB$1:AF$2,2,FALSE),0) -> 3 | R41: =Q41*0.8 -> 2.4 | S41: =Q41*0.6 -> 1.8 | T41: =Q41*1.2 -> 3.6 | U41: =Q41*0.8 -> 2.4 | V41: =Q41*0.3 -> 0.9 | W41: =SUM(Q41:V41) -> 14.1 | X41: =ROUNDUP(W41/20,2) -> 0.71 | Y41: =Z41 -> 710000 | Z41: =X41*1000000 -> 710000
D42: 検索 | E42: 海外購入済企業一覧 | F42: ・海外出光グループ購入済み企業一覧で出力するCSV ・海外企業情報初期化で使用する | H42: 〇 | K42: 〇 | N42: 〇 | P42: 低 | Q42: =IFERROR(HLOOKUP(P42,AB$1:AF$2,2,FALSE),0) -> 3 | R42: =Q42*0.8 -> 2.4 | S42: =Q42*0.6 -> 1.8 | T42: =Q42*1.2 -> 3.6 | U42: =Q42*0.8 -> 2.4 | V42: =Q42*0.3 -> 0.9 | W42: =SUM(Q42:V42) -> 14.1 | X42: =ROUNDUP(W42/20,2) -> 0.71 | Y42: =Z42 -> 710000 | Z42: =X42*1000000 -> 710000
D43: 検索 | E43: 国内企業情報 | F43: ・国内企業詳細で出力するPDF | G43: 〇 | K43: 〇 | M43: 〇 | P43: 中 | Q43: =IFERROR(HLOOKUP(P43,AB$1:AF$2,2,FALSE),0) -> 5 | R43: =Q43*0.8 -> 4 | S43: =Q43*0.6 -> 3 | T43: =Q43*1.2 -> 6 | U43: =Q43*0.8 -> 4 | V43: =Q43*0.3 -> 1.5 | W43: =SUM(Q43:V43) -> 23.5 | X43: =ROUNDUP(W43/20,2) -> 1.18 | Y43: =Z43 -> 1180000 | Z43: =X43*1000000 -> 1180000
D44: 検索 | E44: 海外企業情報 | F44: ・海外企業詳細で出力するPDF | H44: 〇 | K44: 〇 | N44: 〇 | P44: 中 | Q44: =IFERROR(HLOOKUP(P44,AB$1:AF$2,2,FALSE),0) -> 5 | R44: =Q44*0.8 -> 4 | S44: =Q44*0.6 -> 3 | T44: =Q44*1.2 -> 6 | U44: =Q44*0.8 -> 4 | V44: =Q44*0.3 -> 1.5 | W44: =SUM(Q44:V44) -> 23.5 | X44: =ROUNDUP(W44/20,2) -> 1.18 | Y44: =Z44 -> 1180000 | Z44: =X44*1000000 -> 1180000
D45: 表示 | E45: 国内取引先企業一覧 | F45: ・国内取引先一覧で出力するExcel | I45: 〇 | L45: 〇 | N45: 〇 | P45: 中 | Q45: =IFERROR(HLOOKUP(P45,AB$1:AF$2,2,FALSE),0) -> 5 | R45: =Q45*0.8 -> 4 | S45: =Q45*0.6 -> 3 | T45: =Q45*1.2 -> 6 | U45: =Q45*0.8 -> 4 | V45: =Q45*0.3 -> 1.5 | W45: =SUM(Q45:V45) -> 23.5 | X45: =ROUNDUP(W45/20,2) -> 1.18 | Y45: =Z45 -> 1180000 | Z45: =X45*1000000 -> 1180000
D46: 表示 | E46: 海外取引先企業一覧 | F46: ・海外取引先一覧で出力するExcel | I46: 〇 | L46: 〇 | N46: 〇 | P46: 中 | Q46: =IFERROR(HLOOKUP(P46,AB$1:AF$2,2,FALSE),0) -> 5 | R46: =Q46*0.8 -> 4 | S46: =Q46*0.6 -> 3 | T46: =Q46*1.2 -> 6 | U46: =Q46*0.8 -> 4 | V46: =Q46*0.3 -> 1.5 | W46: =SUM(Q46:V46) -> 23.5 | X46: =ROUNDUP(W46/20,2) -> 1.18 | Y46: =Z46 -> 1180000 | Z46: =X46*1000000 -> 1180000
D47: 申請・承認 | E47: 新規限度申請書 | F47: ・新規取引先限度額申請で出力するExcel ・出力したExcelは汎用WFで添付する | I47: 〇 | L47: 〇 | N47: 〇 | P47: 高 | Q47: =IFERROR(HLOOKUP(P47,AB$1:AF$2,2,FALSE),0) -> 7 | R47: =Q47*0.8 -> 5.6 | S47: =Q47*0.6 -> 4.2 | T47: =Q47*1.2 -> 8.4 | U47: =Q47*0.8 -> 5.6 | V47: =Q47*0.3 -> 2.1 | W47: =SUM(Q47:V47) -> 32.9 | X47: =ROUNDUP(W47/20,2) -> 1.65 | Y47: =Z47 -> 1650000 | Z47: =X47*1000000 -> 1650000
A48: 変更 (金額変動なし) | D48: 申請・承認 | E48: 既存限度申請書 | F48: <要件定義未実施> ・既存取引先限度額申請で出力するExcel ・出力したExcelは汎用WFで添付する | I48: 〇 | L48: 〇 | N48: 〇 | P48: 高 | Q48: =IFERROR(HLOOKUP(P48,AB$1:AF$2,2,FALSE),0) -> 7 | R48: =Q48*0.8 -> 5.6 | S48: =Q48*0.6 -> 4.2 | T48: =Q48*1.2 -> 8.4 | U48: =Q48*0.8 -> 5.6 | V48: =Q48*0.3 -> 2.1 | W48: =SUM(Q48:V48) -> 32.9 | X48: =ROUNDUP(W48/20,2) -> 1.65 | Y48: =Z48 -> 1650000 | Z48: =X48*1000000 -> 1650000
A49: 削減 | D49: 計算 | E49: 債権リスク分析 | F49: <要件定義未実施> ・リスク残額で出力するPDF | J49: 〇 | L49: 〇 | O49: 〇 | P49: 中 | Z49: =X49*1000000 -> 0
A50: 削減 | D50: 計算 | E50: 債権リスク分析 | F50: <要件定義未実施> ・リスク残額で出力するCSV | J50: 〇 | L50: 〇 | O50: 〇 | P50: 低 | Z50: =X50*1000000 -> 0
A51: 追加 | D51: 計算 | E51: 債権リスク一覧 | F51: ・債権リスク一覧に表示している内容をExcelに出力する ※リスク残額から分割 | J51: 〇 | L51: 〇 | O51: 〇 | P51: 低 | Q51: =IFERROR(HLOOKUP(P51,AB$1:AF$2,2,FALSE),0) -> 3 | R51: =Q51*0.8 -> 2.4 | S51: =Q51*0.6 -> 1.8 | T51: =Q51*1.2 -> 3.6 | U51: =Q51*0.8 -> 2.4 | V51: =Q51*0.3 -> 0.9 | W51: =SUM(Q51:V51) -> 14.1 | X51: =ROUNDUP(W51/20,2) -> 0.71 | Y51: =Z51 -> 710000 | Z51: =X51*1000000 -> 710000
A52: 追加 | D52: 計算 | E52: 債権管理等級別リスク分析 | F52: ・債権管理等級別リスク分析に表示している内容をExcelに出力する ※リスク残額から分割 | J52: 〇 | L52: 〇 | O52: 〇 | P52: 低 | Q52: =IFERROR(HLOOKUP(P52,AB$1:AF$2,2,FALSE),0) -> 3 | R52: =Q52*0.8 -> 2.4 | S52: =Q52*0.6 -> 1.8 | T52: =Q52*1.2 -> 3.6 | U52: =Q52*0.8 -> 2.4 | V52: =Q52*0.3 -> 0.9 | W52: =SUM(Q52:V52) -> 14.1 | X52: =ROUNDUP(W52/20,2) -> 0.71 | Y52: =Z52 -> 710000 | Z52: =X52*1000000 -> 710000
A53: 追加 | D53: 計算 | E53: 債権リスク推移 | F53: ・債権リスク推移に表示している内容をExcelに出力する ※グラフは対象外 ※リスク残額から分割 | J53: 〇 | L53: 〇 | O53: 〇 | P53: 低 | Q53: =IFERROR(HLOOKUP(P53,AB$1:AF$2,2,FALSE),0) -> 3 | R53: =Q53*0.8 -> 2.4 | S53: =Q53*0.6 -> 1.8 | T53: =Q53*1.2 -> 3.6 | U53: =Q53*0.8 -> 2.4 | V53: =Q53*0.3 -> 0.9 | W53: =SUM(Q53:V53) -> 14.1 | X53: =ROUNDUP(W53/20,2) -> 0.71 | Y53: =Z53 -> 710000 | Z53: =X53*1000000 -> 710000
C54: バッチ | D54: 共通 | E54: 海外企業情報更新 | F54: ・海外企業情報を日次で最新化するバッチ ・モニタリング対象の海外企業情報をD&B APIを使用して最新の情報を取得する | H54: 〇 | K54: 〇 | N54: 〇 | P54: 中 | Q54: =IFERROR(HLOOKUP(P54,AB$1:AF$2,2,FALSE),0) -> 5 | R54: =Q54*0.8 -> 4 | S54: =Q54*0.6 -> 3 | T54: =Q54*1.2 -> 6 | U54: =Q54*0.8 -> 4 | V54: =Q54*0.3 -> 1.5 | W54: =SUM(Q54:V54) -> 23.5 | X54: =ROUNDUP(W54/20,2) -> 1.18 | Y54: =Z54 -> 1180000 | Z54: =X54*1000000 -> 1180000
D55: 共通 | E55: 国内企業情報更新 | F55: ・国内企業情報を日次で最新化するバッチ ・対象の国内企業情報をTSR APIを使用して最新情報を取得する | G55: 〇 | K55: 〇 | M55: 〇 | P55: 中 | Q55: =IFERROR(HLOOKUP(P55,AB$1:AF$2,2,FALSE),0) -> 5 | R55: =Q55*0.8 -> 4 | S55: =Q55*0.6 -> 3 | T55: =Q55*1.2 -> 6 | U55: =Q55*0.8 -> 4 | V55: =Q55*0.3 -> 1.5 | W55: =SUM(Q55:V55) -> 23.5 | X55: =ROUNDUP(W55/20,2) -> 1.18 | Y55: =Z55 -> 1180000 | Z55: =X55*1000000 -> 1180000
D56: 共通 | E56: 海外企業購入情報初期化 | F56: ・海外企業情報初期化でスケジュールされた海外企業一覧でシステム内の購入情報を初期化するバッチ | H56: 〇 | K56: 〇 | N56: 〇 | P56: 中 | Q56: =IFERROR(HLOOKUP(P56,AB$1:AF$2,2,FALSE),0) -> 5 | R56: =Q56*0.8 -> 4 | S56: =Q56*0.6 -> 3 | T56: =Q56*1.2 -> 6 | U56: =Q56*0.8 -> 4 | V56: =Q56*0.3 -> 1.5 | W56: =SUM(Q56:V56) -> 23.5 | X56: =ROUNDUP(W56/20,2) -> 1.18 | Y56: =Z56 -> 1180000 | Z56: =X56*1000000 -> 1180000
A57: 追加 | D57: 共通 | E57: 海外企業購入情報初期化（リカバリ用） | F57: ・海外企業情報初期化リカバリ用のバッチ ・処理は海外企業情報初期化と合わせて行うため工数はなし | H57: 〇 | K57: 〇 | N57: 〇
A58: 変更 (金額変動なし) | D58: 計算 | E58: 等級算出 | F58: <要件定義未実施> ・毎月月初に最新の企業情報で等級を算出するバッチ | I58: 〇 | L58: 〇 | N58: 〇 | P58: 特高 | Q58: =IFERROR(HLOOKUP(P58,AB$1:AF$2,2,FALSE),0) -> 10 | R58: =Q58*0.8 -> 8 | S58: =Q58*0.6 -> 6 | T58: =Q58*1.2 -> 12 | U58: =Q58*0.8 -> 8 | V58: =Q58*0.3 -> 3 | W58: =SUM(Q58:V58) -> 47 | X58: =ROUNDUP(W58/20,2) -> 2.35 | Y58: =Z58 -> 2350000 | Z58: =X58*1000000 -> 2350000
A59: 変更 （金額変動あり） | D59: 申請・承認 | E59: Box監視 | F59: <要件定義未実施> ・汎用WFで出力されたExcelを監視するバッチ | I59: 〇 | L59: 〇 | N59: 〇 | P59: 高 | Q59: =IFERROR(HLOOKUP(P59,AB$1:AF$2,2,FALSE),0) -> 7 | R59: =Q59*0.8 -> 5.6 | S59: =Q59*0.6 -> 4.2 | T59: =Q59*1.2 -> 8.4 | U59: =Q59*0.8 -> 5.6 | V59: =Q59*0.3 -> 2.1 | W59: =SUM(Q59:V59) -> 32.9 | X59: =ROUNDUP(W59/20,2) -> 1.65 | Y59: =Z59 -> 1650000 | Z59: =X59*1000000 -> 1650000
A60: 追加 | D60: 計算 | E60: SAP得意先情報取込 | F60: ・SAPの得意先情報をBoxから取り込むバッチ | I60: 〇 | L60: 〇 | N60: 〇 | P60: 中 | Q60: =IFERROR(HLOOKUP(P60,AB$1:AF$2,2,FALSE),0) -> 5 | R60: =Q60*0.8 -> 4 | S60: =Q60*0.6 -> 3 | T60: =Q60*1.2 -> 6 | U60: =Q60*0.8 -> 4 | V60: =Q60*0.3 -> 1.5 | W60: =SUM(Q60:V60) -> 23.5 | X60: =ROUNDUP(W60/20,2) -> 1.18 | Y60: =Z60 -> 1180000 | Z60: =X60*1000000 -> 1180000
A61: 追加 | D61: 計算 | E61: SAP債権情報取込 | F61: ・SAPの債権情報をBoxから取り込むバッチ | J61: 〇 | L61: 〇 | O61: 〇 | P61: 中 | Q61: =IFERROR(HLOOKUP(P61,AB$1:AF$2,2,FALSE),0) -> 5 | R61: =Q61*0.8 -> 4 | S61: =Q61*0.6 -> 3 | T61: =Q61*1.2 -> 6 | U61: =Q61*0.8 -> 4 | V61: =Q61*0.3 -> 1.5 | W61: =SUM(Q61:V61) -> 23.5 | X61: =ROUNDUP(W61/20,2) -> 1.18 | Y61: =Z61 -> 1180000 | Z61: =X61*1000000 -> 1180000
B62: 非機能要件 | D62: 共通 | E62: データ移行(国内企業情報) | F62: 既存システムからのデータ移行 tsrvan2からのデータ登録 | G62: 〇 | K62: 〇 | M62: 〇 | P62: 低 | Q62: =IFERROR(HLOOKUP(P62,AB$1:AF$2,2,FALSE),0) -> 3 | R62: =Q62*0.8 -> 2.4 | S62: =Q62*0.6 -> 1.8 | T62: =Q62*1.2 -> 3.6 | U62: =Q62*0.8 -> 2.4 | V62: =Q62*0.3 -> 0.9 | W62: =SUM(Q62:V62) -> 14.1 | X62: =ROUNDUP(W62/20,2) -> 0.71 | Y62: =Z62 -> 710000 | Z62: =X62*1000000 -> 710000
D63: 共通 | E63: データ移行(海外企業情報) | F63: 既存システムからのデータ移行 MySQLからのデータ登録 | H63: 〇 | K63: 〇 | N63: 〇 | P63: 低 | Q63: =IFERROR(HLOOKUP(P63,AB$1:AF$2,2,FALSE),0) -> 3 | R63: =Q63*0.8 -> 2.4 | S63: =Q63*0.6 -> 1.8 | T63: =Q63*1.2 -> 3.6 | U63: =Q63*0.8 -> 2.4 | V63: =Q63*0.3 -> 0.9 | W63: =SUM(Q63:V63) -> 14.1 | X63: =ROUNDUP(W63/20,2) -> 0.71 | Y63: =Z63 -> 710000 | Z63: =X63*1000000 -> 710000
D64: 共通 | E64: データ移行(マクロ) | F64: 既存システムからのデータ移行 Excelからのデータ登録 | I64: 〇 | L64: 〇 | N64: 〇 | P64: 高 | Q64: =IFERROR(HLOOKUP(P64,AB$1:AF$2,2,FALSE),0) -> 7 | R64: =Q64*0.8 -> 5.6 | S64: =Q64*0.6 -> 4.2 | T64: =Q64*1.2 -> 8.4 | U64: =Q64*0.8 -> 5.6 | V64: =Q64*0.3 -> 2.1 | W64: =SUM(Q64:V64) -> 32.9 | X64: =ROUNDUP(W64/20,2) -> 1.65 | Y64: =Z64 -> 1650000 | Z64: =X64*1000000 -> 1650000
D65: 共通 | E65: システム構成 | F65: Azure環境の設定 運用設計 | G65: 〇 | K65: 〇 | M65: 〇 | P65: 特高 | Q65: =IFERROR(HLOOKUP(P65,AB$1:AF$2,2,FALSE),0) -> 10 | R65: =Q65*0.8 -> 8 | S65: =Q65*0.6 -> 6 | T65: =Q65*1.2 -> 12 | U65: =Q65*0.8 -> 8 | V65: =Q65*0.3 -> 3 | W65: =SUM(Q65:V65) -> 47 | X65: =ROUNDUP(W65/20,2) -> 2.35 | Y65: =Z65 -> 2350000 | Z65: =X65*1000000 -> 2350000
A66: 変更 (金額変動なし) | D66: 共通 | E66: 共通部品作成 | F66: Webアプリケーションの共通部品を作成 多言語対応 画面の解像度対応 | G66: 〇 | K66: 〇 | M66: 〇 | P66: 高 | Q66: =IFERROR(HLOOKUP(P66,AB$1:AF$2,2,FALSE),0) -> 7 | R66: =Q66*0.8 -> 5.6 | S66: =Q66*0.6 -> 4.2 | T66: =Q66*1.2 -> 8.4 | U66: =Q66*0.8 -> 5.6 | V66: =Q66*0.3 -> 2.1 | W66: =SUM(Q66:V66) -> 32.9 | X66: =ROUNDUP(W66/20,2) -> 1.65 | Y66: =Z66 -> 1650000 | Z66: =X66*1000000 -> 1650000
B67: 小計(人日) | P67: - | Q67: =SUM(Q6:Q66) -> 250 | R67: =SUM(R6:R66) -> 200 | S67: =SUM(S6:S66) -> 150 | T67: =SUM(T6:T66) -> 300 | U67: =SUM(U6:U66) -> 200 | V67: =SUM(V6:V66) -> 75 | W67: =SUM(Q67:V67) -> 1175
B68: 小計(人月) | P68: - | Q68: =Q67/20 -> 12.5 | R68: =R67/20 -> 10 | S68: =S67/20 -> 7.5 | T68: =T67/20 -> 15 | U68: =U67/20 -> 10 | V68: =V67/20 -> 3.75 | W68: =W67/20 -> 58.75 | X68: =SUM(X7:X66) -> 59
B69: 開発費用 | Y69: =SUM(Y7:Y66) -> 59000000
B70: 管理費用 | Y70: =X68*0.2*1400000 -> 16520000
B71: 初期流動(2か月) | Y71: 5400000
B72: 構築費用（管理費用+開発費用） | Y72: =Y69+Y70 -> 75520000
B73: 合計 | Y73: =Y71+Y72 -> 80920000

Sheet 工数見積り_20241022
A1: 【債権管理統合システム】詳細工数（2024/10/22） | AB1: 特高 | AC1: 高 | AD1: 中 | AE1: 低 | AF1: 特低
AB2: 10 | AC2: 7 | AD2: 5 | AE2: 3 | AF2: 2
B3: 大分類 | C3: 中分類 | D3: 小分類 | F3: 画面機能 作業内容 | G3: パターン | P3: 難易度 | Q3: 工程 | W3: 合計 （人日） | X3: 合計 （人月） | Y3: 合計 （金額）
Q4: 設計 | R4: 製造 | S4: 単体テスト | T4: 結合テスト | U4: 総合テスト | V4: 受入テスト支援
G5: 案② | K5: 案③ | M5: 案④
G6: phase1 | H6: phase2 | I6: phase3 | J6: phase4 | K6: phase1 | L6: phase2 | M6: phase1 | N6: phase2 | O6: phase3
B7: 機能要件 | C7: 画面 | D7: 共通 | E7: ログイン | F7: ・EntraID認証 | G7: 〇 | K7: 〇 | M7: 〇 | P7: 中 | Q7: =IFERROR(HLOOKUP(P7,AB$1:AF$2,2,FALSE),0) -> 5 | R7: =Q7*0.8 -> 4 | S7: =Q7*0.6 -> 3 | T7: =Q7*1.2 -> 6 | U7: =Q7*0.8 -> 4 | V7: =Q7*0.3 -> 1.5 | W7: =SUM(Q7:V7) -> 23.5 | X7: =ROUNDUP(W7/20,2) -> 1.18 | Y7: =Z7 -> 1180000 | Z7: =X7*1000000 -> 1180000
D8: 共通 | E8: ダッシュボード | F8: ・ログイン後に遷移する画面 ・各画面へ遷移する画面 | G8: 〇 | K8: 〇 | M8: 〇 | P8: 低 | Q8: =IFERROR(HLOOKUP(P8,AB$1:AF$2,2,FALSE),0) -> 3 | R8: =Q8*0.8 -> 2.4 | S8: =Q8*0.6 -> 1.8 | T8: =Q8*1.2 -> 3.6 | U8: =Q8*0.8 -> 2.4 | V8: =Q8*0.3 -> 0.9 | W8: =SUM(Q8:V8) -> 14.1 | X8: =ROUNDUP(W8/20,2) -> 0.71 | Y8: =Z8 -> 710000 | Z8: =X8*1000000 -> 710000
D9: 共通 | E9: 企業選択 | F9: ・新規取引先限度額申請の企業選択時に使用 ・親会社評価の親会社選択で使用 | I9: 〇 | L9: 〇 | N9: 〇 | P9: 中 | Q9: =IFERROR(HLOOKUP(P9,AB$1:AF$2,2,FALSE),0) -> 5 | R9: =Q9*0.8 -> 4 | S9: =Q9*0.6 -> 3 | T9: =Q9*1.2 -> 6 | U9: =Q9*0.8 -> 4 | V9: =Q9*0.3 -> 1.5 | W9: =SUM(Q9:V9) -> 23.5 | X9: =ROUNDUP(W9/20,2) -> 1.18 | Y9: =Z9 -> 1180000 | Z9: =X9*1000000 -> 1180000
D10: 共通 | E10: 所在地選択 | F10: ・国内取引先一覧の検索で使用するモーダル ・所在地の検索が可能 | G10: 〇 | K10: 〇 | M10: 〇 | P10: 低 | Q10: =IFERROR(HLOOKUP(P10,AB$1:AF$2,2,FALSE),0) -> 3 | R10: =Q10*0.8 -> 2.4 | S10: =Q10*0.6 -> 1.8 | T10: =Q10*1.2 -> 3.6 | U10: =Q10*0.8 -> 2.4 | V10: =Q10*0.3 -> 0.9 | W10: =SUM(Q10:V10) -> 14.1 | X10: =ROUNDUP(W10/20,2) -> 0.71 | Y10: =Z10 -> 710000 | Z10: =X10*1000000 -> 710000
D11: 共通 | E11: 業種選択 | F11: ・国内取引先一覧の検索で使用するモーダル ・業種の検索が可能 | G11: 〇 | K11: 〇 | M11: 〇 | P11: 低 | Q11: =IFERROR(HLOOKUP(P11,AB$1:AF$2,2,FALSE),0) -> 3 | R11: =Q11*0.8 -> 2.4 | S11: =Q11*0.6 -> 1.8 | T11: =Q11*1.2 -> 3.6 | U11: =Q11*0.8 -> 2.4 | V11: =Q11*0.3 -> 0.9 | W11: =SUM(Q11:V11) -> 14.1 | X11: =ROUNDUP(W11/20,2) -> 0.71 | Y11: =Z11 -> 710000 | Z11: =X11*1000000 -> 710000
D12: 共通 | E12: 品目選択 | F12: ・国内取引先一覧の検索で使用するモーダル ・品目の検索が可能 | G12: 〇 | K12: 〇 | M12: 〇 | P12: 低 | Q12: =IFERROR(HLOOKUP(P12,AB$1:AF$2,2,FALSE),0) -> 3 | R12: =Q12*0.8 -> 2.4 | S12: =Q12*0.6 -> 1.8 | T12: =Q12*1.2 -> 3.6 | U12: =Q12*0.8 -> 2.4 | V12: =Q12*0.3 -> 0.9 | W12: =SUM(Q12:V12) -> 14.1 | X12: =ROUNDUP(W12/20,2) -> 0.71 | Y12: =Z12 -> 710000 | Z12: =X12*1000000 -> 710000
D13: 検索 | E13: 海外企業情報検索 | F13: ・D&B APIを使用して海外企業検索をする画面 | H13: 〇 | K13: 〇 | N13: 〇 | P13: 中 | Q13: =IFERROR(HLOOKUP(P13,AB$1:AF$2,2,FALSE),0) -> 5 | R13: =Q13*0.8 -> 4 | S13: =Q13*0.6 -> 3 | T13: =Q13*1.2 -> 6 | U13: =Q13*0.8 -> 4 | V13: =Q13*0.3 -> 1.5 | W13: =SUM(Q13:V13) -> 23.5 | X13: =ROUNDUP(W13/20,2) -> 1.18 | Y13: =Z13 -> 1180000 | Z13: =X13*1000000 -> 1180000
D14: 検索 | E14: 海外出光グループ購入済み企業一覧 | F14: ・D&B APIを使用して購入した企業を検索する画面 ・取引先の設定ができる | H14: 〇 | K14: 〇 | N14: 〇 | P14: 中 | Q14: =IFERROR(HLOOKUP(P14,AB$1:AF$2,2,FALSE),0) -> 5 | R14: =Q14*0.8 -> 4 | S14: =Q14*0.6 -> 3 | T14: =Q14*1.2 -> 6 | U14: =Q14*0.8 -> 4 | V14: =Q14*0.3 -> 1.5 | W14: =SUM(Q14:V14) -> 23.5 | X14: =ROUNDUP(W14/20,2) -> 1.18 | Y14: =Z14 -> 1180000 | Z14: =X14*1000000 -> 1180000
D15: 検索 | E15: 海外企業詳細 | F15: ・海外企業情報を表示する画面 ・購入・未購入で表示できる範囲は異なる ・D&B APIで企業情報の購入ができる ・新規限度額申請をできる ・取引先の設定ができる ・モニタリング設定ができる | H15: 〇 | K15: 〇 | N15: 〇 | P15: 中 | Q15: =IFERROR(HLOOKUP(P15,AB$1:AF$2,2,FALSE),0) -> 5 | R15: =Q15*0.8 -> 4 | S15: =Q15*0.6 -> 3 | T15: =Q15*1.2 -> 6 | U15: =Q15*0.8 -> 4 | V15: =Q15*0.3 -> 1.5 | W15: =SUM(Q15:V15) -> 23.5 | X15: =ROUNDUP(W15/20,2) -> 1.18 | Y15: =Z15 -> 1180000 | Z15: =X15*1000000 -> 1180000
D16: 検索 | E16: 国内企業情報検索 | F16: ・TSR APIを使用して国内企業検索をする画面 | G16: 〇 | K16: 〇 | M16: 〇 | P16: 中 | Q16: =IFERROR(HLOOKUP(P16,AB$1:AF$2,2,FALSE),0) -> 5 | R16: =Q16*0.8 -> 4 | S16: =Q16*0.6 -> 3 | T16: =Q16*1.2 -> 6 | U16: =Q16*0.8 -> 4 | V16: =Q16*0.3 -> 1.5 | W16: =SUM(Q16:V16) -> 23.5 | X16: =ROUNDUP(W16/20,2) -> 1.18 | Y16: =Z16 -> 1180000 | Z16: =X16*1000000 -> 1180000
D17: 検索 | E17: 国内出光グループ取得済み企業一覧 | F17: ・TSR APIを使用して取得した企業を検索する画面 ・取引先の設定ができる | G17: 〇 | K17: 〇 | M17: 〇 | P17: 中 | Q17: =IFERROR(HLOOKUP(P17,AB$1:AF$2,2,FALSE),0) -> 5 | R17: =Q17*0.8 -> 4 | S17: =Q17*0.6 -> 3 | T17: =Q17*1.2 -> 6 | U17: =Q17*0.8 -> 4 | V17: =Q17*0.3 -> 1.5 | W17: =SUM(Q17:V17) -> 23.5 | X17: =ROUNDUP(W17/20,2) -> 1.18 | Y17: =Z17 -> 1180000 | Z17: =X17*1000000 -> 1180000
D18: 検索 | E18: 国内企業詳細 | F18: ・国内企業情報を表示する画面 ・新規限度額申請をできる ・TSR APIで企業情報の購入ができる ・取引先の設定ができる | G18: 〇 | K18: 〇 | M18: 〇 | P18: 中 | Q18: =IFERROR(HLOOKUP(P18,AB$1:AF$2,2,FALSE),0) -> 5 | R18: =Q18*0.8 -> 4 | S18: =Q18*0.6 -> 3 | T18: =Q18*1.2 -> 6 | U18: =Q18*0.8 -> 4 | V18: =Q18*0.3 -> 1.5 | W18: =SUM(Q18:V18) -> 23.5 | X18: =ROUNDUP(W18/20,2) -> 1.18 | Y18: =Z18 -> 1180000 | Z18: =X18*1000000 -> 1180000
D19: 表示 | E19: 海外取引先一覧 | F19: ・取引設定された海外企業を検索する画面 ・既存限度額申請をできる | I19: 〇 | L19: 〇 | N19: 〇 | P19: 中 | Q19: =IFERROR(HLOOKUP(P19,AB$1:AF$2,2,FALSE),0) -> 5 | R19: =Q19*0.8 -> 4 | S19: =Q19*0.6 -> 3 | T19: =Q19*1.2 -> 6 | U19: =Q19*0.8 -> 4 | V19: =Q19*0.3 -> 1.5 | W19: =SUM(Q19:V19) -> 23.5 | X19: =ROUNDUP(W19/20,2) -> 1.18 | Y19: =Z19 -> 1180000 | Z19: =X19*1000000 -> 1180000
D20: 表示 | E20: 国内取引先一覧 | F20: ・取引設定された国内企業を検索する画面 ・既存限度額申請をできる | I20: 〇 | L20: 〇 | N20: 〇 | P20: 中 | Q20: =IFERROR(HLOOKUP(P20,AB$1:AF$2,2,FALSE),0) -> 5 | R20: =Q20*0.8 -> 4 | S20: =Q20*0.6 -> 3 | T20: =Q20*1.2 -> 6 | U20: =Q20*0.8 -> 4 | V20: =Q20*0.3 -> 1.5 | W20: =SUM(Q20:V20) -> 23.5 | X20: =ROUNDUP(W20/20,2) -> 1.18 | Y20: =Z20 -> 1180000 | Z20: =X20*1000000 -> 1180000
D21: 申請 | E21: 新規取引先限度額申請 | F21: ・新規の限度額申請書を作成する画面 ・評価方法を選択して等級及び基準限度額を算出する | I21: 〇 | L21: 〇 | N21: 〇 | P21: 特高 | Q21: =IFERROR(HLOOKUP(P21,AB$1:AF$2,2,FALSE),0) -> 10 | R21: =Q21*0.8 -> 8 | S21: =Q21*0.6 -> 6 | T21: =Q21*1.2 -> 12 | U21: =Q21*0.8 -> 8 | V21: =Q21*0.3 -> 3 | W21: =SUM(Q21:V21) -> 47 | X21: =ROUNDUP(W21/20,2) -> 2.35 | Y21: =Z21 -> 2350000 | Z21: =X21*1000000 -> 2350000
D22: 申請 | E22: 既存取引先限度額申請 | F22: <要件定義未実施> ・既存の限度額申請書を作成する画面 ・取引先一覧で選択した企業の限度額申請書を作成する ・評価方法を選択して等級及び基準限度額を再算出することも可能 | I22: 〇 | L22: 〇 | N22: 〇 | P22: 特高 | Q22: =IFERROR(HLOOKUP(P22,AB$1:AF$2,2,FALSE),0) -> 10 | R22: =Q22*0.8 -> 8 | S22: =Q22*0.6 -> 6 | T22: =Q22*1.2 -> 12 | U22: =Q22*0.8 -> 8 | V22: =Q22*0.3 -> 3 | W22: =SUM(Q22:V22) -> 47 | X22: =ROUNDUP(W22/20,2) -> 2.35 | Y22: =Z22 -> 2350000 | Z22: =X22*1000000 -> 2350000
D23: 計算 | E23: 決算書分析 | F23: ・決算情報を入力して決算分析をする画面 ・算出結果は新規および既存取引先限度額申請で表示する | I23: 〇 | L23: 〇 | N23: 〇 | P23: 高 | Q23: =IFERROR(HLOOKUP(P23,AB$1:AF$2,2,FALSE),0) -> 7 | R23: =Q23*0.8 -> 5.6 | S23: =Q23*0.6 -> 4.2 | T23: =Q23*1.2 -> 8.4 | U23: =Q23*0.8 -> 5.6 | V23: =Q23*0.3 -> 2.1 | W23: =SUM(Q23:V23) -> 32.9 | X23: =ROUNDUP(W23/20,2) -> 1.65 | Y23: =Z23 -> 1650000 | Z23: =X23*1000000 -> 1650000
D24: 計算 | E24: リスク残額 | F24: <要件定義未実施> ・各企業の売掛金、倒産リスクからエクスポージャーを算出して表示する画面 ・部署や取引先、全社などドリルダウンしながら参照ができる ・前提条件としてSAPから売掛金情報を取得してグルーピングできること | J24: 〇 | L24: 〇 | O24: 〇 | P24: 特高 | Q24: =IFERROR(HLOOKUP(P24,AB$1:AF$2,2,FALSE),0) -> 10 | R24: =Q24*0.8 -> 8 | S24: =Q24*0.6 -> 6 | T24: =Q24*1.2 -> 12 | U24: =Q24*0.8 -> 8 | V24: =Q24*0.3 -> 3 | W24: =SUM(Q24:V24) -> 47 | X24: =ROUNDUP(W24/20,2) -> 2.35 | Y24: =Z24 -> 2350000 | Z24: =X24*1000000 -> 2350000
D25: 計算 | E25: 売掛以外の債権 | F25: <要件定義未実施> ・売掛以外の債権を部署ごとなどで確認出来る画面 ・前提条件としてSAPから売掛以外の債権情報を取得できること | J25: 〇 | L25: 〇 | O25: 〇 | P25: 高 | Q25: =IFERROR(HLOOKUP(P25,AB$1:AF$2,2,FALSE),0) -> 7 | R25: =Q25*0.8 -> 5.6 | S25: =Q25*0.6 -> 4.2 | T25: =Q25*1.2 -> 8.4 | U25: =Q25*0.8 -> 5.6 | V25: =Q25*0.3 -> 2.1 | W25: =SUM(Q25:V25) -> 32.9 | X25: =ROUNDUP(W25/20,2) -> 1.65 | Y25: =Z25 -> 1650000 | Z25: =X25*1000000 -> 1650000
D26: 共通 | E26: SAP情報アップロード | F26: <要件定義未実施> ・SAPからの情報を債権管理統合システムに取り込む画面 ※取込バッチになる可能性あり。 | J26: 〇 | L26: 〇 | O26: 〇 | P26: 特高 | Q26: =IFERROR(HLOOKUP(P26,AB$1:AF$2,2,FALSE),0) -> 10 | R26: =Q26*0.8 -> 8 | S26: =Q26*0.6 -> 6 | T26: =Q26*1.2 -> 12 | U26: =Q26*0.8 -> 8 | V26: =Q26*0.3 -> 3 | W26: =SUM(Q26:V26) -> 47 | X26: =ROUNDUP(W26/20,2) -> 2.35 | Y26: =Z26 -> 2350000 | Z26: =X26*1000000 -> 2350000
D27: 共通 | E27: 帝国データバンク企業情報 | F27: <要件定義未実施> ・帝国データバンクの情報をアップロードする画面 ※取込バッチになる可能性あり。 | I27: 〇 | L27: 〇 | N27: 〇 | P27: 低 | Q27: =IFERROR(HLOOKUP(P27,AB$1:AF$2,2,FALSE),0) -> 3 | R27: =Q27*0.8 -> 2.4 | S27: =Q27*0.6 -> 1.8 | T27: =Q27*1.2 -> 3.6 | U27: =Q27*0.8 -> 2.4 | V27: =Q27*0.3 -> 0.9 | W27: =SUM(Q27:V27) -> 14.1 | X27: =ROUNDUP(W27/20,2) -> 0.71 | Y27: =Z27 -> 710000 | Z27: =X27*1000000 -> 710000
D28: 共通 | E28: 為替 | F28: <要件定義未実施> ・為替情報をアップロードする画面 | I28: 〇 | L28: 〇 | N28: 〇 | P28: 低 | Q28: =IFERROR(HLOOKUP(P28,AB$1:AF$2,2,FALSE),0) -> 3 | R28: =Q28*0.8 -> 2.4 | S28: =Q28*0.6 -> 1.8 | T28: =Q28*1.2 -> 3.6 | U28: =Q28*0.8 -> 2.4 | V28: =Q28*0.3 -> 0.9 | W28: =SUM(Q28:V28) -> 14.1 | X28: =ROUNDUP(W28/20,2) -> 0.71 | Y28: =Z28 -> 710000 | Z28: =X28*1000000 -> 710000
D29: 共通 | E29: S&P , Moody's | F29: <要件定義未実施> ・S&P , Moody's情報を編集する画面 ・新規限度額申請で入力した情報を管理 | I29: 〇 | L29: 〇 | N29: 〇 | P29: 低 | Q29: =IFERROR(HLOOKUP(P29,AB$1:AF$2,2,FALSE),0) -> 3 | R29: =Q29*0.8 -> 2.4 | S29: =Q29*0.6 -> 1.8 | T29: =Q29*1.2 -> 3.6 | U29: =Q29*0.8 -> 2.4 | V29: =Q29*0.3 -> 0.9 | W29: =SUM(Q29:V29) -> 14.1 | X29: =ROUNDUP(W29/20,2) -> 0.71 | Y29: =Z29 -> 710000 | Z29: =X29*1000000 -> 710000
D30: 共通 | E30: S&Pソブリン格付け | F30: <要件定義未実施> ・S&Pソブリン格付け情報をアップロードする画面 | I30: 〇 | L30: 〇 | N30: 〇 | P30: 低 | Q30: =IFERROR(HLOOKUP(P30,AB$1:AF$2,2,FALSE),0) -> 3 | R30: =Q30*0.8 -> 2.4 | S30: =Q30*0.6 -> 1.8 | T30: =Q30*1.2 -> 3.6 | U30: =Q30*0.8 -> 2.4 | V30: =Q30*0.3 -> 0.9 | W30: =SUM(Q30:V30) -> 14.1 | X30: =ROUNDUP(W30/20,2) -> 0.71 | Y30: =Z30 -> 710000 | Z30: =X30*1000000 -> 710000
D31: 共通 | E31: 海外企業情報初期化 | F31: ・海外企業情報の初期化対象をアップロードする画面 ・アップロードした企業で初期化をいつ実施するかスケジュールすることができる | H31: 〇 | K31: 〇 | N31: 〇 | P31: 高 | Q31: =IFERROR(HLOOKUP(P31,AB$1:AF$2,2,FALSE),0) -> 7 | R31: =Q31*0.8 -> 5.6 | S31: =Q31*0.6 -> 4.2 | T31: =Q31*1.2 -> 8.4 | U31: =Q31*0.8 -> 5.6 | V31: =Q31*0.3 -> 2.1 | W31: =SUM(Q31:V31) -> 32.9 | X31: =ROUNDUP(W31/20,2) -> 1.65 | Y31: =Z31 -> 1650000 | Z31: =X31*1000000 -> 1650000
C32: 帳票 | D32: 検索 | E32: 国内取得済企業一覧 | F32: ・国内出光グループ取得済み企業一覧で出力するCSV | G32: 〇 | K32: 〇 | M32: 〇 | P32: 低 | Q32: =IFERROR(HLOOKUP(P32,AB$1:AF$2,2,FALSE),0) -> 3 | R32: =Q32*0.8 -> 2.4 | S32: =Q32*0.6 -> 1.8 | T32: =Q32*1.2 -> 3.6 | U32: =Q32*0.8 -> 2.4 | V32: =Q32*0.3 -> 0.9 | W32: =SUM(Q32:V32) -> 14.1 | X32: =ROUNDUP(W32/20,2) -> 0.71 | Y32: =Z32 -> 710000 | Z32: =X32*1000000 -> 710000
D33: 検索 | E33: 海外購入済企業一覧 | F33: ・海外出光グループ購入済み企業一覧で出力するCSV ・海外企業情報初期化で使用する | H33: 〇 | K33: 〇 | N33: 〇 | P33: 低 | Q33: =IFERROR(HLOOKUP(P33,AB$1:AF$2,2,FALSE),0) -> 3 | R33: =Q33*0.8 -> 2.4 | S33: =Q33*0.6 -> 1.8 | T33: =Q33*1.2 -> 3.6 | U33: =Q33*0.8 -> 2.4 | V33: =Q33*0.3 -> 0.9 | W33: =SUM(Q33:V33) -> 14.1 | X33: =ROUNDUP(W33/20,2) -> 0.71 | Y33: =Z33 -> 710000 | Z33: =X33*1000000 -> 710000
D34: 検索 | E34: 国内企業情報 | F34: ・国内企業詳細で出力するPDF | G34: 〇 | K34: 〇 | M34: 〇 | P34: 中 | Q34: =IFERROR(HLOOKUP(P34,AB$1:AF$2,2,FALSE),0) -> 5 | R34: =Q34*0.8 -> 4 | S34: =Q34*0.6 -> 3 | T34: =Q34*1.2 -> 6 | U34: =Q34*0.8 -> 4 | V34: =Q34*0.3 -> 1.5 | W34: =SUM(Q34:V34) -> 23.5 | X34: =ROUNDUP(W34/20,2) -> 1.18 | Y34: =Z34 -> 1180000 | Z34: =X34*1000000 -> 1180000
D35: 検索 | E35: 海外企業情報 | F35: ・海外企業詳細で出力するPDF | H35: 〇 | K35: 〇 | N35: 〇 | P35: 中 | Q35: =IFERROR(HLOOKUP(P35,AB$1:AF$2,2,FALSE),0) -> 5 | R35: =Q35*0.8 -> 4 | S35: =Q35*0.6 -> 3 | T35: =Q35*1.2 -> 6 | U35: =Q35*0.8 -> 4 | V35: =Q35*0.3 -> 1.5 | W35: =SUM(Q35:V35) -> 23.5 | X35: =ROUNDUP(W35/20,2) -> 1.18 | Y35: =Z35 -> 1180000 | Z35: =X35*1000000 -> 1180000
D36: 表示 | E36: 国内取引先企業一覧 | F36: ・国内取引先一覧で出力するExcel | I36: 〇 | L36: 〇 | N36: 〇 | P36: 中 | Q36: =IFERROR(HLOOKUP(P36,AB$1:AF$2,2,FALSE),0) -> 5 | R36: =Q36*0.8 -> 4 | S36: =Q36*0.6 -> 3 | T36: =Q36*1.2 -> 6 | U36: =Q36*0.8 -> 4 | V36: =Q36*0.3 -> 1.5 | W36: =SUM(Q36:V36) -> 23.5 | X36: =ROUNDUP(W36/20,2) -> 1.18 | Y36: =Z36 -> 1180000 | Z36: =X36*1000000 -> 1180000
D37: 表示 | E37: 海外取引先企業一覧 | F37: ・海外取引先一覧で出力するExcel | I37: 〇 | L37: 〇 | N37: 〇 | P37: 中 | Q37: =IFERROR(HLOOKUP(P37,AB$1:AF$2,2,FALSE),0) -> 5 | R37: =Q37*0.8 -> 4 | S37: =Q37*0.6 -> 3 | T37: =Q37*1.2 -> 6 | U37: =Q37*0.8 -> 4 | V37: =Q37*0.3 -> 1.5 | W37: =SUM(Q37:V37) -> 23.5 | X37: =ROUNDUP(W37/20,2) -> 1.18 | Y37: =Z37 -> 1180000 | Z37: =X37*1000000 -> 1180000
D38: 申請・承認 | E38: 新規限度申請書 | F38: ・新規取引先限度額申請で出力するExcel ・出力したExcelは汎用WFで添付する | I38: 〇 | L38: 〇 | N38: 〇 | P38: 高 | Q38: =IFERROR(HLOOKUP(P38,AB$1:AF$2,2,FALSE),0) -> 7 | R38: =Q38*0.8 -> 5.6 | S38: =Q38*0.6 -> 4.2 | T38: =Q38*1.2 -> 8.4 | U38: =Q38*0.8 -> 5.6 | V38: =Q38*0.3 -> 2.1 | W38: =SUM(Q38:V38) -> 32.9 | X38: =ROUNDUP(W38/20,2) -> 1.65 | Y38: =Z38 -> 1650000 | Z38: =X38*1000000 -> 1650000
D39: 申請・承認 | E39: 既存限度申請書 | F39: <要件定義未実施> ・既存取引先限度額申請で出力するExcel ・出力したExcelは汎用WFで添付する | I39: 〇 | L39: 〇 | N39: 〇 | P39: 高 | Q39: =IFERROR(HLOOKUP(P39,AB$1:AF$2,2,FALSE),0) -> 7 | R39: =Q39*0.8 -> 5.6 | S39: =Q39*0.6 -> 4.2 | T39: =Q39*1.2 -> 8.4 | U39: =Q39*0.8 -> 5.6 | V39: =Q39*0.3 -> 2.1 | W39: =SUM(Q39:V39) -> 32.9 | X39: =ROUNDUP(W39/20,2) -> 1.65 | Y39: =Z39 -> 1650000 | Z39: =X39*1000000 -> 1650000
D40: 計算 | E40: 債権リスク分析 | F40: <要件定義未実施> ・リスク残額で出力するPDF | J40: 〇 | L40: 〇 | O40: 〇 | P40: 中 | Q40: =IFERROR(HLOOKUP(P40,AB$1:AF$2,2,FALSE),0) -> 5 | R40: =Q40*0.8 -> 4 | S40: =Q40*0.6 -> 3 | T40: =Q40*1.2 -> 6 | U40: =Q40*0.8 -> 4 | V40: =Q40*0.3 -> 1.5 | W40: =SUM(Q40:V40) -> 23.5 | X40: =ROUNDUP(W40/20,2) -> 1.18 | Y40: =Z40 -> 1180000 | Z40: =X40*1000000 -> 1180000
D41: 計算 | E41: 債権リスク分析 | F41: <要件定義未実施> ・リスク残額で出力するCSV | J41: 〇 | L41: 〇 | O41: 〇 | P41: 低 | Q41: =IFERROR(HLOOKUP(P41,AB$1:AF$2,2,FALSE),0) -> 3 | R41: =Q41*0.8 -> 2.4 | S41: =Q41*0.6 -> 1.8 | T41: =Q41*1.2 -> 3.6 | U41: =Q41*0.8 -> 2.4 | V41: =Q41*0.3 -> 0.9 | W41: =SUM(Q41:V41) -> 14.1 | X41: =ROUNDUP(W41/20,2) -> 0.71 | Y41: =Z41 -> 710000 | Z41: =X41*1000000 -> 710000
C42: バッチ | D42: 共通 | E42: 海外企業情報更新 | F42: ・海外企業情報を日次で最新化するバッチ ・モニタリング対象の海外企業情報をD&B APIを使用して最新の情報を取得する | H42: 〇 | K42: 〇 | N42: 〇 | P42: 中 | Q42: =IFERROR(HLOOKUP(P42,AB$1:AF$2,2,FALSE),0) -> 5 | R42: =Q42*0.8 -> 4 | S42: =Q42*0.6 -> 3 | T42: =Q42*1.2 -> 6 | U42: =Q42*0.8 -> 4 | V42: =Q42*0.3 -> 1.5 | W42: =SUM(Q42:V42) -> 23.5 | X42: =ROUNDUP(W42/20,2) -> 1.18 | Y42: =Z42 -> 1180000 | Z42: =X42*1000000 -> 1180000
D43: 共通 | E43: 国内企業情報更新 | F43: ・国内企業情報を日次で最新化するバッチ ・対象の国内企業情報をTSR APIを使用して最新情報を取得する | G43: 〇 | K43: 〇 | M43: 〇 | P43: 中 | Q43: =IFERROR(HLOOKUP(P43,AB$1:AF$2,2,FALSE),0) -> 5 | R43: =Q43*0.8 -> 4 | S43: =Q43*0.6 -> 3 | T43: =Q43*1.2 -> 6 | U43: =Q43*0.8 -> 4 | V43: =Q43*0.3 -> 1.5 | W43: =SUM(Q43:V43) -> 23.5 | X43: =ROUNDUP(W43/20,2) -> 1.18 | Y43: =Z43 -> 1180000 | Z43: =X43*1000000 -> 1180000
D44: 共通 | E44: 海外企業購入情報初期化 | F44: ・海外企業情報初期化でスケジュールされた海外企業一覧でシステム内の購入情報を初期化するバッチ | H44: 〇 | K44: 〇 | N44: 〇 | P44: 中 | Q44: =IFERROR(HLOOKUP(P44,AB$1:AF$2,2,FALSE),0) -> 5 | R44: =Q44*0.8 -> 4 | S44: =Q44*0.6 -> 3 | T44: =Q44*1.2 -> 6 | U44: =Q44*0.8 -> 4 | V44: =Q44*0.3 -> 1.5 | W44: =SUM(Q44:V44) -> 23.5 | X44: =ROUNDUP(W44/20,2) -> 1.18 | Y44: =Z44 -> 1180000 | Z44: =X44*1000000 -> 1180000
D45: 計算 | E45: 等級算出 | F45: <要件定義未実施> ・毎月月初に最新の企業情報で等級を算出するバッチ | I45: 〇 | L45: 〇 | N45: 〇 | P45: 特高 | Q45: =IFERROR(HLOOKUP(P45,AB$1:AF$2,2,FALSE),0) -> 10 | R45: =Q45*0.8 -> 8 | S45: =Q45*0.6 -> 6 | T45: =Q45*1.2 -> 12 | U45: =Q45*0.8 -> 8 | V45: =Q45*0.3 -> 3 | W45: =SUM(Q45:V45) -> 47 | X45: =ROUNDUP(W45/20,2) -> 2.35 | Y45: =Z45 -> 2350000 | Z45: =X45*1000000 -> 2350000
D46: 申請・承認 | E46: Box監視 | F46: <要件定義未実施> ・汎用WFで出力されたExcelを監視するバッチ | I46: 〇 | L46: 〇 | N46: 〇 | P46: 特高 | Q46: =IFERROR(HLOOKUP(P46,AB$1:AF$2,2,FALSE),0) -> 10 | R46: =Q46*0.8 -> 8 | S46: =Q46*0.6 -> 6 | T46: =Q46*1.2 -> 12 | U46: =Q46*0.8 -> 8 | V46: =Q46*0.3 -> 3 | W46: =SUM(Q46:V46) -> 47 | X46: =ROUNDUP(W46/20,2) -> 2.35 | Y46: =Z46 -> 2350000 | Z46: =X46*1000000 -> 2350000
B47: 非機能要件 | D47: 共通 | E47: データ移行(国内企業情報) | F47: 既存システムからのデータ移行 tsrvan2からのデータ登録 | G47: 〇 | K47: 〇 | M47: 〇 | P47: 低 | Q47: =IFERROR(HLOOKUP(P47,AB$1:AF$2,2,FALSE),0) -> 3 | R47: =Q47*0.8 -> 2.4 | S47: =Q47*0.6 -> 1.8 | T47: =Q47*1.2 -> 3.6 | U47: =Q47*0.8 -> 2.4 | V47: =Q47*0.3 -> 0.9 | W47: =SUM(Q47:V47) -> 14.1 | X47: =ROUNDUP(W47/20,2) -> 0.71 | Y47: =Z47 -> 710000 | Z47: =X47*1000000 -> 710000
D48: 共通 | E48: データ移行(海外企業情報) | F48: 既存システムからのデータ移行 MySQLからのデータ登録 | H48: 〇 | K48: 〇 | N48: 〇 | P48: 低 | Q48: =IFERROR(HLOOKUP(P48,AB$1:AF$2,2,FALSE),0) -> 3 | R48: =Q48*0.8 -> 2.4 | S48: =Q48*0.6 -> 1.8 | T48: =Q48*1.2 -> 3.6 | U48: =Q48*0.8 -> 2.4 | V48: =Q48*0.3 -> 0.9 | W48: =SUM(Q48:V48) -> 14.1 | X48: =ROUNDUP(W48/20,2) -> 0.71 | Y48: =Z48 -> 710000 | Z48: =X48*1000000 -> 710000
D49: 共通 | E49: データ移行(マクロ) | F49: 既存システムからのデータ移行 Excelからのデータ登録 | I49: 〇 | L49: 〇 | N49: 〇 | P49: 高 | Q49: =IFERROR(HLOOKUP(P49,AB$1:AF$2,2,FALSE),0) -> 7 | R49: =Q49*0.8 -> 5.6 | S49: =Q49*0.6 -> 4.2 | T49: =Q49*1.2 -> 8.4 | U49: =Q49*0.8 -> 5.6 | V49: =Q49*0.3 -> 2.1 | W49: =SUM(Q49:V49) -> 32.9 | X49: =ROUNDUP(W49/20,2) -> 1.65 | Y49: =Z49 -> 1650000 | Z49: =X49*1000000 -> 1650000
D50: 共通 | E50: システム構成 | F50: Azure環境の設定 運用設計 | G50: 〇 | K50: 〇 | M50: 〇 | P50: 特高 | Q50: =IFERROR(HLOOKUP(P50,AB$1:AF$2,2,FALSE),0) -> 10 | R50: =Q50*0.8 -> 8 | S50: =Q50*0.6 -> 6 | T50: =Q50*1.2 -> 12 | U50: =Q50*0.8 -> 8 | V50: =Q50*0.3 -> 3 | W50: =SUM(Q50:V50) -> 47 | X50: =ROUNDUP(W50/20,2) -> 2.35 | Y50: =Z50 -> 2350000 | Z50: =X50*1000000 -> 2350000
D51: 共通 | E51: 共通部品作成 | F51: Webアプリケーションの共通部品を作成 | G51: 〇 | K51: 〇 | M51: 〇 | P51: 高 | Q51: =IFERROR(HLOOKUP(P51,AB$1:AF$2,2,FALSE),0) -> 7 | R51: =Q51*0.8 -> 5.6 | S51: =Q51*0.6 -> 4.2 | T51: =Q51*1.2 -> 8.4 | U51: =Q51*0.8 -> 5.6 | V51: =Q51*0.3 -> 2.1 | W51: =SUM(Q51:V51) -> 32.9 | X51: =ROUNDUP(W51/20,2) -> 1.65 | Y51: =Z51 -> 1650000 | Z51: =X51*1000000 -> 1650000
B52: 小計(人日) | P52: - | Q52: =SUM(Q6:Q51) -> 248 | R52: =SUM(R6:R51) -> 198.4 | S52: =SUM(S6:S51) -> 148.8 | T52: =SUM(T6:T51) -> 297.6 | U52: =SUM(U6:U51) -> 198.4 | V52: =SUM(V6:V51) -> 74.4 | W52: =SUM(Q52:V52) -> 1165.6
B53: 小計(人月) | P53: - | Q53: =Q52/20 -> 12.4 | R53: =R52/20 -> 9.92 | S53: =S52/20 -> 7.44 | T53: =T52/20 -> 14.88 | U53: =U52/20 -> 9.92 | V53: =V52/20 -> 3.72 | W53: =W52/20 -> 58.28 | X53: =SUM(X7:X51) -> 58.47
B54: 開発費用 | Y54: =SUM(Y7:Y51) -> 58470000
B55: 管理費用 | Y55: =X53*0.2*1400000 -> 16371600
B56: 初期流動(2か月) | Y56: 5400000
B57: 構築費用（管理費用+開発費用） | Y57: =Y54+Y55 -> 74841600
B58: 合計 | Y58: =Y56+Y57 -> 80241600

Sheet 日本対応パターン
A1: 《顧客提示時は削除予定》
B5: 担当者 | C5: 2024 | G5: 2025年
C6: 12月 | D6: 1月 | E6: 2月 | F6: 3月 | G6: 4月 | H6: 5月 | I6: 6月 | J6: 7月 | K6: 8月 | L6: 9月 | M6: 10月 | N6: 11月 | O6: 12月 | P6: 1月 | Q6: 2月 | R6: 3月 | T6: 合計
C7: 設計 | G7: 製造 | J7: 結合テスト | L7: 総合テスト | M7: 受入テスト支援 | O7: ハイパーケア | Q7: 保守 | R7: 顧客デッドライン | S7: 管理工数
B8: 工数見積もり | C8: =工数見積り_20241115!Q68 -> 12.5 | G8: =工数見積り_20241115!R68+工数見積り_20241115!S68 -> 17.5 | J8: =工数見積り_20241115!T68 -> 15 | L8: =工数見積り_20241115!U68 -> 10 | M8: =工数見積り_20241115!V68 -> 3.75 | S8: 11.27 | T8: =SUM(C8:S8) -> 70.02
B9: 体制(管理者抜き) | C9: =SUM(C12:F18) -> 16.8 | G9: =SUM(G12:I18) -> 15.6 | J9: =SUM(J12:K18) -> 10.4 | L9: =SUM(L12:L18) -> 5.2 | M9: =SUM(M12:N18) -> 7.4 | T9: =SUM(C9:S9) -> 55.4
B10: 川名 | C10: 0.5 | D10: 0.5 | E10: 0.5 | F10: 0.5 | G10: 0.5 | H10: 0.5 | I10: 0.5 | J10: 0.5 | K10: 0.5 | L10: 0.5 | M10: 0.5 | N10: 0.5 | T10: =SUM(C10:R10) -> 6
B11: 野村 | C11: 0.3 | D11: 0.3 | E11: 0.3 | F11: 0.3 | T11: =SUM(C11:R11) -> 1.2
B12: 上木 | C12: 1 | D12: 1 | E12: 1 | F12: 1 | G12: 1 | H12: 1 | I12: 1 | J12: 1 | K12: 1 | L12: 1 | M12: 1 | N12: 1 | O12: 1 | P12: 1 | T12: =SUM(C12:R12) -> 14
B13: 青木 | C13: 0.5 | D13: 0.5 | E13: 0.5 | F13: 0.5 | G13: 0.5 | H13: 0.5 | I13: 0.5 | J13: 0.5 | K13: 0.5 | L13: 0.5 | M13: 0.5 | N13: 0.5 | O13: 0.5 | P13: 0.5 | T13: =SUM(C13:R13) -> 7
B14: 朴 | C14: 1 | D14: 1 | E14: 1 | F14: 1 | G14: 1 | H14: 1 | I14: 1 | J14: 1 | K14: 1 | L14: 1 | T14: =SUM(C14:R14) -> 10
B15: 伊藤 | C15: 0.7 | D15: 0.7 | E15: 0.7 | F15: 0.7 | G15: 0.7 | H15: 0.7 | I15: 0.7 | J15: 0.7 | K15: 0.7 | L15: 0.7 | M15: 0.7 | N15: 0.7 | O15: 1 | P15: 1 | T15: =SUM(C15:R15) -> 10.4
B16: 松島 | C16: 1 | D16: 1 | E16: 1 | F16: 1 | G16: 1 | H16: 1 | I16: 1 | J16: 1 | K16: 1 | L16: 1 | M16: 1 | N16: 1 | T16: =SUM(C16:R16) -> 12
B17: BP1 | G17: 1 | H17: 1 | I17: 1 | J17: 1 | K17: 1 | L17: 1 | M17: 1 | T17: =SUM(C17:R17) -> 7
B18: BP2 | T18: =SUM(C18:R18) -> 0
T19: =SUM(T10:T18) -> 67.6
B20: 川名 | C20: =VLOOKUP($B10,日本単価!$A$4:$B$12,2,FALSE)*C10 -> 700000 | D20: =VLOOKUP($B10,日本単価!$A$4:$B$12,2,FALSE)*D10 -> 700000 | E20: =VLOOKUP($B10,日本単価!$A$4:$B$12,2,FALSE)*E10 -> 700000 | F20: =VLOOKUP($B10,日本単価!$A$4:$B$12,2,FALSE)*F10 -> 700000 | G20: =VLOOKUP($B10,日本単価!$A$4:$B$12,2,FALSE)*G10 -> 700000 | H20: =VLOOKUP($B10,日本単価!$A$4:$B$12,2,FALSE)*H10 -> 700000 | I20: =VLOOKUP($B10,日本単価!$A$4:$B$12,2,FALSE)*I10 -> 700000 | J20: =VLOOKUP($B10,日本単価!$A$4:$B$12,2,FALSE)*J10 -> 700000 | ... Q20: =VLOOKUP($B10,日本単価!$A$4:$B$12,2,FALSE)*Q10 -> 0 | T20: =SUM(C20:R20) -> 8400000
B21: 野村 | C21: =VLOOKUP($B11,日本単価!$A$4:$B$12,2,FALSE)*C11 -> 420000 | D21: =VLOOKUP($B11,日本単価!$A$4:$B$12,2,FALSE)*D11 -> 420000 | E21: =VLOOKUP($B11,日本単価!$A$4:$B$12,2,FALSE)*E11 -> 420000 | F21: =VLOOKUP($B11,日本単価!$A$4:$B$12,2,FALSE)*F11 -> 420000 | G21: =VLOOKUP($B11,日本単価!$A$4:$B$12,2,FALSE)*G11 -> 0 | H21: =VLOOKUP($B11,日本単価!$A$4:$B$12,2,FALSE)*H11 -> 0 | I21: =VLOOKUP($B11,日本単価!$A$4:$B$12,2,FALSE)*I11 -> 0 | J21: =VLOOKUP($B11,日本単価!$A$4:$B$12,2,FALSE)*J11 -> 0 | ... Q21: =VLOOKUP($B11,日本単価!$A$4:$B$12,2,FALSE)*Q11 -> 0 | T21: =SUM(C21:R21) -> 1680000
B22: 上木 | C22: =VLOOKUP($B12,日本単価!$A$4:$B$12,2,FALSE)*C12 -> 1200000 | D22: =VLOOKUP($B12,日本単価!$A$4:$B$12,2,FALSE)*D12 -> 1200000 | E22: =VLOOKUP($B12,日本単価!$A$4:$B$12,2,FALSE)*E12 -> 1200000 | F22: =VLOOKUP($B12,日本単価!$A$4:$B$12,2,FALSE)*F12 -> 1200000 | G22: =VLOOKUP($B12,日本単価!$A$4:$B$12,2,FALSE)*G12 -> 1200000 | H22: =VLOOKUP($B12,日本単価!$A$4:$B$12,2,FALSE)*H12 -> 1200000 | I22: =VLOOKUP($B12,日本単価!$A$4:$B$12,2,FALSE)*I12 -> 1200000 | J22: =VLOOKUP($B12,日本単価!$A$4:$B$12,2,FALSE)*J12 -> 1200000 | ... Q22: =VLOOKUP($B12,日本単価!$A$4:$B$12,2,FALSE)*Q12 -> 0 | T22: =SUM(C22:R22) -> 16800000
B23: 青木 | C23: =VLOOKUP($B13,日本単価!$A$4:$B$12,2,FALSE)*C13 -> 500000 | D23: =VLOOKUP($B13,日本単価!$A$4:$B$12,2,FALSE)*D13 -> 500000 | E23: =VLOOKUP($B13,日本単価!$A$4:$B$12,2,FALSE)*E13 -> 500000 | F23: =VLOOKUP($B13,日本単価!$A$4:$B$12,2,FALSE)*F13 -> 500000 | G23: =VLOOKUP($B13,日本単価!$A$4:$B$12,2,FALSE)*G13 -> 500000 | H23: =VLOOKUP($B13,日本単価!$A$4:$B$12,2,FALSE)*H13 -> 500000 | I23: =VLOOKUP($B13,日本単価!$A$4:$B$12,2,FALSE)*I13 -> 500000 | J23: =VLOOKUP($B13,日本単価!$A$4:$B$12,2,FALSE)*J13 -> 500000 | ... Q23: =VLOOKUP($B13,日本単価!$A$4:$B$12,2,FALSE)*Q13 -> 0 | T23: =SUM(C23:R23) -> 7000000
B24: 朴 | C24: =VLOOKUP($B14,日本単価!$A$4:$B$12,2,FALSE)*C14 -> 1200000 | D24: =VLOOKUP($B14,日本単価!$A$4:$B$12,2,FALSE)*D14 -> 1200000 | E24: =VLOOKUP($B14,日本単価!$A$4:$B$12,2,FALSE)*E14 -> 1200000 | F24: =VLOOKUP($B14,日本単価!$A$4:$B$12,2,FALSE)*F14 -> 1200000 | G24: =VLOOKUP($B14,日本単価!$A$4:$B$12,2,FALSE)*G14 -> 1200000 | H24: =VLOOKUP($B14,日本単価!$A$4:$B$12,2,FALSE)*H14 -> 1200000 | I24: =VLOOKUP($B14,日本単価!$A$4:$B$12,2,FALSE)*I14 -> 1200000 | J24: =VLOOKUP($B14,日本単価!$A$4:$B$12,2,FALSE)*J14 -> 1200000 | ... Q24: =VLOOKUP($B14,日本単価!$A$4:$B$12,2,FALSE)*Q14 -> 0 | T24: =SUM(C24:R24) -> 12000000
B25: 伊藤 | C25: =VLOOKUP($B15,日本単価!$A$4:$B$12,2,FALSE)*C15 -> 700000 | D25: =VLOOKUP($B15,日本単価!$A$4:$B$12,2,FALSE)*D15 -> 700000 | E25: =VLOOKUP($B15,日本単価!$A$4:$B$12,2,FALSE)*E15 -> 700000 | F25: =VLOOKUP($B15,日本単価!$A$4:$B$12,2,FALSE)*F15 -> 700000 | G25: =VLOOKUP($B15,日本単価!$A$4:$B$12,2,FALSE)*G15 -> 700000 | H25: =VLOOKUP($B15,日本単価!$A$4:$B$12,2,FALSE)*H15 -> 700000 | I25: =VLOOKUP($B15,日本単価!$A$4:$B$12,2,FALSE)*I15 -> 700000 | J25: =VLOOKUP($B15,日本単価!$A$4:$B$12,2,FALSE)*J15 -> 700000 | ... Q25: =VLOOKUP($B15,日本単価!$A$4:$B$12,2,FALSE)*Q15 -> 0 | T25: =SUM(C25:R25) -> 10400000
B26: 松島 | C26: =VLOOKUP($B16,日本単価!$A$4:$B$12,2,FALSE)*C16 -> 1000000 | D26: =VLOOKUP($B16,日本単価!$A$4:$B$12,2,FALSE)*D16 -> 1000000 | E26: =VLOOKUP($B16,日本単価!$A$4:$B$12,2,FALSE)*E16 -> 1000000 | F26: =VLOOKUP($B16,日本単価!$A$4:$B$12,2,FALSE)*F16 -> 1000000 | G26: =VLOOKUP($B16,日本単価!$A$4:$B$12,2,FALSE)*G16 -> 1000000 | H26: =VLOOKUP($B16,日本単価!$A$4:$B$12,2,FALSE)*H16 -> 1000000 | I26: =VLOOKUP($B16,日本単価!$A$4:$B$12,2,FALSE)*I16 -> 1000000 | J26: =VLOOKUP($B16,日本単価!$A$4:$B$12,2,FALSE)*J16 -> 1000000 | ... Q26: =VLOOKUP($B16,日本単価!$A$4:$B$12,2,FALSE)*Q16 -> 0 | T26: =SUM(C26:R26) -> 12000000
B27: BP1 | C27: =VLOOKUP($B17,日本単価!$A$4:$B$12,2,FALSE)*C17 -> 0 | D27: =VLOOKUP($B17,日本単価!$A$4:$B$12,2,FALSE)*D17 -> 0 | E27: =VLOOKUP($B17,日本単価!$A$4:$B$12,2,FALSE)*E17 -> 0 | F27: =VLOOKUP($B17,日本単価!$A$4:$B$12,2,FALSE)*F17 -> 0 | G27: =VLOOKUP($B17,日本単価!$A$4:$B$12,2,FALSE)*G17 -> 1000000 | H27: =VLOOKUP($B17,日本単価!$A$4:$B$12,2,FALSE)*H17 -> 1000000 | I27: =VLOOKUP($B17,日本単価!$A$4:$B$12,2,FALSE)*I17 -> 1000000 | J27: =VLOOKUP($B17,日本単価!$A$4:$B$12,2,FALSE)*J17 -> 1000000 | ... Q27: =VLOOKUP($B17,日本単価!$A$4:$B$12,2,FALSE)*Q17 -> 0 | T27: =SUM(C27:R27) -> 7000000
B28: BP2 | C28: =VLOOKUP($B18,日本単価!$A$4:$B$12,2,FALSE)*C18 -> 0 | D28: =VLOOKUP($B18,日本単価!$A$4:$B$12,2,FALSE)*D18 -> 0 | E28: =VLOOKUP($B18,日本単価!$A$4:$B$12,2,FALSE)*E18 -> 0 | F28: =VLOOKUP($B18,日本単価!$A$4:$B$12,2,FALSE)*F18 -> 0 | G28: =VLOOKUP($B18,日本単価!$A$4:$B$12,2,FALSE)*G18 -> 0 | H28: =VLOOKUP($B18,日本単価!$A$4:$B$12,2,FALSE)*H18 -> 0 | I28: =VLOOKUP($B18,日本単価!$A$4:$B$12,2,FALSE)*I18 -> 0 | J28: =VLOOKUP($B18,日本単価!$A$4:$B$12,2,FALSE)*J18 -> 0 | ... Q28: =VLOOKUP($B18,日本単価!$A$4:$B$12,2,FALSE)*Q18 -> 0 | T28: =SUM(C28:R28) -> 0
T29: =SUM(T20:T28) -> 75280000

Sheet オフショア対応パターン
A1: 《顧客提示時は削除予定》
B5: 担当者 | C5: 2024 | G5: 2025年
C6: 12月 | D6: 1月 | E6: 2月 | F6: 3月 | G6: 4月 | H6: 5月 | I6: 6月 | J6: 7月 | K6: 8月 | L6: 9月 | M6: 10月 | N6: 11月 | O6: 12月 | P6: 1月 | Q6: 2月 | R6: 3月 | T6: 合計
C7: 設計 | G7: 製造 | J7: 結合テスト | L7: 総合テスト | M7: 受入テスト支援 | O7: ハイパーケア | Q7: 保守 | R7: 顧客デッドライン | S7: 管理工数
B8: 工数見積もり | C8: =工数見積り_20241115!Q68 -> 12.5 | G8: =工数見積り_20241115!R68+工数見積り_20241115!S68 -> 17.5 | J8: =工数見積り_20241115!T68 -> 15 | L8: =工数見積り_20241115!U68 -> 10 | M8: =工数見積り_20241115!V68 -> 3.75 | S8: 11.27 | T8: =SUM(C8:S8) -> 70.02
B9: 体制(管理者抜き) | C9: =SUM(C12:F20) -> 16.8 | G9: =SUM(G12:I20) -> 20.1 | J9: =SUM(J12:K20) -> 11.4 | L9: =SUM(L12:L20) -> 5.7 | M9: =SUM(M12:N20) -> 9.4 | T9: =SUM(C9:R9) -> 63.4
B10: 川名 | C10: 0.5 | D10: 0.5 | E10: 0.5 | F10: 0.5 | G10: 0.5 | H10: 0.5 | I10: 0.5 | J10: 0.5 | K10: 0.5 | L10: 0.5 | M10: 0.5 | N10: 0.5 | T10: =SUM(C10:R10) -> 6
B11: 野村 | C11: 0.3 | D11: 0.3 | E11: 0.3 | F11: 0.3 | T11: =SUM(C11:R11) -> 1.2
B12: 上木 | C12: 1 | D12: 1 | E12: 1 | F12: 1 | G12: 1 | H12: 1 | I12: 1 | J12: 1 | K12: 1 | L12: 1 | M12: 1 | N12: 1 | O12: 1 | P12: 1 | T12: =SUM(C12:R12) -> 14
B13: 青木 | C13: 0.5 | D13: 0.5 | E13: 0.5 | F13: 0.5 | G13: 0.5 | H13: 0.5 | I13: 0.5 | J13: 0.5 | K13: 0.5 | L13: 0.5 | M13: 0.5 | N13: 0.5 | O13: 0.5 | P13: 0.5 | T13: =SUM(C13:R13) -> 7
B14: 朴 | C14: 1 | D14: 1 | E14: 1 | F14: 1 | G14: 1 | H14: 1 | I14: 1 | T14: =SUM(C14:R14) -> 7
B15: 伊藤 | C15: 0.7 | D15: 0.7 | E15: 0.7 | F15: 0.7 | G15: 0.7 | H15: 0.7 | I15: 0.7 | J15: 0.7 | K15: 0.7 | L15: 0.7 | M15: 0.7 | N15: 0.7 | O15: 1 | P15: 1 | T15: =SUM(C15:R15) -> 10.4
B16: 松島 | C16: 1 | D16: 1 | E16: 1 | F16: 1 | G16: 1 | H16: 1 | I16: 1 | J16: 1 | K16: 1 | L16: 1
B17: ブリッジ | G17: 0.5 | H17: 0.5 | I17: 0.5 | J17: 0.5 | K17: 0.5 | L17: 0.5 | M17: 0.5 | N17: 0.5
B18: オフショア① | G18: 1 | H18: 1 | I18: 1 | J18: 1 | K18: 1 | L18: 1 | M18: 1 | N18: 1
B19: オフショア② | G19: 1 | H19: 1 | I19: 1 | J19: 1 | K19: 1 | L19: 1 | M19: 1 | N19: 1
B20: オフショア③
B22: 川名 | C22: =VLOOKUP($B10,オフショア単価!$A$4:$B$15,2,FALSE)*C10 -> 700000 | D22: =VLOOKUP($B10,オフショア単価!$A$4:$B$15,2,FALSE)*D10 -> 700000 | E22: =VLOOKUP($B10,オフショア単価!$A$4:$B$15,2,FALSE)*E10 -> 700000 | F22: =VLOOKUP($B10,オフショア単価!$A$4:$B$15,2,FALSE)*F10 -> 700000 | G22: =VLOOKUP($B10,オフショア単価!$A$4:$B$15,2,FALSE)*G10 -> 700000 | H22: =VLOOKUP($B10,オフショア単価!$A$4:$B$15,2,FALSE)*H10 -> 700000 | I22: =VLOOKUP($B10,オフショア単価!$A$4:$B$15,2,FALSE)*I10 -> 700000 | J22: =VLOOKUP($B10,オフショア単価!$A$4:$B$15,2,FALSE)*J10 -> 700000 | ... Q22: =VLOOKUP($B10,オフショア単価!$A$4:$B$15,2,FALSE)*Q10 -> 0 | T22: =SUM(C22:R22) -> 8400000
B23: 野村 | C23: =VLOOKUP($B11,オフショア単価!$A$4:$B$15,2,FALSE)*C11 -> 420000 | D23: =VLOOKUP($B11,オフショア単価!$A$4:$B$15,2,FALSE)*D11 -> 420000 | E23: =VLOOKUP($B11,オフショア単価!$A$4:$B$15,2,FALSE)*E11 -> 420000 | F23: =VLOOKUP($B11,オフショア単価!$A$4:$B$15,2,FALSE)*F11 -> 420000 | G23: =VLOOKUP($B11,オフショア単価!$A$4:$B$15,2,FALSE)*G11 -> 0 | H23: =VLOOKUP($B11,オフショア単価!$A$4:$B$15,2,FALSE)*H11 -> 0 | I23: =VLOOKUP($B11,オフショア単価!$A$4:$B$15,2,FALSE)*I11 -> 0 | J23: =VLOOKUP($B11,オフショア単価!$A$4:$B$15,2,FALSE)*J11 -> 0 | ... Q23: =VLOOKUP($B11,オフショア単価!$A$4:$B$15,2,FALSE)*Q11 -> 0 | T23: =SUM(C23:R23) -> 1680000
B24: 上木 | C24: =VLOOKUP($B12,オフショア単価!$A$4:$B$15,2,FALSE)*C12 -> 1200000 | D24: =VLOOKUP($B12,オフショア単価!$A$4:$B$15,2,FALSE)*D12 -> 1200000 | E24: =VLOOKUP($B12,オフショア単価!$A$4:$B$15,2,FALSE)*E12 -> 1200000 | F24: =VLOOKUP($B12,オフショア単価!$A$4:$B$15,2,FALSE)*F12 -> 1200000 | G24: =VLOOKUP($B12,オフショア単価!$A$4:$B$15,2,FALSE)*G12 -> 1200000 | H24: =VLOOKUP($B12,オフショア単価!$A$4:$B$15,2,FALSE)*H12 -> 1200000 | I24: =VLOOKUP($B12,オフショア単価!$A$4:$B$15,2,FALSE)*I12 -> 1200000 | J24: =VLOOKUP($B12,オフショア単価!$A$4:$B$15,2,FALSE)*J12 -> 1200000 | ... Q24: =VLOOKUP($B12,オフショア単価!$A$4:$B$15,2,FALSE)*Q12 -> 0 | T24: =SUM(C24:R24) -> 16800000
B25: 青木 | C25: =VLOOKUP($B13,オフショア単価!$A$4:$B$15,2,FALSE)*C13 -> 500000 | D25: =VLOOKUP($B13,オフショア単価!$A$4:$B$15,2,FALSE)*D13 -> 500000 | E25: =VLOOKUP($B13,オフショア単価!$A$4:$B$15,2,FALSE)*E13 -> 500000 | F25: =VLOOKUP($B13,オフショア単価!$A$4:$B$15,2,FALSE)*F13 -> 500000 | G25: =VLOOKUP($B13,オフショア単価!$A$4:$B$15,2,FALSE)*G13 -> 500000 | H25: =VLOOKUP($B13,オフショア単価!$A$4:$B$15,2,FALSE)*H13 -> 500000 | I25: =VLOOKUP($B13,オフショア単価!$A$4:$B$15,2,FALSE)*I13 -> 500000 | J25: =VLOOKUP($B13,オフショア単価!$A$4:$B$15,2,FALSE)*J13 -> 500000 | ... Q25: =VLOOKUP($B13,オフショア単価!$A$4:$B$15,2,FALSE)*Q13 -> 0 | T25: =SUM(C25:R25) -> 7000000
B26: 朴 | C26: =VLOOKUP($B14,オフショア単価!$A$4:$B$15,2,FALSE)*C14 -> 1200000 | D26: =VLOOKUP($B14,オフショア単価!$A$4:$B$15,2,FALSE)*D14 -> 1200000 | E26: =VLOOKUP($B14,オフショア単価!$A$4:$B$15,2,FALSE)*E14 -> 1200000 | F26: =VLOOKUP($B14,オフショア単価!$A$4:$B$15,2,FALSE)*F14 -> 1200000 | G26: =VLOOKUP($B14,オフショア単価!$A$4:$B$15,2,FALSE)*G14 -> 1200000 | H26: =VLOOKUP($B14,オフショア単価!$A$4:$B$15,2,FALSE)*H14 -> 1200000 | I26: =VLOOKUP($B14,オフショア単価!$A$4:$B$15,2,FALSE)*I14 -> 1200000 | J26: =VLOOKUP($B14,オフショア単価!$A$4:$B$15,2,FALSE)*J14 -> 0 | ... Q26: =VLOOKUP($B14,オフショア単価!$A$4:$B$15,2,FALSE)*Q14 -> 0 | T26: =SUM(C26:R26) -> 8400000
B27: 伊藤 | C27: =VLOOKUP($B15,オフショア単価!$A$4:$B$15,2,FALSE)*C15 -> 700000 | D27: =VLOOKUP($B15,オフショア単価!$A$4:$B$15,2,FALSE)*D15 -> 700000 | E27: =VLOOKUP($B15,オフショア単価!$A$4:$B$15,2,FALSE)*E15 -> 700000 | F27: =VLOOKUP($B15,オフショア単価!$A$4:$B$15,2,FALSE)*F15 -> 700000 | G27: =VLOOKUP($B15,オフショア単価!$A$4:$B$15,2,FALSE)*G15 -> 700000 | H27: =VLOOKUP($B15,オフショア単価!$A$4:$B$15,2,FALSE)*H15 -> 700000 | I27: =VLOOKUP($B15,オフショア単価!$A$4:$B$15,2,FALSE)*I15 -> 700000 | J27: =VLOOKUP($B15,オフショア単価!$A$4:$B$15,2,FALSE)*J15 -> 700000 | ... Q27: =VLOOKUP($B15,オフショア単価!$A$4:$B$15,2,FALSE)*Q15 -> 0 | T27: =SUM(C27:R27) -> 10400000
B28: 松島 | C28: =VLOOKUP($B16,オフショア単価!$A$4:$B$15,2,FALSE)*C16 -> 1000000 | D28: =VLOOKUP($B16,オフショア単価!$A$4:$B$15,2,FALSE)*D16 -> 1000000 | E28: =VLOOKUP($B16,オフショア単価!$A$4:$B$15,2,FALSE)*E16 -> 1000000 | F28: =VLOOKUP($B16,オフショア単価!$A$4:$B$15,2,FALSE)*F16 -> 1000000 | G28: =VLOOKUP($B16,オフショア単価!$A$4:$B$15,2,FALSE)*G16 -> 1000000 | H28: =VLOOKUP($B16,オフショア単価!$A$4:$B$15,2,FALSE)*H16 -> 1000000 | I28: =VLOOKUP($B16,オフショア単価!$A$4:$B$15,2,FALSE)*I16 -> 1000000 | J28: =VLOOKUP($B16,オフショア単価!$A$4:$B$15,2,FALSE)*J16 -> 1000000 | ... Q28: =VLOOKUP($B16,オフショア単価!$A$4:$B$15,2,FALSE)*Q16 -> 0 | T28: =SUM(C28:R28) -> 10000000
B29: ブリッジ | C29: =VLOOKUP($B17,オフショア単価!$A$4:$B$15,2,FALSE)*C17 -> 0 | D29: =VLOOKUP($B17,オフショア単価!$A$4:$B$15,2,FALSE)*D17 -> 0 | E29: =VLOOKUP($B17,オフショア単価!$A$4:$B$15,2,FALSE)*E17 -> 0 | F29: =VLOOKUP($B17,オフショア単価!$A$4:$B$15,2,FALSE)*F17 -> 0 | G29: =VLOOKUP($B17,オフショア単価!$A$4:$B$15,2,FALSE)*G17 -> 500000 | H29: =VLOOKUP($B17,オフショア単価!$A$4:$B$15,2,FALSE)*H17 -> 500000 | I29: =VLOOKUP($B17,オフショア単価!$A$4:$B$15,2,FALSE)*I17 -> 500000 | J29: =VLOOKUP($B17,オフショア単価!$A$4:$B$15,2,FALSE)*J17 -> 500000 | ... Q29: =VLOOKUP($B17,オフショア単価!$A$4:$B$15,2,FALSE)*Q17 -> 0 | T29: =SUM(C29:R29) -> 4000000
B30: オフショア① | C30: =VLOOKUP($B18,オフショア単価!$A$4:$B$15,2,FALSE)*C18 -> 0 | D30: =VLOOKUP($B18,オフショア単価!$A$4:$B$15,2,FALSE)*D18 -> 0 | E30: =VLOOKUP($B18,オフショア単価!$A$4:$B$15,2,FALSE)*E18 -> 0 | F30: =VLOOKUP($B18,オフショア単価!$A$4:$B$15,2,FALSE)*F18 -> 0 | G30: =VLOOKUP($B18,オフショア単価!$A$4:$B$15,2,FALSE)*G18 -> 700000 | H30: =VLOOKUP($B18,オフショア単価!$A$4:$B$15,2,FALSE)*H18 -> 700000 | I30: =VLOOKUP($B18,オフショア単価!$A$4:$B$15,2,FALSE)*I18 -> 700000 | J30: =VLOOKUP($B18,オフショア単価!$A$4:$B$15,2,FALSE)*J18 -> 700000 | ... Q30: =VLOOKUP($B18,オフショア単価!$A$4:$B$15,2,FALSE)*Q18 -> 0 | T30: =SUM(C30:R30) -> 5600000
B31: オフショア② | C31: =VLOOKUP($B19,オフショア単価!$A$4:$B$15,2,FALSE)*C19 -> 0 | D31: =VLOOKUP($B19,オフショア単価!$A$4:$B$15,2,FALSE)*D19 -> 0 | E31: =VLOOKUP($B19,オフショア単価!$A$4:$B$15,2,FALSE)*E19 -> 0 | F31: =VLOOKUP($B19,オフショア単価!$A$4:$B$15,2,FALSE)*F19 -> 0 | G31: =VLOOKUP($B19,オフショア単価!$A$4:$B$15,2,FALSE)*G19 -> 700000 | H31: =VLOOKUP($B19,オフショア単価!$A$4:$B$15,2,FALSE)*H19 -> 700000 | I31: =VLOOKUP($B19,オフショア単価!$A$4:$B$15,2,FALSE)*I19 -> 700000 | J31: =VLOOKUP($B19,オフショア単価!$A$4:$B$15,2,FALSE)*J19 -> 700000 | ... Q31: =VLOOKUP($B19,オフショア単価!$A$4:$B$15,2,FALSE)*Q19 -> 0 | T31: =SUM(C31:R31) -> 5600000
B32: オフショア③ | C32: =VLOOKUP($B20,オフショア単価!$A$4:$B$15,2,FALSE)*C20 -> 0 | D32: =VLOOKUP($B20,オフショア単価!$A$4:$B$15,2,FALSE)*D20 -> 0 | E32: =VLOOKUP($B20,オフショア単価!$A$4:$B$15,2,FALSE)*E20 -> 0 | F32: =VLOOKUP($B20,オフショア単価!$A$4:$B$15,2,FALSE)*F20 -> 0 | G32: =VLOOKUP($B20,オフショア単価!$A$4:$B$15,2,FALSE)*G20 -> 0 | H32: =VLOOKUP($B20,オフショア単価!$A$4:$B$15,2,FALSE)*H20 -> 0 | I32: =VLOOKUP($B20,オフショア単価!$A$4:$B$15,2,FALSE)*I20 -> 0 | J32: =VLOOKUP($B20,オフショア単価!$A$4:$B$15,2,FALSE)*J20 -> 0 | ... Q32: =VLOOKUP($B20,オフショア単価!$A$4:$B$15,2,FALSE)*Q20 -> 0 | T32: =SUM(C32:R32) -> 0
T33: =SUM(T22:T32) -> 77880000

Sheet 日本単価
A1: 《顧客提示時は削除予定》
A4: 川名 | B4: 1400000
A5: 上木 | B5: 1200000
A6: 野村 | B6: 1400000
A7: 青木 | B7: 1000000
A8: 朴 | B8: 1200000
A9: 伊藤 | B9: 1000000
A10: 松島 | B10: 1000000
A11: BP1 | B11: 1000000
A12: BP2 | B12: 1000000

Sheet オフショア単価
A1: 《顧客提示時は削除予定》
A4: 川名 | B4: 1400000
A5: 上木 | B5: 1200000
A6: 野村 | B6: 1400000
A7: 青木 | B7: 1000000
A8: 朴 | B8: 1200000
A9: 伊藤 | B9: 1000000
A10: 松島 | B10: 1000000
A11: ブリッジ | B11: 1000000
A12: オフショア① | B12: 700000
A13: オフショア② | B13: 700000
A14: オフショア③ | B14: 700000

Sheet Sheet1
A1: 初期流動
B2: 案② | C2: 0.5ずつ
B3: 案③ | C3: 1ずつ
K8: phase1 | M8: phase2 | O8: phase3 | Q8: phase4
B9: 案② | C9: 矢羽根ごとの対応(phase4) | I9: 0.1 | K9: 0.5 | L9: 0.5 | M9: 0.5 | N9: 0.5 | O9: 1 | P9: 1 | Q9: 0.5 | R9: 0.5
K10: 2024/12 | L10: 2025/3 | M10: 2025/4 | N10: 2025/6 | O10: 2025/7 | P10: 2025/11 | Q10: 2025/11 | R10: 2026/2
K11: phase1 | M11: phase1
B12: 案③ | C12: phase1(国内 + 海外),phase2(マクロ + エクスポージャ) | I12: 0.06 | K12: 1 | L12: 1 | M12: 1.5 | N12: 1.5
K13: 2024/12 | L13: 2025/5 | M13: 2025/6 | N13: 2025/12
K14: phase1 | M14: phase2 | O14: phase3
B15: 案④ | C15: phase1(国内),phase2(海外 + マクロ),phase3( エクスポージャ) | I15: 0.08 | K15: 0.5 | L15: 0.5 | M15: 1.5 | N15: 1.5 | O15: 0.5 | P15: 0.5
K16: 2024/12 | L16: 2025/3 | M16: 2025/4 | N16: 2025/11 | O16: 2025/12 | P16: 2026/1
