Workbook
Name FP試算法データファンクション: [1]FP係数!$B$26:$B$27
Name 計測種別: [1]FP係数!$B$20:$B$21
Name 高係数: 積算基準!$D$49
Name 高係数_IF: 積算基準!$D$50
Name 参照上限高: 積算基準!$D$17
Name 参照上限中: 積算基準!$E$17
Name 参照上限低: 積算基準!$F$17
Name 参照上限特高: 積算基準!$C$17
Name 参照上限特低: 積算基準!$G$17
Name 成形原料処置: '[2]【参考】UI-22 業務コード定義'!$C$15
Name 単価ランク: [1]IFPUG法・FP概算法!$J$10:$J$14
Name 中係数: 積算基準!$E$49
Name 中係数_IF: 積算基準!$E$50
Name 低係数: 積算基準!$F$49
Name 低係数_IF: 積算基準!$F$50
Name 登録上限高: 積算基準!$D$16
Name 登録上限中: 積算基準!$E$16
Name 登録上限低: 積算基準!$F$16
Name 登録上限特高: 積算基準!$C$16
Name 登録上限特低: 積算基準!$G$16
Name 特高係数: 積算基準!$C$49
Name 特高係数_IF: 積算基準!$C$50
Name 特低係数: 積算基準!$G$49
Name 特低係数_IF: 積算基準!$G$50
Name 標準成形不可時: '[2]【参考】UI-22 業務コード定義'!$C$14

Sheet スケジュール・要員計画
C1: 4月 | D1: 5月 | E1: 6月 | F1: 7月 | G1: 8月 | H1: 9月 | I1: 10月 | J1: 11月 | K1: 12月 | L1: 1月 | M1: 2月 | N1: 3月 | O1: 4月
B2: 要件定義 | Q2: 外部IFは対象外
B3: 基本設計 | Q3: インフラ構築は対象外
B4: UI検討 | Q4: インフラ構成の設計はやる（ヒアリングシートの作成のみ）
B5: 詳細設計 | Q5: 要件定義後に再見積り
B6: 開発 | Q6: 要件定義、総合テスト以降は準委任契約とする
B7: 単体テスト | Q7: 脆弱性診断の実施費用は含まれていない（修正作業は含まれている）
B8: 結合テスト | Q8: オフショア利用の可能性あり
B9: 総合テスト | Q9: ソフトウェア費用は含まれていない
B10: 受入テスト | Q10: 頂いた資料分の見積りしかいれていない（※ユーザー管理は追加した）
B11: 本稼働 | Q11: 出張費用は含まれていない
B12: 初期流動 | Q12: マニュアル作成は含まれている
Q13: ユーザー教育は含まれていない
Q14: PCブラウザのシステムを想定している（タブレット、スマホ対応なし）
Q15: スクラッチ開発を想定している
Q19: 工数 | R19: 単価 | S19: 金額 | T19: 原価 | U19: 粗利 | V19: 粗利率
A20: JP | B20: PM | D20: 1 | E20: 1 | F20: 1 | G20: 1 | H20: 1 | I20: 0.5 | J20: 0.5 | K20: 0.5 | L20: 0.5 | M20: 0.5 | N20: 0.5 | Q20: =SUM(C20:O20) -> 8 | R20: 140 | S20: =Q20*R20 -> 1120 | T20: 65 | U20: =S20-(T20*Q20) -> 600
A21: JP | B21: SE（BP） | D21: 1 | E21: 1 | F21: 1 | G21: 1 | H21: 1 | I21: 1 | J21: 1 | K21: 1 | L21: 1 | M21: 1 | N21: 1 | Q21: =SUM(C21:O21) -> 11 | R21: 110 | S21: =Q21*R21 -> 1210 | T21: 90 | U21: =S21-(T21*Q21) -> 220
A22: JP | B22: SE（BP） | G22: 1 | H22: 1 | I22: 1 | J22: 1 | K22: 1 | Q22: =SUM(C22:O22) -> 5 | R22: 110 | S22: =Q22*R22 -> 550 | T22: 90 | U22: =S22-(T22*Q22) -> 100
A23: JP | B23: PG（BP） | Q23: =SUM(C23:O23) -> 0 | R23: 100 | S23: =Q23*R23 -> 0 | T23: 90 | U23: =S23-(T23*Q23) -> 0
A24: JP | B24: PG（BP） | Q24: =SUM(C24:O24) -> 0 | R24: 100 | S24: =Q24*R24 -> 0 | T24: 90 | U24: =S24-(T24*Q24) -> 0
Q25: =SUM(Q20:Q24) -> 24 | S25: =SUM(S20:S24) -> 2880 | U25: =SUM(U20:U24) -> 920 | V25: =U25/S25 -> 0.31944444
S26: =S25*1.2 -> 3456
A27: JP | B27: PM | D27: 1 | E27: 1 | F27: 1 | G27: 1 | H27: 1 | I27: 0.5 | J27: 0.5 | K27: 0.5 | L27: 0.5 | M27: 0.5 | N27: 0.5 | Q27: =SUM(C27:O27) -> 8 | R27: 140 | S27: =Q27*R27 -> 1120 | T27: 65 | U27: =S27-(T27*Q27) -> 600
A28: JP | B28: PL | Q28: =SUM(C28:O28) -> 0 | R28: 120 | S28: =Q28*R28 -> 0 | T28: 65 | U28: =S28-(T28*Q28) -> 0
A29: JP | B29: SE（BP） | D29: 1 | E29: 1 | F29: 1 | G29: 1 | H29: 1 | I29: 1 | J29: 1 | K29: 1 | L29: 1 | M29: 1 | N29: 1 | Q29: =SUM(C29:O29) -> 11 | R29: 110 | S29: =Q29*R29 -> 1210 | T29: 90 | U29: =S29-(T29*Q29) -> 220
A30: VN | B30: BG | G30: 0.5 | H30: 0.5 | I30: 0.5 | J30: 0.5 | K30: 0.5 | L30: 0.5 | M30: 0.5 | N30: 0.5 | Q30: =SUM(C30:O30) -> 4 | R30: 80 | S30: =Q30*R30 -> 320 | T30: 50 | U30: =S30-(T30*Q30) -> 120
A31: VN | B31: SE | G31: 1 | H31: 1 | I31: 1 | J31: 1 | K31: 1 | L31: 1 | M31: 1 | N31: 1 | Q31: =SUM(C31:O31) -> 8 | R31: 70 | S31: =Q31*R31 -> 560 | T31: 35 | U31: =S31-(T31*Q31) -> 280
A32: VN | B32: PG | G32: 1 | H32: 1 | I32: 1 | J32: 1 | K32: 1 | L32: 1 | M32: 1 | Q32: =SUM(C32:O32) -> 7 | R32: 70 | S32: =Q32*R32 -> 490 | T32: 35 | U32: =S32-(T32*Q32) -> 245
A33: VN | B33: PG | Q33: =SUM(C33:O33) -> 0 | R33: 70 | S33: =Q33*R33 -> 0 | T33: 35 | U33: =S33-(T33*Q33) -> 0
Q34: =SUM(Q27:Q33) -> 38 | S34: =SUM(S27:S33) -> 3700 | U34: =SUM(U27:U33) -> 1465 | V34: =U34/S34 -> 0.39594595
S35: =S34*1.2 -> 4440

Sheet 御見積(画面・機能)（2.5倍）
A2: № | B2: システム名 | C2: 機能名 | F2: JCC詳細設計 | H2: JCC見積 | K2: エグゼ見積 | N2: 分類 | O2: 機能画面説明 | P2: 難易度 | Q2: 新規 改修 | R2: 工程別工数（人日） | U2: 合計 （人日） | V2: 合計 （人月） | W2: 備考
C3: 大項目 | D3: 中項目 | E3: 小項目 | F3: 開始 | G3: 終了 | H3: 製造単体工数 | I3: 結合試験工数 | J3: 合計 | K3: 製造単体工数 | L3: 結合試験工数 | M3: 合計 | R3: 概要把握 設計レビュー | S3: 開発/単体テスト | T3: 結合テスト
A4: 基準工数 | R4: 0.5 | S4: =2.5*1.2*積算基準!F58 -> 9.75 | T4: =2.5*1.2*積算基準!G58 -> 7.875
A5: =ROW()-4 -> 1 | C5: 共通 | D5: アーキテクチャ | N5: 機能 | O5: システムアーキテクチャを構築 | P5: 低 | Q5: 新規 | S5: =CEILING(IF($Q5="新規", IF($P5="特高", S$4*特高係数,IF($P5="高",S$4*高係数,IF($P5="中",S$4*中係数,IF($P5="低",S$4*低係数, IF($P5="特低",S$4*特低係数, 0))))), IF($P5="特高", S$4*特高係数,IF($P5="高",S$4*高係数,IF($P5="中",S$4*中係数,IF($P5="低",S$4*低係数, IF($P5="特低",S$4*特低係数, 0)))))),0.125) -> 6.875 | T5: =CEILING(IF($Q5="新規", IF($P5="特高", T$4*特高係数,IF($P5="高",T$4*高係数,IF($P5="中",T$4*中係数,IF($P5="低",T$4*低係数, IF($P5="特低",T$4*特低係数, 0))))), IF($P5="特高", T$4*特高係数,IF($P5="高",T$4*高係数,IF($P5="中",T$4*中係数,IF($P5="低",T$4*低係数, IF($P5="特低",T$4*特低係数, 0)))))),0.125) -> 5.625 | U5: =SUM(R5:T5) -> 12.5 | V5: =U5/20 -> 0.625
D6: 開発環境・把握・構築 | P6: 低 | Q6: 新規 | S6: =CEILING(IF($Q6="新規", IF($P6="特高", S$4*特高係数,IF($P6="高",S$4*高係数,IF($P6="中",S$4*中係数,IF($P6="低",S$4*低係数, IF($P6="特低",S$4*特低係数, 0))))), IF($P6="特高", S$4*特高係数,IF($P6="高",S$4*高係数,IF($P6="中",S$4*中係数,IF($P6="低",S$4*低係数, IF($P6="特低",S$4*特低係数, 0)))))),0.125) -> 6.875 | T6: =CEILING(IF($Q6="新規", IF($P6="特高", T$4*特高係数,IF($P6="高",T$4*高係数,IF($P6="中",T$4*中係数,IF($P6="低",T$4*低係数, IF($P6="特低",T$4*特低係数, 0))))), IF($P6="特高", T$4*特高係数,IF($P6="高",T$4*高係数,IF($P6="中",T$4*中係数,IF($P6="低",T$4*低係数, IF($P6="特低",T$4*特低係数, 0)))))),0.125) -> 5.625 | U6: =SUM(R6:T6) -> 12.5 | V6: =U6/20 -> 0.625
D7: Azure環境構築（データレイク含む） | P7: 低 | Q7: 新規 | S7: =CEILING(IF($Q7="新規", IF($P7="特高", S$4*特高係数,IF($P7="高",S$4*高係数,IF($P7="中",S$4*中係数,IF($P7="低",S$4*低係数, IF($P7="特低",S$4*特低係数, 0))))), IF($P7="特高", S$4*特高係数,IF($P7="高",S$4*高係数,IF($P7="中",S$4*中係数,IF($P7="低",S$4*低係数, IF($P7="特低",S$4*特低係数, 0)))))),0.125) -> 6.875 | T7: =CEILING(IF($Q7="新規", IF($P7="特高", T$4*特高係数,IF($P7="高",T$4*高係数,IF($P7="中",T$4*中係数,IF($P7="低",T$4*低係数, IF($P7="特低",T$4*特低係数, 0))))), IF($P7="特高", T$4*特高係数,IF($P7="高",T$4*高係数,IF($P7="中",T$4*中係数,IF($P7="低",T$4*低係数, IF($P7="特低",T$4*特低係数, 0)))))),0.125) -> 5.625 | U7: =SUM(R7:T7) -> 12.5 | V7: =U7/20 -> 0.625
D8: 結合テスト計画作成 | P8: 低 | Q8: 新規 | S8: =CEILING(IF($Q8="新規", IF($P8="特高", S$4*特高係数,IF($P8="高",S$4*高係数,IF($P8="中",S$4*中係数,IF($P8="低",S$4*低係数, IF($P8="特低",S$4*特低係数, 0))))), IF($P8="特高", S$4*特高係数,IF($P8="高",S$4*高係数,IF($P8="中",S$4*中係数,IF($P8="低",S$4*低係数, IF($P8="特低",S$4*特低係数, 0)))))),0.125) -> 6.875 | T8: =CEILING(IF($Q8="新規", IF($P8="特高", T$4*特高係数,IF($P8="高",T$4*高係数,IF($P8="中",T$4*中係数,IF($P8="低",T$4*低係数, IF($P8="特低",T$4*特低係数, 0))))), IF($P8="特高", T$4*特高係数,IF($P8="高",T$4*高係数,IF($P8="中",T$4*中係数,IF($P8="低",T$4*低係数, IF($P8="特低",T$4*特低係数, 0)))))),0.125) -> 5.625 | U8: =SUM(R8:T8) -> 12.5 | V8: =U8/20 -> 0.625
D9: A-AUTO設定 | P9: 低 | Q9: 新規 | S9: =CEILING(IF($Q9="新規", IF($P9="特高", S$4*特高係数,IF($P9="高",S$4*高係数,IF($P9="中",S$4*中係数,IF($P9="低",S$4*低係数, IF($P9="特低",S$4*特低係数, 0))))), IF($P9="特高", S$4*特高係数,IF($P9="高",S$4*高係数,IF($P9="中",S$4*中係数,IF($P9="低",S$4*低係数, IF($P9="特低",S$4*特低係数, 0)))))),0.125) -> 6.875 | T9: =CEILING(IF($Q9="新規", IF($P9="特高", T$4*特高係数,IF($P9="高",T$4*高係数,IF($P9="中",T$4*中係数,IF($P9="低",T$4*低係数, IF($P9="特低",T$4*特低係数, 0))))), IF($P9="特高", T$4*特高係数,IF($P9="高",T$4*高係数,IF($P9="中",T$4*中係数,IF($P9="低",T$4*低係数, IF($P9="特低",T$4*特低係数, 0)))))),0.125) -> 5.625 | U9: =SUM(R9:T9) -> 12.5 | V9: =U9/20 -> 0.625
A10: =ROW()-4 -> 6 | C10: セルイン | D10: セルインTBL | F10: 45754 | G10: 45838 | H10: 8 | I10: 4 | J10: =SUM(H10:I10) -> 12 | L10: =K10*0.8 -> 0 | M10: =SUM(K10:L10) -> 0 | N10: DB | P10: 高 | Q10: 新規 | R10: =CEILING(IF($Q10="新規", IF($P10="特高", R$4*特高係数,IF($P10="高",R$4*高係数,IF($P10="中",R$4*中係数,IF($P10="低",R$4*低係数, IF($P10="特低",R$4*特低係数, 0))))), IF($P10="特高", R$4*特高係数,IF($P10="高",R$4*高係数,IF($P10="中",R$4*中係数,IF($P10="低",R$4*低係数, IF($P10="特低",R$4*特低係数, 0)))))),0.125) -> 1 | S10: =CEILING(IF($Q10="新規", IF($P10="特高", S$4*特高係数,IF($P10="高",S$4*高係数,IF($P10="中",S$4*中係数,IF($P10="低",S$4*低係数, IF($P10="特低",S$4*特低係数, 0))))), IF($P10="特高", S$4*特高係数,IF($P10="高",S$4*高係数,IF($P10="中",S$4*中係数,IF($P10="低",S$4*低係数, IF($P10="特低",S$4*特低係数, 0)))))),0.125) -> 19.5 | T10: =CEILING(IF($Q10="新規", IF($P10="特高", T$4*特高係数,IF($P10="高",T$4*高係数,IF($P10="中",T$4*中係数,IF($P10="低",T$4*低係数, IF($P10="特低",T$4*特低係数, 0))))), IF($P10="特高", T$4*特高係数,IF($P10="高",T$4*高係数,IF($P10="中",T$4*中係数,IF($P10="低",T$4*低係数, IF($P10="特低",T$4*特低係数, 0)))))),0.125) -> 15.75 | U10: =SUM(R10:T10) -> 36.25 | V10: =U10/20 -> 1.8125
D11: 売上原価伝送データ | F11: 45754 | G11: 45838 | H11: 8 | I11: 4 | J11: =SUM(H11:I11) -> 12 | L11: =K11*0.8 -> 0 | M11: =SUM(K11:L11) -> 0 | N11: BO | P11: 高 | Q11: 新規 | R11: =CEILING(IF($Q11="新規", IF($P11="特高", R$4*特高係数,IF($P11="高",R$4*高係数,IF($P11="中",R$4*中係数,IF($P11="低",R$4*低係数, IF($P11="特低",R$4*特低係数, 0))))), IF($P11="特高", R$4*特高係数,IF($P11="高",R$4*高係数,IF($P11="中",R$4*中係数,IF($P11="低",R$4*低係数, IF($P11="特低",R$4*特低係数, 0)))))),0.125) -> 1 | S11: =CEILING(IF($Q11="新規", IF($P11="特高", S$4*特高係数,IF($P11="高",S$4*高係数,IF($P11="中",S$4*中係数,IF($P11="低",S$4*低係数, IF($P11="特低",S$4*特低係数, 0))))), IF($P11="特高", S$4*特高係数,IF($P11="高",S$4*高係数,IF($P11="中",S$4*中係数,IF($P11="低",S$4*低係数, IF($P11="特低",S$4*特低係数, 0)))))),0.125) -> 19.5 | T11: =CEILING(IF($Q11="新規", IF($P11="特高", T$4*特高係数,IF($P11="高",T$4*高係数,IF($P11="中",T$4*中係数,IF($P11="低",T$4*低係数, IF($P11="特低",T$4*特低係数, 0))))), IF($P11="特高", T$4*特高係数,IF($P11="高",T$4*高係数,IF($P11="中",T$4*中係数,IF($P11="低",T$4*低係数, IF($P11="特低",T$4*特低係数, 0)))))),0.125) -> 15.75 | U11: =SUM(R11:T11) -> 36.25 | V11: =U11/20 -> 1.8125
D12: 販売実績数量価格推移表 1 | F12: 45754 | G12: 45838 | H12: 18 | I12: 9 | J12: =SUM(H12:I12) -> 27 | L12: =K12*0.8 -> 0 | M12: =SUM(K12:L12) -> 0 | N12: 帳票 | P12: 高 | Q12: 新規 | R12: =CEILING(IF($Q12="新規", IF($P12="特高", R$4*特高係数,IF($P12="高",R$4*高係数,IF($P12="中",R$4*中係数,IF($P12="低",R$4*低係数, IF($P12="特低",R$4*特低係数, 0))))), IF($P12="特高", R$4*特高係数,IF($P12="高",R$4*高係数,IF($P12="中",R$4*中係数,IF($P12="低",R$4*低係数, IF($P12="特低",R$4*特低係数, 0)))))),0.125) -> 1 | S12: =CEILING(IF($Q12="新規", IF($P12="特高", S$4*特高係数,IF($P12="高",S$4*高係数,IF($P12="中",S$4*中係数,IF($P12="低",S$4*低係数, IF($P12="特低",S$4*特低係数, 0))))), IF($P12="特高", S$4*特高係数,IF($P12="高",S$4*高係数,IF($P12="中",S$4*中係数,IF($P12="低",S$4*低係数, IF($P12="特低",S$4*特低係数, 0)))))),0.125) -> 19.5 | T12: =CEILING(IF($Q12="新規", IF($P12="特高", T$4*特高係数,IF($P12="高",T$4*高係数,IF($P12="中",T$4*中係数,IF($P12="低",T$4*低係数, IF($P12="特低",T$4*特低係数, 0))))), IF($P12="特高", T$4*特高係数,IF($P12="高",T$4*高係数,IF($P12="中",T$4*中係数,IF($P12="低",T$4*低係数, IF($P12="特低",T$4*特低係数, 0)))))),0.125) -> 15.75 | U12: =SUM(R12:T12) -> 36.25 | V12: =U12/20 -> 1.8125
D13: 販売実績数量価格推移表 2 | F13: 45754 | G13: 45838 | J13: =SUM(H13:I13) -> 0 | L13: =K13*0.8 -> 0 | M13: =SUM(K13:L13) -> 0 | N13: 帳票 | P13: 低 | Q13: 新規 | R13: =CEILING(IF($Q13="新規", IF($P13="特高", R$4*特高係数,IF($P13="高",R$4*高係数,IF($P13="中",R$4*中係数,IF($P13="低",R$4*低係数, IF($P13="特低",R$4*特低係数, 0))))), IF($P13="特高", R$4*特高係数,IF($P13="高",R$4*高係数,IF($P13="中",R$4*中係数,IF($P13="低",R$4*低係数, IF($P13="特低",R$4*特低係数, 0)))))),0.125) -> 0.375 | S13: =CEILING(IF($Q13="新規", IF($P13="特高", S$4*特高係数,IF($P13="高",S$4*高係数,IF($P13="中",S$4*中係数,IF($P13="低",S$4*低係数, IF($P13="特低",S$4*特低係数, 0))))), IF($P13="特高", S$4*特高係数,IF($P13="高",S$4*高係数,IF($P13="中",S$4*中係数,IF($P13="低",S$4*低係数, IF($P13="特低",S$4*特低係数, 0)))))),0.125) -> 6.875 | T13: =CEILING(IF($Q13="新規", IF($P13="特高", T$4*特高係数,IF($P13="高",T$4*高係数,IF($P13="中",T$4*中係数,IF($P13="低",T$4*低係数, IF($P13="特低",T$4*特低係数, 0))))), IF($P13="特高", T$4*特高係数,IF($P13="高",T$4*高係数,IF($P13="中",T$4*中係数,IF($P13="低",T$4*低係数, IF($P13="特低",T$4*特低係数, 0)))))),0.125) -> 5.625 | U13: =SUM(R13:T13) -> 12.875 | V13: =U13/20 -> 0.64375
D14: 販売実績数量価格推移表 3 | F14: 45754 | G14: 45838 | J14: =SUM(H14:I14) -> 0 | L14: =K14*0.8 -> 0 | M14: =SUM(K14:L14) -> 0 | N14: 帳票 | P14: 低 | Q14: 新規 | R14: =CEILING(IF($Q14="新規", IF($P14="特高", R$4*特高係数,IF($P14="高",R$4*高係数,IF($P14="中",R$4*中係数,IF($P14="低",R$4*低係数, IF($P14="特低",R$4*特低係数, 0))))), IF($P14="特高", R$4*特高係数,IF($P14="高",R$4*高係数,IF($P14="中",R$4*中係数,IF($P14="低",R$4*低係数, IF($P14="特低",R$4*特低係数, 0)))))),0.125) -> 0.375 | S14: =CEILING(IF($Q14="新規", IF($P14="特高", S$4*特高係数,IF($P14="高",S$4*高係数,IF($P14="中",S$4*中係数,IF($P14="低",S$4*低係数, IF($P14="特低",S$4*特低係数, 0))))), IF($P14="特高", S$4*特高係数,IF($P14="高",S$4*高係数,IF($P14="中",S$4*中係数,IF($P14="低",S$4*低係数, IF($P14="特低",S$4*特低係数, 0)))))),0.125) -> 6.875 | T14: =CEILING(IF($Q14="新規", IF($P14="特高", T$4*特高係数,IF($P14="高",T$4*高係数,IF($P14="中",T$4*中係数,IF($P14="低",T$4*低係数, IF($P14="特低",T$4*特低係数, 0))))), IF($P14="特高", T$4*特高係数,IF($P14="高",T$4*高係数,IF($P14="中",T$4*中係数,IF($P14="低",T$4*低係数, IF($P14="特低",T$4*特低係数, 0)))))),0.125) -> 5.625 | U14: =SUM(R14:T14) -> 12.875 | V14: =U14/20 -> 0.64375
D15: 販売実績数量価格推移表 4 | F15: 45754 | G15: 45838 | J15: =SUM(H15:I15) -> 0 | L15: =K15*0.8 -> 0 | M15: =SUM(K15:L15) -> 0 | N15: 帳票 | P15: 低 | Q15: 新規 | R15: =CEILING(IF($Q15="新規", IF($P15="特高", R$4*特高係数,IF($P15="高",R$4*高係数,IF($P15="中",R$4*中係数,IF($P15="低",R$4*低係数, IF($P15="特低",R$4*特低係数, 0))))), IF($P15="特高", R$4*特高係数,IF($P15="高",R$4*高係数,IF($P15="中",R$4*中係数,IF($P15="低",R$4*低係数, IF($P15="特低",R$4*特低係数, 0)))))),0.125) -> 0.375 | S15: =CEILING(IF($Q15="新規", IF($P15="特高", S$4*特高係数,IF($P15="高",S$4*高係数,IF($P15="中",S$4*中係数,IF($P15="低",S$4*低係数, IF($P15="特低",S$4*特低係数, 0))))), IF($P15="特高", S$4*特高係数,IF($P15="高",S$4*高係数,IF($P15="中",S$4*中係数,IF($P15="低",S$4*低係数, IF($P15="特低",S$4*特低係数, 0)))))),0.125) -> 6.875 | T15: =CEILING(IF($Q15="新規", IF($P15="特高", T$4*特高係数,IF($P15="高",T$4*高係数,IF($P15="中",T$4*中係数,IF($P15="低",T$4*低係数, IF($P15="特低",T$4*特低係数, 0))))), IF($P15="特高", T$4*特高係数,IF($P15="高",T$4*高係数,IF($P15="中",T$4*中係数,IF($P15="低",T$4*低係数, IF($P15="特低",T$4*特低係数, 0)))))),0.125) -> 5.625 | U15: =SUM(R15:T15) -> 12.875 | V15: =U15/20 -> 0.64375
D16: 販売実績数量価格推移表 5 | F16: 45754 | G16: 45838 | J16: =SUM(H16:I16) -> 0 | L16: =K16*0.8 -> 0 | M16: =SUM(K16:L16) -> 0 | N16: 帳票 | P16: 低 | Q16: 新規 | R16: =CEILING(IF($Q16="新規", IF($P16="特高", R$4*特高係数,IF($P16="高",R$4*高係数,IF($P16="中",R$4*中係数,IF($P16="低",R$4*低係数, IF($P16="特低",R$4*特低係数, 0))))), IF($P16="特高", R$4*特高係数,IF($P16="高",R$4*高係数,IF($P16="中",R$4*中係数,IF($P16="低",R$4*低係数, IF($P16="特低",R$4*特低係数, 0)))))),0.125) -> 0.375 | S16: =CEILING(IF($Q16="新規", IF($P16="特高", S$4*特高係数,IF($P16="高",S$4*高係数,IF($P16="中",S$4*中係数,IF($P16="低",S$4*低係数, IF($P16="特低",S$4*特低係数, 0))))), IF($P16="特高", S$4*特高係数,IF($P16="高",S$4*高係数,IF($P16="中",S$4*中係数,IF($P16="低",S$4*低係数, IF($P16="特低",S$4*特低係数, 0)))))),0.125) -> 6.875 | T16: =CEILING(IF($Q16="新規", IF($P16="特高", T$4*特高係数,IF($P16="高",T$4*高係数,IF($P16="中",T$4*中係数,IF($P16="低",T$4*低係数, IF($P16="特低",T$4*特低係数, 0))))), IF($P16="特高", T$4*特高係数,IF($P16="高",T$4*高係数,IF($P16="中",T$4*中係数,IF($P16="低",T$4*低係数, IF($P16="特低",T$4*特低係数, 0)))))),0.125) -> 5.625 | U16: =SUM(R16:T16) -> 12.875 | V16: =U16/20 -> 0.64375
D17: セルインデータ伝送 | F17: 45754 | G17: 45838 | H17: 8 | I17: 4 | J17: =SUM(H17:I17) -> 12 | L17: =K17*0.8 -> 0 | M17: =SUM(K17:L17) -> 0 | N17: BO | P17: 高 | Q17: 新規 | R17: =CEILING(IF($Q17="新規", IF($P17="特高", R$4*特高係数,IF($P17="高",R$4*高係数,IF($P17="中",R$4*中係数,IF($P17="低",R$4*低係数, IF($P17="特低",R$4*特低係数, 0))))), IF($P17="特高", R$4*特高係数,IF($P17="高",R$4*高係数,IF($P17="中",R$4*中係数,IF($P17="低",R$4*低係数, IF($P17="特低",R$4*特低係数, 0)))))),0.125) -> 1 | S17: =CEILING(IF($Q17="新規", IF($P17="特高", S$4*特高係数,IF($P17="高",S$4*高係数,IF($P17="中",S$4*中係数,IF($P17="低",S$4*低係数, IF($P17="特低",S$4*特低係数, 0))))), IF($P17="特高", S$4*特高係数,IF($P17="高",S$4*高係数,IF($P17="中",S$4*中係数,IF($P17="低",S$4*低係数, IF($P17="特低",S$4*特低係数, 0)))))),0.125) -> 19.5 | T17: =CEILING(IF($Q17="新規", IF($P17="特高", T$4*特高係数,IF($P17="高",T$4*高係数,IF($P17="中",T$4*中係数,IF($P17="低",T$4*低係数, IF($P17="特低",T$4*特低係数, 0))))), IF($P17="特高", T$4*特高係数,IF($P17="高",T$4*高係数,IF($P17="中",T$4*中係数,IF($P17="低",T$4*低係数, IF($P17="特低",T$4*特低係数, 0)))))),0.125) -> 15.75 | U17: =SUM(R17:T17) -> 36.25 | V17: =U17/20 -> 1.8125
D18: セルイン月次TBL | F18: 45754 | G18: 45838 | H18: 0 | I18: 0 | J18: =SUM(H18:I18) -> 0 | K18: 0 | L18: 0 | M18: =SUM(K18:L18) -> 0 | N18: 内部TBL | R18: =CEILING(IF($Q18="新規", IF($P18="特高", R$4*特高係数,IF($P18="高",R$4*高係数,IF($P18="中",R$4*中係数,IF($P18="低",R$4*低係数, IF($P18="特低",R$4*特低係数, 0))))), IF($P18="特高", R$4*特高係数,IF($P18="高",R$4*高係数,IF($P18="中",R$4*中係数,IF($P18="低",R$4*低係数, IF($P18="特低",R$4*特低係数, 0)))))),0.125) -> 0 | S18: =CEILING(IF($Q18="新規", IF($P18="特高", S$4*特高係数,IF($P18="高",S$4*高係数,IF($P18="中",S$4*中係数,IF($P18="低",S$4*低係数, IF($P18="特低",S$4*特低係数, 0))))), IF($P18="特高", S$4*特高係数,IF($P18="高",S$4*高係数,IF($P18="中",S$4*中係数,IF($P18="低",S$4*低係数, IF($P18="特低",S$4*特低係数, 0)))))),0.125) -> 0 | T18: =CEILING(IF($Q18="新規", IF($P18="特高", T$4*特高係数,IF($P18="高",T$4*高係数,IF($P18="中",T$4*中係数,IF($P18="低",T$4*低係数, IF($P18="特低",T$4*特低係数, 0))))), IF($P18="特高", T$4*特高係数,IF($P18="高",T$4*高係数,IF($P18="中",T$4*中係数,IF($P18="低",T$4*低係数, IF($P18="特低",T$4*特低係数, 0)))))),0.125) -> 0 | U18: =SUM(R18:T18) -> 0 | V18: =U18/20 -> 0
A19: =ROW()-4 -> 15 | C19: セルアウト | D19: セルアウト日別過去データ伝送 | F19: 45748 | G19: 45777 | H19: 0 | I19: 0 | J19: =SUM(H19:I19) -> 0 | K19: 0 | L19: 0 | M19: =SUM(K19:L19) -> 0 | N19: BO | R19: =CEILING(IF($Q19="新規", IF($P19="特高", R$4*特高係数,IF($P19="高",R$4*高係数,IF($P19="中",R$4*中係数,IF($P19="低",R$4*低係数, IF($P19="特低",R$4*特低係数, 0))))), IF($P19="特高", R$4*特高係数,IF($P19="高",R$4*高係数,IF($P19="中",R$4*中係数,IF($P19="低",R$4*低係数, IF($P19="特低",R$4*特低係数, 0)))))),0.125) -> 0 | S19: =CEILING(IF($Q19="新規", IF($P19="特高", S$4*特高係数,IF($P19="高",S$4*高係数,IF($P19="中",S$4*中係数,IF($P19="低",S$4*低係数, IF($P19="特低",S$4*特低係数, 0))))), IF($P19="特高", S$4*特高係数,IF($P19="高",S$4*高係数,IF($P19="中",S$4*中係数,IF($P19="低",S$4*低係数, IF($P19="特低",S$4*特低係数, 0)))))),0.125) -> 0 | T19: =CEILING(IF($Q19="新規", IF($P19="特高", T$4*特高係数,IF($P19="高",T$4*高係数,IF($P19="中",T$4*中係数,IF($P19="低",T$4*低係数, IF($P19="特低",T$4*特低係数, 0))))), IF($P19="特高", T$4*特高係数,IF($P19="高",T$4*高係数,IF($P19="中",T$4*中係数,IF($P19="低",T$4*低係数, IF($P19="特低",T$4*特低係数, 0)))))),0.125) -> 0 | U19: =SUM(R19:T19) -> 0 | V19: =U19/20 -> 0
D20: セルアウト日毎テーブル伝送 | F20: 45748 | G20: 45777 | H20: 8 | I20: 4 | J20: =SUM(H20:I20) -> 12 | L20: =K20*0.8 -> 0 | M20: =SUM(K20:L20) -> 0 | N20: BO | P20: 高 | Q20: 新規 | R20: =CEILING(IF($Q20="新規", IF($P20="特高", R$4*特高係数,IF($P20="高",R$4*高係数,IF($P20="中",R$4*中係数,IF($P20="低",R$4*低係数, IF($P20="特低",R$4*特低係数, 0))))), IF($P20="特高", R$4*特高係数,IF($P20="高",R$4*高係数,IF($P20="中",R$4*中係数,IF($P20="低",R$4*低係数, IF($P20="特低",R$4*特低係数, 0)))))),0.125) -> 1 | S20: =CEILING(IF($Q20="新規", IF($P20="特高", S$4*特高係数,IF($P20="高",S$4*高係数,IF($P20="中",S$4*中係数,IF($P20="低",S$4*低係数, IF($P20="特低",S$4*特低係数, 0))))), IF($P20="特高", S$4*特高係数,IF($P20="高",S$4*高係数,IF($P20="中",S$4*中係数,IF($P20="低",S$4*低係数, IF($P20="特低",S$4*特低係数, 0)))))),0.125) -> 19.5 | T20: =CEILING(IF($Q20="新規", IF($P20="特高", T$4*特高係数,IF($P20="高",T$4*高係数,IF($P20="中",T$4*中係数,IF($P20="低",T$4*低係数, IF($P20="特低",T$4*特低係数, 0))))), IF($P20="特高", T$4*特高係数,IF($P20="高",T$4*高係数,IF($P20="中",T$4*中係数,IF($P20="低",T$4*低係数, IF($P20="特低",T$4*特低係数, 0)))))),0.125) -> 15.75 | U20: =SUM(R20:T20) -> 36.25 | V20: =U20/20 -> 1.8125
D21: セルアウト日毎テーブル伝送 | F21: 45748 | G21: 45777 | H21: 0 | I21: 0 | J21: =SUM(H21:I21) -> 0 | K21: 0 | L21: 0 | M21: =SUM(K21:L21) -> 0 | N21: BO | R21: =CEILING(IF($Q21="新規", IF($P21="特高", R$4*特高係数,IF($P21="高",R$4*高係数,IF($P21="中",R$4*中係数,IF($P21="低",R$4*低係数, IF($P21="特低",R$4*特低係数, 0))))), IF($P21="特高", R$4*特高係数,IF($P21="高",R$4*高係数,IF($P21="中",R$4*中係数,IF($P21="低",R$4*低係数, IF($P21="特低",R$4*特低係数, 0)))))),0.125) -> 0 | S21: =CEILING(IF($Q21="新規", IF($P21="特高", S$4*特高係数,IF($P21="高",S$4*高係数,IF($P21="中",S$4*中係数,IF($P21="低",S$4*低係数, IF($P21="特低",S$4*特低係数, 0))))), IF($P21="特高", S$4*特高係数,IF($P21="高",S$4*高係数,IF($P21="中",S$4*中係数,IF($P21="低",S$4*低係数, IF($P21="特低",S$4*特低係数, 0)))))),0.125) -> 0 | T21: =CEILING(IF($Q21="新規", IF($P21="特高", T$4*特高係数,IF($P21="高",T$4*高係数,IF($P21="中",T$4*中係数,IF($P21="低",T$4*低係数, IF($P21="特低",T$4*特低係数, 0))))), IF($P21="特高", T$4*特高係数,IF($P21="高",T$4*高係数,IF($P21="中",T$4*中係数,IF($P21="低",T$4*低係数, IF($P21="特低",T$4*特低係数, 0)))))),0.125) -> 0 | U21: =SUM(R21:T21) -> 0 | V21: =U21/20 -> 0
D22: セルアウト月次テーブル伝送 | F22: 45748 | G22: 45777 | H22: 0 | I22: 0 | J22: =SUM(H22:I22) -> 0 | K22: 0 | L22: 0 | M22: =SUM(K22:L22) -> 0 | N22: BO | R22: =CEILING(IF($Q22="新規", IF($P22="特高", R$4*特高係数,IF($P22="高",R$4*高係数,IF($P22="中",R$4*中係数,IF($P22="低",R$4*低係数, IF($P22="特低",R$4*特低係数, 0))))), IF($P22="特高", R$4*特高係数,IF($P22="高",R$4*高係数,IF($P22="中",R$4*中係数,IF($P22="低",R$4*低係数, IF($P22="特低",R$4*特低係数, 0)))))),0.125) -> 0 | S22: =CEILING(IF($Q22="新規", IF($P22="特高", S$4*特高係数,IF($P22="高",S$4*高係数,IF($P22="中",S$4*中係数,IF($P22="低",S$4*低係数, IF($P22="特低",S$4*特低係数, 0))))), IF($P22="特高", S$4*特高係数,IF($P22="高",S$4*高係数,IF($P22="中",S$4*中係数,IF($P22="低",S$4*低係数, IF($P22="特低",S$4*特低係数, 0)))))),0.125) -> 0 | T22: =CEILING(IF($Q22="新規", IF($P22="特高", T$4*特高係数,IF($P22="高",T$4*高係数,IF($P22="中",T$4*中係数,IF($P22="低",T$4*低係数, IF($P22="特低",T$4*特低係数, 0))))), IF($P22="特高", T$4*特高係数,IF($P22="高",T$4*高係数,IF($P22="中",T$4*中係数,IF($P22="低",T$4*低係数, IF($P22="特低",T$4*特低係数, 0)))))),0.125) -> 0 | U22: =SUM(R22:T22) -> 0 | V22: =U22/20 -> 0
D23: ｍｙｄｏ情報データ伝送 | F23: 45748 | G23: 45777 | H23: 10 | I23: 6 | J23: =SUM(H23:I23) -> 16 | L23: =K23*0.8 -> 0 | M23: =SUM(K23:L23) -> 0 | N23: BO | P23: 特高 | Q23: 新規 | R23: =CEILING(IF($Q23="新規", IF($P23="特高", R$4*特高係数,IF($P23="高",R$4*高係数,IF($P23="中",R$4*中係数,IF($P23="低",R$4*低係数, IF($P23="特低",R$4*特低係数, 0))))), IF($P23="特高", R$4*特高係数,IF($P23="高",R$4*高係数,IF($P23="中",R$4*中係数,IF($P23="低",R$4*低係数, IF($P23="特低",R$4*特低係数, 0)))))),0.125) -> 1.375 | S23: =CEILING(IF($Q23="新規", IF($P23="特高", S$4*特高係数,IF($P23="高",S$4*高係数,IF($P23="中",S$4*中係数,IF($P23="低",S$4*低係数, IF($P23="特低",S$4*特低係数, 0))))), IF($P23="特高", S$4*特高係数,IF($P23="高",S$4*高係数,IF($P23="中",S$4*中係数,IF($P23="低",S$4*低係数, IF($P23="特低",S$4*特低係数, 0)))))),0.125) -> 25.375 | T23: =CEILING(IF($Q23="新規", IF($P23="特高", T$4*特高係数,IF($P23="高",T$4*高係数,IF($P23="中",T$4*中係数,IF($P23="低",T$4*低係数, IF($P23="特低",T$4*特低係数, 0))))), IF($P23="特高", T$4*特高係数,IF($P23="高",T$4*高係数,IF($P23="中",T$4*中係数,IF($P23="低",T$4*低係数, IF($P23="特低",T$4*特低係数, 0)))))),0.125) -> 20.5 | U23: =SUM(R23:T23) -> 47.25 | V23: =U23/20 -> 2.3625
A24: =ROW()-4 -> 20 | C24: 処理センター17時 | D24: 販売店請求データ作成 | F24: 45748 | G24: 45807 | H24: 10 | I24: 6 | J24: =SUM(H24:I24) -> 16 | L24: =K24*0.8 -> 0 | M24: =SUM(K24:L24) -> 0 | N24: 機能 | P24: 特高 | Q24: 新規 | R24: =CEILING(IF($Q24="新規", IF($P24="特高", R$4*特高係数,IF($P24="高",R$4*高係数,IF($P24="中",R$4*中係数,IF($P24="低",R$4*低係数, IF($P24="特低",R$4*特低係数, 0))))), IF($P24="特高", R$4*特高係数,IF($P24="高",R$4*高係数,IF($P24="中",R$4*中係数,IF($P24="低",R$4*低係数, IF($P24="特低",R$4*特低係数, 0)))))),0.125) -> 1.375 | S24: =CEILING(IF($Q24="新規", IF($P24="特高", S$4*特高係数,IF($P24="高",S$4*高係数,IF($P24="中",S$4*中係数,IF($P24="低",S$4*低係数, IF($P24="特低",S$4*特低係数, 0))))), IF($P24="特高", S$4*特高係数,IF($P24="高",S$4*高係数,IF($P24="中",S$4*中係数,IF($P24="低",S$4*低係数, IF($P24="特低",S$4*特低係数, 0)))))),0.125) -> 25.375 | T24: =CEILING(IF($Q24="新規", IF($P24="特高", T$4*特高係数,IF($P24="高",T$4*高係数,IF($P24="中",T$4*中係数,IF($P24="低",T$4*低係数, IF($P24="特低",T$4*特低係数, 0))))), IF($P24="特高", T$4*特高係数,IF($P24="高",T$4*高係数,IF($P24="中",T$4*中係数,IF($P24="低",T$4*低係数, IF($P24="特低",T$4*特低係数, 0)))))),0.125) -> 20.5 | U24: =SUM(R24:T24) -> 47.25 | V24: =U24/20 -> 2.3625
D25: POS配信1回目(CRC) | F25: 45748 | G25: 45807 | H25: 18 | I25: 9 | J25: =SUM(H25:I25) -> 27 | L25: =K25*0.8 -> 0 | M25: =SUM(K25:L25) -> 0 | N25: 連携 | P25: 特高 | Q25: 新規 | R25: =1.8*CEILING(IF($Q25="新規", IF($P25="特高", R$4*特高係数,IF($P25="高",R$4*高係数,IF($P25="中",R$4*中係数,IF($P25="低",R$4*低係数, IF($P25="特低",R$4*特低係数, 0))))), IF($P25="特高", R$4*特高係数,IF($P25="高",R$4*高係数,IF($P25="中",R$4*中係数,IF($P25="低",R$4*低係数, IF($P25="特低",R$4*特低係数, 0)))))),0.125) -> 2.475 | S25: =1.8*CEILING(IF($Q25="新規", IF($P25="特高", S$4*特高係数,IF($P25="高",S$4*高係数,IF($P25="中",S$4*中係数,IF($P25="低",S$4*低係数, IF($P25="特低",S$4*特低係数, 0))))), IF($P25="特高", S$4*特高係数,IF($P25="高",S$4*高係数,IF($P25="中",S$4*中係数,IF($P25="低",S$4*低係数, IF($P25="特低",S$4*特低係数, 0)))))),0.125) -> 45.675 | T25: =1.8*CEILING(IF($Q25="新規", IF($P25="特高", T$4*特高係数,IF($P25="高",T$4*高係数,IF($P25="中",T$4*中係数,IF($P25="低",T$4*低係数, IF($P25="特低",T$4*特低係数, 0))))), IF($P25="特高", T$4*特高係数,IF($P25="高",T$4*高係数,IF($P25="中",T$4*中係数,IF($P25="低",T$4*低係数, IF($P25="特低",T$4*特低係数, 0)))))),0.125) -> 36.9 | U25: =SUM(R25:T25) -> 85.05 | V25: =U25/20 -> 4.2525
D26: POS配信1回目(ICC) | F26: 45748 | G26: 45807 | H26: 12 | I26: 6 | J26: =SUM(H26:I26) -> 18 | L26: =K26*0.8 -> 0 | M26: =SUM(K26:L26) -> 0 | N26: 連携 | P26: 特高 | Q26: 新規 | R26: =CEILING(IF($Q26="新規", IF($P26="特高", R$4*特高係数,IF($P26="高",R$4*高係数,IF($P26="中",R$4*中係数,IF($P26="低",R$4*低係数, IF($P26="特低",R$4*特低係数, 0))))), IF($P26="特高", R$4*特高係数,IF($P26="高",R$4*高係数,IF($P26="中",R$4*中係数,IF($P26="低",R$4*低係数, IF($P26="特低",R$4*特低係数, 0)))))),0.125) -> 1.375 | S26: =CEILING(IF($Q26="新規", IF($P26="特高", S$4*特高係数,IF($P26="高",S$4*高係数,IF($P26="中",S$4*中係数,IF($P26="低",S$4*低係数, IF($P26="特低",S$4*特低係数, 0))))), IF($P26="特高", S$4*特高係数,IF($P26="高",S$4*高係数,IF($P26="中",S$4*中係数,IF($P26="低",S$4*低係数, IF($P26="特低",S$4*特低係数, 0)))))),0.125) -> 25.375 | T26: =CEILING(IF($Q26="新規", IF($P26="特高", T$4*特高係数,IF($P26="高",T$4*高係数,IF($P26="中",T$4*中係数,IF($P26="低",T$4*低係数, IF($P26="特低",T$4*特低係数, 0))))), IF($P26="特高", T$4*特高係数,IF($P26="高",T$4*高係数,IF($P26="中",T$4*中係数,IF($P26="低",T$4*低係数, IF($P26="特低",T$4*特低係数, 0)))))),0.125) -> 20.5 | U26: =SUM(R26:T26) -> 47.25 | V26: =U26/20 -> 2.3625
D27: POS配信1回目(ITC) | F27: 45748 | G27: 45807 | H27: 0 | I27: 0 | J27: =SUM(H27:I27) -> 0 | K27: 0 | L27: 0 | M27: =SUM(K27:L27) -> 0 | N27: 連携 | R27: =CEILING(IF($Q27="新規", IF($P27="特高", R$4*特高係数,IF($P27="高",R$4*高係数,IF($P27="中",R$4*中係数,IF($P27="低",R$4*低係数, IF($P27="特低",R$4*特低係数, 0))))), IF($P27="特高", R$4*特高係数,IF($P27="高",R$4*高係数,IF($P27="中",R$4*中係数,IF($P27="低",R$4*低係数, IF($P27="特低",R$4*特低係数, 0)))))),0.125) -> 0 | S27: =CEILING(IF($Q27="新規", IF($P27="特高", S$4*特高係数,IF($P27="高",S$4*高係数,IF($P27="中",S$4*中係数,IF($P27="低",S$4*低係数, IF($P27="特低",S$4*特低係数, 0))))), IF($P27="特高", S$4*特高係数,IF($P27="高",S$4*高係数,IF($P27="中",S$4*中係数,IF($P27="低",S$4*低係数, IF($P27="特低",S$4*特低係数, 0)))))),0.125) -> 0 | T27: =CEILING(IF($Q27="新規", IF($P27="特高", T$4*特高係数,IF($P27="高",T$4*高係数,IF($P27="中",T$4*中係数,IF($P27="低",T$4*低係数, IF($P27="特低",T$4*特低係数, 0))))), IF($P27="特高", T$4*特高係数,IF($P27="高",T$4*高係数,IF($P27="中",T$4*中係数,IF($P27="低",T$4*低係数, IF($P27="特低",T$4*特低係数, 0)))))),0.125) -> 0 | U27: =SUM(R27:T27) -> 0 | V27: =U27/20 -> 0
D28: POS配信1回目(CRC) | F28: 45748 | G28: 45807 | H28: 0 | I28: 0 | J28: =SUM(H28:I28) -> 0 | K28: 0 | L28: 0 | M28: =SUM(K28:L28) -> 0 | N28: 連携 | R28: =CEILING(IF($Q28="新規", IF($P28="特高", R$4*特高係数,IF($P28="高",R$4*高係数,IF($P28="中",R$4*中係数,IF($P28="低",R$4*低係数, IF($P28="特低",R$4*特低係数, 0))))), IF($P28="特高", R$4*特高係数,IF($P28="高",R$4*高係数,IF($P28="中",R$4*中係数,IF($P28="低",R$4*低係数, IF($P28="特低",R$4*特低係数, 0)))))),0.125) -> 0 | S28: =CEILING(IF($Q28="新規", IF($P28="特高", S$4*特高係数,IF($P28="高",S$4*高係数,IF($P28="中",S$4*中係数,IF($P28="低",S$4*低係数, IF($P28="特低",S$4*特低係数, 0))))), IF($P28="特高", S$4*特高係数,IF($P28="高",S$4*高係数,IF($P28="中",S$4*中係数,IF($P28="低",S$4*低係数, IF($P28="特低",S$4*特低係数, 0)))))),0.125) -> 0 | T28: =CEILING(IF($Q28="新規", IF($P28="特高", T$4*特高係数,IF($P28="高",T$4*高係数,IF($P28="中",T$4*中係数,IF($P28="低",T$4*低係数, IF($P28="特低",T$4*特低係数, 0))))), IF($P28="特高", T$4*特高係数,IF($P28="高",T$4*高係数,IF($P28="中",T$4*中係数,IF($P28="低",T$4*低係数, IF($P28="特低",T$4*特低係数, 0)))))),0.125) -> 0 | U28: =SUM(R28:T28) -> 0 | V28: =U28/20 -> 0
A29: =ROW()-4 -> 25 | C29: 自動仕入 | D29: 自動仕入連携（ICC） | F29: 45778 | G29: 45838 | H29: 18 | I29: 9 | J29: =SUM(H29:I29) -> 27 | L29: =K29*0.8 -> 0 | M29: =SUM(K29:L29) -> 0 | N29: 連携 | P29: 特高 | Q29: 新規 | R29: =1.8*CEILING(IF($Q29="新規", IF($P29="特高", R$4*特高係数,IF($P29="高",R$4*高係数,IF($P29="中",R$4*中係数,IF($P29="低",R$4*低係数, IF($P29="特低",R$4*特低係数, 0))))), IF($P29="特高", R$4*特高係数,IF($P29="高",R$4*高係数,IF($P29="中",R$4*中係数,IF($P29="低",R$4*低係数, IF($P29="特低",R$4*特低係数, 0)))))),0.125) -> 2.475 | S29: =1.8*CEILING(IF($Q29="新規", IF($P29="特高", S$4*特高係数,IF($P29="高",S$4*高係数,IF($P29="中",S$4*中係数,IF($P29="低",S$4*低係数, IF($P29="特低",S$4*特低係数, 0))))), IF($P29="特高", S$4*特高係数,IF($P29="高",S$4*高係数,IF($P29="中",S$4*中係数,IF($P29="低",S$4*低係数, IF($P29="特低",S$4*特低係数, 0)))))),0.125) -> 45.675 | T29: =1.8*CEILING(IF($Q29="新規", IF($P29="特高", T$4*特高係数,IF($P29="高",T$4*高係数,IF($P29="中",T$4*中係数,IF($P29="低",T$4*低係数, IF($P29="特低",T$4*特低係数, 0))))), IF($P29="特高", T$4*特高係数,IF($P29="高",T$4*高係数,IF($P29="中",T$4*中係数,IF($P29="低",T$4*低係数, IF($P29="特低",T$4*特低係数, 0)))))),0.125) -> 36.9 | U29: =SUM(R29:T29) -> 85.05 | V29: =U29/20 -> 4.2525
D30: 自動仕入連携（ITC） | F30: 45778 | G30: 45838 | H30: 4 | I30: 2 | J30: =SUM(H30:I30) -> 6 | L30: =K30*0.8 -> 0 | M30: =SUM(K30:L30) -> 0 | N30: 連携 | P30: 低 | Q30: 新規 | R30: =CEILING(IF($Q30="新規", IF($P30="特高", R$4*特高係数,IF($P30="高",R$4*高係数,IF($P30="中",R$4*中係数,IF($P30="低",R$4*低係数, IF($P30="特低",R$4*特低係数, 0))))), IF($P30="特高", R$4*特高係数,IF($P30="高",R$4*高係数,IF($P30="中",R$4*中係数,IF($P30="低",R$4*低係数, IF($P30="特低",R$4*特低係数, 0)))))),0.125) -> 0.375 | S30: =CEILING(IF($Q30="新規", IF($P30="特高", S$4*特高係数,IF($P30="高",S$4*高係数,IF($P30="中",S$4*中係数,IF($P30="低",S$4*低係数, IF($P30="特低",S$4*特低係数, 0))))), IF($P30="特高", S$4*特高係数,IF($P30="高",S$4*高係数,IF($P30="中",S$4*中係数,IF($P30="低",S$4*低係数, IF($P30="特低",S$4*特低係数, 0)))))),0.125) -> 6.875 | T30: =CEILING(IF($Q30="新規", IF($P30="特高", T$4*特高係数,IF($P30="高",T$4*高係数,IF($P30="中",T$4*中係数,IF($P30="低",T$4*低係数, IF($P30="特低",T$4*特低係数, 0))))), IF($P30="特高", T$4*特高係数,IF($P30="高",T$4*高係数,IF($P30="中",T$4*中係数,IF($P30="低",T$4*低係数, IF($P30="特低",T$4*特低係数, 0)))))),0.125) -> 5.625 | U30: =SUM(R30:T30) -> 12.875 | V30: =U30/20 -> 0.64375
D31: 自動仕入連携（CRC） | F31: 45778 | G31: 45838 | H31: 0 | I31: 0 | J31: =SUM(H31:I31) -> 0 | K31: 0 | L31: 0 | M31: =SUM(K31:L31) -> 0 | N31: 連携 | R31: =CEILING(IF($Q31="新規", IF($P31="特高", R$4*特高係数,IF($P31="高",R$4*高係数,IF($P31="中",R$4*中係数,IF($P31="低",R$4*低係数, IF($P31="特低",R$4*特低係数, 0))))), IF($P31="特高", R$4*特高係数,IF($P31="高",R$4*高係数,IF($P31="中",R$4*中係数,IF($P31="低",R$4*低係数, IF($P31="特低",R$4*特低係数, 0)))))),0.125) -> 0 | S31: =CEILING(IF($Q31="新規", IF($P31="特高", S$4*特高係数,IF($P31="高",S$4*高係数,IF($P31="中",S$4*中係数,IF($P31="低",S$4*低係数, IF($P31="特低",S$4*特低係数, 0))))), IF($P31="特高", S$4*特高係数,IF($P31="高",S$4*高係数,IF($P31="中",S$4*中係数,IF($P31="低",S$4*低係数, IF($P31="特低",S$4*特低係数, 0)))))),0.125) -> 0 | T31: =CEILING(IF($Q31="新規", IF($P31="特高", T$4*特高係数,IF($P31="高",T$4*高係数,IF($P31="中",T$4*中係数,IF($P31="低",T$4*低係数, IF($P31="特低",T$4*特低係数, 0))))), IF($P31="特高", T$4*特高係数,IF($P31="高",T$4*高係数,IF($P31="中",T$4*中係数,IF($P31="低",T$4*低係数, IF($P31="特低",T$4*特低係数, 0)))))),0.125) -> 0 | U31: =SUM(R31:T31) -> 0 | V31: =U31/20 -> 0
D32: 自動仕入連携（GST） | F32: 45778 | G32: 45838 | H32: 0 | I32: 0 | J32: =SUM(H32:I32) -> 0 | K32: 0 | L32: 0 | M32: =SUM(K32:L32) -> 0 | N32: 連携 | R32: =CEILING(IF($Q32="新規", IF($P32="特高", R$4*特高係数,IF($P32="高",R$4*高係数,IF($P32="中",R$4*中係数,IF($P32="低",R$4*低係数, IF($P32="特低",R$4*特低係数, 0))))), IF($P32="特高", R$4*特高係数,IF($P32="高",R$4*高係数,IF($P32="中",R$4*中係数,IF($P32="低",R$4*低係数, IF($P32="特低",R$4*特低係数, 0)))))),0.125) -> 0 | S32: =CEILING(IF($Q32="新規", IF($P32="特高", S$4*特高係数,IF($P32="高",S$4*高係数,IF($P32="中",S$4*中係数,IF($P32="低",S$4*低係数, IF($P32="特低",S$4*特低係数, 0))))), IF($P32="特高", S$4*特高係数,IF($P32="高",S$4*高係数,IF($P32="中",S$4*中係数,IF($P32="低",S$4*低係数, IF($P32="特低",S$4*特低係数, 0)))))),0.125) -> 0 | T32: =CEILING(IF($Q32="新規", IF($P32="特高", T$4*特高係数,IF($P32="高",T$4*高係数,IF($P32="中",T$4*中係数,IF($P32="低",T$4*低係数, IF($P32="特低",T$4*特低係数, 0))))), IF($P32="特高", T$4*特高係数,IF($P32="高",T$4*高係数,IF($P32="中",T$4*中係数,IF($P32="低",T$4*低係数, IF($P32="特低",T$4*特低係数, 0)))))),0.125) -> 0 | U32: =SUM(R32:T32) -> 0 | V32: =U32/20 -> 0
A33: =ROW()-4 -> 29 | C33: POS処理料・利用料 | D33: POS処理料出クレ決済用データ | F33: 45748 | G33: 45814 | H33: 8 | I33: 4 | J33: =SUM(H33:I33) -> 12 | L33: =K33*0.8 -> 0 | M33: =SUM(K33:L33) -> 0 | N33: 連携 | P33: 高 | Q33: 新規 | R33: =CEILING(IF($Q33="新規", IF($P33="特高", R$4*特高係数,IF($P33="高",R$4*高係数,IF($P33="中",R$4*中係数,IF($P33="低",R$4*低係数, IF($P33="特低",R$4*特低係数, 0))))), IF($P33="特高", R$4*特高係数,IF($P33="高",R$4*高係数,IF($P33="中",R$4*中係数,IF($P33="低",R$4*低係数, IF($P33="特低",R$4*特低係数, 0)))))),0.125) -> 1 | S33: =CEILING(IF($Q33="新規", IF($P33="特高", S$4*特高係数,IF($P33="高",S$4*高係数,IF($P33="中",S$4*中係数,IF($P33="低",S$4*低係数, IF($P33="特低",S$4*特低係数, 0))))), IF($P33="特高", S$4*特高係数,IF($P33="高",S$4*高係数,IF($P33="中",S$4*中係数,IF($P33="低",S$4*低係数, IF($P33="特低",S$4*特低係数, 0)))))),0.125) -> 19.5 | T33: =CEILING(IF($Q33="新規", IF($P33="特高", T$4*特高係数,IF($P33="高",T$4*高係数,IF($P33="中",T$4*中係数,IF($P33="低",T$4*低係数, IF($P33="特低",T$4*特低係数, 0))))), IF($P33="特高", T$4*特高係数,IF($P33="高",T$4*高係数,IF($P33="中",T$4*中係数,IF($P33="低",T$4*低係数, IF($P33="特低",T$4*特低係数, 0)))))),0.125) -> 15.75 | U33: =SUM(R33:T33) -> 36.25 | V33: =U33/20 -> 1.8125
D34: POS利用料機伝 | F34: 45748 | G34: 45814 | H34: 8 | I34: 4 | J34: =SUM(H34:I34) -> 12 | L34: =K34*0.8 -> 0 | M34: =SUM(K34:L34) -> 0 | N34: 連携 | P34: 高 | Q34: 新規 | R34: =CEILING(IF($Q34="新規", IF($P34="特高", R$4*特高係数,IF($P34="高",R$4*高係数,IF($P34="中",R$4*中係数,IF($P34="低",R$4*低係数, IF($P34="特低",R$4*特低係数, 0))))), IF($P34="特高", R$4*特高係数,IF($P34="高",R$4*高係数,IF($P34="中",R$4*中係数,IF($P34="低",R$4*低係数, IF($P34="特低",R$4*特低係数, 0)))))),0.125) -> 1 | S34: =CEILING(IF($Q34="新規", IF($P34="特高", S$4*特高係数,IF($P34="高",S$4*高係数,IF($P34="中",S$4*中係数,IF($P34="低",S$4*低係数, IF($P34="特低",S$4*特低係数, 0))))), IF($P34="特高", S$4*特高係数,IF($P34="高",S$4*高係数,IF($P34="中",S$4*中係数,IF($P34="低",S$4*低係数, IF($P34="特低",S$4*特低係数, 0)))))),0.125) -> 19.5 | T34: =CEILING(IF($Q34="新規", IF($P34="特高", T$4*特高係数,IF($P34="高",T$4*高係数,IF($P34="中",T$4*中係数,IF($P34="低",T$4*低係数, IF($P34="特低",T$4*特低係数, 0))))), IF($P34="特高", T$4*特高係数,IF($P34="高",T$4*高係数,IF($P34="中",T$4*中係数,IF($P34="低",T$4*低係数, IF($P34="特低",T$4*特低係数, 0)))))),0.125) -> 15.75 | U34: =SUM(R34:T34) -> 36.25 | V34: =U34/20 -> 1.8125
D35: POS処理料機伝 | F35: 45748 | G35: 45814 | H35: 8 | I35: 4 | J35: =SUM(H35:I35) -> 12 | L35: =K35*0.8 -> 0 | M35: =SUM(K35:L35) -> 0 | N35: 連携 | P35: 高 | Q35: 新規 | R35: =CEILING(IF($Q35="新規", IF($P35="特高", R$4*特高係数,IF($P35="高",R$4*高係数,IF($P35="中",R$4*中係数,IF($P35="低",R$4*低係数, IF($P35="特低",R$4*特低係数, 0))))), IF($P35="特高", R$4*特高係数,IF($P35="高",R$4*高係数,IF($P35="中",R$4*中係数,IF($P35="低",R$4*低係数, IF($P35="特低",R$4*特低係数, 0)))))),0.125) -> 1 | S35: =CEILING(IF($Q35="新規", IF($P35="特高", S$4*特高係数,IF($P35="高",S$4*高係数,IF($P35="中",S$4*中係数,IF($P35="低",S$4*低係数, IF($P35="特低",S$4*特低係数, 0))))), IF($P35="特高", S$4*特高係数,IF($P35="高",S$4*高係数,IF($P35="中",S$4*中係数,IF($P35="低",S$4*低係数, IF($P35="特低",S$4*特低係数, 0)))))),0.125) -> 19.5 | T35: =CEILING(IF($Q35="新規", IF($P35="特高", T$4*特高係数,IF($P35="高",T$4*高係数,IF($P35="中",T$4*中係数,IF($P35="低",T$4*低係数, IF($P35="特低",T$4*特低係数, 0))))), IF($P35="特高", T$4*特高係数,IF($P35="高",T$4*高係数,IF($P35="中",T$4*中係数,IF($P35="低",T$4*低係数, IF($P35="特低",T$4*特低係数, 0)))))),0.125) -> 15.75 | U35: =SUM(R35:T35) -> 36.25 | V35: =U35/20 -> 1.8125
D36: ＰＯＳ処理料各種確認リスト | F36: 45748 | G36: 45814 | H36: 8 | I36: 4 | J36: =SUM(H36:I36) -> 12 | K36: 12 | L36: =K36*0.8 -> 9.6 | M36: =SUM(K36:L36) -> 21.6 | N36: 帳票 | P36: 高 | Q36: 新規 | R36: =CEILING(IF($Q36="新規", IF($P36="特高", R$4*特高係数,IF($P36="高",R$4*高係数,IF($P36="中",R$4*中係数,IF($P36="低",R$4*低係数, IF($P36="特低",R$4*特低係数, 0))))), IF($P36="特高", R$4*特高係数,IF($P36="高",R$4*高係数,IF($P36="中",R$4*中係数,IF($P36="低",R$4*低係数, IF($P36="特低",R$4*特低係数, 0)))))),0.125) -> 1 | S36: =CEILING(IF($Q36="新規", IF($P36="特高", S$4*特高係数,IF($P36="高",S$4*高係数,IF($P36="中",S$4*中係数,IF($P36="低",S$4*低係数, IF($P36="特低",S$4*特低係数, 0))))), IF($P36="特高", S$4*特高係数,IF($P36="高",S$4*高係数,IF($P36="中",S$4*中係数,IF($P36="低",S$4*低係数, IF($P36="特低",S$4*特低係数, 0)))))),0.125) -> 19.5 | T36: =CEILING(IF($Q36="新規", IF($P36="特高", T$4*特高係数,IF($P36="高",T$4*高係数,IF($P36="中",T$4*中係数,IF($P36="低",T$4*低係数, IF($P36="特低",T$4*特低係数, 0))))), IF($P36="特高", T$4*特高係数,IF($P36="高",T$4*高係数,IF($P36="中",T$4*中係数,IF($P36="低",T$4*低係数, IF($P36="特低",T$4*特低係数, 0)))))),0.125) -> 15.75 | U36: =SUM(R36:T36) -> 36.25 | V36: =U36/20 -> 1.8125
A37: =ROW()-4 -> 33 | C37: エントリ向け_まいどプラス発券 | D37: Mydoプラス発券実績 | F37: 45761 | G37: 45777 | H37: 8 | I37: 4 | J37: =SUM(H37:I37) -> 12 | L37: =K37*0.8 -> 0 | M37: =SUM(K37:L37) -> 0 | N37: DB | P37: 高 | Q37: 新規 | R37: =CEILING(IF($Q37="新規", IF($P37="特高", R$4*特高係数,IF($P37="高",R$4*高係数,IF($P37="中",R$4*中係数,IF($P37="低",R$4*低係数, IF($P37="特低",R$4*特低係数, 0))))), IF($P37="特高", R$4*特高係数,IF($P37="高",R$4*高係数,IF($P37="中",R$4*中係数,IF($P37="低",R$4*低係数, IF($P37="特低",R$4*特低係数, 0)))))),0.125) -> 1 | S37: =CEILING(IF($Q37="新規", IF($P37="特高", S$4*特高係数,IF($P37="高",S$4*高係数,IF($P37="中",S$4*中係数,IF($P37="低",S$4*低係数, IF($P37="特低",S$4*特低係数, 0))))), IF($P37="特高", S$4*特高係数,IF($P37="高",S$4*高係数,IF($P37="中",S$4*中係数,IF($P37="低",S$4*低係数, IF($P37="特低",S$4*特低係数, 0)))))),0.125) -> 19.5 | T37: =CEILING(IF($Q37="新規", IF($P37="特高", T$4*特高係数,IF($P37="高",T$4*高係数,IF($P37="中",T$4*中係数,IF($P37="低",T$4*低係数, IF($P37="特低",T$4*特低係数, 0))))), IF($P37="特高", T$4*特高係数,IF($P37="高",T$4*高係数,IF($P37="中",T$4*中係数,IF($P37="低",T$4*低係数, IF($P37="特低",T$4*特低係数, 0)))))),0.125) -> 15.75 | U37: =SUM(R37:T37) -> 36.25 | V37: =U37/20 -> 1.8125
D38: MYDOPlus発券実績 | F38: 45761 | G38: 45777 | H38: 4 | I38: 2 | J38: =SUM(H38:I38) -> 6 | L38: =K38*0.8 -> 0 | M38: =SUM(K38:L38) -> 0 | N38: 連携 | P38: 低 | Q38: 新規 | R38: =CEILING(IF($Q38="新規", IF($P38="特高", R$4*特高係数,IF($P38="高",R$4*高係数,IF($P38="中",R$4*中係数,IF($P38="低",R$4*低係数, IF($P38="特低",R$4*特低係数, 0))))), IF($P38="特高", R$4*特高係数,IF($P38="高",R$4*高係数,IF($P38="中",R$4*中係数,IF($P38="低",R$4*低係数, IF($P38="特低",R$4*特低係数, 0)))))),0.125) -> 0.375 | S38: =CEILING(IF($Q38="新規", IF($P38="特高", S$4*特高係数,IF($P38="高",S$4*高係数,IF($P38="中",S$4*中係数,IF($P38="低",S$4*低係数, IF($P38="特低",S$4*特低係数, 0))))), IF($P38="特高", S$4*特高係数,IF($P38="高",S$4*高係数,IF($P38="中",S$4*中係数,IF($P38="低",S$4*低係数, IF($P38="特低",S$4*特低係数, 0)))))),0.125) -> 6.875 | T38: =CEILING(IF($Q38="新規", IF($P38="特高", T$4*特高係数,IF($P38="高",T$4*高係数,IF($P38="中",T$4*中係数,IF($P38="低",T$4*低係数, IF($P38="特低",T$4*特低係数, 0))))), IF($P38="特高", T$4*特高係数,IF($P38="高",T$4*高係数,IF($P38="中",T$4*中係数,IF($P38="低",T$4*低係数, IF($P38="特低",T$4*特低係数, 0)))))),0.125) -> 5.625 | U38: =SUM(R38:T38) -> 12.875 | V38: =U38/20 -> 0.64375
A39: =ROW()-4 -> 35 | C39: ｱｽﾄﾓｽ入出荷 | D39: 入出荷共通入力（日次）OneSAP向け | F39: 45761 | G39: 45821 | H39: 18 | I39: 9 | J39: =SUM(H39:I39) -> 27 | L39: =K39*0.8 -> 0 | M39: =SUM(K39:L39) -> 0 | N39: 連携 | P39: 特高 | Q39: 新規 | R39: =1.8*CEILING(IF($Q39="新規", IF($P39="特高", R$4*特高係数,IF($P39="高",R$4*高係数,IF($P39="中",R$4*中係数,IF($P39="低",R$4*低係数, IF($P39="特低",R$4*特低係数, 0))))), IF($P39="特高", R$4*特高係数,IF($P39="高",R$4*高係数,IF($P39="中",R$4*中係数,IF($P39="低",R$4*低係数, IF($P39="特低",R$4*特低係数, 0)))))),0.125) -> 2.475 | S39: =1.8*CEILING(IF($Q39="新規", IF($P39="特高", S$4*特高係数,IF($P39="高",S$4*高係数,IF($P39="中",S$4*中係数,IF($P39="低",S$4*低係数, IF($P39="特低",S$4*特低係数, 0))))), IF($P39="特高", S$4*特高係数,IF($P39="高",S$4*高係数,IF($P39="中",S$4*中係数,IF($P39="低",S$4*低係数, IF($P39="特低",S$4*特低係数, 0)))))),0.125) -> 45.675 | T39: =1.8*CEILING(IF($Q39="新規", IF($P39="特高", T$4*特高係数,IF($P39="高",T$4*高係数,IF($P39="中",T$4*中係数,IF($P39="低",T$4*低係数, IF($P39="特低",T$4*特低係数, 0))))), IF($P39="特高", T$4*特高係数,IF($P39="高",T$4*高係数,IF($P39="中",T$4*中係数,IF($P39="低",T$4*低係数, IF($P39="特低",T$4*特低係数, 0)))))),0.125) -> 36.9 | U39: =SUM(R39:T39) -> 85.05 | V39: =U39/20 -> 4.2525
D40: 商品入荷エラーリスト | F40: 45761 | G40: 45821 | H40: 12 | I40: 6 | J40: =SUM(H40:I40) -> 18 | K40: 20 | L40: =K40*0.8 -> 16 | M40: =SUM(K40:L40) -> 36 | N40: 帳票 | P40: 特高 | Q40: 新規 | R40: =CEILING(IF($Q40="新規", IF($P40="特高", R$4*特高係数,IF($P40="高",R$4*高係数,IF($P40="中",R$4*中係数,IF($P40="低",R$4*低係数, IF($P40="特低",R$4*特低係数, 0))))), IF($P40="特高", R$4*特高係数,IF($P40="高",R$4*高係数,IF($P40="中",R$4*中係数,IF($P40="低",R$4*低係数, IF($P40="特低",R$4*特低係数, 0)))))),0.125) -> 1.375 | S40: =CEILING(IF($Q40="新規", IF($P40="特高", S$4*特高係数,IF($P40="高",S$4*高係数,IF($P40="中",S$4*中係数,IF($P40="低",S$4*低係数, IF($P40="特低",S$4*特低係数, 0))))), IF($P40="特高", S$4*特高係数,IF($P40="高",S$4*高係数,IF($P40="中",S$4*中係数,IF($P40="低",S$4*低係数, IF($P40="特低",S$4*特低係数, 0)))))),0.125) -> 25.375 | T40: =CEILING(IF($Q40="新規", IF($P40="特高", T$4*特高係数,IF($P40="高",T$4*高係数,IF($P40="中",T$4*中係数,IF($P40="低",T$4*低係数, IF($P40="特低",T$4*特低係数, 0))))), IF($P40="特高", T$4*特高係数,IF($P40="高",T$4*高係数,IF($P40="中",T$4*中係数,IF($P40="低",T$4*低係数, IF($P40="特低",T$4*特低係数, 0)))))),0.125) -> 20.5 | U40: =SUM(R40:T40) -> 47.25 | V40: =U40/20 -> 2.3625
D41: 複合伝票（LPG) | F41: 45761 | G41: 45821 | H41: 10 | I41: 6 | J41: =SUM(H41:I41) -> 16 | L41: =K41*0.8 -> 0 | M41: =SUM(K41:L41) -> 0 | N41: 帳票 | P41: 特高 | Q41: 新規 | R41: =CEILING(IF($Q41="新規", IF($P41="特高", R$4*特高係数,IF($P41="高",R$4*高係数,IF($P41="中",R$4*中係数,IF($P41="低",R$4*低係数, IF($P41="特低",R$4*特低係数, 0))))), IF($P41="特高", R$4*特高係数,IF($P41="高",R$4*高係数,IF($P41="中",R$4*中係数,IF($P41="低",R$4*低係数, IF($P41="特低",R$4*特低係数, 0)))))),0.125) -> 1.375 | S41: =CEILING(IF($Q41="新規", IF($P41="特高", S$4*特高係数,IF($P41="高",S$4*高係数,IF($P41="中",S$4*中係数,IF($P41="低",S$4*低係数, IF($P41="特低",S$4*特低係数, 0))))), IF($P41="特高", S$4*特高係数,IF($P41="高",S$4*高係数,IF($P41="中",S$4*中係数,IF($P41="低",S$4*低係数, IF($P41="特低",S$4*特低係数, 0)))))),0.125) -> 25.375 | T41: =CEILING(IF($Q41="新規", IF($P41="特高", T$4*特高係数,IF($P41="高",T$4*高係数,IF($P41="中",T$4*中係数,IF($P41="低",T$4*低係数, IF($P41="特低",T$4*特低係数, 0))))), IF($P41="特高", T$4*特高係数,IF($P41="高",T$4*高係数,IF($P41="中",T$4*中係数,IF($P41="低",T$4*低係数, IF($P41="特低",T$4*特低係数, 0)))))),0.125) -> 20.5 | U41: =SUM(R41:T41) -> 47.25 | V41: =U41/20 -> 2.3625
D42: 在庫受払日報 | F42: 45761 | G42: 45821 | H42: 8 | I42: 4 | J42: =SUM(H42:I42) -> 12 | K42: 12 | L42: =K42*0.8 -> 9.6 | M42: =SUM(K42:L42) -> 21.6 | N42: 帳票 | P42: 高 | Q42: 新規 | R42: =CEILING(IF($Q42="新規", IF($P42="特高", R$4*特高係数,IF($P42="高",R$4*高係数,IF($P42="中",R$4*中係数,IF($P42="低",R$4*低係数, IF($P42="特低",R$4*特低係数, 0))))), IF($P42="特高", R$4*特高係数,IF($P42="高",R$4*高係数,IF($P42="中",R$4*中係数,IF($P42="低",R$4*低係数, IF($P42="特低",R$4*特低係数, 0)))))),0.125) -> 1 | S42: =CEILING(IF($Q42="新規", IF($P42="特高", S$4*特高係数,IF($P42="高",S$4*高係数,IF($P42="中",S$4*中係数,IF($P42="低",S$4*低係数, IF($P42="特低",S$4*特低係数, 0))))), IF($P42="特高", S$4*特高係数,IF($P42="高",S$4*高係数,IF($P42="中",S$4*中係数,IF($P42="低",S$4*低係数, IF($P42="特低",S$4*特低係数, 0)))))),0.125) -> 19.5 | T42: =CEILING(IF($Q42="新規", IF($P42="特高", T$4*特高係数,IF($P42="高",T$4*高係数,IF($P42="中",T$4*中係数,IF($P42="低",T$4*低係数, IF($P42="特低",T$4*特低係数, 0))))), IF($P42="特高", T$4*特高係数,IF($P42="高",T$4*高係数,IF($P42="中",T$4*中係数,IF($P42="低",T$4*低係数, IF($P42="特低",T$4*特低係数, 0)))))),0.125) -> 15.75 | U42: =SUM(R42:T42) -> 36.25 | V42: =U42/20 -> 1.8125
D43: 在庫受払月報 | F43: 45761 | G43: 45821 | H43: 8 | I43: 4 | J43: =SUM(H43:I43) -> 12 | K43: 20 | L43: =K43*0.8 -> 16 | M43: =SUM(K43:L43) -> 36 | N43: 帳票 | P43: 高 | Q43: 新規 | R43: =CEILING(IF($Q43="新規", IF($P43="特高", R$4*特高係数,IF($P43="高",R$4*高係数,IF($P43="中",R$4*中係数,IF($P43="低",R$4*低係数, IF($P43="特低",R$4*特低係数, 0))))), IF($P43="特高", R$4*特高係数,IF($P43="高",R$4*高係数,IF($P43="中",R$4*中係数,IF($P43="低",R$4*低係数, IF($P43="特低",R$4*特低係数, 0)))))),0.125) -> 1 | S43: =CEILING(IF($Q43="新規", IF($P43="特高", S$4*特高係数,IF($P43="高",S$4*高係数,IF($P43="中",S$4*中係数,IF($P43="低",S$4*低係数, IF($P43="特低",S$4*特低係数, 0))))), IF($P43="特高", S$4*特高係数,IF($P43="高",S$4*高係数,IF($P43="中",S$4*中係数,IF($P43="低",S$4*低係数, IF($P43="特低",S$4*特低係数, 0)))))),0.125) -> 19.5 | T43: =CEILING(IF($Q43="新規", IF($P43="特高", T$4*特高係数,IF($P43="高",T$4*高係数,IF($P43="中",T$4*中係数,IF($P43="低",T$4*低係数, IF($P43="特低",T$4*特低係数, 0))))), IF($P43="特高", T$4*特高係数,IF($P43="高",T$4*高係数,IF($P43="中",T$4*中係数,IF($P43="低",T$4*低係数, IF($P43="特低",T$4*特低係数, 0)))))),0.125) -> 15.75 | U43: =SUM(R43:T43) -> 36.25 | V43: =U43/20 -> 1.8125
A44: =ROW()-4 -> 40 | C44: 全国版SS更新 | D44: ＰＯＳ給油所マスタ更新 | F44: 45761 | G44: 45777 | H44: 0 | I44: 0 | J44: =SUM(H44:I44) -> 0 | K44: 0 | L44: 0 | M44: =SUM(K44:L44) -> 0 | R44: =CEILING(IF($Q44="新規", IF($P44="特高", R$4*特高係数,IF($P44="高",R$4*高係数,IF($P44="中",R$4*中係数,IF($P44="低",R$4*低係数, IF($P44="特低",R$4*特低係数, 0))))), IF($P44="特高", R$4*特高係数,IF($P44="高",R$4*高係数,IF($P44="中",R$4*中係数,IF($P44="低",R$4*低係数, IF($P44="特低",R$4*特低係数, 0)))))),0.125) -> 0 | S44: =CEILING(IF($Q44="新規", IF($P44="特高", S$4*特高係数,IF($P44="高",S$4*高係数,IF($P44="中",S$4*中係数,IF($P44="低",S$4*低係数, IF($P44="特低",S$4*特低係数, 0))))), IF($P44="特高", S$4*特高係数,IF($P44="高",S$4*高係数,IF($P44="中",S$4*中係数,IF($P44="低",S$4*低係数, IF($P44="特低",S$4*特低係数, 0)))))),0.125) -> 0 | T44: =CEILING(IF($Q44="新規", IF($P44="特高", T$4*特高係数,IF($P44="高",T$4*高係数,IF($P44="中",T$4*中係数,IF($P44="低",T$4*低係数, IF($P44="特低",T$4*特低係数, 0))))), IF($P44="特高", T$4*特高係数,IF($P44="高",T$4*高係数,IF($P44="中",T$4*中係数,IF($P44="低",T$4*低係数, IF($P44="特低",T$4*特低係数, 0)))))),0.125) -> 0 | U44: =SUM(R44:T44) -> 0 | V44: =U44/20 -> 0
D45: CTC向け全国版SSﾏｽﾀ | F45: 45761 | G45: 45777 | H45: 10 | I45: 6 | J45: =SUM(H45:I45) -> 16 | K45: 32 | L45: =K45*0.8 -> 25.6 | M45: =SUM(K45:L45) -> 57.6 | P45: 特高 | Q45: 新規 | R45: =CEILING(IF($Q45="新規", IF($P45="特高", R$4*特高係数,IF($P45="高",R$4*高係数,IF($P45="中",R$4*中係数,IF($P45="低",R$4*低係数, IF($P45="特低",R$4*特低係数, 0))))), IF($P45="特高", R$4*特高係数,IF($P45="高",R$4*高係数,IF($P45="中",R$4*中係数,IF($P45="低",R$4*低係数, IF($P45="特低",R$4*特低係数, 0)))))),0.125) -> 1.375 | S45: =CEILING(IF($Q45="新規", IF($P45="特高", S$4*特高係数,IF($P45="高",S$4*高係数,IF($P45="中",S$4*中係数,IF($P45="低",S$4*低係数, IF($P45="特低",S$4*特低係数, 0))))), IF($P45="特高", S$4*特高係数,IF($P45="高",S$4*高係数,IF($P45="中",S$4*中係数,IF($P45="低",S$4*低係数, IF($P45="特低",S$4*特低係数, 0)))))),0.125) -> 25.375 | T45: =CEILING(IF($Q45="新規", IF($P45="特高", T$4*特高係数,IF($P45="高",T$4*高係数,IF($P45="中",T$4*中係数,IF($P45="低",T$4*低係数, IF($P45="特低",T$4*特低係数, 0))))), IF($P45="特高", T$4*特高係数,IF($P45="高",T$4*高係数,IF($P45="中",T$4*中係数,IF($P45="低",T$4*低係数, IF($P45="特低",T$4*特低係数, 0)))))),0.125) -> 20.5 | U45: =SUM(R45:T45) -> 47.25 | V45: =U45/20 -> 2.3625
D46: 全国版SSﾏｽﾀ差分 | F46: 45761 | G46: 45777 | H46: 8 | I46: 4 | J46: =SUM(H46:I46) -> 12 | L46: =K46*0.8 -> 0 | M46: =SUM(K46:L46) -> 0 | P46: 高 | Q46: 新規 | R46: =CEILING(IF($Q46="新規", IF($P46="特高", R$4*特高係数,IF($P46="高",R$4*高係数,IF($P46="中",R$4*中係数,IF($P46="低",R$4*低係数, IF($P46="特低",R$4*特低係数, 0))))), IF($P46="特高", R$4*特高係数,IF($P46="高",R$4*高係数,IF($P46="中",R$4*中係数,IF($P46="低",R$4*低係数, IF($P46="特低",R$4*特低係数, 0)))))),0.125) -> 1 | S46: =CEILING(IF($Q46="新規", IF($P46="特高", S$4*特高係数,IF($P46="高",S$4*高係数,IF($P46="中",S$4*中係数,IF($P46="低",S$4*低係数, IF($P46="特低",S$4*特低係数, 0))))), IF($P46="特高", S$4*特高係数,IF($P46="高",S$4*高係数,IF($P46="中",S$4*中係数,IF($P46="低",S$4*低係数, IF($P46="特低",S$4*特低係数, 0)))))),0.125) -> 19.5 | T46: =CEILING(IF($Q46="新規", IF($P46="特高", T$4*特高係数,IF($P46="高",T$4*高係数,IF($P46="中",T$4*中係数,IF($P46="低",T$4*低係数, IF($P46="特低",T$4*特低係数, 0))))), IF($P46="特高", T$4*特高係数,IF($P46="高",T$4*高係数,IF($P46="中",T$4*中係数,IF($P46="低",T$4*低係数, IF($P46="特低",T$4*特低係数, 0)))))),0.125) -> 15.75 | U46: =SUM(R46:T46) -> 36.25 | V46: =U46/20 -> 1.8125
D47: SS台帳、給油所マスタ更新 | F47: 45761 | G47: 45777 | H47: 0 | I47: 0 | J47: =SUM(H47:I47) -> 0 | K47: 0 | L47: 0 | M47: =SUM(K47:L47) -> 0 | R47: =CEILING(IF($Q47="新規", IF($P47="特高", R$4*特高係数,IF($P47="高",R$4*高係数,IF($P47="中",R$4*中係数,IF($P47="低",R$4*低係数, IF($P47="特低",R$4*特低係数, 0))))), IF($P47="特高", R$4*特高係数,IF($P47="高",R$4*高係数,IF($P47="中",R$4*中係数,IF($P47="低",R$4*低係数, IF($P47="特低",R$4*特低係数, 0)))))),0.125) -> 0 | S47: =CEILING(IF($Q47="新規", IF($P47="特高", S$4*特高係数,IF($P47="高",S$4*高係数,IF($P47="中",S$4*中係数,IF($P47="低",S$4*低係数, IF($P47="特低",S$4*特低係数, 0))))), IF($P47="特高", S$4*特高係数,IF($P47="高",S$4*高係数,IF($P47="中",S$4*中係数,IF($P47="低",S$4*低係数, IF($P47="特低",S$4*特低係数, 0)))))),0.125) -> 0 | T47: =CEILING(IF($Q47="新規", IF($P47="特高", T$4*特高係数,IF($P47="高",T$4*高係数,IF($P47="中",T$4*中係数,IF($P47="低",T$4*低係数, IF($P47="特低",T$4*特低係数, 0))))), IF($P47="特高", T$4*特高係数,IF($P47="高",T$4*高係数,IF($P47="中",T$4*中係数,IF($P47="低",T$4*低係数, IF($P47="特低",T$4*特低係数, 0)))))),0.125) -> 0 | U47: =SUM(R47:T47) -> 0 | V47: =U47/20 -> 0
A48: =ROW()-4 -> 44 | C48: 企業情報 | D48: 企業情報検索 | F48: 45778 | G48: 45784 | H48: 8 | I48: 4 | J48: =SUM(H48:I48) -> 12 | K48: 16 | L48: =K48*0.8 -> 12.8 | M48: =SUM(K48:L48) -> 28.8 | N48: 外部接続 | P48: 高 | Q48: 新規 | R48: =CEILING(IF($Q48="新規", IF($P48="特高", R$4*特高係数,IF($P48="高",R$4*高係数,IF($P48="中",R$4*中係数,IF($P48="低",R$4*低係数, IF($P48="特低",R$4*特低係数, 0))))), IF($P48="特高", R$4*特高係数,IF($P48="高",R$4*高係数,IF($P48="中",R$4*中係数,IF($P48="低",R$4*低係数, IF($P48="特低",R$4*特低係数, 0)))))),0.125) -> 1 | S48: =CEILING(IF($Q48="新規", IF($P48="特高", S$4*特高係数,IF($P48="高",S$4*高係数,IF($P48="中",S$4*中係数,IF($P48="低",S$4*低係数, IF($P48="特低",S$4*特低係数, 0))))), IF($P48="特高", S$4*特高係数,IF($P48="高",S$4*高係数,IF($P48="中",S$4*中係数,IF($P48="低",S$4*低係数, IF($P48="特低",S$4*特低係数, 0)))))),0.125) -> 19.5 | T48: =CEILING(IF($Q48="新規", IF($P48="特高", T$4*特高係数,IF($P48="高",T$4*高係数,IF($P48="中",T$4*中係数,IF($P48="低",T$4*低係数, IF($P48="特低",T$4*特低係数, 0))))), IF($P48="特高", T$4*特高係数,IF($P48="高",T$4*高係数,IF($P48="中",T$4*中係数,IF($P48="低",T$4*低係数, IF($P48="特低",T$4*特低係数, 0)))))),0.125) -> 15.75 | U48: =SUM(R48:T48) -> 36.25 | V48: =U48/20 -> 1.8125
A49: =ROW()-4 -> 45 | C49: 処理用SSマスタ作成 | D49: 新SS台帳から処理用SS台帳の作成（バッチ処理） | F49: 45761 | G49: 45779 | H49: 12 | I49: 6 | J49: =SUM(H49:I49) -> 18 | L49: =K49*0.8 -> 0 | M49: =SUM(K49:L49) -> 0 | P49: 特高 | Q49: 新規 | R49: =CEILING(IF($Q49="新規", IF($P49="特高", R$4*特高係数,IF($P49="高",R$4*高係数,IF($P49="中",R$4*中係数,IF($P49="低",R$4*低係数, IF($P49="特低",R$4*特低係数, 0))))), IF($P49="特高", R$4*特高係数,IF($P49="高",R$4*高係数,IF($P49="中",R$4*中係数,IF($P49="低",R$4*低係数, IF($P49="特低",R$4*特低係数, 0)))))),0.125) -> 1.375 | S49: =CEILING(IF($Q49="新規", IF($P49="特高", S$4*特高係数,IF($P49="高",S$4*高係数,IF($P49="中",S$4*中係数,IF($P49="低",S$4*低係数, IF($P49="特低",S$4*特低係数, 0))))), IF($P49="特高", S$4*特高係数,IF($P49="高",S$4*高係数,IF($P49="中",S$4*中係数,IF($P49="低",S$4*低係数, IF($P49="特低",S$4*特低係数, 0)))))),0.125) -> 25.375 | T49: =CEILING(IF($Q49="新規", IF($P49="特高", T$4*特高係数,IF($P49="高",T$4*高係数,IF($P49="中",T$4*中係数,IF($P49="低",T$4*低係数, IF($P49="特低",T$4*特低係数, 0))))), IF($P49="特高", T$4*特高係数,IF($P49="高",T$4*高係数,IF($P49="中",T$4*中係数,IF($P49="低",T$4*低係数, IF($P49="特低",T$4*特低係数, 0)))))),0.125) -> 20.5 | U49: =SUM(R49:T49) -> 47.25 | V49: =U49/20 -> 2.3625
A50: 合計（人日） | R50: =SUM(R5:R49) -> 33.3 | S50: =SUM(S5:S49) -> 663.275 | T50: =SUM(T5:T49) -> 536.575 | U50: =SUM(R50:T50) -> 1233.15
A51: 合計（人月） | R51: =R50/20 -> 1.665 | S51: =S50/20 -> 33.16375 | T51: =T50/20 -> 26.82875 | V51: =SUM(R51:T51) -> 61.6575
Q52: 作業金額 | R52: =ROUNDUP(R51, 1) * 1000000 -> 1700000 | S52: =ROUNDUP(S51, 1) * 1000000 -> 33200000 | T52: =ROUNDUP(T51, 1) * 1000000 -> 26900000 | V52: =SUM(R52:T52) -> 61800000
Q53: 管理 + プレ工数 | R53: =ROUNDUP(SUM(R51:R51)*0.2,1) -> 0.4 | S53: =ROUNDUP(SUM(S51)*0.2,1) -> 6.7 | T53: =ROUNDUP(SUM(T51)*0.2,1) -> 5.4 | V53: =SUM(R53:T53) -> 12.5
Q54: 管理 + プレ工数 金額 | R54: =R53 * 1400000 -> 560000 | S54: =S53 * 1400000 -> 9380000 | T54: =T53 * 1400000 -> 7560000 | V54: =SUM(R54:T54) -> 17500000
Q55: 合計 | R55: =R52 + R54 -> 2260000 | S55: =S52 + S54 -> 42580000 | T55: =T52 + T54 -> 34460000 | V55: =SUM(R55:T55) -> 79300000
A56: 総工数 | U56: =SUM(U50:U55) -> 1233.15 | V56: =V51+V53 -> 74.1575

Sheet 概算
R2: JCC様 見積り工数 | S2: 2倍 | T2: 2.5倍 | U2: 3倍
A3: 合計（人月） | R3: 19.7 | S3: =R3*2 -> 39.4 | T3: =R3*2.5 -> 49.25 | U3: =R3*3 -> 59.1
Q4: 作業金額 | R4: =ROUNDUP(R3, 1) * 1200000 -> 23640000 | S4: =ROUNDUP(S3, 1) * 1200000 -> 47280000 | T4: =ROUNDUP(T3, 1) * 1200000 -> 59160000 | U4: =ROUNDUP(U3, 1) * 1200000 -> 70920000
Q5: 管理 + プレ工数 | R5: =ROUNDUP(SUM(R3:R3)*0.2,1) -> 4 | S5: =ROUNDUP(SUM(S3:S3)*0.2,1) -> 7.9 | T5: =ROUNDUP(SUM(T3:T3)*0.2,1) -> 9.9 | U5: =ROUNDUP(SUM(U3)*0.2,1) -> 11.9
Q6: 管理 + プレ工数 金額 | R6: =R5 * 1400000 -> 5600000 | S6: =S5 * 1400000 -> 11060000 | T6: =T5 * 1400000 -> 13860000 | U6: =U5 * 1400000 -> 16660000
Q7: 合計 | R7: =R4 + R6 -> 29240000 | S7: =S4 + S6 -> 58340000 | T7: =T4 + T6 -> 73020000 | U7: =U4 + U6 -> 87580000
P10: 60人月の場合の要員
Q11: 5月 | R11: 6月 | S11: 7月 | T11: 8月 | U11: 合計
P12: A | Q12: 0.5 | R12: 0.5 | S12: 0.5 | T12: 0.5 | U12: =SUM(Q12:T12) -> 2 | V12: =SUM(U12:U13) -> 4
P13: B | Q13: 0.5 | R13: 0.5 | S13: 0.5 | T13: 0.5 | U13: =SUM(Q13:T13) -> 2
P14: 要員1 | Q14: 1 | R14: 1 | S14: 1 | T14: 1 | U14: =SUM(Q14:T14) -> 4 | V14: =SUM(U14:U28) -> 60
P15: 要員2 | Q15: 1 | R15: 1 | S15: 1 | T15: 1 | U15: =SUM(Q15:T15) -> 4
P16: 要員3 | Q16: 1 | R16: 1 | S16: 1 | T16: 1 | U16: =SUM(Q16:T16) -> 4
P17: 要員4 | Q17: 1 | R17: 1 | S17: 1 | T17: 1 | U17: =SUM(Q17:T17) -> 4
P18: 要員5 | Q18: 1 | R18: 1 | S18: 1 | T18: 1 | U18: =SUM(Q18:T18) -> 4
P19: 要員6 | Q19: 1 | R19: 1 | S19: 1 | T19: 1 | U19: =SUM(Q19:T19) -> 4
P20: 要員7 | Q20: 1 | R20: 1 | S20: 1 | T20: 1 | U20: =SUM(Q20:T20) -> 4
P21: 要員8 | Q21: 1 | R21: 1 | S21: 1 | T21: 1 | U21: =SUM(Q21:T21) -> 4
P22: 要員9 | Q22: 1 | R22: 1 | S22: 1 | T22: 1 | U22: =SUM(Q22:T22) -> 4
P23: 要員10 | Q23: 1 | R23: 1 | S23: 1 | T23: 1 | U23: =SUM(Q23:T23) -> 4
P24: 要員11 | Q24: 1 | R24: 1 | S24: 1 | T24: 1 | U24: =SUM(Q24:T24) -> 4
P25: 要員12 | Q25: 1 | R25: 1 | S25: 1 | T25: 1 | U25: =SUM(Q25:T25) -> 4
P26: 要員13 | Q26: 1 | R26: 1 | S26: 1 | T26: 1 | U26: =SUM(Q26:T26) -> 4
... P28: 要員15 | Q28: 1 | R28: 1 | S28: 1 | T28: 1 | U28: =SUM(Q28:T28) -> 4

Sheet 御見積(画面・機能) (1.5倍)
A2: № | B2: システム名 | C2: 機能名 | F2: JCC詳細設計 | H2: JCC見積 | K2: エグゼ見積 | N2: 分類 | O2: 機能画面説明 | P2: 難易度 | Q2: 新規 改修 | R2: 工程別工数（人日） | U2: 合計 （人日） | V2: 合計 （人月） | W2: 備考
C3: 大項目 | D3: 中項目 | E3: 小項目 | F3: 開始 | G3: 終了 | H3: 製造単体工数 | I3: 結合試験工数 | J3: 合計 | K3: 製造単体工数 | L3: 結合試験工数 | M3: 合計 | R3: 概要把握 設計レビュー | S3: 開発/単体テスト | T3: 結合テスト
A4: 基準工数 | R4: 0.5 | S4: =1.5*1.2*積算基準!F58 -> 5.85 | T4: =1.5*1.2*積算基準!G58 -> 4.725
A5: =ROW()-4 -> 1 | C5: 共通 | D5: アーキテクチャ | N5: 機能 | O5: システムアーキテクチャを構築 | P5: 低 | Q5: 新規 | S5: =CEILING(IF($Q5="新規", IF($P5="特高", S$4*特高係数,IF($P5="高",S$4*高係数,IF($P5="中",S$4*中係数,IF($P5="低",S$4*低係数, IF($P5="特低",S$4*特低係数, 0))))), IF($P5="特高", S$4*特高係数,IF($P5="高",S$4*高係数,IF($P5="中",S$4*中係数,IF($P5="低",S$4*低係数, IF($P5="特低",S$4*特低係数, 0)))))),0.125) -> 4.125 | T5: =CEILING(IF($Q5="新規", IF($P5="特高", T$4*特高係数,IF($P5="高",T$4*高係数,IF($P5="中",T$4*中係数,IF($P5="低",T$4*低係数, IF($P5="特低",T$4*特低係数, 0))))), IF($P5="特高", T$4*特高係数,IF($P5="高",T$4*高係数,IF($P5="中",T$4*中係数,IF($P5="低",T$4*低係数, IF($P5="特低",T$4*特低係数, 0)))))),0.125) -> 3.375 | U5: =SUM(R5:T5) -> 7.5 | V5: =U5/20 -> 0.375
D6: 開発環境・把握・構築 | P6: 低 | Q6: 新規 | S6: =CEILING(IF($Q6="新規", IF($P6="特高", S$4*特高係数,IF($P6="高",S$4*高係数,IF($P6="中",S$4*中係数,IF($P6="低",S$4*低係数, IF($P6="特低",S$4*特低係数, 0))))), IF($P6="特高", S$4*特高係数,IF($P6="高",S$4*高係数,IF($P6="中",S$4*中係数,IF($P6="低",S$4*低係数, IF($P6="特低",S$4*特低係数, 0)))))),0.125) -> 4.125 | T6: =CEILING(IF($Q6="新規", IF($P6="特高", T$4*特高係数,IF($P6="高",T$4*高係数,IF($P6="中",T$4*中係数,IF($P6="低",T$4*低係数, IF($P6="特低",T$4*特低係数, 0))))), IF($P6="特高", T$4*特高係数,IF($P6="高",T$4*高係数,IF($P6="中",T$4*中係数,IF($P6="低",T$4*低係数, IF($P6="特低",T$4*特低係数, 0)))))),0.125) -> 3.375 | U6: =SUM(R6:T6) -> 7.5 | V6: =U6/20 -> 0.375
D7: Azure環境構築（データレイク含む） | P7: 低 | Q7: 新規 | S7: =CEILING(IF($Q7="新規", IF($P7="特高", S$4*特高係数,IF($P7="高",S$4*高係数,IF($P7="中",S$4*中係数,IF($P7="低",S$4*低係数, IF($P7="特低",S$4*特低係数, 0))))), IF($P7="特高", S$4*特高係数,IF($P7="高",S$4*高係数,IF($P7="中",S$4*中係数,IF($P7="低",S$4*低係数, IF($P7="特低",S$4*特低係数, 0)))))),0.125) -> 4.125 | T7: =CEILING(IF($Q7="新規", IF($P7="特高", T$4*特高係数,IF($P7="高",T$4*高係数,IF($P7="中",T$4*中係数,IF($P7="低",T$4*低係数, IF($P7="特低",T$4*特低係数, 0))))), IF($P7="特高", T$4*特高係数,IF($P7="高",T$4*高係数,IF($P7="中",T$4*中係数,IF($P7="低",T$4*低係数, IF($P7="特低",T$4*特低係数, 0)))))),0.125) -> 3.375 | U7: =SUM(R7:T7) -> 7.5 | V7: =U7/20 -> 0.375
D8: 結合テスト計画作成 | P8: 低 | Q8: 新規 | S8: =CEILING(IF($Q8="新規", IF($P8="特高", S$4*特高係数,IF($P8="高",S$4*高係数,IF($P8="中",S$4*中係数,IF($P8="低",S$4*低係数, IF($P8="特低",S$4*特低係数, 0))))), IF($P8="特高", S$4*特高係数,IF($P8="高",S$4*高係数,IF($P8="中",S$4*中係数,IF($P8="低",S$4*低係数, IF($P8="特低",S$4*特低係数, 0)))))),0.125) -> 4.125 | T8: =CEILING(IF($Q8="新規", IF($P8="特高", T$4*特高係数,IF($P8="高",T$4*高係数,IF($P8="中",T$4*中係数,IF($P8="低",T$4*低係数, IF($P8="特低",T$4*特低係数, 0))))), IF($P8="特高", T$4*特高係数,IF($P8="高",T$4*高係数,IF($P8="中",T$4*中係数,IF($P8="低",T$4*低係数, IF($P8="特低",T$4*特低係数, 0)))))),0.125) -> 3.375 | U8: =SUM(R8:T8) -> 7.5 | V8: =U8/20 -> 0.375
D9: A-AUTO設定 | P9: 低 | Q9: 新規 | S9: =CEILING(IF($Q9="新規", IF($P9="特高", S$4*特高係数,IF($P9="高",S$4*高係数,IF($P9="中",S$4*中係数,IF($P9="低",S$4*低係数, IF($P9="特低",S$4*特低係数, 0))))), IF($P9="特高", S$4*特高係数,IF($P9="高",S$4*高係数,IF($P9="中",S$4*中係数,IF($P9="低",S$4*低係数, IF($P9="特低",S$4*特低係数, 0)))))),0.125) -> 4.125 | T9: =CEILING(IF($Q9="新規", IF($P9="特高", T$4*特高係数,IF($P9="高",T$4*高係数,IF($P9="中",T$4*中係数,IF($P9="低",T$4*低係数, IF($P9="特低",T$4*特低係数, 0))))), IF($P9="特高", T$4*特高係数,IF($P9="高",T$4*高係数,IF($P9="中",T$4*中係数,IF($P9="低",T$4*低係数, IF($P9="特低",T$4*特低係数, 0)))))),0.125) -> 3.375 | U9: =SUM(R9:T9) -> 7.5 | V9: =U9/20 -> 0.375
A10: =ROW()-4 -> 6 | C10: セルイン | D10: セルインTBL | F10: 45754 | G10: 45838 | H10: 8 | I10: 4 | J10: =SUM(H10:I10) -> 12 | L10: =K10*0.8 -> 0 | M10: =SUM(K10:L10) -> 0 | N10: DB | P10: 高 | Q10: 新規 | R10: =CEILING(IF($Q10="新規", IF($P10="特高", R$4*特高係数,IF($P10="高",R$4*高係数,IF($P10="中",R$4*中係数,IF($P10="低",R$4*低係数, IF($P10="特低",R$4*特低係数, 0))))), IF($P10="特高", R$4*特高係数,IF($P10="高",R$4*高係数,IF($P10="中",R$4*中係数,IF($P10="低",R$4*低係数, IF($P10="特低",R$4*特低係数, 0)))))),0.125) -> 1 | S10: =CEILING(IF($Q10="新規", IF($P10="特高", S$4*特高係数,IF($P10="高",S$4*高係数,IF($P10="中",S$4*中係数,IF($P10="低",S$4*低係数, IF($P10="特低",S$4*特低係数, 0))))), IF($P10="特高", S$4*特高係数,IF($P10="高",S$4*高係数,IF($P10="中",S$4*中係数,IF($P10="低",S$4*低係数, IF($P10="特低",S$4*特低係数, 0)))))),0.125) -> 11.75 | T10: =CEILING(IF($Q10="新規", IF($P10="特高", T$4*特高係数,IF($P10="高",T$4*高係数,IF($P10="中",T$4*中係数,IF($P10="低",T$4*低係数, IF($P10="特低",T$4*特低係数, 0))))), IF($P10="特高", T$4*特高係数,IF($P10="高",T$4*高係数,IF($P10="中",T$4*中係数,IF($P10="低",T$4*低係数, IF($P10="特低",T$4*特低係数, 0)))))),0.125) -> 9.5 | U10: =SUM(R10:T10) -> 22.25 | V10: =U10/20 -> 1.1125
D11: 売上原価伝送データ | F11: 45754 | G11: 45838 | H11: 8 | I11: 4 | J11: =SUM(H11:I11) -> 12 | L11: =K11*0.8 -> 0 | M11: =SUM(K11:L11) -> 0 | N11: BO | P11: 高 | Q11: 新規 | R11: =CEILING(IF($Q11="新規", IF($P11="特高", R$4*特高係数,IF($P11="高",R$4*高係数,IF($P11="中",R$4*中係数,IF($P11="低",R$4*低係数, IF($P11="特低",R$4*特低係数, 0))))), IF($P11="特高", R$4*特高係数,IF($P11="高",R$4*高係数,IF($P11="中",R$4*中係数,IF($P11="低",R$4*低係数, IF($P11="特低",R$4*特低係数, 0)))))),0.125) -> 1 | S11: =CEILING(IF($Q11="新規", IF($P11="特高", S$4*特高係数,IF($P11="高",S$4*高係数,IF($P11="中",S$4*中係数,IF($P11="低",S$4*低係数, IF($P11="特低",S$4*特低係数, 0))))), IF($P11="特高", S$4*特高係数,IF($P11="高",S$4*高係数,IF($P11="中",S$4*中係数,IF($P11="低",S$4*低係数, IF($P11="特低",S$4*特低係数, 0)))))),0.125) -> 11.75 | T11: =CEILING(IF($Q11="新規", IF($P11="特高", T$4*特高係数,IF($P11="高",T$4*高係数,IF($P11="中",T$4*中係数,IF($P11="低",T$4*低係数, IF($P11="特低",T$4*特低係数, 0))))), IF($P11="特高", T$4*特高係数,IF($P11="高",T$4*高係数,IF($P11="中",T$4*中係数,IF($P11="低",T$4*低係数, IF($P11="特低",T$4*特低係数, 0)))))),0.125) -> 9.5 | U11: =SUM(R11:T11) -> 22.25 | V11: =U11/20 -> 1.1125
D12: 販売実績数量価格推移表 1 | F12: 45754 | G12: 45838 | H12: 18 | I12: 9 | J12: =SUM(H12:I12) -> 27 | L12: =K12*0.8 -> 0 | M12: =SUM(K12:L12) -> 0 | N12: 帳票 | P12: 高 | Q12: 新規 | R12: =CEILING(IF($Q12="新規", IF($P12="特高", R$4*特高係数,IF($P12="高",R$4*高係数,IF($P12="中",R$4*中係数,IF($P12="低",R$4*低係数, IF($P12="特低",R$4*特低係数, 0))))), IF($P12="特高", R$4*特高係数,IF($P12="高",R$4*高係数,IF($P12="中",R$4*中係数,IF($P12="低",R$4*低係数, IF($P12="特低",R$4*特低係数, 0)))))),0.125) -> 1 | S12: =CEILING(IF($Q12="新規", IF($P12="特高", S$4*特高係数,IF($P12="高",S$4*高係数,IF($P12="中",S$4*中係数,IF($P12="低",S$4*低係数, IF($P12="特低",S$4*特低係数, 0))))), IF($P12="特高", S$4*特高係数,IF($P12="高",S$4*高係数,IF($P12="中",S$4*中係数,IF($P12="低",S$4*低係数, IF($P12="特低",S$4*特低係数, 0)))))),0.125) -> 11.75 | T12: =CEILING(IF($Q12="新規", IF($P12="特高", T$4*特高係数,IF($P12="高",T$4*高係数,IF($P12="中",T$4*中係数,IF($P12="低",T$4*低係数, IF($P12="特低",T$4*特低係数, 0))))), IF($P12="特高", T$4*特高係数,IF($P12="高",T$4*高係数,IF($P12="中",T$4*中係数,IF($P12="低",T$4*低係数, IF($P12="特低",T$4*特低係数, 0)))))),0.125) -> 9.5 | U12: =SUM(R12:T12) -> 22.25 | V12: =U12/20 -> 1.1125
D13: 販売実績数量価格推移表 2 | F13: 45754 | G13: 45838 | J13: =SUM(H13:I13) -> 0 | L13: =K13*0.8 -> 0 | M13: =SUM(K13:L13) -> 0 | N13: 帳票 | P13: 低 | Q13: 新規 | R13: =CEILING(IF($Q13="新規", IF($P13="特高", R$4*特高係数,IF($P13="高",R$4*高係数,IF($P13="中",R$4*中係数,IF($P13="低",R$4*低係数, IF($P13="特低",R$4*特低係数, 0))))), IF($P13="特高", R$4*特高係数,IF($P13="高",R$4*高係数,IF($P13="中",R$4*中係数,IF($P13="低",R$4*低係数, IF($P13="特低",R$4*特低係数, 0)))))),0.125) -> 0.375 | S13: =CEILING(IF($Q13="新規", IF($P13="特高", S$4*特高係数,IF($P13="高",S$4*高係数,IF($P13="中",S$4*中係数,IF($P13="低",S$4*低係数, IF($P13="特低",S$4*特低係数, 0))))), IF($P13="特高", S$4*特高係数,IF($P13="高",S$4*高係数,IF($P13="中",S$4*中係数,IF($P13="低",S$4*低係数, IF($P13="特低",S$4*特低係数, 0)))))),0.125) -> 4.125 | T13: =CEILING(IF($Q13="新規", IF($P13="特高", T$4*特高係数,IF($P13="高",T$4*高係数,IF($P13="中",T$4*中係数,IF($P13="低",T$4*低係数, IF($P13="特低",T$4*特低係数, 0))))), IF($P13="特高", T$4*特高係数,IF($P13="高",T$4*高係数,IF($P13="中",T$4*中係数,IF($P13="低",T$4*低係数, IF($P13="特低",T$4*特低係数, 0)))))),0.125) -> 3.375 | U13: =SUM(R13:T13) -> 7.875 | V13: =U13/20 -> 0.39375
D14: 販売実績数量価格推移表 3 | F14: 45754 | G14: 45838 | J14: =SUM(H14:I14) -> 0 | L14: =K14*0.8 -> 0 | M14: =SUM(K14:L14) -> 0 | N14: 帳票 | P14: 低 | Q14: 新規 | R14: =CEILING(IF($Q14="新規", IF($P14="特高", R$4*特高係数,IF($P14="高",R$4*高係数,IF($P14="中",R$4*中係数,IF($P14="低",R$4*低係数, IF($P14="特低",R$4*特低係数, 0))))), IF($P14="特高", R$4*特高係数,IF($P14="高",R$4*高係数,IF($P14="中",R$4*中係数,IF($P14="低",R$4*低係数, IF($P14="特低",R$4*特低係数, 0)))))),0.125) -> 0.375 | S14: =CEILING(IF($Q14="新規", IF($P14="特高", S$4*特高係数,IF($P14="高",S$4*高係数,IF($P14="中",S$4*中係数,IF($P14="低",S$4*低係数, IF($P14="特低",S$4*特低係数, 0))))), IF($P14="特高", S$4*特高係数,IF($P14="高",S$4*高係数,IF($P14="中",S$4*中係数,IF($P14="低",S$4*低係数, IF($P14="特低",S$4*特低係数, 0)))))),0.125) -> 4.125 | T14: =CEILING(IF($Q14="新規", IF($P14="特高", T$4*特高係数,IF($P14="高",T$4*高係数,IF($P14="中",T$4*中係数,IF($P14="低",T$4*低係数, IF($P14="特低",T$4*特低係数, 0))))), IF($P14="特高", T$4*特高係数,IF($P14="高",T$4*高係数,IF($P14="中",T$4*中係数,IF($P14="低",T$4*低係数, IF($P14="特低",T$4*特低係数, 0)))))),0.125) -> 3.375 | U14: =SUM(R14:T14) -> 7.875 | V14: =U14/20 -> 0.39375
D15: 販売実績数量価格推移表 4 | F15: 45754 | G15: 45838 | J15: =SUM(H15:I15) -> 0 | L15: =K15*0.8 -> 0 | M15: =SUM(K15:L15) -> 0 | N15: 帳票 | P15: 低 | Q15: 新規 | R15: =CEILING(IF($Q15="新規", IF($P15="特高", R$4*特高係数,IF($P15="高",R$4*高係数,IF($P15="中",R$4*中係数,IF($P15="低",R$4*低係数, IF($P15="特低",R$4*特低係数, 0))))), IF($P15="特高", R$4*特高係数,IF($P15="高",R$4*高係数,IF($P15="中",R$4*中係数,IF($P15="低",R$4*低係数, IF($P15="特低",R$4*特低係数, 0)))))),0.125) -> 0.375 | S15: =CEILING(IF($Q15="新規", IF($P15="特高", S$4*特高係数,IF($P15="高",S$4*高係数,IF($P15="中",S$4*中係数,IF($P15="低",S$4*低係数, IF($P15="特低",S$4*特低係数, 0))))), IF($P15="特高", S$4*特高係数,IF($P15="高",S$4*高係数,IF($P15="中",S$4*中係数,IF($P15="低",S$4*低係数, IF($P15="特低",S$4*特低係数, 0)))))),0.125) -> 4.125 | T15: =CEILING(IF($Q15="新規", IF($P15="特高", T$4*特高係数,IF($P15="高",T$4*高係数,IF($P15="中",T$4*中係数,IF($P15="低",T$4*低係数, IF($P15="特低",T$4*特低係数, 0))))), IF($P15="特高", T$4*特高係数,IF($P15="高",T$4*高係数,IF($P15="中",T$4*中係数,IF($P15="低",T$4*低係数, IF($P15="特低",T$4*特低係数, 0)))))),0.125) -> 3.375 | U15: =SUM(R15:T15) -> 7.875 | V15: =U15/20 -> 0.39375
D16: 販売実績数量価格推移表 5 | F16: 45754 | G16: 45838 | J16: =SUM(H16:I16) -> 0 | L16: =K16*0.8 -> 0 | M16: =SUM(K16:L16) -> 0 | N16: 帳票 | P16: 低 | Q16: 新規 | R16: =CEILING(IF($Q16="新規", IF($P16="特高", R$4*特高係数,IF($P16="高",R$4*高係数,IF($P16="中",R$4*中係数,IF($P16="低",R$4*低係数, IF($P16="特低",R$4*特低係数, 0))))), IF($P16="特高", R$4*特高係数,IF($P16="高",R$4*高係数,IF($P16="中",R$4*中係数,IF($P16="低",R$4*低係数, IF($P16="特低",R$4*特低係数, 0)))))),0.125) -> 0.375 | S16: =CEILING(IF($Q16="新規", IF($P16="特高", S$4*特高係数,IF($P16="高",S$4*高係数,IF($P16="中",S$4*中係数,IF($P16="低",S$4*低係数, IF($P16="特低",S$4*特低係数, 0))))), IF($P16="特高", S$4*特高係数,IF($P16="高",S$4*高係数,IF($P16="中",S$4*中係数,IF($P16="低",S$4*低係数, IF($P16="特低",S$4*特低係数, 0)))))),0.125) -> 4.125 | T16: =CEILING(IF($Q16="新規", IF($P16="特高", T$4*特高係数,IF($P16="高",T$4*高係数,IF($P16="中",T$4*中係数,IF($P16="低",T$4*低係数, IF($P16="特低",T$4*特低係数, 0))))), IF($P16="特高", T$4*特高係数,IF($P16="高",T$4*高係数,IF($P16="中",T$4*中係数,IF($P16="低",T$4*低係数, IF($P16="特低",T$4*特低係数, 0)))))),0.125) -> 3.375 | U16: =SUM(R16:T16) -> 7.875 | V16: =U16/20 -> 0.39375
D17: セルインデータ伝送 | F17: 45754 | G17: 45838 | H17: 8 | I17: 4 | J17: =SUM(H17:I17) -> 12 | L17: =K17*0.8 -> 0 | M17: =SUM(K17:L17) -> 0 | N17: BO | P17: 高 | Q17: 新規 | R17: =CEILING(IF($Q17="新規", IF($P17="特高", R$4*特高係数,IF($P17="高",R$4*高係数,IF($P17="中",R$4*中係数,IF($P17="低",R$4*低係数, IF($P17="特低",R$4*特低係数, 0))))), IF($P17="特高", R$4*特高係数,IF($P17="高",R$4*高係数,IF($P17="中",R$4*中係数,IF($P17="低",R$4*低係数, IF($P17="特低",R$4*特低係数, 0)))))),0.125) -> 1 | S17: =CEILING(IF($Q17="新規", IF($P17="特高", S$4*特高係数,IF($P17="高",S$4*高係数,IF($P17="中",S$4*中係数,IF($P17="低",S$4*低係数, IF($P17="特低",S$4*特低係数, 0))))), IF($P17="特高", S$4*特高係数,IF($P17="高",S$4*高係数,IF($P17="中",S$4*中係数,IF($P17="低",S$4*低係数, IF($P17="特低",S$4*特低係数, 0)))))),0.125) -> 11.75 | T17: =CEILING(IF($Q17="新規", IF($P17="特高", T$4*特高係数,IF($P17="高",T$4*高係数,IF($P17="中",T$4*中係数,IF($P17="低",T$4*低係数, IF($P17="特低",T$4*特低係数, 0))))), IF($P17="特高", T$4*特高係数,IF($P17="高",T$4*高係数,IF($P17="中",T$4*中係数,IF($P17="低",T$4*低係数, IF($P17="特低",T$4*特低係数, 0)))))),0.125) -> 9.5 | U17: =SUM(R17:T17) -> 22.25 | V17: =U17/20 -> 1.1125
D18: セルイン月次TBL | F18: 45754 | G18: 45838 | H18: 0 | I18: 0 | J18: =SUM(H18:I18) -> 0 | K18: 0 | L18: 0 | M18: =SUM(K18:L18) -> 0 | N18: 内部TBL | R18: =CEILING(IF($Q18="新規", IF($P18="特高", R$4*特高係数,IF($P18="高",R$4*高係数,IF($P18="中",R$4*中係数,IF($P18="低",R$4*低係数, IF($P18="特低",R$4*特低係数, 0))))), IF($P18="特高", R$4*特高係数,IF($P18="高",R$4*高係数,IF($P18="中",R$4*中係数,IF($P18="低",R$4*低係数, IF($P18="特低",R$4*特低係数, 0)))))),0.125) -> 0 | S18: =CEILING(IF($Q18="新規", IF($P18="特高", S$4*特高係数,IF($P18="高",S$4*高係数,IF($P18="中",S$4*中係数,IF($P18="低",S$4*低係数, IF($P18="特低",S$4*特低係数, 0))))), IF($P18="特高", S$4*特高係数,IF($P18="高",S$4*高係数,IF($P18="中",S$4*中係数,IF($P18="低",S$4*低係数, IF($P18="特低",S$4*特低係数, 0)))))),0.125) -> 0 | T18: =CEILING(IF($Q18="新規", IF($P18="特高", T$4*特高係数,IF($P18="高",T$4*高係数,IF($P18="中",T$4*中係数,IF($P18="低",T$4*低係数, IF($P18="特低",T$4*特低係数, 0))))), IF($P18="特高", T$4*特高係数,IF($P18="高",T$4*高係数,IF($P18="中",T$4*中係数,IF($P18="低",T$4*低係数, IF($P18="特低",T$4*特低係数, 0)))))),0.125) -> 0 | U18: =SUM(R18:T18) -> 0 | V18: =U18/20 -> 0
A19: =ROW()-4 -> 15 | C19: セルアウト | D19: セルアウト日別過去データ伝送 | F19: 45748 | G19: 45777 | H19: 0 | I19: 0 | J19: =SUM(H19:I19) -> 0 | K19: 0 | L19: 0 | M19: =SUM(K19:L19) -> 0 | N19: BO | R19: =CEILING(IF($Q19="新規", IF($P19="特高", R$4*特高係数,IF($P19="高",R$4*高係数,IF($P19="中",R$4*中係数,IF($P19="低",R$4*低係数, IF($P19="特低",R$4*特低係数, 0))))), IF($P19="特高", R$4*特高係数,IF($P19="高",R$4*高係数,IF($P19="中",R$4*中係数,IF($P19="低",R$4*低係数, IF($P19="特低",R$4*特低係数, 0)))))),0.125) -> 0 | S19: =CEILING(IF($Q19="新規", IF($P19="特高", S$4*特高係数,IF($P19="高",S$4*高係数,IF($P19="中",S$4*中係数,IF($P19="低",S$4*低係数, IF($P19="特低",S$4*特低係数, 0))))), IF($P19="特高", S$4*特高係数,IF($P19="高",S$4*高係数,IF($P19="中",S$4*中係数,IF($P19="低",S$4*低係数, IF($P19="特低",S$4*特低係数, 0)))))),0.125) -> 0 | T19: =CEILING(IF($Q19="新規", IF($P19="特高", T$4*特高係数,IF($P19="高",T$4*高係数,IF($P19="中",T$4*中係数,IF($P19="低",T$4*低係数, IF($P19="特低",T$4*特低係数, 0))))), IF($P19="特高", T$4*特高係数,IF($P19="高",T$4*高係数,IF($P19="中",T$4*中係数,IF($P19="低",T$4*低係数, IF($P19="特低",T$4*特低係数, 0)))))),0.125) -> 0 | U19: =SUM(R19:T19) -> 0 | V19: =U19/20 -> 0
D20: セルアウト日毎テーブル伝送 | F20: 45748 | G20: 45777 | H20: 8 | I20: 4 | J20: =SUM(H20:I20) -> 12 | L20: =K20*0.8 -> 0 | M20: =SUM(K20:L20) -> 0 | N20: BO | P20: 高 | Q20: 新規 | R20: =CEILING(IF($Q20="新規", IF($P20="特高", R$4*特高係数,IF($P20="高",R$4*高係数,IF($P20="中",R$4*中係数,IF($P20="低",R$4*低係数, IF($P20="特低",R$4*特低係数, 0))))), IF($P20="特高", R$4*特高係数,IF($P20="高",R$4*高係数,IF($P20="中",R$4*中係数,IF($P20="低",R$4*低係数, IF($P20="特低",R$4*特低係数, 0)))))),0.125) -> 1 | S20: =CEILING(IF($Q20="新規", IF($P20="特高", S$4*特高係数,IF($P20="高",S$4*高係数,IF($P20="中",S$4*中係数,IF($P20="低",S$4*低係数, IF($P20="特低",S$4*特低係数, 0))))), IF($P20="特高", S$4*特高係数,IF($P20="高",S$4*高係数,IF($P20="中",S$4*中係数,IF($P20="低",S$4*低係数, IF($P20="特低",S$4*特低係数, 0)))))),0.125) -> 11.75 | T20: =CEILING(IF($Q20="新規", IF($P20="特高", T$4*特高係数,IF($P20="高",T$4*高係数,IF($P20="中",T$4*中係数,IF($P20="低",T$4*低係数, IF($P20="特低",T$4*特低係数, 0))))), IF($P20="特高", T$4*特高係数,IF($P20="高",T$4*高係数,IF($P20="中",T$4*中係数,IF($P20="低",T$4*低係数, IF($P20="特低",T$4*特低係数, 0)))))),0.125) -> 9.5 | U20: =SUM(R20:T20) -> 22.25 | V20: =U20/20 -> 1.1125
D21: セルアウト日毎テーブル伝送 | F21: 45748 | G21: 45777 | H21: 0 | I21: 0 | J21: =SUM(H21:I21) -> 0 | K21: 0 | L21: 0 | M21: =SUM(K21:L21) -> 0 | N21: BO | R21: =CEILING(IF($Q21="新規", IF($P21="特高", R$4*特高係数,IF($P21="高",R$4*高係数,IF($P21="中",R$4*中係数,IF($P21="低",R$4*低係数, IF($P21="特低",R$4*特低係数, 0))))), IF($P21="特高", R$4*特高係数,IF($P21="高",R$4*高係数,IF($P21="中",R$4*中係数,IF($P21="低",R$4*低係数, IF($P21="特低",R$4*特低係数, 0)))))),0.125) -> 0 | S21: =CEILING(IF($Q21="新規", IF($P21="特高", S$4*特高係数,IF($P21="高",S$4*高係数,IF($P21="中",S$4*中係数,IF($P21="低",S$4*低係数, IF($P21="特低",S$4*特低係数, 0))))), IF($P21="特高", S$4*特高係数,IF($P21="高",S$4*高係数,IF($P21="中",S$4*中係数,IF($P21="低",S$4*低係数, IF($P21="特低",S$4*特低係数, 0)))))),0.125) -> 0 | T21: =CEILING(IF($Q21="新規", IF($P21="特高", T$4*特高係数,IF($P21="高",T$4*高係数,IF($P21="中",T$4*中係数,IF($P21="低",T$4*低係数, IF($P21="特低",T$4*特低係数, 0))))), IF($P21="特高", T$4*特高係数,IF($P21="高",T$4*高係数,IF($P21="中",T$4*中係数,IF($P21="低",T$4*低係数, IF($P21="特低",T$4*特低係数, 0)))))),0.125) -> 0 | U21: =SUM(R21:T21) -> 0 | V21: =U21/20 -> 0
D22: セルアウト月次テーブル伝送 | F22: 45748 | G22: 45777 | H22: 0 | I22: 0 | J22: =SUM(H22:I22) -> 0 | K22: 0 | L22: 0 | M22: =SUM(K22:L22) -> 0 | N22: BO | R22: =CEILING(IF($Q22="新規", IF($P22="特高", R$4*特高係数,IF($P22="高",R$4*高係数,IF($P22="中",R$4*中係数,IF($P22="低",R$4*低係数, IF($P22="特低",R$4*特低係数, 0))))), IF($P22="特高", R$4*特高係数,IF($P22="高",R$4*高係数,IF($P22="中",R$4*中係数,IF($P22="低",R$4*低係数, IF($P22="特低",R$4*特低係数, 0)))))),0.125) -> 0 | S22: =CEILING(IF($Q22="新規", IF($P22="特高", S$4*特高係数,IF($P22="高",S$4*高係数,IF($P22="中",S$4*中係数,IF($P22="低",S$4*低係数, IF($P22="特低",S$4*特低係数, 0))))), IF($P22="特高", S$4*特高係数,IF($P22="高",S$4*高係数,IF($P22="中",S$4*中係数,IF($P22="低",S$4*低係数, IF($P22="特低",S$4*特低係数, 0)))))),0.125) -> 0 | T22: =CEILING(IF($Q22="新規", IF($P22="特高", T$4*特高係数,IF($P22="高",T$4*高係数,IF($P22="中",T$4*中係数,IF($P22="低",T$4*低係数, IF($P22="特低",T$4*特低係数, 0))))), IF($P22="特高", T$4*特高係数,IF($P22="高",T$4*高係数,IF($P22="中",T$4*中係数,IF($P22="低",T$4*低係数, IF($P22="特低",T$4*特低係数, 0)))))),0.125) -> 0 | U22: =SUM(R22:T22) -> 0 | V22: =U22/20 -> 0
D23: ｍｙｄｏ情報データ伝送 | F23: 45748 | G23: 45777 | H23: 10 | I23: 6 | J23: =SUM(H23:I23) -> 16 | L23: =K23*0.8 -> 0 | M23: =SUM(K23:L23) -> 0 | N23: BO | P23: 特高 | Q23: 新規 | R23: =CEILING(IF($Q23="新規", IF($P23="特高", R$4*特高係数,IF($P23="高",R$4*高係数,IF($P23="中",R$4*中係数,IF($P23="低",R$4*低係数, IF($P23="特低",R$4*特低係数, 0))))), IF($P23="特高", R$4*特高係数,IF($P23="高",R$4*高係数,IF($P23="中",R$4*中係数,IF($P23="低",R$4*低係数, IF($P23="特低",R$4*特低係数, 0)))))),0.125) -> 1.375 | S23: =CEILING(IF($Q23="新規", IF($P23="特高", S$4*特高係数,IF($P23="高",S$4*高係数,IF($P23="中",S$4*中係数,IF($P23="低",S$4*低係数, IF($P23="特低",S$4*特低係数, 0))))), IF($P23="特高", S$4*特高係数,IF($P23="高",S$4*高係数,IF($P23="中",S$4*中係数,IF($P23="低",S$4*低係数, IF($P23="特低",S$4*特低係数, 0)))))),0.125) -> 15.25 | T23: =CEILING(IF($Q23="新規", IF($P23="特高", T$4*特高係数,IF($P23="高",T$4*高係数,IF($P23="中",T$4*中係数,IF($P23="低",T$4*低係数, IF($P23="特低",T$4*特低係数, 0))))), IF($P23="特高", T$4*特高係数,IF($P23="高",T$4*高係数,IF($P23="中",T$4*中係数,IF($P23="低",T$4*低係数, IF($P23="特低",T$4*特低係数, 0)))))),0.125) -> 12.375 | U23: =SUM(R23:T23) -> 29 | V23: =U23/20 -> 1.45
A24: =ROW()-4 -> 20 | C24: 処理センター17時 | D24: 販売店請求データ作成 | F24: 45748 | G24: 45807 | H24: 10 | I24: 6 | J24: =SUM(H24:I24) -> 16 | L24: =K24*0.8 -> 0 | M24: =SUM(K24:L24) -> 0 | N24: 機能 | P24: 特高 | Q24: 新規 | R24: =CEILING(IF($Q24="新規", IF($P24="特高", R$4*特高係数,IF($P24="高",R$4*高係数,IF($P24="中",R$4*中係数,IF($P24="低",R$4*低係数, IF($P24="特低",R$4*特低係数, 0))))), IF($P24="特高", R$4*特高係数,IF($P24="高",R$4*高係数,IF($P24="中",R$4*中係数,IF($P24="低",R$4*低係数, IF($P24="特低",R$4*特低係数, 0)))))),0.125) -> 1.375 | S24: =CEILING(IF($Q24="新規", IF($P24="特高", S$4*特高係数,IF($P24="高",S$4*高係数,IF($P24="中",S$4*中係数,IF($P24="低",S$4*低係数, IF($P24="特低",S$4*特低係数, 0))))), IF($P24="特高", S$4*特高係数,IF($P24="高",S$4*高係数,IF($P24="中",S$4*中係数,IF($P24="低",S$4*低係数, IF($P24="特低",S$4*特低係数, 0)))))),0.125) -> 15.25 | T24: =CEILING(IF($Q24="新規", IF($P24="特高", T$4*特高係数,IF($P24="高",T$4*高係数,IF($P24="中",T$4*中係数,IF($P24="低",T$4*低係数, IF($P24="特低",T$4*特低係数, 0))))), IF($P24="特高", T$4*特高係数,IF($P24="高",T$4*高係数,IF($P24="中",T$4*中係数,IF($P24="低",T$4*低係数, IF($P24="特低",T$4*特低係数, 0)))))),0.125) -> 12.375 | U24: =SUM(R24:T24) -> 29 | V24: =U24/20 -> 1.45
D25: POS配信1回目(CRC) | F25: 45748 | G25: 45807 | H25: 18 | I25: 9 | J25: =SUM(H25:I25) -> 27 | L25: =K25*0.8 -> 0 | M25: =SUM(K25:L25) -> 0 | N25: 連携 | P25: 特高 | Q25: 新規 | R25: =1.8*CEILING(IF($Q25="新規", IF($P25="特高", R$4*特高係数,IF($P25="高",R$4*高係数,IF($P25="中",R$4*中係数,IF($P25="低",R$4*低係数, IF($P25="特低",R$4*特低係数, 0))))), IF($P25="特高", R$4*特高係数,IF($P25="高",R$4*高係数,IF($P25="中",R$4*中係数,IF($P25="低",R$4*低係数, IF($P25="特低",R$4*特低係数, 0)))))),0.125) -> 2.475 | S25: =1.8*CEILING(IF($Q25="新規", IF($P25="特高", S$4*特高係数,IF($P25="高",S$4*高係数,IF($P25="中",S$4*中係数,IF($P25="低",S$4*低係数, IF($P25="特低",S$4*特低係数, 0))))), IF($P25="特高", S$4*特高係数,IF($P25="高",S$4*高係数,IF($P25="中",S$4*中係数,IF($P25="低",S$4*低係数, IF($P25="特低",S$4*特低係数, 0)))))),0.125) -> 27.45 | T25: =1.8*CEILING(IF($Q25="新規", IF($P25="特高", T$4*特高係数,IF($P25="高",T$4*高係数,IF($P25="中",T$4*中係数,IF($P25="低",T$4*低係数, IF($P25="特低",T$4*特低係数, 0))))), IF($P25="特高", T$4*特高係数,IF($P25="高",T$4*高係数,IF($P25="中",T$4*中係数,IF($P25="低",T$4*低係数, IF($P25="特低",T$4*特低係数, 0)))))),0.125) -> 22.275 | U25: =SUM(R25:T25) -> 52.2 | V25: =U25/20 -> 2.61
D26: POS配信1回目(ICC) | F26: 45748 | G26: 45807 | H26: 12 | I26: 6 | J26: =SUM(H26:I26) -> 18 | L26: =K26*0.8 -> 0 | M26: =SUM(K26:L26) -> 0 | N26: 連携 | P26: 特高 | Q26: 新規 | R26: =CEILING(IF($Q26="新規", IF($P26="特高", R$4*特高係数,IF($P26="高",R$4*高係数,IF($P26="中",R$4*中係数,IF($P26="低",R$4*低係数, IF($P26="特低",R$4*特低係数, 0))))), IF($P26="特高", R$4*特高係数,IF($P26="高",R$4*高係数,IF($P26="中",R$4*中係数,IF($P26="低",R$4*低係数, IF($P26="特低",R$4*特低係数, 0)))))),0.125) -> 1.375 | S26: =CEILING(IF($Q26="新規", IF($P26="特高", S$4*特高係数,IF($P26="高",S$4*高係数,IF($P26="中",S$4*中係数,IF($P26="低",S$4*低係数, IF($P26="特低",S$4*特低係数, 0))))), IF($P26="特高", S$4*特高係数,IF($P26="高",S$4*高係数,IF($P26="中",S$4*中係数,IF($P26="低",S$4*低係数, IF($P26="特低",S$4*特低係数, 0)))))),0.125) -> 15.25 | T26: =CEILING(IF($Q26="新規", IF($P26="特高", T$4*特高係数,IF($P26="高",T$4*高係数,IF($P26="中",T$4*中係数,IF($P26="低",T$4*低係数, IF($P26="特低",T$4*特低係数, 0))))), IF($P26="特高", T$4*特高係数,IF($P26="高",T$4*高係数,IF($P26="中",T$4*中係数,IF($P26="低",T$4*低係数, IF($P26="特低",T$4*特低係数, 0)))))),0.125) -> 12.375 | U26: =SUM(R26:T26) -> 29 | V26: =U26/20 -> 1.45
D27: POS配信1回目(ITC) | F27: 45748 | G27: 45807 | H27: 0 | I27: 0 | J27: =SUM(H27:I27) -> 0 | K27: 0 | L27: 0 | M27: =SUM(K27:L27) -> 0 | N27: 連携 | R27: =CEILING(IF($Q27="新規", IF($P27="特高", R$4*特高係数,IF($P27="高",R$4*高係数,IF($P27="中",R$4*中係数,IF($P27="低",R$4*低係数, IF($P27="特低",R$4*特低係数, 0))))), IF($P27="特高", R$4*特高係数,IF($P27="高",R$4*高係数,IF($P27="中",R$4*中係数,IF($P27="低",R$4*低係数, IF($P27="特低",R$4*特低係数, 0)))))),0.125) -> 0 | S27: =CEILING(IF($Q27="新規", IF($P27="特高", S$4*特高係数,IF($P27="高",S$4*高係数,IF($P27="中",S$4*中係数,IF($P27="低",S$4*低係数, IF($P27="特低",S$4*特低係数, 0))))), IF($P27="特高", S$4*特高係数,IF($P27="高",S$4*高係数,IF($P27="中",S$4*中係数,IF($P27="低",S$4*低係数, IF($P27="特低",S$4*特低係数, 0)))))),0.125) -> 0 | T27: =CEILING(IF($Q27="新規", IF($P27="特高", T$4*特高係数,IF($P27="高",T$4*高係数,IF($P27="中",T$4*中係数,IF($P27="低",T$4*低係数, IF($P27="特低",T$4*特低係数, 0))))), IF($P27="特高", T$4*特高係数,IF($P27="高",T$4*高係数,IF($P27="中",T$4*中係数,IF($P27="低",T$4*低係数, IF($P27="特低",T$4*特低係数, 0)))))),0.125) -> 0 | U27: =SUM(R27:T27) -> 0 | V27: =U27/20 -> 0
D28: POS配信1回目(CRC) | F28: 45748 | G28: 45807 | H28: 0 | I28: 0 | J28: =SUM(H28:I28) -> 0 | K28: 0 | L28: 0 | M28: =SUM(K28:L28) -> 0 | N28: 連携 | R28: =CEILING(IF($Q28="新規", IF($P28="特高", R$4*特高係数,IF($P28="高",R$4*高係数,IF($P28="中",R$4*中係数,IF($P28="低",R$4*低係数, IF($P28="特低",R$4*特低係数, 0))))), IF($P28="特高", R$4*特高係数,IF($P28="高",R$4*高係数,IF($P28="中",R$4*中係数,IF($P28="低",R$4*低係数, IF($P28="特低",R$4*特低係数, 0)))))),0.125) -> 0 | S28: =CEILING(IF($Q28="新規", IF($P28="特高", S$4*特高係数,IF($P28="高",S$4*高係数,IF($P28="中",S$4*中係数,IF($P28="低",S$4*低係数, IF($P28="特低",S$4*特低係数, 0))))), IF($P28="特高", S$4*特高係数,IF($P28="高",S$4*高係数,IF($P28="中",S$4*中係数,IF($P28="低",S$4*低係数, IF($P28="特低",S$4*特低係数, 0)))))),0.125) -> 0 | T28: =CEILING(IF($Q28="新規", IF($P28="特高", T$4*特高係数,IF($P28="高",T$4*高係数,IF($P28="中",T$4*中係数,IF($P28="低",T$4*低係数, IF($P28="特低",T$4*特低係数, 0))))), IF($P28="特高", T$4*特高係数,IF($P28="高",T$4*高係数,IF($P28="中",T$4*中係数,IF($P28="低",T$4*低係数, IF($P28="特低",T$4*特低係数, 0)))))),0.125) -> 0 | U28: =SUM(R28:T28) -> 0 | V28: =U28/20 -> 0
A29: =ROW()-4 -> 25 | C29: 自動仕入 | D29: 自動仕入連携（ICC） | F29: 45778 | G29: 45838 | H29: 18 | I29: 9 | J29: =SUM(H29:I29) -> 27 | L29: =K29*0.8 -> 0 | M29: =SUM(K29:L29) -> 0 | N29: 連携 | P29: 特高 | Q29: 新規 | R29: =1.8*CEILING(IF($Q29="新規", IF($P29="特高", R$4*特高係数,IF($P29="高",R$4*高係数,IF($P29="中",R$4*中係数,IF($P29="低",R$4*低係数, IF($P29="特低",R$4*特低係数, 0))))), IF($P29="特高", R$4*特高係数,IF($P29="高",R$4*高係数,IF($P29="中",R$4*中係数,IF($P29="低",R$4*低係数, IF($P29="特低",R$4*特低係数, 0)))))),0.125) -> 2.475 | S29: =1.8*CEILING(IF($Q29="新規", IF($P29="特高", S$4*特高係数,IF($P29="高",S$4*高係数,IF($P29="中",S$4*中係数,IF($P29="低",S$4*低係数, IF($P29="特低",S$4*特低係数, 0))))), IF($P29="特高", S$4*特高係数,IF($P29="高",S$4*高係数,IF($P29="中",S$4*中係数,IF($P29="低",S$4*低係数, IF($P29="特低",S$4*特低係数, 0)))))),0.125) -> 27.45 | T29: =1.8*CEILING(IF($Q29="新規", IF($P29="特高", T$4*特高係数,IF($P29="高",T$4*高係数,IF($P29="中",T$4*中係数,IF($P29="低",T$4*低係数, IF($P29="特低",T$4*特低係数, 0))))), IF($P29="特高", T$4*特高係数,IF($P29="高",T$4*高係数,IF($P29="中",T$4*中係数,IF($P29="低",T$4*低係数, IF($P29="特低",T$4*特低係数, 0)))))),0.125) -> 22.275 | U29: =SUM(R29:T29) -> 52.2 | V29: =U29/20 -> 2.61
D30: 自動仕入連携（ITC） | F30: 45778 | G30: 45838 | H30: 4 | I30: 2 | J30: =SUM(H30:I30) -> 6 | L30: =K30*0.8 -> 0 | M30: =SUM(K30:L30) -> 0 | N30: 連携 | P30: 低 | Q30: 新規 | R30: =CEILING(IF($Q30="新規", IF($P30="特高", R$4*特高係数,IF($P30="高",R$4*高係数,IF($P30="中",R$4*中係数,IF($P30="低",R$4*低係数, IF($P30="特低",R$4*特低係数, 0))))), IF($P30="特高", R$4*特高係数,IF($P30="高",R$4*高係数,IF($P30="中",R$4*中係数,IF($P30="低",R$4*低係数, IF($P30="特低",R$4*特低係数, 0)))))),0.125) -> 0.375 | S30: =CEILING(IF($Q30="新規", IF($P30="特高", S$4*特高係数,IF($P30="高",S$4*高係数,IF($P30="中",S$4*中係数,IF($P30="低",S$4*低係数, IF($P30="特低",S$4*特低係数, 0))))), IF($P30="特高", S$4*特高係数,IF($P30="高",S$4*高係数,IF($P30="中",S$4*中係数,IF($P30="低",S$4*低係数, IF($P30="特低",S$4*特低係数, 0)))))),0.125) -> 4.125 | T30: =CEILING(IF($Q30="新規", IF($P30="特高", T$4*特高係数,IF($P30="高",T$4*高係数,IF($P30="中",T$4*中係数,IF($P30="低",T$4*低係数, IF($P30="特低",T$4*特低係数, 0))))), IF($P30="特高", T$4*特高係数,IF($P30="高",T$4*高係数,IF($P30="中",T$4*中係数,IF($P30="低",T$4*低係数, IF($P30="特低",T$4*特低係数, 0)))))),0.125) -> 3.375 | U30: =SUM(R30:T30) -> 7.875 | V30: =U30/20 -> 0.39375
D31: 自動仕入連携（CRC） | F31: 45778 | G31: 45838 | H31: 0 | I31: 0 | J31: =SUM(H31:I31) -> 0 | K31: 0 | L31: 0 | M31: =SUM(K31:L31) -> 0 | N31: 連携 | R31: =CEILING(IF($Q31="新規", IF($P31="特高", R$4*特高係数,IF($P31="高",R$4*高係数,IF($P31="中",R$4*中係数,IF($P31="低",R$4*低係数, IF($P31="特低",R$4*特低係数, 0))))), IF($P31="特高", R$4*特高係数,IF($P31="高",R$4*高係数,IF($P31="中",R$4*中係数,IF($P31="低",R$4*低係数, IF($P31="特低",R$4*特低係数, 0)))))),0.125) -> 0 | S31: =CEILING(IF($Q31="新規", IF($P31="特高", S$4*特高係数,IF($P31="高",S$4*高係数,IF($P31="中",S$4*中係数,IF($P31="低",S$4*低係数, IF($P31="特低",S$4*特低係数, 0))))), IF($P31="特高", S$4*特高係数,IF($P31="高",S$4*高係数,IF($P31="中",S$4*中係数,IF($P31="低",S$4*低係数, IF($P31="特低",S$4*特低係数, 0)))))),0.125) -> 0 | T31: =CEILING(IF($Q31="新規", IF($P31="特高", T$4*特高係数,IF($P31="高",T$4*高係数,IF($P31="中",T$4*中係数,IF($P31="低",T$4*低係数, IF($P31="特低",T$4*特低係数, 0))))), IF($P31="特高", T$4*特高係数,IF($P31="高",T$4*高係数,IF($P31="中",T$4*中係数,IF($P31="低",T$4*低係数, IF($P31="特低",T$4*特低係数, 0)))))),0.125) -> 0 | U31: =SUM(R31:T31) -> 0 | V31: =U31/20 -> 0
D32: 自動仕入連携（GST） | F32: 45778 | G32: 45838 | H32: 0 | I32: 0 | J32: =SUM(H32:I32) -> 0 | K32: 0 | L32: 0 | M32: =SUM(K32:L32) -> 0 | N32: 連携 | R32: =CEILING(IF($Q32="新規", IF($P32="特高", R$4*特高係数,IF($P32="高",R$4*高係数,IF($P32="中",R$4*中係数,IF($P32="低",R$4*低係数, IF($P32="特低",R$4*特低係数, 0))))), IF($P32="特高", R$4*特高係数,IF($P32="高",R$4*高係数,IF($P32="中",R$4*中係数,IF($P32="低",R$4*低係数, IF($P32="特低",R$4*特低係数, 0)))))),0.125) -> 0 | S32: =CEILING(IF($Q32="新規", IF($P32="特高", S$4*特高係数,IF($P32="高",S$4*高係数,IF($P32="中",S$4*中係数,IF($P32="低",S$4*低係数, IF($P32="特低",S$4*特低係数, 0))))), IF($P32="特高", S$4*特高係数,IF($P32="高",S$4*高係数,IF($P32="中",S$4*中係数,IF($P32="低",S$4*低係数, IF($P32="特低",S$4*特低係数, 0)))))),0.125) -> 0 | T32: =CEILING(IF($Q32="新規", IF($P32="特高", T$4*特高係数,IF($P32="高",T$4*高係数,IF($P32="中",T$4*中係数,IF($P32="低",T$4*低係数, IF($P32="特低",T$4*特低係数, 0))))), IF($P32="特高", T$4*特高係数,IF($P32="高",T$4*高係数,IF($P32="中",T$4*中係数,IF($P32="低",T$4*低係数, IF($P32="特低",T$4*特低係数, 0)))))),0.125) -> 0 | U32: =SUM(R32:T32) -> 0 | V32: =U32/20 -> 0
A33: =ROW()-4 -> 29 | C33: POS処理料・利用料 | D33: POS処理料出クレ決済用データ | F33: 45748 | G33: 45814 | H33: 8 | I33: 4 | J33: =SUM(H33:I33) -> 12 | L33: =K33*0.8 -> 0 | M33: =SUM(K33:L33) -> 0 | N33: 連携 | P33: 高 | Q33: 新規 | R33: =CEILING(IF($Q33="新規", IF($P33="特高", R$4*特高係数,IF($P33="高",R$4*高係数,IF($P33="中",R$4*中係数,IF($P33="低",R$4*低係数, IF($P33="特低",R$4*特低係数, 0))))), IF($P33="特高", R$4*特高係数,IF($P33="高",R$4*高係数,IF($P33="中",R$4*中係数,IF($P33="低",R$4*低係数, IF($P33="特低",R$4*特低係数, 0)))))),0.125) -> 1 | S33: =CEILING(IF($Q33="新規", IF($P33="特高", S$4*特高係数,IF($P33="高",S$4*高係数,IF($P33="中",S$4*中係数,IF($P33="低",S$4*低係数, IF($P33="特低",S$4*特低係数, 0))))), IF($P33="特高", S$4*特高係数,IF($P33="高",S$4*高係数,IF($P33="中",S$4*中係数,IF($P33="低",S$4*低係数, IF($P33="特低",S$4*特低係数, 0)))))),0.125) -> 11.75 | T33: =CEILING(IF($Q33="新規", IF($P33="特高", T$4*特高係数,IF($P33="高",T$4*高係数,IF($P33="中",T$4*中係数,IF($P33="低",T$4*低係数, IF($P33="特低",T$4*特低係数, 0))))), IF($P33="特高", T$4*特高係数,IF($P33="高",T$4*高係数,IF($P33="中",T$4*中係数,IF($P33="低",T$4*低係数, IF($P33="特低",T$4*特低係数, 0)))))),0.125) -> 9.5 | U33: =SUM(R33:T33) -> 22.25 | V33: =U33/20 -> 1.1125
D34: POS利用料機伝 | F34: 45748 | G34: 45814 | H34: 8 | I34: 4 | J34: =SUM(H34:I34) -> 12 | L34: =K34*0.8 -> 0 | M34: =SUM(K34:L34) -> 0 | N34: 連携 | P34: 高 | Q34: 新規 | R34: =CEILING(IF($Q34="新規", IF($P34="特高", R$4*特高係数,IF($P34="高",R$4*高係数,IF($P34="中",R$4*中係数,IF($P34="低",R$4*低係数, IF($P34="特低",R$4*特低係数, 0))))), IF($P34="特高", R$4*特高係数,IF($P34="高",R$4*高係数,IF($P34="中",R$4*中係数,IF($P34="低",R$4*低係数, IF($P34="特低",R$4*特低係数, 0)))))),0.125) -> 1 | S34: =CEILING(IF($Q34="新規", IF($P34="特高", S$4*特高係数,IF($P34="高",S$4*高係数,IF($P34="中",S$4*中係数,IF($P34="低",S$4*低係数, IF($P34="特低",S$4*特低係数, 0))))), IF($P34="特高", S$4*特高係数,IF($P34="高",S$4*高係数,IF($P34="中",S$4*中係数,IF($P34="低",S$4*低係数, IF($P34="特低",S$4*特低係数, 0)))))),0.125) -> 11.75 | T34: =CEILING(IF($Q34="新規", IF($P34="特高", T$4*特高係数,IF($P34="高",T$4*高係数,IF($P34="中",T$4*中係数,IF($P34="低",T$4*低係数, IF($P34="特低",T$4*特低係数, 0))))), IF($P34="特高", T$4*特高係数,IF($P34="高",T$4*高係数,IF($P34="中",T$4*中係数,IF($P34="低",T$4*低係数, IF($P34="特低",T$4*特低係数, 0)))))),0.125) -> 9.5 | U34: =SUM(R34:T34) -> 22.25 | V34: =U34/20 -> 1.1125
D35: POS処理料機伝 | F35: 45748 | G35: 45814 | H35: 8 | I35: 4 | J35: =SUM(H35:I35) -> 12 | L35: =K35*0.8 -> 0 | M35: =SUM(K35:L35) -> 0 | N35: 連携 | P35: 高 | Q35: 新規 | R35: =CEILING(IF($Q35="新規", IF($P35="特高", R$4*特高係数,IF($P35="高",R$4*高係数,IF($P35="中",R$4*中係数,IF($P35="低",R$4*低係数, IF($P35="特低",R$4*特低係数, 0))))), IF($P35="特高", R$4*特高係数,IF($P35="高",R$4*高係数,IF($P35="中",R$4*中係数,IF($P35="低",R$4*低係数, IF($P35="特低",R$4*特低係数, 0)))))),0.125) -> 1 | S35: =CEILING(IF($Q35="新規", IF($P35="特高", S$4*特高係数,IF($P35="高",S$4*高係数,IF($P35="中",S$4*中係数,IF($P35="低",S$4*低係数, IF($P35="特低",S$4*特低係数, 0))))), IF($P35="特高", S$4*特高係数,IF($P35="高",S$4*高係数,IF($P35="中",S$4*中係数,IF($P35="低",S$4*低係数, IF($P35="特低",S$4*特低係数, 0)))))),0.125) -> 11.75 | T35: =CEILING(IF($Q35="新規", IF($P35="特高", T$4*特高係数,IF($P35="高",T$4*高係数,IF($P35="中",T$4*中係数,IF($P35="低",T$4*低係数, IF($P35="特低",T$4*特低係数, 0))))), IF($P35="特高", T$4*特高係数,IF($P35="高",T$4*高係数,IF($P35="中",T$4*中係数,IF($P35="低",T$4*低係数, IF($P35="特低",T$4*特低係数, 0)))))),0.125) -> 9.5 | U35: =SUM(R35:T35) -> 22.25 | V35: =U35/20 -> 1.1125
D36: ＰＯＳ処理料各種確認リスト | F36: 45748 | G36: 45814 | H36: 8 | I36: 4 | J36: =SUM(H36:I36) -> 12 | K36: 12 | L36: =K36*0.8 -> 9.6 | M36: =SUM(K36:L36) -> 21.6 | N36: 帳票 | P36: 高 | Q36: 新規 | R36: =CEILING(IF($Q36="新規", IF($P36="特高", R$4*特高係数,IF($P36="高",R$4*高係数,IF($P36="中",R$4*中係数,IF($P36="低",R$4*低係数, IF($P36="特低",R$4*特低係数, 0))))), IF($P36="特高", R$4*特高係数,IF($P36="高",R$4*高係数,IF($P36="中",R$4*中係数,IF($P36="低",R$4*低係数, IF($P36="特低",R$4*特低係数, 0)))))),0.125) -> 1 | S36: =CEILING(IF($Q36="新規", IF($P36="特高", S$4*特高係数,IF($P36="高",S$4*高係数,IF($P36="中",S$4*中係数,IF($P36="低",S$4*低係数, IF($P36="特低",S$4*特低係数, 0))))), IF($P36="特高", S$4*特高係数,IF($P36="高",S$4*高係数,IF($P36="中",S$4*中係数,IF($P36="低",S$4*低係数, IF($P36="特低",S$4*特低係数, 0)))))),0.125) -> 11.75 | T36: =CEILING(IF($Q36="新規", IF($P36="特高", T$4*特高係数,IF($P36="高",T$4*高係数,IF($P36="中",T$4*中係数,IF($P36="低",T$4*低係数, IF($P36="特低",T$4*特低係数, 0))))), IF($P36="特高", T$4*特高係数,IF($P36="高",T$4*高係数,IF($P36="中",T$4*中係数,IF($P36="低",T$4*低係数, IF($P36="特低",T$4*特低係数, 0)))))),0.125) -> 9.5 | U36: =SUM(R36:T36) -> 22.25 | V36: =U36/20 -> 1.1125
A37: =ROW()-4 -> 33 | C37: エントリ向け_まいどプラス発券 | D37: Mydoプラス発券実績 | F37: 45761 | G37: 45777 | H37: 8 | I37: 4 | J37: =SUM(H37:I37) -> 12 | L37: =K37*0.8 -> 0 | M37: =SUM(K37:L37) -> 0 | N37: DB | P37: 高 | Q37: 新規 | R37: =CEILING(IF($Q37="新規", IF($P37="特高", R$4*特高係数,IF($P37="高",R$4*高係数,IF($P37="中",R$4*中係数,IF($P37="低",R$4*低係数, IF($P37="特低",R$4*特低係数, 0))))), IF($P37="特高", R$4*特高係数,IF($P37="高",R$4*高係数,IF($P37="中",R$4*中係数,IF($P37="低",R$4*低係数, IF($P37="特低",R$4*特低係数, 0)))))),0.125) -> 1 | S37: =CEILING(IF($Q37="新規", IF($P37="特高", S$4*特高係数,IF($P37="高",S$4*高係数,IF($P37="中",S$4*中係数,IF($P37="低",S$4*低係数, IF($P37="特低",S$4*特低係数, 0))))), IF($P37="特高", S$4*特高係数,IF($P37="高",S$4*高係数,IF($P37="中",S$4*中係数,IF($P37="低",S$4*低係数, IF($P37="特低",S$4*特低係数, 0)))))),0.125) -> 11.75 | T37: =CEILING(IF($Q37="新規", IF($P37="特高", T$4*特高係数,IF($P37="高",T$4*高係数,IF($P37="中",T$4*中係数,IF($P37="低",T$4*低係数, IF($P37="特低",T$4*特低係数, 0))))), IF($P37="特高", T$4*特高係数,IF($P37="高",T$4*高係数,IF($P37="中",T$4*中係数,IF($P37="低",T$4*低係数, IF($P37="特低",T$4*特低係数, 0)))))),0.125) -> 9.5 | U37: =SUM(R37:T37) -> 22.25 | V37: =U37/20 -> 1.1125
D38: MYDOPlus発券実績 | F38: 45761 | G38: 45777 | H38: 4 | I38: 2 | J38: =SUM(H38:I38) -> 6 | L38: =K38*0.8 -> 0 | M38: =SUM(K38:L38) -> 0 | N38: 連携 | P38: 低 | Q38: 新規 | R38: =CEILING(IF($Q38="新規", IF($P38="特高", R$4*特高係数,IF($P38="高",R$4*高係数,IF($P38="中",R$4*中係数,IF($P38="低",R$4*低係数, IF($P38="特低",R$4*特低係数, 0))))), IF($P38="特高", R$4*特高係数,IF($P38="高",R$4*高係数,IF($P38="中",R$4*中係数,IF($P38="低",R$4*低係数, IF($P38="特低",R$4*特低係数, 0)))))),0.125) -> 0.375 | S38: =CEILING(IF($Q38="新規", IF($P38="特高", S$4*特高係数,IF($P38="高",S$4*高係数,IF($P38="中",S$4*中係数,IF($P38="低",S$4*低係数, IF($P38="特低",S$4*特低係数, 0))))), IF($P38="特高", S$4*特高係数,IF($P38="高",S$4*高係数,IF($P38="中",S$4*中係数,IF($P38="低",S$4*低係数, IF($P38="特低",S$4*特低係数, 0)))))),0.125) -> 4.125 | T38: =CEILING(IF($Q38="新規", IF($P38="特高", T$4*特高係数,IF($P38="高",T$4*高係数,IF($P38="中",T$4*中係数,IF($P38="低",T$4*低係数, IF($P38="特低",T$4*特低係数, 0))))), IF($P38="特高", T$4*特高係数,IF($P38="高",T$4*高係数,IF($P38="中",T$4*中係数,IF($P38="低",T$4*低係数, IF($P38="特低",T$4*特低係数, 0)))))),0.125) -> 3.375 | U38: =SUM(R38:T38) -> 7.875 | V38: =U38/20 -> 0.39375
A39: =ROW()-4 -> 35 | C39: ｱｽﾄﾓｽ入出荷 | D39: 入出荷共通入力（日次）OneSAP向け | F39: 45761 | G39: 45821 | H39: 18 | I39: 9 | J39: =SUM(H39:I39) -> 27 | L39: =K39*0.8 -> 0 | M39: =SUM(K39:L39) -> 0 | N39: 連携 | P39: 特高 | Q39: 新規 | R39: =1.8*CEILING(IF($Q39="新規", IF($P39="特高", R$4*特高係数,IF($P39="高",R$4*高係数,IF($P39="中",R$4*中係数,IF($P39="低",R$4*低係数, IF($P39="特低",R$4*特低係数, 0))))), IF($P39="特高", R$4*特高係数,IF($P39="高",R$4*高係数,IF($P39="中",R$4*中係数,IF($P39="低",R$4*低係数, IF($P39="特低",R$4*特低係数, 0)))))),0.125) -> 2.475 | S39: =1.8*CEILING(IF($Q39="新規", IF($P39="特高", S$4*特高係数,IF($P39="高",S$4*高係数,IF($P39="中",S$4*中係数,IF($P39="低",S$4*低係数, IF($P39="特低",S$4*特低係数, 0))))), IF($P39="特高", S$4*特高係数,IF($P39="高",S$4*高係数,IF($P39="中",S$4*中係数,IF($P39="低",S$4*低係数, IF($P39="特低",S$4*特低係数, 0)))))),0.125) -> 27.45 | T39: =1.8*CEILING(IF($Q39="新規", IF($P39="特高", T$4*特高係数,IF($P39="高",T$4*高係数,IF($P39="中",T$4*中係数,IF($P39="低",T$4*低係数, IF($P39="特低",T$4*特低係数, 0))))), IF($P39="特高", T$4*特高係数,IF($P39="高",T$4*高係数,IF($P39="中",T$4*中係数,IF($P39="低",T$4*低係数, IF($P39="特低",T$4*特低係数, 0)))))),0.125) -> 22.275 | U39: =SUM(R39:T39) -> 52.2 | V39: =U39/20 -> 2.61
D40: 商品入荷エラーリスト | F40: 45761 | G40: 45821 | H40: 12 | I40: 6 | J40: =SUM(H40:I40) -> 18 | K40: 20 | L40: =K40*0.8 -> 16 | M40: =SUM(K40:L40) -> 36 | N40: 帳票 | P40: 特高 | Q40: 新規 | R40: =CEILING(IF($Q40="新規", IF($P40="特高", R$4*特高係数,IF($P40="高",R$4*高係数,IF($P40="中",R$4*中係数,IF($P40="低",R$4*低係数, IF($P40="特低",R$4*特低係数, 0))))), IF($P40="特高", R$4*特高係数,IF($P40="高",R$4*高係数,IF($P40="中",R$4*中係数,IF($P40="低",R$4*低係数, IF($P40="特低",R$4*特低係数, 0)))))),0.125) -> 1.375 | S40: =CEILING(IF($Q40="新規", IF($P40="特高", S$4*特高係数,IF($P40="高",S$4*高係数,IF($P40="中",S$4*中係数,IF($P40="低",S$4*低係数, IF($P40="特低",S$4*特低係数, 0))))), IF($P40="特高", S$4*特高係数,IF($P40="高",S$4*高係数,IF($P40="中",S$4*中係数,IF($P40="低",S$4*低係数, IF($P40="特低",S$4*特低係数, 0)))))),0.125) -> 15.25 | T40: =CEILING(IF($Q40="新規", IF($P40="特高", T$4*特高係数,IF($P40="高",T$4*高係数,IF($P40="中",T$4*中係数,IF($P40="低",T$4*低係数, IF($P40="特低",T$4*特低係数, 0))))), IF($P40="特高", T$4*特高係数,IF($P40="高",T$4*高係数,IF($P40="中",T$4*中係数,IF($P40="低",T$4*低係数, IF($P40="特低",T$4*特低係数, 0)))))),0.125) -> 12.375 | U40: =SUM(R40:T40) -> 29 | V40: =U40/20 -> 1.45
D41: 複合伝票（LPG) | F41: 45761 | G41: 45821 | H41: 10 | I41: 6 | J41: =SUM(H41:I41) -> 16 | L41: =K41*0.8 -> 0 | M41: =SUM(K41:L41) -> 0 | N41: 帳票 | P41: 特高 | Q41: 新規 | R41: =CEILING(IF($Q41="新規", IF($P41="特高", R$4*特高係数,IF($P41="高",R$4*高係数,IF($P41="中",R$4*中係数,IF($P41="低",R$4*低係数, IF($P41="特低",R$4*特低係数, 0))))), IF($P41="特高", R$4*特高係数,IF($P41="高",R$4*高係数,IF($P41="中",R$4*中係数,IF($P41="低",R$4*低係数, IF($P41="特低",R$4*特低係数, 0)))))),0.125) -> 1.375 | S41: =CEILING(IF($Q41="新規", IF($P41="特高", S$4*特高係数,IF($P41="高",S$4*高係数,IF($P41="中",S$4*中係数,IF($P41="低",S$4*低係数, IF($P41="特低",S$4*特低係数, 0))))), IF($P41="特高", S$4*特高係数,IF($P41="高",S$4*高係数,IF($P41="中",S$4*中係数,IF($P41="低",S$4*低係数, IF($P41="特低",S$4*特低係数, 0)))))),0.125) -> 15.25 | T41: =CEILING(IF($Q41="新規", IF($P41="特高", T$4*特高係数,IF($P41="高",T$4*高係数,IF($P41="中",T$4*中係数,IF($P41="低",T$4*低係数, IF($P41="特低",T$4*特低係数, 0))))), IF($P41="特高", T$4*特高係数,IF($P41="高",T$4*高係数,IF($P41="中",T$4*中係数,IF($P41="低",T$4*低係数, IF($P41="特低",T$4*特低係数, 0)))))),0.125) -> 12.375 | U41: =SUM(R41:T41) -> 29 | V41: =U41/20 -> 1.45
D42: 在庫受払日報 | F42: 45761 | G42: 45821 | H42: 8 | I42: 4 | J42: =SUM(H42:I42) -> 12 | K42: 12 | L42: =K42*0.8 -> 9.6 | M42: =SUM(K42:L42) -> 21.6 | N42: 帳票 | P42: 高 | Q42: 新規 | R42: =CEILING(IF($Q42="新規", IF($P42="特高", R$4*特高係数,IF($P42="高",R$4*高係数,IF($P42="中",R$4*中係数,IF($P42="低",R$4*低係数, IF($P42="特低",R$4*特低係数, 0))))), IF($P42="特高", R$4*特高係数,IF($P42="高",R$4*高係数,IF($P42="中",R$4*中係数,IF($P42="低",R$4*低係数, IF($P42="特低",R$4*特低係数, 0)))))),0.125) -> 1 | S42: =CEILING(IF($Q42="新規", IF($P42="特高", S$4*特高係数,IF($P42="高",S$4*高係数,IF($P42="中",S$4*中係数,IF($P42="低",S$4*低係数, IF($P42="特低",S$4*特低係数, 0))))), IF($P42="特高", S$4*特高係数,IF($P42="高",S$4*高係数,IF($P42="中",S$4*中係数,IF($P42="低",S$4*低係数, IF($P42="特低",S$4*特低係数, 0)))))),0.125) -> 11.75 | T42: =CEILING(IF($Q42="新規", IF($P42="特高", T$4*特高係数,IF($P42="高",T$4*高係数,IF($P42="中",T$4*中係数,IF($P42="低",T$4*低係数, IF($P42="特低",T$4*特低係数, 0))))), IF($P42="特高", T$4*特高係数,IF($P42="高",T$4*高係数,IF($P42="中",T$4*中係数,IF($P42="低",T$4*低係数, IF($P42="特低",T$4*特低係数, 0)))))),0.125) -> 9.5 | U42: =SUM(R42:T42) -> 22.25 | V42: =U42/20 -> 1.1125
D43: 在庫受払月報 | F43: 45761 | G43: 45821 | H43: 8 | I43: 4 | J43: =SUM(H43:I43) -> 12 | K43: 20 | L43: =K43*0.8 -> 16 | M43: =SUM(K43:L43) -> 36 | N43: 帳票 | P43: 高 | Q43: 新規 | R43: =CEILING(IF($Q43="新規", IF($P43="特高", R$4*特高係数,IF($P43="高",R$4*高係数,IF($P43="中",R$4*中係数,IF($P43="低",R$4*低係数, IF($P43="特低",R$4*特低係数, 0))))), IF($P43="特高", R$4*特高係数,IF($P43="高",R$4*高係数,IF($P43="中",R$4*中係数,IF($P43="低",R$4*低係数, IF($P43="特低",R$4*特低係数, 0)))))),0.125) -> 1 | S43: =CEILING(IF($Q43="新規", IF($P43="特高", S$4*特高係数,IF($P43="高",S$4*高係数,IF($P43="中",S$4*中係数,IF($P43="低",S$4*低係数, IF($P43="特低",S$4*特低係数, 0))))), IF($P43="特高", S$4*特高係数,IF($P43="高",S$4*高係数,IF($P43="中",S$4*中係数,IF($P43="低",S$4*低係数, IF($P43="特低",S$4*特低係数, 0)))))),0.125) -> 11.75 | T43: =CEILING(IF($Q43="新規", IF($P43="特高", T$4*特高係数,IF($P43="高",T$4*高係数,IF($P43="中",T$4*中係数,IF($P43="低",T$4*低係数, IF($P43="特低",T$4*特低係数, 0))))), IF($P43="特高", T$4*特高係数,IF($P43="高",T$4*高係数,IF($P43="中",T$4*中係数,IF($P43="低",T$4*低係数, IF($P43="特低",T$4*特低係数, 0)))))),0.125) -> 9.5 | U43: =SUM(R43:T43) -> 22.25 | V43: =U43/20 -> 1.1125
A44: =ROW()-4 -> 40 | C44: 全国版SS更新 | D44: ＰＯＳ給油所マスタ更新 | F44: 45761 | G44: 45777 | H44: 0 | I44: 0 | J44: =SUM(H44:I44) -> 0 | K44: 0 | L44: 0 | M44: =SUM(K44:L44) -> 0 | R44: =CEILING(IF($Q44="新規", IF($P44="特高", R$4*特高係数,IF($P44="高",R$4*高係数,IF($P44="中",R$4*中係数,IF($P44="低",R$4*低係数, IF($P44="特低",R$4*特低係数, 0))))), IF($P44="特高", R$4*特高係数,IF($P44="高",R$4*高係数,IF($P44="中",R$4*中係数,IF($P44="低",R$4*低係数, IF($P44="特低",R$4*特低係数, 0)))))),0.125) -> 0 | S44: =CEILING(IF($Q44="新規", IF($P44="特高", S$4*特高係数,IF($P44="高",S$4*高係数,IF($P44="中",S$4*中係数,IF($P44="低",S$4*低係数, IF($P44="特低",S$4*特低係数, 0))))), IF($P44="特高", S$4*特高係数,IF($P44="高",S$4*高係数,IF($P44="中",S$4*中係数,IF($P44="低",S$4*低係数, IF($P44="特低",S$4*特低係数, 0)))))),0.125) -> 0 | T44: =CEILING(IF($Q44="新規", IF($P44="特高", T$4*特高係数,IF($P44="高",T$4*高係数,IF($P44="中",T$4*中係数,IF($P44="低",T$4*低係数, IF($P44="特低",T$4*特低係数, 0))))), IF($P44="特高", T$4*特高係数,IF($P44="高",T$4*高係数,IF($P44="中",T$4*中係数,IF($P44="低",T$4*低係数, IF($P44="特低",T$4*特低係数, 0)))))),0.125) -> 0 | U44: =SUM(R44:T44) -> 0 | V44: =U44/20 -> 0
D45: CTC向け全国版SSﾏｽﾀ | F45: 45761 | G45: 45777 | H45: 10 | I45: 6 | J45: =SUM(H45:I45) -> 16 | K45: 32 | L45: =K45*0.8 -> 25.6 | M45: =SUM(K45:L45) -> 57.6 | P45: 特高 | Q45: 新規 | R45: =CEILING(IF($Q45="新規", IF($P45="特高", R$4*特高係数,IF($P45="高",R$4*高係数,IF($P45="中",R$4*中係数,IF($P45="低",R$4*低係数, IF($P45="特低",R$4*特低係数, 0))))), IF($P45="特高", R$4*特高係数,IF($P45="高",R$4*高係数,IF($P45="中",R$4*中係数,IF($P45="低",R$4*低係数, IF($P45="特低",R$4*特低係数, 0)))))),0.125) -> 1.375 | S45: =CEILING(IF($Q45="新規", IF($P45="特高", S$4*特高係数,IF($P45="高",S$4*高係数,IF($P45="中",S$4*中係数,IF($P45="低",S$4*低係数, IF($P45="特低",S$4*特低係数, 0))))), IF($P45="特高", S$4*特高係数,IF($P45="高",S$4*高係数,IF($P45="中",S$4*中係数,IF($P45="低",S$4*低係数, IF($P45="特低",S$4*特低係数, 0)))))),0.125) -> 15.25 | T45: =CEILING(IF($Q45="新規", IF($P45="特高", T$4*特高係数,IF($P45="高",T$4*高係数,IF($P45="中",T$4*中係数,IF($P45="低",T$4*低係数, IF($P45="特低",T$4*特低係数, 0))))), IF($P45="特高", T$4*特高係数,IF($P45="高",T$4*高係数,IF($P45="中",T$4*中係数,IF($P45="低",T$4*低係数, IF($P45="特低",T$4*特低係数, 0)))))),0.125) -> 12.375 | U45: =SUM(R45:T45) -> 29 | V45: =U45/20 -> 1.45
D46: 全国版SSﾏｽﾀ差分 | F46: 45761 | G46: 45777 | H46: 8 | I46: 4 | J46: =SUM(H46:I46) -> 12 | L46: =K46*0.8 -> 0 | M46: =SUM(K46:L46) -> 0 | P46: 高 | Q46: 新規 | R46: =CEILING(IF($Q46="新規", IF($P46="特高", R$4*特高係数,IF($P46="高",R$4*高係数,IF($P46="中",R$4*中係数,IF($P46="低",R$4*低係数, IF($P46="特低",R$4*特低係数, 0))))), IF($P46="特高", R$4*特高係数,IF($P46="高",R$4*高係数,IF($P46="中",R$4*中係数,IF($P46="低",R$4*低係数, IF($P46="特低",R$4*特低係数, 0)))))),0.125) -> 1 | S46: =CEILING(IF($Q46="新規", IF($P46="特高", S$4*特高係数,IF($P46="高",S$4*高係数,IF($P46="中",S$4*中係数,IF($P46="低",S$4*低係数, IF($P46="特低",S$4*特低係数, 0))))), IF($P46="特高", S$4*特高係数,IF($P46="高",S$4*高係数,IF($P46="中",S$4*中係数,IF($P46="低",S$4*低係数, IF($P46="特低",S$4*特低係数, 0)))))),0.125) -> 11.75 | T46: =CEILING(IF($Q46="新規", IF($P46="特高", T$4*特高係数,IF($P46="高",T$4*高係数,IF($P46="中",T$4*中係数,IF($P46="低",T$4*低係数, IF($P46="特低",T$4*特低係数, 0))))), IF($P46="特高", T$4*特高係数,IF($P46="高",T$4*高係数,IF($P46="中",T$4*中係数,IF($P46="低",T$4*低係数, IF($P46="特低",T$4*特低係数, 0)))))),0.125) -> 9.5 | U46: =SUM(R46:T46) -> 22.25 | V46: =U46/20 -> 1.1125
D47: SS台帳、給油所マスタ更新 | F47: 45761 | G47: 45777 | H47: 0 | I47: 0 | J47: =SUM(H47:I47) -> 0 | K47: 0 | L47: 0 | M47: =SUM(K47:L47) -> 0 | R47: =CEILING(IF($Q47="新規", IF($P47="特高", R$4*特高係数,IF($P47="高",R$4*高係数,IF($P47="中",R$4*中係数,IF($P47="低",R$4*低係数, IF($P47="特低",R$4*特低係数, 0))))), IF($P47="特高", R$4*特高係数,IF($P47="高",R$4*高係数,IF($P47="中",R$4*中係数,IF($P47="低",R$4*低係数, IF($P47="特低",R$4*特低係数, 0)))))),0.125) -> 0 | S47: =CEILING(IF($Q47="新規", IF($P47="特高", S$4*特高係数,IF($P47="高",S$4*高係数,IF($P47="中",S$4*中係数,IF($P47="低",S$4*低係数, IF($P47="特低",S$4*特低係数, 0))))), IF($P47="特高", S$4*特高係数,IF($P47="高",S$4*高係数,IF($P47="中",S$4*中係数,IF($P47="低",S$4*低係数, IF($P47="特低",S$4*特低係数, 0)))))),0.125) -> 0 | T47: =CEILING(IF($Q47="新規", IF($P47="特高", T$4*特高係数,IF($P47="高",T$4*高係数,IF($P47="中",T$4*中係数,IF($P47="低",T$4*低係数, IF($P47="特低",T$4*特低係数, 0))))), IF($P47="特高", T$4*特高係数,IF($P47="高",T$4*高係数,IF($P47="中",T$4*中係数,IF($P47="低",T$4*低係数, IF($P47="特低",T$4*特低係数, 0)))))),0.125) -> 0 | U47: =SUM(R47:T47) -> 0 | V47: =U47/20 -> 0
A48: =ROW()-4 -> 44 | C48: 企業情報 | D48: 企業情報検索 | F48: 45778 | G48: 45784 | H48: 8 | I48: 4 | J48: =SUM(H48:I48) -> 12 | K48: 16 | L48: =K48*0.8 -> 12.8 | M48: =SUM(K48:L48) -> 28.8 | N48: 外部接続 | P48: 高 | Q48: 新規 | R48: =CEILING(IF($Q48="新規", IF($P48="特高", R$4*特高係数,IF($P48="高",R$4*高係数,IF($P48="中",R$4*中係数,IF($P48="低",R$4*低係数, IF($P48="特低",R$4*特低係数, 0))))), IF($P48="特高", R$4*特高係数,IF($P48="高",R$4*高係数,IF($P48="中",R$4*中係数,IF($P48="低",R$4*低係数, IF($P48="特低",R$4*特低係数, 0)))))),0.125) -> 1 | S48: =CEILING(IF($Q48="新規", IF($P48="特高", S$4*特高係数,IF($P48="高",S$4*高係数,IF($P48="中",S$4*中係数,IF($P48="低",S$4*低係数, IF($P48="特低",S$4*特低係数, 0))))), IF($P48="特高", S$4*特高係数,IF($P48="高",S$4*高係数,IF($P48="中",S$4*中係数,IF($P48="低",S$4*低係数, IF($P48="特低",S$4*特低係数, 0)))))),0.125) -> 11.75 | T48: =CEILING(IF($Q48="新規", IF($P48="特高", T$4*特高係数,IF($P48="高",T$4*高係数,IF($P48="中",T$4*中係数,IF($P48="低",T$4*低係数, IF($P48="特低",T$4*特低係数, 0))))), IF($P48="特高", T$4*特高係数,IF($P48="高",T$4*高係数,IF($P48="中",T$4*中係数,IF($P48="低",T$4*低係数, IF($P48="特低",T$4*特低係数, 0)))))),0.125) -> 9.5 | U48: =SUM(R48:T48) -> 22.25 | V48: =U48/20 -> 1.1125
A49: =ROW()-4 -> 45 | C49: 処理用SSマスタ作成 | D49: 新SS台帳から処理用SS台帳の作成（バッチ処理） | F49: 45761 | G49: 45779 | H49: 12 | I49: 6 | J49: =SUM(H49:I49) -> 18 | L49: =K49*0.8 -> 0 | M49: =SUM(K49:L49) -> 0 | P49: 特高 | Q49: 新規 | R49: =CEILING(IF($Q49="新規", IF($P49="特高", R$4*特高係数,IF($P49="高",R$4*高係数,IF($P49="中",R$4*中係数,IF($P49="低",R$4*低係数, IF($P49="特低",R$4*特低係数, 0))))), IF($P49="特高", R$4*特高係数,IF($P49="高",R$4*高係数,IF($P49="中",R$4*中係数,IF($P49="低",R$4*低係数, IF($P49="特低",R$4*特低係数, 0)))))),0.125) -> 1.375 | S49: =CEILING(IF($Q49="新規", IF($P49="特高", S$4*特高係数,IF($P49="高",S$4*高係数,IF($P49="中",S$4*中係数,IF($P49="低",S$4*低係数, IF($P49="特低",S$4*特低係数, 0))))), IF($P49="特高", S$4*特高係数,IF($P49="高",S$4*高係数,IF($P49="中",S$4*中係数,IF($P49="低",S$4*低係数, IF($P49="特低",S$4*特低係数, 0)))))),0.125) -> 15.25 | T49: =CEILING(IF($Q49="新規", IF($P49="特高", T$4*特高係数,IF($P49="高",T$4*高係数,IF($P49="中",T$4*中係数,IF($P49="低",T$4*低係数, IF($P49="特低",T$4*特低係数, 0))))), IF($P49="特高", T$4*特高係数,IF($P49="高",T$4*高係数,IF($P49="中",T$4*中係数,IF($P49="低",T$4*低係数, IF($P49="特低",T$4*特低係数, 0)))))),0.125) -> 12.375 | U49: =SUM(R49:T49) -> 29 | V49: =U49/20 -> 1.45
A50: 合計（人日） | R50: =SUM(R5:R49) -> 33.3 | S50: =SUM(S5:S49) -> 398.975 | T50: =SUM(T5:T49) -> 323.575 | U50: =SUM(R50:T50) -> 755.85
A51: 合計（人月） | R51: =R50/20 -> 1.665 | S51: =S50/20 -> 19.94875 | T51: =T50/20 -> 16.17875 | V51: =SUM(R51:T51) -> 37.7925
Q52: 作業金額 | R52: =ROUNDUP(R51, 1) * 1000000 -> 1700000 | S52: =ROUNDUP(S51, 1) * 1000000 -> 20000000 | T52: =ROUNDUP(T51, 1) * 1000000 -> 16200000 | V52: =SUM(R52:T52) -> 37900000
Q53: 管理 + プレ工数 | R53: =ROUNDUP(SUM(R51:R51)*0.2,1) -> 0.4 | S53: =ROUNDUP(SUM(S51)*0.2,1) -> 4 | T53: =ROUNDUP(SUM(T51)*0.2,1) -> 3.3 | V53: =SUM(R53:T53) -> 7.7
Q54: 管理 + プレ工数 金額 | R54: =R53 * 1400000 -> 560000 | S54: =S53 * 1400000 -> 5600000 | T54: =T53 * 1400000 -> 4620000 | V54: =SUM(R54:T54) -> 10780000
Q55: 合計 | R55: =R52 + R54 -> 2260000 | S55: =S52 + S54 -> 25600000 | T55: =T52 + T54 -> 20820000 | V55: =SUM(R55:T55) -> 48680000
A56: 総工数 | U56: =SUM(U50:U55) -> 755.85 | V56: =V51+V53 -> 45.4925

Sheet 御見積(画面・機能) (1倍)
A2: № | B2: システム名 | C2: 機能名 | F2: JCC詳細設計 | H2: JCC見積 | K2: エグゼ見積 | N2: 分類 | O2: 機能画面説明 | P2: 難易度 | Q2: 新規 改修 | R2: 工程別工数（人日） | U2: 合計 （人日） | V2: 合計 （人月） | W2: 備考
C3: 大項目 | D3: 中項目 | E3: 小項目 | F3: 開始 | G3: 終了 | H3: 製造単体工数 | I3: 結合試験工数 | J3: 合計 | K3: 製造単体工数 | L3: 結合試験工数 | M3: 合計 | R3: 概要把握 設計レビュー | S3: 開発/単体テスト | T3: 結合テスト
A4: 基準工数 | R4: 0.5 | S4: =1.2*積算基準!F58 -> 3.9 | T4: =1.2*積算基準!G58 -> 3.15
A5: =ROW()-4 -> 1 | C5: 共通 | D5: アーキテクチャ | N5: 機能 | O5: システムアーキテクチャを構築 | P5: 中 | Q5: 新規 | R5: 0 | S5: =CEILING(IF($Q5="新規", IF($P5="特高", S$4*特高係数,IF($P5="高",S$4*高係数,IF($P5="中",S$4*中係数,IF($P5="低",S$4*低係数, IF($P5="特低",S$4*特低係数, 0))))), IF($P5="特高", S$4*特高係数,IF($P5="高",S$4*高係数,IF($P5="中",S$4*中係数,IF($P5="低",S$4*低係数, IF($P5="特低",S$4*特低係数, 0)))))),0.125) -> 6.25 | T5: =CEILING(IF($Q5="新規", IF($P5="特高", T$4*特高係数,IF($P5="高",T$4*高係数,IF($P5="中",T$4*中係数,IF($P5="低",T$4*低係数, IF($P5="特低",T$4*特低係数, 0))))), IF($P5="特高", T$4*特高係数,IF($P5="高",T$4*高係数,IF($P5="中",T$4*中係数,IF($P5="低",T$4*低係数, IF($P5="特低",T$4*特低係数, 0)))))),0.125) -> 5.125 | U5: =SUM(R5:T5) -> 11.375 | V5: =U5/20 -> 0.56875
D6: 開発環境・把握・構築 | P6: 中 | Q6: 新規 | R6: 0 | S6: =CEILING(IF($Q6="新規", IF($P6="特高", S$4*特高係数,IF($P6="高",S$4*高係数,IF($P6="中",S$4*中係数,IF($P6="低",S$4*低係数, IF($P6="特低",S$4*特低係数, 0))))), IF($P6="特高", S$4*特高係数,IF($P6="高",S$4*高係数,IF($P6="中",S$4*中係数,IF($P6="低",S$4*低係数, IF($P6="特低",S$4*特低係数, 0)))))),0.125) -> 6.25 | T6: =CEILING(IF($Q6="新規", IF($P6="特高", T$4*特高係数,IF($P6="高",T$4*高係数,IF($P6="中",T$4*中係数,IF($P6="低",T$4*低係数, IF($P6="特低",T$4*特低係数, 0))))), IF($P6="特高", T$4*特高係数,IF($P6="高",T$4*高係数,IF($P6="中",T$4*中係数,IF($P6="低",T$4*低係数, IF($P6="特低",T$4*特低係数, 0)))))),0.125) -> 5.125 | U6: =SUM(R6:T6) -> 11.375 | V6: =U6/20 -> 0.56875
D7: Azure環境構築（データレイク含む） | P7: 中 | Q7: 新規 | R7: 0 | S7: =CEILING(IF($Q7="新規", IF($P7="特高", S$4*特高係数,IF($P7="高",S$4*高係数,IF($P7="中",S$4*中係数,IF($P7="低",S$4*低係数, IF($P7="特低",S$4*特低係数, 0))))), IF($P7="特高", S$4*特高係数,IF($P7="高",S$4*高係数,IF($P7="中",S$4*中係数,IF($P7="低",S$4*低係数, IF($P7="特低",S$4*特低係数, 0)))))),0.125) -> 6.25 | T7: =CEILING(IF($Q7="新規", IF($P7="特高", T$4*特高係数,IF($P7="高",T$4*高係数,IF($P7="中",T$4*中係数,IF($P7="低",T$4*低係数, IF($P7="特低",T$4*特低係数, 0))))), IF($P7="特高", T$4*特高係数,IF($P7="高",T$4*高係数,IF($P7="中",T$4*中係数,IF($P7="低",T$4*低係数, IF($P7="特低",T$4*特低係数, 0)))))),0.125) -> 5.125 | U7: =SUM(R7:T7) -> 11.375 | V7: =U7/20 -> 0.56875
D8: 結合テスト計画作成 | P8: 中 | Q8: 新規 | R8: 0 | S8: =CEILING(IF($Q8="新規", IF($P8="特高", S$4*特高係数,IF($P8="高",S$4*高係数,IF($P8="中",S$4*中係数,IF($P8="低",S$4*低係数, IF($P8="特低",S$4*特低係数, 0))))), IF($P8="特高", S$4*特高係数,IF($P8="高",S$4*高係数,IF($P8="中",S$4*中係数,IF($P8="低",S$4*低係数, IF($P8="特低",S$4*特低係数, 0)))))),0.125) -> 6.25 | T8: =CEILING(IF($Q8="新規", IF($P8="特高", T$4*特高係数,IF($P8="高",T$4*高係数,IF($P8="中",T$4*中係数,IF($P8="低",T$4*低係数, IF($P8="特低",T$4*特低係数, 0))))), IF($P8="特高", T$4*特高係数,IF($P8="高",T$4*高係数,IF($P8="中",T$4*中係数,IF($P8="低",T$4*低係数, IF($P8="特低",T$4*特低係数, 0)))))),0.125) -> 5.125 | U8: =SUM(R8:T8) -> 11.375 | V8: =U8/20 -> 0.56875
D9: A-AUTO設定 | P9: 中 | Q9: 新規 | R9: 0 | S9: =CEILING(IF($Q9="新規", IF($P9="特高", S$4*特高係数,IF($P9="高",S$4*高係数,IF($P9="中",S$4*中係数,IF($P9="低",S$4*低係数, IF($P9="特低",S$4*特低係数, 0))))), IF($P9="特高", S$4*特高係数,IF($P9="高",S$4*高係数,IF($P9="中",S$4*中係数,IF($P9="低",S$4*低係数, IF($P9="特低",S$4*特低係数, 0)))))),0.125) -> 6.25 | T9: =CEILING(IF($Q9="新規", IF($P9="特高", T$4*特高係数,IF($P9="高",T$4*高係数,IF($P9="中",T$4*中係数,IF($P9="低",T$4*低係数, IF($P9="特低",T$4*特低係数, 0))))), IF($P9="特高", T$4*特高係数,IF($P9="高",T$4*高係数,IF($P9="中",T$4*中係数,IF($P9="低",T$4*低係数, IF($P9="特低",T$4*特低係数, 0)))))),0.125) -> 5.125 | U9: =SUM(R9:T9) -> 11.375 | V9: =U9/20 -> 0.56875
A10: =ROW()-4 -> 6 | C10: セルイン | D10: セルインTBL | F10: 45754 | G10: 45838 | H10: 8 | I10: 4 | J10: =SUM(H10:I10) -> 12 | L10: =K10*0.8 -> 0 | M10: =SUM(K10:L10) -> 0 | N10: DB | P10: 高 | Q10: 新規 | R10: =CEILING(IF($Q10="新規", IF($P10="特高", R$4*特高係数,IF($P10="高",R$4*高係数,IF($P10="中",R$4*中係数,IF($P10="低",R$4*低係数, IF($P10="特低",R$4*特低係数, 0))))), IF($P10="特高", R$4*特高係数,IF($P10="高",R$4*高係数,IF($P10="中",R$4*中係数,IF($P10="低",R$4*低係数, IF($P10="特低",R$4*特低係数, 0)))))),0.125) -> 1 | S10: =CEILING(IF($Q10="新規", IF($P10="特高", S$4*特高係数,IF($P10="高",S$4*高係数,IF($P10="中",S$4*中係数,IF($P10="低",S$4*低係数, IF($P10="特低",S$4*特低係数, 0))))), IF($P10="特高", S$4*特高係数,IF($P10="高",S$4*高係数,IF($P10="中",S$4*中係数,IF($P10="低",S$4*低係数, IF($P10="特低",S$4*特低係数, 0)))))),0.125) -> 7.875 | T10: =CEILING(IF($Q10="新規", IF($P10="特高", T$4*特高係数,IF($P10="高",T$4*高係数,IF($P10="中",T$4*中係数,IF($P10="低",T$4*低係数, IF($P10="特低",T$4*特低係数, 0))))), IF($P10="特高", T$4*特高係数,IF($P10="高",T$4*高係数,IF($P10="中",T$4*中係数,IF($P10="低",T$4*低係数, IF($P10="特低",T$4*特低係数, 0)))))),0.125) -> 6.375 | U10: =SUM(R10:T10) -> 15.25 | V10: =U10/20 -> 0.7625
D11: 売上原価伝送データ | F11: 45754 | G11: 45838 | H11: 8 | I11: 4 | J11: =SUM(H11:I11) -> 12 | L11: =K11*0.8 -> 0 | M11: =SUM(K11:L11) -> 0 | N11: BO | P11: 高 | Q11: 新規 | R11: =CEILING(IF($Q11="新規", IF($P11="特高", R$4*特高係数,IF($P11="高",R$4*高係数,IF($P11="中",R$4*中係数,IF($P11="低",R$4*低係数, IF($P11="特低",R$4*特低係数, 0))))), IF($P11="特高", R$4*特高係数,IF($P11="高",R$4*高係数,IF($P11="中",R$4*中係数,IF($P11="低",R$4*低係数, IF($P11="特低",R$4*特低係数, 0)))))),0.125) -> 1 | S11: =CEILING(IF($Q11="新規", IF($P11="特高", S$4*特高係数,IF($P11="高",S$4*高係数,IF($P11="中",S$4*中係数,IF($P11="低",S$4*低係数, IF($P11="特低",S$4*特低係数, 0))))), IF($P11="特高", S$4*特高係数,IF($P11="高",S$4*高係数,IF($P11="中",S$4*中係数,IF($P11="低",S$4*低係数, IF($P11="特低",S$4*特低係数, 0)))))),0.125) -> 7.875 | T11: =CEILING(IF($Q11="新規", IF($P11="特高", T$4*特高係数,IF($P11="高",T$4*高係数,IF($P11="中",T$4*中係数,IF($P11="低",T$4*低係数, IF($P11="特低",T$4*特低係数, 0))))), IF($P11="特高", T$4*特高係数,IF($P11="高",T$4*高係数,IF($P11="中",T$4*中係数,IF($P11="低",T$4*低係数, IF($P11="特低",T$4*特低係数, 0)))))),0.125) -> 6.375 | U11: =SUM(R11:T11) -> 15.25 | V11: =U11/20 -> 0.7625
D12: 販売実績数量価格推移表 1 | F12: 45754 | G12: 45838 | H12: 18 | I12: 9 | J12: =SUM(H12:I12) -> 27 | L12: =K12*0.8 -> 0 | M12: =SUM(K12:L12) -> 0 | N12: 帳票 | P12: 高 | Q12: 新規 | R12: =CEILING(IF($Q12="新規", IF($P12="特高", R$4*特高係数,IF($P12="高",R$4*高係数,IF($P12="中",R$4*中係数,IF($P12="低",R$4*低係数, IF($P12="特低",R$4*特低係数, 0))))), IF($P12="特高", R$4*特高係数,IF($P12="高",R$4*高係数,IF($P12="中",R$4*中係数,IF($P12="低",R$4*低係数, IF($P12="特低",R$4*特低係数, 0)))))),0.125) -> 1 | S12: =CEILING(IF($Q12="新規", IF($P12="特高", S$4*特高係数,IF($P12="高",S$4*高係数,IF($P12="中",S$4*中係数,IF($P12="低",S$4*低係数, IF($P12="特低",S$4*特低係数, 0))))), IF($P12="特高", S$4*特高係数,IF($P12="高",S$4*高係数,IF($P12="中",S$4*中係数,IF($P12="低",S$4*低係数, IF($P12="特低",S$4*特低係数, 0)))))),0.125) -> 7.875 | T12: =CEILING(IF($Q12="新規", IF($P12="特高", T$4*特高係数,IF($P12="高",T$4*高係数,IF($P12="中",T$4*中係数,IF($P12="低",T$4*低係数, IF($P12="特低",T$4*特低係数, 0))))), IF($P12="特高", T$4*特高係数,IF($P12="高",T$4*高係数,IF($P12="中",T$4*中係数,IF($P12="低",T$4*低係数, IF($P12="特低",T$4*特低係数, 0)))))),0.125) -> 6.375 | U12: =SUM(R12:T12) -> 15.25 | V12: =U12/20 -> 0.7625
D13: 販売実績数量価格推移表 2 | F13: 45754 | G13: 45838 | J13: =SUM(H13:I13) -> 0 | L13: =K13*0.8 -> 0 | M13: =SUM(K13:L13) -> 0 | N13: 帳票 | P13: 低 | Q13: 新規 | R13: =CEILING(IF($Q13="新規", IF($P13="特高", R$4*特高係数,IF($P13="高",R$4*高係数,IF($P13="中",R$4*中係数,IF($P13="低",R$4*低係数, IF($P13="特低",R$4*特低係数, 0))))), IF($P13="特高", R$4*特高係数,IF($P13="高",R$4*高係数,IF($P13="中",R$4*中係数,IF($P13="低",R$4*低係数, IF($P13="特低",R$4*特低係数, 0)))))),0.125) -> 0.375 | S13: =CEILING(IF($Q13="新規", IF($P13="特高", S$4*特高係数,IF($P13="高",S$4*高係数,IF($P13="中",S$4*中係数,IF($P13="低",S$4*低係数, IF($P13="特低",S$4*特低係数, 0))))), IF($P13="特高", S$4*特高係数,IF($P13="高",S$4*高係数,IF($P13="中",S$4*中係数,IF($P13="低",S$4*低係数, IF($P13="特低",S$4*特低係数, 0)))))),0.125) -> 2.75 | T13: =CEILING(IF($Q13="新規", IF($P13="特高", T$4*特高係数,IF($P13="高",T$4*高係数,IF($P13="中",T$4*中係数,IF($P13="低",T$4*低係数, IF($P13="特低",T$4*特低係数, 0))))), IF($P13="特高", T$4*特高係数,IF($P13="高",T$4*高係数,IF($P13="中",T$4*中係数,IF($P13="低",T$4*低係数, IF($P13="特低",T$4*特低係数, 0)))))),0.125) -> 2.25 | U13: =SUM(R13:T13) -> 5.375 | V13: =U13/20 -> 0.26875
D14: 販売実績数量価格推移表 3 | F14: 45754 | G14: 45838 | J14: =SUM(H14:I14) -> 0 | L14: =K14*0.8 -> 0 | M14: =SUM(K14:L14) -> 0 | N14: 帳票 | P14: 低 | Q14: 新規 | R14: =CEILING(IF($Q14="新規", IF($P14="特高", R$4*特高係数,IF($P14="高",R$4*高係数,IF($P14="中",R$4*中係数,IF($P14="低",R$4*低係数, IF($P14="特低",R$4*特低係数, 0))))), IF($P14="特高", R$4*特高係数,IF($P14="高",R$4*高係数,IF($P14="中",R$4*中係数,IF($P14="低",R$4*低係数, IF($P14="特低",R$4*特低係数, 0)))))),0.125) -> 0.375 | S14: =CEILING(IF($Q14="新規", IF($P14="特高", S$4*特高係数,IF($P14="高",S$4*高係数,IF($P14="中",S$4*中係数,IF($P14="低",S$4*低係数, IF($P14="特低",S$4*特低係数, 0))))), IF($P14="特高", S$4*特高係数,IF($P14="高",S$4*高係数,IF($P14="中",S$4*中係数,IF($P14="低",S$4*低係数, IF($P14="特低",S$4*特低係数, 0)))))),0.125) -> 2.75 | T14: =CEILING(IF($Q14="新規", IF($P14="特高", T$4*特高係数,IF($P14="高",T$4*高係数,IF($P14="中",T$4*中係数,IF($P14="低",T$4*低係数, IF($P14="特低",T$4*特低係数, 0))))), IF($P14="特高", T$4*特高係数,IF($P14="高",T$4*高係数,IF($P14="中",T$4*中係数,IF($P14="低",T$4*低係数, IF($P14="特低",T$4*特低係数, 0)))))),0.125) -> 2.25 | U14: =SUM(R14:T14) -> 5.375 | V14: =U14/20 -> 0.26875
D15: 販売実績数量価格推移表 4 | F15: 45754 | G15: 45838 | J15: =SUM(H15:I15) -> 0 | L15: =K15*0.8 -> 0 | M15: =SUM(K15:L15) -> 0 | N15: 帳票 | P15: 低 | Q15: 新規 | R15: =CEILING(IF($Q15="新規", IF($P15="特高", R$4*特高係数,IF($P15="高",R$4*高係数,IF($P15="中",R$4*中係数,IF($P15="低",R$4*低係数, IF($P15="特低",R$4*特低係数, 0))))), IF($P15="特高", R$4*特高係数,IF($P15="高",R$4*高係数,IF($P15="中",R$4*中係数,IF($P15="低",R$4*低係数, IF($P15="特低",R$4*特低係数, 0)))))),0.125) -> 0.375 | S15: =CEILING(IF($Q15="新規", IF($P15="特高", S$4*特高係数,IF($P15="高",S$4*高係数,IF($P15="中",S$4*中係数,IF($P15="低",S$4*低係数, IF($P15="特低",S$4*特低係数, 0))))), IF($P15="特高", S$4*特高係数,IF($P15="高",S$4*高係数,IF($P15="中",S$4*中係数,IF($P15="低",S$4*低係数, IF($P15="特低",S$4*特低係数, 0)))))),0.125) -> 2.75 | T15: =CEILING(IF($Q15="新規", IF($P15="特高", T$4*特高係数,IF($P15="高",T$4*高係数,IF($P15="中",T$4*中係数,IF($P15="低",T$4*低係数, IF($P15="特低",T$4*特低係数, 0))))), IF($P15="特高", T$4*特高係数,IF($P15="高",T$4*高係数,IF($P15="中",T$4*中係数,IF($P15="低",T$4*低係数, IF($P15="特低",T$4*特低係数, 0)))))),0.125) -> 2.25 | U15: =SUM(R15:T15) -> 5.375 | V15: =U15/20 -> 0.26875
D16: 販売実績数量価格推移表 5 | F16: 45754 | G16: 45838 | J16: =SUM(H16:I16) -> 0 | L16: =K16*0.8 -> 0 | M16: =SUM(K16:L16) -> 0 | N16: 帳票 | P16: 低 | Q16: 新規 | R16: =CEILING(IF($Q16="新規", IF($P16="特高", R$4*特高係数,IF($P16="高",R$4*高係数,IF($P16="中",R$4*中係数,IF($P16="低",R$4*低係数, IF($P16="特低",R$4*特低係数, 0))))), IF($P16="特高", R$4*特高係数,IF($P16="高",R$4*高係数,IF($P16="中",R$4*中係数,IF($P16="低",R$4*低係数, IF($P16="特低",R$4*特低係数, 0)))))),0.125) -> 0.375 | S16: =CEILING(IF($Q16="新規", IF($P16="特高", S$4*特高係数,IF($P16="高",S$4*高係数,IF($P16="中",S$4*中係数,IF($P16="低",S$4*低係数, IF($P16="特低",S$4*特低係数, 0))))), IF($P16="特高", S$4*特高係数,IF($P16="高",S$4*高係数,IF($P16="中",S$4*中係数,IF($P16="低",S$4*低係数, IF($P16="特低",S$4*特低係数, 0)))))),0.125) -> 2.75 | T16: =CEILING(IF($Q16="新規", IF($P16="特高", T$4*特高係数,IF($P16="高",T$4*高係数,IF($P16="中",T$4*中係数,IF($P16="低",T$4*低係数, IF($P16="特低",T$4*特低係数, 0))))), IF($P16="特高", T$4*特高係数,IF($P16="高",T$4*高係数,IF($P16="中",T$4*中係数,IF($P16="低",T$4*低係数, IF($P16="特低",T$4*特低係数, 0)))))),0.125) -> 2.25 | U16: =SUM(R16:T16) -> 5.375 | V16: =U16/20 -> 0.26875
D17: セルインデータ伝送 | F17: 45754 | G17: 45838 | H17: 8 | I17: 4 | J17: =SUM(H17:I17) -> 12 | L17: =K17*0.8 -> 0 | M17: =SUM(K17:L17) -> 0 | N17: BO | P17: 高 | Q17: 新規 | R17: =CEILING(IF($Q17="新規", IF($P17="特高", R$4*特高係数,IF($P17="高",R$4*高係数,IF($P17="中",R$4*中係数,IF($P17="低",R$4*低係数, IF($P17="特低",R$4*特低係数, 0))))), IF($P17="特高", R$4*特高係数,IF($P17="高",R$4*高係数,IF($P17="中",R$4*中係数,IF($P17="低",R$4*低係数, IF($P17="特低",R$4*特低係数, 0)))))),0.125) -> 1 | S17: =CEILING(IF($Q17="新規", IF($P17="特高", S$4*特高係数,IF($P17="高",S$4*高係数,IF($P17="中",S$4*中係数,IF($P17="低",S$4*低係数, IF($P17="特低",S$4*特低係数, 0))))), IF($P17="特高", S$4*特高係数,IF($P17="高",S$4*高係数,IF($P17="中",S$4*中係数,IF($P17="低",S$4*低係数, IF($P17="特低",S$4*特低係数, 0)))))),0.125) -> 7.875 | T17: =CEILING(IF($Q17="新規", IF($P17="特高", T$4*特高係数,IF($P17="高",T$4*高係数,IF($P17="中",T$4*中係数,IF($P17="低",T$4*低係数, IF($P17="特低",T$4*特低係数, 0))))), IF($P17="特高", T$4*特高係数,IF($P17="高",T$4*高係数,IF($P17="中",T$4*中係数,IF($P17="低",T$4*低係数, IF($P17="特低",T$4*特低係数, 0)))))),0.125) -> 6.375 | U17: =SUM(R17:T17) -> 15.25 | V17: =U17/20 -> 0.7625
D18: セルイン月次TBL | F18: 45754 | G18: 45838 | H18: 0 | I18: 0 | J18: =SUM(H18:I18) -> 0 | K18: 0 | L18: 0 | M18: =SUM(K18:L18) -> 0 | N18: 内部TBL | R18: =CEILING(IF($Q18="新規", IF($P18="特高", R$4*特高係数,IF($P18="高",R$4*高係数,IF($P18="中",R$4*中係数,IF($P18="低",R$4*低係数, IF($P18="特低",R$4*特低係数, 0))))), IF($P18="特高", R$4*特高係数,IF($P18="高",R$4*高係数,IF($P18="中",R$4*中係数,IF($P18="低",R$4*低係数, IF($P18="特低",R$4*特低係数, 0)))))),0.125) -> 0 | S18: =CEILING(IF($Q18="新規", IF($P18="特高", S$4*特高係数,IF($P18="高",S$4*高係数,IF($P18="中",S$4*中係数,IF($P18="低",S$4*低係数, IF($P18="特低",S$4*特低係数, 0))))), IF($P18="特高", S$4*特高係数,IF($P18="高",S$4*高係数,IF($P18="中",S$4*中係数,IF($P18="低",S$4*低係数, IF($P18="特低",S$4*特低係数, 0)))))),0.125) -> 0 | T18: =CEILING(IF($Q18="新規", IF($P18="特高", T$4*特高係数,IF($P18="高",T$4*高係数,IF($P18="中",T$4*中係数,IF($P18="低",T$4*低係数, IF($P18="特低",T$4*特低係数, 0))))), IF($P18="特高", T$4*特高係数,IF($P18="高",T$4*高係数,IF($P18="中",T$4*中係数,IF($P18="低",T$4*低係数, IF($P18="特低",T$4*特低係数, 0)))))),0.125) -> 0 | U18: =SUM(R18:T18) -> 0 | V18: =U18/20 -> 0
A19: =ROW()-4 -> 15 | C19: セルアウト | D19: セルアウト日別過去データ伝送 | F19: 45748 | G19: 45777 | H19: 0 | I19: 0 | J19: =SUM(H19:I19) -> 0 | K19: 0 | L19: 0 | M19: =SUM(K19:L19) -> 0 | N19: BO | R19: =CEILING(IF($Q19="新規", IF($P19="特高", R$4*特高係数,IF($P19="高",R$4*高係数,IF($P19="中",R$4*中係数,IF($P19="低",R$4*低係数, IF($P19="特低",R$4*特低係数, 0))))), IF($P19="特高", R$4*特高係数,IF($P19="高",R$4*高係数,IF($P19="中",R$4*中係数,IF($P19="低",R$4*低係数, IF($P19="特低",R$4*特低係数, 0)))))),0.125) -> 0 | S19: =CEILING(IF($Q19="新規", IF($P19="特高", S$4*特高係数,IF($P19="高",S$4*高係数,IF($P19="中",S$4*中係数,IF($P19="低",S$4*低係数, IF($P19="特低",S$4*特低係数, 0))))), IF($P19="特高", S$4*特高係数,IF($P19="高",S$4*高係数,IF($P19="中",S$4*中係数,IF($P19="低",S$4*低係数, IF($P19="特低",S$4*特低係数, 0)))))),0.125) -> 0 | T19: =CEILING(IF($Q19="新規", IF($P19="特高", T$4*特高係数,IF($P19="高",T$4*高係数,IF($P19="中",T$4*中係数,IF($P19="低",T$4*低係数, IF($P19="特低",T$4*特低係数, 0))))), IF($P19="特高", T$4*特高係数,IF($P19="高",T$4*高係数,IF($P19="中",T$4*中係数,IF($P19="低",T$4*低係数, IF($P19="特低",T$4*特低係数, 0)))))),0.125) -> 0 | U19: =SUM(R19:T19) -> 0 | V19: =U19/20 -> 0
D20: セルアウト日毎テーブル伝送 | F20: 45748 | G20: 45777 | H20: 8 | I20: 4 | J20: =SUM(H20:I20) -> 12 | L20: =K20*0.8 -> 0 | M20: =SUM(K20:L20) -> 0 | N20: BO | P20: 高 | Q20: 新規 | R20: =CEILING(IF($Q20="新規", IF($P20="特高", R$4*特高係数,IF($P20="高",R$4*高係数,IF($P20="中",R$4*中係数,IF($P20="低",R$4*低係数, IF($P20="特低",R$4*特低係数, 0))))), IF($P20="特高", R$4*特高係数,IF($P20="高",R$4*高係数,IF($P20="中",R$4*中係数,IF($P20="低",R$4*低係数, IF($P20="特低",R$4*特低係数, 0)))))),0.125) -> 1 | S20: =CEILING(IF($Q20="新規", IF($P20="特高", S$4*特高係数,IF($P20="高",S$4*高係数,IF($P20="中",S$4*中係数,IF($P20="低",S$4*低係数, IF($P20="特低",S$4*特低係数, 0))))), IF($P20="特高", S$4*特高係数,IF($P20="高",S$4*高係数,IF($P20="中",S$4*中係数,IF($P20="低",S$4*低係数, IF($P20="特低",S$4*特低係数, 0)))))),0.125) -> 7.875 | T20: =CEILING(IF($Q20="新規", IF($P20="特高", T$4*特高係数,IF($P20="高",T$4*高係数,IF($P20="中",T$4*中係数,IF($P20="低",T$4*低係数, IF($P20="特低",T$4*特低係数, 0))))), IF($P20="特高", T$4*特高係数,IF($P20="高",T$4*高係数,IF($P20="中",T$4*中係数,IF($P20="低",T$4*低係数, IF($P20="特低",T$4*特低係数, 0)))))),0.125) -> 6.375 | U20: =SUM(R20:T20) -> 15.25 | V20: =U20/20 -> 0.7625
D21: セルアウト日毎テーブル伝送 | F21: 45748 | G21: 45777 | H21: 0 | I21: 0 | J21: =SUM(H21:I21) -> 0 | K21: 0 | L21: 0 | M21: =SUM(K21:L21) -> 0 | N21: BO | R21: =CEILING(IF($Q21="新規", IF($P21="特高", R$4*特高係数,IF($P21="高",R$4*高係数,IF($P21="中",R$4*中係数,IF($P21="低",R$4*低係数, IF($P21="特低",R$4*特低係数, 0))))), IF($P21="特高", R$4*特高係数,IF($P21="高",R$4*高係数,IF($P21="中",R$4*中係数,IF($P21="低",R$4*低係数, IF($P21="特低",R$4*特低係数, 0)))))),0.125) -> 0 | S21: =CEILING(IF($Q21="新規", IF($P21="特高", S$4*特高係数,IF($P21="高",S$4*高係数,IF($P21="中",S$4*中係数,IF($P21="低",S$4*低係数, IF($P21="特低",S$4*特低係数, 0))))), IF($P21="特高", S$4*特高係数,IF($P21="高",S$4*高係数,IF($P21="中",S$4*中係数,IF($P21="低",S$4*低係数, IF($P21="特低",S$4*特低係数, 0)))))),0.125) -> 0 | T21: =CEILING(IF($Q21="新規", IF($P21="特高", T$4*特高係数,IF($P21="高",T$4*高係数,IF($P21="中",T$4*中係数,IF($P21="低",T$4*低係数, IF($P21="特低",T$4*特低係数, 0))))), IF($P21="特高", T$4*特高係数,IF($P21="高",T$4*高係数,IF($P21="中",T$4*中係数,IF($P21="低",T$4*低係数, IF($P21="特低",T$4*特低係数, 0)))))),0.125) -> 0 | U21: =SUM(R21:T21) -> 0 | V21: =U21/20 -> 0
D22: セルアウト月次テーブル伝送 | F22: 45748 | G22: 45777 | H22: 0 | I22: 0 | J22: =SUM(H22:I22) -> 0 | K22: 0 | L22: 0 | M22: =SUM(K22:L22) -> 0 | N22: BO | R22: =CEILING(IF($Q22="新規", IF($P22="特高", R$4*特高係数,IF($P22="高",R$4*高係数,IF($P22="中",R$4*中係数,IF($P22="低",R$4*低係数, IF($P22="特低",R$4*特低係数, 0))))), IF($P22="特高", R$4*特高係数,IF($P22="高",R$4*高係数,IF($P22="中",R$4*中係数,IF($P22="低",R$4*低係数, IF($P22="特低",R$4*特低係数, 0)))))),0.125) -> 0 | S22: =CEILING(IF($Q22="新規", IF($P22="特高", S$4*特高係数,IF($P22="高",S$4*高係数,IF($P22="中",S$4*中係数,IF($P22="低",S$4*低係数, IF($P22="特低",S$4*特低係数, 0))))), IF($P22="特高", S$4*特高係数,IF($P22="高",S$4*高係数,IF($P22="中",S$4*中係数,IF($P22="低",S$4*低係数, IF($P22="特低",S$4*特低係数, 0)))))),0.125) -> 0 | T22: =CEILING(IF($Q22="新規", IF($P22="特高", T$4*特高係数,IF($P22="高",T$4*高係数,IF($P22="中",T$4*中係数,IF($P22="低",T$4*低係数, IF($P22="特低",T$4*特低係数, 0))))), IF($P22="特高", T$4*特高係数,IF($P22="高",T$4*高係数,IF($P22="中",T$4*中係数,IF($P22="低",T$4*低係数, IF($P22="特低",T$4*特低係数, 0)))))),0.125) -> 0 | U22: =SUM(R22:T22) -> 0 | V22: =U22/20 -> 0
D23: ｍｙｄｏ情報データ伝送 | F23: 45748 | G23: 45777 | H23: 10 | I23: 6 | J23: =SUM(H23:I23) -> 16 | L23: =K23*0.8 -> 0 | M23: =SUM(K23:L23) -> 0 | N23: BO | P23: 特高 | Q23: 新規 | R23: =CEILING(IF($Q23="新規", IF($P23="特高", R$4*特高係数,IF($P23="高",R$4*高係数,IF($P23="中",R$4*中係数,IF($P23="低",R$4*低係数, IF($P23="特低",R$4*特低係数, 0))))), IF($P23="特高", R$4*特高係数,IF($P23="高",R$4*高係数,IF($P23="中",R$4*中係数,IF($P23="低",R$4*低係数, IF($P23="特低",R$4*特低係数, 0)))))),0.125) -> 1.375 | S23: =CEILING(IF($Q23="新規", IF($P23="特高", S$4*特高係数,IF($P23="高",S$4*高係数,IF($P23="中",S$4*中係数,IF($P23="低",S$4*低係数, IF($P23="特低",S$4*特低係数, 0))))), IF($P23="特高", S$4*特高係数,IF($P23="高",S$4*高係数,IF($P23="中",S$4*中係数,IF($P23="低",S$4*低係数, IF($P23="特低",S$4*特低係数, 0)))))),0.125) -> 10.25 | T23: =CEILING(IF($Q23="新規", IF($P23="特高", T$4*特高係数,IF($P23="高",T$4*高係数,IF($P23="中",T$4*中係数,IF($P23="低",T$4*低係数, IF($P23="特低",T$4*特低係数, 0))))), IF($P23="特高", T$4*特高係数,IF($P23="高",T$4*高係数,IF($P23="中",T$4*中係数,IF($P23="低",T$4*低係数, IF($P23="特低",T$4*特低係数, 0)))))),0.125) -> 8.25 | U23: =SUM(R23:T23) -> 19.875 | V23: =U23/20 -> 0.99375
A24: =ROW()-4 -> 20 | C24: 処理センター17時 | D24: 販売店請求データ作成 | F24: 45748 | G24: 45807 | H24: 10 | I24: 6 | J24: =SUM(H24:I24) -> 16 | L24: =K24*0.8 -> 0 | M24: =SUM(K24:L24) -> 0 | N24: 機能 | P24: 特高 | Q24: 新規 | R24: =CEILING(IF($Q24="新規", IF($P24="特高", R$4*特高係数,IF($P24="高",R$4*高係数,IF($P24="中",R$4*中係数,IF($P24="低",R$4*低係数, IF($P24="特低",R$4*特低係数, 0))))), IF($P24="特高", R$4*特高係数,IF($P24="高",R$4*高係数,IF($P24="中",R$4*中係数,IF($P24="低",R$4*低係数, IF($P24="特低",R$4*特低係数, 0)))))),0.125) -> 1.375 | S24: =CEILING(IF($Q24="新規", IF($P24="特高", S$4*特高係数,IF($P24="高",S$4*高係数,IF($P24="中",S$4*中係数,IF($P24="低",S$4*低係数, IF($P24="特低",S$4*特低係数, 0))))), IF($P24="特高", S$4*特高係数,IF($P24="高",S$4*高係数,IF($P24="中",S$4*中係数,IF($P24="低",S$4*低係数, IF($P24="特低",S$4*特低係数, 0)))))),0.125) -> 10.25 | T24: =CEILING(IF($Q24="新規", IF($P24="特高", T$4*特高係数,IF($P24="高",T$4*高係数,IF($P24="中",T$4*中係数,IF($P24="低",T$4*低係数, IF($P24="特低",T$4*特低係数, 0))))), IF($P24="特高", T$4*特高係数,IF($P24="高",T$4*高係数,IF($P24="中",T$4*中係数,IF($P24="低",T$4*低係数, IF($P24="特低",T$4*特低係数, 0)))))),0.125) -> 8.25 | U24: =SUM(R24:T24) -> 19.875 | V24: =U24/20 -> 0.99375
D25: POS配信1回目(CRC) | F25: 45748 | G25: 45807 | H25: 18 | I25: 9 | J25: =SUM(H25:I25) -> 27 | L25: =K25*0.8 -> 0 | M25: =SUM(K25:L25) -> 0 | N25: 連携 | P25: 特高 | Q25: 新規 | R25: =1.8*CEILING(IF($Q25="新規", IF($P25="特高", R$4*特高係数,IF($P25="高",R$4*高係数,IF($P25="中",R$4*中係数,IF($P25="低",R$4*低係数, IF($P25="特低",R$4*特低係数, 0))))), IF($P25="特高", R$4*特高係数,IF($P25="高",R$4*高係数,IF($P25="中",R$4*中係数,IF($P25="低",R$4*低係数, IF($P25="特低",R$4*特低係数, 0)))))),0.125) -> 2.475 | S25: =1.8*CEILING(IF($Q25="新規", IF($P25="特高", S$4*特高係数,IF($P25="高",S$4*高係数,IF($P25="中",S$4*中係数,IF($P25="低",S$4*低係数, IF($P25="特低",S$4*特低係数, 0))))), IF($P25="特高", S$4*特高係数,IF($P25="高",S$4*高係数,IF($P25="中",S$4*中係数,IF($P25="低",S$4*低係数, IF($P25="特低",S$4*特低係数, 0)))))),0.125) -> 18.45 | T25: =1.8*CEILING(IF($Q25="新規", IF($P25="特高", T$4*特高係数,IF($P25="高",T$4*高係数,IF($P25="中",T$4*中係数,IF($P25="低",T$4*低係数, IF($P25="特低",T$4*特低係数, 0))))), IF($P25="特高", T$4*特高係数,IF($P25="高",T$4*高係数,IF($P25="中",T$4*中係数,IF($P25="低",T$4*低係数, IF($P25="特低",T$4*特低係数, 0)))))),0.125) -> 14.85 | U25: =SUM(R25:T25) -> 35.775 | V25: =U25/20 -> 1.78875
D26: POS配信1回目(ICC) | F26: 45748 | G26: 45807 | H26: 12 | I26: 6 | J26: =SUM(H26:I26) -> 18 | L26: =K26*0.8 -> 0 | M26: =SUM(K26:L26) -> 0 | N26: 連携 | P26: 特高 | Q26: 新規 | R26: =CEILING(IF($Q26="新規", IF($P26="特高", R$4*特高係数,IF($P26="高",R$4*高係数,IF($P26="中",R$4*中係数,IF($P26="低",R$4*低係数, IF($P26="特低",R$4*特低係数, 0))))), IF($P26="特高", R$4*特高係数,IF($P26="高",R$4*高係数,IF($P26="中",R$4*中係数,IF($P26="低",R$4*低係数, IF($P26="特低",R$4*特低係数, 0)))))),0.125) -> 1.375 | S26: =CEILING(IF($Q26="新規", IF($P26="特高", S$4*特高係数,IF($P26="高",S$4*高係数,IF($P26="中",S$4*中係数,IF($P26="低",S$4*低係数, IF($P26="特低",S$4*特低係数, 0))))), IF($P26="特高", S$4*特高係数,IF($P26="高",S$4*高係数,IF($P26="中",S$4*中係数,IF($P26="低",S$4*低係数, IF($P26="特低",S$4*特低係数, 0)))))),0.125) -> 10.25 | T26: =CEILING(IF($Q26="新規", IF($P26="特高", T$4*特高係数,IF($P26="高",T$4*高係数,IF($P26="中",T$4*中係数,IF($P26="低",T$4*低係数, IF($P26="特低",T$4*特低係数, 0))))), IF($P26="特高", T$4*特高係数,IF($P26="高",T$4*高係数,IF($P26="中",T$4*中係数,IF($P26="低",T$4*低係数, IF($P26="特低",T$4*特低係数, 0)))))),0.125) -> 8.25 | U26: =SUM(R26:T26) -> 19.875 | V26: =U26/20 -> 0.99375
D27: POS配信1回目(ITC) | F27: 45748 | G27: 45807 | H27: 0 | I27: 0 | J27: =SUM(H27:I27) -> 0 | K27: 0 | L27: 0 | M27: =SUM(K27:L27) -> 0 | N27: 連携 | R27: =CEILING(IF($Q27="新規", IF($P27="特高", R$4*特高係数,IF($P27="高",R$4*高係数,IF($P27="中",R$4*中係数,IF($P27="低",R$4*低係数, IF($P27="特低",R$4*特低係数, 0))))), IF($P27="特高", R$4*特高係数,IF($P27="高",R$4*高係数,IF($P27="中",R$4*中係数,IF($P27="低",R$4*低係数, IF($P27="特低",R$4*特低係数, 0)))))),0.125) -> 0 | S27: =CEILING(IF($Q27="新規", IF($P27="特高", S$4*特高係数,IF($P27="高",S$4*高係数,IF($P27="中",S$4*中係数,IF($P27="低",S$4*低係数, IF($P27="特低",S$4*特低係数, 0))))), IF($P27="特高", S$4*特高係数,IF($P27="高",S$4*高係数,IF($P27="中",S$4*中係数,IF($P27="低",S$4*低係数, IF($P27="特低",S$4*特低係数, 0)))))),0.125) -> 0 | T27: =CEILING(IF($Q27="新規", IF($P27="特高", T$4*特高係数,IF($P27="高",T$4*高係数,IF($P27="中",T$4*中係数,IF($P27="低",T$4*低係数, IF($P27="特低",T$4*特低係数, 0))))), IF($P27="特高", T$4*特高係数,IF($P27="高",T$4*高係数,IF($P27="中",T$4*中係数,IF($P27="低",T$4*低係数, IF($P27="特低",T$4*特低係数, 0)))))),0.125) -> 0 | U27: =SUM(R27:T27) -> 0 | V27: =U27/20 -> 0
D28: POS配信1回目(CRC) | F28: 45748 | G28: 45807 | H28: 0 | I28: 0 | J28: =SUM(H28:I28) -> 0 | K28: 0 | L28: 0 | M28: =SUM(K28:L28) -> 0 | N28: 連携 | R28: =CEILING(IF($Q28="新規", IF($P28="特高", R$4*特高係数,IF($P28="高",R$4*高係数,IF($P28="中",R$4*中係数,IF($P28="低",R$4*低係数, IF($P28="特低",R$4*特低係数, 0))))), IF($P28="特高", R$4*特高係数,IF($P28="高",R$4*高係数,IF($P28="中",R$4*中係数,IF($P28="低",R$4*低係数, IF($P28="特低",R$4*特低係数, 0)))))),0.125) -> 0 | S28: =CEILING(IF($Q28="新規", IF($P28="特高", S$4*特高係数,IF($P28="高",S$4*高係数,IF($P28="中",S$4*中係数,IF($P28="低",S$4*低係数, IF($P28="特低",S$4*特低係数, 0))))), IF($P28="特高", S$4*特高係数,IF($P28="高",S$4*高係数,IF($P28="中",S$4*中係数,IF($P28="低",S$4*低係数, IF($P28="特低",S$4*特低係数, 0)))))),0.125) -> 0 | T28: =CEILING(IF($Q28="新規", IF($P28="特高", T$4*特高係数,IF($P28="高",T$4*高係数,IF($P28="中",T$4*中係数,IF($P28="低",T$4*低係数, IF($P28="特低",T$4*特低係数, 0))))), IF($P28="特高", T$4*特高係数,IF($P28="高",T$4*高係数,IF($P28="中",T$4*中係数,IF($P28="低",T$4*低係数, IF($P28="特低",T$4*特低係数, 0)))))),0.125) -> 0 | U28: =SUM(R28:T28) -> 0 | V28: =U28/20 -> 0
A29: =ROW()-4 -> 25 | C29: 自動仕入 | D29: 自動仕入連携（ICC） | F29: 45778 | G29: 45838 | H29: 18 | I29: 9 | J29: =SUM(H29:I29) -> 27 | L29: =K29*0.8 -> 0 | M29: =SUM(K29:L29) -> 0 | N29: 連携 | P29: 特高 | Q29: 新規 | R29: =1.8*CEILING(IF($Q29="新規", IF($P29="特高", R$4*特高係数,IF($P29="高",R$4*高係数,IF($P29="中",R$4*中係数,IF($P29="低",R$4*低係数, IF($P29="特低",R$4*特低係数, 0))))), IF($P29="特高", R$4*特高係数,IF($P29="高",R$4*高係数,IF($P29="中",R$4*中係数,IF($P29="低",R$4*低係数, IF($P29="特低",R$4*特低係数, 0)))))),0.125) -> 2.475 | S29: =1.8*CEILING(IF($Q29="新規", IF($P29="特高", S$4*特高係数,IF($P29="高",S$4*高係数,IF($P29="中",S$4*中係数,IF($P29="低",S$4*低係数, IF($P29="特低",S$4*特低係数, 0))))), IF($P29="特高", S$4*特高係数,IF($P29="高",S$4*高係数,IF($P29="中",S$4*中係数,IF($P29="低",S$4*低係数, IF($P29="特低",S$4*特低係数, 0)))))),0.125) -> 18.45 | T29: =1.8*CEILING(IF($Q29="新規", IF($P29="特高", T$4*特高係数,IF($P29="高",T$4*高係数,IF($P29="中",T$4*中係数,IF($P29="低",T$4*低係数, IF($P29="特低",T$4*特低係数, 0))))), IF($P29="特高", T$4*特高係数,IF($P29="高",T$4*高係数,IF($P29="中",T$4*中係数,IF($P29="低",T$4*低係数, IF($P29="特低",T$4*特低係数, 0)))))),0.125) -> 14.85 | U29: =SUM(R29:T29) -> 35.775 | V29: =U29/20 -> 1.78875
D30: 自動仕入連携（ITC） | F30: 45778 | G30: 45838 | H30: 4 | I30: 2 | J30: =SUM(H30:I30) -> 6 | L30: =K30*0.8 -> 0 | M30: =SUM(K30:L30) -> 0 | N30: 連携 | P30: 低 | Q30: 新規 | R30: =CEILING(IF($Q30="新規", IF($P30="特高", R$4*特高係数,IF($P30="高",R$4*高係数,IF($P30="中",R$4*中係数,IF($P30="低",R$4*低係数, IF($P30="特低",R$4*特低係数, 0))))), IF($P30="特高", R$4*特高係数,IF($P30="高",R$4*高係数,IF($P30="中",R$4*中係数,IF($P30="低",R$4*低係数, IF($P30="特低",R$4*特低係数, 0)))))),0.125) -> 0.375 | S30: =CEILING(IF($Q30="新規", IF($P30="特高", S$4*特高係数,IF($P30="高",S$4*高係数,IF($P30="中",S$4*中係数,IF($P30="低",S$4*低係数, IF($P30="特低",S$4*特低係数, 0))))), IF($P30="特高", S$4*特高係数,IF($P30="高",S$4*高係数,IF($P30="中",S$4*中係数,IF($P30="低",S$4*低係数, IF($P30="特低",S$4*特低係数, 0)))))),0.125) -> 2.75 | T30: =CEILING(IF($Q30="新規", IF($P30="特高", T$4*特高係数,IF($P30="高",T$4*高係数,IF($P30="中",T$4*中係数,IF($P30="低",T$4*低係数, IF($P30="特低",T$4*特低係数, 0))))), IF($P30="特高", T$4*特高係数,IF($P30="高",T$4*高係数,IF($P30="中",T$4*中係数,IF($P30="低",T$4*低係数, IF($P30="特低",T$4*特低係数, 0)))))),0.125) -> 2.25 | U30: =SUM(R30:T30) -> 5.375 | V30: =U30/20 -> 0.26875
D31: 自動仕入連携（CRC） | F31: 45778 | G31: 45838 | H31: 0 | I31: 0 | J31: =SUM(H31:I31) -> 0 | K31: 0 | L31: 0 | M31: =SUM(K31:L31) -> 0 | N31: 連携 | R31: =CEILING(IF($Q31="新規", IF($P31="特高", R$4*特高係数,IF($P31="高",R$4*高係数,IF($P31="中",R$4*中係数,IF($P31="低",R$4*低係数, IF($P31="特低",R$4*特低係数, 0))))), IF($P31="特高", R$4*特高係数,IF($P31="高",R$4*高係数,IF($P31="中",R$4*中係数,IF($P31="低",R$4*低係数, IF($P31="特低",R$4*特低係数, 0)))))),0.125) -> 0 | S31: =CEILING(IF($Q31="新規", IF($P31="特高", S$4*特高係数,IF($P31="高",S$4*高係数,IF($P31="中",S$4*中係数,IF($P31="低",S$4*低係数, IF($P31="特低",S$4*特低係数, 0))))), IF($P31="特高", S$4*特高係数,IF($P31="高",S$4*高係数,IF($P31="中",S$4*中係数,IF($P31="低",S$4*低係数, IF($P31="特低",S$4*特低係数, 0)))))),0.125) -> 0 | T31: =CEILING(IF($Q31="新規", IF($P31="特高", T$4*特高係数,IF($P31="高",T$4*高係数,IF($P31="中",T$4*中係数,IF($P31="低",T$4*低係数, IF($P31="特低",T$4*特低係数, 0))))), IF($P31="特高", T$4*特高係数,IF($P31="高",T$4*高係数,IF($P31="中",T$4*中係数,IF($P31="低",T$4*低係数, IF($P31="特低",T$4*特低係数, 0)))))),0.125) -> 0 | U31: =SUM(R31:T31) -> 0 | V31: =U31/20 -> 0
D32: 自動仕入連携（GST） | F32: 45778 | G32: 45838 | H32: 0 | I32: 0 | J32: =SUM(H32:I32) -> 0 | K32: 0 | L32: 0 | M32: =SUM(K32:L32) -> 0 | N32: 連携 | R32: =CEILING(IF($Q32="新規", IF($P32="特高", R$4*特高係数,IF($P32="高",R$4*高係数,IF($P32="中",R$4*中係数,IF($P32="低",R$4*低係数, IF($P32="特低",R$4*特低係数, 0))))), IF($P32="特高", R$4*特高係数,IF($P32="高",R$4*高係数,IF($P32="中",R$4*中係数,IF($P32="低",R$4*低係数, IF($P32="特低",R$4*特低係数, 0)))))),0.125) -> 0 | S32: =CEILING(IF($Q32="新規", IF($P32="特高", S$4*特高係数,IF($P32="高",S$4*高係数,IF($P32="中",S$4*中係数,IF($P32="低",S$4*低係数, IF($P32="特低",S$4*特低係数, 0))))), IF($P32="特高", S$4*特高係数,IF($P32="高",S$4*高係数,IF($P32="中",S$4*中係数,IF($P32="低",S$4*低係数, IF($P32="特低",S$4*特低係数, 0)))))),0.125) -> 0 | T32: =CEILING(IF($Q32="新規", IF($P32="特高", T$4*特高係数,IF($P32="高",T$4*高係数,IF($P32="中",T$4*中係数,IF($P32="低",T$4*低係数, IF($P32="特低",T$4*特低係数, 0))))), IF($P32="特高", T$4*特高係数,IF($P32="高",T$4*高係数,IF($P32="中",T$4*中係数,IF($P32="低",T$4*低係数, IF($P32="特低",T$4*特低係数, 0)))))),0.125) -> 0 | U32: =SUM(R32:T32) -> 0 | V32: =U32/20 -> 0
A33: =ROW()-4 -> 29 | C33: POS処理料・利用料 | D33: POS処理料出クレ決済用データ | F33: 45748 | G33: 45814 | H33: 8 | I33: 4 | J33: =SUM(H33:I33) -> 12 | L33: =K33*0.8 -> 0 | M33: =SUM(K33:L33) -> 0 | N33: 連携 | P33: 高 | Q33: 新規 | R33: =CEILING(IF($Q33="新規", IF($P33="特高", R$4*特高係数,IF($P33="高",R$4*高係数,IF($P33="中",R$4*中係数,IF($P33="低",R$4*低係数, IF($P33="特低",R$4*特低係数, 0))))), IF($P33="特高", R$4*特高係数,IF($P33="高",R$4*高係数,IF($P33="中",R$4*中係数,IF($P33="低",R$4*低係数, IF($P33="特低",R$4*特低係数, 0)))))),0.125) -> 1 | S33: =CEILING(IF($Q33="新規", IF($P33="特高", S$4*特高係数,IF($P33="高",S$4*高係数,IF($P33="中",S$4*中係数,IF($P33="低",S$4*低係数, IF($P33="特低",S$4*特低係数, 0))))), IF($P33="特高", S$4*特高係数,IF($P33="高",S$4*高係数,IF($P33="中",S$4*中係数,IF($P33="低",S$4*低係数, IF($P33="特低",S$4*特低係数, 0)))))),0.125) -> 7.875 | T33: =CEILING(IF($Q33="新規", IF($P33="特高", T$4*特高係数,IF($P33="高",T$4*高係数,IF($P33="中",T$4*中係数,IF($P33="低",T$4*低係数, IF($P33="特低",T$4*特低係数, 0))))), IF($P33="特高", T$4*特高係数,IF($P33="高",T$4*高係数,IF($P33="中",T$4*中係数,IF($P33="低",T$4*低係数, IF($P33="特低",T$4*特低係数, 0)))))),0.125) -> 6.375 | U33: =SUM(R33:T33) -> 15.25 | V33: =U33/20 -> 0.7625
D34: POS利用料機伝 | F34: 45748 | G34: 45814 | H34: 8 | I34: 4 | J34: =SUM(H34:I34) -> 12 | L34: =K34*0.8 -> 0 | M34: =SUM(K34:L34) -> 0 | N34: 連携 | P34: 高 | Q34: 新規 | R34: =CEILING(IF($Q34="新規", IF($P34="特高", R$4*特高係数,IF($P34="高",R$4*高係数,IF($P34="中",R$4*中係数,IF($P34="低",R$4*低係数, IF($P34="特低",R$4*特低係数, 0))))), IF($P34="特高", R$4*特高係数,IF($P34="高",R$4*高係数,IF($P34="中",R$4*中係数,IF($P34="低",R$4*低係数, IF($P34="特低",R$4*特低係数, 0)))))),0.125) -> 1 | S34: =CEILING(IF($Q34="新規", IF($P34="特高", S$4*特高係数,IF($P34="高",S$4*高係数,IF($P34="中",S$4*中係数,IF($P34="低",S$4*低係数, IF($P34="特低",S$4*特低係数, 0))))), IF($P34="特高", S$4*特高係数,IF($P34="高",S$4*高係数,IF($P34="中",S$4*中係数,IF($P34="低",S$4*低係数, IF($P34="特低",S$4*特低係数, 0)))))),0.125) -> 7.875 | T34: =CEILING(IF($Q34="新規", IF($P34="特高", T$4*特高係数,IF($P34="高",T$4*高係数,IF($P34="中",T$4*中係数,IF($P34="低",T$4*低係数, IF($P34="特低",T$4*特低係数, 0))))), IF($P34="特高", T$4*特高係数,IF($P34="高",T$4*高係数,IF($P34="中",T$4*中係数,IF($P34="低",T$4*低係数, IF($P34="特低",T$4*特低係数, 0)))))),0.125) -> 6.375 | U34: =SUM(R34:T34) -> 15.25 | V34: =U34/20 -> 0.7625
D35: POS処理料機伝 | F35: 45748 | G35: 45814 | H35: 8 | I35: 4 | J35: =SUM(H35:I35) -> 12 | L35: =K35*0.8 -> 0 | M35: =SUM(K35:L35) -> 0 | N35: 連携 | P35: 高 | Q35: 新規 | R35: =CEILING(IF($Q35="新規", IF($P35="特高", R$4*特高係数,IF($P35="高",R$4*高係数,IF($P35="中",R$4*中係数,IF($P35="低",R$4*低係数, IF($P35="特低",R$4*特低係数, 0))))), IF($P35="特高", R$4*特高係数,IF($P35="高",R$4*高係数,IF($P35="中",R$4*中係数,IF($P35="低",R$4*低係数, IF($P35="特低",R$4*特低係数, 0)))))),0.125) -> 1 | S35: =CEILING(IF($Q35="新規", IF($P35="特高", S$4*特高係数,IF($P35="高",S$4*高係数,IF($P35="中",S$4*中係数,IF($P35="低",S$4*低係数, IF($P35="特低",S$4*特低係数, 0))))), IF($P35="特高", S$4*特高係数,IF($P35="高",S$4*高係数,IF($P35="中",S$4*中係数,IF($P35="低",S$4*低係数, IF($P35="特低",S$4*特低係数, 0)))))),0.125) -> 7.875 | T35: =CEILING(IF($Q35="新規", IF($P35="特高", T$4*特高係数,IF($P35="高",T$4*高係数,IF($P35="中",T$4*中係数,IF($P35="低",T$4*低係数, IF($P35="特低",T$4*特低係数, 0))))), IF($P35="特高", T$4*特高係数,IF($P35="高",T$4*高係数,IF($P35="中",T$4*中係数,IF($P35="低",T$4*低係数, IF($P35="特低",T$4*特低係数, 0)))))),0.125) -> 6.375 | U35: =SUM(R35:T35) -> 15.25 | V35: =U35/20 -> 0.7625
D36: ＰＯＳ処理料各種確認リスト | F36: 45748 | G36: 45814 | H36: 8 | I36: 4 | J36: =SUM(H36:I36) -> 12 | K36: 15 | L36: =K36*0.8 -> 12 | M36: =SUM(K36:L36) -> 27 | N36: 帳票 | P36: 高 | Q36: 新規 | R36: =CEILING(IF($Q36="新規", IF($P36="特高", R$4*特高係数,IF($P36="高",R$4*高係数,IF($P36="中",R$4*中係数,IF($P36="低",R$4*低係数, IF($P36="特低",R$4*特低係数, 0))))), IF($P36="特高", R$4*特高係数,IF($P36="高",R$4*高係数,IF($P36="中",R$4*中係数,IF($P36="低",R$4*低係数, IF($P36="特低",R$4*特低係数, 0)))))),0.125) -> 1 | S36: =CEILING(IF($Q36="新規", IF($P36="特高", S$4*特高係数,IF($P36="高",S$4*高係数,IF($P36="中",S$4*中係数,IF($P36="低",S$4*低係数, IF($P36="特低",S$4*特低係数, 0))))), IF($P36="特高", S$4*特高係数,IF($P36="高",S$4*高係数,IF($P36="中",S$4*中係数,IF($P36="低",S$4*低係数, IF($P36="特低",S$4*特低係数, 0)))))),0.125) -> 7.875 | T36: =CEILING(IF($Q36="新規", IF($P36="特高", T$4*特高係数,IF($P36="高",T$4*高係数,IF($P36="中",T$4*中係数,IF($P36="低",T$4*低係数, IF($P36="特低",T$4*特低係数, 0))))), IF($P36="特高", T$4*特高係数,IF($P36="高",T$4*高係数,IF($P36="中",T$4*中係数,IF($P36="低",T$4*低係数, IF($P36="特低",T$4*特低係数, 0)))))),0.125) -> 6.375 | U36: =SUM(R36:T36) -> 15.25 | V36: =U36/20 -> 0.7625
A37: =ROW()-4 -> 33 | C37: エントリ向け_まいどプラス発券 | D37: Mydoプラス発券実績 | F37: 45761 | G37: 45777 | H37: 8 | I37: 4 | J37: =SUM(H37:I37) -> 12 | L37: =K37*0.8 -> 0 | M37: =SUM(K37:L37) -> 0 | N37: DB | P37: 高 | Q37: 新規 | R37: =CEILING(IF($Q37="新規", IF($P37="特高", R$4*特高係数,IF($P37="高",R$4*高係数,IF($P37="中",R$4*中係数,IF($P37="低",R$4*低係数, IF($P37="特低",R$4*特低係数, 0))))), IF($P37="特高", R$4*特高係数,IF($P37="高",R$4*高係数,IF($P37="中",R$4*中係数,IF($P37="低",R$4*低係数, IF($P37="特低",R$4*特低係数, 0)))))),0.125) -> 1 | S37: =CEILING(IF($Q37="新規", IF($P37="特高", S$4*特高係数,IF($P37="高",S$4*高係数,IF($P37="中",S$4*中係数,IF($P37="低",S$4*低係数, IF($P37="特低",S$4*特低係数, 0))))), IF($P37="特高", S$4*特高係数,IF($P37="高",S$4*高係数,IF($P37="中",S$4*中係数,IF($P37="低",S$4*低係数, IF($P37="特低",S$4*特低係数, 0)))))),0.125) -> 7.875 | T37: =CEILING(IF($Q37="新規", IF($P37="特高", T$4*特高係数,IF($P37="高",T$4*高係数,IF($P37="中",T$4*中係数,IF($P37="低",T$4*低係数, IF($P37="特低",T$4*特低係数, 0))))), IF($P37="特高", T$4*特高係数,IF($P37="高",T$4*高係数,IF($P37="中",T$4*中係数,IF($P37="低",T$4*低係数, IF($P37="特低",T$4*特低係数, 0)))))),0.125) -> 6.375 | U37: =SUM(R37:T37) -> 15.25 | V37: =U37/20 -> 0.7625
D38: MYDOPlus発券実績 | F38: 45761 | G38: 45777 | H38: 4 | I38: 2 | J38: =SUM(H38:I38) -> 6 | L38: =K38*0.8 -> 0 | M38: =SUM(K38:L38) -> 0 | N38: 連携 | P38: 低 | Q38: 新規 | R38: =CEILING(IF($Q38="新規", IF($P38="特高", R$4*特高係数,IF($P38="高",R$4*高係数,IF($P38="中",R$4*中係数,IF($P38="低",R$4*低係数, IF($P38="特低",R$4*特低係数, 0))))), IF($P38="特高", R$4*特高係数,IF($P38="高",R$4*高係数,IF($P38="中",R$4*中係数,IF($P38="低",R$4*低係数, IF($P38="特低",R$4*特低係数, 0)))))),0.125) -> 0.375 | S38: =CEILING(IF($Q38="新規", IF($P38="特高", S$4*特高係数,IF($P38="高",S$4*高係数,IF($P38="中",S$4*中係数,IF($P38="低",S$4*低係数, IF($P38="特低",S$4*特低係数, 0))))), IF($P38="特高", S$4*特高係数,IF($P38="高",S$4*高係数,IF($P38="中",S$4*中係数,IF($P38="低",S$4*低係数, IF($P38="特低",S$4*特低係数, 0)))))),0.125) -> 2.75 | T38: =CEILING(IF($Q38="新規", IF($P38="特高", T$4*特高係数,IF($P38="高",T$4*高係数,IF($P38="中",T$4*中係数,IF($P38="低",T$4*低係数, IF($P38="特低",T$4*特低係数, 0))))), IF($P38="特高", T$4*特高係数,IF($P38="高",T$4*高係数,IF($P38="中",T$4*中係数,IF($P38="低",T$4*低係数, IF($P38="特低",T$4*特低係数, 0)))))),0.125) -> 2.25 | U38: =SUM(R38:T38) -> 5.375 | V38: =U38/20 -> 0.26875
A39: =ROW()-4 -> 35 | C39: ｱｽﾄﾓｽ入出荷 | D39: 入出荷共通入力（日次）OneSAP向け | F39: 45761 | G39: 45821 | H39: 18 | I39: 9 | J39: =SUM(H39:I39) -> 27 | L39: =K39*0.8 -> 0 | M39: =SUM(K39:L39) -> 0 | N39: 連携 | P39: 特高 | Q39: 新規 | R39: =1.8*CEILING(IF($Q39="新規", IF($P39="特高", R$4*特高係数,IF($P39="高",R$4*高係数,IF($P39="中",R$4*中係数,IF($P39="低",R$4*低係数, IF($P39="特低",R$4*特低係数, 0))))), IF($P39="特高", R$4*特高係数,IF($P39="高",R$4*高係数,IF($P39="中",R$4*中係数,IF($P39="低",R$4*低係数, IF($P39="特低",R$4*特低係数, 0)))))),0.125) -> 2.475 | S39: =1.8*CEILING(IF($Q39="新規", IF($P39="特高", S$4*特高係数,IF($P39="高",S$4*高係数,IF($P39="中",S$4*中係数,IF($P39="低",S$4*低係数, IF($P39="特低",S$4*特低係数, 0))))), IF($P39="特高", S$4*特高係数,IF($P39="高",S$4*高係数,IF($P39="中",S$4*中係数,IF($P39="低",S$4*低係数, IF($P39="特低",S$4*特低係数, 0)))))),0.125) -> 18.45 | T39: =1.8*CEILING(IF($Q39="新規", IF($P39="特高", T$4*特高係数,IF($P39="高",T$4*高係数,IF($P39="中",T$4*中係数,IF($P39="低",T$4*低係数, IF($P39="特低",T$4*特低係数, 0))))), IF($P39="特高", T$4*特高係数,IF($P39="高",T$4*高係数,IF($P39="中",T$4*中係数,IF($P39="低",T$4*低係数, IF($P39="特低",T$4*特低係数, 0)))))),0.125) -> 14.85 | U39: =SUM(R39:T39) -> 35.775 | V39: =U39/20 -> 1.78875
D40: 商品入荷エラーリスト | F40: 45761 | G40: 45821 | H40: 12 | I40: 6 | J40: =SUM(H40:I40) -> 18 | K40: 25 | L40: =K40*0.8 -> 20 | M40: =SUM(K40:L40) -> 45 | N40: 帳票 | P40: 特高 | Q40: 新規 | R40: =CEILING(IF($Q40="新規", IF($P40="特高", R$4*特高係数,IF($P40="高",R$4*高係数,IF($P40="中",R$4*中係数,IF($P40="低",R$4*低係数, IF($P40="特低",R$4*特低係数, 0))))), IF($P40="特高", R$4*特高係数,IF($P40="高",R$4*高係数,IF($P40="中",R$4*中係数,IF($P40="低",R$4*低係数, IF($P40="特低",R$4*特低係数, 0)))))),0.125) -> 1.375 | S40: =CEILING(IF($Q40="新規", IF($P40="特高", S$4*特高係数,IF($P40="高",S$4*高係数,IF($P40="中",S$4*中係数,IF($P40="低",S$4*低係数, IF($P40="特低",S$4*特低係数, 0))))), IF($P40="特高", S$4*特高係数,IF($P40="高",S$4*高係数,IF($P40="中",S$4*中係数,IF($P40="低",S$4*低係数, IF($P40="特低",S$4*特低係数, 0)))))),0.125) -> 10.25 | T40: =CEILING(IF($Q40="新規", IF($P40="特高", T$4*特高係数,IF($P40="高",T$4*高係数,IF($P40="中",T$4*中係数,IF($P40="低",T$4*低係数, IF($P40="特低",T$4*特低係数, 0))))), IF($P40="特高", T$4*特高係数,IF($P40="高",T$4*高係数,IF($P40="中",T$4*中係数,IF($P40="低",T$4*低係数, IF($P40="特低",T$4*特低係数, 0)))))),0.125) -> 8.25 | U40: =SUM(R40:T40) -> 19.875 | V40: =U40/20 -> 0.99375
D41: 複合伝票（LPG) | F41: 45761 | G41: 45821 | H41: 10 | I41: 6 | J41: =SUM(H41:I41) -> 16 | L41: =K41*0.8 -> 0 | M41: =SUM(K41:L41) -> 0 | N41: 帳票 | P41: 特高 | Q41: 新規 | R41: =CEILING(IF($Q41="新規", IF($P41="特高", R$4*特高係数,IF($P41="高",R$4*高係数,IF($P41="中",R$4*中係数,IF($P41="低",R$4*低係数, IF($P41="特低",R$4*特低係数, 0))))), IF($P41="特高", R$4*特高係数,IF($P41="高",R$4*高係数,IF($P41="中",R$4*中係数,IF($P41="低",R$4*低係数, IF($P41="特低",R$4*特低係数, 0)))))),0.125) -> 1.375 | S41: =CEILING(IF($Q41="新規", IF($P41="特高", S$4*特高係数,IF($P41="高",S$4*高係数,IF($P41="中",S$4*中係数,IF($P41="低",S$4*低係数, IF($P41="特低",S$4*特低係数, 0))))), IF($P41="特高", S$4*特高係数,IF($P41="高",S$4*高係数,IF($P41="中",S$4*中係数,IF($P41="低",S$4*低係数, IF($P41="特低",S$4*特低係数, 0)))))),0.125) -> 10.25 | T41: =CEILING(IF($Q41="新規", IF($P41="特高", T$4*特高係数,IF($P41="高",T$4*高係数,IF($P41="中",T$4*中係数,IF($P41="低",T$4*低係数, IF($P41="特低",T$4*特低係数, 0))))), IF($P41="特高", T$4*特高係数,IF($P41="高",T$4*高係数,IF($P41="中",T$4*中係数,IF($P41="低",T$4*低係数, IF($P41="特低",T$4*特低係数, 0)))))),0.125) -> 8.25 | U41: =SUM(R41:T41) -> 19.875 | V41: =U41/20 -> 0.99375
D42: 在庫受払日報 | F42: 45761 | G42: 45821 | H42: 8 | I42: 4 | J42: =SUM(H42:I42) -> 12 | K42: 15 | L42: =K42*0.8 -> 12 | M42: =SUM(K42:L42) -> 27 | N42: 帳票 | P42: 高 | Q42: 新規 | R42: =CEILING(IF($Q42="新規", IF($P42="特高", R$4*特高係数,IF($P42="高",R$4*高係数,IF($P42="中",R$4*中係数,IF($P42="低",R$4*低係数, IF($P42="特低",R$4*特低係数, 0))))), IF($P42="特高", R$4*特高係数,IF($P42="高",R$4*高係数,IF($P42="中",R$4*中係数,IF($P42="低",R$4*低係数, IF($P42="特低",R$4*特低係数, 0)))))),0.125) -> 1 | S42: =CEILING(IF($Q42="新規", IF($P42="特高", S$4*特高係数,IF($P42="高",S$4*高係数,IF($P42="中",S$4*中係数,IF($P42="低",S$4*低係数, IF($P42="特低",S$4*特低係数, 0))))), IF($P42="特高", S$4*特高係数,IF($P42="高",S$4*高係数,IF($P42="中",S$4*中係数,IF($P42="低",S$4*低係数, IF($P42="特低",S$4*特低係数, 0)))))),0.125) -> 7.875 | T42: =CEILING(IF($Q42="新規", IF($P42="特高", T$4*特高係数,IF($P42="高",T$4*高係数,IF($P42="中",T$4*中係数,IF($P42="低",T$4*低係数, IF($P42="特低",T$4*特低係数, 0))))), IF($P42="特高", T$4*特高係数,IF($P42="高",T$4*高係数,IF($P42="中",T$4*中係数,IF($P42="低",T$4*低係数, IF($P42="特低",T$4*特低係数, 0)))))),0.125) -> 6.375 | U42: =SUM(R42:T42) -> 15.25 | V42: =U42/20 -> 0.7625
D43: 在庫受払月報 | F43: 45761 | G43: 45821 | H43: 8 | I43: 4 | J43: =SUM(H43:I43) -> 12 | K43: 25 | L43: =K43*0.8 -> 20 | M43: =SUM(K43:L43) -> 45 | N43: 帳票 | P43: 高 | Q43: 新規 | R43: =CEILING(IF($Q43="新規", IF($P43="特高", R$4*特高係数,IF($P43="高",R$4*高係数,IF($P43="中",R$4*中係数,IF($P43="低",R$4*低係数, IF($P43="特低",R$4*特低係数, 0))))), IF($P43="特高", R$4*特高係数,IF($P43="高",R$4*高係数,IF($P43="中",R$4*中係数,IF($P43="低",R$4*低係数, IF($P43="特低",R$4*特低係数, 0)))))),0.125) -> 1 | S43: =CEILING(IF($Q43="新規", IF($P43="特高", S$4*特高係数,IF($P43="高",S$4*高係数,IF($P43="中",S$4*中係数,IF($P43="低",S$4*低係数, IF($P43="特低",S$4*特低係数, 0))))), IF($P43="特高", S$4*特高係数,IF($P43="高",S$4*高係数,IF($P43="中",S$4*中係数,IF($P43="低",S$4*低係数, IF($P43="特低",S$4*特低係数, 0)))))),0.125) -> 7.875 | T43: =CEILING(IF($Q43="新規", IF($P43="特高", T$4*特高係数,IF($P43="高",T$4*高係数,IF($P43="中",T$4*中係数,IF($P43="低",T$4*低係数, IF($P43="特低",T$4*特低係数, 0))))), IF($P43="特高", T$4*特高係数,IF($P43="高",T$4*高係数,IF($P43="中",T$4*中係数,IF($P43="低",T$4*低係数, IF($P43="特低",T$4*特低係数, 0)))))),0.125) -> 6.375 | U43: =SUM(R43:T43) -> 15.25 | V43: =U43/20 -> 0.7625
A44: =ROW()-4 -> 40 | C44: 全国版SS更新 | D44: ＰＯＳ給油所マスタ更新 | F44: 45761 | G44: 45777 | H44: 0 | I44: 0 | J44: =SUM(H44:I44) -> 0 | K44: 0 | L44: 0 | M44: =SUM(K44:L44) -> 0 | R44: =CEILING(IF($Q44="新規", IF($P44="特高", R$4*特高係数,IF($P44="高",R$4*高係数,IF($P44="中",R$4*中係数,IF($P44="低",R$4*低係数, IF($P44="特低",R$4*特低係数, 0))))), IF($P44="特高", R$4*特高係数,IF($P44="高",R$4*高係数,IF($P44="中",R$4*中係数,IF($P44="低",R$4*低係数, IF($P44="特低",R$4*特低係数, 0)))))),0.125) -> 0 | S44: =CEILING(IF($Q44="新規", IF($P44="特高", S$4*特高係数,IF($P44="高",S$4*高係数,IF($P44="中",S$4*中係数,IF($P44="低",S$4*低係数, IF($P44="特低",S$4*特低係数, 0))))), IF($P44="特高", S$4*特高係数,IF($P44="高",S$4*高係数,IF($P44="中",S$4*中係数,IF($P44="低",S$4*低係数, IF($P44="特低",S$4*特低係数, 0)))))),0.125) -> 0 | T44: =CEILING(IF($Q44="新規", IF($P44="特高", T$4*特高係数,IF($P44="高",T$4*高係数,IF($P44="中",T$4*中係数,IF($P44="低",T$4*低係数, IF($P44="特低",T$4*特低係数, 0))))), IF($P44="特高", T$4*特高係数,IF($P44="高",T$4*高係数,IF($P44="中",T$4*中係数,IF($P44="低",T$4*低係数, IF($P44="特低",T$4*特低係数, 0)))))),0.125) -> 0 | U44: =SUM(R44:T44) -> 0 | V44: =U44/20 -> 0
D45: CTC向け全国版SSﾏｽﾀ | F45: 45761 | G45: 45777 | H45: 10 | I45: 6 | J45: =SUM(H45:I45) -> 16 | K45: 40 | L45: =K45*0.8 -> 32 | M45: =SUM(K45:L45) -> 72 | P45: 特高 | Q45: 新規 | R45: =CEILING(IF($Q45="新規", IF($P45="特高", R$4*特高係数,IF($P45="高",R$4*高係数,IF($P45="中",R$4*中係数,IF($P45="低",R$4*低係数, IF($P45="特低",R$4*特低係数, 0))))), IF($P45="特高", R$4*特高係数,IF($P45="高",R$4*高係数,IF($P45="中",R$4*中係数,IF($P45="低",R$4*低係数, IF($P45="特低",R$4*特低係数, 0)))))),0.125) -> 1.375 | S45: =CEILING(IF($Q45="新規", IF($P45="特高", S$4*特高係数,IF($P45="高",S$4*高係数,IF($P45="中",S$4*中係数,IF($P45="低",S$4*低係数, IF($P45="特低",S$4*特低係数, 0))))), IF($P45="特高", S$4*特高係数,IF($P45="高",S$4*高係数,IF($P45="中",S$4*中係数,IF($P45="低",S$4*低係数, IF($P45="特低",S$4*特低係数, 0)))))),0.125) -> 10.25 | T45: =CEILING(IF($Q45="新規", IF($P45="特高", T$4*特高係数,IF($P45="高",T$4*高係数,IF($P45="中",T$4*中係数,IF($P45="低",T$4*低係数, IF($P45="特低",T$4*特低係数, 0))))), IF($P45="特高", T$4*特高係数,IF($P45="高",T$4*高係数,IF($P45="中",T$4*中係数,IF($P45="低",T$4*低係数, IF($P45="特低",T$4*特低係数, 0)))))),0.125) -> 8.25 | U45: =SUM(R45:T45) -> 19.875 | V45: =U45/20 -> 0.99375
D46: 全国版SSﾏｽﾀ差分 | F46: 45761 | G46: 45777 | H46: 8 | I46: 4 | J46: =SUM(H46:I46) -> 12 | L46: =K46*0.8 -> 0 | M46: =SUM(K46:L46) -> 0 | P46: 高 | Q46: 新規 | R46: =CEILING(IF($Q46="新規", IF($P46="特高", R$4*特高係数,IF($P46="高",R$4*高係数,IF($P46="中",R$4*中係数,IF($P46="低",R$4*低係数, IF($P46="特低",R$4*特低係数, 0))))), IF($P46="特高", R$4*特高係数,IF($P46="高",R$4*高係数,IF($P46="中",R$4*中係数,IF($P46="低",R$4*低係数, IF($P46="特低",R$4*特低係数, 0)))))),0.125) -> 1 | S46: =CEILING(IF($Q46="新規", IF($P46="特高", S$4*特高係数,IF($P46="高",S$4*高係数,IF($P46="中",S$4*中係数,IF($P46="低",S$4*低係数, IF($P46="特低",S$4*特低係数, 0))))), IF($P46="特高", S$4*特高係数,IF($P46="高",S$4*高係数,IF($P46="中",S$4*中係数,IF($P46="低",S$4*低係数, IF($P46="特低",S$4*特低係数, 0)))))),0.125) -> 7.875 | T46: =CEILING(IF($Q46="新規", IF($P46="特高", T$4*特高係数,IF($P46="高",T$4*高係数,IF($P46="中",T$4*中係数,IF($P46="低",T$4*低係数, IF($P46="特低",T$4*特低係数, 0))))), IF($P46="特高", T$4*特高係数,IF($P46="高",T$4*高係数,IF($P46="中",T$4*中係数,IF($P46="低",T$4*低係数, IF($P46="特低",T$4*特低係数, 0)))))),0.125) -> 6.375 | U46: =SUM(R46:T46) -> 15.25 | V46: =U46/20 -> 0.7625
D47: SS台帳、給油所マスタ更新 | F47: 45761 | G47: 45777 | H47: 0 | I47: 0 | J47: =SUM(H47:I47) -> 0 | K47: 0 | L47: 0 | M47: =SUM(K47:L47) -> 0 | R47: =CEILING(IF($Q47="新規", IF($P47="特高", R$4*特高係数,IF($P47="高",R$4*高係数,IF($P47="中",R$4*中係数,IF($P47="低",R$4*低係数, IF($P47="特低",R$4*特低係数, 0))))), IF($P47="特高", R$4*特高係数,IF($P47="高",R$4*高係数,IF($P47="中",R$4*中係数,IF($P47="低",R$4*低係数, IF($P47="特低",R$4*特低係数, 0)))))),0.125) -> 0 | S47: =CEILING(IF($Q47="新規", IF($P47="特高", S$4*特高係数,IF($P47="高",S$4*高係数,IF($P47="中",S$4*中係数,IF($P47="低",S$4*低係数, IF($P47="特低",S$4*特低係数, 0))))), IF($P47="特高", S$4*特高係数,IF($P47="高",S$4*高係数,IF($P47="中",S$4*中係数,IF($P47="低",S$4*低係数, IF($P47="特低",S$4*特低係数, 0)))))),0.125) -> 0 | T47: =CEILING(IF($Q47="新規", IF($P47="特高", T$4*特高係数,IF($P47="高",T$4*高係数,IF($P47="中",T$4*中係数,IF($P47="低",T$4*低係数, IF($P47="特低",T$4*特低係数, 0))))), IF($P47="特高", T$4*特高係数,IF($P47="高",T$4*高係数,IF($P47="中",T$4*中係数,IF($P47="低",T$4*低係数, IF($P47="特低",T$4*特低係数, 0)))))),0.125) -> 0 | U47: =SUM(R47:T47) -> 0 | V47: =U47/20 -> 0
A48: =ROW()-4 -> 44 | C48: 企業情報 | D48: 企業情報検索 | F48: 45778 | G48: 45784 | H48: 8 | I48: 4 | J48: =SUM(H48:I48) -> 12 | K48: 20 | L48: =K48*0.8 -> 16 | M48: =SUM(K48:L48) -> 36 | N48: 外部接続 | P48: 高 | Q48: 新規 | R48: =CEILING(IF($Q48="新規", IF($P48="特高", R$4*特高係数,IF($P48="高",R$4*高係数,IF($P48="中",R$4*中係数,IF($P48="低",R$4*低係数, IF($P48="特低",R$4*特低係数, 0))))), IF($P48="特高", R$4*特高係数,IF($P48="高",R$4*高係数,IF($P48="中",R$4*中係数,IF($P48="低",R$4*低係数, IF($P48="特低",R$4*特低係数, 0)))))),0.125) -> 1 | S48: =CEILING(IF($Q48="新規", IF($P48="特高", S$4*特高係数,IF($P48="高",S$4*高係数,IF($P48="中",S$4*中係数,IF($P48="低",S$4*低係数, IF($P48="特低",S$4*特低係数, 0))))), IF($P48="特高", S$4*特高係数,IF($P48="高",S$4*高係数,IF($P48="中",S$4*中係数,IF($P48="低",S$4*低係数, IF($P48="特低",S$4*特低係数, 0)))))),0.125) -> 7.875 | T48: =CEILING(IF($Q48="新規", IF($P48="特高", T$4*特高係数,IF($P48="高",T$4*高係数,IF($P48="中",T$4*中係数,IF($P48="低",T$4*低係数, IF($P48="特低",T$4*特低係数, 0))))), IF($P48="特高", T$4*特高係数,IF($P48="高",T$4*高係数,IF($P48="中",T$4*中係数,IF($P48="低",T$4*低係数, IF($P48="特低",T$4*特低係数, 0)))))),0.125) -> 6.375 | U48: =SUM(R48:T48) -> 15.25 | V48: =U48/20 -> 0.7625
A49: =ROW()-4 -> 45 | C49: 処理用SSマスタ作成 | D49: 新SS台帳から処理用SS台帳の作成（バッチ処理） | F49: 45761 | G49: 45779 | H49: 12 | I49: 6 | J49: =SUM(H49:I49) -> 18 | L49: =K49*0.8 -> 0 | M49: =SUM(K49:L49) -> 0 | P49: 特高 | Q49: 新規 | R49: =CEILING(IF($Q49="新規", IF($P49="特高", R$4*特高係数,IF($P49="高",R$4*高係数,IF($P49="中",R$4*中係数,IF($P49="低",R$4*低係数, IF($P49="特低",R$4*特低係数, 0))))), IF($P49="特高", R$4*特高係数,IF($P49="高",R$4*高係数,IF($P49="中",R$4*中係数,IF($P49="低",R$4*低係数, IF($P49="特低",R$4*特低係数, 0)))))),0.125) -> 1.375 | S49: =CEILING(IF($Q49="新規", IF($P49="特高", S$4*特高係数,IF($P49="高",S$4*高係数,IF($P49="中",S$4*中係数,IF($P49="低",S$4*低係数, IF($P49="特低",S$4*特低係数, 0))))), IF($P49="特高", S$4*特高係数,IF($P49="高",S$4*高係数,IF($P49="中",S$4*中係数,IF($P49="低",S$4*低係数, IF($P49="特低",S$4*特低係数, 0)))))),0.125) -> 10.25 | T49: =CEILING(IF($Q49="新規", IF($P49="特高", T$4*特高係数,IF($P49="高",T$4*高係数,IF($P49="中",T$4*中係数,IF($P49="低",T$4*低係数, IF($P49="特低",T$4*特低係数, 0))))), IF($P49="特高", T$4*特高係数,IF($P49="高",T$4*高係数,IF($P49="中",T$4*中係数,IF($P49="低",T$4*低係数, IF($P49="特低",T$4*特低係数, 0)))))),0.125) -> 8.25 | U49: =SUM(R49:T49) -> 19.875 | V49: =U49/20 -> 0.99375
A50: 合計（人日） | R50: =SUM(R5:R49) -> 33.3 | S50: =SUM(S5:S49) -> 285.1 | T50: =SUM(T5:T49) -> 230.675 | U50: =SUM(R50:T50) -> 549.075
A51: 合計（人月） | R51: =R50/20 -> 1.665 | S51: =S50/20 -> 14.255 | T51: =T50/20 -> 11.53375 | V51: =SUM(R51:T51) -> 27.45375
Q52: 作業金額 | R52: =ROUNDUP(R51, 1) * 1000000 -> 1700000 | S52: =ROUNDUP(S51, 1) * 1000000 -> 14300000 | T52: =ROUNDUP(T51, 1) * 1000000 -> 11600000 | V52: =SUM(R52:T52) -> 27600000
Q53: 管理 + プレ工数 | R53: =ROUNDUP(SUM(R51:R51)*0.2,1) -> 0.4 | S53: =ROUNDUP(SUM(S51)*0.2,1) -> 2.9 | T53: =ROUNDUP(SUM(T51)*0.2,1) -> 2.4 | V53: =SUM(R53:T53) -> 5.7
Q54: 管理 + プレ工数 金額 | R54: =R53 * 1400000 -> 560000 | S54: =S53 * 1400000 -> 4060000 | T54: =T53 * 1400000 -> 3360000 | V54: =SUM(R54:T54) -> 7980000
Q55: 合計 | R55: =R52 + R54 -> 2260000 | S55: =S52 + S54 -> 18360000 | T55: =T52 + T54 -> 14960000 | V55: =SUM(R55:T55) -> 35580000
A56: 総工数 | U56: =SUM(U50:U55) -> 549.075 | V56: =V51+V53 -> 33.15375

Sheet 積算基準
A1: 積算基準
A3: １．難易度を「特高」~「特低」までの５段階に分類する。
B5: 難易度
B6: 特高
B7: 高
B8: 中
B9: 低
B10: 特低
A12: ２．難易度の判断基準は、項目数により、区別する。
B14: 難易度判定：基準項目数
B15: 分類 | C15: 特高 | D15: 高 | E15: 中 | F15: 低 | G15: 特低
B16: 登録 | C16: 40 | D16: 30 | E16: 20 | F16: 10 | G16: 0
B17: 参照 | C17: 50 | D17: 40 | E17: 30 | F17: 20 | G17: 10
A19: ３．IPA発行「ソフトウェア開発データ白書」に基づく、各工程の工数比率を使用する。
B21: 工数比率（IPA ソフトウェア開発データ白書より）
B22: 基本設計 | C22: 詳細設計 | D22: 開発/単体テスト | E22: 結合テスト | F22: 総合テスト | G22: 合計
B23: 0.161 | C23: 0.175 | D23: 0.37 | E23: 0.167 | F23: 0.127 | G23: =SUM(B23:F23) -> 1
A26: ４．難易度「中」の基本設計～システムテストまでの標準工数を「8.75人日（全体工数が9.5人日となるよう調整）」とする。
B28: 画面・機能側標準工数（端数は0.125人日で丸め）
B29: 合計 | C29: 基本設計 | D29: 詳細設計 | E29: 開発/単体テスト | F29: 結合テスト | G29: 総合テスト
B30: 8.75 | C30: =CEILING($B30*B23,0.125) -> 1.5 | D30: =CEILING($B30*C23,0.125) -> 1.625 | E30: =CEILING($B30*D23,0.125) -> 3.25 | F30: =CEILING($B30*E23,0.125) -> 1.5 | G30: =CEILING($B30*F23,0.125) -> 1.125
B32: IF側標準工数（端数は0.125人日で丸め）
B33: 合計 | C33: 基本設計 | D33: 詳細設計 | E33: 開発/単体テスト | F33: 結合テスト | G33: 総合テスト
B34: 3.5 | C34: =CEILING($B34*B23,0.125) -> 0.625 | D34: =CEILING($B34*C23,0.125) -> 0.625 | E34: =CEILING($B34*D23,0.125) -> 1.375 | F34: =CEILING($B34*E23,0.125) -> 0.625 | G34: =CEILING($B34*F23,0.125) -> 0.5
A36: ５．他の工程の工数を下記の基準により算出する。
B38: 工程別 標準工数（端数は0.125人日で丸め）
B39: 工程 | C39: 合計 | D39: 要件定義 | E39: 基本設計 | F39: 詳細設計 | G39: 開発/単体テスト | H39: 結合テスト | I39: 総合テスト | J39: 受入テスト | K39: 本稼働 | L39: PJ管理
B40: 比率 | D40: 0.1 | E40: =B23 -> 0.161 | F40: =C23 -> 0.175 | G40: =D23 -> 0.37 | H40: =E23 -> 0.167 | I40: =F23 -> 0.127 | J40: 0.5 | K40: 0.25 | L40: 0.15
B41: 標準工数（画面・機能） | C41: =SUM(D41:L41) -> 12.875 | D41: =CEILING(SUM(E41:I41)*D40,0.125) -> 1 | E41: =C30 -> 1.5 | F41: =D30 -> 1.625 | G41: =E30 -> 3.25 | H41: =F30 -> 1.5 | I41: =G30 -> 1.125 | J41: =CEILING(H41*J40,0.125) -> 0.75 | K41: =CEILING(H41*K40,0.125) -> 0.375 | L41: =CEILING(SUM(D41:K41)*L40,0.125) -> 1.75
B42: 標準工数（IF） | C42: =SUM(D42:L42) -> 5.5 | D42: =CEILING(D40*SUM(E42:I42),0.125) -> 0.375 | E42: =C34 -> 0.625 | F42: =D34 -> 0.625 | G42: =E34 -> 1.375 | H42: =F34 -> 0.625 | I42: =G34 -> 0.5 | J42: =CEILING(J40*H42,0.125) -> 0.375 | K42: =CEILING(K40*H42,0.125) -> 0.25 | L42: =CEILING(L40*SUM(D42:K42),0.125) -> 0.75
B43: 0.5
A45: ６．他の難易度の工数は、下記の係数に基づき、積算する。
B47: 難易度別の工数係数
B48: 係数 | C48: 特高 | D48: 高 | E48: 中 | F48: 低 | G48: 特低
C49: 2.6 | D49: 2 | E49: 1.6 | F49: 0.7 | G49: 0.3 | H49: 画面・機能
C50: 1.5 | D50: 1.25 | E50: 1 | F50: 0.75 | G50: 0.2 | H50: IF
A53: 7．本案件の工程に合わせての工数を算出する。
B55: 工程別 標準工数（端数は0.125人日で丸め）
B56: 工程 | C56: 合計 | D56: 要件定義 | E56: 設計 | F56: 開発/単体テスト | G56: 結合テスト | H56: 受入テスト | I56: PJ管理
B57: 工数比率 | D57: 0.1 | E57: =SUM(B23:C23) -> 0.336 | F57: =D23 -> 0.37 | G57: =SUM(E23:F23) -> 0.294 | H57: 0.25 | I57: 0.15
B58: 標準工数（画面・機能） | C58: =SUM(D58:I58) -> 12 | D58: =CEILING(SUM(E58:G58)*D57,0.125) -> 1 | E58: =SUM(C30:D30) -> 3.125 | F58: =E30 -> 3.25 | G58: =SUM(F30:G30) -> 2.625 | H58: =CEILING(H41*H57,0.125) -> 0.375 | I58: =CEILING(SUM(D58:H58)*I57,0.125) -> 1.625
B59: 標準工数（IF） | C59: =SUM(D59:I59) -> 2.625 | D59: 0 | E59: =SUM(C34:D34) -> 1.25 | F59: =E34 -> 1.375 | G59: 0 | H59: 0 | I59: 0
B61: 平均単価(万) | C61: 100
