Workbook

Sheet 依頼概要
B3: 1. 経緯
B4: 館林DCセンターの廃止に伴い、現在のサーバ郡を移転する必要がある。
B5: 期日までに以下のいずれかの対応をとる必要がある。
B6: （２）Azureに構築される縮小版の共通基盤に移行
B7: ※現状よりスペックは低下、Oracleは19C
B8: 加えて、館林DC以外（現地）のサーバに関してWindows2016サーバはサポート期限切れに伴い、再構築を行う必要がある。
B11: 2. 依頼事項
B12: 各システム毎に概算見積を行ってほしい。
B13: （２）Azureに構築される縮小版の共通基盤に移行
C14: 対象：現行共通基盤を利用しているシステム
C15: 時期：2025年度1Q以降見込
C16: 出光側で構築した縮小版共通基盤へアプリ、帳票、バッチを移行
C17: 縮小版共通基盤の構成は現行共通基盤を踏襲した形となるが、OS,MWのバージョンは変更となる見込み
B20: 3. 希望期日
B21: 2024/12中に概算見積提示
B24: 顧客受領資料より

Sheet 想定作業
A1: 前提
B2: 業務・機能変更は行わない。
B3: サーバ構成は現行踏襲とする。
B4: DBは現行踏襲（Oracle、SQLSever継続）
B5: JavaフレームワークはStruts継続
B6: テストは新規構築した本番環境（次期本番機）にて行う。
B7: 開始時期を2025/4月以降
B8: ※検証、予備環境は最低限の動作確認（アプリ起動、ログイン確認程度）を想定
A11: 想定作業
A12: 全パターン共通
B13: IP,ホスト名変更に伴う各種（IF、DB等）向け先変更、検証
B14: アプリ動作検証（全画面、帳票、バッチ、IF打鍵 ※初期画面の描画や正常系の動作に問題がないことを確認）
B15: アプリケーション構築、ミドルウェアのセットアップ ※デプロイ作業のみ想定
B16: ※関連基盤の切り替えは完了しており、アプリケーションのAzure移行の切り替え作業は1回の未実施を想定（基盤切り替えが複数回発生する場合は別途工数が必要となります）
A18: （２）Azureに構築される縮小版の共通基盤に移行
B19: 全パターン共通の作業のみ

Sheet 概要図(千葉)
C1: ファイル連携 | F1: 工場系保守対象 | I1: 館林管理
C2: DBデータ連携 | F2: 工場系保守対象外 | I2: 現地管理
K63: Azure環境
K121: Azure環境

Sheet 概要図(徳山)
C1: ファイル連携 | F1: 工場系保守対象 | I1: 館林管理
C2: DBデータ連携 | F2: 工場系保守対象外 | I2: 現地管理
C60: Azure環境
C114: Azure環境

Sheet システム概要
E1: システム概要 | M1: システム規模 | S1: 共通基盤利用状況（現状）
A2: サービス: サービス番号 | B2: サービス名 | C2: 保守領域 | D2: 移行状況 | E2: 業務概要 | F2: OS | G2: アプリ | H2: DB | I2: ミドルウェア | J2: フレームワーク | K2: その他 | L2: サーバ構成 | M2: 画面 | N2: 帳票 | O2: バッチ | P2: IF | Q2: テーブル | R2: その他 | S2: 共通AP | T2: 共通DB | U2: 連携 | V2: レポート | W2: 認証 | X2: バッチ
A3: SVC-00000710 | B3: 数量確定システム(千葉) | C3: 工場系 | D3: 縮小共通基盤移行中 ⇒クラウドアーキ環境へ移行へ方針変更 | E3: 千葉事業所及び徳山事業所の石油化学装置の生産、在庫、PL(パイプライン)出荷、品目転換数量の管理を行うシステム。またタンクヤードの日報作成(ヤード日報)機能も持つ。 | F3: Red Hat Enterprise Linux7.3 | G3: java 1.8.0_202 Tomcat 9.0 | H3: Oracle19C | I3: A-AUTO | J3: struts 1.2.9 | L3: 本番 共通基盤（館林） 検証 共通基盤（館林） | M3: 千葉：41 徳山：30 | N3: 千葉：23 徳山：7 | O3: 共通：2 千葉：9 徳山：4 | P3: 千葉：8 徳山：4 | Q3: 共通：58 千葉：16 徳山：9 | S3: 〇 | T3: 〇 | U3: 〇 | V3: × | W3: 〇 | X3: 〇 | Y3: e
A4: SVC-00000857 | B4: 数量確定システム(徳山) | Y4: e
A5: - | B5: 用役管理システム(千葉工場) | C5: 工場系 | D5: 縮小共通基盤移行中 ⇒クラウドアーキ環境へ移行へ方針変更 | E5: 石油化学装置の生産数量、用役数量の管理を行うシステム。 | F5: Red Hat Enterprise Linux7.3 | G5: java 1.8.0_202 Tomcat 9.0 | H5: Oracle19C | I5: A-AUTO | J5: struts 1.2.9 | L5: 本番 共通基盤（館林） 検証 共通基盤（館林） | M5: 千葉：28 徳山：17 | N5: 千葉：43 徳山：6 | O5: 共通：0 千葉：0 徳山：0 | P5: 千葉：0 徳山：0 | Q5: 共通：11 千葉：1 徳山：11 | S5: 〇 | T5: 〇 | U5: 〇 | V5: × | W5: 〇 | X5: 〇 | Y5: e
A6: SVC-00000858 | B6: 用役管理システム(徳山工場) | Y6: e
A7: SVC-00001700 | B7: 千葉化学品質管理システム | C7: 工場系 | D7: 縮小共通基盤移行中 ⇒クラウドアーキ環境へ移行へ方針変更 | E7: 千葉事業所(工場)の品質管理課にて行う各種試験(工程、製品、物性)、及びそれに付随する業務(ロット管理、試験料金計算)を行うシステム。 | F7: Red Hat Enterprise Linux7.3 | G7: java 1.8.0_202 Tomcat 9.0 | H7: Oracle19C | I7: A-AUTO | J7: struts 1.2.9 | K7: List Creatorでの帳票作成 | L7: 本番 共通基盤（館林） 検証 共通基盤（館林） | M7: 83 | N7: 25 | O7: 5 | P7: 4 | Q7: 67 | S7: 〇 | T7: 〇 | U7: 〇 | V7: 〇 | W7: 〇 | X7: 〇 | Y7: e
A8: SVC-00000854 | B8: ＬＭＰＰ包装システム | C8: 工場系 | D8: 縮小共通基盤移行中 ⇒クラウドアーキ環境へ移行へ方針変更 | E8: 千葉事業所(工場)のSPS、LMPP装置で生産される製品の包装管理を行うシステム。 | F8: Red Hat Enterprise Linux7.3 | G8: java 1.8.0_202 Tomcat 9.0 | H8: Oracle19C | I8: A-AUTO | J8: struts 1.2.9 | K8: List Creatorでの帳票作成 | L8: 本番 共通基盤（館林） 検証 共通基盤（館林） | M8: 17 | N8: 3 | O8: 1 | P8: 3 | Q8: 12 | S8: 〇 | T8: 〇 | U8: 〇 | V8: 〇 | W8: 〇 | X8: 〇 | Y8: e
A9: SVC-00000877 | B9: 工場DB | C9: 工場系 | D9: 縮小共通基盤移行中 ⇒クラウドアーキ環境へ移行へ方針変更 ※アプリはXenApp | E9: 徳山事業所の石油化学装置の生産、在庫の計画値及び実績値を管理するDB及びエクセルマクロ群。 | F9: - | G9: Excel | H9: Oracle19C | I9: - | J9: - | L9: 本番 共通基盤（館林） 検証 共通基盤（館林） | M9: 0 | N9: 0 | O9: 0 | P9: 0 | Q9: 211 | S9: × | T9: 〇 | U9: × | V9: × | W9: × | X9: × | Y9: e
A10: SVC-00000705 | B10: 千葉ヤ－ド操業システム | C10: 工場系 | D10: OS更新対応にて現地サーバ構築済み | E10: 千葉事業所及び徳山事業所の石油化学品の入出荷を管理するシステム。 | F10: WindowsServer2022 | G10: java 1.8.0_152 WebLogic 12.2.1.2.0 | H10: SQLServer2022 | I10: A-AUTO | J10: struts 1.2.9 | L10: 本番 AP/DBサーバ×2（現地） AP/DB予備×2（館林） 検証 AP/DBサーバ×2（館林） | M10: 80 | N10: 20 | O10: 千葉：20 徳山：19 | P10: 千葉：16 徳山：15 | Q10: 75 | S10: × | T10: 〇 | U10: 〇 | V10: × | W10: 〇 | X10: × | Y10: e
A11: SVC-00000707 | B11: 徳山ヤ－ド操業システム | S11: × | T11: 〇 | U11: 〇 | V11: × | W11: 〇 | X11: × | Y11: e
A12: SVC-00000704 | B12: 千葉製品倉庫システム | C12: 工場系 | D12: 未実施（現地サーバ） | E12: 千葉事業所(工場)で生産されているポリマー製品の包装、入出荷、在庫管理を行うシステム。 | F12: WindowsServer2016 | G12: VB.NET | H12: Oracle12C | I12: Systemwalker Operation Manager OWFT | L12: 本番 AP/DBサーバ（現地） 検証 APサーバ（館林） | M12: 68 | N12: 43 | O12: 9 | P12: 45 | Q12: 205 | S12: × | T12: × | U12: 〇 | V12: × | W12: × | X12: × | Y12: e
A13: SVC-00000901 | B13: 千葉工場数量確定システム（ポリマ－） | C13: 工場系 | D13: 未実施（現地サーバ） | E13: 千葉事業所(工場)で生産されているポリマー製品の生産、在庫、PL(パイプライン)出荷、品目転換数量の管理を行うシステム。 | F13: WindowsServer2016 | G13: ASP.NET | H13: Oracle12C | I13: Systemwalker Operation Manager OWFT | M13: 20 | N13: 4 | O13: 2 | P13: 2 | Q13: 30 | S13: × | T13: × | U13: × | V13: × | W13: × | X13: × | Y13: e
A14: SVC-00000711 | B14: ＡＢＣ数量確定システム | C14: 工場系 | D14: 未実施（現地サーバ） | E14: 千葉事業所(工場)のABC装置で生産される製品の生産管理を行うシステム。 | F14: WindowsServer2016 | G14: C# | H14: Oracle12C | I14: Systemwalker Operation Manager OWFT | M14: 15 | N14: 0 | O14: 12 | P14: 5 | Q14: 24 | S14: × | T14: × | U14: × | V14: × | W14: × | X14: × | Y14: e
A15: - | B15: 千葉L3.5 | C15: 工場系 | D15: 未実施（現地サーバ） | E15: L3層に存在するシステムとL4層に存在するシステムの中継となるサーバ | F15: WindowsServer2016 | G15: - | H15: - | I15: Systemwalker Operation Manager OWFT | J15: - | L15: 本番 APサーバ（現地） 検証 APサーバ（館林） | M15: 0 | N15: 0 | O15: 2 | P15: 千葉：52 徳山：14 | Q15: 0 | S15: × | T15: × | U15: × | V15: × | W15: × | X15: ×
A16: - | B16: 徳山L3.5 | S16: × | T16: × | U16: × | V16: × | W16: × | X16: ×
A17: SVC-00001969 | B17: 用役集計 | C17: 工場系 | D17: excelファイルでの構築の為不要 | E17: 用役管理システムで出力した帳票のデータをOneSAPへ連携する為のシステム。 | G17: Excel | S17: - | T17: 不明 | U17: - | V17: - | W17: - | X17: - | Y17: e
A18: SVC-00001975 | B18: PRM HULFT | C18: 工場系 | D18: 2023年Azure移行済み | E18: PRMSAP⇔製品倉庫等PRMシステムの連携中継サーバ | S18: × | T18: × | U18: × | V18: × | W18: × | X18: × | Y18: e
A19: SVC-00000702 | B19: ロット管理明細表システム（PRM） | C19: 工場系 | D19: XenAppにて稼働 | G19: Excel | S19: × | T19: × | U19: × | V19: × | W19: × | X19: × | Y19: e
A20: SVC-00000706 | B20: 工場ロ－カルＥｘｃｅｌシステム | C20: 工場系 | S20: × | T20: 不明 | U20: × | V20: × | W20: × | X20: × | Y20: e
A21: SVC-00000876 | B21: スクラップ管理システム | C21: 工場系 | S21: × | T21: × | U21: × | V21: × | W21: × | X21: × | Y21: e

Sheet Sheet1
B3: No | C3: パターン | D3: 説明 | E3: 金額
B4: 1 | C4: 次期アーキへ移行 | D4: 次期アーキへ移行のため概算総額 | E4: ='見積 (システム・基盤別サマリ) '!K12 -> 68960000
B5: 1-1 | D5: 上記の内、次期アーキ要件定義フェーズ金額 | E5: =SUM('見積 (システム・工程別サマリ)'!M21:M26) -> 12020000
B6: 1-2 | D6: 次期アーキ要件定義を現契約で実施するにあたり、現契約から追加で必要な金額 | E6: ='見積 (システム・工程別サマリ)'!Q28 -> 5213000
B7: 2 | C7: 縮小共通基盤へ移行 | D7: 中断中の移行フェーズを再開するにあたり、現契約から追加で必要な金額 | E7: ='見積 (縮小共通基盤継続） '!D23 -> 6549000
B8: 3 | C8: 縮小共通基盤へ移行後、次期アーキへ移行 | D8: No1+No2 | E8: ='見積 (システム・縮小共通基盤⇒クラウドアーキサマリ) '!M13 -> 75509000

Sheet 見積 (縮小共通基盤継続） 
C1: 工数直入力のため注意！！
C2: 移行フェーズ作業実績
G3: 備考
B5: No. | C5: 月 | D5: 作業内容 | E5: 工数 | F5: 金額
B6: 1 | C6: 7月（当初予定作業） | D6: 縮小共通基盤移行作業 ・環境構築 ・システムテスト準備 | E6: 2.335 | F6: 2444000 | G6: 石井：0.71人月*1,400k=\994,000 天川：0.5人月*1,000k=\500,000 馬場：0.5人月*1,000k=\500,000 BSE：0.125人月*800k=\100,000 VT：0.5人月*700k=\350,000
B7: 2 | C7: 8月（当初予定外作業） | D7: 次期アーキに向けた調査・検証作業 | E7: 4.38 | F7: 4366000 | G7: ①～8/25+残日数 石井：14.8人日+残2人日=0.84人月*1,400k=\1,176,000 天川：18.3人日+残4人日=1.12人月*1,000k=\1,120,000 馬場：19.3人日+残4人日=1.17人月*1,000k=\1,170,000 ②VT BSE：0.25人月*800k=\200,000 VT：1人月*700k=\700,000
B8: 3 | C8: 9月（当初予定外作業） | D8: 次期アーキに向けた調査・検証作業 | E8: 2.2 | F8: 2183000 | G8: 9月中旬に方針確定と想定し、8月の0.5人月分で算出
B9: 計 | E9: =SUM(E6:E8) -> 8.915 | F9: =SUM(F6:F8) -> 8993000
C12: 案件名 | D12: 見積金額
C13: LMPP包装システム Azure移行（移行フェーズ） | D13: 2160000
C14: 千葉化学品質管理システム Azure移行（移行フェーズ） | D14: 2160000
C15: 数量確定システム Azure移行（移行フェーズ） | D15: 5440000
C16: 用役管理システム Azure移行（移行フェーズ） | D16: 5300000
C17: 工場DB Azure移行（移行フェーズ） | D17: 740000
B18: ① | C18: 現契約合計 | D18: =SUM(D13:D17) -> 15800000
B19: ② | C19: 縮小共通基盤作業実績（7月作業実績） | D19: =F6 -> 2444000
B20: ③ | C20: 縮小共通基盤残作業分費用 （①-②） | D20: =D18-F6 -> 13356000
B21: ④ | C21: 次期アーキ調査・検証分費用 （8月、9月作業実績） | D21: =SUM(F7:F8) -> 6549000
B22: ⑤ | C22: 現契約残額（①-②-④） | D22: =D18-D19-D21 -> 6807000
B23: ⑥ | C23: 追加発注分（③-⑤） | D23: =D20-D22 -> 6549000
D24: ※ヤード認証基盤対応分は除く

Sheet 見積 (システム・基盤別サマリ) 
C1: 工数直入力のため注意！！
C2: 見積 (基盤別サマリ)
C3: パターン | D3: クラウドアーキ基盤に移行 | P3: 備考
D4: アプリ | L4: DB | N4: 全体
B5: No. | C5: システム | D5: 共通 (基盤に関わらず共通して必要な作業) | E5: AP基盤 | F5: 認証基盤 | G5: バッチ基盤 | H5: DB基盤 | I5: 管理 | J5: 工数計 | K5: 金額 | L5: 工数計 | M5: 金額 | N5: 工数計 | O5: 金額
B6: 1 | C6: 数量確定システム（千葉・徳山） | D6: 5.5 | E6: 9.2 | F6: 1.3 | G6: 0.9 | H6: 0 | I6: 3.8 | J6: =SUM(D6:I6) -> 20.7 | K6: =SUM(D6:H6)*1000000+I6*1400000 -> 22220000 | L6: 0 | M6: 0 | N6: =SUM(J6:J10)+L6 -> 58.3 | O6: =SUM(K6:K10)+M6 -> 62900000
B7: 2 | C7: 用役管理システム（千葉・徳山） | D7: 5.2 | E7: 5.3 | F7: 0.5 | G7: 0 | H7: 0 | I7: 2.6 | J7: =SUM(D7:I7) -> 13.6 | K7: =SUM(D7:H7)*1000000+I7*1400000 -> 14640000
B8: 3 | C8: 千葉化学品質管理システム | D8: 3.2 | E8: 7 | F8: 1.2 | G8: 0.7 | H8: 0 | I8: 2.7 | J8: =SUM(D8:I8) -> 14.8 | K8: =SUM(D8:H8)*1000000+I8*1400000 -> 15880000
B9: 4 | C9: ＬＭＰＰ包装システム | D9: 2.2 | E9: 3 | F9: 0.6 | G9: 0.6 | H9: 0 | I9: 1.9 | J9: =SUM(D9:I9) -> 8.3 | K9: =SUM(D9:H9)*1000000+I9*1400000 -> 9060000
B10: 5 | C10: 工場DB | D10: 0.4 | I10: 0.5 | J10: =SUM(D10:I10) -> 0.9 | K10: =SUM(D10:H10)*1000000+I10*1400000 -> 1100000
B11: 6 | C11: ヤ－ド操業システム（千葉・徳山） | D11: 2.4 | E11: 0 | F11: 2.4 | G11: 0 | H11: 0 | I11: 0.9 | J11: =SUM(D11:I11) -> 5.7 | K11: =SUM(D11:H11)*1000000+I11*1400000 -> 6060000 | L11: 0 | M11: =SUM(M5:M10) -> 0 | N11: =SUM(J11:J11)+L11 -> 5.7 | O11: =SUM(K11:K11)+M6 -> 6060000
B12: 計 | D12: =SUM(D6:D11) -> 18.9 | E12: =SUM(E6:E11) -> 24.5 | F12: =SUM(F6:F11) -> 6 | G12: =SUM(G6:G11) -> 2.2 | H12: =SUM(H6:H11) -> 0 | I12: =SUM(I6:I11) -> 12.4 | J12: =SUM(D12:I12) -> 64 | K12: =SUM(K6:K11) -> 68960000 | L12: =SUM(L6:L11) -> 0 | M12: =SUM(M6:M11) -> 0 | N12: =SUM(N6:N11) -> 64 | O12: =SUM(O6:O11) -> 68960000
B13: 単価 | D13: 1000000 | E13: 1000000 | F13: 1000000 | G13: 1000000 | H13: 1000000 | I13: 1400000
B14: 金額 | D14: =D12*D13 -> 18900000 | E14: =E12*E13 -> 24500000 | F14: =F12*F13 -> 6000000 | G14: =G12*G13 -> 2200000 | H14: =H12*H13 -> 0 | I14: =I12*I13 -> 17360000

Sheet 見積 (システム・工程別サマリ)
C1: 工数直入力のため注意！！
C2: 見積（工程別サマリ）
C3: パターン | D3: クラウドアーキ基盤に移行 | R3: 備考
D4: アプリ | N4: DB | P4: 全体
B5: No. | C5: システム | D5: 調査・要件定義 | E5: 設計 | F5: 製造 | G5: 結合テスト | H5: システムテスト | I5: ユーザテスト | J5: 本番稼働 | K5: 管理 | L5: 工数計 | M5: 金額 | N5: 工数計 | O5: 金額 | P5: 工数計 | Q5: 金額
B6: 1 | C6: 数量確定システム（千葉・徳山） | D6: 3.2 | E6: 1.6 | F6: 2.7 | G6: 5.2 | H6: 1.4 | I6: 0.8 | J6: 2 | K6: 3.8 | L6: =SUM(D6:K6) -> 20.7 | M6: =SUM(D6:J6)*1000000+K6*1400000 -> 22220000 | N6: 0 | O6: 0 | P6: =SUM(L6:L10)+N6 -> 58.3 | Q6: =SUM(M6:M10)+O6 -> 62900000
B7: 2 | C7: 用役管理システム（千葉・徳山） | D7: 1.4 | E7: 1.1 | F7: 1.5 | G7: 3.1 | H7: 1.1 | I7: 0.8 | J7: 2 | K7: 2.6 | L7: =SUM(D7:K7) -> 13.6 | M7: =SUM(D7:J7)*1000000+K7*1400000 -> 14640000
B8: 3 | C8: 千葉化学品質管理システム | D8: 1.7 | E8: 1.4 | F8: 1.6 | G8: 5.5 | H8: 0.8 | I8: 0.5 | J8: 0.6 | K8: 2.7 | L8: =SUM(D8:K8) -> 14.8 | M8: =SUM(D8:J8)*1000000+K8*1400000 -> 15880000
B9: 4 | C9: ＬＭＰＰ包装システム | D9: 1.3 | E9: 0.4 | F9: 1.6 | G9: 1.2 | H9: 0.8 | I9: 0.5 | J9: 0.6 | K9: 1.9 | L9: =SUM(D9:K9) -> 8.3 | M9: =SUM(D9:J9)*1000000+K9*1400000 -> 9060000
B10: 5 | C10: 工場DB | J10: 0.4 | K10: 0.5 | L10: =SUM(D10:K10) -> 0.9 | M10: =SUM(D10:J10)*1000000+K10*1400000 -> 1100000
B11: 6 | C11: ヤ－ド操業システム（千葉・徳山） | D11: 0.5 | E11: 0.4 | F11: 0.7 | G11: 1.4 | H11: 0.2 | I11: 0.1 | J11: 1.5 | K11: 0.9 | L11: =SUM(D11:K11) -> 5.7 | M11: =SUM(D11:J11)*1000000+K11*1400000 -> 6060000 | N11: 0 | O11: =SUM(O5:O10) -> 0 | P11: =SUM(L11:L11)+N11 -> 5.7 | Q11: =SUM(M11:M11)+O6 -> 6060000
B12: 計 | D12: =SUM(D6:D11) -> 8.1 | E12: =SUM(E6:E11) -> 4.9 | F12: =SUM(F6:F11) -> 8.1 | G12: =SUM(G6:G11) -> 16.4 | H12: =SUM(H6:H11) -> 4.3 | I12: =SUM(I6:I11) -> 2.7 | J12: =SUM(J6:J11) -> 7.1 | K12: =SUM(K6:K11) -> 12.4 | L12: =SUM(D12:K12) -> 64 | M12: =SUM(M6:M11) -> 68960000 | N12: =SUM(N6:N11) -> 0 | O12: =SUM(O6:O11) -> 0 | P12: =SUM(P6:P11) -> 64 | Q12: =SUM(Q6:Q11) -> 68960000
B13: 単価 | D13: 1000000 | E13: 1000000 | F13: 1000000 | G13: 1000000 | H13: 1000000 | I13: 1000000 | J13: 1000000 | K13: 1400000
B14: 金額 | D14: =D12*D13 -> 8100000 | E14: =E12*E13 -> 4900000 | F14: =F12*F13 -> 8100000 | G14: =G12*G13 -> 16400000 | H14: =H12*H13 -> 4300000 | I14: =I12*I13 -> 2700000 | J14: =J12*J13 -> 7100000 | K14: =K12*K13 -> 17360000
C17: 調査・要件定義（移行フェーズの契約変更）
C18: パターン | D18: クラウドアーキ基盤に移行 | R18: 備考
D19: アプリ | N19: DB | P19: 全体
B20: No. | C20: システム | D20: 調査・要件定義 | E20: 設計 | F20: 製造 | G20: 結合テスト | H20: システムテスト | I20: ユーザテスト | J20: 本番稼働 | K20: 管理 | L20: 工数計 | M20: 金額 | N20: 工数計 | O20: 金額 | P20: 工数計 | Q20: 金額
B21: 1 | C21: 数量確定システム（千葉・徳山） | D21: 3.2 | K21: 0.9 | L21: =SUM(D21:K21) -> 4.1 | M21: =SUM(D21:J21)*1000000+K21*1400000 -> 4460000 | N21: 0 | O21: 0 | P21: =SUM(L21:L25)+N21 -> 10.2 | Q21: =SUM(M21:M25)+O21 -> 11240000
B22: 2 | C22: 用役管理システム（千葉・徳山） | D22: 1.4 | K22: 0.6 | L22: =SUM(D22:K22) -> 2 | M22: =SUM(D22:J22)*1000000+K22*1400000 -> 2240000
B23: 3 | C23: 千葉化学品質管理システム | D23: 1.7 | K23: 0.6 | L23: =SUM(D23:K23) -> 2.3 | M23: =SUM(D23:J23)*1000000+K23*1400000 -> 2540000
B24: 4 | C24: ＬＭＰＰ包装システム | D24: 1.3 | K24: 0.5 | L24: =SUM(D24:K24) -> 1.8 | M24: =SUM(D24:J24)*1000000+K24*1400000 -> 2000000
B25: 5 | C25: 工場DB | L25: =SUM(D25:K25) -> 0 | M25: =SUM(D25:J25)*1000000+K25*1400000 -> 0
B26: 6 | C26: ヤ－ド操業システム（千葉・徳山） | D26: 0.5 | K26: 0.2 | L26: =SUM(D26:K26) -> 0.7 | M26: =SUM(D26:J26)*1000000+K26*1400000 -> 780000 | P26: =SUM(L26:L26)+N26 -> 0.7 | Q26: =SUM(M26:M26)+O26 -> 780000
B27: 7 | C27: 縮小共通基盤（移行フェーズ） | L27: =SUM(D27:K27) -> 0 | M27: -6807000 | P27: =SUM(L27:L27)+N27 -> 0 | Q27: =SUM(M27:M27)+O21 -> -6807000 | R27: 現契約残額を差し引き
B28: 計 | D28: =SUM(D21:D27) -> 8.1 | E28: =SUM(E21:E27) -> 0 | F28: =SUM(F21:F27) -> 0 | G28: =SUM(G21:G27) -> 0 | H28: =SUM(H21:H27) -> 0 | I28: =SUM(I21:I27) -> 0 | J28: =SUM(J21:J27) -> 0 | K28: =SUM(K22:K27) -> 1.9 | L28: =SUM(D28:K28) -> 10 | M28: =SUM(M21:M27) -> 5213000 | N28: =SUM(N21:N27) -> 0 | O28: =SUM(O21:O27) -> 0 | P28: =SUM(P21:P27) -> 10.9 | Q28: =SUM(Q21:Q27) -> 5213000
B29: 単価 | D29: 1000000 | E29: 1000000 | F29: 1000000 | G29: 1000000 | H29: 1000000 | I29: 1000000 | J29: 1000000 | K29: 1400000
B30: 金額 | D30: =D28*D29 -> 8100000 | E30: =E28*E29 -> 0 | F30: =F28*F29 -> 0 | G30: =G28*G29 -> 0 | H30: =H28*H29 -> 0 | I30: =I28*I29 -> 0 | J30: =J28*J29 -> 0 | K30: =K28*K29 -> 2660000
C32: 調査・要件定義(クラウドアーキから開始)
C33: パターン | D33: クラウドアーキ基盤に移行 | R33: 備考
D34: アプリ | N34: DB | P34: 全体
B35: No. | C35: システム | D35: 調査・要件定義 | E35: 設計 | F35: 製造 | G35: 結合テスト | H35: システムテスト | I35: ユーザテスト | J35: 本番稼働 | K35: 管理 | L35: 工数計 | M35: 金額 | N35: 工数計 | O35: 金額 | P35: 工数計 | Q35: 金額
B36: 1 | C36: 数量確定システム（千葉・徳山） | D36: 3.2 | K36: 0.9 | L36: =SUM(D36:K36) -> 4.1 | M36: =SUM(D36:J36)*1000000+K36*1400000 -> 4460000 | N36: 0 | O36: 0 | P36: =SUM(L36:L40)+N36 -> 10.2 | Q36: =SUM(M36:M40)+O36 -> 11240000
B37: 2 | C37: 用役管理システム（千葉・徳山） | D37: 1.4 | K37: 0.6 | L37: =SUM(D37:K37) -> 2 | M37: =SUM(D37:J37)*1000000+K37*1400000 -> 2240000
B38: 3 | C38: 千葉化学品質管理システム | D38: 1.7 | K38: 0.6 | L38: =SUM(D38:K38) -> 2.3 | M38: =SUM(D38:J38)*1000000+K38*1400000 -> 2540000
B39: 4 | C39: ＬＭＰＰ包装システム | D39: 1.3 | K39: 0.5 | L39: =SUM(D39:K39) -> 1.8 | M39: =SUM(D39:J39)*1000000+K39*1400000 -> 2000000
B40: 5 | C40: 工場DB | L40: =SUM(D40:K40) -> 0 | M40: =SUM(D40:J40)*1000000+K40*1400000 -> 0
B41: 6 | C41: ヤ－ド操業システム（千葉・徳山） | D41: 0.5 | K41: 0.2 | L41: =SUM(D41:K41) -> 0.7 | M41: =SUM(D41:J41)*1000000+K41*1400000 -> 780000 | P41: =SUM(L41:L41)+N41 -> 0.7 | Q41: =SUM(M41:M41)+O36 -> 780000
B42: 計 | D42: =SUM(D36:D41) -> 8.1 | E42: =SUM(E36:E41) -> 0 | F42: =SUM(F36:F41) -> 0 | G42: =SUM(G36:G41) -> 0 | H42: =SUM(H36:H41) -> 0 | I42: =SUM(I36:I41) -> 0 | J42: =SUM(J36:J41) -> 0 | K42: =SUM(K37:K41) -> 1.9 | L42: =SUM(D42:K42) -> 10 | M42: =SUM(M36:M41) -> 12020000 | N42: =SUM(N36:N41) -> 0 | O42: =SUM(O36:O41) -> 0 | P42: =SUM(P36:P41) -> 10.9 | Q42: =SUM(Q36:Q41) -> 12020000
B43: 単価 | D43: 1000000 | E43: 1000000 | F43: 1000000 | G43: 1000000 | H43: 1000000 | I43: 1000000 | J43: 1000000 | K43: 1400000
B44: 金額 | D44: =D42*D43 -> 8100000 | E44: =E42*E43 -> 0 | F44: =F42*F43 -> 0 | G44: =G42*G43 -> 0 | H44: =H42*H43 -> 0 | I44: =I42*I43 -> 0 | J44: =J42*J43 -> 0 | K44: =K42*K43 -> 2660000
C46: 開発フェーズ
C47: パターン | D47: クラウドアーキ基盤に移行 | R47: 備考
D48: アプリ | N48: DB | P48: 全体
B49: No. | C49: システム | D49: 調査・要件定義 | E49: 設計 | F49: 製造 | G49: 結合テスト | H49: システムテスト | I49: ユーザテスト | J49: 本番稼働 | K49: 管理 | L49: 工数計 | M49: 金額 | N49: 工数計 | O49: 金額 | P49: 工数計 | Q49: 金額
B50: 1 | C50: 数量確定システム（千葉・徳山） | E50: 1.6 | F50: 2.7 | G50: 5.2 | K50: 1.9 | L50: =SUM(D50:K50) -> 11.4 | M50: =SUM(D50:J50)*1000000+K50*1400000 -> 12160000 | N50: 0 | O50: 0 | P50: =SUM(L50:L54)+N50 -> 32.4 | Q50: =SUM(M50:M54)+O50 -> 34600000
B51: 2 | C51: 用役管理システム（千葉・徳山） | E51: 1.1 | F51: 1.5 | G51: 3.1 | K51: 1.2 | L51: =SUM(D51:K51) -> 6.9 | M51: =SUM(D51:J51)*1000000+K51*1400000 -> 7380000
B52: 3 | C52: 千葉化学品質管理システム | E52: 1.4 | F52: 1.6 | G52: 5.5 | K52: 1.6 | L52: =SUM(D52:K52) -> 10.1 | M52: =SUM(D52:J52)*1000000+K52*1400000 -> 10740000
B53: 4 | C53: ＬＭＰＰ包装システム | E53: 0.4 | F53: 1.6 | G53: 1.2 | K53: 0.8 | L53: =SUM(D53:K53) -> 4 | M53: =SUM(D53:J53)*1000000+K53*1400000 -> 4320000
B54: 5 | C54: 工場DB | L54: =SUM(D54:K54) -> 0 | M54: =SUM(D54:J54)*1000000+K54*1400000 -> 0
B55: 6 | C55: ヤ－ド操業システム（千葉・徳山） | E55: 0.4 | F55: 0.7 | G55: 1.4 | K55: 0.4 | L55: =SUM(D55:K55) -> 2.9 | M55: =SUM(D55:J55)*1000000+K55*1400000 -> 3060000 | P55: =SUM(L55:L55)+N55 -> 2.9 | Q55: =SUM(M55:M55)+O50 -> 3060000
B56: 計 | D56: =SUM(D50:D55) -> 0 | E56: =SUM(E50:E55) -> 4.9 | F56: =SUM(F50:F55) -> 8.1 | G56: =SUM(G50:G55) -> 16.4 | H56: =SUM(H50:H55) -> 0 | I56: =SUM(I50:I55) -> 0 | J56: =SUM(J50:J55) -> 0 | K56: =SUM(K50:K55) -> 5.9 | L56: =SUM(D56:K56) -> 35.3 | M56: =SUM(M50:M55) -> 37660000 | N56: =SUM(N50:N55) -> 0 | O56: =SUM(O50:O55) -> 0 | P56: =SUM(P50:P55) -> 35.3 | Q56: =SUM(Q50:Q55) -> 37660000
B57: 単価 | D57: 1000000 | E57: 1000000 | F57: 1000000 | G57: 1000000 | H57: 1000000 | I57: 1000000 | J57: 1000000 | K57: 1400000
B58: 金額 | D58: =D56*D57 -> 0 | E58: =E56*E57 -> 4900000 | F58: =F56*F57 -> 8100000 | G58: =G56*G57 -> 16400000 | H58: =H56*H57 -> 0 | I58: =I56*I57 -> 0 | J58: =J56*J57 -> 0 | K58: =K56*K57 -> 8260000
C60: ST以降
C61: パターン | D61: クラウドアーキ基盤に移行 | R61: 備考
D62: アプリ | N62: DB | P62: 全体
B63: No. | C63: システム | D63: 調査・要件定義 | E63: 設計 | F63: 製造 | G63: 結合テスト | H63: システムテスト | I63: ユーザテスト | J63: 本番稼働 | K63: 管理 | L63: 工数計 | M63: 金額 | N63: 工数計 | O63: 金額 | P63: 工数計 | Q63: 金額
B64: 1 | C64: 数量確定システム（千葉・徳山） | H64: 1.4 | I64: 0.8 | J64: 2 | K64: 1 | L64: =SUM(D64:K64) -> 5.2 | M64: =SUM(D64:J64)*1000000+K64*1400000 -> 5600000 | N64: 0 | O64: 0 | P64: =SUM(L64:L68)+N64 -> 15.7 | Q64: =SUM(M64:M68)+O64 -> 17060000
B65: 2 | C65: 用役管理システム（千葉・徳山） | H65: 1.1 | I65: 0.8 | J65: 2 | K65: 0.8 | L65: =SUM(D65:K65) -> 4.7 | M65: =SUM(D65:J65)*1000000+K65*1400000 -> 5020000
B66: 3 | C66: 千葉化学品質管理システム | H66: 0.8 | I66: 0.5 | J66: 0.6 | K66: 0.5 | L66: =SUM(D66:K66) -> 2.4 | M66: =SUM(D66:J66)*1000000+K66*1400000 -> 2600000
B67: 4 | C67: ＬＭＰＰ包装システム | H67: 0.8 | I67: 0.5 | J67: 0.6 | K67: 0.6 | L67: =SUM(D67:K67) -> 2.5 | M67: =SUM(D67:J67)*1000000+K67*1400000 -> 2740000
B68: 5 | C68: 工場DB | J68: 0.4 | K68: 0.5 | L68: =SUM(D68:K68) -> 0.9 | M68: =SUM(D68:J68)*1000000+K68*1400000 -> 1100000
B69: 6 | C69: ヤ－ド操業システム（千葉・徳山） | H69: 0.2 | I69: 0.1 | J69: 1.5 | K69: 0.3 | L69: =SUM(D69:K69) -> 2.1 | M69: =SUM(D69:J69)*1000000+K69*1400000 -> 2220000 | P69: =SUM(L69:L69)+N69 -> 2.1 | Q69: =SUM(M69:M69)+O64 -> 2220000
B70: 計 | D70: =SUM(D64:D69) -> 0 | E70: =SUM(E64:E69) -> 0 | F70: =SUM(F64:F69) -> 0 | G70: =SUM(G64:G69) -> 0 | H70: =SUM(H64:H69) -> 4.3 | I70: =SUM(I64:I69) -> 2.7 | J70: =SUM(J64:J69) -> 7.1 | K70: =SUM(K64:K69) -> 3.7 | L70: =SUM(D70:K70) -> 17.8 | M70: =SUM(M64:M69) -> 19280000 | N70: =SUM(N64:N69) -> 0 | O70: =SUM(O64:O69) -> 0 | P70: =SUM(P64:P69) -> 17.8 | Q70: =SUM(Q64:Q69) -> 19280000
B71: 単価 | D71: 1000000 | E71: 1000000 | F71: 1000000 | G71: 1000000 | H71: 1000000 | I71: 1000000 | J71: 1000000 | K71: 1400000
B72: 金額 | D72: =D70*D71 -> 0 | E72: =E70*E71 -> 0 | F72: =F70*F71 -> 0 | G72: =G70*G71 -> 0 | H72: =H70*H71 -> 4300000 | I72: =I70*I71 -> 2700000 | J72: =J70*J71 -> 7100000 | K72: =K70*K71 -> 5180000
J74: 小計 | K74: 数量確定システム（千葉・徳山） | L74: =SUM(L36,L50,L64) -> 20.7 | M74: =SUM(M36,M50,M64) -> 22220000
K75: 用役管理システム（千葉・徳山） | L75: =SUM(L37,L51,L65) -> 13.6 | M75: =SUM(M37,M51,M65) -> 14640000
K76: 千葉化学品質管理システム | L76: =SUM(L38,L52,L66) -> 14.8 | M76: =SUM(M38,M52,M66) -> 15880000

Sheet 見積 (システム・縮小共通基盤⇒クラウドアーキサマリ) 
C1: 工数直入力のため注意！！
C2: 見積（縮小共通基盤⇒クラウドアーキサマリ）
C3: パターン | D3: クラウドアーキ基盤に移行 | R3: 備考
D4: アプリ | N4: DB | P4: 全体
B5: No. | C5: システム | D5: 調査・要件定義 | E5: 設計 | F5: 製造 | G5: 結合テスト | H5: システムテスト | I5: ユーザテスト | J5: 本番稼働 | K5: 管理 | L5: 工数計 | M5: 金額 | N5: 工数計 | O5: 金額 | P5: 工数計 | Q5: 金額
B6: 1 | C6: 数量確定システム（千葉・徳山） | D6: 3.2 | E6: 1.6 | F6: 2.7 | G6: 5.2 | H6: 1.4 | I6: 0.8 | J6: 2 | K6: 3.8 | L6: =SUM(D6:K6) -> 20.7 | M6: =SUM(D6:J6)*1000000+K6*1400000 -> 22220000 | N6: 0 | O6: 0 | P6: =SUM(L6:L10)+N6 -> 58.3 | Q6: =SUM(M6:M10)+O6 -> 62900000
B7: 2 | C7: 用役管理システム（千葉・徳山） | D7: 1.4 | E7: 1.1 | F7: 1.5 | G7: 3.1 | H7: 1.1 | I7: 0.8 | J7: 2 | K7: 2.6 | L7: =SUM(D7:K7) -> 13.6 | M7: =SUM(D7:J7)*1000000+K7*1400000 -> 14640000
B8: 3 | C8: 千葉化学品質管理システム | D8: 1.7 | E8: 1.4 | F8: 1.6 | G8: 5.5 | H8: 0.8 | I8: 0.5 | J8: 0.6 | K8: 2.7 | L8: =SUM(D8:K8) -> 14.8 | M8: =SUM(D8:J8)*1000000+K8*1400000 -> 15880000
B9: 4 | C9: ＬＭＰＰ包装システム | D9: 1.3 | E9: 0.4 | F9: 1.6 | G9: 1.2 | H9: 0.8 | I9: 0.5 | J9: 0.6 | K9: 1.9 | L9: =SUM(D9:K9) -> 8.3 | M9: =SUM(D9:J9)*1000000+K9*1400000 -> 9060000
B10: 5 | C10: 工場DB | J10: 0.4 | K10: 0.5 | L10: =SUM(D10:K10) -> 0.9 | M10: =SUM(D10:J10)*1000000+K10*1400000 -> 1100000
B11: 6 | C11: ヤ－ド操業システム（千葉・徳山） | D11: 0.5 | E11: 0.4 | F11: 0.7 | G11: 1.4 | H11: 0.2 | I11: 0.1 | J11: 1.5 | K11: 0.9 | L11: =SUM(D11:K11) -> 5.7 | M11: =SUM(D11:J11)*1000000+K11*1400000 -> 6060000 | N11: 0 | O11: =SUM(O4:O9) -> 0 | P11: =SUM(L11:L11)+N11 -> 5.7 | Q11: =SUM(M11)+O11 -> 6060000
B12: 7 | C12: 縮小共通基盤対応 | M12: ='見積 (縮小共通基盤継続） '!D23 -> 6549000 | N12: 0 | O12: =SUM(O5:O10) -> 0 | P12: =SUM(L12:L12)+N12 -> 0 | Q12: =SUM(M12:M12)+O6 -> 6549000 | R12: 残作業工数
B13: 計 | D13: =SUM(D6:D12) -> 8.1 | E13: =SUM(E6:E12) -> 4.9 | F13: =SUM(F6:F12) -> 8.1 | G13: =SUM(G6:G12) -> 16.4 | H13: =SUM(H6:H12) -> 4.3 | I13: =SUM(I6:I12) -> 2.7 | J13: =SUM(J6:J12) -> 7.1 | K13: =SUM(K6:K12) -> 12.4 | L13: =SUM(D13:K13) -> 64 | M13: =SUM(M6:M12) -> 75509000 | N13: =SUM(N6:N12) -> 0 | O13: =SUM(O6:O12) -> 0 | P13: =SUM(P6:P12) -> 64 | Q13: =SUM(Q6:Q12) -> 75509000
B14: 単価 | D14: 1000000 | E14: 1000000 | F14: 1000000 | G14: 1000000 | H14: 1000000 | I14: 1000000 | J14: 1000000 | K14: 1400000
B15: 金額 | D15: =D13*D14 -> 8100000 | E15: =E13*E14 -> 4900000 | F15: =F13*F14 -> 8100000 | G15: =G13*G14 -> 16400000 | H15: =H13*H14 -> 4300000 | I15: =I13*I14 -> 2700000 | J15: =J13*J14 -> 7100000 | K15: =K13*K14 -> 17360000

Sheet 見積 (各フェーズ毎、品管包装付替済) 
C1: 工数直入力のため注意！！
C2: 見積（工程別サマリ）
C3: パターン | D3: クラウドアーキ基盤に移行 | R3: 備考
D4: アプリ | N4: DB | P4: 全体
B5: No. | C5: システム | D5: 調査・要件定義 | E5: 設計 | F5: 製造 | G5: 結合テスト | H5: システムテスト | I5: ユーザテスト | J5: 本番稼働 | K5: 管理 | L5: 工数計 | M5: 金額 | N5: 工数計 | O5: 金額 | P5: 工数計 | Q5: 金額
B6: 1 | C6: 数量確定システム（千葉・徳山） | D6: 3.2 | E6: 1.6 | F6: 2.7 | G6: 5.2 | H6: 1.4 | I6: 0.8 | J6: 2 | K6: 3.8 | L6: =SUM(D6:K6) -> 20.7 | M6: =SUM(D6:J6)*1000000+K6*1400000 -> 22220000 | N6: 0 | O6: 0 | P6: =SUM(L6:L10)+N6 -> 58.3 | Q6: =SUM(M6:M10)+O6 -> 62900000
B7: 2 | C7: 用役管理システム（千葉・徳山） | D7: 1.4 | E7: 1.1 | F7: 1.5 | G7: 3.1 | H7: 1.1 | I7: 0.8 | J7: 2 | K7: 2.6 | L7: =SUM(D7:K7) -> 13.6 | M7: =SUM(D7:J7)*1000000+K7*1400000 -> 14640000
B8: 3 | C8: 千葉化学品質管理システム | D8: 1.5 | E8: 0.9 | F8: 1.2 | G8: 3.1 | H8: 0.6 | I8: 0.3 | J8: 0.3 | K8: 2.2 | L8: =SUM(D8:K8) -> 10.1 | M8: =SUM(D8:J8)*1000000+K8*1400000 -> 10980000
B9: 4 | C9: ＬＭＰＰ包装システム | D9: 1.5 | E9: 0.9 | F9: 2 | G9: 3.6 | H9: 1 | I9: 0.7 | J9: 0.9 | K9: 2.4 | L9: =SUM(D9:K9) -> 13 | M9: =SUM(D9:J9)*1000000+K9*1400000 -> 13960000
B10: 5 | C10: 工場DB | J10: 0.4 | K10: 0.5 | L10: =SUM(D10:K10) -> 0.9 | M10: =SUM(D10:J10)*1000000+K10*1400000 -> 1100000
B11: 6 | C11: ヤ－ド操業システム（千葉・徳山） | D11: 0.5 | E11: 0.4 | F11: 0.7 | G11: 1.4 | H11: 0.2 | I11: 0.1 | J11: 1.5 | K11: 0.9 | L11: =SUM(D11:K11) -> 5.7 | M11: =SUM(D11:J11)*1000000+K11*1400000 -> 6060000 | N11: 0 | O11: =SUM(O5:O10) -> 0 | P11: =SUM(L11:L11)+N11 -> 5.7 | Q11: =SUM(M11:M11)+O6 -> 6060000
B12: 計 | D12: =SUM(D6:D11) -> 8.1 | E12: =SUM(E6:E11) -> 4.9 | F12: =SUM(F6:F11) -> 8.1 | G12: =SUM(G6:G11) -> 16.4 | H12: =SUM(H6:H11) -> 4.3 | I12: =SUM(I6:I11) -> 2.7 | J12: =SUM(J6:J11) -> 7.1 | K12: =SUM(K6:K11) -> 12.4 | L12: =SUM(D12:K12) -> 64 | M12: =SUM(M6:M11) -> 68960000 | N12: =SUM(N6:N11) -> 0 | O12: =SUM(O6:O11) -> 0 | P12: =SUM(P6:P11) -> 64 | Q12: =SUM(Q6:Q11) -> 68960000
B13: 単価 | D13: 1000000 | E13: 1000000 | F13: 1000000 | G13: 1000000 | H13: 1000000 | I13: 1000000 | J13: 1000000 | K13: 1400000
B14: 金額 | D14: =D12*D13 -> 8100000 | E14: =E12*E13 -> 4900000 | F14: =F12*F13 -> 8100000 | G14: =G12*G13 -> 16400000 | H14: =H12*H13 -> 4300000 | I14: =I12*I13 -> 2700000 | J14: =J12*J13 -> 7100000 | K14: =K12*K13 -> 17360000
C16: 調査・要件定義（移行フェーズの契約変更）
C17: パターン | D17: クラウドアーキ基盤に移行 | R17: 備考
D18: アプリ | N18: DB | P18: 全体
B19: No. | C19: システム | D19: 調査・要件定義 | E19: 設計 | F19: 製造 | G19: 結合テスト | H19: システムテスト | I19: ユーザテスト | J19: 本番稼働 | K19: 管理 | L19: 工数計 | M19: 金額 | N19: 工数計 | O19: 金額 | P19: 工数計 | Q19: 金額
B20: 1 | C20: 数量確定システム（千葉・徳山） | D20: 3.2 | K20: 0.9 | L20: =SUM(D20:K20) -> 4.1 | M20: =SUM(D20:J20)*1000000+K20*1400000 -> 4460000 | N20: 0 | O20: 0 | P20: =SUM(L20:L24)+N20 -> 10.2 | Q20: =SUM(M20:M24)+O20 -> 11240000
B21: 2 | C21: 用役管理システム（千葉・徳山） | D21: 1.4 | K21: 0.6 | L21: =SUM(D21:K21) -> 2 | M21: =SUM(D21:J21)*1000000+K21*1400000 -> 2240000
B22: 3 | C22: 千葉化学品質管理システム | D22: 1.7 | K22: 0.6 | L22: =SUM(D22:K22) -> 2.3 | M22: =SUM(D22:J22)*1000000+K22*1400000 -> 2540000
B23: 4 | C23: ＬＭＰＰ包装システム | D23: 1.3 | K23: 0.5 | L23: =SUM(D23:K23) -> 1.8 | M23: =SUM(D23:J23)*1000000+K23*1400000 -> 2000000
B24: 5 | C24: 工場DB | L24: =SUM(D24:K24) -> 0 | M24: =SUM(D24:J24)*1000000+K24*1400000 -> 0
B25: 6 | C25: ヤ－ド操業システム（千葉・徳山） | D25: 0.5 | K25: 0.2 | L25: =SUM(D25:K25) -> 0.7 | M25: =SUM(D25:J25)*1000000+K25*1400000 -> 780000 | P25: =SUM(L25:L25)+N25 -> 0.7 | Q25: =SUM(M25:M25)+O25 -> 780000
B26: 7 | C26: 縮小共通基盤（移行フェーズ） | L26: =SUM(D26:K26) -> 0 | M26: -6807000 | P26: =SUM(L26:L26)+N26 -> 0 | Q26: =SUM(M26:M26)+O20 -> -6807000 | R26: 現契約残額を差し引き
B27: 計 | D27: =SUM(D20:D26) -> 8.1 | E27: =SUM(E20:E26) -> 0 | F27: =SUM(F20:F26) -> 0 | G27: =SUM(G20:G26) -> 0 | H27: =SUM(H20:H26) -> 0 | I27: =SUM(I20:I26) -> 0 | J27: =SUM(J20:J26) -> 0 | K27: =SUM(K21:K26) -> 1.9 | L27: =SUM(D27:K27) -> 10 | M27: =SUM(M20:M26) -> 5213000 | N27: =SUM(N20:N26) -> 0 | O27: =SUM(O20:O26) -> 0 | P27: =SUM(P20:P26) -> 10.9 | Q27: =SUM(Q20:Q26) -> 5213000
B28: 単価 | D28: 1000000 | E28: 1000000 | F28: 1000000 | G28: 1000000 | H28: 1000000 | I28: 1000000 | J28: 1000000 | K28: 1400000
B29: 金額 | D29: =D27*D28 -> 8100000 | E29: =E27*E28 -> 0 | F29: =F27*F28 -> 0 | G29: =G27*G28 -> 0 | H29: =H27*H28 -> 0 | I29: =I27*I28 -> 0 | J29: =J27*J28 -> 0 | K29: =K27*K28 -> 2660000
C31: 調査・要件定義(クラウドアーキから開始)
C32: パターン | D32: クラウドアーキ基盤に移行 | R32: 備考
D33: アプリ | N33: DB | P33: 全体
B34: No. | C34: システム | D34: 調査・要件定義 | E34: 設計 | F34: 製造 | G34: 結合テスト | H34: システムテスト | I34: ユーザテスト | J34: 本番稼働 | K34: 管理 | L34: 工数計 | M34: 金額 | N34: 工数計 | O34: 金額 | P34: 工数計 | Q34: 金額
B35: 1 | C35: 数量確定システム（千葉・徳山） | D35: 3.2 | E35: 1.6 | K35: 0.8 | L35: =SUM(D35:K35) -> 5.6 | M35: =SUM(D35:J35)*1000000+K35*1400000 -> 5920000 | N35: 0 | O35: 0 | P35: =SUM(L35:L39)+N35 -> 15 | Q35: =SUM(M35:M39)+O35 -> 16160000
B36: 2 | C36: 用役管理システム（千葉・徳山） | D36: 1.4 | E36: 1.1 | K36: 0.7 | L36: =SUM(D36:K36) -> 3.2 | M36: =SUM(D36:J36)*1000000+K36*1400000 -> 3480000
B37: 3 | C37: 千葉化学品質管理システム | D37: 1.5 | E37: 0.9 | K37: 0.7 | L37: =SUM(D37:K37) -> 3.1 | M37: =SUM(D37:J37)*1000000+K37*1400000 -> 3380000
B38: 4 | C38: ＬＭＰＰ包装システム | D38: 1.5 | E38: 0.9 | K38: 0.7 | L38: =SUM(D38:K38) -> 3.1 | M38: =SUM(D38:J38)*1000000+K38*1400000 -> 3380000
B39: 5 | C39: 工場DB | L39: =SUM(D39:K39) -> 0 | M39: =SUM(D39:J39)*1000000+K39*1400000 -> 0
B40: 6 | C40: ヤ－ド操業システム（千葉・徳山） | D40: 0.5 | E40: 0.4 | K40: 0.3 | L40: =SUM(D40:K40) -> 1.2 | M40: =SUM(D40:J40)*1000000+K40*1400000 -> 1320000 | P40: =SUM(L40:L40)+N40 -> 1.2 | Q40: =SUM(M40:M40)+O35 -> 1320000
B41: 計 | D41: =SUM(D35:D40) -> 8.1 | E41: =SUM(E35:E40) -> 4.9 | F41: =SUM(F35:F40) -> 0 | G41: =SUM(G35:G40) -> 0 | H41: =SUM(H35:H40) -> 0 | I41: =SUM(I35:I40) -> 0 | J41: =SUM(J35:J40) -> 0 | K41: =SUM(K35:K40) -> 3.2 | L41: =SUM(D41:K41) -> 16.2 | M41: =SUM(M35:M40) -> 17480000 | N41: =SUM(N35:N40) -> 0 | O41: =SUM(O35:O40) -> 0 | P41: =SUM(P35:P40) -> 16.2 | Q41: =SUM(Q35:Q40) -> 17480000
B42: 単価 | D42: 1000000 | E42: 1000000 | F42: 1000000 | G42: 1000000 | H42: 1000000 | I42: 1000000 | J42: 1000000 | K42: 1400000
B43: 金額 | D43: =D41*D42 -> 8100000 | E43: =E41*E42 -> 4900000 | F43: =F41*F42 -> 0 | G43: =G41*G42 -> 0 | H43: =H41*H42 -> 0 | I43: =I41*I42 -> 0 | J43: =J41*J42 -> 0 | K43: =K41*K42 -> 4480000
L44: 契約済み残額 | M44: 6807000
C45: 調査・要件定義（移行フェーズの契約変更）
C46: パターン | D46: クラウドアーキ基盤に移行 | R46: 備考
D47: アプリ | N47: DB | P47: 全体
B48: No. | C48: システム | D48: 調査・要件定義 | E48: 設計 | F48: 製造 | G48: 結合テスト | H48: システムテスト | I48: ユーザテスト | J48: 本番稼働 | K48: 管理 | L48: 工数計 | M48: 金額 | N48: 工数計 | O48: 金額 | P48: 工数計 | Q48: 金額
B49: 1 | C49: 数量確定システム（千葉・徳山） | D49: 3.2 | K49: 0.9 | L49: =SUM(D49:K49) -> 4.1 | M49: =SUM(D49:J49)*1000000+K49*1400000 -> 4460000 | N49: 0 | O49: 0 | P49: =SUM(L49:L53)+N49 -> 10.2 | Q49: =SUM(M49:M53)+O49 -> 11240000
B50: 2 | C50: 用役管理システム（千葉・徳山） | D50: 1.4 | K50: 0.6 | L50: =SUM(D50:K50) -> 2 | M50: =SUM(D50:J50)*1000000+K50*1400000 -> 2240000
B51: 3 | C51: 千葉化学品質管理システム | D51: 1.7 | K51: 0.6 | L51: =SUM(D51:K51) -> 2.3 | M51: =SUM(D51:J51)*1000000+K51*1400000 -> 2540000
B52: 4 | C52: ＬＭＰＰ包装システム | D52: 1.3 | K52: 0.5 | L52: =SUM(D52:K52) -> 1.8 | M52: =SUM(D52:J52)*1000000+K52*1400000 -> 2000000
B53: 5 | C53: 工場DB | L53: =SUM(D53:K53) -> 0 | M53: =SUM(D53:J53)*1000000+K53*1400000 -> 0
B54: 6 | C54: ヤ－ド操業システム（千葉・徳山） | D54: 0.5 | K54: 0.2 | L54: =SUM(D54:K54) -> 0.7 | M54: =SUM(D54:J54)*1000000+K54*1400000 -> 780000 | P54: =SUM(L54:L54)+N54 -> 0.7 | Q54: =SUM(M54:M54)+O54 -> 780000
B55: 7 | C55: 縮小共通基盤（移行フェーズ） | L55: =SUM(D55:K55) -> 0 | M55: -6807000 | P55: =SUM(L55:L55)+N55 -> 0 | Q55: =SUM(M55:M55)+O49 -> -6807000 | R55: 現契約残額を差し引き
B56: 計 | D56: =SUM(D49:D55) -> 8.1 | E56: =SUM(E49:E55) -> 0 | F56: =SUM(F49:F55) -> 0 | G56: =SUM(G49:G55) -> 0 | H56: =SUM(H49:H55) -> 0 | I56: =SUM(I49:I55) -> 0 | J56: =SUM(J49:J55) -> 0 | K56: =SUM(K50:K55) -> 1.9 | L56: =SUM(D56:K56) -> 10 | M56: =SUM(M49:M55) -> 5213000 | N56: =SUM(N49:N55) -> 0 | O56: =SUM(O49:O55) -> 0 | P56: =SUM(P49:P55) -> 10.9 | Q56: =SUM(Q49:Q55) -> 5213000
B57: 単価 | D57: 1000000 | E57: 1000000 | F57: 1000000 | G57: 1000000 | H57: 1000000 | I57: 1000000 | J57: 1000000 | K57: 1400000
B58: 金額 | D58: =D56*D57 -> 8100000 | E58: =E56*E57 -> 0 | F58: =F56*F57 -> 0 | G58: =G56*G57 -> 0 | H58: =H56*H57 -> 0 | I58: =I56*I57 -> 0 | J58: =J56*J57 -> 0 | K58: =K56*K57 -> 2660000
L59: 差額 | M59: =M41-M44 -> 10673000
C60: 調査・要件定義(クラウドアーキから開始)値引き
C61: パターン | D61: クラウドアーキ基盤に移行 | R61: 備考
D62: アプリ | N62: DB | P62: 全体
B63: No. | C63: システム | D63: 調査・要件定義 | E63: 設計 | F63: 製造 | G63: 結合テスト | H63: システムテスト | I63: ユーザテスト | J63: 本番稼働 | K63: 管理 | L63: 工数計 | M63: 金額 | N63: 工数計 | O63: 金額 | P63: 工数計 | Q63: 金額
B64: 1 | C64: 数量確定システム（千葉・徳山） | D64: 0.2 | E64: 1.6 | K64: 0.8 | L64: =SUM(D64:K64) -> 2.6 | M64: =SUM(D64:J64)*1000000+K64*1400000 -> 2920000 | N64: 0 | O64: 0 | P64: =SUM(L64:L68)+N64 -> 8.193 | Q64: =SUM(M64:M68)+O64 -> 9353000
B65: 2 | C65: 用役管理システム（千葉・徳山） | D65: 0.2 | E65: 1.1 | K65: 0.7 | L65: =SUM(D65:K65) -> 2 | M65: =SUM(D65:J65)*1000000+K65*1400000 -> 2280000
B66: 3 | C66: 千葉化学品質管理システム | D66: 0.193 | E66: 0.9 | K66: 0.7 | L66: =SUM(D66:K66) -> 1.793 | M66: =SUM(D66:J66)*1000000+K66*1400000 -> 2073000
B67: 4 | C67: ＬＭＰＰ包装システム | D67: 0.2 | E67: 0.9 | K67: 0.7 | L67: =SUM(D67:K67) -> 1.8 | M67: =SUM(D67:J67)*1000000+K67*1400000 -> 2080000
B68: 5 | C68: 工場DB | L68: =SUM(D68:K68) -> 0 | M68: =SUM(D68:J68)*1000000+K68*1400000 -> 0
B69: 6 | C69: ヤ－ド操業システム（千葉・徳山） | D69: 0.5 | E69: 0.4 | K69: 0.3 | L69: =SUM(D69:K69) -> 1.2 | M69: =SUM(D69:J69)*1000000+K69*1400000 -> 1320000 | P69: =SUM(L69:L69)+N69 -> 1.2 | Q69: =SUM(M69:M69)+O64 -> 1320000
B70: 計 | D70: =SUM(D64:D69) -> 1.293 | E70: =SUM(E64:E69) -> 4.9 | F70: =SUM(F64:F69) -> 0 | G70: =SUM(G64:G69) -> 0 | H70: =SUM(H64:H69) -> 0 | I70: =SUM(I64:I69) -> 0 | J70: =SUM(J64:J69) -> 0 | K70: =SUM(K64:K69) -> 3.2 | L70: =SUM(D70:K70) -> 9.393 | M70: =SUM(M64:M69) -> 10673000 | N70: =SUM(N64:N69) -> 0 | O70: =SUM(O64:O69) -> 0 | P70: =SUM(P64:P69) -> 9.393 | Q70: =SUM(Q64:Q69) -> 10673000
B71: 単価 | D71: 1000000 | E71: 1000000 | F71: 1000000 | G71: 1000000 | H71: 1000000 | I71: 1000000 | J71: 1000000 | K71: 1400000
B72: 金額 | D72: =D70*D71 -> 1293000 | E72: =E70*E71 -> 4900000 | F72: =F70*F71 -> 0 | G72: =G70*G71 -> 0 | H72: =H70*H71 -> 0 | I72: =I70*I71 -> 0 | J72: =J70*J71 -> 0 | K72: =K70*K71 -> 4480000
L73: =K41/L41 -> 0.19753086
C74: 開発フェーズ
C75: パターン | D75: クラウドアーキ基盤に移行 | R75: 備考
D76: アプリ | N76: DB | P76: 全体
B77: No. | C77: システム | D77: 調査・要件定義 | E77: 設計 | F77: 製造 | G77: 結合テスト | H77: システムテスト | I77: ユーザテスト | J77: 本番稼働 | K77: 管理 | L77: 工数計 | M77: 金額 | N77: 工数計 | O77: 金額 | P77: 工数計 | Q77: 金額
B78: 1 | C78: 数量確定システム（千葉・徳山） | F78: 2.7 | G78: 5.2 | K78: 2 | L78: =SUM(D78:K78) -> 9.9 | M78: =SUM(D78:J78)*1000000+K78*1400000 -> 10700000 | N78: 0 | O78: 0 | P78: =SUM(L78:L82)+N78 -> 27.6 | Q78: =SUM(M78:M82)+O78 -> 29680000
B79: 2 | C79: 用役管理システム（千葉・徳山） | F79: 1.5 | G79: 3.1 | K79: 1.1 | L79: =SUM(D79:K79) -> 5.7 | M79: =SUM(D79:J79)*1000000+K79*1400000 -> 6140000
B80: 3 | C80: 千葉化学品質管理システム | F80: 1.2 | G80: 3.1 | K80: 1 | L80: =SUM(D80:K80) -> 5.3 | M80: =SUM(D80:J80)*1000000+K80*1400000 -> 5700000
B81: 4 | C81: ＬＭＰＰ包装システム | F81: 2 | G81: 3.6 | K81: 1.1 | L81: =SUM(D81:K81) -> 6.7 | M81: =SUM(D81:J81)*1000000+K81*1400000 -> 7140000
B82: 5 | C82: 工場DB | L82: =SUM(D82:K82) -> 0 | M82: =SUM(D82:J82)*1000000+K82*1400000 -> 0
B83: 6 | C83: ヤ－ド操業システム（千葉・徳山） | F83: 0.7 | G83: 1.4 | K83: 0.3 | L83: =SUM(D83:K83) -> 2.4 | M83: =SUM(D83:J83)*1000000+K83*1400000 -> 2520000 | P83: =SUM(L83:L83)+N83 -> 2.4 | Q83: =SUM(M83:M83)+O78 -> 2520000
B84: 計 | D84: =SUM(D78:D83) -> 0 | E84: =SUM(E78:E83) -> 0 | F84: =SUM(F78:F83) -> 8.1 | G84: =SUM(G78:G83) -> 16.4 | H84: =SUM(H78:H83) -> 0 | I84: =SUM(I78:I83) -> 0 | J84: =SUM(J78:J83) -> 0 | K84: =SUM(K78:K83) -> 5.5 | L84: =SUM(D84:K84) -> 30 | M84: =SUM(M78:M83) -> 32200000 | N84: =SUM(N78:N83) -> 0 | O84: =SUM(O78:O83) -> 0 | P84: =SUM(P78:P83) -> 30 | Q84: =SUM(Q78:Q83) -> 32200000
B85: 単価 | D85: 1000000 | E85: 1000000 | F85: 1000000 | G85: 1000000 | H85: 1000000 | I85: 1000000 | J85: 1000000 | K85: 1400000
B86: 金額 | D86: =D84*D85 -> 0 | E86: =E84*E85 -> 0 | F86: =F84*F85 -> 8100000 | G86: =G84*G85 -> 16400000 | H86: =H84*H85 -> 0 | I86: =I84*I85 -> 0 | J86: =J84*J85 -> 0 | K86: =K84*K85 -> 7700000
L87: =K84/L84 -> 0.18333333
C88: ST以降
C89: パターン | D89: クラウドアーキ基盤に移行 | R89: 備考
D90: アプリ | N90: DB | P90: 全体
B91: No. | C91: システム | D91: 調査・要件定義 | E91: 設計 | F91: 製造 | G91: 結合テスト | H91: システムテスト | I91: ユーザテスト | J91: 本番稼働 | K91: 管理 | L91: 工数計 | M91: 金額 | N91: 工数計 | O91: 金額 | P91: 工数計 | Q91: 金額
B92: 1 | C92: 数量確定システム（千葉・徳山） | H92: 1.4 | I92: 0.8 | J92: 2 | K92: 1 | L92: =SUM(D92:K92) -> 5.2 | M92: =SUM(D92:J92)*1000000+K92*1400000 -> 5600000 | N92: 0 | O92: 0 | P92: =SUM(L92:L96)+N92 -> 15.7 | Q92: =SUM(M92:M96)+O92 -> 17060000
B93: 2 | C93: 用役管理システム（千葉・徳山） | H93: 1.1 | I93: 0.8 | J93: 2 | K93: 0.8 | L93: =SUM(D93:K93) -> 4.7 | M93: =SUM(D93:J93)*1000000+K93*1400000 -> 5020000
B94: 3 | C94: 千葉化学品質管理システム | H94: 0.6 | I94: 0.3 | J94: 0.3 | K94: 0.5 | L94: =SUM(D94:K94) -> 1.7 | M94: =SUM(D94:J94)*1000000+K94*1400000 -> 1900000
B95: 4 | C95: ＬＭＰＰ包装システム | H95: 1 | I95: 0.7 | J95: 0.9 | K95: 0.6 | L95: =SUM(D95:K95) -> 3.2 | M95: =SUM(D95:J95)*1000000+K95*1400000 -> 3440000
B96: 5 | C96: 工場DB | J96: 0.4 | K96: 0.5 | L96: =SUM(D96:K96) -> 0.9 | M96: =SUM(D96:J96)*1000000+K96*1400000 -> 1100000
B97: 6 | C97: ヤ－ド操業システム（千葉・徳山） | H97: 0.2 | I97: 0.1 | J97: 1.5 | K97: 0.3 | L97: =SUM(D97:K97) -> 2.1 | M97: =SUM(D97:J97)*1000000+K97*1400000 -> 2220000 | P97: =SUM(L97:L97)+N97 -> 2.1 | Q97: =SUM(M97:M97)+O92 -> 2220000
B98: 計 | D98: =SUM(D92:D97) -> 0 | E98: =SUM(E92:E97) -> 0 | F98: =SUM(F92:F97) -> 0 | G98: =SUM(G92:G97) -> 0 | H98: =SUM(H92:H97) -> 4.3 | I98: =SUM(I92:I97) -> 2.7 | J98: =SUM(J92:J97) -> 7.1 | K98: =SUM(K92:K97) -> 3.7 | L98: =SUM(D98:K98) -> 17.8 | M98: =SUM(M92:M97) -> 19280000 | N98: =SUM(N92:N97) -> 0 | O98: =SUM(O92:O97) -> 0 | P98: =SUM(P92:P97) -> 17.8 | Q98: =SUM(Q92:Q97) -> 19280000
B99: 単価 | D99: 1000000 | E99: 1000000 | F99: 1000000 | G99: 1000000 | H99: 1000000 | I99: 1000000 | J99: 1000000 | K99: 1400000
B100: 金額 | D100: =D98*D99 -> 0 | E100: =E98*E99 -> 0 | F100: =F98*F99 -> 0 | G100: =G98*G99 -> 0 | H100: =H98*H99 -> 4300000 | I100: =I98*I99 -> 2700000 | J100: =J98*J99 -> 7100000 | K100: =K98*K99 -> 5180000
L101: =K98/L98 -> 0.20786517
J102: 小計 | K102: 数量確定システム（千葉・徳山） | L102: =SUM(L35,L78,L92) -> 20.7 | M102: =SUM(M35,M78,M92) -> 22220000
...

Sheet 見積 (要件_設計で区切り) 
C1: 工数直入力のため注意！！
C2: 見積（工程別サマリ）
C3: パターン | D3: クラウドアーキ基盤に移行 | R3: 備考
D4: アプリ | N4: DB | P4: 全体
B5: No. | C5: システム | D5: 調査・要件定義 | E5: 設計 | F5: 製造 | G5: 結合テスト | H5: システムテスト | I5: ユーザテスト | J5: 本番稼働 | K5: 管理 | L5: 工数計 | M5: 金額 | N5: 工数計 | O5: 金額 | P5: 工数計 | Q5: 金額
B6: 1 | C6: 数量確定システム（千葉・徳山） | D6: 3.2 | E6: 1.6 | F6: 2.7 | G6: 5.2 | H6: 1.4 | I6: 0.8 | J6: 2 | K6: 3.8 | L6: =SUM(D6:K6) -> 20.7 | M6: =SUM(D6:J6)*1000000+K6*1400000 -> 22220000 | N6: 0 | O6: 0 | P6: =SUM(L6:L10)+N6 -> 58.3 | Q6: =SUM(M6:M10)+O6 -> 62900000
B7: 2 | C7: 用役管理システム（千葉・徳山） | D7: 1.4 | E7: 1.1 | F7: 1.5 | G7: 3.1 | H7: 1.1 | I7: 0.8 | J7: 2 | K7: 2.6 | L7: =SUM(D7:K7) -> 13.6 | M7: =SUM(D7:J7)*1000000+K7*1400000 -> 14640000
B8: 3 | C8: 千葉化学品質管理システム | D8: 1.7 | E8: 1.4 | F8: 1.6 | G8: 5.5 | H8: 0.8 | I8: 0.5 | J8: 0.6 | K8: 2.7 | L8: =SUM(D8:K8) -> 14.8 | M8: =SUM(D8:J8)*1000000+K8*1400000 -> 15880000
B9: 4 | C9: ＬＭＰＰ包装システム | D9: 1.3 | E9: 0.4 | F9: 1.6 | G9: 1.2 | H9: 0.8 | I9: 0.5 | J9: 0.6 | K9: 1.9 | L9: =SUM(D9:K9) -> 8.3 | M9: =SUM(D9:J9)*1000000+K9*1400000 -> 9060000
B10: 5 | C10: 工場DB | J10: 0.4 | K10: 0.5 | L10: =SUM(D10:K10) -> 0.9 | M10: =SUM(D10:J10)*1000000+K10*1400000 -> 1100000
B11: 6 | C11: ヤ－ド操業システム（千葉・徳山） | D11: 0.5 | E11: 0.4 | F11: 0.7 | G11: 1.4 | H11: 0.2 | I11: 0.1 | J11: 1.5 | K11: 0.9 | L11: =SUM(D11:K11) -> 5.7 | M11: =SUM(D11:J11)*1000000+K11*1400000 -> 6060000 | N11: 0 | O11: =SUM(O5:O10) -> 0 | P11: =SUM(L11:L11)+N11 -> 5.7 | Q11: =SUM(M11:M11)+O6 -> 6060000
B12: 計 | D12: =SUM(D6:D11) -> 8.1 | E12: =SUM(E6:E11) -> 4.9 | F12: =SUM(F6:F11) -> 8.1 | G12: =SUM(G6:G11) -> 16.4 | H12: =SUM(H6:H11) -> 4.3 | I12: =SUM(I6:I11) -> 2.7 | J12: =SUM(J6:J11) -> 7.1 | K12: =SUM(K6:K11) -> 12.4 | L12: =SUM(D12:K12) -> 64 | M12: =SUM(M6:M11) -> 68960000 | N12: =SUM(N6:N11) -> 0 | O12: =SUM(O6:O11) -> 0 | P12: =SUM(P6:P11) -> 64 | Q12: =SUM(Q6:Q11) -> 68960000
B13: 単価 | D13: 1000000 | E13: 1000000 | F13: 1000000 | G13: 1000000 | H13: 1000000 | I13: 1000000 | J13: 1000000 | K13: 1400000
B14: 金額 | D14: =D12*D13 -> 8100000 | E14: =E12*E13 -> 4900000 | F14: =F12*F13 -> 8100000 | G14: =G12*G13 -> 16400000 | H14: =H12*H13 -> 4300000 | I14: =I12*I13 -> 2700000 | J14: =J12*J13 -> 7100000 | K14: =K12*K13 -> 17360000
C16: 調査・要件定義（移行フェーズの契約変更）
C17: パターン | D17: クラウドアーキ基盤に移行 | R17: 備考
D18: アプリ | N18: DB | P18: 全体
B19: No. | C19: システム | D19: 調査・要件定義 | E19: 設計 | F19: 製造 | G19: 結合テスト | H19: システムテスト | I19: ユーザテスト | J19: 本番稼働 | K19: 管理 | L19: 工数計 | M19: 金額 | N19: 工数計 | O19: 金額 | P19: 工数計 | Q19: 金額
B20: 1 | C20: 数量確定システム（千葉・徳山） | D20: 3.2 | K20: 0.9 | L20: =SUM(D20:K20) -> 4.1 | M20: =SUM(D20:J20)*1000000+K20*1400000 -> 4460000 | N20: 0 | O20: 0 | P20: =SUM(L20:L24)+N20 -> 10.2 | Q20: =SUM(M20:M24)+O20 -> 11240000
B21: 2 | C21: 用役管理システム（千葉・徳山） | D21: 1.4 | K21: 0.6 | L21: =SUM(D21:K21) -> 2 | M21: =SUM(D21:J21)*1000000+K21*1400000 -> 2240000
B22: 3 | C22: 千葉化学品質管理システム | D22: 1.7 | K22: 0.6 | L22: =SUM(D22:K22) -> 2.3 | M22: =SUM(D22:J22)*1000000+K22*1400000 -> 2540000
B23: 4 | C23: ＬＭＰＰ包装システム | D23: 1.3 | K23: 0.5 | L23: =SUM(D23:K23) -> 1.8 | M23: =SUM(D23:J23)*1000000+K23*1400000 -> 2000000
B24: 5 | C24: 工場DB | L24: =SUM(D24:K24) -> 0 | M24: =SUM(D24:J24)*1000000+K24*1400000 -> 0
B25: 6 | C25: ヤ－ド操業システム（千葉・徳山） | D25: 0.5 | K25: 0.2 | L25: =SUM(D25:K25) -> 0.7 | M25: =SUM(D25:J25)*1000000+K25*1400000 -> 780000 | P25: =SUM(L25:L25)+N25 -> 0.7 | Q25: =SUM(M25:M25)+O25 -> 780000
B26: 7 | C26: 縮小共通基盤（移行フェーズ） | L26: =SUM(D26:K26) -> 0 | M26: -6807000 | P26: =SUM(L26:L26)+N26 -> 0 | Q26: =SUM(M26:M26)+O20 -> -6807000 | R26: 現契約残額を差し引き
B27: 計 | D27: =SUM(D20:D26) -> 8.1 | E27: =SUM(E20:E26) -> 0 | F27: =SUM(F20:F26) -> 0 | G27: =SUM(G20:G26) -> 0 | H27: =SUM(H20:H26) -> 0 | I27: =SUM(I20:I26) -> 0 | J27: =SUM(J20:J26) -> 0 | K27: =SUM(K21:K26) -> 1.9 | L27: =SUM(D27:K27) -> 10 | M27: =SUM(M20:M26) -> 5213000 | N27: =SUM(N20:N26) -> 0 | O27: =SUM(O20:O26) -> 0 | P27: =SUM(P20:P26) -> 10.9 | Q27: =SUM(Q20:Q26) -> 5213000
B28: 単価 | D28: 1000000 | E28: 1000000 | F28: 1000000 | G28: 1000000 | H28: 1000000 | I28: 1000000 | J28: 1000000 | K28: 1400000
B29: 金額 | D29: =D27*D28 -> 8100000 | E29: =E27*E28 -> 0 | F29: =F27*F28 -> 0 | G29: =G27*G28 -> 0 | H29: =H27*H28 -> 0 | I29: =I27*I28 -> 0 | J29: =J27*J28 -> 0 | K29: =K27*K28 -> 2660000
C31: 調査・要件定義(クラウドアーキから開始)
C32: パターン | D32: クラウドアーキ基盤に移行 | R32: 備考
D33: アプリ | N33: DB | P33: 全体
B34: No. | C34: システム | D34: 調査・要件定義 | E34: 設計 | F34: 製造 | G34: 結合テスト | H34: システムテスト | I34: ユーザテスト | J34: 本番稼働 | K34: 管理 | L34: 工数計 | M34: 金額 | N34: 工数計 | O34: 金額 | P34: 工数計 | Q34: 金額
B35: 1 | C35: 数量確定システム（千葉・徳山） | D35: 3.2 | E35: 1.6 | K35: 1.2 | L35: =SUM(D35:K35) -> 6 | M35: =SUM(D35:J35)*1000000+K35*1400000 -> 6480000 | N35: 0 | O35: 0 | P35: =SUM(L35:L39)+N35 -> 15.6 | Q35: =SUM(M35:M39)+O35 -> 17000000
B36: 2 | C36: 用役管理システム（千葉・徳山） | D36: 1.4 | E36: 1.1 | K36: 0.8 | L36: =SUM(D36:K36) -> 3.3 | M36: =SUM(D36:J36)*1000000+K36*1400000 -> 3620000
B37: 3 | C37: 千葉化学品質管理システム | D37: 1.7 | E37: 1.4 | K37: 0.8 | L37: =SUM(D37:K37) -> 3.9 | M37: =SUM(D37:J37)*1000000+K37*1400000 -> 4220000
B38: 4 | C38: ＬＭＰＰ包装システム | D38: 1.3 | E38: 0.4 | K38: 0.7 | L38: =SUM(D38:K38) -> 2.4 | M38: =SUM(D38:J38)*1000000+K38*1400000 -> 2680000
B39: 5 | C39: 工場DB | L39: =SUM(D39:K39) -> 0 | M39: =SUM(D39:J39)*1000000+K39*1400000 -> 0
B40: 6 | C40: ヤ－ド操業システム（千葉・徳山） | D40: 0.5 | E40: 0.4 | K40: 0.3 | L40: =SUM(D40:K40) -> 1.2 | M40: =SUM(D40:J40)*1000000+K40*1400000 -> 1320000 | P40: =SUM(L40:L40)+N40 -> 1.2 | Q40: =SUM(M40:M40)+O35 -> 1320000
B41: 計 | D41: =SUM(D35:D40) -> 8.1 | E41: =SUM(E35:E40) -> 4.9 | F41: =SUM(F35:F40) -> 0 | G41: =SUM(G35:G40) -> 0 | H41: =SUM(H35:H40) -> 0 | I41: =SUM(I35:I40) -> 0 | J41: =SUM(J35:J40) -> 0 | K41: =SUM(K36:K40) -> 2.6 | L41: =SUM(D41:K41) -> 15.6 | M41: =SUM(M35:M40) -> 18320000 | N41: =SUM(N35:N40) -> 0 | O41: =SUM(O35:O40) -> 0 | P41: =SUM(P35:P40) -> 16.8 | Q41: =SUM(Q35:Q40) -> 18320000
B42: 単価 | D42: 1000000 | E42: 1000000 | F42: 1000000 | G42: 1000000 | H42: 1000000 | I42: 1000000 | J42: 1000000 | K42: 1400000
B43: 金額 | D43: =D41*D42 -> 8100000 | E43: =E41*E42 -> 4900000 | F43: =F41*F42 -> 0 | G43: =G41*G42 -> 0 | H43: =H41*H42 -> 0 | I43: =I41*I42 -> 0 | J43: =J41*J42 -> 0 | K43: =K41*K42 -> 3640000
C45: 開発フェーズ
C46: パターン | D46: クラウドアーキ基盤に移行 | R46: 備考
D47: アプリ | N47: DB | P47: 全体
B48: No. | C48: システム | D48: 調査・要件定義 | E48: 設計 | F48: 製造 | G48: 結合テスト | H48: システムテスト | I48: ユーザテスト | J48: 本番稼働 | K48: 管理 | L48: 工数計 | M48: 金額 | N48: 工数計 | O48: 金額 | P48: 工数計 | Q48: 金額
B49: 1 | C49: 数量確定システム（千葉・徳山） | F49: 2.7 | G49: 5.2 | K49: 1.6 | L49: =SUM(D49:K49) -> 9.5 | M49: =SUM(D49:J49)*1000000+K49*1400000 -> 10140000 | N49: 0 | O49: 0 | P49: =SUM(L49:L53)+N49 -> 27 | Q49: =SUM(M49:M53)+O49 -> 28840000
B50: 2 | C50: 用役管理システム（千葉・徳山） | F50: 1.5 | G50: 3.1 | K50: 1 | L50: =SUM(D50:K50) -> 5.6 | M50: =SUM(D50:J50)*1000000+K50*1400000 -> 6000000
B51: 3 | C51: 千葉化学品質管理システム | F51: 1.6 | G51: 5.5 | K51: 1.4 | L51: =SUM(D51:K51) -> 8.5 | M51: =SUM(D51:J51)*1000000+K51*1400000 -> 9060000
B52: 4 | C52: ＬＭＰＰ包装システム | F52: 1.6 | G52: 1.2 | K52: 0.6 | L52: =SUM(D52:K52) -> 3.4 | M52: =SUM(D52:J52)*1000000+K52*1400000 -> 3640000
B53: 5 | C53: 工場DB | L53: =SUM(D53:K53) -> 0 | M53: =SUM(D53:J53)*1000000+K53*1400000 -> 0
B54: 6 | C54: ヤ－ド操業システム（千葉・徳山） | F54: 0.7 | G54: 1.4 | K54: 0.3 | L54: =SUM(D54:K54) -> 2.4 | M54: =SUM(D54:J54)*1000000+K54*1400000 -> 2520000 | P54: =SUM(L54:L54)+N54 -> 2.4 | Q54: =SUM(M54:M54)+O49 -> 2520000
B55: 計 | D55: =SUM(D49:D54) -> 0 | E55: =SUM(E49:E54) -> 0 | F55: =SUM(F49:F54) -> 8.1 | G55: =SUM(G49:G54) -> 16.4 | H55: =SUM(H49:H54) -> 0 | I55: =SUM(I49:I54) -> 0 | J55: =SUM(J49:J54) -> 0 | K55: =SUM(K49:K54) -> 4.9 | L55: =SUM(D55:K55) -> 29.4 | M55: =SUM(M49:M54) -> 31360000 | N55: =SUM(N49:N54) -> 0 | O55: =SUM(O49:O54) -> 0 | P55: =SUM(P49:P54) -> 29.4 | Q55: =SUM(Q49:Q54) -> 31360000
B56: 単価 | D56: 1000000 | E56: 1000000 | F56: 1000000 | G56: 1000000 | H56: 1000000 | I56: 1000000 | J56: 1000000 | K56: 1400000
B57: 金額 | D57: =D55*D56 -> 0 | E57: =E55*E56 -> 0 | F57: =F55*F56 -> 8100000 | G57: =G55*G56 -> 16400000 | H57: =H55*H56 -> 0 | I57: =I55*I56 -> 0 | J57: =J55*J56 -> 0 | K57: =K55*K56 -> 6860000
C59: ST以降
C60: パターン | D60: クラウドアーキ基盤に移行 | R60: 備考
D61: アプリ | N61: DB | P61: 全体
B62: No. | C62: システム | D62: 調査・要件定義 | E62: 設計 | F62: 製造 | G62: 結合テスト | H62: システムテスト | I62: ユーザテスト | J62: 本番稼働 | K62: 管理 | L62: 工数計 | M62: 金額 | N62: 工数計 | O62: 金額 | P62: 工数計 | Q62: 金額
B63: 1 | C63: 数量確定システム（千葉・徳山） | H63: 1.4 | I63: 0.8 | J63: 2 | K63: 1 | L63: =SUM(D63:K63) -> 5.2 | M63: =SUM(D63:J63)*1000000+K63*1400000 -> 5600000 | N63: 0 | O63: 0 | P63: =SUM(L63:L67)+N63 -> 15.7 | Q63: =SUM(M63:M67)+O63 -> 17060000
B64: 2 | C64: 用役管理システム（千葉・徳山） | H64: 1.1 | I64: 0.8 | J64: 2 | K64: 0.8 | L64: =SUM(D64:K64) -> 4.7 | M64: =SUM(D64:J64)*1000000+K64*1400000 -> 5020000
B65: 3 | C65: 千葉化学品質管理システム | H65: 0.8 | I65: 0.5 | J65: 0.6 | K65: 0.5 | L65: =SUM(D65:K65) -> 2.4 | M65: =SUM(D65:J65)*1000000+K65*1400000 -> 2600000
B66: 4 | C66: ＬＭＰＰ包装システム | H66: 0.8 | I66: 0.5 | J66: 0.6 | K66: 0.6 | L66: =SUM(D66:K66) -> 2.5 | M66: =SUM(D66:J66)*1000000+K66*1400000 -> 2740000
B67: 5 | C67: 工場DB | J67: 0.4 | K67: 0.5 | L67: =SUM(D67:K67) -> 0.9 | M67: =SUM(D67:J67)*1000000+K67*1400000 -> 1100000
B68: 6 | C68: ヤ－ド操業システム（千葉・徳山） | H68: 0.2 | I68: 0.1 | J68: 1.5 | K68: 0.3 | L68: =SUM(D68:K68) -> 2.1 | M68: =SUM(D68:J68)*1000000+K68*1400000 -> 2220000 | P68: =SUM(L68:L68)+N68 -> 2.1 | Q68: =SUM(M68:M68)+O63 -> 2220000
B69: 計 | D69: =SUM(D63:D68) -> 0 | E69: =SUM(E63:E68) -> 0 | F69: =SUM(F63:F68) -> 0 | G69: =SUM(G63:G68) -> 0 | H69: =SUM(H63:H68) -> 4.3 | I69: =SUM(I63:I68) -> 2.7 | J69: =SUM(J63:J68) -> 7.1 | K69: =SUM(K63:K68) -> 3.7 | L69: =SUM(D69:K69) -> 17.8 | M69: =SUM(M63:M68) -> 19280000 | N69: =SUM(N63:N68) -> 0 | O69: =SUM(O63:O68) -> 0 | P69: =SUM(P63:P68) -> 17.8 | Q69: =SUM(Q63:Q68) -> 19280000
B70: 単価 | D70: 1000000 | E70: 1000000 | F70: 1000000 | G70: 1000000 | H70: 1000000 | I70: 1000000 | J70: 1000000 | K70: 1400000
B71: 金額 | D71: =D69*D70 -> 0 | E71: =E69*E70 -> 0 | F71: =F69*F70 -> 0 | G71: =G69*G70 -> 0 | H71: =H69*H70 -> 4300000 | I71: =I69*I70 -> 2700000 | J71: =J69*J70 -> 7100000 | K71: =K69*K70 -> 5180000
J73: 小計 | K73: 数量確定システム（千葉・徳山） | L73: =SUM(L35,L49,L63) -> 20.7 | M73: =SUM(M35,M49,M63) -> 22220000
K74: 用役管理システム（千葉・徳山） | L74: =SUM(L36,L50,L64) -> 13.6 | M74: =SUM(M36,M50,M64) -> 14640000
K75: 千葉化学品質管理システム | L75: =SUM(L37,L51,L65) -> 14.8 | M75: =SUM(M37,M51,M65) -> 15880000
K76: 包装管理システム | L76: =SUM(L38,L52,L66) -> 8.3 | M76: =SUM(M38,M52,M66) -> 9060000
K77: 工場DBシステム | L77: =SUM(L39,L53,L67) -> 0.9 | M77: =SUM(M39,M53,M67) -> 1100000
K78: ヤード操業 | L78: =SUM(L40,L54,L68) -> 5.7 | M78: =SUM(M40,M54,M68) -> 6060000
C81: 検証用
C82: 要件定義+設計
C83: パターン | D83: クラウドアーキ基盤に移行 | R83: 備考
D84: アプリ | N84: DB | P84: 全体
B85: No. | C85: システム | D85: 調査・要件定義 | E85: 設計 | F85: 製造 | G85: 結合テスト | H85: システムテスト | I85: ユーザテスト | J85: 本番稼働 | K85: 管理 | L85: 工数計 | M85: 金額 | N85: 工数計 | O85: 金額 | P85: 工数計 | Q85: 金額
B86: 1 | C86: 数量確定システム（千葉・徳山） | D86: 3.2 | E86: 1.6 | K86: 1.2 | L86: =SUM(D86:K86) -> 6 | M86: =SUM(D86:J86)*1000000+K86*1400000 -> 6480000 | N86: 0 | O86: 0 | P86: =SUM(L86:L90)+N86 -> 15.6 | Q86: =SUM(M86:M90)+O86 -> 17000000
B87: 2 | C87: 用役管理システム（千葉・徳山） | D87: 1.4 | E87: 1.1 | K87: 0.8 | L87: =SUM(D87:K87) -> 3.3 | M87: =SUM(D87:J87)*1000000+K87*1400000 -> 3620000
B88: 3 | C88: 千葉化学品質管理システム | D88: 1.7 | E88: 1.4 | K88: 0.8 | L88: =SUM(D88:K88) -> 3.9 | M88: =SUM(D88:J88)*1000000+K88*1400000 -> 4220000
B89: 4 | C89: ＬＭＰＰ包装システム | D89: 1.3 | E89: 0.4 | K89: 0.7 | L89: =SUM(D89:K89) -> 2.4 | M89: =SUM(D89:J89)*1000000+K89*1400000 -> 2680000
B90: 5 | C90: 工場DB | L90: =SUM(D90:K90) -> 0 | M90: =SUM(D90:J90)*1000000+K90*1400000 -> 0
B91: 6 | C91: ヤ－ド操業システム（千葉・徳山） | D91: 0.5 | E91: 0.4 | K91: 0.3 | L91: =SUM(D91:K91) -> 1.2 | M91: =SUM(D91:J91)*1000000+K91*1400000 -> 1320000 | P91: =SUM(L91:L91)+N91 -> 1.2 | Q91: =SUM(M91:M91)+O86 -> 1320000
B92: 計 | D92: =SUM(D86:D91) -> 8.1 | E92: =SUM(E86:E91) -> 4.9 | F92: =SUM(F86:F91) -> 0 | G92: =SUM(G86:G91) -> 0 | H92: =SUM(H86:H91) -> 0 | I92: =SUM(I86:I91) -> 0 | J92: =SUM(J86:J91) -> 0 | K92: =SUM(K86:K91) -> 3.8 | L92: =SUM(D92:K92) -> 16.8 | M92: =SUM(M86:M91) -> 18320000 | N92: =SUM(N86:N91) -> 0 | O92: =SUM(O86:O91) -> 0 | P92: =SUM(P86:P91) -> 16.8 | Q92: =SUM(Q86:Q91) -> 18320000
B93: 単価 | D93: 1000000 | E93: 1000000 | F93: 1000000 | G93: 1000000 | H93: 1000000 | I93: 1000000 | J93: 1000000 | K93: 1400000
B94: 金額 | D94: =D92*D93 -> 8100000 | E94: =E92*E93 -> 4900000 | F94: =F92*F93 -> 0 | G94: =G92*G93 -> 0 | H94: =H92*H93 -> 0 | I94: =I92*I93 -> 0 | J94: =J92*J93 -> 0 | K94: =K92*K93 -> 5320000
C95: 当初要件見積もり差分 計 | D95: =D92-D117 -> 0 | E95: =E92-E117 -> 4.9 | F95: =F92-F117 -> 0 | G95: =G92-G117 -> 0 | H95: =H92-H117 -> 0 | I95: =I92-I117 -> 0 | J95: =J92-J117 -> 0 | K95: =K92-K117 -> 1 | ... M95: =M92-M117 -> 6300000
C96: 当初要件見積もり差分 単価 | D96: =D93-D118 -> 0 | E96: =E93-E118 -> 0 | F96: =F93-F118 -> 0 | G96: =G93-G118 -> 0 | H96: =H93-H118 -> 0 | I96: =I93-I118 -> 0 | J96: =J93-J118 -> 0 | K96: =K93-K118 -> 0 | ... M96: =M93-M118 -> 0
C97: 当初要件見積もり差分 金額 | D97: =D94-D119 -> 0 | E97: =E94-E119 -> 4900000 | F97: =F94-F119 -> 0 | G97: =G94-G119 -> 0 | H97: =H94-H119 -> 0 | I97: =I94-I119 -> 0 | J97: =J94-J119 -> 0 | K97: =K94-K119 -> 1400000 | ... M97: =M94-M119 -> 0
I99: 設計追加による差分 | L99: 工数 | M99: 金額
K100: 数量確定システム（千葉・徳山） | L100: =L86-L111 -> 1.9 | M100: =M86-M111 -> 2020000
K101: 用役管理システム（千葉・徳山） | L101: =L87-L112 -> 1.3 | M101: =M87-M112 -> 1380000
K102: 千葉化学品質管理システム | L102: =L88-L113 -> 1.6 | M102: =M88-M113 -> 1680000
K103: 包装管理システム | L103: =L89-L114 -> 0.6 | M103: =M89-M114 -> 680000
K104: 工場DBシステム | L104: =L90-L115 -> 0 | M104: =M90-M115 -> 0
K105: ヤード操業 | L105: =L91-L116 -> 0.5 | M105: =M91-M116 -> 540000
L106: =SUM(L100:L105) -> 5.9 | M106: =SUM(M100:M105) -> 6300000
C107: 調査・要件定義(クラウドアーキから開始)
C108: パターン | D108: クラウドアーキ基盤に移行 | R108: 備考
...

Sheet スケジュール案・要員計画（全体）
A2: システム | B2: 担当 | C2: 2024年 | O2: 2025年 | S2: 202６年
C3: 1月 | D3: 2月 | E3: 3月 | F3: 4月 | G3: 5月 | H3: 6月 | I3: 7月 | J3: 8月 | K3: 9月 | L3: 10月 | M3: 11月 | N3: 12月 | O3: 9月 | P3: 10月 | Q3: 11月 | R3: 12月 | S3: １月 | T3: ２月 | U3: ３月 | V3: ４月 | W3: ５月 | X3: ６月
A4: マイルストン | K4: ★縮小共通基盤構築 | P4: ★新共通基盤構築 | U4: ★館林DC廃止
A5: 数量確定システム（千葉・徳山）
A6: 用役管理システム（千葉・徳山）
A7: 千葉化学品質管理システム
A8: ＬＭＰＰ包装システム
A9: ヤード操業システム
A10: 工場DB
B12: 本番リリースタイミング
A13: 千葉化学品質管理システム | B13: 2026年2月上旬
A14: ＬＭＰＰ包装システム | B14: 2026年2月上旬
A15: 工場DB | B15: 2026年2月上旬
A16: ヤード操業システム（千葉・徳山） | B16: 2026年2月中旬
A17: 数量確定システム（千葉・徳山） | B17: 2026年2月下旬
A18: 用役管理システム（千葉・徳山） | B18: 2026年2月下旬
A20: 想定要員数
A21: 管理 | O21: 2 | P21: 2 | Q21: 2 | R21: 2 | S21: 2 | T21: 1.5
A22: 数量確定 | O22: 2 | P22: 2 | Q22: 3 | R22: 3.5 | S22: 2 | T22: 1
A23: 用役管理 | O23: 1 | P23: 2 | Q23: 3 | R23: 2.5 | S23: 2 | T23: 1
A24: 千葉化学 | O24: 1 | P24: 2 | Q24: 3 | R24: 3.5 | S24: 2 | T24: 0.5
A25: 包装 | O25: 1 | P25: 1 | Q25: 1 | R25: 1.5 | S25: 0.5 | T25: 0.5
A26: ヤード操業 | F26: 2 | G26: 2 | H26: 5 | I26: 5 | J26: 5 | K26: 5 | L26: 5 | M26: 5 | N26: 5 | O26: 1 | P26: 1 | Q26: 1 | R26: 1 | S26: 1 | T26: 0.5
A27: 合計 | C27: =SUM(C22:C26) -> 0 | D27: =SUM(D22:D26) -> 0 | E27: =SUM(E22:E26) -> 0 | F27: =SUM(F22:F26) -> 2 | G27: =SUM(G22:G26) -> 2 | H27: =SUM(H22:H26) -> 5 | I27: =SUM(I22:I26) -> 5 | J27: =SUM(J22:J26) -> 5 | ... N27: =SUM(N22:N26) -> 5 | O27: =SUM(O21:O26) -> 8 | P27: =SUM(P21:P26) -> 10 | Q27: =SUM(Q21:Q26) -> 13 | R27: =SUM(R21:R26) -> 14 | S27: =SUM(S21:S26) -> 9.5 | T27: =SUM(T21:T26) -> 5 | U27: =SUM(U21:U26) -> 0 | V27: =SUM(V21:V26) -> 0 | ... X27: =SUM(X21:X26) -> 0
A30: 要員
A31: 要員
A32: 管理（工場） | B32: 野村 | O32: 0.5 | P32: 0.5 | Q32: 0.5 | R32: 0.5 | S32: 0.5 | T32: 0.5 | U32: 0.25 | Y32: =SUM(O32:X32) -> 3.25 | Z32: 人月
A33: 管理（工場） | B33: 石井 | O33: 0.5 | P33: 0.5 | Q33: 0.5 | R33: 0.5 | S33: 0.5 | T33: 0.5 | U33: 0.5 | Y33: =SUM(O33:X33) -> 3.5 | Z33: 人月
A34: 管理（工場） | B34: グエン・タン・ドゥオック | O34: 0.5 | P34: 1 | Q34: 1 | R34: 1 | S34: 1 | T34: 1 | U34: 0.5 | Y34: =SUM(O34:X34) -> 6 | Z34: 人月
A35: 数量確定 | B35: 天川 | O35: 0.5 | P35: 0.5 | Q35: 0.5 | R35: 0.5 | S35: 0.5 | T35: 0.5 | U35: 0.5 | Y35: =SUM(O35:X35) -> 3.5 | Z35: 人月
A36: 数量確定 | B36: グエン・チュン・グエン | O36: 0.25 | P36: 0.5 | Q36: 0.5 | R36: 0.5 | S36: 0.5 | T36: 0.5 | U36: 0.25 | Y36: =SUM(O36:X36) -> 3 | Z36: 人月
A37: 数量確定 | B37: ドー・ﾘｲ・アイン・トゥ | O37: 0.5 | P37: 1 | Q37: 1 | R37: 1 | Y37: =SUM(O37:X37) -> 3.5 | Z37: 人月
A38: 数量確定 | B38: レ・ファム・バオ・ロック | O38: 0.5 | P38: 1 | Q38: 1 | R38: 1 | Y38: =SUM(O38:X38) -> 3.5 | Z38: 人月
A39: 数量確定 | B39: VT1 | Q39: 1 | R39: 1 | Y39: =SUM(O39:X39) -> 2 | Z39: 人月
A40: 数量確定 | B40: VT5 | R40: 0.5 | Y40: =SUM(O40:X40) -> 0.5 | Z40: 人月
A41: 用役管理 | B41: 天川 | O41: 0.5 | P41: 0.5 | Q41: 0.5 | R41: 0.5 | S41: 0.5 | T41: 0.5 | U41: 0.5 | Y41: =SUM(O41:X41) -> 3.5 | Z41: 人月
A42: 用役管理 | B42: グエン・チュン・グエン | O42: 0.25 | P42: 0.5 | Q42: 0.5 | R42: 0.5 | S42: 0.5 | T42: 0.5 | U42: 0.25 | Y42: =SUM(O42:X42) -> 3 | Z42: 人月
A43: 用役管理 | B43: ドー・グエン・ティ・トゥイ・ズイ | P43: 1 | Q43: 1 | R43: 1 | Y43: =SUM(O43:X43) -> 3 | Z43: 人月
A44: 用役管理 | B44: VT2 | Q44: 1 | R44: 1 | Y44: =SUM(O44:X44) -> 2 | Z44: 人月
A45: 用役管理 | B45: VT5 | R45: 0.5 | Y45: =SUM(O45:X45) -> 0.5 | Z45: 人月
A46: 千葉化学 | B46: 馬場 | O46: 0.5 | P46: 0.5 | Q46: 0.5 | R46: 0.5 | S46: 0.5 | T46: 0.5 | Y46: =SUM(O46:X46) -> 3 | Z46: 人月
A47: 千葉化学 | B47: ズオン・ゴック・フー | O47: 0.25 | P47: 0.5 | Q47: 0.5 | R47: 0.5 | S47: 0.5 | T47: 0.5 | Y47: =SUM(O47:X47) -> 2.75 | Z47: 人月
A48: 千葉化学 | B48: グエン・ダン・ティエン | P48: 1 | Q48: 1 | R48: 1 | Y48: =SUM(O48:X48) -> 3 | Z48: 人月
A49: 千葉化学 | B49: ファン・グエン・タム | P49: 1 | Q49: 1 | R49: 1 | Y49: =SUM(O49:X49) -> 3 | Z49: 人月
A50: 千葉化学 | B50: VT3 | Q50: 1 | R50: 1 | Y50: =SUM(O50:X50) -> 2 | Z50: 人月
A51: 千葉化学 | B51: VT6 | R51: 0.5 | Y51: =SUM(O51:X51) -> 0.5 | Z51: 人月
A52: 包装 | B52: 馬場 | O52: 0.5 | P52: 0.5 | Q52: 0.5 | R52: 0.5 | S52: 0.5 | T52: 0.5 | Y52: =SUM(O52:X52) -> 3 | Z52: 人月
A53: 包装 | B53: ズオン・ゴック・フー | O53: 0.25 | P53: 0.5 | Q53: 0.5 | R53: 0.5 | S53: 0.5 | T53: 0.5 | Y53: =SUM(O53:X53) -> 2.75 | Z53: 人月
A54: 包装 | B54: VT4 | Q54: 1 | R54: 1 | Y54: =SUM(O54:X54) -> 2 | Z54: 人月
A55: 包装 | B55: VT6 | R55: 0.5 | Y55: =SUM(O55:X55) -> 0.5 | Z55: 人月
A56: ヤード操業 | B56: チャン・クォック・ズイ | F56: 2 | G56: 2 | H56: 5 | I56: 5 | J56: 5 | K56: 5 | L56: 5 | M56: 5 | N56: 5 | O56: 0.5 | P56: 1 | Q56: 1 | R56: 1 | S56: 1 | T56: 1 | Y56: =SUM(O56:X56) -> 5.5 | Z56: 人月
A57: 小計 | C57: =SUM(C36:C56) -> 0 | D57: =SUM(D36:D56) -> 0 | E57: =SUM(E36:E56) -> 0 | F57: =SUM(F36:F56) -> 2 | G57: =SUM(G36:G56) -> 2 | H57: =SUM(H36:H56) -> 5 | I57: =SUM(I36:I56) -> 5 | J57: =SUM(J36:J56) -> 5 | ... N57: =SUM(N36:N56) -> 5 | O57: =SUM(O32:O56) -> 6 | P57: =SUM(P32:P56) -> 12 | Q57: =SUM(Q32:Q56) -> 16 | R57: =SUM(R32:R56) -> 18 | S57: =SUM(S32:S56) -> 7 | T57: =SUM(T32:T56) -> 7 | U57: =SUM(U32:U56) -> 2.75 | V57: =SUM(V32:V56) -> 0 | ... X57: =SUM(X32:X56) -> 0
A58: コミュニケータ | B58: グエン・ミン・トー | F58: 2 | G58: 2 | H58: 5 | I58: 5 | J58: 5 | K58: 5 | L58: 5 | M58: 5 | N58: 5 | O58: 0.5 | P58: 1 | Q58: 1 | R58: 1 | S58: 0.5 | T58: 0.5 | Y58: =SUM(O58:X58) -> 4.5 | Z58: 人月
A59: ブリッジ | B59: チュン | F59: 2 | G59: 2 | H59: 5 | I59: 5 | J59: 5 | K59: 5 | L59: 5 | M59: 5 | N59: 5 | O59: 0.25 | P59: 0.5 | Q59: 0.5 | R59: 0.5 | Y59: =SUM(O59:X59) -> 1.75 | Z59: 人月
A60: ブリッジ | B60: チャンホアンフック | F60: 2 | G60: 2 | H60: 5 | I60: 5 | J60: 5 | K60: 5 | L60: 5 | M60: 5 | N60: 5 | Y60: =SUM(O60:X60) -> 0 | Z60: 人月
A61: ブリッジ | B61: ブイクアンティエン | F61: 2 | G61: 2 | H61: 5 | I61: 5 | J61: 5 | K61: 5 | L61: 5 | M61: 5 | N61: 5 | O61: 0.25 | P61: 0.5 | Q61: 0.5 | R61: 0.5 | S61: 0.5 | T61: 0.5 | Y61: =SUM(O61:X61) -> 2.75 | Z61: 人月
A62: 管理（工場） | B62: 黒田智之 | Q62: 0.5 | R62: 0.5 | S62: 0.5 | T62: 0.5 | U62: 0.5 | Y62: =SUM(O62:X62) -> 2.5 | Z62: 人月
A63: 数量確定 | B63: 吉田 | Q63: 0.5 | R63: 0.5 | S63: 0.5 | T63: 0.5 | U63: 0.5 | Y63: =SUM(O63:X63) -> 2.5 | Z63: 人月
A64: 用役管理 | B64: 吉田 | Q64: 0.5 | R64: 0.5 | S64: 0.5 | T64: 0.5 | U64: 0.5 | Y64: =SUM(O64:X64) -> 2.5 | Z64: 人月
A65: 千葉化学 | B65: 菊間 | Q65: 0.5 | R65: 0.5 | S65: 0.5 | T65: 0.5 | Y65: =SUM(O65:X65) -> 2 | Z65: 人月
A66: 包装 | B66: 菊間 | Q66: 0.5 | R66: 0.5 | S66: 0.5 | T66: 0.5 | Y66: =SUM(O66:X66) -> 2 | Z66: 人月
A67: 合計 | C67: =SUM(C42:C61) -> 0 | D67: =SUM(D42:D61) -> 0 | E67: =SUM(E42:E61) -> 0 | F67: =SUM(F42:F61) -> 12 | G67: =SUM(G42:G61) -> 12 | H67: =SUM(H42:H61) -> 30 | I67: =SUM(I42:I61) -> 30 | J67: =SUM(J42:J61) -> 30 | ... N67: =SUM(N42:N61) -> 30 | O67: =SUM(O57:O61) -> 7 | P67: =SUM(P57:P61) -> 14 | Q67: =SUM(Q57:Q61) -> 18 | R67: =SUM(R57:R61) -> 20 | S67: =SUM(S57:S61) -> 8 | T67: =SUM(T57:T61) -> 8 | U67: =SUM(U57:U61) -> 2.75 | V67: =SUM(V57:V61) -> 0 | ... X67: =SUM(X57:X61) -> 0
A69: 売上
A70: 野村 | B70: 1000000 | O70: =SUMIF($B$27:$B$56,$A70,O$27:O$56)*$B70 -> 500000 | P70: =SUMIF($B$27:$B$56,$A70,P$27:P$56)*$B70 -> 500000 | Q70: =SUMIF($B$27:$B$56,$A70,Q$27:Q$56)*$B70 -> 500000 | R70: =SUMIF($B$27:$B$56,$A70,R$27:R$56)*$B70 -> 500000 | S70: =SUMIF($B$27:$B$56,$A70,S$27:S$56)*$B70 -> 500000 | T70: =SUMIF($B$27:$B$56,$A70,T$27:T$56)*$B70 -> 500000 | U70: =SUMIF($B$27:$B$56,$A70,U$27:U$56)*$B70 -> 250000
A71: 石井 | B71: 1000000 | O71: =SUMIF($B$27:$B$56,$A71,O$27:O$56)*$B71 -> 500000 | P71: =SUMIF($B$27:$B$56,$A71,P$27:P$56)*$B71 -> 500000 | Q71: =SUMIF($B$27:$B$56,$A71,Q$27:Q$56)*$B71 -> 500000 | R71: =SUMIF($B$27:$B$56,$A71,R$27:R$56)*$B71 -> 500000 | S71: =SUMIF($B$27:$B$56,$A71,S$27:S$56)*$B71 -> 500000 | T71: =SUMIF($B$27:$B$56,$A71,T$27:T$56)*$B71 -> 500000 | U71: =SUMIF($B$27:$B$56,$A71,U$27:U$56)*$B71 -> 500000
A72: 天川 | B72: 1000000 | O72: =SUMIF($B$27:$B$56,$A72,O$27:O$56)*$B72 -> 1000000 | P72: =SUMIF($B$27:$B$56,$A72,P$27:P$56)*$B72 -> 1000000 | Q72: =SUMIF($B$27:$B$56,$A72,Q$27:Q$56)*$B72 -> 1000000 | R72: =SUMIF($B$27:$B$56,$A72,R$27:R$56)*$B72 -> 1000000 | S72: =SUMIF($B$27:$B$56,$A72,S$27:S$56)*$B72 -> 1000000 | T72: =SUMIF($B$27:$B$56,$A72,T$27:T$56)*$B72 -> 1000000 | U72: =SUMIF($B$27:$B$56,$A72,U$27:U$56)*$B72 -> 1000000
A73: 馬場 | B73: 1000000 | O73: =SUMIF($B$27:$B$56,$A73,O$27:O$56)*$B73 -> 1000000 | P73: =SUMIF($B$27:$B$56,$A73,P$27:P$56)*$B73 -> 1000000 | Q73: =SUMIF($B$27:$B$56,$A73,Q$27:Q$56)*$B73 -> 1000000 | R73: =SUMIF($B$27:$B$56,$A73,R$27:R$56)*$B73 -> 1000000 | S73: =SUMIF($B$27:$B$56,$A73,S$27:S$56)*$B73 -> 1000000 | T73: =SUMIF($B$27:$B$56,$A73,T$27:T$56)*$B73 -> 1000000 | U73: =SUMIF($B$27:$B$56,$A73,U$27:U$56)*$B73 -> 0
A74: グエン・タン・ドゥオック | B74: 700000 | O74: =SUMIF($B$27:$B$56,$A74,O$27:O$56)*$B74 -> 350000 | P74: =SUMIF($B$27:$B$56,$A74,P$27:P$56)*$B74 -> 700000 | Q74: =SUMIF($B$27:$B$56,$A74,Q$27:Q$56)*$B74 -> 700000 | R74: =SUMIF($B$27:$B$56,$A74,R$27:R$56)*$B74 -> 700000 | S74: =SUMIF($B$27:$B$56,$A74,S$27:S$56)*$B74 -> 700000 | T74: =SUMIF($B$27:$B$56,$A74,T$27:T$56)*$B74 -> 700000 | U74: =SUMIF($B$27:$B$56,$A74,U$27:U$56)*$B74 -> 350000
A75: グエン・チュン・グエン | B75: 700000 | O75: =SUMIF($B$27:$B$56,$A75,O$27:O$56)*$B75 -> 350000 | P75: =SUMIF($B$27:$B$56,$A75,P$27:P$56)*$B75 -> 700000 | Q75: =SUMIF($B$27:$B$56,$A75,Q$27:Q$56)*$B75 -> 700000 | R75: =SUMIF($B$27:$B$56,$A75,R$27:R$56)*$B75 -> 700000 | S75: =SUMIF($B$27:$B$56,$A75,S$27:S$56)*$B75 -> 700000 | T75: =SUMIF($B$27:$B$56,$A75,T$27:T$56)*$B75 -> 700000 | U75: =SUMIF($B$27:$B$56,$A75,U$27:U$56)*$B75 -> 350000
A76: ドー・ﾘｲ・アイン・トゥ | B76: 700000 | O76: =SUMIF($B$27:$B$56,$A76,O$27:O$56)*$B76 -> 350000 | P76: =SUMIF($B$27:$B$56,$A76,P$27:P$56)*$B76 -> 700000 | Q76: =SUMIF($B$27:$B$56,$A76,Q$27:Q$56)*$B76 -> 700000 | R76: =SUMIF($B$27:$B$56,$A76,R$27:R$56)*$B76 -> 700000 | S76: =SUMIF($B$27:$B$56,$A76,S$27:S$56)*$B76 -> 0 | T76: =SUMIF($B$27:$B$56,$A76,T$27:T$56)*$B76 -> 0 | U76: =SUMIF($B$27:$B$56,$A76,U$27:U$56)*$B76 -> 0
A77: レ・ファム・バオ・ロック | B77: 700000 | O77: =SUMIF($B$27:$B$56,$A77,O$27:O$56)*$B77 -> 350000 | P77: =SUMIF($B$27:$B$56,$A77,P$27:P$56)*$B77 -> 700000 | Q77: =SUMIF($B$27:$B$56,$A77,Q$27:Q$56)*$B77 -> 700000 | R77: =SUMIF($B$27:$B$56,$A77,R$27:R$56)*$B77 -> 700000 | S77: =SUMIF($B$27:$B$56,$A77,S$27:S$56)*$B77 -> 0 | T77: =SUMIF($B$27:$B$56,$A77,T$27:T$56)*$B77 -> 0 | U77: =SUMIF($B$27:$B$56,$A77,U$27:U$56)*$B77 -> 0
A78: ズオン・ゴック・フー | B78: 700000 | O78: =SUMIF($B$27:$B$56,$A78,O$27:O$56)*$B78 -> 350000 | P78: =SUMIF($B$27:$B$56,$A78,P$27:P$56)*$B78 -> 700000 | Q78: =SUMIF($B$27:$B$56,$A78,Q$27:Q$56)*$B78 -> 700000 | R78: =SUMIF($B$27:$B$56,$A78,R$27:R$56)*$B78 -> 700000 | S78: =SUMIF($B$27:$B$56,$A78,S$27:S$56)*$B78 -> 700000 | T78: =SUMIF($B$27:$B$56,$A78,T$27:T$56)*$B78 -> 700000 | U78: =SUMIF($B$27:$B$56,$A78,U$27:U$56)*$B78 -> 0
A79: チャン・クォック・ズイ | B79: 700000 | O79: =SUMIF($B$27:$B$56,$A79,O$27:O$56)*$B79 -> 350000 | P79: =SUMIF($B$27:$B$56,$A79,P$27:P$56)*$B79 -> 700000 | Q79: =SUMIF($B$27:$B$56,$A79,Q$27:Q$56)*$B79 -> 700000 | R79: =SUMIF($B$27:$B$56,$A79,R$27:R$56)*$B79 -> 700000 | S79: =SUMIF($B$27:$B$56,$A79,S$27:S$56)*$B79 -> 700000 | T79: =SUMIF($B$27:$B$56,$A79,T$27:T$56)*$B79 -> 700000 | U79: =SUMIF($B$27:$B$56,$A79,U$27:U$56)*$B79 -> 0
A80: ドー・グエン・ティ・トゥイ・ズイ | B80: 700000 | O80: =SUMIF($B$27:$B$56,$A80,O$27:O$56)*$B80 -> 0 | P80: =SUMIF($B$27:$B$56,$A80,P$27:P$56)*$B80 -> 700000 | Q80: =SUMIF($B$27:$B$56,$A80,Q$27:Q$56)*$B80 -> 700000 | R80: =SUMIF($B$27:$B$56,$A80,R$27:R$56)*$B80 -> 700000 | S80: =SUMIF($B$27:$B$56,$A80,S$27:S$56)*$B80 -> 0 | T80: =SUMIF($B$27:$B$56,$A80,T$27:T$56)*$B80 -> 0 | U80: =SUMIF($B$27:$B$56,$A80,U$27:U$56)*$B80 -> 0
A81: グエン・ダン・ティエン | B81: 700000 | O81: =SUMIF($B$27:$B$56,$A81,O$27:O$56)*$B81 -> 0 | P81: =SUMIF($B$27:$B$56,$A81,P$27:P$56)*$B81 -> 700000 | Q81: =SUMIF($B$27:$B$56,$A81,Q$27:Q$56)*$B81 -> 700000 | R81: =SUMIF($B$27:$B$56,$A81,R$27:R$56)*$B81 -> 700000 | S81: =SUMIF($B$27:$B$56,$A81,S$27:S$56)*$B81 -> 0 | T81: =SUMIF($B$27:$B$56,$A81,T$27:T$56)*$B81 -> 0 | U81: =SUMIF($B$27:$B$56,$A81,U$27:U$56)*$B81 -> 0
A82: ファン・グエン・タム | B82: 700000 | O82: =SUMIF($B$27:$B$56,$A82,O$27:O$56)*$B82 -> 0 | P82: =SUMIF($B$27:$B$56,$A82,P$27:P$56)*$B82 -> 700000 | Q82: =SUMIF($B$27:$B$56,$A82,Q$27:Q$56)*$B82 -> 700000 | R82: =SUMIF($B$27:$B$56,$A82,R$27:R$56)*$B82 -> 700000 | S82: =SUMIF($B$27:$B$56,$A82,S$27:S$56)*$B82 -> 0 | T82: =SUMIF($B$27:$B$56,$A82,T$27:T$56)*$B82 -> 0 | U82: =SUMIF($B$27:$B$56,$A82,U$27:U$56)*$B82 -> 0
A83: グエン・ミン・トー | B83: 700000 | F83: 2 | G83: 2 | H83: 5 | I83: 5 | J83: 5 | K83: 5 | L83: 5 | M83: 5 | N83: 5 | O83: =SUMIF($B$27:$B$56,$A83,O$27:O$56)*$B83 -> 0 | P83: =SUMIF($B$27:$B$56,$A83,P$27:P$56)*$B83 -> 0 | Q83: =SUMIF($B$27:$B$56,$A83,Q$27:Q$56)*$B83 -> 0 | R83: =SUMIF($B$27:$B$56,$A83,R$27:R$56)*$B83 -> 0 | S83: =SUMIF($B$27:$B$56,$A83,S$27:S$56)*$B83 -> 0 | T83: =SUMIF($B$27:$B$56,$A83,T$27:T$56)*$B83 -> 0 | U83: =SUMIF($B$27:$B$56,$A83,U$27:U$56)*$B83 -> 0
A84: チュン | B84: 1000000 | F84: 2 | G84: 2 | H84: 5 | I84: 5 | J84: 5 | K84: 5 | L84: 5 | M84: 5 | N84: 5 | O84: =SUMIF($B$27:$B$56,$A84,O$27:O$56)*$B84 -> 0 | P84: =SUMIF($B$27:$B$56,$A84,P$27:P$56)*$B84 -> 0 | Q84: =SUMIF($B$27:$B$56,$A84,Q$27:Q$56)*$B84 -> 0 | R84: =SUMIF($B$27:$B$56,$A84,R$27:R$56)*$B84 -> 0 | S84: =SUMIF($B$27:$B$56,$A84,S$27:S$56)*$B84 -> 0 | T84: =SUMIF($B$27:$B$56,$A84,T$27:T$56)*$B84 -> 0 | U84: =SUMIF($B$27:$B$56,$A84,U$27:U$56)*$B84 -> 0
A85: チャンホアンフック | B85: 800000 | F85: 2 | G85: 2 | H85: 5 | I85: 5 | J85: 5 | K85: 5 | L85: 5 | M85: 5 | N85: 5 | O85: =SUMIF($B$27:$B$56,$A85,O$27:O$56)*$B85 -> 0 | P85: =SUMIF($B$27:$B$56,$A85,P$27:P$56)*$B85 -> 0 | Q85: =SUMIF($B$27:$B$56,$A85,Q$27:Q$56)*$B85 -> 0 | R85: =SUMIF($B$27:$B$56,$A85,R$27:R$56)*$B85 -> 0 | S85: =SUMIF($B$27:$B$56,$A85,S$27:S$56)*$B85 -> 0 | T85: =SUMIF($B$27:$B$56,$A85,T$27:T$56)*$B85 -> 0 | U85: =SUMIF($B$27:$B$56,$A85,U$27:U$56)*$B85 -> 0
A86: ブイクアンティエン | B86: 1000000 | F86: 2 | G86: 2 | H86: 5 | I86: 5 | J86: 5 | K86: 5 | L86: 5 | M86: 5 | N86: 5 | O86: =SUMIF($B$27:$B$56,$A86,O$27:O$56)*$B86 -> 0 | P86: =SUMIF($B$27:$B$56,$A86,P$27:P$56)*$B86 -> 0 | Q86: =SUMIF($B$27:$B$56,$A86,Q$27:Q$56)*$B86 -> 0 | R86: =SUMIF($B$27:$B$56,$A86,R$27:R$56)*$B86 -> 0 | S86: =SUMIF($B$27:$B$56,$A86,S$27:S$56)*$B86 -> 0 | T86: =SUMIF($B$27:$B$56,$A86,T$27:T$56)*$B86 -> 0 | U86: =SUMIF($B$27:$B$56,$A86,U$27:U$56)*$B86 -> 0
A87: VT1 | B87: 700000 | F87: 2 | G87: 2 | H87: 5 | I87: 5 | J87: 5 | K87: 5 | L87: 5 | M87: 5 | N87: 5 | O87: =SUMIF($B$27:$B$56,$A87,O$27:O$56)*$B87 -> 0 | P87: =SUMIF($B$27:$B$56,$A87,P$27:P$56)*$B87 -> 0 | Q87: =SUMIF($B$27:$B$56,$A87,Q$27:Q$56)*$B87 -> 700000 | R87: =SUMIF($B$27:$B$56,$A87,R$27:R$56)*$B87 -> 700000 | S87: =SUMIF($B$27:$B$56,$A87,S$27:S$56)*$B87 -> 0 | T87: =SUMIF($B$27:$B$56,$A87,T$27:T$56)*$B87 -> 0 | U87: =SUMIF($B$27:$B$56,$A87,U$27:U$56)*$B87 -> 0
A88: VT2 | B88: 700000 | F88: 2 | G88: 2 | H88: 5 | I88: 5 | J88: 5 | K88: 5 | L88: 5 | M88: 5 | N88: 5 | O88: =SUMIF($B$27:$B$56,$A88,O$27:O$56)*$B88 -> 0 | P88: =SUMIF($B$27:$B$56,$A88,P$27:P$56)*$B88 -> 0 | Q88: =SUMIF($B$27:$B$56,$A88,Q$27:Q$56)*$B88 -> 700000 | R88: =SUMIF($B$27:$B$56,$A88,R$27:R$56)*$B88 -> 700000 | S88: =SUMIF($B$27:$B$56,$A88,S$27:S$56)*$B88 -> 0 | T88: =SUMIF($B$27:$B$56,$A88,T$27:T$56)*$B88 -> 0 | U88: =SUMIF($B$27:$B$56,$A88,U$27:U$56)*$B88 -> 0
A89: VT3 | B89: 700000 | F89: 2 | G89: 2 | H89: 5 | I89: 5 | J89: 5 | K89: 5 | L89: 5 | M89: 5 | N89: 5 | O89: =SUMIF($B$27:$B$56,$A89,O$27:O$56)*$B89 -> 0 | P89: =SUMIF($B$27:$B$56,$A89,P$27:P$56)*$B89 -> 0 | Q89: =SUMIF($B$27:$B$56,$A89,Q$27:Q$56)*$B89 -> 700000 | R89: =SUMIF($B$27:$B$56,$A89,R$27:R$56)*$B89 -> 700000 | S89: =SUMIF($B$27:$B$56,$A89,S$27:S$56)*$B89 -> 0 | T89: =SUMIF($B$27:$B$56,$A89,T$27:T$56)*$B89 -> 0 | U89: =SUMIF($B$27:$B$56,$A89,U$27:U$56)*$B89 -> 0
A90: VT4 | B90: 700000 | F90: 2 | G90: 2 | H90: 5 | I90: 5 | J90: 5 | K90: 5 | L90: 5 | M90: 5 | N90: 5 | O90: =SUMIF($B$27:$B$56,$A90,O$27:O$56)*$B90 -> 0 | P90: =SUMIF($B$27:$B$56,$A90,P$27:P$56)*$B90 -> 0 | Q90: =SUMIF($B$27:$B$56,$A90,Q$27:Q$56)*$B90 -> 700000 | R90: =SUMIF($B$27:$B$56,$A90,R$27:R$56)*$B90 -> 700000 | S90: =SUMIF($B$27:$B$56,$A90,S$27:S$56)*$B90 -> 0 | T90: =SUMIF($B$27:$B$56,$A90,T$27:T$56)*$B90 -> 0 | U90: =SUMIF($B$27:$B$56,$A90,U$27:U$56)*$B90 -> 0
A91: VT5 | B91: 700000 | F91: 2 | G91: 2 | H91: 5 | I91: 5 | J91: 5 | K91: 5 | L91: 5 | M91: 5 | N91: 5 | O91: =SUMIF($B$27:$B$56,$A91,O$27:O$56)*$B91 -> 0 | P91: =SUMIF($B$27:$B$56,$A91,P$27:P$56)*$B91 -> 0 | Q91: =SUMIF($B$27:$B$56,$A91,Q$27:Q$56)*$B91 -> 0 | R91: =SUMIF($B$27:$B$56,$A91,R$27:R$56)*$B91 -> 700000 | S91: =SUMIF($B$27:$B$56,$A91,S$27:S$56)*$B91 -> 0 | T91: =SUMIF($B$27:$B$56,$A91,T$27:T$56)*$B91 -> 0 | U91: =SUMIF($B$27:$B$56,$A91,U$27:U$56)*$B91 -> 0
A92: VT6 | B92: 700000 | F92: 2 | G92: 2 | H92: 5 | I92: 5 | J92: 5 | K92: 5 | L92: 5 | M92: 5 | N92: 5 | O92: =SUMIF($B$27:$B$56,$A92,O$27:O$56)*$B92 -> 0 | P92: =SUMIF($B$27:$B$56,$A92,P$27:P$56)*$B92 -> 0 | Q92: =SUMIF($B$27:$B$56,$A92,Q$27:Q$56)*$B92 -> 0 | R92: =SUMIF($B$27:$B$56,$A92,R$27:R$56)*$B92 -> 700000 | S92: =SUMIF($B$27:$B$56,$A92,S$27:S$56)*$B92 -> 0 | T92: =SUMIF($B$27:$B$56,$A92,T$27:T$56)*$B92 -> 0 | U92: =SUMIF($B$27:$B$56,$A92,U$27:U$56)*$B92 -> 0
A93: 黒田智之 | B93: 1000000 | F93: 2 | G93: 2 | H93: 5 | I93: 5 | J93: 5 | K93: 5 | L93: 5 | M93: 5 | N93: 5 | O93: =SUMIF($B$27:$B$56,$A93,O$27:O$56)*$B93 -> 0 | P93: =SUMIF($B$27:$B$56,$A93,P$27:P$56)*$B93 -> 0 | Q93: =SUMIF($B$27:$B$56,$A93,Q$27:Q$56)*$B93 -> 0 | R93: =SUMIF($B$27:$B$56,$A93,R$27:R$56)*$B93 -> 0 | S93: =SUMIF($B$27:$B$56,$A93,S$27:S$56)*$B93 -> 0 | T93: =SUMIF($B$27:$B$56,$A93,T$27:T$56)*$B93 -> 0 | U93: =SUMIF($B$27:$B$56,$A93,U$27:U$56)*$B93 -> 0
A94: 吉田 | B94: 1000000 | F94: 2 | G94: 2 | H94: 5 | I94: 5 | J94: 5 | K94: 5 | L94: 5 | M94: 5 | N94: 5 | O94: =SUMIF($B$27:$B$56,$A94,O$27:O$56)*$B94 -> 0 | P94: =SUMIF($B$27:$B$56,$A94,P$27:P$56)*$B94 -> 0 | Q94: =SUMIF($B$27:$B$56,$A94,Q$27:Q$56)*$B94 -> 0 | R94: =SUMIF($B$27:$B$56,$A94,R$27:R$56)*$B94 -> 0 | S94: =SUMIF($B$27:$B$56,$A94,S$27:S$56)*$B94 -> 0 | T94: =SUMIF($B$27:$B$56,$A94,T$27:T$56)*$B94 -> 0 | U94: =SUMIF($B$27:$B$56,$A94,U$27:U$56)*$B94 -> 0
A95: 菊間 | B95: 1000000 | F95: 2 | G95: 2 | H95: 5 | I95: 5 | J95: 5 | K95: 5 | L95: 5 | M95: 5 | N95: 5 | O95: =SUMIF($B$27:$B$56,$A95,O$27:O$56)*$B95 -> 0 | P95: =SUMIF($B$27:$B$56,$A95,P$27:P$56)*$B95 -> 0 | Q95: =SUMIF($B$27:$B$56,$A95,Q$27:Q$56)*$B95 -> 0 | R95: =SUMIF($B$27:$B$56,$A95,R$27:R$56)*$B95 -> 0 | S95: =SUMIF($B$27:$B$56,$A95,S$27:S$56)*$B95 -> 0 | T95: =SUMIF($B$27:$B$56,$A95,T$27:T$56)*$B95 -> 0 | U95: =SUMIF($B$27:$B$56,$A95,U$27:U$56)*$B95 -> 0
A96: 合計 | C96: =SUM(C75:C95) -> 0 | D96: =SUM(D75:D95) -> 0 | E96: =SUM(E75:E95) -> 0 | F96: =SUM(F75:F95) -> 26 | G96: =SUM(G75:G95) -> 26 | H96: =SUM(H75:H95) -> 65 | I96: =SUM(I75:I95) -> 65 | J96: =SUM(J75:J95) -> 65 | ... N96: =SUM(N75:N95) -> 65 | O96: =SUM(O70:O95) -> 5100000 | P96: =SUM(P70:P95) -> 9300000 | Q96: =SUM(Q70:Q95) -> 12100000 | R96: =SUM(R70:R95) -> 13500000 | S96: =SUM(S70:S95) -> 5800000 | T96: =SUM(T70:T95) -> 5800000 | U96: =SUM(U70:U95) -> 2450000 | V96: =SUM(V70:V95) -> 0 | ... X96: =SUM(X70:X95) -> 0 | Y96: =SUM(O96:X96) -> 54050000
A98: 粗利コスト
A99: 野村 | B99: 600000 | O99: =SUMIF($B$27:$B$56,$A99,O$27:O$56)*$B99 -> 300000 | P99: =SUMIF($B$27:$B$56,$A99,P$27:P$56)*$B99 -> 300000 | Q99: =SUMIF($B$27:$B$56,$A99,Q$27:Q$56)*$B99 -> 300000 | R99: =SUMIF($B$27:$B$56,$A99,R$27:R$56)*$B99 -> 300000 | S99: =SUMIF($B$27:$B$56,$A99,S$27:S$56)*$B99 -> 300000 | T99: =SUMIF($B$27:$B$56,$A99,T$27:T$56)*$B99 -> 300000 | U99: =SUMIF($B$27:$B$56,$A99,U$27:U$56)*$B99 -> 150000
A100: 石井 | B100: 600000 | O100: =SUMIF($B$27:$B$56,$A100,O$27:O$56)*$B100 -> 300000 | P100: =SUMIF($B$27:$B$56,$A100,P$27:P$56)*$B100 -> 300000 | Q100: =SUMIF($B$27:$B$56,$A100,Q$27:Q$56)*$B100 -> 300000 | R100: =SUMIF($B$27:$B$56,$A100,R$27:R$56)*$B100 -> 300000 | S100: =SUMIF($B$27:$B$56,$A100,S$27:S$56)*$B100 -> 300000 | T100: =SUMIF($B$27:$B$56,$A100,T$27:T$56)*$B100 -> 300000 | U100: =SUMIF($B$27:$B$56,$A100,U$27:U$56)*$B100 -> 300000
A101: 天川 | B101: 500000 | O101: =SUMIF($B$27:$B$56,$A101,O$27:O$56)*$B101 -> 500000 | P101: =SUMIF($B$27:$B$56,$A101,P$27:P$56)*$B101 -> 500000 | Q101: =SUMIF($B$27:$B$56,$A101,Q$27:Q$56)*$B101 -> 500000 | R101: =SUMIF($B$27:$B$56,$A101,R$27:R$56)*$B101 -> 500000 | S101: =SUMIF($B$27:$B$56,$A101,S$27:S$56)*$B101 -> 500000 | T101: =SUMIF($B$27:$B$56,$A101,T$27:T$56)*$B101 -> 500000 | U101: =SUMIF($B$27:$B$56,$A101,U$27:U$56)*$B101 -> 500000
A102: 馬場 | B102: 500000 | O102: =SUMIF($B$27:$B$56,$A102,O$27:O$56)*$B102 -> 500000 | P102: =SUMIF($B$27:$B$56,$A102,P$27:P$56)*$B102 -> 500000 | Q102: =SUMIF($B$27:$B$56,$A102,Q$27:Q$56)*$B102 -> 500000 | R102: =SUMIF($B$27:$B$56,$A102,R$27:R$56)*$B102 -> 500000 | S102: =SUMIF($B$27:$B$56,$A102,S$27:S$56)*$B102 -> 500000 | T102: =SUMIF($B$27:$B$56,$A102,T$27:T$56)*$B102 -> 500000 | U102: =SUMIF($B$27:$B$56,$A102,U$27:U$56)*$B102 -> 0
A103: グエン・タン・ドゥオック | B103: 450000 | O103: =SUMIF($B$27:$B$56,$A103,O$27:O$56)*$B103 -> 225000 | P103: =SUMIF($B$27:$B$56,$A103,P$27:P$56)*$B103 -> 450000 | Q103: =SUMIF($B$27:$B$56,$A103,Q$27:Q$56)*$B103 -> 450000 | R103: =SUMIF($B$27:$B$56,$A103,R$27:R$56)*$B103 -> 450000 | S103: =SUMIF($B$27:$B$56,$A103,S$27:S$56)*$B103 -> 450000 | T103: =SUMIF($B$27:$B$56,$A103,T$27:T$56)*$B103 -> 450000 | U103: =SUMIF($B$27:$B$56,$A103,U$27:U$56)*$B103 -> 225000
A104: グエン・チュン・グエン | B104: 350000 | O104: =SUMIF($B$27:$B$56,$A104,O$27:O$56)*$B104 -> 175000 | P104: =SUMIF($B$27:$B$56,$A104,P$27:P$56)*$B104 -> 350000 | Q104: =SUMIF($B$27:$B$56,$A104,Q$27:Q$56)*$B104 -> 350000 | R104: =SUMIF($B$27:$B$56,$A104,R$27:R$56)*$B104 -> 350000 | S104: =SUMIF($B$27:$B$56,$A104,S$27:S$56)*$B104 -> 350000 | T104: =SUMIF($B$27:$B$56,$A104,T$27:T$56)*$B104 -> 350000 | U104: =SUMIF($B$27:$B$56,$A104,U$27:U$56)*$B104 -> 175000
A105: ドー・ﾘｲ・アイン・トゥ | B105: 350000 | O105: =SUMIF($B$27:$B$56,$A105,O$27:O$56)*$B105 -> 175000 | P105: =SUMIF($B$27:$B$56,$A105,P$27:P$56)*$B105 -> 350000 | Q105: =SUMIF($B$27:$B$56,$A105,Q$27:Q$56)*$B105 -> 350000 | R105: =SUMIF($B$27:$B$56,$A105,R$27:R$56)*$B105 -> 350000 | S105: =SUMIF($B$27:$B$56,$A105,S$27:S$56)*$B105 -> 0 | T105: =SUMIF($B$27:$B$56,$A105,T$27:T$56)*$B105 -> 0 | U105: =SUMIF($B$27:$B$56,$A105,U$27:U$56)*$B105 -> 0
A106: レ・ファム・バオ・ロック | B106: 350000 | O106: =SUMIF($B$27:$B$56,$A106,O$27:O$56)*$B106 -> 175000 | P106: =SUMIF($B$27:$B$56,$A106,P$27:P$56)*$B106 -> 350000 | Q106: =SUMIF($B$27:$B$56,$A106,Q$27:Q$56)*$B106 -> 350000 | R106: =SUMIF($B$27:$B$56,$A106,R$27:R$56)*$B106 -> 350000 | S106: =SUMIF($B$27:$B$56,$A106,S$27:S$56)*$B106 -> 0 | T106: =SUMIF($B$27:$B$56,$A106,T$27:T$56)*$B106 -> 0 | U106: =SUMIF($B$27:$B$56,$A106,U$27:U$56)*$B106 -> 0
A107: ズオン・ゴック・フー | B107: 350000 | O107: =SUMIF($B$27:$B$56,$A107,O$27:O$56)*$B107 -> 175000 | P107: =SUMIF($B$27:$B$56,$A107,P$27:P$56)*$B107 -> 350000 | Q107: =SUMIF($B$27:$B$56,$A107,Q$27:Q$56)*$B107 -> 350000 | R107: =SUMIF($B$27:$B$56,$A107,R$27:R$56)*$B107 -> 350000 | S107: =SUMIF($B$27:$B$56,$A107,S$27:S$56)*$B107 -> 350000 | T107: =SUMIF($B$27:$B$56,$A107,T$27:T$56)*$B107 -> 350000 | U107: =SUMIF($B$27:$B$56,$A107,U$27:U$56)*$B107 -> 0
...

Sheet スケジュール案・要員計画 (開発フェーズ_工程別)
O1: 調査・要件定義 | P1: 設計 | Q1: 製造 | R1: 結合テスト | S1: システムテスト | T1: ユーザテスト | U1: 本番稼働
A3: システム | B3: 担当 | C3: 2024年 | O3: 2025年 | S3: 202６年
C4: 1月 | D4: 2月 | E4: 3月 | F4: 4月 | G4: 5月 | H4: 6月 | I4: 7月 | J4: 8月 | K4: 9月 | L4: 10月 | M4: 11月 | N4: 12月 | O4: 9月 | P4: 10月 | Q4: 11月 | R4: 12月 | S4: １月 | T4: ２月 | U4: ３月 | V4: ４月 | W4: ５月 | X4: ６月
A5: マイルストン | K5: ★縮小共通基盤構築 | P5: ★新共通基盤構築 | U5: ★館林DC廃止
A6: 数量確定システム（千葉・徳山）
A7: 用役管理システム（千葉・徳山）
A8: 千葉化学品質管理システム
A9: ＬＭＰＰ包装システム
A10: ヤード操業システム
A11: 工場DB
B13: 本番リリースタイミング
A14: 千葉化学品質管理システム | B14: 2026年2月上旬
A15: ＬＭＰＰ包装システム | B15: 2026年2月上旬
A16: 工場DB | B16: 2026年2月上旬
A17: ヤード操業システム（千葉・徳山） | B17: 2026年2月中旬
A18: 数量確定システム（千葉・徳山） | B18: 2026年2月下旬
A19: 用役管理システム（千葉・徳山） | B19: 2026年2月下旬
A21: 想定要員数(工程単位) | Z21: 管理のみ
A22: 管理 | Q22: =AB29 -> 2.6 | R22: =AC29 -> 3.4 | S22: =AD29 -> 1.5 | T22: =AE29 -> 1.1 | U22: =AF29 -> 1.9 | V22: =SUM(Q22:U22) -> 10.5 | Z22: 調査・要件定義 | AA22: 設計 | AB22: 製造 | AC22: 結合テスト | AD22: システムテスト | AE22: ユーザテスト | AF22: 本番稼働
A23: 数量確定システム（千葉・徳山） | Q23: 3.2 | R23: 5.2 | S23: 1.4 | T23: 0.8 | U23: 2 | V23: =SUM(Q23:U23) -> 12.6 | Y23: 数量確定システム（千葉・徳山） | Z23: 0 | AA23: 0 | AB23: 0.8 | AC23: 1 | AD23: 0.5 | AE23: 0.3 | AF23: 0.5
A24: 用役管理システム（千葉・徳山） | Q24: 2.1 | R24: 3.1 | S24: 1.1 | T24: 0.8 | U24: 2 | V24: =SUM(Q24:U24) -> 9.1 | Y24: 用役管理システム（千葉・徳山） | Z24: 0 | AA24: 0 | AB24: 0.5 | AC24: 0.7 | AD24: 0.3 | AE24: 0.3 | AF24: 0.4
A25: 千葉化学品質管理システム | Q25: 2.2 | R25: 5.5 | S25: 0.8 | T25: 0.5 | U25: 0.5 | V25: =SUM(Q25:U25) -> 9.5 | Y25: 千葉化学品質管理システム | Z25: 0 | AA25: 0 | AB25: 0.6 | AC25: 1 | AD25: 0.3 | AE25: 0.2 | AF25: 0.2
A26: ＬＭＰＰ包装システム | Q26: 2 | R26: 1.2 | S26: 0.8 | T26: 0.5 | U26: 0.5 | V26: =SUM(Q26:U26) -> 5 | Y26: ＬＭＰＰ包装システム | Z26: 0 | AA26: 0 | AB26: 0.6 | AC26: 0.4 | AD26: 0.3 | AE26: 0.2 | AF26: 0.2
A27: 工場DB | Q27: 0 | R27: 0 | S27: 0 | T27: 0.1 | U27: 0.3 | V27: =SUM(Q27:U27) -> 0.4 | Y27: 工場DB | Z27: 0 | AA27: 0 | AB27: 0 | AC27: 0 | AD27: 0 | AE27: 0 | AF27: 0.4
A28: ヤ－ド操業システム（千葉・徳山） | Q28: 1 | R28: 1.4 | S28: 0.2 | T28: 0.1 | U28: 1.3 | V28: =SUM(Q28:U28) -> 4 | Y28: ヤ－ド操業システム（千葉・徳山） | Z28: 0 | AA28: 0 | AB28: 0.1 | AC28: 0.3 | AD28: 0.1 | AE28: 0.1 | AF28: 0.2
A29: 合計 | C29: =SUM(C24:C28) -> 0 | D29: =SUM(D24:D28) -> 0 | E29: =SUM(E24:E28) -> 0 | F29: =SUM(F24:F28) -> 0 | G29: =SUM(G24:G28) -> 0 | H29: =SUM(H24:H28) -> 0 | I29: =SUM(I24:I28) -> 0 | J29: =SUM(J24:J28) -> 0 | ... N29: =SUM(N24:N28) -> 0 | O29: =SUM(O23:O28) -> 0 | P29: =SUM(P23:P28) -> 0 | Q29: =SUM(Q22:Q28) -> 13.1 | R29: =SUM(R22:R28) -> 19.8 | S29: =SUM(S22:S28) -> 5.8 | T29: =SUM(T22:T28) -> 3.9 | U29: =SUM(U22:U28) -> 8.5 | V29: =SUM(Q29:U29) -> 51.1 | Z29: =SUM(Z23:Z28) -> 0 | AA29: =SUM(AA23:AA28) -> 0 | AB29: =SUM(AB23:AB28) -> 2.6 | AC29: =SUM(AC23:AC28) -> 3.4 | AD29: =SUM(AD23:AD28) -> 1.5 | AE29: =SUM(AE23:AE28) -> 1.1 | AF29: =SUM(AF23:AF28) -> 1.9
A31: 要員
A32: 管理（工場） | B32: 野村 | Q32: 0.5 | R32: 0.5 | S32: 0.5 | T32: 0.5 | U32: 0.25 | V32: =SUM(Q32:U32) -> 2.25
A33: 管理（工場） | B33: 石井 | Q33: 0.5 | R33: 0.5 | S33: 0.5 | T33: 0.5 | U33: 0.5 | V33: =SUM(Q33:U33) -> 2.5
A34: 管理（工場） | B34: グエン・タン・ドゥオック | Q34: 1 | R34: 1 | S34: 1 | T34: 1 | U34: 0.5 | V34: =SUM(Q34:U34) -> 4.5
A35: 数量確定 | B35: 天川 | Q35: 0.5 | R35: 0.5 | S35: 0.5 | T35: 0.5 | U35: 0.5 | V35: =SUM(Q35:U35) -> 2.5
A36: 数量確定 | B36: グエン・チュン・グエン | Q36: 0.5 | R36: 0.5 | S36: 0.5 | T36: 0.5 | U36: 0.5 | V36: =SUM(Q36:U36) -> 2.5
A37: 数量確定 | B37: ドー・ﾘｲ・アイン・トゥ | Q37: 1 | R37: 1 | V37: =SUM(Q37:U37) -> 2
A38: 数量確定 | B38: レ・ファム・バオ・ロック | Q38: 1 | R38: 1 | V38: =SUM(Q38:U38) -> 2
A39: 数量確定 | B39: VT1 | Q39: 0.5 | R39: 0.5 | V39: =SUM(Q39:U39) -> 1
A40: 用役管理 | B40: 天川 | Q40: 0.5 | R40: 0.5 | S40: 0.5 | T40: 0.5 | U40: 0.5 | V40: =SUM(Q40:U40) -> 2.5
A41: 用役管理 | B41: グエン・チュン・グエン | Q41: 0.5 | R41: 0.5 | S41: 0.5 | T41: 0.5 | U41: 0.5 | V41: =SUM(Q41:U41) -> 2.5
A42: 用役管理 | B42: ドー・グエン・ティ・トゥイ・ズイ | Q42: 1 | R42: 1 | V42: =SUM(Q42:U42) -> 2
A43: 用役管理 | B43: VT1 | Q43: 0.5 | R43: 0.5 | V43: =SUM(Q43:U43) -> 1
A44: 千葉化学 | B44: 馬場 | Q44: 0.5 | R44: 0.5 | S44: 0.5 | T44: 0.5 | U44: 0.5 | V44: =SUM(Q44:U44) -> 2.5
A45: 千葉化学 | B45: ズオン・ゴック・フー | Q45: 0.5 | R45: 0.5 | S45: 0.5 | T45: 0.25 | U45: 0.25 | V45: =SUM(Q45:U45) -> 2
A46: 千葉化学 | B46: グエン・ダン・ティエン | Q46: 1 | R46: 1 | V46: =SUM(Q46:U46) -> 2
A47: 千葉化学 | B47: ファン・グエン・タム | Q47: 1 | R47: 1 | V47: =SUM(Q47:U47) -> 2
A48: 千葉化学 | B48: VT2 | Q48: 0.5 | R48: 0.5 | V48: =SUM(Q48:U48) -> 1
A49: 千葉化学 | B49: VT3 | R49: 1 | V49: =SUM(Q49:U49) -> 1
A50: 包装 | B50: 馬場 | Q50: 0.5 | R50: 0.5 | S50: 0.5 | T50: 0.5 | U50: 0.5 | V50: =SUM(Q50:U50) -> 2.5
A51: 包装 | B51: ズオン・ゴック・フー | Q51: 0.5 | R51: 0.5 | S51: 0.5 | T51: 0.25 | U51: 0.25 | V51: =SUM(Q51:U51) -> 2
A52: 包装 | B52: VT2 | Q52: 0.5 | R52: 0.5 | V52: =SUM(Q52:U52) -> 1
A53: 包装 | B53: VT4 | R53: 1 | V53: =SUM(Q53:U53) -> 1
A54: ヤード操業 | B54: チャン・クォック・ズイ | F54: 2 | G54: 2 | H54: 5 | I54: 5 | J54: 5 | K54: 5 | L54: 5 | M54: 5 | N54: 5 | Q54: 1 | R54: 1 | S54: 1 | T54: 0.5 | U54: 0.5 | V54: =SUM(Q54:U54) -> 4
A55: 工場DB | B55: 天川 | F55: 2 | G55: 2 | H55: 5 | I55: 5 | J55: 5 | K55: 5 | L55: 5 | M55: 5 | N55: 5 | U55: 0.2 | V55: =SUM(Q55:U55) -> 0.2
A56: 工場DB | B56: 馬場 | F56: 2 | G56: 2 | H56: 5 | I56: 5 | J56: 5 | K56: 5 | L56: 5 | M56: 5 | N56: 5 | U56: 0.2 | V56: =SUM(Q56:U56) -> 0.2
A57: 小計 | C57: =SUM(C36:C56) -> 0 | D57: =SUM(D36:D56) -> 0 | E57: =SUM(E36:E56) -> 0 | F57: =SUM(F36:F56) -> 6 | G57: =SUM(G36:G56) -> 6 | H57: =SUM(H36:H56) -> 15 | I57: =SUM(I36:I56) -> 15 | J57: =SUM(J36:J56) -> 15 | ... N57: =SUM(N36:N56) -> 15 | Q57: =SUM(Q32:Q56) -> 14 | R57: =SUM(R32:R56) -> 16 | S57: =SUM(S32:S56) -> 7 | T57: =SUM(T32:T56) -> 6 | U57: =SUM(U32:U56) -> 5.65 | V57: =SUM(Q57:U57) -> 48.65
A58: コミュニケータ | B58: グエン・ミン・トー | F58: 2 | G58: 2 | H58: 5 | I58: 5 | J58: 5 | K58: 5 | L58: 5 | M58: 5 | N58: 5 | Q58: 1 | R58: 1 | S58: 0.5 | T58: 0.5 | V58: =SUM(Q58:U58) -> 3
A59: ブリッジ | B59: チュン | F59: 2 | G59: 2 | H59: 5 | I59: 5 | J59: 5 | K59: 5 | L59: 5 | M59: 5 | N59: 5 | Q59: 0.5 | R59: 0.5 | V59: =SUM(Q59:U59) -> 1
A60: ブリッジ | B60: チャンホアンフック | F60: 2 | G60: 2 | H60: 5 | I60: 5 | J60: 5 | K60: 5 | L60: 5 | M60: 5 | N60: 5 | V60: =SUM(Q60:U60) -> 0
A61: ブリッジ | B61: ブイクアンティエン | F61: 2 | G61: 2 | H61: 5 | I61: 5 | J61: 5 | K61: 5 | L61: 5 | M61: 5 | N61: 5 | Q61: 0.5 | R61: 0.5 | S61: 0.5 | T61: 0.5 | V61: =SUM(Q61:U61) -> 2
A62: 管理（工場） | B62: 黒田智之 | Q62: 0.5 | R62: 0.5 | S62: 0.5 | T62: 0.5 | U62: 0.5 | V62: =SUM(Q62:U62) -> 2.5
A63: 数量確定 | B63: 吉田 | Q63: 0.5 | R63: 0.5 | S63: 0.5 | T63: 0.5 | U63: 0.5 | V63: =SUM(Q63:U63) -> 2.5
A64: 用役管理 | B64: 吉田 | Q64: 0.5 | R64: 0.5 | S64: 0.5 | T64: 0.5 | U64: 0.5 | V64: =SUM(Q64:U64) -> 2.5
A65: 千葉化学 | B65: 菊間 | Q65: 0.5 | R65: 0.5 | S65: 0.5 | T65: 0.5 | V65: =SUM(Q65:U65) -> 2
A66: 包装 | B66: 菊間 | Q66: 0.5 | R66: 0.5 | S66: 0.5 | T66: 0.5 | V66: =SUM(Q66:U66) -> 2
A67: 合計 | C67: =SUM(C41:C61) -> 0 | D67: =SUM(D41:D61) -> 0 | E67: =SUM(E41:E61) -> 0 | F67: =SUM(F41:F61) -> 20 | G67: =SUM(G41:G61) -> 20 | H67: =SUM(H41:H61) -> 50 | I67: =SUM(I41:I61) -> 50 | J67: =SUM(J41:J61) -> 50 | ... N67: =SUM(N41:N61) -> 50 | O67: =SUM(O57:O61) -> 0 | P67: =SUM(P57:P61) -> 0 | Q67: =SUM(Q57:Q66) -> 18.5 | R67: =SUM(R57:R66) -> 20.5 | S67: =SUM(S57:S66) -> 10.5 | T67: =SUM(T57:T66) -> 9.5 | U67: =SUM(U57:U66) -> 7.15 | V67: =SUM(Q67:U67) -> 66.15
A69: 売上 | O69: 調査・要件定義 | P69: 設計 | Q69: 製造 | R69: 結合テスト | S69: システムテスト | T69: ユーザテスト | U69: 本番稼働
A70: 野村 | B70: 1000000 | O70: =SUMIF($B$20:$B$56,$A70,O$20:O$56)*$B70 -> 0 | P70: =SUMIF($B$20:$B$56,$A70,P$20:P$56)*$B70 -> 0 | Q70: =SUMIF($B$20:$B$56,$A70,Q$20:Q$56)*$B70 -> 500000 | R70: =SUMIF($B$20:$B$56,$A70,R$20:R$56)*$B70 -> 500000 | S70: =SUMIF($B$20:$B$56,$A70,S$20:S$56)*$B70 -> 500000 | T70: =SUMIF($B$20:$B$56,$A70,T$20:T$56)*$B70 -> 500000 | U70: =SUMIF($B$20:$B$56,$A70,U$20:U$56)*$B70 -> 250000
A71: 石井 | B71: 1000000 | O71: =SUMIF($B$20:$B$56,$A71,O$20:O$56)*$B71 -> 0 | P71: =SUMIF($B$20:$B$56,$A71,P$20:P$56)*$B71 -> 0 | Q71: =SUMIF($B$20:$B$56,$A71,Q$20:Q$56)*$B71 -> 500000 | R71: =SUMIF($B$20:$B$56,$A71,R$20:R$56)*$B71 -> 500000 | S71: =SUMIF($B$20:$B$56,$A71,S$20:S$56)*$B71 -> 500000 | T71: =SUMIF($B$20:$B$56,$A71,T$20:T$56)*$B71 -> 500000 | U71: =SUMIF($B$20:$B$56,$A71,U$20:U$56)*$B71 -> 500000
A72: 天川 | B72: 1000000 | O72: =SUMIF($B$20:$B$56,$A72,O$20:O$56)*$B72 -> 0 | P72: =SUMIF($B$20:$B$56,$A72,P$20:P$56)*$B72 -> 0 | Q72: =SUMIF($B$20:$B$56,$A72,Q$20:Q$56)*$B72 -> 1000000 | R72: =SUMIF($B$20:$B$56,$A72,R$20:R$56)*$B72 -> 1000000 | S72: =SUMIF($B$20:$B$56,$A72,S$20:S$56)*$B72 -> 1000000 | T72: =SUMIF($B$20:$B$56,$A72,T$20:T$56)*$B72 -> 1000000 | U72: =SUMIF($B$20:$B$56,$A72,U$20:U$56)*$B72 -> 1200000
A73: 馬場 | B73: 1000000 | O73: =SUMIF($B$20:$B$56,$A73,O$20:O$56)*$B73 -> 0 | P73: =SUMIF($B$20:$B$56,$A73,P$20:P$56)*$B73 -> 0 | Q73: =SUMIF($B$20:$B$56,$A73,Q$20:Q$56)*$B73 -> 1000000 | R73: =SUMIF($B$20:$B$56,$A73,R$20:R$56)*$B73 -> 1000000 | S73: =SUMIF($B$20:$B$56,$A73,S$20:S$56)*$B73 -> 1000000 | T73: =SUMIF($B$20:$B$56,$A73,T$20:T$56)*$B73 -> 1000000 | U73: =SUMIF($B$20:$B$56,$A73,U$20:U$56)*$B73 -> 1200000
A74: グエン・タン・ドゥオック | B74: 700000 | O74: =SUMIF($B$20:$B$56,$A74,O$20:O$56)*$B74 -> 0 | P74: =SUMIF($B$20:$B$56,$A74,P$20:P$56)*$B74 -> 0 | Q74: =SUMIF($B$20:$B$56,$A74,Q$20:Q$56)*$B74 -> 700000 | R74: =SUMIF($B$20:$B$56,$A74,R$20:R$56)*$B74 -> 700000 | S74: =SUMIF($B$20:$B$56,$A74,S$20:S$56)*$B74 -> 700000 | T74: =SUMIF($B$20:$B$56,$A74,T$20:T$56)*$B74 -> 700000 | U74: =SUMIF($B$20:$B$56,$A74,U$20:U$56)*$B74 -> 350000
A75: グエン・チュン・グエン | B75: 700000 | O75: =SUMIF($B$20:$B$56,$A75,O$20:O$56)*$B75 -> 0 | P75: =SUMIF($B$20:$B$56,$A75,P$20:P$56)*$B75 -> 0 | Q75: =SUMIF($B$20:$B$56,$A75,Q$20:Q$56)*$B75 -> 700000 | R75: =SUMIF($B$20:$B$56,$A75,R$20:R$56)*$B75 -> 700000 | S75: =SUMIF($B$20:$B$56,$A75,S$20:S$56)*$B75 -> 700000 | T75: =SUMIF($B$20:$B$56,$A75,T$20:T$56)*$B75 -> 700000 | U75: =SUMIF($B$20:$B$56,$A75,U$20:U$56)*$B75 -> 700000
A76: ドー・ﾘｲ・アイン・トゥ | B76: 700000 | O76: =SUMIF($B$20:$B$56,$A76,O$20:O$56)*$B76 -> 0 | P76: =SUMIF($B$20:$B$56,$A76,P$20:P$56)*$B76 -> 0 | Q76: =SUMIF($B$20:$B$56,$A76,Q$20:Q$56)*$B76 -> 700000 | R76: =SUMIF($B$20:$B$56,$A76,R$20:R$56)*$B76 -> 700000 | S76: =SUMIF($B$20:$B$56,$A76,S$20:S$56)*$B76 -> 0 | T76: =SUMIF($B$20:$B$56,$A76,T$20:T$56)*$B76 -> 0 | U76: =SUMIF($B$20:$B$56,$A76,U$20:U$56)*$B76 -> 0
A77: レ・ファム・バオ・ロック | B77: 700000 | O77: =SUMIF($B$20:$B$56,$A77,O$20:O$56)*$B77 -> 0 | P77: =SUMIF($B$20:$B$56,$A77,P$20:P$56)*$B77 -> 0 | Q77: =SUMIF($B$20:$B$56,$A77,Q$20:Q$56)*$B77 -> 700000 | R77: =SUMIF($B$20:$B$56,$A77,R$20:R$56)*$B77 -> 700000 | S77: =SUMIF($B$20:$B$56,$A77,S$20:S$56)*$B77 -> 0 | T77: =SUMIF($B$20:$B$56,$A77,T$20:T$56)*$B77 -> 0 | U77: =SUMIF($B$20:$B$56,$A77,U$20:U$56)*$B77 -> 0
A78: ズオン・ゴック・フー | B78: 700000 | O78: =SUMIF($B$20:$B$56,$A78,O$20:O$56)*$B78 -> 0 | P78: =SUMIF($B$20:$B$56,$A78,P$20:P$56)*$B78 -> 0 | Q78: =SUMIF($B$20:$B$56,$A78,Q$20:Q$56)*$B78 -> 700000 | R78: =SUMIF($B$20:$B$56,$A78,R$20:R$56)*$B78 -> 700000 | S78: =SUMIF($B$20:$B$56,$A78,S$20:S$56)*$B78 -> 700000 | T78: =SUMIF($B$20:$B$56,$A78,T$20:T$56)*$B78 -> 350000 | U78: =SUMIF($B$20:$B$56,$A78,U$20:U$56)*$B78 -> 350000
A79: チャン・クォック・ズイ | B79: 700000 | O79: =SUMIF($B$20:$B$56,$A79,O$20:O$56)*$B79 -> 0 | P79: =SUMIF($B$20:$B$56,$A79,P$20:P$56)*$B79 -> 0 | Q79: =SUMIF($B$20:$B$56,$A79,Q$20:Q$56)*$B79 -> 700000 | R79: =SUMIF($B$20:$B$56,$A79,R$20:R$56)*$B79 -> 700000 | S79: =SUMIF($B$20:$B$56,$A79,S$20:S$56)*$B79 -> 700000 | T79: =SUMIF($B$20:$B$56,$A79,T$20:T$56)*$B79 -> 350000 | U79: =SUMIF($B$20:$B$56,$A79,U$20:U$56)*$B79 -> 350000
A80: ドー・グエン・ティ・トゥイ・ズイ | B80: 700000 | O80: =SUMIF($B$20:$B$56,$A80,O$20:O$56)*$B80 -> 0 | P80: =SUMIF($B$20:$B$56,$A80,P$20:P$56)*$B80 -> 0 | Q80: =SUMIF($B$20:$B$56,$A80,Q$20:Q$56)*$B80 -> 700000 | R80: =SUMIF($B$20:$B$56,$A80,R$20:R$56)*$B80 -> 700000 | S80: =SUMIF($B$20:$B$56,$A80,S$20:S$56)*$B80 -> 0 | T80: =SUMIF($B$20:$B$56,$A80,T$20:T$56)*$B80 -> 0 | U80: =SUMIF($B$20:$B$56,$A80,U$20:U$56)*$B80 -> 0
A81: グエン・ダン・ティエン | B81: 700000 | O81: =SUMIF($B$20:$B$56,$A81,O$20:O$56)*$B81 -> 0 | P81: =SUMIF($B$20:$B$56,$A81,P$20:P$56)*$B81 -> 0 | Q81: =SUMIF($B$20:$B$56,$A81,Q$20:Q$56)*$B81 -> 700000 | R81: =SUMIF($B$20:$B$56,$A81,R$20:R$56)*$B81 -> 700000 | S81: =SUMIF($B$20:$B$56,$A81,S$20:S$56)*$B81 -> 0 | T81: =SUMIF($B$20:$B$56,$A81,T$20:T$56)*$B81 -> 0 | U81: =SUMIF($B$20:$B$56,$A81,U$20:U$56)*$B81 -> 0
A82: ファン・グエン・タム | B82: 700000 | O82: =SUMIF($B$20:$B$56,$A82,O$20:O$56)*$B82 -> 0 | P82: =SUMIF($B$20:$B$56,$A82,P$20:P$56)*$B82 -> 0 | Q82: =SUMIF($B$20:$B$56,$A82,Q$20:Q$56)*$B82 -> 700000 | R82: =SUMIF($B$20:$B$56,$A82,R$20:R$56)*$B82 -> 700000 | S82: =SUMIF($B$20:$B$56,$A82,S$20:S$56)*$B82 -> 0 | T82: =SUMIF($B$20:$B$56,$A82,T$20:T$56)*$B82 -> 0 | U82: =SUMIF($B$20:$B$56,$A82,U$20:U$56)*$B82 -> 0
A83: グエン・ミン・トー | B83: 700000 | F83: 2 | G83: 2 | H83: 5 | I83: 5 | J83: 5 | K83: 5 | L83: 5 | M83: 5 | N83: 5 | O83: =SUMIF($B$20:$B$56,$A83,O$20:O$56)*$B83 -> 0 | P83: =SUMIF($B$20:$B$56,$A83,P$20:P$56)*$B83 -> 0 | Q83: =SUMIF($B$20:$B$56,$A83,Q$20:Q$56)*$B83 -> 0 | R83: =SUMIF($B$20:$B$56,$A83,R$20:R$56)*$B83 -> 0 | S83: =SUMIF($B$20:$B$56,$A83,S$20:S$56)*$B83 -> 0 | T83: =SUMIF($B$20:$B$56,$A83,T$20:T$56)*$B83 -> 0 | U83: =SUMIF($B$20:$B$56,$A83,U$20:U$56)*$B83 -> 0
A84: チュン | B84: 1000000 | F84: 2 | G84: 2 | H84: 5 | I84: 5 | J84: 5 | K84: 5 | L84: 5 | M84: 5 | N84: 5 | O84: =SUMIF($B$20:$B$56,$A84,O$20:O$56)*$B84 -> 0 | P84: =SUMIF($B$20:$B$56,$A84,P$20:P$56)*$B84 -> 0 | Q84: =SUMIF($B$20:$B$56,$A84,Q$20:Q$56)*$B84 -> 0 | R84: =SUMIF($B$20:$B$56,$A84,R$20:R$56)*$B84 -> 0 | S84: =SUMIF($B$20:$B$56,$A84,S$20:S$56)*$B84 -> 0 | T84: =SUMIF($B$20:$B$56,$A84,T$20:T$56)*$B84 -> 0 | U84: =SUMIF($B$20:$B$56,$A84,U$20:U$56)*$B84 -> 0
A85: チャンホアンフック | B85: 800000 | F85: 2 | G85: 2 | H85: 5 | I85: 5 | J85: 5 | K85: 5 | L85: 5 | M85: 5 | N85: 5 | O85: =SUMIF($B$20:$B$56,$A85,O$20:O$56)*$B85 -> 0 | P85: =SUMIF($B$20:$B$56,$A85,P$20:P$56)*$B85 -> 0 | Q85: =SUMIF($B$20:$B$56,$A85,Q$20:Q$56)*$B85 -> 0 | R85: =SUMIF($B$20:$B$56,$A85,R$20:R$56)*$B85 -> 0 | S85: =SUMIF($B$20:$B$56,$A85,S$20:S$56)*$B85 -> 0 | T85: =SUMIF($B$20:$B$56,$A85,T$20:T$56)*$B85 -> 0 | U85: =SUMIF($B$20:$B$56,$A85,U$20:U$56)*$B85 -> 0
A86: ブイクアンティエン | B86: 1000000 | F86: 2 | G86: 2 | H86: 5 | I86: 5 | J86: 5 | K86: 5 | L86: 5 | M86: 5 | N86: 5 | O86: =SUMIF($B$20:$B$56,$A86,O$20:O$56)*$B86 -> 0 | P86: =SUMIF($B$20:$B$56,$A86,P$20:P$56)*$B86 -> 0 | Q86: =SUMIF($B$20:$B$56,$A86,Q$20:Q$56)*$B86 -> 0 | R86: =SUMIF($B$20:$B$56,$A86,R$20:R$56)*$B86 -> 0 | S86: =SUMIF($B$20:$B$56,$A86,S$20:S$56)*$B86 -> 0 | T86: =SUMIF($B$20:$B$56,$A86,T$20:T$56)*$B86 -> 0 | U86: =SUMIF($B$20:$B$56,$A86,U$20:U$56)*$B86 -> 0
A87: VT1 | B87: 700000 | F87: 2 | G87: 2 | H87: 5 | I87: 5 | J87: 5 | K87: 5 | L87: 5 | M87: 5 | N87: 5 | O87: =SUMIF($B$20:$B$56,$A87,O$20:O$56)*$B87 -> 0 | P87: =SUMIF($B$20:$B$56,$A87,P$20:P$56)*$B87 -> 0 | Q87: =SUMIF($B$20:$B$56,$A87,Q$20:Q$56)*$B87 -> 700000 | R87: =SUMIF($B$20:$B$56,$A87,R$20:R$56)*$B87 -> 700000 | S87: =SUMIF($B$20:$B$56,$A87,S$20:S$56)*$B87 -> 0 | T87: =SUMIF($B$20:$B$56,$A87,T$20:T$56)*$B87 -> 0 | U87: =SUMIF($B$20:$B$56,$A87,U$20:U$56)*$B87 -> 0
A88: VT2 | B88: 700000 | F88: 2 | G88: 2 | H88: 5 | I88: 5 | J88: 5 | K88: 5 | L88: 5 | M88: 5 | N88: 5 | O88: =SUMIF($B$20:$B$56,$A88,O$20:O$56)*$B88 -> 0 | P88: =SUMIF($B$20:$B$56,$A88,P$20:P$56)*$B88 -> 0 | Q88: =SUMIF($B$20:$B$56,$A88,Q$20:Q$56)*$B88 -> 700000 | R88: =SUMIF($B$20:$B$56,$A88,R$20:R$56)*$B88 -> 700000 | S88: =SUMIF($B$20:$B$56,$A88,S$20:S$56)*$B88 -> 0 | T88: =SUMIF($B$20:$B$56,$A88,T$20:T$56)*$B88 -> 0 | U88: =SUMIF($B$20:$B$56,$A88,U$20:U$56)*$B88 -> 0
A89: VT3 | B89: 700000 | F89: 2 | G89: 2 | H89: 5 | I89: 5 | J89: 5 | K89: 5 | L89: 5 | M89: 5 | N89: 5 | O89: =SUMIF($B$20:$B$56,$A89,O$20:O$56)*$B89 -> 0 | P89: =SUMIF($B$20:$B$56,$A89,P$20:P$56)*$B89 -> 0 | Q89: =SUMIF($B$20:$B$56,$A89,Q$20:Q$56)*$B89 -> 0 | R89: =SUMIF($B$20:$B$56,$A89,R$20:R$56)*$B89 -> 700000 | S89: =SUMIF($B$20:$B$56,$A89,S$20:S$56)*$B89 -> 0 | T89: =SUMIF($B$20:$B$56,$A89,T$20:T$56)*$B89 -> 0 | U89: =SUMIF($B$20:$B$56,$A89,U$20:U$56)*$B89 -> 0
A90: VT4 | B90: 700000 | F90: 2 | G90: 2 | H90: 5 | I90: 5 | J90: 5 | K90: 5 | L90: 5 | M90: 5 | N90: 5 | O90: =SUMIF($B$20:$B$56,$A90,O$20:O$56)*$B90 -> 0 | P90: =SUMIF($B$20:$B$56,$A90,P$20:P$56)*$B90 -> 0 | Q90: =SUMIF($B$20:$B$56,$A90,Q$20:Q$56)*$B90 -> 0 | R90: =SUMIF($B$20:$B$56,$A90,R$20:R$56)*$B90 -> 700000 | S90: =SUMIF($B$20:$B$56,$A90,S$20:S$56)*$B90 -> 0 | T90: =SUMIF($B$20:$B$56,$A90,T$20:T$56)*$B90 -> 0 | U90: =SUMIF($B$20:$B$56,$A90,U$20:U$56)*$B90 -> 0
A91: 黒田智之 | B91: 1000000 | F91: 2 | G91: 2 | H91: 5 | I91: 5 | J91: 5 | K91: 5 | L91: 5 | M91: 5 | N91: 5 | O91: =SUMIF($B$20:$B$56,$A91,O$20:O$56)*$B91 -> 0 | P91: =SUMIF($B$20:$B$56,$A91,P$20:P$56)*$B91 -> 0 | Q91: =SUMIF($B$20:$B$56,$A91,Q$20:Q$56)*$B91 -> 0 | R91: =SUMIF($B$20:$B$56,$A91,R$20:R$56)*$B91 -> 0 | S91: =SUMIF($B$20:$B$56,$A91,S$20:S$56)*$B91 -> 0 | T91: =SUMIF($B$20:$B$56,$A91,T$20:T$56)*$B91 -> 0 | U91: =SUMIF($B$20:$B$56,$A91,U$20:U$56)*$B91 -> 0
A92: 吉田 | B92: 1000000 | F92: 2 | G92: 2 | H92: 5 | I92: 5 | J92: 5 | K92: 5 | L92: 5 | M92: 5 | N92: 5 | O92: =SUMIF($B$20:$B$56,$A92,O$20:O$56)*$B92 -> 0 | P92: =SUMIF($B$20:$B$56,$A92,P$20:P$56)*$B92 -> 0 | Q92: =SUMIF($B$20:$B$56,$A92,Q$20:Q$56)*$B92 -> 0 | R92: =SUMIF($B$20:$B$56,$A92,R$20:R$56)*$B92 -> 0 | S92: =SUMIF($B$20:$B$56,$A92,S$20:S$56)*$B92 -> 0 | T92: =SUMIF($B$20:$B$56,$A92,T$20:T$56)*$B92 -> 0 | U92: =SUMIF($B$20:$B$56,$A92,U$20:U$56)*$B92 -> 0
A93: 菊間 | B93: 1000000 | F93: 2 | G93: 2 | H93: 5 | I93: 5 | J93: 5 | K93: 5 | L93: 5 | M93: 5 | N93: 5 | O93: =SUMIF($B$20:$B$56,$A93,O$20:O$56)*$B93 -> 0 | P93: =SUMIF($B$20:$B$56,$A93,P$20:P$56)*$B93 -> 0 | Q93: =SUMIF($B$20:$B$56,$A93,Q$20:Q$56)*$B93 -> 0 | R93: =SUMIF($B$20:$B$56,$A93,R$20:R$56)*$B93 -> 0 | S93: =SUMIF($B$20:$B$56,$A93,S$20:S$56)*$B93 -> 0 | T93: =SUMIF($B$20:$B$56,$A93,T$20:T$56)*$B93 -> 0 | U93: =SUMIF($B$20:$B$56,$A93,U$20:U$56)*$B93 -> 0
A94: 合計 | C94: =SUM(C75:C93) -> 0 | D94: =SUM(D75:D93) -> 0 | E94: =SUM(E75:E93) -> 0 | F94: =SUM(F75:F93) -> 22 | G94: =SUM(G75:G93) -> 22 | H94: =SUM(H75:H93) -> 55 | I94: =SUM(I75:I93) -> 55 | J94: =SUM(J75:J93) -> 55 | ... N94: =SUM(N75:N93) -> 55 | O94: =SUM(O70:O93) -> 0 | P94: =SUM(P70:P93) -> 0 | Q94: =SUM(Q70:Q93) -> 10700000 | R94: =SUM(R70:R93) -> 12100000 | S94: =SUM(S70:S93) -> 5800000 | T94: =SUM(T70:T93) -> 5100000 | U94: =SUM(U70:U93) -> 4900000 | Y94: =SUM(O94:X94) -> 38600000
A96: コスト（コスト合計より粗利算出） | O96: 調査・要件定義 | P96: 設計 | Q96: 製造 | R96: 結合テスト | S96: システムテスト | T96: ユーザテスト | U96: 本番稼働
A97: 野村 | B97: 600000 | O97: =SUMIF($B$20:$B$56,$A97,O$20:O$56)*$B97 -> 0 | P97: =SUMIF($B$20:$B$56,$A97,P$20:P$56)*$B97 -> 0 | Q97: =SUMIF($B$20:$B$56,$A97,Q$20:Q$56)*$B97 -> 300000 | R97: =SUMIF($B$20:$B$56,$A97,R$20:R$56)*$B97 -> 300000 | S97: =SUMIF($B$20:$B$56,$A97,S$20:S$56)*$B97 -> 300000 | T97: =SUMIF($B$20:$B$56,$A97,T$20:T$56)*$B97 -> 300000 | U97: =SUMIF($B$20:$B$56,$A97,U$20:U$56)*$B97 -> 150000
A98: 石井 | B98: 600000 | O98: =SUMIF($B$20:$B$56,$A98,O$20:O$56)*$B98 -> 0 | P98: =SUMIF($B$20:$B$56,$A98,P$20:P$56)*$B98 -> 0 | Q98: =SUMIF($B$20:$B$56,$A98,Q$20:Q$56)*$B98 -> 300000 | R98: =SUMIF($B$20:$B$56,$A98,R$20:R$56)*$B98 -> 300000 | S98: =SUMIF($B$20:$B$56,$A98,S$20:S$56)*$B98 -> 300000 | T98: =SUMIF($B$20:$B$56,$A98,T$20:T$56)*$B98 -> 300000 | U98: =SUMIF($B$20:$B$56,$A98,U$20:U$56)*$B98 -> 300000
A99: 天川 | B99: 500000 | O99: =SUMIF($B$20:$B$56,$A99,O$20:O$56)*$B99 -> 0 | P99: =SUMIF($B$20:$B$56,$A99,P$20:P$56)*$B99 -> 0 | Q99: =SUMIF($B$20:$B$56,$A99,Q$20:Q$56)*$B99 -> 500000 | R99: =SUMIF($B$20:$B$56,$A99,R$20:R$56)*$B99 -> 500000 | S99: =SUMIF($B$20:$B$56,$A99,S$20:S$56)*$B99 -> 500000 | T99: =SUMIF($B$20:$B$56,$A99,T$20:T$56)*$B99 -> 500000 | U99: =SUMIF($B$20:$B$56,$A99,U$20:U$56)*$B99 -> 600000
A100: 馬場 | B100: 500000 | O100: =SUMIF($B$20:$B$56,$A100,O$20:O$56)*$B100 -> 0 | P100: =SUMIF($B$20:$B$56,$A100,P$20:P$56)*$B100 -> 0 | Q100: =SUMIF($B$20:$B$56,$A100,Q$20:Q$56)*$B100 -> 500000 | R100: =SUMIF($B$20:$B$56,$A100,R$20:R$56)*$B100 -> 500000 | S100: =SUMIF($B$20:$B$56,$A100,S$20:S$56)*$B100 -> 500000 | T100: =SUMIF($B$20:$B$56,$A100,T$20:T$56)*$B100 -> 500000 | U100: =SUMIF($B$20:$B$56,$A100,U$20:U$56)*$B100 -> 600000
A101: グエン・タン・ドゥオック | B101: 450000 | O101: =SUMIF($B$20:$B$56,$A101,O$20:O$56)*$B101 -> 0 | P101: =SUMIF($B$20:$B$56,$A101,P$20:P$56)*$B101 -> 0 | Q101: =SUMIF($B$20:$B$56,$A101,Q$20:Q$56)*$B101 -> 450000 | R101: =SUMIF($B$20:$B$56,$A101,R$20:R$56)*$B101 -> 450000 | S101: =SUMIF($B$20:$B$56,$A101,S$20:S$56)*$B101 -> 450000 | T101: =SUMIF($B$20:$B$56,$A101,T$20:T$56)*$B101 -> 450000 | U101: =SUMIF($B$20:$B$56,$A101,U$20:U$56)*$B101 -> 225000
A102: グエン・チュン・グエン | B102: 350000 | O102: =SUMIF($B$20:$B$56,$A102,O$20:O$56)*$B102 -> 0 | P102: =SUMIF($B$20:$B$56,$A102,P$20:P$56)*$B102 -> 0 | Q102: =SUMIF($B$20:$B$56,$A102,Q$20:Q$56)*$B102 -> 350000 | R102: =SUMIF($B$20:$B$56,$A102,R$20:R$56)*$B102 -> 350000 | S102: =SUMIF($B$20:$B$56,$A102,S$20:S$56)*$B102 -> 350000 | T102: =SUMIF($B$20:$B$56,$A102,T$20:T$56)*$B102 -> 350000 | U102: =SUMIF($B$20:$B$56,$A102,U$20:U$56)*$B102 -> 350000
A103: ドー・ﾘｲ・アイン・トゥ | B103: 350000 | O103: =SUMIF($B$20:$B$56,$A103,O$20:O$56)*$B103 -> 0 | P103: =SUMIF($B$20:$B$56,$A103,P$20:P$56)*$B103 -> 0 | Q103: =SUMIF($B$20:$B$56,$A103,Q$20:Q$56)*$B103 -> 350000 | R103: =SUMIF($B$20:$B$56,$A103,R$20:R$56)*$B103 -> 350000 | S103: =SUMIF($B$20:$B$56,$A103,S$20:S$56)*$B103 -> 0 | T103: =SUMIF($B$20:$B$56,$A103,T$20:T$56)*$B103 -> 0 | U103: =SUMIF($B$20:$B$56,$A103,U$20:U$56)*$B103 -> 0
A104: レ・ファム・バオ・ロック | B104: 350000 | O104: =SUMIF($B$20:$B$56,$A104,O$20:O$56)*$B104 -> 0 | P104: =SUMIF($B$20:$B$56,$A104,P$20:P$56)*$B104 -> 0 | Q104: =SUMIF($B$20:$B$56,$A104,Q$20:Q$56)*$B104 -> 350000 | R104: =SUMIF($B$20:$B$56,$A104,R$20:R$56)*$B104 -> 350000 | S104: =SUMIF($B$20:$B$56,$A104,S$20:S$56)*$B104 -> 0 | T104: =SUMIF($B$20:$B$56,$A104,T$20:T$56)*$B104 -> 0 | U104: =SUMIF($B$20:$B$56,$A104,U$20:U$56)*$B104 -> 0
A105: ズオン・ゴック・フー | B105: 350000 | O105: =SUMIF($B$20:$B$56,$A105,O$20:O$56)*$B105 -> 0 | P105: =SUMIF($B$20:$B$56,$A105,P$20:P$56)*$B105 -> 0 | Q105: =SUMIF($B$20:$B$56,$A105,Q$20:Q$56)*$B105 -> 350000 | R105: =SUMIF($B$20:$B$56,$A105,R$20:R$56)*$B105 -> 350000 | S105: =SUMIF($B$20:$B$56,$A105,S$20:S$56)*$B105 -> 350000 | T105: =SUMIF($B$20:$B$56,$A105,T$20:T$56)*$B105 -> 175000 | U105: =SUMIF($B$20:$B$56,$A105,U$20:U$56)*$B105 -> 175000
A106: チャン・クォック・ズイ | B106: 350000 | O106: =SUMIF($B$20:$B$56,$A106,O$20:O$56)*$B106 -> 0 | P106: =SUMIF($B$20:$B$56,$A106,P$20:P$56)*$B106 -> 0 | Q106: =SUMIF($B$20:$B$56,$A106,Q$20:Q$56)*$B106 -> 350000 | R106: =SUMIF($B$20:$B$56,$A106,R$20:R$56)*$B106 -> 350000 | S106: =SUMIF($B$20:$B$56,$A106,S$20:S$56)*$B106 -> 350000 | T106: =SUMIF($B$20:$B$56,$A106,T$20:T$56)*$B106 -> 175000 | U106: =SUMIF($B$20:$B$56,$A106,U$20:U$56)*$B106 -> 175000
...

Sheet スケジュール案・要員計画 (開発フェーズ_月別)
A2: システム | B2: 担当 | C2: 2024年 | O2: 2025年 | S2: 202６年
C3: 1月 | D3: 2月 | E3: 3月 | F3: 4月 | G3: 5月 | H3: 6月 | I3: 7月 | J3: 8月 | K3: 9月 | L3: 10月 | M3: 11月 | N3: 12月 | O3: 9月 | P3: 10月 | Q3: 11月 | R3: 12月 | S3: １月 | T3: ２月 | U3: ３月
A4: マイルストン | K4: ★縮小共通基盤構築 | P4: ★新共通基盤構築 | U4: ★館林DC廃止
A5: 数量確定システム（千葉・徳山）
A6: 用役管理システム（千葉・徳山）
A7: 千葉化学品質管理システム
A8: ＬＭＰＰ包装システム
A9: ヤード操業システム
A10: 工場DB
B12: 本番リリースタイミング
A13: 千葉化学品質管理システム | B13: 2026年2月上旬
A14: ＬＭＰＰ包装システム | B14: 2026年2月上旬
A15: 工場DB | B15: 2026年2月上旬
A16: ヤード操業システム（千葉・徳山） | B16: 2026年2月中旬
A17: 数量確定システム（千葉・徳山） | B17: 2026年2月下旬
A18: 用役管理システム（千葉・徳山） | B18: 2026年2月下旬
A20: 想定要員数(月単位)
A21: 管理 | Q21: 3 | R21: 3 | S21: 1.5 | T21: 1.5 | U21: 1.5 | V21: =SUM(O21:U21) -> 10.5
A22: 数量確定システム（千葉・徳山） | Q22: 5.6 | R22: 4 | S22: 1 | T22: 1 | U22: 1 | V22: =SUM(O22:U22) -> 12.6
A23: 用役管理システム（千葉・徳山） | Q23: 3.6 | R23: 2.5 | S23: 1 | T23: 1 | U23: 1 | V23: =SUM(O23:U23) -> 9.1
A24: 千葉化学品質管理システム | Q24: 4 | R24: 3.5 | S24: 1 | T24: 1 | V24: =SUM(O24:U24) -> 9.5
A25: ＬＭＰＰ包装システム | Q25: 2 | R25: 2 | S25: 0.5 | T25: 0.5 | V25: =SUM(O25:U25) -> 5
A26: 工場DB | Q26: 0 | R26: 0 | S26: 0 | T26: 0.4 | V26: =SUM(O26:U26) -> 0.4
A27: ヤ－ド操業システム（千葉・徳山） | Q27: 1.5 | R27: 0.5 | S27: 1 | T27: 1 | V27: =SUM(O27:U27) -> 4
A28: 合計 | C28: =SUM(C22:C27) -> 0 | D28: =SUM(D22:D27) -> 0 | E28: =SUM(E22:E27) -> 0 | F28: =SUM(F22:F27) -> 0 | G28: =SUM(G22:G27) -> 0 | H28: =SUM(H22:H27) -> 0 | I28: =SUM(I22:I27) -> 0 | J28: =SUM(J22:J27) -> 0 | ... N28: =SUM(N22:N27) -> 0 | O28: =SUM(O21:O27) -> 0 | P28: =SUM(P21:P27) -> 0 | Q28: =SUM(Q21:Q27) -> 19.7 | R28: =SUM(R21:R27) -> 15.5 | S28: =SUM(S21:S27) -> 6 | T28: =SUM(T21:T27) -> 6.4 | U28: =SUM(U21:U27) -> 3.5 | V28: =SUM(O28:U28) -> 51.1
A31: 想定要員数(工程単位) | O31: 調査・要件定義 | P31: 設計 | Q31: 製造 | R31: 結合テスト | S31: システムテスト | T31: ユーザテスト | U31: 本番稼働
A32: 管理 | Q32: 2.6 | R32: 3.4 | S32: 1.5 | T32: 1.1 | U32: 1.9
A33: 数量確定システム（千葉・徳山） | Q33: 3.2 | R33: 5.2 | S33: 1.4 | T33: 0.8 | U33: 2
A34: 用役管理システム（千葉・徳山） | Q34: 2.1 | R34: 3.1 | S34: 1.1 | T34: 0.8 | U34: 2
A35: 千葉化学品質管理システム | Q35: 2.2 | R35: 5.5 | S35: 0.8 | T35: 0.5 | U35: 0.5
A36: ＬＭＰＰ包装システム | Q36: 2.1 | R36: 1.2 | S36: 0.8 | T36: 0.5 | U36: 0.5
A37: 工場DB | Q37: 0 | R37: 0 | S37: 0 | T37: 0.1 | U37: 0.3
A38: ヤ－ド操業システム（千葉・徳山） | Q38: 0.9 | R38: 1.4 | S38: 0.2 | T38: 0.1 | U38: 1.3
A39: 合計 | C39: =SUM(C34:C38) -> 0 | D39: =SUM(D34:D38) -> 0 | E39: =SUM(E34:E38) -> 0 | F39: =SUM(F34:F38) -> 0 | G39: =SUM(G34:G38) -> 0 | H39: =SUM(H34:H38) -> 0 | I39: =SUM(I34:I38) -> 0 | J39: =SUM(J34:J38) -> 0 | ... N39: =SUM(N34:N38) -> 0 | O39: =SUM(O33:O38) -> 0 | P39: =SUM(P33:P38) -> 0 | Q39: =SUM(Q32:Q38) -> 13.1 | R39: =SUM(R32:R38) -> 19.8 | S39: =SUM(S32:S38) -> 5.8 | T39: =SUM(T32:T38) -> 3.9 | U39: =SUM(U32:U38) -> 8.5
A41: 要員 | X41: 要員人数 | Z41: 計画(月) | AB41: 計画(工程)
A42: 管理（工場） | B42: 野村 | Q42: 0.5 | R42: 0.5 | S42: 0.5 | T42: 0.5 | U42: 0.25 | V42: =SUM(O42:U42) -> 2.25 | W42: 管理（工場） | X42: =SUMIF($A$42:$A$77,W42,$V$42:$V$77) -> 11.75 | Y42: 人月 | Z42: =V21 -> 10.5 | AA42: 人月 | AB42: 10.5
A43: 管理（工場） | B43: 石井 | Q43: 0.5 | R43: 0.5 | S43: 0.5 | T43: 0.5 | U43: 0.5 | V43: =SUM(O43:U43) -> 2.5 | W43: 数量確定 | X43: =SUMIF($A$42:$A$77,W43,$V$42:$V$77) -> 12.5 | Y43: 人月 | Z43: =V22 -> 12.6 | AA43: 人月 | AB43: 12.6
A44: 管理（工場） | B44: グエン・タン・ドゥオック | Q44: 1 | R44: 1 | S44: 1 | T44: 1 | U44: 0.5 | V44: =SUM(O44:U44) -> 4.5 | W44: 用役管理 | X44: =SUMIF($A$42:$A$77,W44,$V$42:$V$77) -> 10.5 | Y44: 人月 | Z44: =V23 -> 9.1 | AA44: 人月 | AB44: 9.1
A45: 数量確定 | B45: 天川 | Q45: 0.5 | R45: 0.5 | S45: 0.5 | T45: 0.5 | U45: 0.5 | V45: =SUM(O45:U45) -> 2.5 | W45: 千葉化学 | X45: =SUMIF($A$42:$A$77,W45,$V$42:$V$77) -> 12.5 | Y45: 人月 | Z45: =V24 -> 9.5 | AA45: 人月 | AB45: 9.5
A46: 数量確定 | B46: グエン・チュン・グエン | Q46: 0.5 | R46: 0.5 | S46: 0.5 | T46: 0.5 | U46: 0.5 | V46: =SUM(O46:U46) -> 2.5 | W46: 包装 | X46: =SUMIF($A$42:$A$77,W46,$V$42:$V$77) -> 8.5 | Y46: 人月 | Z46: =V25 -> 5 | AA46: 人月 | AB46: 5
A47: 数量確定 | B47: ドー・ﾘｲ・アイン・トゥ | Q47: 1 | R47: 1 | V47: =SUM(O47:U47) -> 2 | W47: 工場DB | X47: =SUMIF($A$42:$A$77,W47,$V$42:$V$77) -> 0.4 | Y47: 人月 | Z47: =V26 -> 0.4 | AA47: 人月 | AB47: 0.4
A48: 数量確定 | B48: レ・ファム・バオ・ロック | Q48: 1 | R48: 1 | V48: =SUM(O48:U48) -> 2 | W48: ヤード操業 | X48: =SUMIF($A$42:$A$77,W48,$V$42:$V$77) -> 4 | Y48: 人月 | Z48: =V27 -> 4 | AA48: 人月 | AB48: 4
A49: 数量確定 | B49: VT1 | Q49: 0.5 | R49: 0.5 | V49: =SUM(O49:U49) -> 1 | W49: コミュニケータ | X49: =SUMIF($A$42:$A$77,W49,$V$42:$V$77) -> 3 | Y49: 人月 | AA49: 人月
A50: 用役管理 | B50: 天川 | Q50: 0.5 | R50: 0.5 | S50: 0.5 | T50: 0.5 | U50: 0.5 | V50: =SUM(O50:U50) -> 2.5 | W50: ブリッジ | X50: =SUMIF($A$42:$A$77,W50,$V$42:$V$77) -> 3 | Y50: 人月 | AA50: 人月
A51: 用役管理 | B51: グエン・チュン・グエン | Q51: 0.5 | R51: 0.5 | S51: 0.5 | T51: 0.5 | U51: 0.5 | V51: =SUM(O51:U51) -> 2.5 | X51: =SUM(X42:X50) -> 66.15 | Y51: 人月 | Z51: =SUM(Z42:Z50) -> 51.1 | AB51: =SUM(AB42:AB50) -> 51.1
A52: 用役管理 | B52: ドー・グエン・ティ・トゥイ・ズイ | Q52: 1 | R52: 1 | V52: =SUM(O52:U52) -> 2
A53: 用役管理 | B53: VT1 | Q53: 0.5 | R53: 0.5 | V53: =SUM(O53:U53) -> 1
A54: 千葉化学 | B54: 馬場 | Q54: 0.5 | R54: 0.5 | S54: 0.5 | T54: 0.5 | U54: 0.5 | V54: =SUM(O54:U54) -> 2.5
A55: 千葉化学 | B55: ズオン・ゴック・フー | Q55: 0.5 | R55: 0.5 | S55: 0.5 | T55: 0.5 | V55: =SUM(O55:U55) -> 2
A56: 千葉化学 | B56: グエン・ダン・ティエン | Q56: 1 | R56: 1 | V56: =SUM(O56:U56) -> 2
A57: 千葉化学 | B57: ファン・グエン・タム | Q57: 1 | R57: 1 | V57: =SUM(O57:U57) -> 2
A58: 千葉化学 | B58: VT2 | Q58: 0.5 | R58: 0.5 | V58: =SUM(O58:U58) -> 1
A59: 千葉化学 | B59: VT3 | R59: 1 | V59: =SUM(O59:U59) -> 1
A60: 包装 | B60: 馬場 | Q60: 0.5 | R60: 0.5 | S60: 0.5 | T60: 0.5 | U60: 0.5 | V60: =SUM(O60:U60) -> 2.5
A61: 包装 | B61: ズオン・ゴック・フー | Q61: 0.5 | R61: 0.5 | S61: 0.5 | T61: 0.5 | V61: =SUM(O61:U61) -> 2
A62: 包装 | B62: VT2 | Q62: 0.5 | R62: 0.5 | V62: =SUM(O62:U62) -> 1
A63: 包装 | B63: VT4 | R63: 1 | V63: =SUM(O63:U63) -> 1
A64: ヤード操業 | B64: チャン・クォック・ズイ | F64: 2 | G64: 2 | H64: 5 | I64: 5 | J64: 5 | K64: 5 | L64: 5 | M64: 5 | N64: 5 | Q64: 1 | R64: 1 | S64: 1 | T64: 1 | V64: =SUM(O64:U64) -> 4
A65: 工場DB | B65: 天川 | F65: 2 | G65: 2 | H65: 5 | I65: 5 | J65: 5 | K65: 5 | L65: 5 | M65: 5 | N65: 5 | T65: 0.2 | V65: =SUM(O65:U65) -> 0.2
A66: 工場DB | B66: 馬場 | F66: 2 | G66: 2 | H66: 5 | I66: 5 | J66: 5 | K66: 5 | L66: 5 | M66: 5 | N66: 5 | T66: 0.2 | V66: =SUM(O66:U66) -> 0.2
B67: 小計 | C67: =SUM(C46:C64) -> 0 | D67: =SUM(D46:D64) -> 0 | E67: =SUM(E46:E64) -> 0 | F67: =SUM(F46:F64) -> 2 | G67: =SUM(G46:G64) -> 2 | H67: =SUM(H46:H64) -> 5 | I67: =SUM(I46:I64) -> 5 | J67: =SUM(J46:J64) -> 5 | ... N67: =SUM(N46:N64) -> 5 | Q67: =SUM(Q42:Q66) -> 14 | R67: =SUM(R42:R66) -> 16 | S67: =SUM(S42:S66) -> 7 | T67: =SUM(T42:T66) -> 7.4 | U67: =SUM(U42:U66) -> 4.25 | V67: =SUM(O67:U67) -> 48.65
A68: コミュニケータ | B68: グエン・ミン・トー | F68: 2 | G68: 2 | H68: 5 | I68: 5 | J68: 5 | K68: 5 | L68: 5 | M68: 5 | N68: 5 | Q68: 1 | R68: 1 | S68: 0.5 | T68: 0.5 | V68: =SUM(O68:U68) -> 3
A69: ブリッジ | B69: チュン | F69: 2 | G69: 2 | H69: 5 | I69: 5 | J69: 5 | K69: 5 | L69: 5 | M69: 5 | N69: 5 | Q69: 0.5 | R69: 0.5 | V69: =SUM(O69:U69) -> 1
A70: ブリッジ | B70: チャンホアンフック | F70: 2 | G70: 2 | H70: 5 | I70: 5 | J70: 5 | K70: 5 | L70: 5 | M70: 5 | N70: 5 | V70: =SUM(O70:U70) -> 0
A71: ブリッジ | B71: ブイクアンティエン | F71: 2 | G71: 2 | H71: 5 | I71: 5 | J71: 5 | K71: 5 | L71: 5 | M71: 5 | N71: 5 | Q71: 0.5 | R71: 0.5 | S71: 0.5 | T71: 0.5 | V71: =SUM(O71:U71) -> 2
A72: 管理（工場） | B72: 黒田智之 | Q72: 0.5 | R72: 0.5 | S72: 0.5 | T72: 0.5 | U72: 0.5 | V72: =SUM(O72:U72) -> 2.5
A73: 数量確定 | B73: 吉田 | Q73: 0.5 | R73: 0.5 | S73: 0.5 | T73: 0.5 | U73: 0.5 | V73: =SUM(O73:U73) -> 2.5
A74: 用役管理 | B74: 吉田 | Q74: 0.5 | R74: 0.5 | S74: 0.5 | T74: 0.5 | U74: 0.5 | V74: =SUM(O74:U74) -> 2.5
A75: 千葉化学 | B75: 菊間 | Q75: 0.5 | R75: 0.5 | S75: 0.5 | T75: 0.5 | V75: =SUM(O75:U75) -> 2
A76: 包装 | B76: 菊間 | Q76: 0.5 | R76: 0.5 | S76: 0.5 | T76: 0.5 | V76: =SUM(O76:U76) -> 2
B77: 合計 | C77: =SUM(C51:C71) -> 0 | D77: =SUM(D51:D71) -> 0 | E77: =SUM(E51:E71) -> 0 | F77: =SUM(F51:F71) -> 16 | G77: =SUM(G51:G71) -> 16 | H77: =SUM(H51:H71) -> 40 | I77: =SUM(I51:I71) -> 40 | J77: =SUM(J51:J71) -> 40 | ... N77: =SUM(N51:N71) -> 40 | O77: =SUM(O67:O71) -> 0 | P77: =SUM(P67:P71) -> 0 | Q77: =SUM(Q67:Q76) -> 18.5 | R77: =SUM(R67:R76) -> 20.5 | S77: =SUM(S67:S76) -> 10.5 | T77: =SUM(T67:T76) -> 10.9 | U77: =SUM(U67:U76) -> 5.75 | V77: =SUM(O77:U77) -> 66.15
A79: 売上
A80: 野村 | B80: 1000000 | O80: =SUMIF($B$28:$B$66,$A80,O$28:O$66)*$B80 -> 0 | P80: =SUMIF($B$28:$B$66,$A80,P$28:P$66)*$B80 -> 0 | Q80: =SUMIF($B$28:$B$66,$A80,Q$28:Q$66)*$B80 -> 500000 | R80: =SUMIF($B$28:$B$66,$A80,R$28:R$66)*$B80 -> 500000 | S80: =SUMIF($B$28:$B$66,$A80,S$28:S$66)*$B80 -> 500000 | T80: =SUMIF($B$28:$B$66,$A80,T$28:T$66)*$B80 -> 500000 | U80: =SUMIF($B$28:$B$66,$A80,U$28:U$66)*$B80 -> 250000
A81: 石井 | B81: 1000000 | O81: =SUMIF($B$28:$B$66,$A81,O$28:O$66)*$B81 -> 0 | P81: =SUMIF($B$28:$B$66,$A81,P$28:P$66)*$B81 -> 0 | Q81: =SUMIF($B$28:$B$66,$A81,Q$28:Q$66)*$B81 -> 500000 | R81: =SUMIF($B$28:$B$66,$A81,R$28:R$66)*$B81 -> 500000 | S81: =SUMIF($B$28:$B$66,$A81,S$28:S$66)*$B81 -> 500000 | T81: =SUMIF($B$28:$B$66,$A81,T$28:T$66)*$B81 -> 500000 | U81: =SUMIF($B$28:$B$66,$A81,U$28:U$66)*$B81 -> 500000
A82: 天川 | B82: 1000000 | O82: =SUMIF($B$28:$B$66,$A82,O$28:O$66)*$B82 -> 0 | P82: =SUMIF($B$28:$B$66,$A82,P$28:P$66)*$B82 -> 0 | Q82: =SUMIF($B$28:$B$66,$A82,Q$28:Q$66)*$B82 -> 1000000 | R82: =SUMIF($B$28:$B$66,$A82,R$28:R$66)*$B82 -> 1000000 | S82: =SUMIF($B$28:$B$66,$A82,S$28:S$66)*$B82 -> 1000000 | T82: =SUMIF($B$28:$B$66,$A82,T$28:T$66)*$B82 -> 1200000 | U82: =SUMIF($B$28:$B$66,$A82,U$28:U$66)*$B82 -> 1000000
A83: 馬場 | B83: 1000000 | O83: =SUMIF($B$28:$B$66,$A83,O$28:O$66)*$B83 -> 0 | P83: =SUMIF($B$28:$B$66,$A83,P$28:P$66)*$B83 -> 0 | Q83: =SUMIF($B$28:$B$66,$A83,Q$28:Q$66)*$B83 -> 1000000 | R83: =SUMIF($B$28:$B$66,$A83,R$28:R$66)*$B83 -> 1000000 | S83: =SUMIF($B$28:$B$66,$A83,S$28:S$66)*$B83 -> 1000000 | T83: =SUMIF($B$28:$B$66,$A83,T$28:T$66)*$B83 -> 1200000 | U83: =SUMIF($B$28:$B$66,$A83,U$28:U$66)*$B83 -> 1000000
A84: グエン・タン・ドゥオック | B84: 700000 | O84: =SUMIF($B$28:$B$66,$A84,O$28:O$66)*$B84 -> 0 | P84: =SUMIF($B$28:$B$66,$A84,P$28:P$66)*$B84 -> 0 | Q84: =SUMIF($B$28:$B$66,$A84,Q$28:Q$66)*$B84 -> 700000 | R84: =SUMIF($B$28:$B$66,$A84,R$28:R$66)*$B84 -> 700000 | S84: =SUMIF($B$28:$B$66,$A84,S$28:S$66)*$B84 -> 700000 | T84: =SUMIF($B$28:$B$66,$A84,T$28:T$66)*$B84 -> 700000 | U84: =SUMIF($B$28:$B$66,$A84,U$28:U$66)*$B84 -> 350000
A85: グエン・チュン・グエン | B85: 700000 | O85: =SUMIF($B$28:$B$66,$A85,O$28:O$66)*$B85 -> 0 | P85: =SUMIF($B$28:$B$66,$A85,P$28:P$66)*$B85 -> 0 | Q85: =SUMIF($B$28:$B$66,$A85,Q$28:Q$66)*$B85 -> 700000 | R85: =SUMIF($B$28:$B$66,$A85,R$28:R$66)*$B85 -> 700000 | S85: =SUMIF($B$28:$B$66,$A85,S$28:S$66)*$B85 -> 700000 | T85: =SUMIF($B$28:$B$66,$A85,T$28:T$66)*$B85 -> 700000 | U85: =SUMIF($B$28:$B$66,$A85,U$28:U$66)*$B85 -> 700000
A86: ドー・ﾘｲ・アイン・トゥ | B86: 700000 | O86: =SUMIF($B$28:$B$66,$A86,O$28:O$66)*$B86 -> 0 | P86: =SUMIF($B$28:$B$66,$A86,P$28:P$66)*$B86 -> 0 | Q86: =SUMIF($B$28:$B$66,$A86,Q$28:Q$66)*$B86 -> 700000 | R86: =SUMIF($B$28:$B$66,$A86,R$28:R$66)*$B86 -> 700000 | S86: =SUMIF($B$28:$B$66,$A86,S$28:S$66)*$B86 -> 0 | T86: =SUMIF($B$28:$B$66,$A86,T$28:T$66)*$B86 -> 0 | U86: =SUMIF($B$28:$B$66,$A86,U$28:U$66)*$B86 -> 0
A87: レ・ファム・バオ・ロック | B87: 700000 | O87: =SUMIF($B$28:$B$66,$A87,O$28:O$66)*$B87 -> 0 | P87: =SUMIF($B$28:$B$66,$A87,P$28:P$66)*$B87 -> 0 | Q87: =SUMIF($B$28:$B$66,$A87,Q$28:Q$66)*$B87 -> 700000 | R87: =SUMIF($B$28:$B$66,$A87,R$28:R$66)*$B87 -> 700000 | S87: =SUMIF($B$28:$B$66,$A87,S$28:S$66)*$B87 -> 0 | T87: =SUMIF($B$28:$B$66,$A87,T$28:T$66)*$B87 -> 0 | U87: =SUMIF($B$28:$B$66,$A87,U$28:U$66)*$B87 -> 0
A88: ズオン・ゴック・フー | B88: 700000 | O88: =SUMIF($B$28:$B$66,$A88,O$28:O$66)*$B88 -> 0 | P88: =SUMIF($B$28:$B$66,$A88,P$28:P$66)*$B88 -> 0 | Q88: =SUMIF($B$28:$B$66,$A88,Q$28:Q$66)*$B88 -> 700000 | R88: =SUMIF($B$28:$B$66,$A88,R$28:R$66)*$B88 -> 700000 | S88: =SUMIF($B$28:$B$66,$A88,S$28:S$66)*$B88 -> 700000 | T88: =SUMIF($B$28:$B$66,$A88,T$28:T$66)*$B88 -> 700000 | U88: =SUMIF($B$28:$B$66,$A88,U$28:U$66)*$B88 -> 0
A89: チャン・クォック・ズイ | B89: 700000 | O89: =SUMIF($B$28:$B$66,$A89,O$28:O$66)*$B89 -> 0 | P89: =SUMIF($B$28:$B$66,$A89,P$28:P$66)*$B89 -> 0 | Q89: =SUMIF($B$28:$B$66,$A89,Q$28:Q$66)*$B89 -> 700000 | R89: =SUMIF($B$28:$B$66,$A89,R$28:R$66)*$B89 -> 700000 | S89: =SUMIF($B$28:$B$66,$A89,S$28:S$66)*$B89 -> 700000 | T89: =SUMIF($B$28:$B$66,$A89,T$28:T$66)*$B89 -> 700000 | U89: =SUMIF($B$28:$B$66,$A89,U$28:U$66)*$B89 -> 0
A90: ドー・グエン・ティ・トゥイ・ズイ | B90: 700000 | O90: =SUMIF($B$28:$B$66,$A90,O$28:O$66)*$B90 -> 0 | P90: =SUMIF($B$28:$B$66,$A90,P$28:P$66)*$B90 -> 0 | Q90: =SUMIF($B$28:$B$66,$A90,Q$28:Q$66)*$B90 -> 700000 | R90: =SUMIF($B$28:$B$66,$A90,R$28:R$66)*$B90 -> 700000 | S90: =SUMIF($B$28:$B$66,$A90,S$28:S$66)*$B90 -> 0 | T90: =SUMIF($B$28:$B$66,$A90,T$28:T$66)*$B90 -> 0 | U90: =SUMIF($B$28:$B$66,$A90,U$28:U$66)*$B90 -> 0
A91: グエン・ダン・ティエン | B91: 700000 | O91: =SUMIF($B$28:$B$66,$A91,O$28:O$66)*$B91 -> 0 | P91: =SUMIF($B$28:$B$66,$A91,P$28:P$66)*$B91 -> 0 | Q91: =SUMIF($B$28:$B$66,$A91,Q$28:Q$66)*$B91 -> 700000 | R91: =SUMIF($B$28:$B$66,$A91,R$28:R$66)*$B91 -> 700000 | S91: =SUMIF($B$28:$B$66,$A91,S$28:S$66)*$B91 -> 0 | T91: =SUMIF($B$28:$B$66,$A91,T$28:T$66)*$B91 -> 0 | U91: =SUMIF($B$28:$B$66,$A91,U$28:U$66)*$B91 -> 0
A92: ファン・グエン・タム | B92: 700000 | O92: =SUMIF($B$28:$B$66,$A92,O$28:O$66)*$B92 -> 0 | P92: =SUMIF($B$28:$B$66,$A92,P$28:P$66)*$B92 -> 0 | Q92: =SUMIF($B$28:$B$66,$A92,Q$28:Q$66)*$B92 -> 700000 | R92: =SUMIF($B$28:$B$66,$A92,R$28:R$66)*$B92 -> 700000 | S92: =SUMIF($B$28:$B$66,$A92,S$28:S$66)*$B92 -> 0 | T92: =SUMIF($B$28:$B$66,$A92,T$28:T$66)*$B92 -> 0 | U92: =SUMIF($B$28:$B$66,$A92,U$28:U$66)*$B92 -> 0
A93: グエン・ミン・トー | B93: 700000 | F93: 2 | G93: 2 | H93: 5 | I93: 5 | J93: 5 | K93: 5 | L93: 5 | M93: 5 | N93: 5 | O93: =SUMIF($B$28:$B$66,$A93,O$28:O$66)*$B93 -> 0 | P93: =SUMIF($B$28:$B$66,$A93,P$28:P$66)*$B93 -> 0 | Q93: =SUMIF($B$28:$B$66,$A93,Q$28:Q$66)*$B93 -> 0 | R93: =SUMIF($B$28:$B$66,$A93,R$28:R$66)*$B93 -> 0 | S93: =SUMIF($B$28:$B$66,$A93,S$28:S$66)*$B93 -> 0 | T93: =SUMIF($B$28:$B$66,$A93,T$28:T$66)*$B93 -> 0 | U93: =SUMIF($B$28:$B$66,$A93,U$28:U$66)*$B93 -> 0
A94: チュン | B94: 1000000 | F94: 2 | G94: 2 | H94: 5 | I94: 5 | J94: 5 | K94: 5 | L94: 5 | M94: 5 | N94: 5 | O94: =SUMIF($B$28:$B$66,$A94,O$28:O$66)*$B94 -> 0 | P94: =SUMIF($B$28:$B$66,$A94,P$28:P$66)*$B94 -> 0 | Q94: =SUMIF($B$28:$B$66,$A94,Q$28:Q$66)*$B94 -> 0 | R94: =SUMIF($B$28:$B$66,$A94,R$28:R$66)*$B94 -> 0 | S94: =SUMIF($B$28:$B$66,$A94,S$28:S$66)*$B94 -> 0 | T94: =SUMIF($B$28:$B$66,$A94,T$28:T$66)*$B94 -> 0 | U94: =SUMIF($B$28:$B$66,$A94,U$28:U$66)*$B94 -> 0
A95: チャンホアンフック | B95: 800000 | F95: 2 | G95: 2 | H95: 5 | I95: 5 | J95: 5 | K95: 5 | L95: 5 | M95: 5 | N95: 5 | O95: =SUMIF($B$28:$B$66,$A95,O$28:O$66)*$B95 -> 0 | P95: =SUMIF($B$28:$B$66,$A95,P$28:P$66)*$B95 -> 0 | Q95: =SUMIF($B$28:$B$66,$A95,Q$28:Q$66)*$B95 -> 0 | R95: =SUMIF($B$28:$B$66,$A95,R$28:R$66)*$B95 -> 0 | S95: =SUMIF($B$28:$B$66,$A95,S$28:S$66)*$B95 -> 0 | T95: =SUMIF($B$28:$B$66,$A95,T$28:T$66)*$B95 -> 0 | U95: =SUMIF($B$28:$B$66,$A95,U$28:U$66)*$B95 -> 0
A96: ブイクアンティエン | B96: 1000000 | F96: 2 | G96: 2 | H96: 5 | I96: 5 | J96: 5 | K96: 5 | L96: 5 | M96: 5 | N96: 5 | O96: =SUMIF($B$28:$B$66,$A96,O$28:O$66)*$B96 -> 0 | P96: =SUMIF($B$28:$B$66,$A96,P$28:P$66)*$B96 -> 0 | Q96: =SUMIF($B$28:$B$66,$A96,Q$28:Q$66)*$B96 -> 0 | R96: =SUMIF($B$28:$B$66,$A96,R$28:R$66)*$B96 -> 0 | S96: =SUMIF($B$28:$B$66,$A96,S$28:S$66)*$B96 -> 0 | T96: =SUMIF($B$28:$B$66,$A96,T$28:T$66)*$B96 -> 0 | U96: =SUMIF($B$28:$B$66,$A96,U$28:U$66)*$B96 -> 0
A97: VT1 | B97: 700000 | F97: 2 | G97: 2 | H97: 5 | I97: 5 | J97: 5 | K97: 5 | L97: 5 | M97: 5 | N97: 5 | O97: =SUMIF($B$28:$B$66,$A97,O$28:O$66)*$B97 -> 0 | P97: =SUMIF($B$28:$B$66,$A97,P$28:P$66)*$B97 -> 0 | Q97: =SUMIF($B$28:$B$66,$A97,Q$28:Q$66)*$B97 -> 700000 | R97: =SUMIF($B$28:$B$66,$A97,R$28:R$66)*$B97 -> 700000 | S97: =SUMIF($B$28:$B$66,$A97,S$28:S$66)*$B97 -> 0 | T97: =SUMIF($B$28:$B$66,$A97,T$28:T$66)*$B97 -> 0 | U97: =SUMIF($B$28:$B$66,$A97,U$28:U$66)*$B97 -> 0
A98: VT2 | B98: 700000 | F98: 2 | G98: 2 | H98: 5 | I98: 5 | J98: 5 | K98: 5 | L98: 5 | M98: 5 | N98: 5 | O98: =SUMIF($B$28:$B$66,$A98,O$28:O$66)*$B98 -> 0 | P98: =SUMIF($B$28:$B$66,$A98,P$28:P$66)*$B98 -> 0 | Q98: =SUMIF($B$28:$B$66,$A98,Q$28:Q$66)*$B98 -> 700000 | R98: =SUMIF($B$28:$B$66,$A98,R$28:R$66)*$B98 -> 700000 | S98: =SUMIF($B$28:$B$66,$A98,S$28:S$66)*$B98 -> 0 | T98: =SUMIF($B$28:$B$66,$A98,T$28:T$66)*$B98 -> 0 | U98: =SUMIF($B$28:$B$66,$A98,U$28:U$66)*$B98 -> 0
A99: VT3 | B99: 700000 | F99: 2 | G99: 2 | H99: 5 | I99: 5 | J99: 5 | K99: 5 | L99: 5 | M99: 5 | N99: 5 | O99: =SUMIF($B$28:$B$66,$A99,O$28:O$66)*$B99 -> 0 | P99: =SUMIF($B$28:$B$66,$A99,P$28:P$66)*$B99 -> 0 | Q99: =SUMIF($B$28:$B$66,$A99,Q$28:Q$66)*$B99 -> 0 | R99: =SUMIF($B$28:$B$66,$A99,R$28:R$66)*$B99 -> 700000 | S99: =SUMIF($B$28:$B$66,$A99,S$28:S$66)*$B99 -> 0 | T99: =SUMIF($B$28:$B$66,$A99,T$28:T$66)*$B99 -> 0 | U99: =SUMIF($B$28:$B$66,$A99,U$28:U$66)*$B99 -> 0
A100: VT4 | B100: 700000 | F100: 2 | G100: 2 | H100: 5 | I100: 5 | J100: 5 | K100: 5 | L100: 5 | M100: 5 | N100: 5 | O100: =SUMIF($B$28:$B$66,$A100,O$28:O$66)*$B100 -> 0 | P100: =SUMIF($B$28:$B$66,$A100,P$28:P$66)*$B100 -> 0 | Q100: =SUMIF($B$28:$B$66,$A100,Q$28:Q$66)*$B100 -> 0 | R100: =SUMIF($B$28:$B$66,$A100,R$28:R$66)*$B100 -> 700000 | S100: =SUMIF($B$28:$B$66,$A100,S$28:S$66)*$B100 -> 0 | T100: =SUMIF($B$28:$B$66,$A100,T$28:T$66)*$B100 -> 0 | U100: =SUMIF($B$28:$B$66,$A100,U$28:U$66)*$B100 -> 0
A101: 黒田智之 | B101: 1000000 | F101: 2 | G101: 2 | H101: 5 | I101: 5 | J101: 5 | K101: 5 | L101: 5 | M101: 5 | N101: 5 | O101: =SUMIF($B$28:$B$66,$A101,O$28:O$66)*$B101 -> 0 | P101: =SUMIF($B$28:$B$66,$A101,P$28:P$66)*$B101 -> 0 | Q101: =SUMIF($B$28:$B$66,$A101,Q$28:Q$66)*$B101 -> 0 | R101: =SUMIF($B$28:$B$66,$A101,R$28:R$66)*$B101 -> 0 | S101: =SUMIF($B$28:$B$66,$A101,S$28:S$66)*$B101 -> 0 | T101: =SUMIF($B$28:$B$66,$A101,T$28:T$66)*$B101 -> 0 | U101: =SUMIF($B$28:$B$66,$A101,U$28:U$66)*$B101 -> 0
A102: 吉田 | B102: 1000000 | F102: 2 | G102: 2 | H102: 5 | I102: 5 | J102: 5 | K102: 5 | L102: 5 | M102: 5 | N102: 5 | O102: =SUMIF($B$28:$B$66,$A102,O$28:O$66)*$B102 -> 0 | P102: =SUMIF($B$28:$B$66,$A102,P$28:P$66)*$B102 -> 0 | Q102: =SUMIF($B$28:$B$66,$A102,Q$28:Q$66)*$B102 -> 0 | R102: =SUMIF($B$28:$B$66,$A102,R$28:R$66)*$B102 -> 0 | S102: =SUMIF($B$28:$B$66,$A102,S$28:S$66)*$B102 -> 0 | T102: =SUMIF($B$28:$B$66,$A102,T$28:T$66)*$B102 -> 0 | U102: =SUMIF($B$28:$B$66,$A102,U$28:U$66)*$B102 -> 0
A103: 菊間 | B103: 1000000 | F103: 2 | G103: 2 | H103: 5 | I103: 5 | J103: 5 | K103: 5 | L103: 5 | M103: 5 | N103: 5 | O103: =SUMIF($B$28:$B$66,$A103,O$28:O$66)*$B103 -> 0 | P103: =SUMIF($B$28:$B$66,$A103,P$28:P$66)*$B103 -> 0 | Q103: =SUMIF($B$28:$B$66,$A103,Q$28:Q$66)*$B103 -> 0 | R103: =SUMIF($B$28:$B$66,$A103,R$28:R$66)*$B103 -> 0 | S103: =SUMIF($B$28:$B$66,$A103,S$28:S$66)*$B103 -> 0 | T103: =SUMIF($B$28:$B$66,$A103,T$28:T$66)*$B103 -> 0 | U103: =SUMIF($B$28:$B$66,$A103,U$28:U$66)*$B103 -> 0
A104: 合計 | C104: =SUM(C85:C103) -> 0 | D104: =SUM(D85:D103) -> 0 | E104: =SUM(E85:E103) -> 0 | F104: =SUM(F85:F103) -> 22 | G104: =SUM(G85:G103) -> 22 | H104: =SUM(H85:H103) -> 55 | I104: =SUM(I85:I103) -> 55 | J104: =SUM(J85:J103) -> 55 | ... N104: =SUM(N85:N103) -> 55 | O104: =SUM(O80:O103) -> 0 | P104: =SUM(P80:P103) -> 0 | Q104: =SUM(Q80:Q103) -> 10700000 | R104: =SUM(R80:R103) -> 12100000 | S104: =SUM(S80:S103) -> 5800000 | T104: =SUM(T80:T103) -> 6200000 | U104: =SUM(U80:U103) -> 3800000 | V104: =SUM(O104:U104) -> 38600000
A106: コスト（コスト合計より粗利算出）
A107: 野村 | B107: 600000 | O107: =SUMIF($B$28:$B$66,$A107,O$28:O$66)*$B107 -> 0 | P107: =SUMIF($B$28:$B$66,$A107,P$28:P$66)*$B107 -> 0 | Q107: =SUMIF($B$28:$B$66,$A107,Q$28:Q$66)*$B107 -> 300000 | R107: =SUMIF($B$28:$B$66,$A107,R$28:R$66)*$B107 -> 300000 | S107: =SUMIF($B$28:$B$66,$A107,S$28:S$66)*$B107 -> 300000 | T107: =SUMIF($B$28:$B$66,$A107,T$28:T$66)*$B107 -> 300000 | U107: =SUMIF($B$28:$B$66,$A107,U$28:U$66)*$B107 -> 150000
A108: 石井 | B108: 600000 | O108: =SUMIF($B$28:$B$66,$A108,O$28:O$66)*$B108 -> 0 | P108: =SUMIF($B$28:$B$66,$A108,P$28:P$66)*$B108 -> 0 | Q108: =SUMIF($B$28:$B$66,$A108,Q$28:Q$66)*$B108 -> 300000 | R108: =SUMIF($B$28:$B$66,$A108,R$28:R$66)*$B108 -> 300000 | S108: =SUMIF($B$28:$B$66,$A108,S$28:S$66)*$B108 -> 300000 | T108: =SUMIF($B$28:$B$66,$A108,T$28:T$66)*$B108 -> 300000 | U108: =SUMIF($B$28:$B$66,$A108,U$28:U$66)*$B108 -> 300000
...

Sheet 再見積 (システム・工程別サマリ)  (2)
C1: 工数直入力のため注意！！
C2: 見積（工程別サマリ）
C3: パターン | D3: クラウドアーキ基盤に移行 | R3: 備考
D4: アプリ | N4: DB | P4: 全体
B5: No. | C5: システム | D5: 調査・要件定義 | E5: 設計 | F5: 製造 | G5: 結合テスト | H5: システムテスト | I5: ユーザテスト | J5: 本番稼働 | K5: 管理 | L5: 工数計 | M5: 金額 | N5: 工数計 | O5: 金額 | P5: 工数計 | Q5: 金額
B6: 1 | C6: 数量確定システム（千葉・徳山） | D6: 3.2 | E6: 1.6 | F6: 2.7 | G6: 5.2 | H6: 1.4 | I6: 0.8 | J6: 2 | K6: 3.8 | L6: =SUM(D6:K6) -> 20.7 | M6: =SUM(D6:J6)*1000000+K6*1400000 -> 22220000 | N6: 0 | O6: 0 | P6: =SUM(L6:L10)+N6 -> 58.4 | Q6: =SUM(M6:M10)+O6 -> 63040000
B7: 2 | C7: 用役管理システム（千葉・徳山） | D7: 1.4 | E7: 1.1 | F7: 1.5 | G7: 3.1 | H7: 1.1 | I7: 0.8 | J7: 2 | K7: 2.6 | L7: =SUM(D7:K7) -> 13.6 | M7: =SUM(D7:J7)*1000000+K7*1400000 -> 14640000
B8: 3 | C8: 千葉化学品質管理システム | D8: 1.7 | E8: 1.4 | F8: 1.6 | G8: 5.5 | H8: 0.8 | I8: 0.5 | J8: 0.6 | K8: 2.8 | L8: =SUM(D8:K8) -> 14.9 | M8: =SUM(D8:J8)*1000000+K8*1400000 -> 16020000
B9: 4 | C9: ＬＭＰＰ包装システム | D9: 1.3 | E9: 0.4 | F9: 1.6 | G9: 1.2 | H9: 0.8 | I9: 0.5 | J9: 0.6 | K9: 1.9 | L9: =SUM(D9:K9) -> 8.3 | M9: =SUM(D9:J9)*1000000+K9*1400000 -> 9060000
B10: 5 | C10: 工場DB | J10: 0.4 | K10: 0.5 | L10: =SUM(D10:K10) -> 0.9 | M10: =SUM(D10:J10)*1000000+K10*1400000 -> 1100000
B11: 6 | C11: ヤ－ド操業システム（千葉・徳山） | D11: 0.5 | E11: 0.4 | F11: 0.7 | G11: 1.4 | H11: 0.2 | I11: 0.1 | J11: 1.5 | K11: 0.9 | L11: =SUM(D11:K11) -> 5.7 | M11: =SUM(D11:J11)*1000000+K11*1400000 -> 6060000 | N11: 0 | O11: =SUM(O5:O10) -> 0 | P11: =SUM(L11:L11)+N11 -> 5.7 | Q11: =SUM(M11:M11)+O6 -> 6060000
B12: 計 | D12: =SUM(D6:D11) -> 8.1 | E12: =SUM(E6:E11) -> 4.9 | F12: =SUM(F6:F11) -> 8.1 | G12: =SUM(G6:G11) -> 16.4 | H12: =SUM(H6:H11) -> 4.3 | I12: =SUM(I6:I11) -> 2.7 | J12: =SUM(J6:J11) -> 7.1 | K12: =SUM(K6:K11) -> 12.5 | L12: =SUM(D12:K12) -> 64.1 | M12: =SUM(M6:M11) -> 69100000 | N12: =SUM(N6:N11) -> 0 | O12: =SUM(O6:O11) -> 0 | P12: =SUM(P6:P11) -> 64.1 | Q12: =SUM(Q6:Q11) -> 69100000
B13: 単価 | D13: 1000000 | E13: 1000000 | F13: 1000000 | G13: 1000000 | H13: 1000000 | I13: 1000000 | J13: 1000000 | K13: 1400000
B14: 金額 | D14: =D12*D13 -> 8100000 | E14: =E12*E13 -> 4900000 | F14: =F12*F13 -> 8100000 | G14: =G12*G13 -> 16400000 | H14: =H12*H13 -> 4300000 | I14: =I12*I13 -> 2700000 | J14: =J12*J13 -> 7100000 | K14: =K12*K13 -> 17500000
C16: 再見積もり（工程別サマリ）
C17: パターン | D17: クラウドアーキ基盤に移行 | R17: 備考
D18: アプリ | N18: DB | P18: 全体
B19: No. | C19: システム | D19: 調査・要件定義 | E19: 設計 | F19: 製造 | G19: 結合テスト | H19: システムテスト | I19: ユーザテスト | J19: 本番稼働 | K19: 管理 | L19: 工数計 | M19: 金額 | N19: 工数計 | O19: 金額 | P19: 工数計 | Q19: 金額
B20: 1 | C20: 数量確定システム（千葉・徳山） | D20: 3.2 | E20: 1.6 | F20: 3.2 | G20: 5.2 | H20: 1.4 | I20: 0.8 | J20: 2 | K20: 3.9 | L20: =SUM(D20:K20) -> 21.3 | M20: =SUM(D20:J20)*1000000+K20*1400000 -> 22860000 | N20: 0 | O20: 0 | P20: =SUM(L20:L24)+N20 -> 61 | Q20: =SUM(M20:M24)+O20 -> 65800000
B21: 2 | C21: 用役管理システム（千葉・徳山） | D21: 1.4 | E21: 1.1 | F21: 2.1 | G21: 3.1 | H21: 1.1 | I21: 0.8 | J21: 2 | K21: 2.7 | L21: =SUM(D21:K21) -> 14.3 | M21: =SUM(D21:J21)*1000000+K21*1400000 -> 15380000
B22: 3 | C22: 千葉化学品質管理システム | D22: 1.7 | E22: 1.4 | F22: 2.2 | G22: 5.5 | H22: 0.8 | I22: 0.5 | J22: 0.6 | K22: 2.9 | L22: =SUM(D22:K22) -> 15.6 | M22: =SUM(D22:J22)*1000000+K22*1400000 -> 16760000
B23: 4 | C23: ＬＭＰＰ包装システム | D23: 1.3 | E23: 0.4 | F23: 2.1 | G23: 1.2 | H23: 0.8 | I23: 0.5 | J23: 0.6 | K23: 2 | L23: =SUM(D23:K23) -> 8.9 | M23: =SUM(D23:J23)*1000000+K23*1400000 -> 9700000
B24: 5 | C24: 工場DB | J24: 0.4 | K24: 0.5 | L24: =SUM(D24:K24) -> 0.9 | M24: =SUM(D24:J24)*1000000+K24*1400000 -> 1100000
B25: 6 | C25: ヤ－ド操業システム（千葉・徳山） | D25: 0.5 | E25: 0.4 | F25: 0.9 | G25: 1.4 | H25: 0.2 | I25: 0.1 | J25: 1.5 | K25: 0.9 | L25: =SUM(D25:K25) -> 5.9 | M25: =SUM(D25:J25)*1000000+K25*1400000 -> 6260000 | N25: 0 | O25: =SUM(O19:O24) -> 0 | P25: =SUM(L25:L25)+N25 -> 5.9 | Q25: =SUM(M25:M25)+O20 -> 6260000
B26: 計 | D26: =SUM(D20:D25) -> 8.1 | E26: =SUM(E20:E25) -> 4.9 | F26: =SUM(F20:F25) -> 10.5 | G26: =SUM(G20:G25) -> 16.4 | H26: =SUM(H20:H25) -> 4.3 | I26: =SUM(I20:I25) -> 2.7 | J26: =SUM(J20:J25) -> 7.1 | K26: =SUM(K20:K25) -> 12.9 | L26: =SUM(D26:K26) -> 66.9 | M26: =SUM(M20:M25) -> 72060000 | N26: =SUM(N20:N25) -> 0 | O26: =SUM(O20:O25) -> 0 | P26: =SUM(P20:P25) -> 66.9 | Q26: =SUM(Q20:Q25) -> 72060000
B27: 単価 | D27: 1000000 | E27: 1000000 | F27: 1000000 | G27: 1000000 | H27: 1000000 | I27: 1000000 | J27: 1000000 | K27: 1400000
B28: 金額 | D28: =D26*D27 -> 8100000 | E28: =E26*E27 -> 4900000 | F28: =F26*F27 -> 10500000 | G28: =G26*G27 -> 16400000 | H28: =H26*H27 -> 4300000 | I28: =I26*I27 -> 2700000 | J28: =J26*J27 -> 7100000 | K28: =K26*K27 -> 18060000
Q29: =Q26-Q12 -> 2960000
C31: 再見積もり（開発フェーズ以降）
C32: パターン | D32: クラウドアーキ基盤に移行 | R32: 備考
D33: アプリ | N33: DB | P33: 全体
B34: No. | C34: システム | D34: 調査・要件定義 | E34: 設計 | F34: 製造 | G34: 結合テスト | H34: システムテスト | I34: ユーザテスト | J34: 本番稼働 | K34: 管理 | L34: 工数計 | M34: 金額 | N34: 工数計 | O34: 金額 | P34: 工数計 | Q34: 金額
B35: 1 | C35: 数量確定システム（千葉・徳山） | F35: 3.2 | G35: 5.2 | H35: 1.4 | I35: 1 | J35: 2 | K35: 3.1 | L35: =SUM(D35:K35) -> 15.9 | M35: =SUM(D35:J35)*1000000+K35*1400000 -> 17140000 | N35: 0 | O35: 0 | P35: =SUM(L35:L39)+N35 -> 47.1 | Q35: =SUM(M35:M39)+O35 -> 50860000
B36: 2 | C36: 用役管理システム（千葉・徳山） | F36: 2.1 | G36: 3.1 | H36: 1.1 | I36: 1 | J36: 2 | K36: 2.2 | L36: =SUM(D36:K36) -> 11.5 | M36: =SUM(D36:J36)*1000000+K36*1400000 -> 12380000
B37: 3 | C37: 千葉化学品質管理システム | F37: 2.2 | G37: 5.5 | H37: 0.8 | I37: 0.7 | J37: 0.6 | K37: 2.3 | L37: =SUM(D37:K37) -> 12.1 | M37: =SUM(D37:J37)*1000000+K37*1400000 -> 13020000
B38: 4 | C38: ＬＭＰＰ包装システム | F38: 2.1 | G38: 1.2 | H38: 0.8 | I38: 0.7 | J38: 0.6 | K38: 1.7 | L38: =SUM(D38:K38) -> 7.1 | M38: =SUM(D38:J38)*1000000+K38*1400000 -> 7780000
B39: 5 | C39: 工場DB | J39: 0.4 | K39: 0.1 | L39: =SUM(D39:K39) -> 0.5 | M39: =SUM(D39:J39)*1000000+K39*1400000 -> 540000
B40: 6 | C40: ヤ－ド操業システム（千葉・徳山） | F40: 0.9 | G40: 1.4 | H40: 0.2 | I40: 0.3 | J40: 1.5 | K40: 0.7 | L40: =SUM(D40:K40) -> 5 | M40: =SUM(D40:J40)*1000000+K40*1400000 -> 5280000 | N40: 0 | O40: =SUM(O34:O39) -> 0 | P40: =SUM(L40:L40)+N40 -> 5 | Q40: =SUM(M40:M40)+O35 -> 5280000
B41: 計 | D41: =SUM(D35:D40) -> 0 | E41: =SUM(E35:E40) -> 0 | F41: =SUM(F35:F40) -> 10.5 | G41: =SUM(G35:G40) -> 16.4 | H41: =SUM(H35:H40) -> 4.3 | I41: =SUM(I35:I40) -> 3.7 | J41: =SUM(J35:J40) -> 7.1 | K41: =SUM(K35:K40) -> 10.1 | L41: =SUM(D41:K41) -> 52.1 | M41: =SUM(M35:M40) -> 56140000 | N41: =SUM(N35:N40) -> 0 | O41: =SUM(O35:O40) -> 0 | P41: =SUM(P35:P40) -> 52.1 | Q41: =SUM(Q35:Q40) -> 56140000
B42: 単価 | D42: 1000000 | E42: 1000000 | F42: 1000000 | G42: 1000000 | H42: 1000000 | I42: 1000000 | J42: 1000000 | K42: 1400000
B43: 金額 | D43: =D41*D42 -> 0 | E43: =E41*E42 -> 0 | F43: =F41*F42 -> 10500000 | G43: =G41*G42 -> 16400000 | H43: =H41*H42 -> 4300000 | I43: =I41*I42 -> 3700000 | J43: =J41*J42 -> 7100000 | K43: =K41*K42 -> 14140000
Q44: =Q41-Q27 -> 56140000
C45: 再見積もり（開発フェーズ）
C46: パターン | D46: クラウドアーキ基盤に移行 | R46: 備考
D47: アプリ | N47: DB | P47: 全体
B48: No. | C48: システム | D48: 調査・要件定義 | E48: 設計 | F48: 製造 | G48: 結合テスト | H48: システムテスト | I48: ユーザテスト | J48: 本番稼働 | K48: 管理 | L48: 工数計 | M48: 金額 | N48: 工数計 | O48: 金額 | P48: 工数計 | Q48: 金額
B49: 1 | C49: 数量確定システム（千葉・徳山） | F49: 3.2 | G49: 5.2 | K49: 1.6 | L49: =SUM(D49:K49) -> 10 | M49: =SUM(D49:J49)*1000000+K49*1400000 -> 10640000 | N49: 0 | O49: 0 | P49: =SUM(L49:L53)+N49 -> 29.8 | Q49: =SUM(M49:M53)+O49 -> 31880000
B50: 2 | C50: 用役管理システム（千葉・徳山） | F50: 2.1 | G50: 3.1 | K50: 1.2 | L50: =SUM(D50:K50) -> 6.4 | M50: =SUM(D50:J50)*1000000+K50*1400000 -> 6880000
B51: 3 | C51: 千葉化学品質管理システム | F51: 2.2 | G51: 5.5 | K51: 1.5 | L51: =SUM(D51:K51) -> 9.2 | M51: =SUM(D51:J51)*1000000+K51*1400000 -> 9800000
B52: 4 | C52: ＬＭＰＰ包装システム | F52: 2.1 | G52: 1.2 | K52: 0.9 | L52: =SUM(D52:K52) -> 4.2 | M52: =SUM(D52:J52)*1000000+K52*1400000 -> 4560000
B53: 5 | C53: 工場DB | L53: =SUM(D53:K53) -> 0 | M53: =SUM(D53:J53)*1000000+K53*1400000 -> 0
B54: 6 | C54: ヤ－ド操業システム（千葉・徳山） | F54: 0.9 | G54: 1.4 | K54: 0.3 | L54: =SUM(D54:K54) -> 2.6 | M54: =SUM(D54:J54)*1000000+K54*1400000 -> 2720000 | N54: 0 | O54: =SUM(O48:O53) -> 0 | P54: =SUM(L54:L54)+N54 -> 2.6 | Q54: =SUM(M54:M54)+O49 -> 2720000
B55: 計 | D55: =SUM(D49:D54) -> 0 | E55: =SUM(E49:E54) -> 0 | F55: =SUM(F49:F54) -> 10.5 | G55: =SUM(G49:G54) -> 16.4 | H55: =SUM(H49:H54) -> 0 | I55: =SUM(I49:I54) -> 0 | J55: =SUM(J49:J54) -> 0 | K55: =SUM(K49:K54) -> 5.5 | L55: =SUM(D55:K55) -> 32.4 | M55: =SUM(M49:M54) -> 34600000 | N55: =SUM(N49:N54) -> 0 | O55: =SUM(O49:O54) -> 0 | P55: =SUM(P49:P54) -> 32.4 | Q55: =SUM(Q49:Q54) -> 34600000
B56: 単価 | D56: 1000000 | E56: 1000000 | F56: 1000000 | G56: 1000000 | H56: 1000000 | I56: 1000000 | J56: 1000000 | K56: 1400000
B57: 金額 | D57: =D55*D56 -> 0 | E57: =E55*E56 -> 0 | F57: =F55*F56 -> 10500000 | G57: =G55*G56 -> 16400000 | H57: =H55*H56 -> 0 | I57: =I55*I56 -> 0 | J57: =J55*J56 -> 0 | K57: =K55*K56 -> 7700000
C60: 再見積もり（移行フェーズ）
C61: パターン | D61: クラウドアーキ基盤に移行 | R61: 備考
D62: アプリ | N62: DB | P62: 全体
B63: No. | C63: システム | D63: 調査・要件定義 | E63: 設計 | F63: 製造 | G63: 結合テスト | H63: システムテスト | I63: ユーザテスト | J63: 本番稼働 | K63: 管理 | L63: 工数計 | M63: 金額 | N63: 工数計 | O63: 金額 | P63: 工数計 | Q63: 金額
B64: 1 | C64: 数量確定システム（千葉・徳山） | H64: 1.4 | I64: 1 | J64: 2 | K64: 1.5 | L64: =SUM(D64:K64) -> 5.9 | M64: =SUM(D64:J64)*1000000+K64*1400000 -> 6500000 | N64: 0 | O64: 0 | P64: =SUM(L64:L68)+N64 -> 17.3 | Q64: =SUM(M64:M68)+O64 -> 18980000
B65: 2 | C65: 用役管理システム（千葉・徳山） | H65: 1.1 | I65: 1 | J65: 2 | K65: 1 | L65: =SUM(D65:K65) -> 5.1 | M65: =SUM(D65:J65)*1000000+K65*1400000 -> 5500000
B66: 3 | C66: 千葉化学品質管理システム | H66: 0.8 | I66: 0.7 | J66: 0.6 | K66: 0.8 | L66: =SUM(D66:K66) -> 2.9 | M66: =SUM(D66:J66)*1000000+K66*1400000 -> 3220000
B67: 4 | C67: ＬＭＰＰ包装システム | H67: 0.8 | I67: 0.7 | J67: 0.6 | K67: 0.8 | L67: =SUM(D67:K67) -> 2.9 | M67: =SUM(D67:J67)*1000000+K67*1400000 -> 3220000
B68: 5 | C68: 工場DB | J68: 0.4 | K68: 0.1 | L68: =SUM(D68:K68) -> 0.5 | M68: =SUM(D68:J68)*1000000+K68*1400000 -> 540000
B69: 6 | C69: ヤ－ド操業システム（千葉・徳山） | H69: 0.2 | I69: 0.3 | J69: 1.5 | K69: 0.4 | L69: =SUM(D69:K69) -> 2.4 | M69: =SUM(D69:J69)*1000000+K69*1400000 -> 2560000 | N69: 0 | O69: =SUM(O63:O68) -> 0 | P69: =SUM(L69:L69)+N69 -> 2.4 | Q69: =SUM(M69:M69)+O64 -> 2560000
B70: 計 | D70: =SUM(D64:D69) -> 0 | E70: =SUM(E64:E69) -> 0 | F70: =SUM(F64:F69) -> 0 | G70: =SUM(G64:G69) -> 0 | H70: =SUM(H64:H69) -> 4.3 | I70: =SUM(I64:I69) -> 3.7 | J70: =SUM(J64:J69) -> 7.1 | K70: =SUM(K64:K69) -> 4.6 | L70: =SUM(D70:K70) -> 19.7 | M70: =SUM(M64:M69) -> 21540000 | N70: =SUM(N64:N69) -> 0 | O70: =SUM(O64:O69) -> 0 | P70: =SUM(P64:P69) -> 19.7 | Q70: =SUM(Q64:Q69) -> 21540000
B71: 単価 | D71: 1000000 | E71: 1000000 | F71: 1000000 | G71: 1000000 | H71: 1000000 | I71: 1000000 | J71: 1000000 | K71: 1400000
B72: 金額 | D72: =D70*D71 -> 0 | E72: =E70*E71 -> 0 | F72: =F70*F71 -> 0 | G72: =G70*G71 -> 0 | H72: =H70*H71 -> 4300000 | I72: =I70*I71 -> 3700000 | J72: =J70*J71 -> 7100000 | K72: =K70*K71 -> 6440000
K75: 検算
L76: システム | M76: 開発＋移行 | N76: 開発以降
L77: 数量確定システム（千葉・徳山） | M77: =M49+M64 -> 17140000 | N77: =M35 -> 17140000
L78: 用役管理システム（千葉・徳山） | M78: =M50+M65 -> 12380000 | N78: =M36 -> 12380000
L79: 千葉化学品質管理システム | M79: =M51+M66 -> 13020000 | N79: =M37 -> 13020000
L80: ＬＭＰＰ包装システム | M80: =M52+M67 -> 7780000 | N80: =M38 -> 7780000
L81: 工場DB | M81: =M53+M68 -> 540000 | N81: =M39 -> 540000
L82: ヤ－ド操業システム（千葉・徳山） | M82: =M54+M69 -> 5280000 | N82: =M40 -> 5280000
M83: =SUM(M77:M82) -> 56140000 | N83: =SUM(N77:N82) -> 56140000

Sheet スケジュール案・要員計画 (開発フェーズ_月別) (2)
A2: システム | B2: 担当 | C2: 2024年 | O2: 2025年 | S2: 202６年
C3: 1月 | D3: 2月 | E3: 3月 | F3: 4月 | G3: 5月 | H3: 6月 | I3: 7月 | J3: 8月 | K3: 9月 | L3: 10月 | M3: 11月 | N3: 12月 | O3: 9月 | P3: 10月 | Q3: 11月 | R3: 12月 | S3: １月 | T3: ２月 | U3: ３月
A4: マイルストン | K4: ★縮小共通基盤構築 | P4: ★新共通基盤構築 | U4: ★館林DC廃止
A5: 数量確定システム（千葉・徳山）
A6: 用役管理システム（千葉・徳山）
A7: 千葉化学品質管理システム
A8: ＬＭＰＰ包装システム
A9: ヤード操業システム
A10: 工場DB
B12: 本番リリースタイミング
A13: 千葉化学品質管理システム | B13: 2026年2月上旬
A14: ＬＭＰＰ包装システム | B14: 2026年2月上旬
A15: 工場DB | B15: 2026年2月上旬
A16: ヤード操業システム（千葉・徳山） | B16: 2026年2月中旬
A17: 数量確定システム（千葉・徳山） | B17: 2026年2月下旬
A18: 用役管理システム（千葉・徳山） | B18: 2026年2月下旬
A20: 想定要員数(月単位)
A21: 管理 | Q21: 3 | R21: 3 | S21: 1.5 | T21: 1.5 | U21: 1.5 | V21: =SUM(O21:U21) -> 10.5
A22: 数量確定システム（千葉・徳山） | Q22: 5.6 | R22: 4 | S22: 1 | T22: 1 | U22: 1 | V22: =SUM(O22:U22) -> 12.6
A23: 用役管理システム（千葉・徳山） | Q23: 3.6 | R23: 2.5 | S23: 1 | T23: 1 | U23: 1 | V23: =SUM(O23:U23) -> 9.1
A24: 千葉化学品質管理システム | Q24: 4 | R24: 3.5 | S24: 1 | T24: 1 | V24: =SUM(O24:U24) -> 9.5
A25: ＬＭＰＰ包装システム | Q25: 2 | R25: 2 | S25: 0.5 | T25: 0.5 | V25: =SUM(O25:U25) -> 5
A26: 工場DB | Q26: 0 | R26: 0 | S26: 0 | T26: 0.4 | V26: =SUM(O26:U26) -> 0.4
A27: ヤ－ド操業システム（千葉・徳山） | Q27: 1.5 | R27: 0.5 | S27: 1 | T27: 1 | V27: =SUM(O27:U27) -> 4
A28: 合計 | C28: =SUM(C22:C27) -> 0 | D28: =SUM(D22:D27) -> 0 | E28: =SUM(E22:E27) -> 0 | F28: =SUM(F22:F27) -> 0 | G28: =SUM(G22:G27) -> 0 | H28: =SUM(H22:H27) -> 0 | I28: =SUM(I22:I27) -> 0 | J28: =SUM(J22:J27) -> 0 | ... N28: =SUM(N22:N27) -> 0 | O28: =SUM(O21:O27) -> 0 | P28: =SUM(P21:P27) -> 0 | Q28: =SUM(Q21:Q27) -> 19.7 | R28: =SUM(R21:R27) -> 15.5 | S28: =SUM(S21:S27) -> 6 | T28: =SUM(T21:T27) -> 6.4 | U28: =SUM(U21:U27) -> 3.5 | V28: =SUM(O28:U28) -> 51.1
R29: 7.75
A31: 想定要員数(工程単位) | O31: 調査・要件定義 | P31: 設計 | Q31: 製造 | R31: 結合テスト | S31: システムテスト | T31: ユーザテスト | U31: 本番稼働
A32: 管理 | Q32: 2.6 | R32: 3.4 | S32: 1.5 | T32: 1.1 | U32: 1.9
A33: 数量確定システム（千葉・徳山） | Q33: 3.2 | R33: 5.2 | S33: 1.4 | T33: 0.8 | U33: 2
A34: 用役管理システム（千葉・徳山） | Q34: 2.1 | R34: 3.1 | S34: 1.1 | T34: 0.8 | U34: 2
A35: 千葉化学品質管理システム | Q35: 2.2 | R35: 5.5 | S35: 0.8 | T35: 0.5 | U35: 0.5
A36: ＬＭＰＰ包装システム | Q36: 2.1 | R36: 1.2 | S36: 0.8 | T36: 0.5 | U36: 0.5
A37: 工場DB | Q37: 0 | R37: 0 | S37: 0 | T37: 0.1 | U37: 0.3
A38: ヤ－ド操業システム（千葉・徳山） | Q38: 0.9 | R38: 1.4 | S38: 0.2 | T38: 0.1 | U38: 1.3
A39: 合計 | C39: =SUM(C34:C38) -> 0 | D39: =SUM(D34:D38) -> 0 | E39: =SUM(E34:E38) -> 0 | F39: =SUM(F34:F38) -> 0 | G39: =SUM(G34:G38) -> 0 | H39: =SUM(H34:H38) -> 0 | I39: =SUM(I34:I38) -> 0 | J39: =SUM(J34:J38) -> 0 | ... N39: =SUM(N34:N38) -> 0 | O39: =SUM(O33:O38) -> 0 | P39: =SUM(P33:P38) -> 0 | Q39: =SUM(Q32:Q38) -> 13.1 | R39: =SUM(R32:R38) -> 19.8 | S39: =SUM(S32:S38) -> 5.8 | T39: =SUM(T32:T38) -> 3.9 | U39: =SUM(U32:U38) -> 8.5
A41: 要員 | X41: 要員人数 | Z41: 計画(月) | AB41: 計画(工程)
A42: 管理（工場） | B42: 野村 | Q42: 0.5 | R42: 0.5 | S42: 0.5 | T42: 0.5 | U42: 0.25 | V42: =SUM(O42:U42) -> 2.25 | W42: 管理（工場） | X42: =SUMIF($A$42:$A$77,W42,$V$42:$V$77) -> 11.5 | Y42: 人月 | Z42: =V21 -> 10.5 | AA42: 人月 | AB42: 10.5
A43: 管理（工場） | B43: 石井 | Q43: 0.5 | R43: 0.5 | S43: 0.5 | T43: 0.5 | U43: 0.25 | V43: =SUM(O43:U43) -> 2.25 | W43: 数量確定 | X43: =SUMIF($A$42:$A$77,W43,$V$42:$V$77) -> 11.75 | Y43: 人月 | Z43: =V22 -> 12.6 | AA43: 人月 | AB43: 12.6
A44: 管理（工場） | B44: グエン・タン・ドゥオック | Q44: 1 | R44: 1 | S44: 1 | T44: 1 | U44: 0.5 | V44: =SUM(O44:U44) -> 4.5 | W44: 用役管理 | X44: =SUMIF($A$42:$A$77,W44,$V$42:$V$77) -> 9.25 | Y44: 人月 | Z44: =V23 -> 9.1 | AA44: 人月 | AB44: 9.1
A45: 数量確定 | B45: 天川 | Q45: 0.5 | R45: 0.5 | S45: 0.5 | T45: 0.5 | V45: =SUM(O45:U45) -> 2 | W45: 千葉化学 | X45: =SUMIF($A$42:$A$77,W45,$V$42:$V$77) -> 12 | Y45: 人月 | Z45: =V24 -> 9.5 | AA45: 人月 | AB45: 9.5
A46: 数量確定 | B46: グエン・チュン・グエン | Q46: 0.5 | R46: 0.5 | S46: 0.5 | T46: 0.5 | U46: 0.25 | V46: =SUM(O46:U46) -> 2.25 | W46: 包装 | X46: =SUMIF($A$42:$A$77,W46,$V$42:$V$77) -> 8 | Y46: 人月 | Z46: =V25 -> 5 | AA46: 人月 | AB46: 5
A47: 数量確定 | B47: ドー・ﾘｲ・アイン・トゥ | Q47: 1 | R47: 1 | V47: =SUM(O47:U47) -> 2 | W47: 工場DB | X47: =SUMIF($A$42:$A$77,W47,$V$42:$V$77) -> 0.4 | Y47: 人月 | Z47: =V26 -> 0.4 | AA47: 人月 | AB47: 0.4
A48: 数量確定 | B48: レ・ファム・バオ・ロック | Q48: 1 | R48: 1 | V48: =SUM(O48:U48) -> 2 | W48: ヤード操業 | X48: =SUMIF($A$42:$A$77,W48,$V$42:$V$77) -> 4 | Y48: 人月 | Z48: =V27 -> 4 | AA48: 人月 | AB48: 4
A49: 数量確定 | B49: VT1 | Q49: 0.5 | R49: 0.5 | V49: =SUM(O49:U49) -> 1 | W49: コミュニケータ | X49: =SUMIF($A$42:$A$77,W49,$V$42:$V$77) -> 3 | Y49: 人月 | AA49: 人月
A50: 用役管理 | B50: 天川 | Q50: 0.5 | R50: 0.5 | S50: 0.5 | T50: 0.5 | V50: =SUM(O50:U50) -> 2 | W50: ブリッジ | X50: =SUMIF($A$42:$A$77,W50,$V$42:$V$77) -> 3.25 | Y50: 人月 | AA50: 人月
A51: 用役管理 | B51: グエン・チュン・グエン | Q51: 0.5 | R51: 0.5 | S51: 0.5 | T51: 0.5 | U51: 0.25 | V51: =SUM(O51:U51) -> 2.25 | X51: =SUM(X42:X50) -> 63.15 | Y51: 人月 | Z51: =SUM(Z42:Z50) -> 51.1 | AB51: =SUM(AB42:AB50) -> 51.1
A52: 用役管理 | B52: ドー・グエン・ティ・トゥイ・ズイ | Q52: 1 | R52: 1 | V52: =SUM(O52:U52) -> 2
A53: 用役管理 | B53: VT1 | Q53: 0.5 | V53: =SUM(O53:U53) -> 0.5
A54: 千葉化学 | B54: 馬場 | Q54: 0.5 | R54: 0.5 | S54: 0.5 | T54: 0.5 | V54: =SUM(O54:U54) -> 2
A55: 千葉化学 | B55: ズオン・ゴック・フー | Q55: 0.5 | R55: 0.5 | S55: 0.5 | T55: 0.5 | V55: =SUM(O55:U55) -> 2
A56: 千葉化学 | B56: グエン・ダン・ティエン | Q56: 1 | R56: 1 | V56: =SUM(O56:U56) -> 2
A57: 千葉化学 | B57: ファン・グエン・タム | Q57: 1 | R57: 1 | V57: =SUM(O57:U57) -> 2
A58: 千葉化学 | B58: VT2 | Q58: 0.5 | R58: 0.5 | V58: =SUM(O58:U58) -> 1
A59: 千葉化学 | B59: VT3 | R59: 1 | V59: =SUM(O59:U59) -> 1
A60: 包装 | B60: 馬場 | Q60: 0.5 | R60: 0.5 | S60: 0.5 | T60: 0.5 | V60: =SUM(O60:U60) -> 2
A61: 包装 | B61: ズオン・ゴック・フー | Q61: 0.5 | R61: 0.5 | S61: 0.5 | T61: 0.5 | V61: =SUM(O61:U61) -> 2
A62: 包装 | B62: VT2 | Q62: 0.5 | R62: 0.5 | V62: =SUM(O62:U62) -> 1
A63: 包装 | B63: VT4 | R63: 1 | V63: =SUM(O63:U63) -> 1
A64: ヤード操業 | B64: チャン・クォック・ズイ | F64: 2 | G64: 2 | H64: 5 | I64: 5 | J64: 5 | K64: 5 | L64: 5 | M64: 5 | N64: 5 | Q64: 1 | R64: 1 | S64: 1 | T64: 1 | V64: =SUM(O64:U64) -> 4
A65: 工場DB | B65: 天川 | F65: 2 | G65: 2 | H65: 5 | I65: 5 | J65: 5 | K65: 5 | L65: 5 | M65: 5 | N65: 5 | T65: 0.2 | V65: =SUM(O65:U65) -> 0.2
A66: 工場DB | B66: 馬場 | F66: 2 | G66: 2 | H66: 5 | I66: 5 | J66: 5 | K66: 5 | L66: 5 | M66: 5 | N66: 5 | T66: 0.2 | V66: =SUM(O66:U66) -> 0.2
A67: コミュニケータ | B67: グエン・ミン・トー | F67: 2 | G67: 2 | H67: 5 | I67: 5 | J67: 5 | K67: 5 | L67: 5 | M67: 5 | N67: 5 | Q67: 1 | R67: 1 | S67: 0.5 | T67: 0.5 | V67: =SUM(O67:U67) -> 3
A68: ブリッジ | B68: チュン | F68: 2 | G68: 2 | H68: 5 | I68: 5 | J68: 5 | K68: 5 | L68: 5 | M68: 5 | N68: 5 | Q68: 0.5 | R68: 0.5 | V68: =SUM(O68:U68) -> 1
A69: ブリッジ | B69: チャンホアンフック | F69: 2 | G69: 2 | H69: 5 | I69: 5 | J69: 5 | K69: 5 | L69: 5 | M69: 5 | N69: 5 | V69: =SUM(O69:U69) -> 0
A70: ブリッジ | B70: ブイクアンティエン | F70: 2 | G70: 2 | H70: 5 | I70: 5 | J70: 5 | K70: 5 | L70: 5 | M70: 5 | N70: 5 | Q70: 0.5 | R70: 0.5 | S70: 0.5 | T70: 0.5 | U70: 0.25 | V70: =SUM(O70:U70) -> 2.25
A71: 管理（工場） | B71: 黒田智之 | Q71: 0.5 | R71: 0.5 | S71: 0.5 | T71: 0.5 | U71: 0.5 | V71: =SUM(O71:U71) -> 2.5
A72: 数量確定 | B72: 吉田 | Q72: 0.5 | R72: 0.5 | S72: 0.5 | T72: 0.5 | U72: 0.5 | V72: =SUM(O72:U72) -> 2.5
A73: 用役管理 | B73: 吉田 | Q73: 0.5 | R73: 0.5 | S73: 0.5 | T73: 0.5 | U73: 0.5 | V73: =SUM(O73:U73) -> 2.5
A74: 千葉化学 | B74: 菊間 | Q74: 0.5 | R74: 0.5 | S74: 0.5 | T74: 0.5 | V74: =SUM(O74:U74) -> 2
A75: 包装 | B75: 菊間 | Q75: 0.5 | R75: 0.5 | S75: 0.5 | T75: 0.5 | V75: =SUM(O75:U75) -> 2
B76: 小計 | C76: =SUM(C46:C64) -> 0 | D76: =SUM(D46:D64) -> 0 | E76: =SUM(E46:E64) -> 0 | F76: =SUM(F46:F64) -> 2 | G76: =SUM(G46:G64) -> 2 | H76: =SUM(H46:H64) -> 5 | I76: =SUM(I46:I64) -> 5 | J76: =SUM(J46:J64) -> 5 | ... N76: =SUM(N46:N64) -> 5 | Q76: =SUM(Q42:Q75) -> 18.5 | R76: =SUM(R42:R75) -> 20 | S76: =SUM(S42:S75) -> 10.5 | T76: =SUM(T42:T75) -> 10.9 | U76: =SUM(U42:U75) -> 3.25 | V76: =SUM(O76:U76) -> 63.15
B77: 合計 | C77: =SUM(C51:C70) -> 0 | D77: =SUM(D51:D70) -> 0 | E77: =SUM(E51:E70) -> 0 | F77: =SUM(F51:F70) -> 14 | G77: =SUM(G51:G70) -> 14 | H77: =SUM(H51:H70) -> 35 | I77: =SUM(I51:I70) -> 35 | J77: =SUM(J51:J70) -> 35 | ... N77: =SUM(N51:N70) -> 35 | O77: =SUM(O76:O76) -> 0 | P77: =SUM(P76:P76) -> 0 | Q77: =SUM(Q76:Q76) -> 18.5 | R77: =SUM(R76:R76) -> 20 | S77: =SUM(S76:S76) -> 10.5 | T77: =SUM(T76:T76) -> 10.9 | U77: =SUM(U76:U76) -> 3.25 | V77: =SUM(O77:U77) -> 63.15
A79: 売上
A80: 野村 | B80: 1000000 | O80: =SUMIF($B$28:$B$75,$A80,O$28:O$75)*$B80 -> 0 | P80: =SUMIF($B$28:$B$75,$A80,P$28:P$75)*$B80 -> 0 | Q80: =SUMIF($B$28:$B$75,$A80,Q$28:Q$75)*$B80 -> 500000 | R80: =SUMIF($B$28:$B$75,$A80,R$28:R$75)*$B80 -> 500000 | S80: =SUMIF($B$28:$B$75,$A80,S$28:S$75)*$B80 -> 500000 | T80: =SUMIF($B$28:$B$75,$A80,T$28:T$75)*$B80 -> 500000 | U80: =SUMIF($B$28:$B$75,$A80,U$28:U$75)*$B80 -> 250000
A81: 石井 | B81: 1000000 | O81: =SUMIF($B$28:$B$75,$A81,O$28:O$75)*$B81 -> 0 | P81: =SUMIF($B$28:$B$75,$A81,P$28:P$75)*$B81 -> 0 | Q81: =SUMIF($B$28:$B$75,$A81,Q$28:Q$75)*$B81 -> 500000 | R81: =SUMIF($B$28:$B$75,$A81,R$28:R$75)*$B81 -> 500000 | S81: =SUMIF($B$28:$B$75,$A81,S$28:S$75)*$B81 -> 500000 | T81: =SUMIF($B$28:$B$75,$A81,T$28:T$75)*$B81 -> 500000 | U81: =SUMIF($B$28:$B$75,$A81,U$28:U$75)*$B81 -> 250000
A82: 天川 | B82: 1000000 | O82: =SUMIF($B$28:$B$75,$A82,O$28:O$75)*$B82 -> 0 | P82: =SUMIF($B$28:$B$75,$A82,P$28:P$75)*$B82 -> 0 | Q82: =SUMIF($B$28:$B$75,$A82,Q$28:Q$75)*$B82 -> 1000000 | R82: =SUMIF($B$28:$B$75,$A82,R$28:R$75)*$B82 -> 1000000 | S82: =SUMIF($B$28:$B$75,$A82,S$28:S$75)*$B82 -> 1000000 | T82: =SUMIF($B$28:$B$75,$A82,T$28:T$75)*$B82 -> 1200000 | U82: =SUMIF($B$28:$B$75,$A82,U$28:U$75)*$B82 -> 0
A83: 馬場 | B83: 1000000 | O83: =SUMIF($B$28:$B$75,$A83,O$28:O$75)*$B83 -> 0 | P83: =SUMIF($B$28:$B$75,$A83,P$28:P$75)*$B83 -> 0 | Q83: =SUMIF($B$28:$B$75,$A83,Q$28:Q$75)*$B83 -> 1000000 | R83: =SUMIF($B$28:$B$75,$A83,R$28:R$75)*$B83 -> 1000000 | S83: =SUMIF($B$28:$B$75,$A83,S$28:S$75)*$B83 -> 1000000 | T83: =SUMIF($B$28:$B$75,$A83,T$28:T$75)*$B83 -> 1200000 | U83: =SUMIF($B$28:$B$75,$A83,U$28:U$75)*$B83 -> 0
A84: グエン・タン・ドゥオック | B84: 700000 | O84: =SUMIF($B$28:$B$75,$A84,O$28:O$75)*$B84 -> 0 | P84: =SUMIF($B$28:$B$75,$A84,P$28:P$75)*$B84 -> 0 | Q84: =SUMIF($B$28:$B$75,$A84,Q$28:Q$75)*$B84 -> 700000 | R84: =SUMIF($B$28:$B$75,$A84,R$28:R$75)*$B84 -> 700000 | S84: =SUMIF($B$28:$B$75,$A84,S$28:S$75)*$B84 -> 700000 | T84: =SUMIF($B$28:$B$75,$A84,T$28:T$75)*$B84 -> 700000 | U84: =SUMIF($B$28:$B$75,$A84,U$28:U$75)*$B84 -> 350000
A85: グエン・チュン・グエン | B85: 700000 | O85: =SUMIF($B$28:$B$75,$A85,O$28:O$75)*$B85 -> 0 | P85: =SUMIF($B$28:$B$75,$A85,P$28:P$75)*$B85 -> 0 | Q85: =SUMIF($B$28:$B$75,$A85,Q$28:Q$75)*$B85 -> 700000 | R85: =SUMIF($B$28:$B$75,$A85,R$28:R$75)*$B85 -> 700000 | S85: =SUMIF($B$28:$B$75,$A85,S$28:S$75)*$B85 -> 700000 | T85: =SUMIF($B$28:$B$75,$A85,T$28:T$75)*$B85 -> 700000 | U85: =SUMIF($B$28:$B$75,$A85,U$28:U$75)*$B85 -> 350000
A86: ドー・ﾘｲ・アイン・トゥ | B86: 700000 | O86: =SUMIF($B$28:$B$75,$A86,O$28:O$75)*$B86 -> 0 | P86: =SUMIF($B$28:$B$75,$A86,P$28:P$75)*$B86 -> 0 | Q86: =SUMIF($B$28:$B$75,$A86,Q$28:Q$75)*$B86 -> 700000 | R86: =SUMIF($B$28:$B$75,$A86,R$28:R$75)*$B86 -> 700000 | S86: =SUMIF($B$28:$B$75,$A86,S$28:S$75)*$B86 -> 0 | T86: =SUMIF($B$28:$B$75,$A86,T$28:T$75)*$B86 -> 0 | U86: =SUMIF($B$28:$B$75,$A86,U$28:U$75)*$B86 -> 0
A87: レ・ファム・バオ・ロック | B87: 700000 | O87: =SUMIF($B$28:$B$75,$A87,O$28:O$75)*$B87 -> 0 | P87: =SUMIF($B$28:$B$75,$A87,P$28:P$75)*$B87 -> 0 | Q87: =SUMIF($B$28:$B$75,$A87,Q$28:Q$75)*$B87 -> 700000 | R87: =SUMIF($B$28:$B$75,$A87,R$28:R$75)*$B87 -> 700000 | S87: =SUMIF($B$28:$B$75,$A87,S$28:S$75)*$B87 -> 0 | T87: =SUMIF($B$28:$B$75,$A87,T$28:T$75)*$B87 -> 0 | U87: =SUMIF($B$28:$B$75,$A87,U$28:U$75)*$B87 -> 0
A88: ズオン・ゴック・フー | B88: 700000 | O88: =SUMIF($B$28:$B$75,$A88,O$28:O$75)*$B88 -> 0 | P88: =SUMIF($B$28:$B$75,$A88,P$28:P$75)*$B88 -> 0 | Q88: =SUMIF($B$28:$B$75,$A88,Q$28:Q$75)*$B88 -> 700000 | R88: =SUMIF($B$28:$B$75,$A88,R$28:R$75)*$B88 -> 700000 | S88: =SUMIF($B$28:$B$75,$A88,S$28:S$75)*$B88 -> 700000 | T88: =SUMIF($B$28:$B$75,$A88,T$28:T$75)*$B88 -> 700000 | U88: =SUMIF($B$28:$B$75,$A88,U$28:U$75)*$B88 -> 0
A89: チャン・クォック・ズイ | B89: 700000 | O89: =SUMIF($B$28:$B$75,$A89,O$28:O$75)*$B89 -> 0 | P89: =SUMIF($B$28:$B$75,$A89,P$28:P$75)*$B89 -> 0 | Q89: =SUMIF($B$28:$B$75,$A89,Q$28:Q$75)*$B89 -> 700000 | R89: =SUMIF($B$28:$B$75,$A89,R$28:R$75)*$B89 -> 700000 | S89: =SUMIF($B$28:$B$75,$A89,S$28:S$75)*$B89 -> 700000 | T89: =SUMIF($B$28:$B$75,$A89,T$28:T$75)*$B89 -> 700000 | U89: =SUMIF($B$28:$B$75,$A89,U$28:U$75)*$B89 -> 0
A90: ドー・グエン・ティ・トゥイ・ズイ | B90: 700000 | O90: =SUMIF($B$28:$B$75,$A90,O$28:O$75)*$B90 -> 0 | P90: =SUMIF($B$28:$B$75,$A90,P$28:P$75)*$B90 -> 0 | Q90: =SUMIF($B$28:$B$75,$A90,Q$28:Q$75)*$B90 -> 700000 | R90: =SUMIF($B$28:$B$75,$A90,R$28:R$75)*$B90 -> 700000 | S90: =SUMIF($B$28:$B$75,$A90,S$28:S$75)*$B90 -> 0 | T90: =SUMIF($B$28:$B$75,$A90,T$28:T$75)*$B90 -> 0 | U90: =SUMIF($B$28:$B$75,$A90,U$28:U$75)*$B90 -> 0
A91: グエン・ダン・ティエン | B91: 700000 | O91: =SUMIF($B$28:$B$75,$A91,O$28:O$75)*$B91 -> 0 | P91: =SUMIF($B$28:$B$75,$A91,P$28:P$75)*$B91 -> 0 | Q91: =SUMIF($B$28:$B$75,$A91,Q$28:Q$75)*$B91 -> 700000 | R91: =SUMIF($B$28:$B$75,$A91,R$28:R$75)*$B91 -> 700000 | S91: =SUMIF($B$28:$B$75,$A91,S$28:S$75)*$B91 -> 0 | T91: =SUMIF($B$28:$B$75,$A91,T$28:T$75)*$B91 -> 0 | U91: =SUMIF($B$28:$B$75,$A91,U$28:U$75)*$B91 -> 0
A92: ファン・グエン・タム | B92: 700000 | O92: =SUMIF($B$28:$B$75,$A92,O$28:O$75)*$B92 -> 0 | P92: =SUMIF($B$28:$B$75,$A92,P$28:P$75)*$B92 -> 0 | Q92: =SUMIF($B$28:$B$75,$A92,Q$28:Q$75)*$B92 -> 700000 | R92: =SUMIF($B$28:$B$75,$A92,R$28:R$75)*$B92 -> 700000 | S92: =SUMIF($B$28:$B$75,$A92,S$28:S$75)*$B92 -> 0 | T92: =SUMIF($B$28:$B$75,$A92,T$28:T$75)*$B92 -> 0 | U92: =SUMIF($B$28:$B$75,$A92,U$28:U$75)*$B92 -> 0
A93: グエン・ミン・トー | B93: 700000 | F93: 2 | G93: 2 | H93: 5 | I93: 5 | J93: 5 | K93: 5 | L93: 5 | M93: 5 | N93: 5 | O93: =SUMIF($B$28:$B$75,$A93,O$28:O$75)*$B93 -> 0 | P93: =SUMIF($B$28:$B$75,$A93,P$28:P$75)*$B93 -> 0 | Q93: =SUMIF($B$28:$B$75,$A93,Q$28:Q$75)*$B93 -> 700000 | R93: =SUMIF($B$28:$B$75,$A93,R$28:R$75)*$B93 -> 700000 | S93: =SUMIF($B$28:$B$75,$A93,S$28:S$75)*$B93 -> 350000 | T93: =SUMIF($B$28:$B$75,$A93,T$28:T$75)*$B93 -> 350000 | U93: =SUMIF($B$28:$B$75,$A93,U$28:U$75)*$B93 -> 0
A94: チュン | B94: 1000000 | F94: 2 | G94: 2 | H94: 5 | I94: 5 | J94: 5 | K94: 5 | L94: 5 | M94: 5 | N94: 5 | O94: =SUMIF($B$28:$B$75,$A94,O$28:O$75)*$B94 -> 0 | P94: =SUMIF($B$28:$B$75,$A94,P$28:P$75)*$B94 -> 0 | Q94: =SUMIF($B$28:$B$75,$A94,Q$28:Q$75)*$B94 -> 500000 | R94: =SUMIF($B$28:$B$75,$A94,R$28:R$75)*$B94 -> 500000 | S94: =SUMIF($B$28:$B$75,$A94,S$28:S$75)*$B94 -> 0 | T94: =SUMIF($B$28:$B$75,$A94,T$28:T$75)*$B94 -> 0 | U94: =SUMIF($B$28:$B$75,$A94,U$28:U$75)*$B94 -> 0
A95: チャンホアンフック | B95: 800000 | F95: 2 | G95: 2 | H95: 5 | I95: 5 | J95: 5 | K95: 5 | L95: 5 | M95: 5 | N95: 5 | O95: =SUMIF($B$28:$B$75,$A95,O$28:O$75)*$B95 -> 0 | P95: =SUMIF($B$28:$B$75,$A95,P$28:P$75)*$B95 -> 0 | Q95: =SUMIF($B$28:$B$75,$A95,Q$28:Q$75)*$B95 -> 0 | R95: =SUMIF($B$28:$B$75,$A95,R$28:R$75)*$B95 -> 0 | S95: =SUMIF($B$28:$B$75,$A95,S$28:S$75)*$B95 -> 0 | T95: =SUMIF($B$28:$B$75,$A95,T$28:T$75)*$B95 -> 0 | U95: =SUMIF($B$28:$B$75,$A95,U$28:U$75)*$B95 -> 0
A96: ブイクアンティエン | B96: 1000000 | F96: 2 | G96: 2 | H96: 5 | I96: 5 | J96: 5 | K96: 5 | L96: 5 | M96: 5 | N96: 5 | O96: =SUMIF($B$28:$B$75,$A96,O$28:O$75)*$B96 -> 0 | P96: =SUMIF($B$28:$B$75,$A96,P$28:P$75)*$B96 -> 0 | Q96: =SUMIF($B$28:$B$75,$A96,Q$28:Q$75)*$B96 -> 500000 | R96: =SUMIF($B$28:$B$75,$A96,R$28:R$75)*$B96 -> 500000 | S96: =SUMIF($B$28:$B$75,$A96,S$28:S$75)*$B96 -> 500000 | T96: =SUMIF($B$28:$B$75,$A96,T$28:T$75)*$B96 -> 500000 | U96: =SUMIF($B$28:$B$75,$A96,U$28:U$75)*$B96 -> 250000
A97: VT1 | B97: 700000 | F97: 2 | G97: 2 | H97: 5 | I97: 5 | J97: 5 | K97: 5 | L97: 5 | M97: 5 | N97: 5 | O97: =SUMIF($B$28:$B$75,$A97,O$28:O$75)*$B97 -> 0 | P97: =SUMIF($B$28:$B$75,$A97,P$28:P$75)*$B97 -> 0 | Q97: =SUMIF($B$28:$B$75,$A97,Q$28:Q$75)*$B97 -> 700000 | R97: =SUMIF($B$28:$B$75,$A97,R$28:R$75)*$B97 -> 350000 | S97: =SUMIF($B$28:$B$75,$A97,S$28:S$75)*$B97 -> 0 | T97: =SUMIF($B$28:$B$75,$A97,T$28:T$75)*$B97 -> 0 | U97: =SUMIF($B$28:$B$75,$A97,U$28:U$75)*$B97 -> 0
A98: VT2 | B98: 700000 | F98: 2 | G98: 2 | H98: 5 | I98: 5 | J98: 5 | K98: 5 | L98: 5 | M98: 5 | N98: 5 | O98: =SUMIF($B$28:$B$75,$A98,O$28:O$75)*$B98 -> 0 | P98: =SUMIF($B$28:$B$75,$A98,P$28:P$75)*$B98 -> 0 | Q98: =SUMIF($B$28:$B$75,$A98,Q$28:Q$75)*$B98 -> 700000 | R98: =SUMIF($B$28:$B$75,$A98,R$28:R$75)*$B98 -> 700000 | S98: =SUMIF($B$28:$B$75,$A98,S$28:S$75)*$B98 -> 0 | T98: =SUMIF($B$28:$B$75,$A98,T$28:T$75)*$B98 -> 0 | U98: =SUMIF($B$28:$B$75,$A98,U$28:U$75)*$B98 -> 0
A99: VT3 | B99: 700000 | F99: 2 | G99: 2 | H99: 5 | I99: 5 | J99: 5 | K99: 5 | L99: 5 | M99: 5 | N99: 5 | O99: =SUMIF($B$28:$B$75,$A99,O$28:O$75)*$B99 -> 0 | P99: =SUMIF($B$28:$B$75,$A99,P$28:P$75)*$B99 -> 0 | Q99: =SUMIF($B$28:$B$75,$A99,Q$28:Q$75)*$B99 -> 0 | R99: =SUMIF($B$28:$B$75,$A99,R$28:R$75)*$B99 -> 700000 | S99: =SUMIF($B$28:$B$75,$A99,S$28:S$75)*$B99 -> 0 | T99: =SUMIF($B$28:$B$75,$A99,T$28:T$75)*$B99 -> 0 | U99: =SUMIF($B$28:$B$75,$A99,U$28:U$75)*$B99 -> 0
A100: VT4 | B100: 700000 | F100: 2 | G100: 2 | H100: 5 | I100: 5 | J100: 5 | K100: 5 | L100: 5 | M100: 5 | N100: 5 | O100: =SUMIF($B$28:$B$75,$A100,O$28:O$75)*$B100 -> 0 | P100: =SUMIF($B$28:$B$75,$A100,P$28:P$75)*$B100 -> 0 | Q100: =SUMIF($B$28:$B$75,$A100,Q$28:Q$75)*$B100 -> 0 | R100: =SUMIF($B$28:$B$75,$A100,R$28:R$75)*$B100 -> 700000 | S100: =SUMIF($B$28:$B$75,$A100,S$28:S$75)*$B100 -> 0 | T100: =SUMIF($B$28:$B$75,$A100,T$28:T$75)*$B100 -> 0 | U100: =SUMIF($B$28:$B$75,$A100,U$28:U$75)*$B100 -> 0
A101: 黒田智之 | B101: 1000000 | F101: 2 | G101: 2 | H101: 5 | I101: 5 | J101: 5 | K101: 5 | L101: 5 | M101: 5 | N101: 5 | O101: =SUMIF($B$28:$B$75,$A101,O$28:O$75)*$B101 -> 0 | P101: =SUMIF($B$28:$B$75,$A101,P$28:P$75)*$B101 -> 0 | Q101: =SUMIF($B$28:$B$75,$A101,Q$28:Q$75)*$B101 -> 500000 | R101: =SUMIF($B$28:$B$75,$A101,R$28:R$75)*$B101 -> 500000 | S101: =SUMIF($B$28:$B$75,$A101,S$28:S$75)*$B101 -> 500000 | T101: =SUMIF($B$28:$B$75,$A101,T$28:T$75)*$B101 -> 500000 | U101: =SUMIF($B$28:$B$75,$A101,U$28:U$75)*$B101 -> 500000
A102: 吉田 | B102: 1000000 | F102: 2 | G102: 2 | H102: 5 | I102: 5 | J102: 5 | K102: 5 | L102: 5 | M102: 5 | N102: 5 | O102: =SUMIF($B$28:$B$75,$A102,O$28:O$75)*$B102 -> 0 | P102: =SUMIF($B$28:$B$75,$A102,P$28:P$75)*$B102 -> 0 | Q102: =SUMIF($B$28:$B$75,$A102,Q$28:Q$75)*$B102 -> 1000000 | R102: =SUMIF($B$28:$B$75,$A102,R$28:R$75)*$B102 -> 1000000 | S102: =SUMIF($B$28:$B$75,$A102,S$28:S$75)*$B102 -> 1000000 | T102: =SUMIF($B$28:$B$75,$A102,T$28:T$75)*$B102 -> 1000000 | U102: =SUMIF($B$28:$B$75,$A102,U$28:U$75)*$B102 -> 1000000
A103: 菊間 | B103: 1000000 | F103: 2 | G103: 2 | H103: 5 | I103: 5 | J103: 5 | K103: 5 | L103: 5 | M103: 5 | N103: 5 | O103: =SUMIF($B$28:$B$75,$A103,O$28:O$75)*$B103 -> 0 | P103: =SUMIF($B$28:$B$75,$A103,P$28:P$75)*$B103 -> 0 | Q103: =SUMIF($B$28:$B$75,$A103,Q$28:Q$75)*$B103 -> 1000000 | R103: =SUMIF($B$28:$B$75,$A103,R$28:R$75)*$B103 -> 1000000 | S103: =SUMIF($B$28:$B$75,$A103,S$28:S$75)*$B103 -> 1000000 | T103: =SUMIF($B$28:$B$75,$A103,T$28:T$75)*$B103 -> 1000000 | U103: =SUMIF($B$28:$B$75,$A103,U$28:U$75)*$B103 -> 0
A104: 合計 | C104: =SUM(C85:C103) -> 0 | D104: =SUM(D85:D103) -> 0 | E104: =SUM(E85:E103) -> 0 | F104: =SUM(F85:F103) -> 22 | G104: =SUM(G85:G103) -> 22 | H104: =SUM(H85:H103) -> 55 | I104: =SUM(I85:I103) -> 55 | J104: =SUM(J85:J103) -> 55 | ... N104: =SUM(N85:N103) -> 55 | O104: =SUM(O80:O103) -> 0 | P104: =SUM(P80:P103) -> 0 | Q104: =SUM(Q80:Q103) -> 14900000 | R104: =SUM(R80:R103) -> 15950000 | S104: =SUM(S80:S103) -> 9150000 | T104: =SUM(T80:T103) -> 9550000 | U104: =SUM(U80:U103) -> 2950000 | V104: =SUM(O104:U104) -> 52500000
A106: コスト（コスト合計より粗利算出）
A107: 野村 | B107: 600000 | O107: =SUMIF($B$28:$B$66,$A107,O$28:O$66)*$B107 -> 0 | P107: =SUMIF($B$28:$B$66,$A107,P$28:P$66)*$B107 -> 0 | Q107: =SUMIF($B$28:$B$66,$A107,Q$28:Q$66)*$B107 -> 300000 | R107: =SUMIF($B$28:$B$66,$A107,R$28:R$66)*$B107 -> 300000 | S107: =SUMIF($B$28:$B$66,$A107,S$28:S$66)*$B107 -> 300000 | T107: =SUMIF($B$28:$B$66,$A107,T$28:T$66)*$B107 -> 300000 | U107: =SUMIF($B$28:$B$66,$A107,U$28:U$66)*$B107 -> 150000
...

Sheet スケジュール案・要員計画 (開発フェーズ_工程別) (2)
O1: 調査・要件定義 | P1: 設計 | Q1: 製造 | R1: 結合テスト | S1: システムテスト | T1: ユーザテスト | U1: 本番稼働
A3: システム | B3: 担当 | C3: 2024年 | O3: 2025年 | S3: 202６年
C4: 1月 | D4: 2月 | E4: 3月 | F4: 4月 | G4: 5月 | H4: 6月 | I4: 7月 | J4: 8月 | K4: 9月 | L4: 10月 | M4: 11月 | N4: 12月 | O4: 9月 | P4: 10月 | Q4: 11月 | R4: 12月 | S4: １月 | T4: ２月 | U4: ３月 | V4: ４月 | W4: ５月 | X4: ６月
A5: マイルストン | K5: ★縮小共通基盤構築 | P5: ★新共通基盤構築 | U5: ★館林DC廃止
A6: 数量確定システム（千葉・徳山）
A7: 用役管理システム（千葉・徳山）
A8: 千葉化学品質管理システム
A9: ＬＭＰＰ包装システム
A10: ヤード操業システム
A11: 工場DB
B13: 本番リリースタイミング
A14: 千葉化学品質管理システム | B14: 2026年2月上旬
A15: ＬＭＰＰ包装システム | B15: 2026年2月上旬
A16: 工場DB | B16: 2026年2月上旬
A17: ヤード操業システム（千葉・徳山） | B17: 2026年2月中旬
A18: 数量確定システム（千葉・徳山） | B18: 2026年2月下旬
A19: 用役管理システム（千葉・徳山） | B19: 2026年2月下旬
A21: 想定要員数(工程単位) | Z21: 管理のみ
A22: 管理 | Q22: =AB29 -> 2.6 | R22: =AC29 -> 3.4 | S22: =AD29 -> 1.5 | T22: =AE29 -> 1.1 | U22: =AF29 -> 1.9 | V22: =SUM(Q22:U22) -> 10.5 | Z22: 調査・要件定義 | AA22: 設計 | AB22: 製造 | AC22: 結合テスト | AD22: システムテスト | AE22: ユーザテスト | AF22: 本番稼働
A23: 数量確定システム（千葉・徳山） | Q23: 3.2 | R23: 5.2 | S23: 1.4 | T23: 0.8 | U23: 2 | V23: =SUM(Q23:U23) -> 12.6 | Y23: 数量確定システム（千葉・徳山） | Z23: 0 | AA23: 0 | AB23: 0.8 | AC23: 1 | AD23: 0.5 | AE23: 0.3 | AF23: 0.5
A24: 用役管理システム（千葉・徳山） | Q24: 2.1 | R24: 3.1 | S24: 1.1 | T24: 0.8 | U24: 2 | V24: =SUM(Q24:U24) -> 9.1 | Y24: 用役管理システム（千葉・徳山） | Z24: 0 | AA24: 0 | AB24: 0.5 | AC24: 0.7 | AD24: 0.3 | AE24: 0.3 | AF24: 0.4
A25: 千葉化学品質管理システム | Q25: 2.2 | R25: 5.5 | S25: 0.8 | T25: 0.5 | U25: 0.5 | V25: =SUM(Q25:U25) -> 9.5 | Y25: 千葉化学品質管理システム | Z25: 0 | AA25: 0 | AB25: 0.6 | AC25: 1 | AD25: 0.3 | AE25: 0.2 | AF25: 0.2
A26: ＬＭＰＰ包装システム | Q26: 2 | R26: 1.2 | S26: 0.8 | T26: 0.5 | U26: 0.5 | V26: =SUM(Q26:U26) -> 5 | Y26: ＬＭＰＰ包装システム | Z26: 0 | AA26: 0 | AB26: 0.6 | AC26: 0.4 | AD26: 0.3 | AE26: 0.2 | AF26: 0.2
A27: 工場DB | Q27: 0 | R27: 0 | S27: 0 | T27: 0.1 | U27: 0.3 | V27: =SUM(Q27:U27) -> 0.4 | Y27: 工場DB | Z27: 0 | AA27: 0 | AB27: 0 | AC27: 0 | AD27: 0 | AE27: 0 | AF27: 0.4
A28: ヤ－ド操業システム（千葉・徳山） | Q28: 1 | R28: 1.4 | S28: 0.2 | T28: 0.1 | U28: 1.3 | V28: =SUM(Q28:U28) -> 4 | Y28: ヤ－ド操業システム（千葉・徳山） | Z28: 0 | AA28: 0 | AB28: 0.1 | AC28: 0.3 | AD28: 0.1 | AE28: 0.1 | AF28: 0.2
A29: 合計 | C29: =SUM(C24:C28) -> 0 | D29: =SUM(D24:D28) -> 0 | E29: =SUM(E24:E28) -> 0 | F29: =SUM(F24:F28) -> 0 | G29: =SUM(G24:G28) -> 0 | H29: =SUM(H24:H28) -> 0 | I29: =SUM(I24:I28) -> 0 | J29: =SUM(J24:J28) -> 0 | ... N29: =SUM(N24:N28) -> 0 | O29: =SUM(O23:O28) -> 0 | P29: =SUM(P23:P28) -> 0 | Q29: =SUM(Q22:Q28) -> 13.1 | R29: =SUM(R22:R28) -> 19.8 | S29: =SUM(S22:S28) -> 5.8 | T29: =SUM(T22:T28) -> 3.9 | U29: =SUM(U22:U28) -> 8.5 | V29: =SUM(Q29:U29) -> 51.1 | Z29: =SUM(Z23:Z28) -> 0 | AA29: =SUM(AA23:AA28) -> 0 | AB29: =SUM(AB23:AB28) -> 2.6 | AC29: =SUM(AC23:AC28) -> 3.4 | AD29: =SUM(AD23:AD28) -> 1.5 | AE29: =SUM(AE23:AE28) -> 1.1 | AF29: =SUM(AF23:AF28) -> 1.9
A31: 要員
A32: 管理（工場） | B32: 野村 | Q32: 0.5 | R32: 0.5 | S32: 0.5 | T32: 0.5 | U32: 0.25 | V32: =SUM(Q32:U32) -> 2.25
A33: 管理（工場） | B33: 石井 | Q33: 0.5 | R33: 0.5 | S33: 0.5 | T33: 0.5 | U33: 0.5 | V33: =SUM(Q33:U33) -> 2.5
A34: 管理（工場） | B34: グエン・タン・ドゥオック | Q34: 1 | R34: 1 | S34: 1 | T34: 1 | U34: 0.5 | V34: =SUM(Q34:U34) -> 4.5
A35: 数量確定 | B35: 天川 | Q35: 0.5 | R35: 0.5 | S35: 0.5 | T35: 0.5 | U35: 0.5 | V35: =SUM(Q35:U35) -> 2.5
A36: 数量確定 | B36: グエン・チュン・グエン | Q36: 0.5 | R36: 0.5 | S36: 0.5 | T36: 0.5 | U36: 0.5 | V36: =SUM(Q36:U36) -> 2.5
A37: 数量確定 | B37: ドー・ﾘｲ・アイン・トゥ | Q37: 1 | R37: 1 | V37: =SUM(Q37:U37) -> 2
A38: 数量確定 | B38: レ・ファム・バオ・ロック | Q38: 1 | R38: 1 | V38: =SUM(Q38:U38) -> 2
A39: 数量確定 | B39: VT1 | Q39: 0.5 | R39: 0.5 | V39: =SUM(Q39:U39) -> 1
A40: 用役管理 | B40: 天川 | Q40: 0.5 | R40: 0.5 | S40: 0.5 | T40: 0.5 | U40: 0.5 | V40: =SUM(Q40:U40) -> 2.5
A41: 用役管理 | B41: グエン・チュン・グエン | Q41: 0.5 | R41: 0.5 | S41: 0.5 | T41: 0.5 | U41: 0.5 | V41: =SUM(Q41:U41) -> 2.5
A42: 用役管理 | B42: ドー・グエン・ティ・トゥイ・ズイ | Q42: 1 | R42: 1 | V42: =SUM(Q42:U42) -> 2
A43: 用役管理 | B43: VT1 | Q43: 0.5 | R43: 0.5 | V43: =SUM(Q43:U43) -> 1
A44: 千葉化学 | B44: 馬場 | Q44: 0.5 | R44: 0.5 | S44: 0.5 | T44: 0.5 | U44: 0.5 | V44: =SUM(Q44:U44) -> 2.5
A45: 千葉化学 | B45: ズオン・ゴック・フー | Q45: 0.5 | R45: 0.5 | S45: 0.5 | T45: 0.25 | U45: 0.25 | V45: =SUM(Q45:U45) -> 2
A46: 千葉化学 | B46: グエン・ダン・ティエン | Q46: 1 | R46: 1 | V46: =SUM(Q46:U46) -> 2
A47: 千葉化学 | B47: ファン・グエン・タム | Q47: 1 | R47: 1 | V47: =SUM(Q47:U47) -> 2
A48: 千葉化学 | B48: VT2 | Q48: 0.5 | R48: 0.5 | V48: =SUM(Q48:U48) -> 1
A49: 千葉化学 | B49: VT3 | Q49: 1 | R49: 1 | V49: =SUM(Q49:U49) -> 2
A50: 包装 | B50: 馬場 | Q50: 0.5 | R50: 0.5 | S50: 0.5 | T50: 0.5 | U50: 0.5 | V50: =SUM(Q50:U50) -> 2.5
A51: 包装 | B51: ズオン・ゴック・フー | Q51: 0.5 | R51: 0.5 | S51: 0.5 | T51: 0.25 | U51: 0.25 | V51: =SUM(Q51:U51) -> 2
A52: 包装 | B52: VT2 | Q52: 0.5 | R52: 0.5 | V52: =SUM(Q52:U52) -> 1
A53: 包装 | B53: VT4 | Q53: 1 | R53: 1 | V53: =SUM(Q53:U53) -> 2
A54: ヤード操業 | B54: チャン・クォック・ズイ | F54: 2 | G54: 2 | H54: 5 | I54: 5 | J54: 5 | K54: 5 | L54: 5 | M54: 5 | N54: 5 | Q54: 1 | R54: 1 | S54: 1 | T54: 0.5 | U54: 0.5 | V54: =SUM(Q54:U54) -> 4
A55: 工場DB | B55: 天川 | F55: 2 | G55: 2 | H55: 5 | I55: 5 | J55: 5 | K55: 5 | L55: 5 | M55: 5 | N55: 5 | U55: 0.2 | V55: =SUM(Q55:U55) -> 0.2
A56: 工場DB | B56: 馬場 | F56: 2 | G56: 2 | H56: 5 | I56: 5 | J56: 5 | K56: 5 | L56: 5 | M56: 5 | N56: 5 | U56: 0.2 | V56: =SUM(Q56:U56) -> 0.2
A57: コミュニケータ | B57: グエン・ミン・トー | F57: 2 | G57: 2 | H57: 5 | I57: 5 | J57: 5 | K57: 5 | L57: 5 | M57: 5 | N57: 5 | Q57: 1 | R57: 1 | S57: 0.5 | T57: 0.5 | V57: =SUM(Q57:U57) -> 3
A58: ブリッジ | B58: チュン | F58: 2 | G58: 2 | H58: 5 | I58: 5 | J58: 5 | K58: 5 | L58: 5 | M58: 5 | N58: 5 | Q58: 0.5 | R58: 0.5 | V58: =SUM(Q58:U58) -> 1
A59: ブリッジ | B59: チャンホアンフック | F59: 2 | G59: 2 | H59: 5 | I59: 5 | J59: 5 | K59: 5 | L59: 5 | M59: 5 | N59: 5 | V59: =SUM(Q59:U59) -> 0
A60: ブリッジ | B60: ブイクアンティエン | F60: 2 | G60: 2 | H60: 5 | I60: 5 | J60: 5 | K60: 5 | L60: 5 | M60: 5 | N60: 5 | Q60: 0.5 | R60: 0.5 | S60: 0.5 | T60: 0.5 | V60: =SUM(Q60:U60) -> 2
A61: 管理（工場） | B61: 黒田智之 | Q61: 0.5 | R61: 0.5 | S61: 0.5 | T61: 0.5 | U61: 0.5 | V61: =SUM(Q61:U61) -> 2.5
A62: 数量確定 | B62: 吉田 | Q62: 0.5 | R62: 0.5 | S62: 0.5 | T62: 0.5 | U62: 0.5 | V62: =SUM(Q62:U62) -> 2.5
A63: 用役管理 | B63: 吉田 | Q63: 0.5 | R63: 0.5 | S63: 0.5 | T63: 0.5 | U63: 0.5 | V63: =SUM(Q63:U63) -> 2.5
A64: 千葉化学 | B64: 菊間 | Q64: 0.5 | R64: 0.5 | S64: 0.5 | T64: 0.5 | V64: =SUM(Q64:U64) -> 2
A65: 包装 | B65: 菊間 | Q65: 0.5 | R65: 0.5 | S65: 0.5 | T65: 0.5 | V65: =SUM(Q65:U65) -> 2
A66: 小計 | C66: =SUM(C36:C56) -> 0 | D66: =SUM(D36:D56) -> 0 | E66: =SUM(E36:E56) -> 0 | F66: =SUM(F36:F56) -> 6 | G66: =SUM(G36:G56) -> 6 | H66: =SUM(H36:H56) -> 15 | I66: =SUM(I36:I56) -> 15 | J66: =SUM(J36:J56) -> 15 | ... N66: =SUM(N36:N56) -> 15 | Q66: =SUM(Q32:Q56) -> 16 | R66: =SUM(R32:R56) -> 16 | S66: =SUM(S32:S56) -> 7 | T66: =SUM(T32:T56) -> 6 | U66: =SUM(U32:U56) -> 5.65 | V66: =SUM(Q66:U66) -> 50.65
A67: 合計 | C67: =SUM(C41:C60) -> 0 | D67: =SUM(D41:D60) -> 0 | E67: =SUM(E41:E60) -> 0 | F67: =SUM(F41:F60) -> 14 | G67: =SUM(G41:G60) -> 14 | H67: =SUM(H41:H60) -> 35 | I67: =SUM(I41:I60) -> 35 | J67: =SUM(J41:J60) -> 35 | ... N67: =SUM(N41:N60) -> 35 | O67: =SUM(O66:O66) -> 0 | P67: =SUM(P66:P66) -> 0 | Q67: =SUM(Q66:Q66) -> 16 | R67: =SUM(R66:R66) -> 16 | S67: =SUM(S66:S66) -> 7 | T67: =SUM(T66:T66) -> 6 | U67: =SUM(U66:U66) -> 5.65 | V67: =SUM(Q67:U67) -> 50.65
A69: 売上 | O69: 調査・要件定義 | P69: 設計 | Q69: 製造 | R69: 結合テスト | S69: システムテスト | T69: ユーザテスト | U69: 本番稼働
A70: 野村 | B70: 1000000 | O70: =SUMIF($B$20:$B$65,$A70,O$20:O$65)*$B70 -> 0 | P70: =SUMIF($B$20:$B$65,$A70,P$20:P$65)*$B70 -> 0 | Q70: =SUMIF($B$20:$B$65,$A70,Q$20:Q$65)*$B70 -> 500000 | R70: =SUMIF($B$20:$B$65,$A70,R$20:R$65)*$B70 -> 500000 | S70: =SUMIF($B$20:$B$65,$A70,S$20:S$65)*$B70 -> 500000 | T70: =SUMIF($B$20:$B$65,$A70,T$20:T$65)*$B70 -> 500000 | U70: =SUMIF($B$20:$B$65,$A70,U$20:U$65)*$B70 -> 250000
A71: 石井 | B71: 1000000 | O71: =SUMIF($B$20:$B$65,$A71,O$20:O$65)*$B71 -> 0 | P71: =SUMIF($B$20:$B$65,$A71,P$20:P$65)*$B71 -> 0 | Q71: =SUMIF($B$20:$B$65,$A71,Q$20:Q$65)*$B71 -> 500000 | R71: =SUMIF($B$20:$B$65,$A71,R$20:R$65)*$B71 -> 500000 | S71: =SUMIF($B$20:$B$65,$A71,S$20:S$65)*$B71 -> 500000 | T71: =SUMIF($B$20:$B$65,$A71,T$20:T$65)*$B71 -> 500000 | U71: =SUMIF($B$20:$B$65,$A71,U$20:U$65)*$B71 -> 500000
A72: 天川 | B72: 1000000 | O72: =SUMIF($B$20:$B$65,$A72,O$20:O$65)*$B72 -> 0 | P72: =SUMIF($B$20:$B$65,$A72,P$20:P$65)*$B72 -> 0 | Q72: =SUMIF($B$20:$B$65,$A72,Q$20:Q$65)*$B72 -> 1000000 | R72: =SUMIF($B$20:$B$65,$A72,R$20:R$65)*$B72 -> 1000000 | S72: =SUMIF($B$20:$B$65,$A72,S$20:S$65)*$B72 -> 1000000 | T72: =SUMIF($B$20:$B$65,$A72,T$20:T$65)*$B72 -> 1000000 | U72: =SUMIF($B$20:$B$65,$A72,U$20:U$65)*$B72 -> 1200000
A73: 馬場 | B73: 1000000 | O73: =SUMIF($B$20:$B$65,$A73,O$20:O$65)*$B73 -> 0 | P73: =SUMIF($B$20:$B$65,$A73,P$20:P$65)*$B73 -> 0 | Q73: =SUMIF($B$20:$B$65,$A73,Q$20:Q$65)*$B73 -> 1000000 | R73: =SUMIF($B$20:$B$65,$A73,R$20:R$65)*$B73 -> 1000000 | S73: =SUMIF($B$20:$B$65,$A73,S$20:S$65)*$B73 -> 1000000 | T73: =SUMIF($B$20:$B$65,$A73,T$20:T$65)*$B73 -> 1000000 | U73: =SUMIF($B$20:$B$65,$A73,U$20:U$65)*$B73 -> 1200000
A74: グエン・タン・ドゥオック | B74: 700000 | O74: =SUMIF($B$20:$B$65,$A74,O$20:O$65)*$B74 -> 0 | P74: =SUMIF($B$20:$B$65,$A74,P$20:P$65)*$B74 -> 0 | Q74: =SUMIF($B$20:$B$65,$A74,Q$20:Q$65)*$B74 -> 700000 | R74: =SUMIF($B$20:$B$65,$A74,R$20:R$65)*$B74 -> 700000 | S74: =SUMIF($B$20:$B$65,$A74,S$20:S$65)*$B74 -> 700000 | T74: =SUMIF($B$20:$B$65,$A74,T$20:T$65)*$B74 -> 700000 | U74: =SUMIF($B$20:$B$65,$A74,U$20:U$65)*$B74 -> 350000
A75: グエン・チュン・グエン | B75: 700000 | O75: =SUMIF($B$20:$B$65,$A75,O$20:O$65)*$B75 -> 0 | P75: =SUMIF($B$20:$B$65,$A75,P$20:P$65)*$B75 -> 0 | Q75: =SUMIF($B$20:$B$65,$A75,Q$20:Q$65)*$B75 -> 700000 | R75: =SUMIF($B$20:$B$65,$A75,R$20:R$65)*$B75 -> 700000 | S75: =SUMIF($B$20:$B$65,$A75,S$20:S$65)*$B75 -> 700000 | T75: =SUMIF($B$20:$B$65,$A75,T$20:T$65)*$B75 -> 700000 | U75: =SUMIF($B$20:$B$65,$A75,U$20:U$65)*$B75 -> 700000
A76: ドー・ﾘｲ・アイン・トゥ | B76: 700000 | O76: =SUMIF($B$20:$B$65,$A76,O$20:O$65)*$B76 -> 0 | P76: =SUMIF($B$20:$B$65,$A76,P$20:P$65)*$B76 -> 0 | Q76: =SUMIF($B$20:$B$65,$A76,Q$20:Q$65)*$B76 -> 700000 | R76: =SUMIF($B$20:$B$65,$A76,R$20:R$65)*$B76 -> 700000 | S76: =SUMIF($B$20:$B$65,$A76,S$20:S$65)*$B76 -> 0 | T76: =SUMIF($B$20:$B$65,$A76,T$20:T$65)*$B76 -> 0 | U76: =SUMIF($B$20:$B$65,$A76,U$20:U$65)*$B76 -> 0
A77: レ・ファム・バオ・ロック | B77: 700000 | O77: =SUMIF($B$20:$B$65,$A77,O$20:O$65)*$B77 -> 0 | P77: =SUMIF($B$20:$B$65,$A77,P$20:P$65)*$B77 -> 0 | Q77: =SUMIF($B$20:$B$65,$A77,Q$20:Q$65)*$B77 -> 700000 | R77: =SUMIF($B$20:$B$65,$A77,R$20:R$65)*$B77 -> 700000 | S77: =SUMIF($B$20:$B$65,$A77,S$20:S$65)*$B77 -> 0 | T77: =SUMIF($B$20:$B$65,$A77,T$20:T$65)*$B77 -> 0 | U77: =SUMIF($B$20:$B$65,$A77,U$20:U$65)*$B77 -> 0
A78: ズオン・ゴック・フー | B78: 700000 | O78: =SUMIF($B$20:$B$65,$A78,O$20:O$65)*$B78 -> 0 | P78: =SUMIF($B$20:$B$65,$A78,P$20:P$65)*$B78 -> 0 | Q78: =SUMIF($B$20:$B$65,$A78,Q$20:Q$65)*$B78 -> 700000 | R78: =SUMIF($B$20:$B$65,$A78,R$20:R$65)*$B78 -> 700000 | S78: =SUMIF($B$20:$B$65,$A78,S$20:S$65)*$B78 -> 700000 | T78: =SUMIF($B$20:$B$65,$A78,T$20:T$65)*$B78 -> 350000 | U78: =SUMIF($B$20:$B$65,$A78,U$20:U$65)*$B78 -> 350000
A79: チャン・クォック・ズイ | B79: 700000 | O79: =SUMIF($B$20:$B$65,$A79,O$20:O$65)*$B79 -> 0 | P79: =SUMIF($B$20:$B$65,$A79,P$20:P$65)*$B79 -> 0 | Q79: =SUMIF($B$20:$B$65,$A79,Q$20:Q$65)*$B79 -> 700000 | R79: =SUMIF($B$20:$B$65,$A79,R$20:R$65)*$B79 -> 700000 | S79: =SUMIF($B$20:$B$65,$A79,S$20:S$65)*$B79 -> 700000 | T79: =SUMIF($B$20:$B$65,$A79,T$20:T$65)*$B79 -> 350000 | U79: =SUMIF($B$20:$B$65,$A79,U$20:U$65)*$B79 -> 350000
A80: ドー・グエン・ティ・トゥイ・ズイ | B80: 700000 | O80: =SUMIF($B$20:$B$65,$A80,O$20:O$65)*$B80 -> 0 | P80: =SUMIF($B$20:$B$65,$A80,P$20:P$65)*$B80 -> 0 | Q80: =SUMIF($B$20:$B$65,$A80,Q$20:Q$65)*$B80 -> 700000 | R80: =SUMIF($B$20:$B$65,$A80,R$20:R$65)*$B80 -> 700000 | S80: =SUMIF($B$20:$B$65,$A80,S$20:S$65)*$B80 -> 0 | T80: =SUMIF($B$20:$B$65,$A80,T$20:T$65)*$B80 -> 0 | U80: =SUMIF($B$20:$B$65,$A80,U$20:U$65)*$B80 -> 0
A81: グエン・ダン・ティエン | B81: 700000 | O81: =SUMIF($B$20:$B$65,$A81,O$20:O$65)*$B81 -> 0 | P81: =SUMIF($B$20:$B$65,$A81,P$20:P$65)*$B81 -> 0 | Q81: =SUMIF($B$20:$B$65,$A81,Q$20:Q$65)*$B81 -> 700000 | R81: =SUMIF($B$20:$B$65,$A81,R$20:R$65)*$B81 -> 700000 | S81: =SUMIF($B$20:$B$65,$A81,S$20:S$65)*$B81 -> 0 | T81: =SUMIF($B$20:$B$65,$A81,T$20:T$65)*$B81 -> 0 | U81: =SUMIF($B$20:$B$65,$A81,U$20:U$65)*$B81 -> 0
A82: ファン・グエン・タム | B82: 700000 | O82: =SUMIF($B$20:$B$65,$A82,O$20:O$65)*$B82 -> 0 | P82: =SUMIF($B$20:$B$65,$A82,P$20:P$65)*$B82 -> 0 | Q82: =SUMIF($B$20:$B$65,$A82,Q$20:Q$65)*$B82 -> 700000 | R82: =SUMIF($B$20:$B$65,$A82,R$20:R$65)*$B82 -> 700000 | S82: =SUMIF($B$20:$B$65,$A82,S$20:S$65)*$B82 -> 0 | T82: =SUMIF($B$20:$B$65,$A82,T$20:T$65)*$B82 -> 0 | U82: =SUMIF($B$20:$B$65,$A82,U$20:U$65)*$B82 -> 0
A83: グエン・ミン・トー | B83: 700000 | F83: 2 | G83: 2 | H83: 5 | I83: 5 | J83: 5 | K83: 5 | L83: 5 | M83: 5 | N83: 5 | O83: =SUMIF($B$20:$B$65,$A83,O$20:O$65)*$B83 -> 0 | P83: =SUMIF($B$20:$B$65,$A83,P$20:P$65)*$B83 -> 0 | Q83: =SUMIF($B$20:$B$65,$A83,Q$20:Q$65)*$B83 -> 700000 | R83: =SUMIF($B$20:$B$65,$A83,R$20:R$65)*$B83 -> 700000 | S83: =SUMIF($B$20:$B$65,$A83,S$20:S$65)*$B83 -> 350000 | T83: =SUMIF($B$20:$B$65,$A83,T$20:T$65)*$B83 -> 350000 | U83: =SUMIF($B$20:$B$65,$A83,U$20:U$65)*$B83 -> 0
A84: チュン | B84: 1000000 | F84: 2 | G84: 2 | H84: 5 | I84: 5 | J84: 5 | K84: 5 | L84: 5 | M84: 5 | N84: 5 | O84: =SUMIF($B$20:$B$65,$A84,O$20:O$65)*$B84 -> 0 | P84: =SUMIF($B$20:$B$65,$A84,P$20:P$65)*$B84 -> 0 | Q84: =SUMIF($B$20:$B$65,$A84,Q$20:Q$65)*$B84 -> 500000 | R84: =SUMIF($B$20:$B$65,$A84,R$20:R$65)*$B84 -> 500000 | S84: =SUMIF($B$20:$B$65,$A84,S$20:S$65)*$B84 -> 0 | T84: =SUMIF($B$20:$B$65,$A84,T$20:T$65)*$B84 -> 0 | U84: =SUMIF($B$20:$B$65,$A84,U$20:U$65)*$B84 -> 0
A85: チャンホアンフック | B85: 800000 | F85: 2 | G85: 2 | H85: 5 | I85: 5 | J85: 5 | K85: 5 | L85: 5 | M85: 5 | N85: 5 | O85: =SUMIF($B$20:$B$65,$A85,O$20:O$65)*$B85 -> 0 | P85: =SUMIF($B$20:$B$65,$A85,P$20:P$65)*$B85 -> 0 | Q85: =SUMIF($B$20:$B$65,$A85,Q$20:Q$65)*$B85 -> 0 | R85: =SUMIF($B$20:$B$65,$A85,R$20:R$65)*$B85 -> 0 | S85: =SUMIF($B$20:$B$65,$A85,S$20:S$65)*$B85 -> 0 | T85: =SUMIF($B$20:$B$65,$A85,T$20:T$65)*$B85 -> 0 | U85: =SUMIF($B$20:$B$65,$A85,U$20:U$65)*$B85 -> 0
A86: ブイクアンティエン | B86: 1000000 | F86: 2 | G86: 2 | H86: 5 | I86: 5 | J86: 5 | K86: 5 | L86: 5 | M86: 5 | N86: 5 | O86: =SUMIF($B$20:$B$65,$A86,O$20:O$65)*$B86 -> 0 | P86: =SUMIF($B$20:$B$65,$A86,P$20:P$65)*$B86 -> 0 | Q86: =SUMIF($B$20:$B$65,$A86,Q$20:Q$65)*$B86 -> 500000 | R86: =SUMIF($B$20:$B$65,$A86,R$20:R$65)*$B86 -> 500000 | S86: =SUMIF($B$20:$B$65,$A86,S$20:S$65)*$B86 -> 500000 | T86: =SUMIF($B$20:$B$65,$A86,T$20:T$65)*$B86 -> 500000 | U86: =SUMIF($B$20:$B$65,$A86,U$20:U$65)*$B86 -> 0
A87: VT1 | B87: 700000 | F87: 2 | G87: 2 | H87: 5 | I87: 5 | J87: 5 | K87: 5 | L87: 5 | M87: 5 | N87: 5 | O87: =SUMIF($B$20:$B$65,$A87,O$20:O$65)*$B87 -> 0 | P87: =SUMIF($B$20:$B$65,$A87,P$20:P$65)*$B87 -> 0 | Q87: =SUMIF($B$20:$B$65,$A87,Q$20:Q$65)*$B87 -> 700000 | R87: =SUMIF($B$20:$B$65,$A87,R$20:R$65)*$B87 -> 700000 | S87: =SUMIF($B$20:$B$65,$A87,S$20:S$65)*$B87 -> 0 | T87: =SUMIF($B$20:$B$65,$A87,T$20:T$65)*$B87 -> 0 | U87: =SUMIF($B$20:$B$65,$A87,U$20:U$65)*$B87 -> 0
A88: VT2 | B88: 700000 | F88: 2 | G88: 2 | H88: 5 | I88: 5 | J88: 5 | K88: 5 | L88: 5 | M88: 5 | N88: 5 | O88: =SUMIF($B$20:$B$65,$A88,O$20:O$65)*$B88 -> 0 | P88: =SUMIF($B$20:$B$65,$A88,P$20:P$65)*$B88 -> 0 | Q88: =SUMIF($B$20:$B$65,$A88,Q$20:Q$65)*$B88 -> 700000 | R88: =SUMIF($B$20:$B$65,$A88,R$20:R$65)*$B88 -> 700000 | S88: =SUMIF($B$20:$B$65,$A88,S$20:S$65)*$B88 -> 0 | T88: =SUMIF($B$20:$B$65,$A88,T$20:T$65)*$B88 -> 0 | U88: =SUMIF($B$20:$B$65,$A88,U$20:U$65)*$B88 -> 0
A89: VT3 | B89: 700000 | F89: 2 | G89: 2 | H89: 5 | I89: 5 | J89: 5 | K89: 5 | L89: 5 | M89: 5 | N89: 5 | O89: =SUMIF($B$20:$B$65,$A89,O$20:O$65)*$B89 -> 0 | P89: =SUMIF($B$20:$B$65,$A89,P$20:P$65)*$B89 -> 0 | Q89: =SUMIF($B$20:$B$65,$A89,Q$20:Q$65)*$B89 -> 700000 | R89: =SUMIF($B$20:$B$65,$A89,R$20:R$65)*$B89 -> 700000 | S89: =SUMIF($B$20:$B$65,$A89,S$20:S$65)*$B89 -> 0 | T89: =SUMIF($B$20:$B$65,$A89,T$20:T$65)*$B89 -> 0 | U89: =SUMIF($B$20:$B$65,$A89,U$20:U$65)*$B89 -> 0
A90: VT4 | B90: 700000 | F90: 2 | G90: 2 | H90: 5 | I90: 5 | J90: 5 | K90: 5 | L90: 5 | M90: 5 | N90: 5 | O90: =SUMIF($B$20:$B$65,$A90,O$20:O$65)*$B90 -> 0 | P90: =SUMIF($B$20:$B$65,$A90,P$20:P$65)*$B90 -> 0 | Q90: =SUMIF($B$20:$B$65,$A90,Q$20:Q$65)*$B90 -> 700000 | R90: =SUMIF($B$20:$B$65,$A90,R$20:R$65)*$B90 -> 700000 | S90: =SUMIF($B$20:$B$65,$A90,S$20:S$65)*$B90 -> 0 | T90: =SUMIF($B$20:$B$65,$A90,T$20:T$65)*$B90 -> 0 | U90: =SUMIF($B$20:$B$65,$A90,U$20:U$65)*$B90 -> 0
A91: 黒田智之 | B91: 1000000 | F91: 2 | G91: 2 | H91: 5 | I91: 5 | J91: 5 | K91: 5 | L91: 5 | M91: 5 | N91: 5 | O91: =SUMIF($B$20:$B$65,$A91,O$20:O$65)*$B91 -> 0 | P91: =SUMIF($B$20:$B$65,$A91,P$20:P$65)*$B91 -> 0 | Q91: =SUMIF($B$20:$B$65,$A91,Q$20:Q$65)*$B91 -> 500000 | R91: =SUMIF($B$20:$B$65,$A91,R$20:R$65)*$B91 -> 500000 | S91: =SUMIF($B$20:$B$65,$A91,S$20:S$65)*$B91 -> 500000 | T91: =SUMIF($B$20:$B$65,$A91,T$20:T$65)*$B91 -> 500000 | U91: =SUMIF($B$20:$B$65,$A91,U$20:U$65)*$B91 -> 500000
A92: 吉田 | B92: 1000000 | F92: 2 | G92: 2 | H92: 5 | I92: 5 | J92: 5 | K92: 5 | L92: 5 | M92: 5 | N92: 5 | O92: =SUMIF($B$20:$B$65,$A92,O$20:O$65)*$B92 -> 0 | P92: =SUMIF($B$20:$B$65,$A92,P$20:P$65)*$B92 -> 0 | Q92: =SUMIF($B$20:$B$65,$A92,Q$20:Q$65)*$B92 -> 1000000 | R92: =SUMIF($B$20:$B$65,$A92,R$20:R$65)*$B92 -> 1000000 | S92: =SUMIF($B$20:$B$65,$A92,S$20:S$65)*$B92 -> 1000000 | T92: =SUMIF($B$20:$B$65,$A92,T$20:T$65)*$B92 -> 1000000 | U92: =SUMIF($B$20:$B$65,$A92,U$20:U$65)*$B92 -> 1000000
A93: 菊間 | B93: 1000000 | F93: 2 | G93: 2 | H93: 5 | I93: 5 | J93: 5 | K93: 5 | L93: 5 | M93: 5 | N93: 5 | O93: =SUMIF($B$20:$B$65,$A93,O$20:O$65)*$B93 -> 0 | P93: =SUMIF($B$20:$B$65,$A93,P$20:P$65)*$B93 -> 0 | Q93: =SUMIF($B$20:$B$65,$A93,Q$20:Q$65)*$B93 -> 1000000 | R93: =SUMIF($B$20:$B$65,$A93,R$20:R$65)*$B93 -> 1000000 | S93: =SUMIF($B$20:$B$65,$A93,S$20:S$65)*$B93 -> 1000000 | T93: =SUMIF($B$20:$B$65,$A93,T$20:T$65)*$B93 -> 1000000 | U93: =SUMIF($B$20:$B$65,$A93,U$20:U$65)*$B93 -> 0
A94: 合計 | C94: =SUM(C75:C93) -> 0 | D94: =SUM(D75:D93) -> 0 | E94: =SUM(E75:E93) -> 0 | F94: =SUM(F75:F93) -> 22 | G94: =SUM(G75:G93) -> 22 | H94: =SUM(H75:H93) -> 55 | I94: =SUM(I75:I93) -> 55 | J94: =SUM(J75:J93) -> 55 | ... N94: =SUM(N75:N93) -> 55 | O94: =SUM(O70:O93) -> 0 | P94: =SUM(P70:P93) -> 0 | Q94: =SUM(Q70:Q93) -> 16300000 | R94: =SUM(R70:R93) -> 16300000 | S94: =SUM(S70:S93) -> 9150000 | T94: =SUM(T70:T93) -> 8450000 | U94: =SUM(U70:U93) -> 6400000 | Y94: =SUM(O94:X94) -> 56600000
A96: コスト（コスト合計より粗利算出） | O96: 調査・要件定義 | P96: 設計 | Q96: 製造 | R96: 結合テスト | S96: システムテスト | T96: ユーザテスト | U96: 本番稼働
A97: 野村 | B97: 600000 | O97: =SUMIF($B$20:$B$56,$A97,O$20:O$56)*$B97 -> 0 | P97: =SUMIF($B$20:$B$56,$A97,P$20:P$56)*$B97 -> 0 | Q97: =SUMIF($B$20:$B$56,$A97,Q$20:Q$56)*$B97 -> 300000 | R97: =SUMIF($B$20:$B$56,$A97,R$20:R$56)*$B97 -> 300000 | S97: =SUMIF($B$20:$B$56,$A97,S$20:S$56)*$B97 -> 300000 | T97: =SUMIF($B$20:$B$56,$A97,T$20:T$56)*$B97 -> 300000 | U97: =SUMIF($B$20:$B$56,$A97,U$20:U$56)*$B97 -> 150000
A98: 石井 | B98: 600000 | O98: =SUMIF($B$20:$B$56,$A98,O$20:O$56)*$B98 -> 0 | P98: =SUMIF($B$20:$B$56,$A98,P$20:P$56)*$B98 -> 0 | Q98: =SUMIF($B$20:$B$56,$A98,Q$20:Q$56)*$B98 -> 300000 | R98: =SUMIF($B$20:$B$56,$A98,R$20:R$56)*$B98 -> 300000 | S98: =SUMIF($B$20:$B$56,$A98,S$20:S$56)*$B98 -> 300000 | T98: =SUMIF($B$20:$B$56,$A98,T$20:T$56)*$B98 -> 300000 | U98: =SUMIF($B$20:$B$56,$A98,U$20:U$56)*$B98 -> 300000
A99: 天川 | B99: 500000 | O99: =SUMIF($B$20:$B$56,$A99,O$20:O$56)*$B99 -> 0 | P99: =SUMIF($B$20:$B$56,$A99,P$20:P$56)*$B99 -> 0 | Q99: =SUMIF($B$20:$B$56,$A99,Q$20:Q$56)*$B99 -> 500000 | R99: =SUMIF($B$20:$B$56,$A99,R$20:R$56)*$B99 -> 500000 | S99: =SUMIF($B$20:$B$56,$A99,S$20:S$56)*$B99 -> 500000 | T99: =SUMIF($B$20:$B$56,$A99,T$20:T$56)*$B99 -> 500000 | U99: =SUMIF($B$20:$B$56,$A99,U$20:U$56)*$B99 -> 600000
A100: 馬場 | B100: 500000 | O100: =SUMIF($B$20:$B$56,$A100,O$20:O$56)*$B100 -> 0 | P100: =SUMIF($B$20:$B$56,$A100,P$20:P$56)*$B100 -> 0 | Q100: =SUMIF($B$20:$B$56,$A100,Q$20:Q$56)*$B100 -> 500000 | R100: =SUMIF($B$20:$B$56,$A100,R$20:R$56)*$B100 -> 500000 | S100: =SUMIF($B$20:$B$56,$A100,S$20:S$56)*$B100 -> 500000 | T100: =SUMIF($B$20:$B$56,$A100,T$20:T$56)*$B100 -> 500000 | U100: =SUMIF($B$20:$B$56,$A100,U$20:U$56)*$B100 -> 600000
A101: グエン・タン・ドゥオック | B101: 450000 | O101: =SUMIF($B$20:$B$56,$A101,O$20:O$56)*$B101 -> 0 | P101: =SUMIF($B$20:$B$56,$A101,P$20:P$56)*$B101 -> 0 | Q101: =SUMIF($B$20:$B$56,$A101,Q$20:Q$56)*$B101 -> 450000 | R101: =SUMIF($B$20:$B$56,$A101,R$20:R$56)*$B101 -> 450000 | S101: =SUMIF($B$20:$B$56,$A101,S$20:S$56)*$B101 -> 450000 | T101: =SUMIF($B$20:$B$56,$A101,T$20:T$56)*$B101 -> 450000 | U101: =SUMIF($B$20:$B$56,$A101,U$20:U$56)*$B101 -> 225000
A102: グエン・チュン・グエン | B102: 350000 | O102: =SUMIF($B$20:$B$56,$A102,O$20:O$56)*$B102 -> 0 | P102: =SUMIF($B$20:$B$56,$A102,P$20:P$56)*$B102 -> 0 | Q102: =SUMIF($B$20:$B$56,$A102,Q$20:Q$56)*$B102 -> 350000 | R102: =SUMIF($B$20:$B$56,$A102,R$20:R$56)*$B102 -> 350000 | S102: =SUMIF($B$20:$B$56,$A102,S$20:S$56)*$B102 -> 350000 | T102: =SUMIF($B$20:$B$56,$A102,T$20:T$56)*$B102 -> 350000 | U102: =SUMIF($B$20:$B$56,$A102,U$20:U$56)*$B102 -> 350000
A103: ドー・ﾘｲ・アイン・トゥ | B103: 350000 | O103: =SUMIF($B$20:$B$56,$A103,O$20:O$56)*$B103 -> 0 | P103: =SUMIF($B$20:$B$56,$A103,P$20:P$56)*$B103 -> 0 | Q103: =SUMIF($B$20:$B$56,$A103,Q$20:Q$56)*$B103 -> 350000 | R103: =SUMIF($B$20:$B$56,$A103,R$20:R$56)*$B103 -> 350000 | S103: =SUMIF($B$20:$B$56,$A103,S$20:S$56)*$B103 -> 0 | T103: =SUMIF($B$20:$B$56,$A103,T$20:T$56)*$B103 -> 0 | U103: =SUMIF($B$20:$B$56,$A103,U$20:U$56)*$B103 -> 0
A104: レ・ファム・バオ・ロック | B104: 350000 | O104: =SUMIF($B$20:$B$56,$A104,O$20:O$56)*$B104 -> 0 | P104: =SUMIF($B$20:$B$56,$A104,P$20:P$56)*$B104 -> 0 | Q104: =SUMIF($B$20:$B$56,$A104,Q$20:Q$56)*$B104 -> 350000 | R104: =SUMIF($B$20:$B$56,$A104,R$20:R$56)*$B104 -> 350000 | S104: =SUMIF($B$20:$B$56,$A104,S$20:S$56)*$B104 -> 0 | T104: =SUMIF($B$20:$B$56,$A104,T$20:T$56)*$B104 -> 0 | U104: =SUMIF($B$20:$B$56,$A104,U$20:U$56)*$B104 -> 0
A105: ズオン・ゴック・フー | B105: 350000 | O105: =SUMIF($B$20:$B$56,$A105,O$20:O$56)*$B105 -> 0 | P105: =SUMIF($B$20:$B$56,$A105,P$20:P$56)*$B105 -> 0 | Q105: =SUMIF($B$20:$B$56,$A105,Q$20:Q$56)*$B105 -> 350000 | R105: =SUMIF($B$20:$B$56,$A105,R$20:R$56)*$B105 -> 350000 | S105: =SUMIF($B$20:$B$56,$A105,S$20:S$56)*$B105 -> 350000 | T105: =SUMIF($B$20:$B$56,$A105,T$20:T$56)*$B105 -> 175000 | U105: =SUMIF($B$20:$B$56,$A105,U$20:U$56)*$B105 -> 175000
A106: チャン・クォック・ズイ | B106: 350000 | O106: =SUMIF($B$20:$B$56,$A106,O$20:O$56)*$B106 -> 0 | P106: =SUMIF($B$20:$B$56,$A106,P$20:P$56)*$B106 -> 0 | Q106: =SUMIF($B$20:$B$56,$A106,Q$20:Q$56)*$B106 -> 350000 | R106: =SUMIF($B$20:$B$56,$A106,R$20:R$56)*$B106 -> 350000 | S106: =SUMIF($B$20:$B$56,$A106,S$20:S$56)*$B106 -> 350000 | T106: =SUMIF($B$20:$B$56,$A106,T$20:T$56)*$B106 -> 175000 | U106: =SUMIF($B$20:$B$56,$A106,U$20:U$56)*$B106 -> 175000
...

Sheet 再見積 (システム・工程別サマリ) _ベース
C1: 工数直入力のため注意！！
C2: 見積（工程別サマリ）
C3: パターン | D3: クラウドアーキ基盤に移行 | R3: 備考
D4: アプリ | N4: DB | P4: 全体
B5: No. | C5: システム | D5: 調査・要件定義 | E5: 設計 | F5: 製造 | G5: 結合テスト | H5: システムテスト | I5: ユーザテスト | J5: 本番稼働 | K5: 管理 | L5: 工数計 | M5: 金額 | N5: 工数計 | O5: 金額 | P5: 工数計 | Q5: 金額
B6: 1 | C6: 数量確定システム（千葉・徳山） | D6: 3.2 | E6: 1.6 | F6: 2.7 | G6: 5.2 | H6: 1.4 | I6: 0.8 | J6: 2 | K6: 3.8 | L6: =SUM(D6:K6) -> 20.7 | M6: =SUM(D6:J6)*1000000+K6*1400000 -> 22220000 | N6: 0 | O6: 0 | P6: =SUM(L6:L10)+N6 -> 58.4 | Q6: =SUM(M6:M10)+O6 -> 63040000
B7: 2 | C7: 用役管理システム（千葉・徳山） | D7: 1.4 | E7: 1.1 | F7: 1.5 | G7: 3.1 | H7: 1.1 | I7: 0.8 | J7: 2 | K7: 2.6 | L7: =SUM(D7:K7) -> 13.6 | M7: =SUM(D7:J7)*1000000+K7*1400000 -> 14640000
B8: 3 | C8: 千葉化学品質管理システム | D8: 1.7 | E8: 1.4 | F8: 1.6 | G8: 5.5 | H8: 0.8 | I8: 0.5 | J8: 0.6 | K8: 2.8 | L8: =SUM(D8:K8) -> 14.9 | M8: =SUM(D8:J8)*1000000+K8*1400000 -> 16020000
B9: 4 | C9: ＬＭＰＰ包装システム | D9: 1.3 | E9: 0.4 | F9: 1.6 | G9: 1.2 | H9: 0.8 | I9: 0.5 | J9: 0.6 | K9: 1.9 | L9: =SUM(D9:K9) -> 8.3 | M9: =SUM(D9:J9)*1000000+K9*1400000 -> 9060000
B10: 5 | C10: 工場DB | J10: 0.4 | K10: 0.5 | L10: =SUM(D10:K10) -> 0.9 | M10: =SUM(D10:J10)*1000000+K10*1400000 -> 1100000
B11: 6 | C11: ヤ－ド操業システム（千葉・徳山） | D11: 0.5 | E11: 0.4 | F11: 0.7 | G11: 1.4 | H11: 0.2 | I11: 0.1 | J11: 1.5 | K11: 0.9 | L11: =SUM(D11:K11) -> 5.7 | M11: =SUM(D11:J11)*1000000+K11*1400000 -> 6060000 | N11: 0 | O11: =SUM(O5:O10) -> 0 | P11: =SUM(L11:L11)+N11 -> 5.7 | Q11: =SUM(M11:M11)+O6 -> 6060000
B12: 計 | D12: =SUM(D6:D11) -> 8.1 | E12: =SUM(E6:E11) -> 4.9 | F12: =SUM(F6:F11) -> 8.1 | G12: =SUM(G6:G11) -> 16.4 | H12: =SUM(H6:H11) -> 4.3 | I12: =SUM(I6:I11) -> 2.7 | J12: =SUM(J6:J11) -> 7.1 | K12: =SUM(K6:K11) -> 12.5 | L12: =SUM(D12:K12) -> 64.1 | M12: =SUM(M6:M11) -> 69100000 | N12: =SUM(N6:N11) -> 0 | O12: =SUM(O6:O11) -> 0 | P12: =SUM(P6:P11) -> 64.1 | Q12: =SUM(Q6:Q11) -> 69100000
B13: 単価 | D13: 1000000 | E13: 1000000 | F13: 1000000 | G13: 1000000 | H13: 1000000 | I13: 1000000 | J13: 1000000 | K13: 1400000
B14: 金額 | D14: =D12*D13 -> 8100000 | E14: =E12*E13 -> 4900000 | F14: =F12*F13 -> 8100000 | G14: =G12*G13 -> 16400000 | H14: =H12*H13 -> 4300000 | I14: =I12*I13 -> 2700000 | J14: =J12*J13 -> 7100000 | K14: =K12*K13 -> 17500000
C16: 再見積もり（工程別サマリ）
C17: パターン | D17: クラウドアーキ基盤に移行 | R17: 備考
D18: アプリ | N18: DB | P18: 全体
B19: No. | C19: システム | D19: 調査・要件定義 | E19: 設計 | F19: 製造 | G19: 結合テスト | H19: システムテスト | I19: ユーザテスト | J19: 本番稼働 | K19: 管理 | L19: 工数計 | M19: 金額 | N19: 工数計 | O19: 金額 | P19: 工数計 | Q19: 金額
B20: 1 | C20: 数量確定システム（千葉・徳山） | D20: 3.2 | E20: 1.6 | F20: 3.2 | G20: 5.2 | H20: 1.4 | I20: 1.9 | J20: 2 | K20: 3.9 | L20: =SUM(D20:K20) -> 22.4 | M20: =SUM(D20:J20)*1000000+K20*1400000 -> 23960000 | N20: 0 | O20: 0 | P20: =SUM(L20:L24)+N20 -> 64.2 | Q20: =SUM(M20:M24)+O20 -> 68840000
B21: 2 | C21: 用役管理システム（千葉・徳山） | D21: 1.4 | E21: 1.1 | F21: 2.1 | G21: 3.1 | H21: 1.1 | I21: 1.9 | J21: 2 | K21: 2.7 | L21: =SUM(D21:K21) -> 15.4 | M21: =SUM(D21:J21)*1000000+K21*1400000 -> 16480000
B22: 3 | C22: 千葉化学品質管理システム | D22: 1.7 | E22: 1.4 | F22: 2.2 | G22: 5.5 | H22: 0.8 | I22: 1.2 | J22: 0.6 | K22: 2.9 | L22: =SUM(D22:K22) -> 16.3 | M22: =SUM(D22:J22)*1000000+K22*1400000 -> 17460000
B23: 4 | C23: ＬＭＰＰ包装システム | D23: 1.3 | E23: 0.4 | F23: 2.1 | G23: 1.2 | H23: 0.8 | I23: 1.2 | J23: 0.6 | K23: 2 | L23: =SUM(D23:K23) -> 9.6 | M23: =SUM(D23:J23)*1000000+K23*1400000 -> 10400000
B24: 5 | C24: 工場DB | J24: 0.4 | K24: 0.1 | L24: =SUM(D24:K24) -> 0.5 | M24: =SUM(D24:J24)*1000000+K24*1400000 -> 540000
B25: 6 | C25: ヤ－ド操業システム（千葉・徳山） | D25: 0.5 | E25: 0.4 | F25: 0.9 | G25: 1.4 | H25: 0.2 | I25: 0.7 | J25: 1.5 | K25: 0.9 | L25: =SUM(D25:K25) -> 6.5 | M25: =SUM(D25:J25)*1000000+K25*1400000 -> 6860000 | N25: 0 | O25: =SUM(O19:O24) -> 0 | P25: =SUM(L25:L25)+N25 -> 6.5 | Q25: =SUM(M25:M25)+O20 -> 6860000
B26: 計 | D26: =SUM(D20:D25) -> 8.1 | E26: =SUM(E20:E25) -> 4.9 | F26: =SUM(F20:F25) -> 10.5 | G26: =SUM(G20:G25) -> 16.4 | H26: =SUM(H20:H25) -> 4.3 | I26: =SUM(I20:I25) -> 6.9 | J26: =SUM(J20:J25) -> 7.1 | K26: =SUM(K20:K25) -> 12.5 | L26: =SUM(D26:K26) -> 70.7 | M26: =SUM(M20:M25) -> 75700000 | N26: =SUM(N20:N25) -> 0 | O26: =SUM(O20:O25) -> 0 | P26: =SUM(P20:P25) -> 70.7 | Q26: =SUM(Q20:Q25) -> 75700000
B27: 単価 | D27: 1000000 | E27: 1000000 | F27: 1000000 | G27: 1000000 | H27: 1000000 | I27: 1000000 | J27: 1000000 | K27: 1400000
B28: 金額 | D28: =D26*D27 -> 8100000 | E28: =E26*E27 -> 4900000 | F28: =F26*F27 -> 10500000 | G28: =G26*G27 -> 16400000 | H28: =H26*H27 -> 4300000 | I28: =I26*I27 -> 6900000 | J28: =J26*J27 -> 7100000 | K28: =K26*K27 -> 17500000
Q29: =Q26-Q12 -> 6600000
C31: 再見積もり（開発フェーズ以降）
C32: パターン | D32: クラウドアーキ基盤に移行 | R32: 備考
D33: アプリ | N33: DB | P33: 全体
B34: No. | C34: システム | D34: 調査・要件定義 | E34: 設計 | F34: 製造 | G34: 結合テスト | H34: システムテスト | I34: ユーザテスト | J34: 本番稼働 | K34: 管理 | L34: 工数計 | M34: 金額 | N34: 工数計 | O34: 金額 | P34: 工数計 | Q34: 金額
B35: 1 | C35: 数量確定システム（千葉・徳山） | F35: 3.2 | G35: 5.2 | H35: 1.4 | I35: 1.9 | J35: 2 | K35: 3.9 | L35: =SUM(D35:K35) -> 17.6 | M35: =SUM(D35:J35)*1000000+K35*1400000 -> 19160000 | N35: 0 | O35: 0 | P35: =SUM(L35:L39)+N35 -> 52.1 | Q35: =SUM(M35:M39)+O35 -> 56740000
B36: 2 | C36: 用役管理システム（千葉・徳山） | F36: 2.1 | G36: 3.1 | H36: 1.1 | I36: 1.9 | J36: 2 | K36: 2.7 | L36: =SUM(D36:K36) -> 12.9 | M36: =SUM(D36:J36)*1000000+K36*1400000 -> 13980000
B37: 3 | C37: 千葉化学品質管理システム | F37: 2.2 | G37: 5.5 | H37: 0.8 | I37: 1.2 | J37: 0.6 | K37: 2.9 | L37: =SUM(D37:K37) -> 13.2 | M37: =SUM(D37:J37)*1000000+K37*1400000 -> 14360000
B38: 4 | C38: ＬＭＰＰ包装システム | F38: 2.1 | G38: 1.2 | H38: 0.8 | I38: 1.2 | J38: 0.6 | K38: 2 | L38: =SUM(D38:K38) -> 7.9 | M38: =SUM(D38:J38)*1000000+K38*1400000 -> 8700000
B39: 5 | C39: 工場DB | J39: 0.4 | K39: 0.1 | L39: =SUM(D39:K39) -> 0.5 | M39: =SUM(D39:J39)*1000000+K39*1400000 -> 540000
B40: 6 | C40: ヤ－ド操業システム（千葉・徳山） | F40: 0.9 | G40: 1.4 | H40: 0.2 | I40: 0.7 | J40: 1.5 | K40: 0.9 | L40: =SUM(D40:K40) -> 5.6 | M40: =SUM(D40:J40)*1000000+K40*1400000 -> 5960000 | N40: 0 | O40: =SUM(O34:O39) -> 0 | P40: =SUM(L40:L40)+N40 -> 5.6 | Q40: =SUM(M40:M40)+O35 -> 5960000
B41: 計 | D41: =SUM(D35:D40) -> 0 | E41: =SUM(E35:E40) -> 0 | F41: =SUM(F35:F40) -> 10.5 | G41: =SUM(G35:G40) -> 16.4 | H41: =SUM(H35:H40) -> 4.3 | I41: 6.9 | J41: =SUM(J35:J40) -> 7.1 | K41: 12.5 | L41: =SUM(D41:K41) -> 57.7 | M41: =SUM(M35:M40) -> 62700000 | N41: =SUM(N35:N40) -> 0 | O41: =SUM(O35:O40) -> 0 | P41: =SUM(P35:P40) -> 57.7 | Q41: =SUM(Q35:Q40) -> 62700000
B42: 単価 | D42: 1000000 | E42: 1000000 | F42: 1000000 | G42: 1000000 | H42: 1000000 | I42: 1000000 | J42: 1000000 | K42: 1400000
B43: 金額 | D43: =D41*D42 -> 0 | E43: =E41*E42 -> 0 | F43: =F41*F42 -> 10500000 | G43: =G41*G42 -> 16400000 | H43: =H41*H42 -> 4300000 | I43: =I41*I42 -> 6900000 | J43: =J41*J42 -> 7100000 | K43: =K41*K42 -> 17500000
C45: 再見積もり（開発フェーズ）
C46: パターン | D46: クラウドアーキ基盤に移行 | R46: 備考
D47: アプリ | N47: DB | P47: 全体
B48: No. | C48: システム | D48: 調査・要件定義 | E48: 設計 | F48: 製造 | G48: 結合テスト | H48: システムテスト | I48: ユーザテスト | J48: 本番稼働 | K48: 管理 | L48: 工数計 | M48: 金額 | N48: 工数計 | O48: 金額 | P48: 工数計 | Q48: 金額
B49: 1 | C49: 数量確定システム（千葉・徳山） | F49: 3.2 | G49: 5.2 | K49: 2 | L49: =SUM(D49:K49) -> 10.4 | M49: =SUM(D49:J49)*1000000+K49*1400000 -> 11200000 | N49: 0 | O49: 0 | P49: =SUM(L49:L53)+N49 -> 30.8 | Q49: =SUM(M49:M53)+O49 -> 33280000
B50: 2 | C50: 用役管理システム（千葉・徳山） | F50: 2.1 | G50: 3.1 | K50: 1.4 | L50: =SUM(D50:K50) -> 6.6 | M50: =SUM(D50:J50)*1000000+K50*1400000 -> 7160000
B51: 3 | C51: 千葉化学品質管理システム | F51: 2.2 | G51: 5.5 | K51: 1.8 | L51: =SUM(D51:K51) -> 9.5 | M51: =SUM(D51:J51)*1000000+K51*1400000 -> 10220000
B52: 4 | C52: ＬＭＰＰ包装システム | F52: 2.1 | G52: 1.2 | K52: 1 | L52: =SUM(D52:K52) -> 4.3 | M52: =SUM(D52:J52)*1000000+K52*1400000 -> 4700000
B53: 5 | C53: 工場DB | L53: =SUM(D53:K53) -> 0 | M53: =SUM(D53:J53)*1000000+K53*1400000 -> 0
B54: 6 | C54: ヤ－ド操業システム（千葉・徳山） | F54: 0.9 | G54: 1.4 | K54: 0.5 | L54: =SUM(D54:K54) -> 2.8 | M54: =SUM(D54:J54)*1000000+K54*1400000 -> 3000000 | N54: 0 | O54: =SUM(O48:O53) -> 0 | P54: =SUM(L54:L54)+N54 -> 2.8 | Q54: =SUM(M54:M54)+O49 -> 3000000
B55: 計 | D55: =SUM(D49:D54) -> 0 | E55: =SUM(E49:E54) -> 0 | F55: =SUM(F49:F54) -> 10.5 | G55: =SUM(G49:G54) -> 16.4 | H55: =SUM(H49:H54) -> 0 | I55: =SUM(I49:I54) -> 0 | J55: =SUM(J49:J54) -> 0 | K55: =SUM(K49:K54) -> 6.7 | L55: =SUM(D55:K55) -> 33.6 | M55: =SUM(M49:M54) -> 36280000 | N55: =SUM(N49:N54) -> 0 | O55: =SUM(O49:O54) -> 0 | P55: =SUM(P49:P54) -> 33.6 | Q55: =SUM(Q49:Q54) -> 36280000
B56: 単価 | D56: 1000000 | E56: 1000000 | F56: 1000000 | G56: 1000000 | H56: 1000000 | I56: 1000000 | J56: 1000000 | K56: 1400000
B57: 金額 | D57: =D55*D56 -> 0 | E57: =E55*E56 -> 0 | F57: =F55*F56 -> 10500000 | G57: =G55*G56 -> 16400000 | H57: =H55*H56 -> 0 | I57: =I55*I56 -> 0 | J57: =J55*J56 -> 0 | K57: =K55*K56 -> 9380000
C60: 再見積もり（移行フェーズ）
C61: パターン | D61: クラウドアーキ基盤に移行 | R61: 備考
D62: アプリ | N62: DB | P62: 全体
B63: No. | C63: システム | D63: 調査・要件定義 | E63: 設計 | F63: 製造 | G63: 結合テスト | H63: システムテスト | I63: ユーザテスト | J63: 本番稼働 | K63: 管理 | L63: 工数計 | M63: 金額 | N63: 工数計 | O63: 金額 | P63: 工数計 | Q63: 金額
B64: 1 | C64: 数量確定システム（千葉・徳山） | H64: 1.4 | I64: 1.9 | J64: 2 | K64: 1.6 | L64: =SUM(D64:K64) -> 6.9 | M64: =SUM(D64:J64)*1000000+K64*1400000 -> 7540000 | N64: 0 | O64: 0 | P64: =SUM(L64:L68)+N64 -> 21 | Q64: =SUM(M64:M68)+O64 -> 23040000
B65: 2 | C65: 用役管理システム（千葉・徳山） | H65: 1.1 | I65: 1.9 | J65: 2 | K65: 1.3 | L65: =SUM(D65:K65) -> 6.3 | M65: =SUM(D65:J65)*1000000+K65*1400000 -> 6820000
B66: 3 | C66: 千葉化学品質管理システム | H66: 0.8 | I66: 1.2 | J66: 0.6 | K66: 1 | L66: =SUM(D66:K66) -> 3.6 | M66: =SUM(D66:J66)*1000000+K66*1400000 -> 4000000
B67: 4 | C67: ＬＭＰＰ包装システム | H67: 0.8 | I67: 1.2 | J67: 0.6 | K67: 1.1 | L67: =SUM(D67:K67) -> 3.7 | M67: =SUM(D67:J67)*1000000+K67*1400000 -> 4140000
B68: 5 | C68: 工場DB | J68: 0.4 | K68: 0.1 | L68: =SUM(D68:K68) -> 0.5 | M68: =SUM(D68:J68)*1000000+K68*1400000 -> 540000
B69: 6 | C69: ヤ－ド操業システム（千葉・徳山） | H69: 0.2 | I69: 0.7 | J69: 1.5 | K69: 0.7 | L69: =SUM(D69:K69) -> 3.1 | M69: =SUM(D69:J69)*1000000+K69*1400000 -> 3380000 | N69: 0 | O69: =SUM(O63:O68) -> 0 | P69: =SUM(L69:L69)+N69 -> 3.1 | Q69: =SUM(M69:M69)+O64 -> 3380000
B70: 計 | D70: =SUM(D64:D69) -> 0 | E70: =SUM(E64:E69) -> 0 | F70: =SUM(F64:F69) -> 0 | G70: =SUM(G64:G69) -> 0 | H70: =SUM(H64:H69) -> 4.3 | I70: 6.9 | J70: =SUM(J64:J69) -> 7.1 | K70: =SUM(K64:K69) -> 5.8 | L70: =SUM(D70:K70) -> 24.1 | M70: =SUM(M64:M69) -> 26420000 | N70: =SUM(N64:N69) -> 0 | O70: =SUM(O64:O69) -> 0 | P70: =SUM(P64:P69) -> 24.1 | Q70: =SUM(Q64:Q69) -> 26420000
B71: 単価 | D71: 1000000 | E71: 1000000 | F71: 1000000 | G71: 1000000 | H71: 1000000 | I71: 1000000 | J71: 1000000 | K71: 1400000
B72: 金額 | D72: =D70*D71 -> 0 | E72: =E70*E71 -> 0 | F72: =F70*F71 -> 0 | G72: =G70*G71 -> 0 | H72: =H70*H71 -> 4300000 | I72: =I70*I71 -> 6900000 | J72: =J70*J71 -> 7100000 | K72: =K70*K71 -> 8120000
K75: 検算
L76: システム | M76: 開発＋移行 | N76: 開発以降
L77: 数量確定システム（千葉・徳山） | M77: =M49+M64 -> 18740000 | N77: =M35 -> 19160000
L78: 用役管理システム（千葉・徳山） | M78: =M50+M65 -> 13980000 | N78: =M36 -> 13980000
L79: 千葉化学品質管理システム | M79: =M51+M66 -> 14220000 | N79: =M37 -> 14360000
L80: ＬＭＰＰ包装システム | M80: =M52+M67 -> 8840000 | N80: =M38 -> 8700000
L81: 工場DB | M81: =M53+M68 -> 540000 | N81: =M39 -> 540000
L82: ヤ－ド操業システム（千葉・徳山） | M82: =M54+M69 -> 6380000 | N82: =M40 -> 5960000
M83: =SUM(M77:M82) -> 62700000 | N83: =SUM(N77:N82) -> 62700000

Sheet 再見積 (システム・工程別サマリ) BK
C1: 工数直入力のため注意！！
C2: 見積（工程別サマリ）
C3: パターン | D3: クラウドアーキ基盤に移行 | R3: 備考
D4: アプリ | N4: DB | P4: 全体
B5: No. | C5: システム | D5: 調査・要件定義 | E5: 設計 | F5: 製造 | G5: 結合テスト | H5: システムテスト | I5: ユーザテスト | J5: 本番稼働 | K5: 管理 | L5: 工数計 | M5: 金額 | N5: 工数計 | O5: 金額 | P5: 工数計 | Q5: 金額
B6: 1 | C6: 数量確定システム（千葉・徳山） | D6: 3.2 | E6: 1.6 | F6: 2.7 | G6: 5.2 | H6: 1.4 | I6: 0.8 | J6: 2 | K6: 3.8 | L6: =SUM(D6:K6) -> 20.7 | M6: =SUM(D6:J6)*1000000+K6*1400000 -> 22220000 | N6: 0 | O6: 0 | P6: =SUM(L6:L10)+N6 -> 58.4 | Q6: =SUM(M6:M10)+O6 -> 63040000
B7: 2 | C7: 用役管理システム（千葉・徳山） | D7: 1.4 | E7: 1.1 | F7: 1.5 | G7: 3.1 | H7: 1.1 | I7: 0.8 | J7: 2 | K7: 2.6 | L7: =SUM(D7:K7) -> 13.6 | M7: =SUM(D7:J7)*1000000+K7*1400000 -> 14640000
B8: 3 | C8: 千葉化学品質管理システム | D8: 1.7 | E8: 1.4 | F8: 1.6 | G8: 5.5 | H8: 0.8 | I8: 0.5 | J8: 0.6 | K8: 2.8 | L8: =SUM(D8:K8) -> 14.9 | M8: =SUM(D8:J8)*1000000+K8*1400000 -> 16020000
B9: 4 | C9: ＬＭＰＰ包装システム | D9: 1.3 | E9: 0.4 | F9: 1.6 | G9: 1.2 | H9: 0.8 | I9: 0.5 | J9: 0.6 | K9: 1.9 | L9: =SUM(D9:K9) -> 8.3 | M9: =SUM(D9:J9)*1000000+K9*1400000 -> 9060000
B10: 5 | C10: 工場DB | J10: 0.4 | K10: 0.5 | L10: =SUM(D10:K10) -> 0.9 | M10: =SUM(D10:J10)*1000000+K10*1400000 -> 1100000
B11: 6 | C11: ヤ－ド操業システム（千葉・徳山） | D11: 0.5 | E11: 0.4 | F11: 0.7 | G11: 1.4 | H11: 0.2 | I11: 0.1 | J11: 1.5 | K11: 0.9 | L11: =SUM(D11:K11) -> 5.7 | M11: =SUM(D11:J11)*1000000+K11*1400000 -> 6060000 | N11: 0 | O11: =SUM(O5:O10) -> 0 | P11: =SUM(L11:L11)+N11 -> 5.7 | Q11: =SUM(M11:M11)+O6 -> 6060000
B12: 計 | D12: =SUM(D6:D11) -> 8.1 | E12: =SUM(E6:E11) -> 4.9 | F12: =SUM(F6:F11) -> 8.1 | G12: =SUM(G6:G11) -> 16.4 | H12: =SUM(H6:H11) -> 4.3 | I12: =SUM(I6:I11) -> 2.7 | J12: =SUM(J6:J11) -> 7.1 | K12: =SUM(K6:K11) -> 12.5 | L12: =SUM(D12:K12) -> 64.1 | M12: =SUM(M6:M11) -> 69100000 | N12: =SUM(N6:N11) -> 0 | O12: =SUM(O6:O11) -> 0 | P12: =SUM(P6:P11) -> 64.1 | Q12: =SUM(Q6:Q11) -> 69100000
B13: 単価 | D13: 1000000 | E13: 1000000 | F13: 1000000 | G13: 1000000 | H13: 1000000 | I13: 1000000 | J13: 1000000 | K13: 1400000
B14: 金額 | D14: =D12*D13 -> 8100000 | E14: =E12*E13 -> 4900000 | F14: =F12*F13 -> 8100000 | G14: =G12*G13 -> 16400000 | H14: =H12*H13 -> 4300000 | I14: =I12*I13 -> 2700000 | J14: =J12*J13 -> 7100000 | K14: =K12*K13 -> 17500000
C16: 再見積もり（工程別サマリ）
C17: パターン | D17: クラウドアーキ基盤に移行 | R17: 備考
D18: アプリ | N18: DB | P18: 全体
B19: No. | C19: システム | D19: 調査・要件定義 | E19: 設計 | F19: 製造 | G19: 結合テスト | H19: システムテスト | I19: ユーザテスト | J19: 本番稼働 | K19: 管理 | L19: 工数計 | M19: 金額 | N19: 工数計 | O19: 金額 | P19: 工数計 | Q19: 金額
B20: 1 | C20: 数量確定システム（千葉・徳山） | D20: 3.2 | E20: 1.6 | F20: 2 | G20: 5.7 | H20: 1.5 | I20: 3 | J20: 0.8 | K20: 3.5 | L20: =SUM(D20:K20) -> 21.3 | M20: =SUM(D20:J20)*1000000+K20*1400000 -> 22700000 | N20: 0 | O20: 0 | P20: =SUM(L20:L24)+N20 -> 63.9 | Q20: =SUM(M20:M24)+O20 -> 68420000
B21: 2 | C21: 用役管理システム（千葉・徳山） | D21: 1.4 | E21: 1.1 | F21: 1.5 | G21: 3.4 | H21: 1.5 | I21: 3 | J21: 0.8 | K21: 2.7 | L21: =SUM(D21:K21) -> 15.4 | M21: =SUM(D21:J21)*1000000+K21*1400000 -> 16480000
B22: 3 | C22: 千葉化学品質管理システム | D22: 1.7 | E22: 1.4 | F22: 1.5 | G22: 6 | H22: 1 | I22: 1.3 | J22: 0.5 | K22: 2.7 | L22: =SUM(D22:K22) -> 16.1 | M22: =SUM(D22:J22)*1000000+K22*1400000 -> 17180000
B23: 4 | C23: ＬＭＰＰ包装システム | D23: 1.3 | E23: 0.4 | F23: 1.5 | G23: 2.4 | H23: 1 | I23: 1.2 | J23: 0.5 | K23: 2.3 | L23: =SUM(D23:K23) -> 10.6 | M23: =SUM(D23:J23)*1000000+K23*1400000 -> 11520000
B24: 5 | C24: 工場DB | J24: 0.4 | K24: 0.1 | L24: =SUM(D24:K24) -> 0.5 | M24: =SUM(D24:J24)*1000000+K24*1400000 -> 540000
B25: 6 | C25: ヤ－ド操業システム（千葉・徳山） | D25: 0.5 | E25: 0.4 | F25: 1 | G25: 1.5 | H25: 0.5 | I25: 1.5 | J25: 1 | K25: 1.2 | L25: =SUM(D25:K25) -> 7.6 | M25: =SUM(D25:J25)*1000000+K25*1400000 -> 8080000 | N25: 0 | O25: =SUM(O19:O24) -> 0 | P25: =SUM(L25:L25)+N25 -> 7.6 | Q25: =SUM(M25:M25)+O20 -> 8080000
B26: 計 | D26: =SUM(D20:D25) -> 8.1 | E26: =SUM(E20:E25) -> 4.9 | F26: =SUM(F20:F25) -> 7.5 | G26: =SUM(G20:G25) -> 19 | H26: =SUM(H20:H25) -> 5.5 | I26: =SUM(I20:I25) -> 10 | J26: =SUM(J20:J25) -> 4 | K26: =SUM(K20:K25) -> 12.5 | L26: =SUM(D26:K26) -> 71.5 | M26: =SUM(M20:M25) -> 76500000 | N26: =SUM(N20:N25) -> 0 | O26: =SUM(O20:O25) -> 0 | P26: =SUM(P20:P25) -> 71.5 | Q26: =SUM(Q20:Q25) -> 76500000
B27: 単価 | D27: 1000000 | E27: 1000000 | F27: 1000000 | G27: 1000000 | H27: 1000000 | I27: 1000000 | J27: 1000000 | K27: 1400000
B28: 金額 | D28: =D26*D27 -> 8100000 | E28: =E26*E27 -> 4900000 | F28: =F26*F27 -> 7500000 | G28: =G26*G27 -> 19000000 | H28: =H26*H27 -> 5500000 | I28: =I26*I27 -> 10000000 | J28: =J26*J27 -> 4000000 | K28: =K26*K27 -> 17500000
Q29: =Q26-Q12 -> 7400000
C31: 再見積もり（開発フェーズ以降）
C32: パターン | D32: クラウドアーキ基盤に移行 | R32: 備考
D33: アプリ | N33: DB | P33: 全体
B34: No. | C34: システム | D34: 調査・要件定義 | E34: 設計 | F34: 製造 | G34: 結合テスト | H34: システムテスト | I34: ユーザテスト | J34: 本番稼働 | K34: 管理 | L34: 工数計 | M34: 金額 | N34: 工数計 | O34: 金額 | P34: 工数計 | Q34: 金額
B35: 1 | C35: 数量確定システム（千葉・徳山） | F35: 2 | G35: 5.7 | H35: 1.5 | I35: 3 | J35: 0.8 | K35: 3.5 | L35: =SUM(D35:K35) -> 16.5 | M35: =SUM(D35:J35)*1000000+K35*1400000 -> 17900000 | N35: 0 | O35: 0 | P35: =SUM(L35:L39)+N35 -> 51.8 | Q35: =SUM(M35:M39)+O35 -> 56320000
B36: 2 | C36: 用役管理システム（千葉・徳山） | F36: 1.5 | G36: 3.4 | H36: 1.5 | I36: 3 | J36: 0.8 | K36: 2.7 | L36: =SUM(D36:K36) -> 12.9 | M36: =SUM(D36:J36)*1000000+K36*1400000 -> 13980000
B37: 3 | C37: 千葉化学品質管理システム | F37: 1.5 | G37: 6 | H37: 1 | I37: 1.3 | J37: 0.5 | K37: 2.7 | L37: =SUM(D37:K37) -> 13 | M37: =SUM(D37:J37)*1000000+K37*1400000 -> 14080000
B38: 4 | C38: ＬＭＰＰ包装システム | F38: 1.5 | G38: 2.4 | H38: 1 | I38: 1.2 | J38: 0.5 | K38: 2.3 | L38: =SUM(D38:K38) -> 8.9 | M38: =SUM(D38:J38)*1000000+K38*1400000 -> 9820000
B39: 5 | C39: 工場DB | J39: 0.4 | K39: 0.1 | L39: =SUM(D39:K39) -> 0.5 | M39: =SUM(D39:J39)*1000000+K39*1400000 -> 540000
B40: 6 | C40: ヤ－ド操業システム（千葉・徳山） | F40: 1 | G40: 1.5 | H40: 0.5 | I40: 1.5 | J40: 1 | K40: 1.2 | L40: =SUM(D40:K40) -> 6.7 | M40: =SUM(D40:J40)*1000000+K40*1400000 -> 7180000 | N40: 0 | O40: =SUM(O34:O39) -> 0 | P40: =SUM(L40:L40)+N40 -> 6.7 | Q40: =SUM(M40:M40)+O35 -> 7180000
B41: 計 | D41: =SUM(D35:D40) -> 0 | E41: =SUM(E35:E40) -> 0 | F41: =SUM(F35:F40) -> 7.5 | G41: =SUM(G35:G40) -> 19 | H41: =SUM(H35:H40) -> 5.5 | I41: 6.9 | J41: =SUM(J35:J40) -> 4 | K41: 12.5 | L41: =SUM(D41:K41) -> 55.4 | M41: =SUM(M35:M40) -> 63500000 | N41: =SUM(N35:N40) -> 0 | O41: =SUM(O35:O40) -> 0 | P41: =SUM(P35:P40) -> 58.5 | Q41: =SUM(Q35:Q40) -> 63500000
B42: 単価 | D42: 1000000 | E42: 1000000 | F42: 1000000 | G42: 1000000 | H42: 1000000 | I42: 1000000 | J42: 1000000 | K42: 1400000
B43: 金額 | D43: =D41*D42 -> 0 | E43: =E41*E42 -> 0 | F43: =F41*F42 -> 7500000 | G43: =G41*G42 -> 19000000 | H43: =H41*H42 -> 5500000 | I43: =I41*I42 -> 6900000 | J43: =J41*J42 -> 4000000 | K43: =K41*K42 -> 17500000
C45: 再見積もり（開発フェーズ）
C46: パターン | D46: クラウドアーキ基盤に移行 | R46: 備考
D47: アプリ | N47: DB | P47: 全体
B48: No. | C48: システム | D48: 調査・要件定義 | E48: 設計 | F48: 製造 | G48: 結合テスト | H48: システムテスト | I48: ユーザテスト | J48: 本番稼働 | K48: 管理 | L48: 工数計 | M48: 金額 | N48: 工数計 | O48: 金額 | P48: 工数計 | Q48: 金額
B49: 1 | C49: 数量確定システム（千葉・徳山） | F49: 2 | G49: 5.7 | K49: 2 | L49: =SUM(D49:K49) -> 9.7 | M49: =SUM(D49:J49)*1000000+K49*1400000 -> 10500000 | N49: 0 | O49: 0 | P49: =SUM(L49:L53)+N49 -> 30.2 | Q49: =SUM(M49:M53)+O49 -> 32680000
B50: 2 | C50: 用役管理システム（千葉・徳山） | F50: 1.5 | G50: 3.4 | K50: 1.4 | L50: =SUM(D50:K50) -> 6.3 | M50: =SUM(D50:J50)*1000000+K50*1400000 -> 6860000
B51: 3 | C51: 千葉化学品質管理システム | F51: 1.5 | G51: 6 | K51: 1.8 | L51: =SUM(D51:K51) -> 9.3 | M51: =SUM(D51:J51)*1000000+K51*1400000 -> 10020000
B52: 4 | C52: ＬＭＰＰ包装システム | F52: 1.5 | G52: 2.4 | K52: 1 | L52: =SUM(D52:K52) -> 4.9 | M52: =SUM(D52:J52)*1000000+K52*1400000 -> 5300000
B53: 5 | C53: 工場DB | L53: =SUM(D53:K53) -> 0 | M53: =SUM(D53:J53)*1000000+K53*1400000 -> 0
B54: 6 | C54: ヤ－ド操業システム（千葉・徳山） | F54: 1 | G54: 1.5 | K54: 0.5 | L54: =SUM(D54:K54) -> 3 | M54: =SUM(D54:J54)*1000000+K54*1400000 -> 3200000 | N54: 0 | O54: =SUM(O48:O53) -> 0 | P54: =SUM(L54:L54)+N54 -> 3 | Q54: =SUM(M54:M54)+O49 -> 3200000
B55: 計 | D55: =SUM(D49:D54) -> 0 | E55: =SUM(E49:E54) -> 0 | F55: =SUM(F49:F54) -> 7.5 | G55: =SUM(G49:G54) -> 19 | H55: =SUM(H49:H54) -> 0 | I55: =SUM(I49:I54) -> 0 | J55: =SUM(J49:J54) -> 0 | K55: =SUM(K49:K54) -> 6.7 | L55: =SUM(D55:K55) -> 33.2 | M55: =SUM(M49:M54) -> 35880000 | N55: =SUM(N49:N54) -> 0 | O55: =SUM(O49:O54) -> 0 | P55: =SUM(P49:P54) -> 33.2 | Q55: =SUM(Q49:Q54) -> 35880000
B56: 単価 | D56: 1000000 | E56: 1000000 | F56: 1000000 | G56: 1000000 | H56: 1000000 | I56: 1000000 | J56: 1000000 | K56: 1400000
B57: 金額 | D57: =D55*D56 -> 0 | E57: =E55*E56 -> 0 | F57: =F55*F56 -> 7500000 | G57: =G55*G56 -> 19000000 | H57: =H55*H56 -> 0 | I57: =I55*I56 -> 0 | J57: =J55*J56 -> 0 | K57: =K55*K56 -> 9380000
C60: 再見積もり（移行フェーズ）
C61: パターン | D61: クラウドアーキ基盤に移行 | R61: 備考
D62: アプリ | N62: DB | P62: 全体
B63: No. | C63: システム | D63: 調査・要件定義 | E63: 設計 | F63: 製造 | G63: 結合テスト | H63: システムテスト | I63: ユーザテスト | J63: 本番稼働 | K63: 管理 | L63: 工数計 | M63: 金額 | N63: 工数計 | O63: 金額 | P63: 工数計 | Q63: 金額
B64: 1 | C64: 数量確定システム（千葉・徳山） | H64: 1.5 | I64: 3 | J64: 0.8 | K64: 1.6 | L64: =SUM(D64:K64) -> 6.9 | M64: =SUM(D64:J64)*1000000+K64*1400000 -> 7540000 | N64: 0 | O64: 0 | P64: =SUM(L64:L68)+N64 -> 21.6 | Q64: =SUM(M64:M68)+O64 -> 23640000
B65: 2 | C65: 用役管理システム（千葉・徳山） | H65: 1.5 | I65: 3 | J65: 0.8 | K65: 1.3 | L65: =SUM(D65:K65) -> 6.6 | M65: =SUM(D65:J65)*1000000+K65*1400000 -> 7120000
B66: 3 | C66: 千葉化学品質管理システム | H66: 1 | I66: 1.3 | J66: 0.5 | K66: 1 | L66: =SUM(D66:K66) -> 3.8 | M66: =SUM(D66:J66)*1000000+K66*1400000 -> 4200000
B67: 4 | C67: ＬＭＰＰ包装システム | H67: 1 | I67: 1.2 | J67: 0.5 | K67: 1.1 | L67: =SUM(D67:K67) -> 3.8 | M67: =SUM(D67:J67)*1000000+K67*1400000 -> 4240000
B68: 5 | C68: 工場DB | J68: 0.4 | K68: 0.1 | L68: =SUM(D68:K68) -> 0.5 | M68: =SUM(D68:J68)*1000000+K68*1400000 -> 540000
B69: 6 | C69: ヤ－ド操業システム（千葉・徳山） | H69: 0.5 | I69: 1.5 | J69: 1 | K69: 0.7 | L69: =SUM(D69:K69) -> 3.7 | M69: =SUM(D69:J69)*1000000+K69*1400000 -> 3980000 | N69: 0 | O69: =SUM(O63:O68) -> 0 | P69: =SUM(L69:L69)+N69 -> 3.7 | Q69: =SUM(M69:M69)+O64 -> 3980000
B70: 計 | D70: =SUM(D64:D69) -> 0 | E70: =SUM(E64:E69) -> 0 | F70: =SUM(F64:F69) -> 0 | G70: =SUM(G64:G69) -> 0 | H70: =SUM(H64:H69) -> 5.5 | I70: 6.9 | J70: =SUM(J64:J69) -> 4 | K70: =SUM(K64:K69) -> 5.8 | L70: =SUM(D70:K70) -> 22.2 | M70: =SUM(M64:M69) -> 27620000 | N70: =SUM(N64:N69) -> 0 | O70: =SUM(O64:O69) -> 0 | P70: =SUM(P64:P69) -> 25.3 | Q70: =SUM(Q64:Q69) -> 27620000
B71: 単価 | D71: 1000000 | E71: 1000000 | F71: 1000000 | G71: 1000000 | H71: 1000000 | I71: 1000000 | J71: 1000000 | K71: 1400000
B72: 金額 | D72: =D70*D71 -> 0 | E72: =E70*E71 -> 0 | F72: =F70*F71 -> 0 | G72: =G70*G71 -> 0 | H72: =H70*H71 -> 5500000 | I72: =I70*I71 -> 6900000 | J72: =J70*J71 -> 4000000 | K72: =K70*K71 -> 8120000
K75: 検算
L76: システム | M76: 開発＋移行 | N76: 開発以降
L77: 数量確定システム（千葉・徳山） | M77: =M49+M64 -> 18040000 | N77: =M35 -> 17900000
L78: 用役管理システム（千葉・徳山） | M78: =M50+M65 -> 13980000 | N78: =M36 -> 13980000
L79: 千葉化学品質管理システム | M79: =M51+M66 -> 14220000 | N79: =M37 -> 14080000
L80: ＬＭＰＰ包装システム | M80: =M52+M67 -> 9540000 | N80: =M38 -> 9820000
L81: 工場DB | M81: =M53+M68 -> 540000 | N81: =M39 -> 540000
L82: ヤ－ド操業システム（千葉・徳山） | M82: =M54+M69 -> 7180000 | N82: =M40 -> 7180000
M83: =SUM(M77:M82) -> 63500000 | N83: =SUM(N77:N82) -> 63500000

Sheet 再見積 (システム・工程別サマリ) 
C1: 工数直入力のため注意！！
C2: 見積（工程別サマリ）
C3: パターン | D3: クラウドアーキ基盤に移行 | R3: 備考
D4: アプリ | N4: DB | P4: 全体
B5: No. | C5: システム | D5: 調査・要件定義 | E5: 設計 | F5: 製造 | G5: 結合テスト | H5: システムテスト | I5: ユーザテスト | J5: 本番稼働 | K5: 管理 | L5: 工数計 | M5: 金額 | N5: 工数計 | O5: 金額 | P5: 工数計 | Q5: 金額
B6: 1 | C6: 数量確定システム（千葉・徳山） | D6: 3.2 | E6: 1.6 | F6: 2.7 | G6: 5.2 | H6: 1.4 | I6: 0.8 | J6: 2 | K6: 3.8 | L6: =SUM(D6:K6) -> 20.7 | M6: =SUM(D6:J6)*1000000+K6*1400000 -> 22220000 | N6: 0 | O6: 0 | P6: =SUM(L6:L10)+N6 -> 58.4 | Q6: =SUM(M6:M10)+O6 -> 63040000
B7: 2 | C7: 用役管理システム（千葉・徳山） | D7: 1.4 | E7: 1.1 | F7: 1.5 | G7: 3.1 | H7: 1.1 | I7: 0.8 | J7: 2 | K7: 2.6 | L7: =SUM(D7:K7) -> 13.6 | M7: =SUM(D7:J7)*1000000+K7*1400000 -> 14640000
B8: 3 | C8: 千葉化学品質管理システム | D8: 1.7 | E8: 1.4 | F8: 1.6 | G8: 5.5 | H8: 0.8 | I8: 0.5 | J8: 0.6 | K8: 2.8 | L8: =SUM(D8:K8) -> 14.9 | M8: =SUM(D8:J8)*1000000+K8*1400000 -> 16020000
B9: 4 | C9: ＬＭＰＰ包装システム | D9: 1.3 | E9: 0.4 | F9: 1.6 | G9: 1.2 | H9: 0.8 | I9: 0.5 | J9: 0.6 | K9: 1.9 | L9: =SUM(D9:K9) -> 8.3 | M9: =SUM(D9:J9)*1000000+K9*1400000 -> 9060000
B10: 5 | C10: 工場DB | J10: 0.4 | K10: 0.5 | L10: =SUM(D10:K10) -> 0.9 | M10: =SUM(D10:J10)*1000000+K10*1400000 -> 1100000
B11: 6 | C11: ヤ－ド操業システム（千葉・徳山） | D11: 0.5 | E11: 0.4 | F11: 0.7 | G11: 1.4 | H11: 0.2 | I11: 0.1 | J11: 1.5 | K11: 0.9 | L11: =SUM(D11:K11) -> 5.7 | M11: =SUM(D11:J11)*1000000+K11*1400000 -> 6060000 | N11: 0 | O11: =SUM(O5:O10) -> 0 | P11: =SUM(L11:L11)+N11 -> 5.7 | Q11: =SUM(M11:M11)+O6 -> 6060000
B12: 計 | D12: =SUM(D6:D11) -> 8.1 | E12: =SUM(E6:E11) -> 4.9 | F12: =SUM(F6:F11) -> 8.1 | G12: =SUM(G6:G11) -> 16.4 | H12: =SUM(H6:H11) -> 4.3 | I12: =SUM(I6:I11) -> 2.7 | J12: =SUM(J6:J11) -> 7.1 | K12: =SUM(K6:K11) -> 12.5 | L12: =SUM(D12:K12) -> 64.1 | M12: =SUM(M6:M11) -> 69100000 | N12: =SUM(N6:N11) -> 0 | O12: =SUM(O6:O11) -> 0 | P12: =SUM(P6:P11) -> 64.1 | Q12: =SUM(Q6:Q11) -> 69100000
B13: 単価 | D13: 1000000 | E13: 1000000 | F13: 1000000 | G13: 1000000 | H13: 1000000 | I13: 1000000 | J13: 1000000 | K13: 1400000
B14: 金額 | D14: =D12*D13 -> 8100000 | E14: =E12*E13 -> 4900000 | F14: =F12*F13 -> 8100000 | G14: =G12*G13 -> 16400000 | H14: =H12*H13 -> 4300000 | I14: =I12*I13 -> 2700000 | J14: =J12*J13 -> 7100000 | K14: =K12*K13 -> 17500000
C16: 再見積もり（工程別サマリ）
C17: パターン | D17: クラウドアーキ基盤に移行 | R17: 備考
D18: アプリ | N18: DB | P18: 全体
B19: No. | C19: システム | D19: 調査・要件定義 | E19: 設計 | F19: 製造 | G19: 結合テスト | H19: システムテスト | I19: ユーザテスト | J19: 本番稼働 | K19: 管理 | L19: 工数計 | M19: 金額 | N19: 工数計 | O19: 金額 | P19: 工数計 | Q19: 金額
B20: 1 | C20: 数量確定システム（千葉・徳山） | D20: 3.2 | E20: 1.6 | F20: 2 | G20: 5.7 | H20: 1.5 | I20: 1 | J20: 2 | K20: 3.6 | L20: =SUM(D20:K20) -> 20.6 | M20: =SUM(D20:J20)*1000000+K20*1400000 -> 22040000 | N20: 0 | O20: 0 | P20: =SUM(L20:L24)+N20 -> 61.6 | Q20: =SUM(M20:M24)+O20 -> 66200000
B21: 2 | C21: 用役管理システム（千葉・徳山） | D21: 1.4 | E21: 1.1 | F21: 1.5 | G21: 3.4 | H21: 1.5 | I21: 1 | J21: 2 | K21: 2.7 | L21: =SUM(D21:K21) -> 14.6 | M21: =SUM(D21:J21)*1000000+K21*1400000 -> 15680000
B22: 3 | C22: 千葉化学品質管理システム | D22: 1.7 | E22: 1.4 | F22: 1.5 | G22: 6 | H22: 1 | I22: 0.7 | J22: 0.6 | K22: 2.8 | L22: =SUM(D22:K22) -> 15.7 | M22: =SUM(D22:J22)*1000000+K22*1400000 -> 16820000
B23: 4 | C23: ＬＭＰＰ包装システム | D23: 1.3 | E23: 0.4 | F23: 1.5 | G23: 2.4 | H23: 1 | I23: 0.7 | J23: 0.6 | K23: 2.3 | L23: =SUM(D23:K23) -> 10.2 | M23: =SUM(D23:J23)*1000000+K23*1400000 -> 11120000
B24: 5 | C24: 工場DB | J24: 0.4 | K24: 0.1 | L24: =SUM(D24:K24) -> 0.5 | M24: =SUM(D24:J24)*1000000+K24*1400000 -> 540000
B25: 6 | C25: ヤ－ド操業システム（千葉・徳山） | D25: 0.5 | E25: 0.4 | F25: 1 | G25: 1.5 | H25: 0.5 | I25: 0.3 | J25: 1.5 | K25: 1.2 | L25: =SUM(D25:K25) -> 6.9 | M25: =SUM(D25:J25)*1000000+K25*1400000 -> 7380000 | N25: 0 | O25: =SUM(O19:O24) -> 0 | P25: =SUM(L25:L25)+N25 -> 6.9 | Q25: =SUM(M25:M25)+O20 -> 7380000
B26: 計 | D26: =SUM(D20:D25) -> 8.1 | E26: =SUM(E20:E25) -> 4.9 | F26: =SUM(F20:F25) -> 7.5 | G26: =SUM(G20:G25) -> 19 | H26: =SUM(H20:H25) -> 5.5 | I26: =SUM(I20:I25) -> 3.7 | J26: =SUM(J20:J25) -> 7.1 | K26: =SUM(K20:K25) -> 12.7 | L26: =SUM(D26:K26) -> 68.5 | M26: =SUM(M20:M25) -> 73580000 | N26: =SUM(N20:N25) -> 0 | O26: =SUM(O20:O25) -> 0 | P26: =SUM(P20:P25) -> 68.5 | Q26: =SUM(Q20:Q25) -> 73580000
B27: 単価 | D27: 1000000 | E27: 1000000 | F27: 1000000 | G27: 1000000 | H27: 1000000 | I27: 1000000 | J27: 1000000 | K27: 1400000
B28: 金額 | D28: =D26*D27 -> 8100000 | E28: =E26*E27 -> 4900000 | F28: =F26*F27 -> 7500000 | G28: =G26*G27 -> 19000000 | H28: =H26*H27 -> 5500000 | I28: =I26*I27 -> 3700000 | J28: =J26*J27 -> 7100000 | K28: =K26*K27 -> 17780000
Q29: =Q26-Q12 -> 4480000
C31: 再見積もり（開発フェーズ以降）
C32: パターン | D32: クラウドアーキ基盤に移行 | R32: 備考
D33: アプリ | N33: DB | P33: 全体
B34: No. | C34: システム | D34: 調査・要件定義 | E34: 設計 | F34: 製造 | G34: 結合テスト | H34: システムテスト | I34: ユーザテスト | J34: 本番稼働 | K34: 管理 | L34: 工数計 | M34: 金額 | N34: 工数計 | O34: 金額 | P34: 工数計 | Q34: 金額
B35: 1 | C35: 数量確定システム（千葉・徳山） | F35: 2 | G35: 5.7 | H35: 1.5 | I35: 1 | J35: 2 | K35: 3.2 | L35: =SUM(D35:K35) -> 15.4 | M35: =SUM(D35:J35)*1000000+K35*1400000 -> 16680000 | N35: 0 | O35: 0 | P35: =SUM(L35:L39)+N35 -> 47.9 | Q35: =SUM(M35:M39)+O35 -> 51860000
B36: 2 | C36: 用役管理システム（千葉・徳山） | F36: 1.5 | G36: 3.4 | H36: 1.5 | I36: 1 | J36: 2 | K36: 2.2 | L36: =SUM(D36:K36) -> 11.6 | M36: =SUM(D36:J36)*1000000+K36*1400000 -> 12480000
