Workbook

Sheet 想定作業
A1: 前提
B2: 業務・機能変更は行わない。
B3: サーバ構成は現行踏襲とする。
B4: DBは現行踏襲（Oracle、SQLSever継続）
B5: JavaフレームワークはStruts継続
B6: テストは新規構築した本番環境（次期本番機）にて行う。
B7: ※検証、予備環境は最低限の動作確認（アプリ起動、ログイン確認程度）を想定
A10: 想定作業
A11: 全パターン共通
B12: IP,ホスト名変更に伴う各種（IF、DB等）向け先変更、検証
B13: データ移行
B14: アプリ動作検証（全画面、帳票、バッチ、IF打鍵※現新比較）
B15: アプリケーション構築、ミドルウェアのセットアップ
B16: IF連携ID変更（連携NASを利用しているもの）※新システム
A18: （１）次期アーキテクチャとしてAzure環境に再構築
B19: DB構築（構成の検討から） | E19: ※本見積は各システム毎に個別にOracle構築を想定
B20: Office 365化に伴うExcel帳票の非互換調査、対応
B21: DBバージョンアップ（19c⇒22c）に伴う非互換調査、対応
B22: WebLogic⇒Tomcat移行に伴う非互換調査、対応
B23: スケジューラ変更（Systemwalker Operation Manager⇒A-AUTO）に伴う非互換調査、対応
A25: （２）Azureに構築される縮小版の共通基盤に移行
B26: 全パターン共通の作業のみ
B27: JDKとWLSはマイナーバージョンアップされるが、Strutsへの非互換は無い認識
B28: ※DBを個別構築する場合は以下が追加
B29: DB構築（構成の検討から）
B30: DBバージョンアップ（19c⇒22c）に伴う非互換調査、対応
A32: （３）現地Windows2016サーバ再構築
B33: サーバ構築（実際の構築作業は出光だが、スペック見積等）
B34: DB構築
B35: DBバージョンアップ（Oracle19c⇒22c、SQLServer2016⇒2022）に伴う非互換調査、対応
B36: .NET Framework非互換調査、64bit非互換調査（製品倉庫、ABC、数量ポリマー）
B37: Office 365化に伴うExcel帳票の非互換調査、対応（製品倉庫のみ）
B38: Azure環境制約（Dドライブ、OSユーザ）※ヤード予備機がAzure構築のため、現地本番も構成合わせる必要

Sheet スケジュール案＿
A2: システム | B2: 担当 | C2: 2025年 | O2: 2026年 | AA2: 2027年 | AM2: 2027年
C3: 1月 | D3: 2月 | E3: 3月 | F3: 4月 | G3: 5月 | H3: 6月 | I3: 7月 | J3: 8月 | K3: 9月 | L3: 10月 | M3: 11月 | N3: 12月 | O3: 1月 | P3: 2月 | Q3: 3月 | R3: 4月 | S3: 5月 | T3: 6月 | U3: 7月 | V3: 8月 | W3: 9月 | X3: 10月 | Y3: 11月 | Z3: 12月 | AA3: 1月 | AB3: 2月 | AC3: 3月 | AD3: 4月 | AE3: 5月 | AF3: 6月 | AG3: 7月 | AH3: 8月 | AI3: 9月 | AJ3: 10月 | AK3: 11月 | AL3: 12月 | AM3: 1月 | AN3: 2月 | AO3: 3月 | AP3: 4月 | AQ3: 5月
A4: マイルストン | L4: ★千葉切替 | M4: ★徳山切替
A5: 千葉PIMS
A6: 徳山PIMS
A8: 想定要員数（作業者のみ）
A14: 合計 | C14: =SUM(C9:C13) -> 0 | D14: =SUM(D9:D13) -> 0 | E14: =SUM(E9:E13) -> 0 | F14: =SUM(F9:F13) -> 0 | G14: =SUM(G9:G13) -> 0 | H14: =SUM(H9:H13) -> 0 | I14: =SUM(I9:I13) -> 0 | J14: =SUM(J9:J13) -> 0 | ... AQ14: =SUM(AQ9:AQ13) -> 0
A15: 作業者 | B15: 売上(1,000k) | C15: =C14*1000000 -> 0 | D15: =D14*1000000 -> 0 | E15: =E14*1000000 -> 0 | F15: =F14*1000000 -> 0 | G15: =G14*1000000 -> 0 | H15: =H14*1000000 -> 0 | I15: =I14*1000000 -> 0 | J15: =J14*1000000 -> 0 | ... AQ15: =AQ14*1000000 -> 0 | AR15: =SUM(C15:AQ15) -> 0
B16: 経費(800k) | C16: =C14*800000 -> 0 | D16: =D14*800000 -> 0 | E16: =E14*800000 -> 0 | F16: =F14*800000 -> 0 | G16: =G14*800000 -> 0 | H16: =H14*800000 -> 0 | I16: =I14*800000 -> 0 | J16: =J14*800000 -> 0 | ... AQ16: =AQ14*800000 -> 0 | AR16: =SUM(C16:AQ16) -> 0
A17: 管理者 | B17: 売上(1,400k) | F17: 1400000 | G17: 1400000 | H17: 1400000 | I17: 1400000 | J17: 1400000 | K17: 1400000 | L17: 1400000 | M17: 1400000 | N17: 1400000 | O17: 1400000 | P17: 1400000 | Q17: 1400000 | R17: 1400000 | S17: 1400000 | T17: 1400000 | U17: 1400000 | V17: 1400000 | W17: 1400000 | X17: 1400000 | Y17: 1400000 | Z17: 1400000 | AA17: 1400000 | AB17: 1400000 | AC17: 1400000 | AD17: 1400000 | AE17: 1400000 | AF17: 1400000 | AG17: 1400000 | AH17: 1400000 | AI17: 1400000 | AJ17: 1400000 | AK17: 1400000 | AL17: 1400000 | AM17: 1400000 | AN17: 1400000 | AO17: 1400000 | AR17: =SUM(C17:AQ17) -> 50400000
B18: 経費(1,000k) | F18: 1000000 | G18: 1000000 | H18: 1000000 | I18: 1000000 | J18: 1000000 | K18: 1000000 | L18: 1000000 | M18: 1000000 | N18: 1000000 | O18: 1000000 | P18: 1000000 | Q18: 1000000 | R18: 1000000 | S18: 1000000 | T18: 1000000 | U18: 1000000 | V18: 1000000 | W18: 1000000 | X18: 1000000 | Y18: 1000000 | Z18: 1000000 | AA18: 1000000 | AB18: 1000000 | AC18: 1000000 | AD18: 1000000 | AE18: 1000000 | AF18: 1000000 | AG18: 1000000 | AH18: 1000000 | AI18: 1000000 | AJ18: 1000000 | AK18: 1000000 | AL18: 1000000 | AM18: 1000000 | AN18: 1000000 | AO18: 1000000 | AR18: =SUM(C18:AQ18) -> 36000000
AP19: 売上合計 | AR19: =AR15+AR17 -> 50400000
AP20: 経費合計 | AR20: =AR16+AR18 -> 36000000
AP21: 粗利 | AR21: =AR19-AR20 -> 14400000
AP22: 粗利率 | AR22: =AR21/AR19 -> 0.28571429

Sheet 概要図(千葉)
C1: ファイル連携 | F1: 工場系保守対象 | I1: 館林管理
C2: DBデータ連携 | F2: 工場系保守対象外 | I2: 現地管理

Sheet 対応概要
A2: 発生事象
A3: OneSAPからのオーダーで輸送形態「990 無関係」が連携されるとヤード操業システムの取込処理が途中で止まってしまう事象が発生している。
A5: 対応内容
A6: １．OneSAPからのオーダーで輸送形態「990 無関係」が連携された場合、エラーとして弾き、処理を継続する
A7: ２．ダッシュボード画面の入出荷オーダ受信ログでエラーとして出力する

Sheet 概要図(徳山)
C1: ファイル連携 | F1: 工場系保守対象 | I1: 館林管理
C2: DBデータ連携 | F2: 工場系保守対象外 | I2: 現地管理

Sheet システム概要
F1: システム概要 | N1: システム規模 | T1: 共通基盤利用状況（現状）
A2: サービス: サービス番号 | B2: サービス名 | C2: 保守領域 | D2: 移行状況 | E2: 作業パターン ※想定作業シート参照 | F2: 業務概要 | G2: OS | H2: アプリ | I2: DB | J2: ミドルウェア | K2: フレームワーク | L2: その他 | M2: サーバ構成 | N2: 画面 | O2: 帳票 | P2: バッチ | Q2: IF | R2: テーブル | S2: その他 | T2: 共通AP | U2: 共通DB | V2: 連携 | W2: レポート | X2: 認証 | Y2: バッチ
A3: SVC-00000710 | B3: 千葉数量確定システム | C3: 工場系 | D3: 未実施（共通基盤） | E3: （1）or（2） | F3: 千葉事業所及び徳山事業所の石油化学装置の生産、在庫、PL(パイプライン)出荷、品目転換数量の管理を行うシステム。またタンクヤードの日報作成(ヤード日報)機能も持つ。 | G3: Red Hat Enterprise Linux7.3 | H3: java 1.8.0_152 WebLogic 12.2.1.2.0 | I3: Oracle19C | J3: Systemwalker Operation Manager | K3: struts 1.2.9 | M3: 本番 共通基盤（館林） 検証 共通基盤（館林） | N3: 千葉：41 徳山：30 | O3: 千葉：23 徳山：7 | P3: 共通：2 千葉：9 徳山：4 | Q3: 千葉：8 徳山：4 | R3: 共通：58 千葉：16 徳山：9 | T3: 〇 | U3: 〇 | V3: 〇 | W3: × | X3: 〇 | Y3: 〇 | Z3: e
A4: SVC-00000857 | B4: 徳山工場数量確定システム | Z4: e
A5: - | B5: 千葉工場用役管理システム | C5: 工場系 | D5: 未実施（共通基盤） | E5: （1）or（2） | F5: 石油化学装置の生産数量、用役数量の管理を行うシステム。 | G5: Red Hat Enterprise Linux7.3 | H5: java 1.8.0_152 WebLogic 12.2.1.2.0 | I5: Oracle19C | J5: Systemwalker Operation Manager | K5: struts 1.2.9 | M5: 本番 共通基盤（館林） 検証 共通基盤（館林） | N5: 千葉：28 徳山：17 | O5: 千葉：43 徳山：6 | P5: 共通：0 千葉：0 徳山：0 | Q5: 千葉：0 徳山：0 | R5: 共通：11 千葉：1 徳山：11 | T5: 〇 | U5: 〇 | V5: 〇 | W5: × | X5: 〇 | Y5: 〇 | Z5: e
A6: SVC-00000858 | B6: 徳山工場用役管理システム | Z6: e
A7: SVC-00001700 | B7: 千葉化学品質管理システム | C7: 工場系 | D7: 未実施（共通基盤） | E7: （1）or（2） | F7: 千葉事業所(工場)の品質管理課にて行う各種試験(工程、製品、物性)、及びそれに付随する業務(ロット管理、試験料金計算)を行うシステム。 | G7: Red Hat Enterprise Linux7.3 | H7: java 1.8.0_131 WebLogic 12.2.1.2.0 | I7: Oracle19C | J7: Systemwalker Operation Manager | K7: struts 1.2.9 | L7: List Creatorでの帳票作成 | M7: 本番 共通基盤（館林） 検証 共通基盤（館林） | N7: 83 | O7: 25 | P7: 5 | Q7: 4 | R7: 67 | T7: 〇 | U7: 〇 | V7: 〇 | W7: 〇 | X7: 〇 | Y7: 〇 | Z7: e
A8: SVC-00000854 | B8: ＬＭＰＰ包装システム | C8: 工場系 | D8: 未実施（共通基盤） | E8: （1）or（2） | F8: 千葉事業所(工場)のSPS、LMPP装置で生産される製品の包装管理を行うシステム。 | G8: Red Hat Enterprise Linux7.3 | H8: java 1.8.0_131 WebLogic 12.2.1.2.0 | I8: Oracle19C | J8: Systemwalker Operation Manager | K8: struts 1.2.9 | L8: List Creatorでの帳票作成 | M8: 本番 共通基盤（館林） 検証 共通基盤（館林） | N8: 17 | O8: 3 | P8: 1 | Q8: 3 | R8: 12 | T8: 〇 | U8: 〇 | V8: 〇 | W8: 〇 | X8: 〇 | Y8: 〇 | Z8: e
A9: SVC-00000877 | B9: 工場DB | C9: 工場系 | D9: 未実施（共通基盤） ※アプリはXenApp | E9: （1）or（2） | F9: 徳山事業所の石油化学装置の生産、在庫の計画値及び実績値を管理するDB及びエクセルマクロ群。 | G9: - | H9: Excel | I9: Oracle19C | J9: - | K9: - | M9: 本番 共通基盤（館林） 検証 共通基盤（館林） | N9: 0 | O9: 0 | P9: 0 | Q9: 0 | R9: 211 | T9: × | U9: 〇 | V9: × | W9: × | X9: × | Y9: × | Z9: e
A10: SVC-00000705 | B10: 千葉ヤ－ド操業システム | C10: 工場系 | D10: 未実施（共通基盤） | E10: （3） | F10: 千葉事業所及び徳山事業所の石油化学品の入出荷を管理するシステム。 | G10: WindowsServer2016 | H10: java 1.8.0_152 WebLogic 12.2.1.2.0 | I10: SQLServer2016 | J10: Systemwalker Operation Manager OWFT | K10: struts 1.2.9 | M10: 本番 AP/DBサーバ×2（現地） AP/DB予備×2（館林） 検証 AP/DBサーバ×2（館林） | N10: 80 | O10: 20 | P10: 千葉：20 徳山：19 | Q10: 千葉：16 徳山：15 | R10: 75 | T10: × | U10: 〇 | V10: 〇 | W10: × | X10: × | Y10: × | Z10: e
A11: SVC-00000707 | B11: 徳山ヤ－ド操業システム | T11: × | U11: 〇 | V11: 〇 | W11: × | X11: × | Y11: × | Z11: e
A12: SVC-00000704 | B12: 千葉製品倉庫システム | C12: 工場系 | D12: 未実施（現地サーバ） | E12: （3） | F12: 千葉事業所(工場)で生産されているポリマー製品の包装、入出荷、在庫管理を行うシステム。 | G12: WindowsServer2016 | H12: VB.NET | I12: Oracle12C | J12: Systemwalker Operation Manager OWFT | M12: 本番 AP/DBサーバ（現地） 検証 APサーバ（館林） | N12: 68 | O12: 43 | P12: 9 | Q12: 45 | R12: 205 | T12: × | U12: × | V12: 〇 | W12: × | X12: × | Y12: × | Z12: e
A13: SVC-00000901 | B13: 千葉工場数量確定システム（ポリマ－） | C13: 工場系 | D13: 未実施（現地サーバ） | E13: （3） | F13: 千葉事業所(工場)で生産されているポリマー製品の生産、在庫、PL(パイプライン)出荷、品目転換数量の管理を行うシステム。 | G13: WindowsServer2016 | H13: ASP.NET | I13: Oracle12C | J13: Systemwalker Operation Manager OWFT | N13: 20 | O13: 4 | P13: 2 | Q13: 2 | R13: 30 | T13: × | U13: × | V13: × | W13: × | X13: × | Y13: × | Z13: e
A14: SVC-00000711 | B14: ＡＢＣ数量確定システム | C14: 工場系 | D14: 未実施（現地サーバ） | E14: （3） | F14: 千葉事業所(工場)のABC装置で生産される製品の生産管理を行うシステム。 | G14: WindowsServer2016 | H14: C# | I14: Oracle12C | J14: Systemwalker Operation Manager OWFT | N14: 15 | O14: 0 | P14: 12 | Q14: 5 | R14: 24 | T14: × | U14: × | V14: × | W14: × | X14: × | Y14: × | Z14: e
A15: - | B15: 千葉L3.5 | C15: 工場系 | D15: 未実施（現地サーバ） | E15: （3） | F15: L3層に存在するシステムとL4層に存在するシステムの中継となるサーバ | G15: WindowsServer2016 | H15: - | I15: - | J15: Systemwalker Operation Manager OWFT | K15: - | M15: 本番 APサーバ（現地） 検証 APサーバ（館林） | N15: 0 | O15: 0 | P15: 2 | Q15: 千葉：52 徳山：22 | R15: 0 | T15: × | U15: × | V15: × | W15: × | X15: × | Y15: ×
A16: - | B16: 徳山L3.5 | T16: × | U16: × | V16: × | W16: × | X16: × | Y16: ×

Sheet 見積（数量確定システム）_bk
C1: システム名：数量確定システム
D2: パターン | E2: （１）次期アーキテクチャとしてAzure環境に再構築 | J2: （２）Azureに構築される縮小版の共通基盤に移行 | O2: （３）現地Windows2016サーバ再構築
E3: 想定工数(人月) | J3: 想定工数(人月) | O3: 想定工数(人月)
B4: No. | C4: 変更箇所カテゴリ | D4: タスク | E4: 要件定義・設計 | F4: 製造 | G4: 試験・本番稼働 | H4: 管理 | I4: 全体工数 | J4: 要件定義・設計 | K4: 製造 | L4: 試験・本番稼働 | M4: 管理 | N4: 全体工数 | O4: 要件定義・設計 | P4: 製造 | Q4: 試験・本番稼働 | R4: 管理 | S4: 全体工数 | T4: 備考
B5: 1 | C5: Azure移行 | D5: IP,ホスト名変更に伴う各種（IF、DB等）向け先変更、検証 | E5: 1 | F5: 0.5 | G5: 1 | H5: =SUM(E5:G5)*0.15 -> 0.375 | I5: =SUM(E5:H5) -> 2.875 | J5: 1 | K5: 0.5 | L5: 1 | M5: =SUM(J5:L5)*0.15 -> 0.375 | N5: =SUM(J5:M5) -> 2.875 | R5: =SUM(O5:Q5)*0.15 -> 0 | S5: =SUM(O5:R5) -> 0
B6: 2 | C6: Azure移行 | D6: アプリ動作検証（各パターンで検証範囲は異なる） | E6: 1.25 | F6: 0.5 | G6: 1 | H6: =SUM(E6:G6)*0.15 -> 0.4125 | I6: =SUM(E6:H6) -> 3.1625 | J6: 0.25 | K6: 0.25 | L6: 0.5 | M6: =SUM(J6:L6)*0.15 -> 0.15 | N6: =SUM(J6:M6) -> 1.15
B7: 3 | C7: サーバ更新 | D7: アプリケーション構築、ミドルウェアのセットアップ | E7: 1 | F7: 1 | G7: 0.5 | H7: =SUM(E7:G7)*0.15 -> 0.375 | I7: =SUM(E7:H7) -> 2.875 | J7: 0.5 | K7: 0.5 | L7: 0.5 | M7: =SUM(J7:L7)*0.15 -> 0.225 | N7: =SUM(J7:M7) -> 1.725 | R7: =SUM(O7:Q7)*0.15 -> 0 | S7: =SUM(O7:R7) -> 0
B8: 4 | C8: DB移行 | D8: データ移行 | E8: 0.25 | F8: 0.1 | G8: 0.1 | H8: =SUM(E8:G8)*0.15 -> 0.0675 | I8: =SUM(E8:H8) -> 0.5175 | J8: 0.1 | K8: 0.1 | L8: 0.25 | M8: =SUM(J8:L8)*0.15 -> 0.0675 | N8: =SUM(J8:M8) -> 0.5175 | R8: =SUM(O8:Q8)*0.15 -> 0 | S8: =SUM(O8:R8) -> 0
B9: 5 | C9: DB移行 | D9: DB構築（構成の検討から） | E9: 1.5 | F9: 1 | G9: 0.5 | H9: =SUM(E9:G9)*0.15 -> 0.45 | I9: =SUM(E9:H9) -> 3.45 | M9: =SUM(J9:L9)*0.15 -> 0 | N9: =SUM(J9:M9) -> 0
B10: 6 | C10: DB移行 | D10: DBバージョンアップ（19c⇒22c）に伴う非互換調査、対応 | E10: 1 | F10: 1 | G10: 0.5 | H10: =SUM(E10:G10)*0.15 -> 0.375 | I10: =SUM(E10:H10) -> 2.875 | M10: =SUM(J10:L10)*0.15 -> 0 | N10: =SUM(J10:M10) -> 0
B11: 7 | C11: Office更新 | D11: テンプレートファイル調査・対応 | E11: 0.1 | F11: 0.1 | G11: 0.1 | H11: =SUM(E11:G11)*0.15 -> 0.045 | I11: =SUM(E11:H11) -> 0.345 | M11: =SUM(J11:L11)*0.15 -> 0 | N11: =SUM(J11:M11) -> 0 | R11: =SUM(O11:Q11)*0.15 -> 0 | S11: =SUM(O11:R11) -> 0
B12: 8 | C12: TOMCAT移行 | D12: アプリケーションの移行 | E12: 0.1 | F12: 0.1 | G12: 0.1 | H12: =SUM(E12:G12)*0.15 -> 0.045 | I12: =SUM(E12:H12) -> 0.345 | M12: =SUM(J12:L12)*0.15 -> 0 | N12: =SUM(J12:M12) -> 0 | R12: =SUM(O12:Q12)*0.15 -> 0 | S12: =SUM(O12:R12) -> 0
B13: 9 | C13: ミドルウェア移行 | D13: A-Auto検証 | E13: 0.1 | F13: 0.1 | G13: 0.1 | H13: =SUM(E13:G13)*0.15 -> 0.045 | I13: =SUM(E13:H13) -> 0.345 | M13: =SUM(J13:L13)*0.15 -> 0 | N13: =SUM(J13:M13) -> 0 | R13: =SUM(O13:Q13)*0.15 -> 0 | S13: =SUM(O13:R13) -> 0 | T13: 非互換検証
B14: 10 | C14: ミドルウェア移行 | D14: オペマネのA-Auto更新 | E14: 0.5 | F14: 0.25 | G14: 0.25 | H14: =SUM(E14:G14)*0.15 -> 0.15 | I14: =SUM(E14:H14) -> 1.15 | M14: =SUM(J14:L14)*0.15 -> 0 | N14: =SUM(J14:M14) -> 0 | R14: =SUM(O14:Q14)*0.15 -> 0 | S14: =SUM(O14:R14) -> 0 | T14: A-AUTO14本
D16: 合計工数 | E16: =SUM(E5:E14) -> 6.8 | F16: =SUM(F5:F14) -> 4.65 | G16: =SUM(G5:G14) -> 4.15 | H16: =SUM(H5:H14) -> 2.34 | I16: =SUM(I5:I14) -> 17.94 | J16: =SUM(J5:J14) -> 1.85 | K16: =SUM(K5:K14) -> 1.35 | L16: =SUM(L5:L14) -> 2.25 | ... S16: =SUM(S5:S14) -> 0
D18: 単価(千円) | E18: 1000 | F18: 1000 | G18: 1000 | H18: 1200 | I18: =AVERAGE(E18:H18) -> 1050 | J18: 1000 | K18: 1000 | L18: 1000 | M18: 1200 | N18: =AVERAGE(J18:M18) -> 1050 | O18: 1000 | P18: 1000 | Q18: 1000 | R18: 1200 | S18: =AVERAGE(O18:R18) -> 1050
D19: 金額(千円) | E19: =E16*E18 -> 6800 | F19: =F16*F18 -> 4650 | G19: =G16*G18 -> 4150 | H19: =H16*H18 -> 2808 | I19: =SUM(E19:H19) -> 18408 | J19: =J16*J18 -> 1850 | K19: =K16*K18 -> 1350 | L19: =L16*L18 -> 2250 | M19: =M16*M18 -> 981 | N19: =SUM(J19:M19) -> 6431 | O19: =O16*O18 -> 0 | P19: =P16*P18 -> 0 | Q19: =Q16*Q18 -> 0 | R19: =R16*R18 -> 0 | S19: =SUM(O19:R19) -> 0

Sheet 見積（〇〇システム）
C1: システム名：
D2: パターン | E2: （１）次期アーキテクチャとしてAzure環境に再構築 | J2: （２）Azureに構築される縮小版の共通基盤に移行 | O2: （３）現地Windows2016サーバ再構築
E3: 想定工数(人月) | J3: 想定工数(人月) | O3: 想定工数(人月)
B4: No. | C4: 変更箇所カテゴリ | D4: タスク | E4: 要件定義・設計 | F4: 製造 | G4: 試験・本番稼働 | H4: 管理 | I4: 全体工数 | J4: 要件定義・設計 | K4: 製造 | L4: 試験・本番稼働 | M4: 管理 | N4: 全体工数 | O4: 要件定義・設計 | P4: 製造 | Q4: 試験・本番稼働 | R4: 管理 | S4: 全体工数 | T4: 備考
B5: 1 | C5: Azure移行 | D5: アプリケーション構築、向け先変更、IF検証、ミドルウェアのセットアップ | E5: 1 | F5: 0.5 | G5: 1 | H5: =SUM(E5:G5)*0.15 -> 0.375 | I5: =SUM(E5:H5) -> 2.875 | J5: 1 | K5: 0.5 | L5: 1 | M5: =SUM(J5:L5)*0.15 -> 0.375 | N5: =SUM(J5:M5) -> 2.875 | O5: 1 | P5: 0.5 | Q5: 1 | R5: =SUM(O5:Q5)*0.15 -> 0.375 | S5: =SUM(O5:R5) -> 2.875 | T5: 参考：Windows Server 2012 更新対応
B6: 2 | C6: Azure移行 | D6: アプリケーション構築、向け先変更、IF検証、ミドルウェアのセットアップ | E6: 0.25 | F6: 0.5 | G6: 1 | H6: =SUM(E6:G6)*0.15 -> 0.2625 | I6: =SUM(E6:H6) -> 2.0125 | J6: 0.25 | K6: 0.5 | L6: 1 | M6: =SUM(J6:L6)*0.15 -> 0.2625 | N6: =SUM(J6:M6) -> 2.0125 | O6: 0.25 | P6: 0.5 | Q6: 1 | R6: =SUM(O6:Q6)*0.15 -> 0.2625 | S6: =SUM(O6:R6) -> 2.0125 | T6: 参考：Windows Server 2012 更新対応
B7: 3 | C7: Azure移行 | D7: アプリケーション構築、向け先変更、IF検証、ミドルウェアのセットアップ | E7: 1 | F7: 0.5 | G7: 1 | H7: =SUM(E7:G7)*0.15 -> 0.375 | I7: =SUM(E7:H7) -> 2.875 | J7: 1 | K7: 0.5 | L7: 1 | M7: =SUM(J7:L7)*0.15 -> 0.375 | N7: =SUM(J7:M7) -> 2.875 | O7: 1 | P7: 0.5 | Q7: 1 | R7: =SUM(O7:Q7)*0.15 -> 0.375 | S7: =SUM(O7:R7) -> 2.875 | T7: 参考：Windows Server 2012 更新対応
B8: 4 | C8: Azure移行 | D8: アプリケーション構築、向け先変更、IF検証、ミドルウェアのセットアップ | E8: 1 | F8: 0.5 | G8: 1 | H8: =SUM(E8:G8)*0.15 -> 0.375 | I8: =SUM(E8:H8) -> 2.875 | J8: 1 | K8: 0.5 | L8: 1 | M8: =SUM(J8:L8)*0.15 -> 0.375 | N8: =SUM(J8:M8) -> 2.875 | O8: 1 | P8: 0.5 | Q8: 1 | R8: =SUM(O8:Q8)*0.15 -> 0.375 | S8: =SUM(O8:R8) -> 2.875 | T8: 参考：Windows Server 2012 更新対応
B9: 5 | C9: Azure移行 | D9: アプリケーション構築、向け先変更、IF検証、ミドルウェアのセットアップ | E9: 1 | F9: 0.5 | G9: 1 | H9: =SUM(E9:G9)*0.15 -> 0.375 | I9: =SUM(E9:H9) -> 2.875 | J9: 1 | K9: 0.5 | L9: 1 | M9: =SUM(J9:L9)*0.15 -> 0.375 | N9: =SUM(J9:M9) -> 2.875 | O9: 1 | P9: 0.5 | Q9: 1 | R9: =SUM(O9:Q9)*0.15 -> 0.375 | S9: =SUM(O9:R9) -> 2.875 | T9: 参考：Windows Server 2012 更新対応
B10: 6 | C10: サーバ更新 | D10: 向け先変更、IF検証、ミドルウェアのセットアップ | E10: 1 | F10: 0.25 | G10: 0.5 | H10: =SUM(E10:G10)*0.15 -> 0.2625 | I10: =SUM(E10:H10) -> 2.0125 | J10: 1 | K10: 0.25 | L10: 0.5 | M10: =SUM(J10:L10)*0.15 -> 0.2625 | N10: =SUM(J10:M10) -> 2.0125 | O10: 1 | P10: 0.25 | Q10: 0.5 | R10: =SUM(O10:Q10)*0.15 -> 0.2625 | S10: =SUM(O10:R10) -> 2.0125
B11: 7 | C11: サーバ更新 | D11: 向け先変更、IF検証、ミドルウェアのセットアップ | E11: 0.25 | F11: 0.25 | G11: 0.5 | H11: =SUM(E11:G11)*0.15 -> 0.15 | I11: =SUM(E11:H11) -> 1.15 | J11: 0.25 | K11: 0.25 | L11: 0.5 | M11: =SUM(J11:L11)*0.15 -> 0.15 | N11: =SUM(J11:M11) -> 1.15 | O11: 0.25 | P11: 0.25 | Q11: 0.5 | R11: =SUM(O11:Q11)*0.15 -> 0.15 | S11: =SUM(O11:R11) -> 1.15
B12: 8 | C12: OS更新 | D12: .netFramework非互換調査、64bit非互換調査 | E12: 0.5 | F12: 0.5 | G12: 1 | H12: =SUM(E12:G12)*0.15 -> 0.3 | I12: =SUM(E12:H12) -> 2.3 | J12: 0.5 | K12: 0.5 | L12: 1 | M12: =SUM(J12:L12)*0.15 -> 0.3 | N12: =SUM(J12:M12) -> 2.3 | O12: 0.5 | P12: 0.5 | Q12: 1 | R12: =SUM(O12:Q12)*0.15 -> 0.3 | S12: =SUM(O12:R12) -> 2.3
B13: 9 | C13: OS更新 | D13: .netFramework非互換調査、64bit非互換調査 | E13: 0.5 | F13: 0.25 | G13: 1 | H13: =SUM(E13:G13)*0.15 -> 0.2625 | I13: =SUM(E13:H13) -> 2.0125 | J13: 0.5 | K13: 0.25 | L13: 1 | M13: =SUM(J13:L13)*0.15 -> 0.2625 | N13: =SUM(J13:M13) -> 2.0125 | O13: 0.5 | P13: 0.25 | Q13: 1 | R13: =SUM(O13:Q13)*0.15 -> 0.2625 | S13: =SUM(O13:R13) -> 2.0125
B14: 10 | C14: OS更新 | D14: .netFramework非互換調査、64bit非互換調査 | E14: 0.5 | F14: 0.25 | G14: 0.5 | H14: =SUM(E14:G14)*0.15 -> 0.1875 | I14: =SUM(E14:H14) -> 1.4375 | J14: 0.5 | K14: 0.25 | L14: 0.5 | M14: =SUM(J14:L14)*0.15 -> 0.1875 | N14: =SUM(J14:M14) -> 1.4375 | O14: 0.5 | P14: 0.25 | Q14: 0.5 | R14: =SUM(O14:Q14)*0.15 -> 0.1875 | S14: =SUM(O14:R14) -> 1.4375
B15: 11 | C15: OS更新 | D15: .netFramework非互換調査、64bit非互換調査 | E15: 1 | F15: 1 | G15: 1 | H15: =SUM(E15:G15)*0.15 -> 0.45 | I15: =SUM(E15:H15) -> 3.45 | J15: 1 | K15: 1 | L15: 1 | M15: =SUM(J15:L15)*0.15 -> 0.45 | N15: =SUM(J15:M15) -> 3.45 | O15: 1 | P15: 1 | Q15: 1 | R15: =SUM(O15:Q15)*0.15 -> 0.45 | S15: =SUM(O15:R15) -> 3.45
B16: 12 | C16: OS更新 | D16: .netFramework非互換調査、64bit非互換調査 | E16: - | F16: 0.25 | G16: 0.5 | H16: =SUM(E16:G16)*0.15 -> 0.1125 | I16: =SUM(E16:H16) -> 0.8625 | J16: - | K16: 0.25 | L16: 0.5 | M16: =SUM(J16:L16)*0.15 -> 0.1125 | N16: =SUM(J16:M16) -> 0.8625 | O16: - | P16: 0.25 | Q16: 0.5 | R16: =SUM(O16:Q16)*0.15 -> 0.1125 | S16: =SUM(O16:R16) -> 0.8625
B17: 13 | C17: Office更新 | D17: テンプレートファイル調査・対応 | E17: 0.1 | F17: 0.1 | G17: 0.1 | H17: =SUM(E17:G17)*0.15 -> 0.045 | I17: =SUM(E17:H17) -> 0.345 | J17: 0.1 | K17: 0.1 | L17: 0.1 | M17: =SUM(J17:L17)*0.15 -> 0.045 | N17: =SUM(J17:M17) -> 0.345 | O17: 0.1 | P17: 0.1 | Q17: 0.1 | R17: =SUM(O17:Q17)*0.15 -> 0.045 | S17: =SUM(O17:R17) -> 0.345
B18: 14 | C18: Office更新 | D18: テンプレートファイル調査・対応 | E18: 0.1 | F18: 0.1 | G18: 0.1 | H18: =SUM(E18:G18)*0.15 -> 0.045 | I18: =SUM(E18:H18) -> 0.345 | J18: 0.1 | K18: 0.1 | L18: 0.1 | M18: =SUM(J18:L18)*0.15 -> 0.045 | N18: =SUM(J18:M18) -> 0.345 | O18: 0.1 | P18: 0.1 | Q18: 0.1 | R18: =SUM(O18:Q18)*0.15 -> 0.045 | S18: =SUM(O18:R18) -> 0.345
B19: 15 | C19: Office更新 | D19: テンプレートファイル調査・対応 | E19: 0.1 | F19: 0.1 | G19: 0.1 | H19: =SUM(E19:G19)*0.15 -> 0.045 | I19: =SUM(E19:H19) -> 0.345 | J19: 0.1 | K19: 0.1 | L19: 0.1 | M19: =SUM(J19:L19)*0.15 -> 0.045 | N19: =SUM(J19:M19) -> 0.345 | O19: 0.1 | P19: 0.1 | Q19: 0.1 | R19: =SUM(O19:Q19)*0.15 -> 0.045 | S19: =SUM(O19:R19) -> 0.345
B20: 16 | C20: DB移行 | D20: バージョンアップ、データ移行、向け先変更 | E20: 0.1 | F20: 0.1 | G20: 0.1 | H20: =SUM(E20:G20)*0.15 -> 0.045 | I20: =SUM(E20:H20) -> 0.345 | J20: 0.1 | K20: 0.1 | L20: 0.1 | M20: =SUM(J20:L20)*0.15 -> 0.045 | N20: =SUM(J20:M20) -> 0.345 | O20: 0.1 | P20: 0.1 | Q20: 0.1 | R20: =SUM(O20:Q20)*0.15 -> 0.045 | S20: =SUM(O20:R20) -> 0.345
B21: 17 | C21: DB移行 | D21: バージョンアップ、データ移行、向け先変更 | E21: 0.1 | F21: 0.1 | G21: 0.1 | H21: =SUM(E21:G21)*0.15 -> 0.045 | I21: =SUM(E21:H21) -> 0.345 | J21: 0.1 | K21: 0.1 | L21: 0.1 | M21: =SUM(J21:L21)*0.15 -> 0.045 | N21: =SUM(J21:M21) -> 0.345 | O21: 0.1 | P21: 0.1 | Q21: 0.1 | R21: =SUM(O21:Q21)*0.15 -> 0.045 | S21: =SUM(O21:R21) -> 0.345
B22: 18 | C22: DB移行 | D22: バージョンアップ、データ移行、向け先変更 | E22: 0.1 | F22: 0.1 | G22: 0.1 | H22: =SUM(E22:G22)*0.15 -> 0.045 | I22: =SUM(E22:H22) -> 0.345 | J22: 0.1 | K22: 0.1 | L22: 0.1 | M22: =SUM(J22:L22)*0.15 -> 0.045 | N22: =SUM(J22:M22) -> 0.345 | O22: 0.1 | P22: 0.1 | Q22: 0.1 | R22: =SUM(O22:Q22)*0.15 -> 0.045 | S22: =SUM(O22:R22) -> 0.345
B23: 19 | C23: DB移行 | D23: バージョンアップ、データ移行、向け先変更 | E23: 0.1 | F23: 0.1 | G23: 0.1 | H23: =SUM(E23:G23)*0.15 -> 0.045 | I23: =SUM(E23:H23) -> 0.345 | J23: 0.1 | K23: 0.1 | L23: 0.1 | M23: =SUM(J23:L23)*0.15 -> 0.045 | N23: =SUM(J23:M23) -> 0.345 | O23: 0.1 | P23: 0.1 | Q23: 0.1 | R23: =SUM(O23:Q23)*0.15 -> 0.045 | S23: =SUM(O23:R23) -> 0.345
B24: 20 | C24: DB移行 | D24: バージョンアップ、データ移行、向け先変更 | E24: 0.1 | F24: 0.1 | G24: 0.1 | H24: =SUM(E24:G24)*0.15 -> 0.045 | I24: =SUM(E24:H24) -> 0.345 | J24: 0.1 | K24: 0.1 | L24: 0.1 | M24: =SUM(J24:L24)*0.15 -> 0.045 | N24: =SUM(J24:M24) -> 0.345 | O24: 0.1 | P24: 0.1 | Q24: 0.1 | R24: =SUM(O24:Q24)*0.15 -> 0.045 | S24: =SUM(O24:R24) -> 0.345
B25: 21 | C25: TOMCAT移行 | D25: アプリケーションの移行 | E25: 0.1 | F25: 0.1 | G25: 0.1 | H25: =SUM(E25:G25)*0.15 -> 0.045 | I25: =SUM(E25:H25) -> 0.345 | J25: 0.1 | K25: 0.1 | L25: 0.1 | M25: =SUM(J25:L25)*0.15 -> 0.045 | N25: =SUM(J25:M25) -> 0.345 | O25: 0.1 | P25: 0.1 | Q25: 0.1 | R25: =SUM(O25:Q25)*0.15 -> 0.045 | S25: =SUM(O25:R25) -> 0.345
B26: 22 | C26: TOMCAT移行 | D26: アプリケーションの移行 | E26: 0.1 | F26: 0.1 | G26: 0.1 | H26: =SUM(E26:G26)*0.15 -> 0.045 | I26: =SUM(E26:H26) -> 0.345 | J26: 0.1 | K26: 0.1 | L26: 0.1 | M26: =SUM(J26:L26)*0.15 -> 0.045 | N26: =SUM(J26:M26) -> 0.345 | O26: 0.1 | P26: 0.1 | Q26: 0.1 | R26: =SUM(O26:Q26)*0.15 -> 0.045 | S26: =SUM(O26:R26) -> 0.345
B27: 23 | C27: TOMCAT移行 | D27: アプリケーションの移行 | E27: 0.1 | F27: 0.1 | G27: 0.1 | H27: =SUM(E27:G27)*0.15 -> 0.045 | I27: =SUM(E27:H27) -> 0.345 | J27: 0.1 | K27: 0.1 | L27: 0.1 | M27: =SUM(J27:L27)*0.15 -> 0.045 | N27: =SUM(J27:M27) -> 0.345 | O27: 0.1 | P27: 0.1 | Q27: 0.1 | R27: =SUM(O27:Q27)*0.15 -> 0.045 | S27: =SUM(O27:R27) -> 0.345
B28: 24 | C28: TOMCAT移行 | D28: アプリケーションの移行 | E28: 0.1 | F28: 0.1 | G28: 0.1 | H28: =SUM(E28:G28)*0.15 -> 0.045 | I28: =SUM(E28:H28) -> 0.345 | J28: 0.1 | K28: 0.1 | L28: 0.1 | M28: =SUM(J28:L28)*0.15 -> 0.045 | N28: =SUM(J28:M28) -> 0.345 | O28: 0.1 | P28: 0.1 | Q28: 0.1 | R28: =SUM(O28:Q28)*0.15 -> 0.045 | S28: =SUM(O28:R28) -> 0.345
B29: 25 | C29: ミドルウェア移行 | D29: A-Auto検証 | E29: 0.1 | F29: 0.1 | G29: 0.1 | H29: =SUM(E29:G29)*0.15 -> 0.045 | I29: =SUM(E29:H29) -> 0.345 | J29: 0.1 | K29: 0.1 | L29: 0.1 | M29: =SUM(J29:L29)*0.15 -> 0.045 | N29: =SUM(J29:M29) -> 0.345 | O29: 0.1 | P29: 0.1 | Q29: 0.1 | R29: =SUM(O29:Q29)*0.15 -> 0.045 | S29: =SUM(O29:R29) -> 0.345 | T29: 非互換検証
B30: 26 | C30: ミドルウェア移行 | D30: オペマネのA-Auto更新 | E30: 0.1 | F30: 0.1 | G30: 0.1 | H30: =SUM(E30:G30)*0.15 -> 0.045 | I30: =SUM(E30:H30) -> 0.345 | J30: 0.1 | K30: 0.1 | L30: 0.1 | M30: =SUM(J30:L30)*0.15 -> 0.045 | N30: =SUM(J30:M30) -> 0.345 | O30: 0.1 | P30: 0.1 | Q30: 0.1 | R30: =SUM(O30:Q30)*0.15 -> 0.045 | S30: =SUM(O30:R30) -> 0.345 | T30: A-AUTO14本
B31: 27 | C31: ミドルウェア移行 | D31: オペマネのA-Auto更新 | E31: 0.1 | F31: 0.1 | G31: 0.1 | H31: =SUM(E31:G31)*0.15 -> 0.045 | I31: =SUM(E31:H31) -> 0.345 | J31: 0.1 | K31: 0.1 | L31: 0.1 | M31: =SUM(J31:L31)*0.15 -> 0.045 | N31: =SUM(J31:M31) -> 0.345 | O31: 0.1 | P31: 0.1 | Q31: 0.1 | R31: =SUM(O31:Q31)*0.15 -> 0.045 | S31: =SUM(O31:R31) -> 0.345 | T31: A-AUTO6本
D33: 合計工数 | E33: =SUM(E17:E31) -> 1.5 | F33: =SUM(F17:F31) -> 1.5 | G33: =SUM(G17:G31) -> 1.5 | H33: =SUM(H17:H31) -> 0.675 | I33: =SUM(I17:I31) -> 5.175 | J33: =SUM(J17:J31) -> 1.5 | K33: =SUM(K17:K31) -> 1.5 | L33: =SUM(L17:L31) -> 1.5 | ... S33: =SUM(S17:S31) -> 5.175
D35: 単価(千円) | E35: 1000 | F35: 1000 | G35: 1000 | H35: 1200 | I35: =AVERAGE(E35:H35) -> 1050 | J35: 1000 | K35: 1000 | L35: 1000 | M35: 1200 | N35: =AVERAGE(J35:M35) -> 1050 | O35: 1000 | P35: 1000 | Q35: 1000 | R35: 1200 | S35: =AVERAGE(O35:R35) -> 1050
D36: 金額(千円) | E36: =E33*E35 -> 1500 | F36: =F33*F35 -> 1500 | G36: =G33*G35 -> 1500 | H36: =H33*H35 -> 810 | I36: =SUM(E36:H36) -> 5310 | J36: =J33*J35 -> 1500 | K36: =K33*K35 -> 1500 | L36: =L33*L35 -> 1500 | M36: =M33*M35 -> 810 | N36: =SUM(J36:M36) -> 5310 | O36: =O33*O35 -> 1500 | P36: =P33*P35 -> 1500 | Q36: =Q33*Q35 -> 1500 | R36: =R33*R35 -> 810 | S36: =SUM(O36:R36) -> 5310

Sheet 見積 (サマリ)
D2: 計算機更新対応 | L2: 備考
D3: アプリ
B4: No. | C4: システム | D4: 調査・要件定義 | E4: 設計 | F4: 製造 | G4: 試験 | H4: 本番稼働 | I4: 管理 | J4: 工数計 | K4: 金額
B5: 1 | C5: OneSAP連携改修 | D5: =見積!E4 -> 0 | E5: =見積!E5 -> 0.05 | F5: =見積!E6 -> 0.2 | G5: =見積!E7 -> 0.1 | H5: =見積!E9 -> 0.05 | I5: =見積!E11 -> 0.06 | J5: =SUM(D5:I5) -> 0.46 | K5: =SUM(D5:H5)*1000000+I5*1400000 -> 484000
B6: 計 | D6: =SUM(D5:D5) -> 0 | E6: =SUM(E5:E5) -> 0.05 | F6: =SUM(F5:F5) -> 0.2 | G6: =SUM(G5:G5) -> 0.1 | H6: =SUM(H5:H5) -> 0.05 | I6: =SUM(I5:I5) -> 0.06 | J6: =SUM(D6:I6) -> 0.46 | K6: =SUM(K5:K5) -> 484000
B7: 単価 | D7: 1000000 | E7: 1000000 | F7: 1000000 | G7: 1000000 | H7: 1000000 | I7: 1400000
B8: 金額 | D8: =D6*D7 -> 0 | E8: =E6*E7 -> 50000 | F8: =F6*F7 -> 200000 | G8: =G6*G7 -> 100000 | H8: =H6*H7 -> 50000 | I8: =I6*I7 -> 84000

Sheet 見積
B1: システム名： | C1: ヤード操業システム
B3: 工程 | C3: タスク | D3: 概算工数 | E3: 工数計 | F3: 成果物 | G3: 備考 | H3: 人日
B4: 調査・要件定義 | D4: =ROUND(H4/20,2) -> 0 | E4: 0 | G4: ※対応内容自体はユーザと認識合わせ済み
B5: 設計 | C5: 設計書修正 | D5: =ROUND(H5/20,2) -> 0.05 | E5: 0.05 | F5: UI-15 外部システムインタフェース定義.xlsx | G5: 設計書修正：2h+4h | H5: =ROUNDUP((2*1+4)/8,0) -> 1
B6: 製造 | C6: プログラム修正 | D6: =ROUND(H6/20,2) -> 0.2 | E6: 0.2 | F6: 修正後プログラムファイル | G6: 不要輸送形態排除：4h エラー出力：28h | H6: =32/8 -> 4
B7: 試験 | C7: 結合テスト | D7: =ROUND(H7/20,2) -> 0.1 | E7: 0.1 | F7: テスト仕様書兼結果報告書 | G7: テスト仕様書作成：4h テスト実施：3h レビュー：2h | H7: =ROUNDUP(9/8,0) -> 2
D8: =ROUND(H8/20,2) -> 0
B9: 本番稼働 | C9: 本番リリース | D9: =ROUND(H9/20,2) -> 0.05 | E9: 0.05 | F9: 本番作業手順書 | G9: 作業手順書作成：4h 本番作業：4h | H9: =ROUNDUP(8/8,0) -> 1
D10: =ROUND(H10/20,2) -> 0
B11: 管理 | C11: PJ管理 | D11: =ROUND(H11/20,2) -> 0.06 | E11: 0.06 | F11: プロジェクト計画書 課題管理表 スケジュール（WBS） 議事録 レビュー管理表 | G11: PJ管理、定例会、各工程完了レビュー | H11: =SUM(H4:H10)*0.15+I11 -> 1.2 | I11: 0
B12: 合計 | E12: =SUM(E4:E11) -> 0.46 | H12: =SUM(H4:H11) -> 9.2

Sheet スケジュール案
B3: M
B4: 1W | C4: 2W | D4: 3W | E4: 4W
B7: ※本件単体で対応を行う場合

Sheet Sheet1
B2: 【対応方針】
C3: ・共通基盤DBに乗っているDB(数量確定、工場DB、品管、包装)は縮小基盤へ移動
C4: ・基本全てのオペマネはA-AUTOに変更
C5: ・独立したサーバとして寄せられるシステムは寄せる(数量確定システムと用役管理システム、品管と包装)
B8: 【対象】
B9: No | C9: サーバ名 | E9: 構成 | F9: 超概算(人月) | G9: 内訳 | H9: 内訳(端数切り上げ) | I9: 備考
B10: 1 | C10: 千葉ヤード操業サーバ | E10: WindowsServer2022 SQLServer2022 | F10: 5.75 | G10: ベース金額 +webシステムテスト +webシステムテスト修正 +tomcat非互換 +個別DB | H10: 4 +0.5 +0.25 +0.5 +0.5 | I10: Azure構築 A-AOUT化無し | J10: =4 +0.5 +0.25 +0.5 +0.5 -> 5.75
B11: 2 | C11: 徳山ヤード操業サーバ | E11: WindowsServer2022 SQLServer2022 | F11: 5.75 | G11: ベース金額 +webシステムテスト +webシステムテスト修正 +tomcat非互換 +個別DB | H11: 4 +0.5 +0.25 +0.5 +0.5 | I11: Azure構築 A-AOUT化無し | J11: =4 +0.5 +0.25 +0.5 +0.5 -> 5.75
B12: 3 | C12: 数量用役システムサーバ | E12: Red Hat Enterprise Linux8.6 | F12: 8.5 | G12: ベース金額 +webシステムテスト×4 +webシステムテスト修正×4 +tomcat非互換×2 +A-AUTO14本 | H12: 4 +0.5*4 +0.25*4 +0.5*2 +0.5(14*5/8/20) | I12: Azure構築 | J12: =4 +0.5*4 +0.25*4 +0.5*2 +0.5 -> 8.5
B13: 4 | C13: 品管包装システムサーバ | E13: Red Hat Enterprise Linux8.6 | F13: 6.75 | G13: ベース金額 +webシステムテスト×2 +webシステムテスト修正×2 +tomcat非互換×2 +A-AUTO6本 | H13: 4 +0.5*2 +0.25*2 +0.5*2 +0.25(6*5/8/20) | I13: Azure構築 | J13: =4 +0.5*2 +0.25*2 +0.5*2 +0.25 -> 6.75
B14: 5 | C14: 工場DB | F14: 0.5 | G14: システムテスト | H14: 0.5 | I14: Azure構築、DB構築後のエクセルでのテスト実施
B15: 6 | C15: PRMサーバ | E15: WindowsServer2022 Oracle22c | F15: 6.75 | G15: ベース金額 +webシステムテスト×3 +webシステムテスト修正×3 +個別DB | H15: 4 +0.5*3 +0.25*3 +0.5 | I15: Azure構築、 PRM資産の為DB個別構築想定 | J15: =4 +0.5*3 +0.25*3 +0.5 -> 6.75
B16: 7 | C16: 千葉L3.5サーバ | E16: WindowsServer2022 | F16: 4 | G16: ベース金額 | H16: 4 | I16: 現地作成 A-AOUT化無し
B17: 8 | C17: 徳山L3.5サーバ | E17: WindowsServer2022 | F17: 4 | G17: ベース金額 | H17: 4 | I17: 現地作成 A-AOUT化無し
B18: 9 | C18: DBサーバ | E18: Oracle22c | I18: 縮小基盤への移設
C19: (参考)2012サーバ更新 | F19: 3.35 | I19: Azure構築
F21: ベース金額：4人月(内容：調査、基本設計、環境構築、結合テスト 、システムテスト、本番移行・初期流動、プロジェクト管理)
F22: webシステムテスト：0.5人月
F23: webシステムテスト修正：0.25人月
F24: tomcat非互換：0.5人月
F25: 個別DB：0.5人月
F26: A-AUTO：1本＊5H
H27: =350+50*4+20*4+50*2+50 -> 780
F28: =14*5/8*(100/20) -> 43.75 | H28: =350+50*3+20*3+80 -> 640
F29: =12*5/8*(100/20) -> 37.5
F30: =19*5/8*(100/20) -> 59.375
F31: =6*5/8*(100/20) -> 18.75
F32: =24*5/8*(100/20) -> 75
F33: =3*5/8*(100/20) -> 9.375
