Workbook
Name PJ番号: #REF!
Name PJ番号: #REF!
Name PJ番号: #REF!
Name ＰＪ表紙名: #REF!
Name ＰＪ表紙名: #REF!
Name ＰＪ表紙名: #REF!
Name ＰＭ名: [1]プロジェクト実施計画書!$G$7
Name プロジェクトコード: [2]!プロジェクト情報[見積番号]
Name プロジェクトコード: [2]!プロジェクト情報[見積番号]
Name プロジェクトコード: '[3]プロジェクト報告書（3.3版）'!$L$9
Name プロジェクト名: [2]!プロジェクト情報[プロジェクト名]
Name プロジェクト名: [2]!プロジェクト情報[プロジェクト名]
Name プロジェクト名: '[3]プロジェクト報告書（3.3版）'!$L$10
Name プロジェクト名称: #REF!
Name プロジェクト名称: #REF!
Name プロジェクト名称: #REF!
Name 月: #REF!
Name 月: #REF!
Name 月: #REF!
Name 検収完了日: '[3]プロジェクト報告書（3.3版）'!$AI$21
Name 顧客コード: #REF!
Name 顧客コード: #REF!
Name 顧客コード: #REF!
Name 顧客満足度調査の依頼先担当者メールアドレス: '[3]プロジェクト報告書（3.3版）'!$AI$48
Name 顧客満足度調査の依頼先担当者名: '[3]プロジェクト報告書（3.3版）'!$L$48
Name 顧客名: '[3]プロジェクト報告書（3.3版）'!$L$13
Name 顧客名称: #REF!
Name 顧客名称: #REF!
Name 顧客名称: #REF!
Name 作成者: #REF!
Name 作成者: #REF!
Name 作成者: #REF!
Name 主管部門: #REF!
Name 主管部門: #REF!
Name 主管部門: #REF!
Name 受注額: [2]!プロジェクト情報[受注額]
Name 所属: [2]!担当者情報[所属]
Name 担当者名: [2]!担当者情報[担当者]
Name 日: #REF!
Name 日: #REF!
Name 日: #REF!
Name 年: #REF!
Name 年: #REF!
Name 年: #REF!
Name 部門名: #REF!
Name 部門名: #REF!
Name 部門名: #REF!

Sheet 運転管理(パターン１)
A1: 要員配置計画（運転管理制御システム通信サーバ更新：パターン１）
B2: TOPへ
B3: 受注金額 | C3: 10850000
B4: 売上計上額 | C4: =E13 -> 10150000
B5: 原価金額 | C5: =E14 -> 5220000
B6: 粗利額 | C6: =C3-C5 -> 5630000
B7: 粗利率 | C7: =IF(C3=0,0,C6/C3) -> 0.51889401
F9: 2026年 | BB9: 2027年 | CX9: 2028年
F10: 1Q | R10: 2Q | AD10: 3Q | AP10: 4Q | BB10: 1Q | BN10: 2Q | BZ10: 3Q | CL10: 4Q | CX10: 1Q | DJ10: 2Q | DV10: 3Q | EH10: 4Q
F11: 45017 | J11: 45047 | N11: 45078 | R11: 45108 | V11: 45139 | Z11: 45170 | AD11: 45200 | AH11: 45231 | AL11: 45261 | AP11: 45292 | AT11: 45323 | AX11: 45352 | BB11: 45383 | BF11: 45413 | BJ11: 45444 | BN11: 45474 | BR11: 45505 | BV11: 45536 | BZ11: 45566 | CD11: 45597 | CH11: 45627 | CL11: 45658 | CP11: 45689 | CT11: 45717 | CX11: 45383 | DB11: 45413 | DF11: 45444 | DJ11: 45474 | DN11: 45505 | DR11: 45536 | DV11: 45566 | DZ11: 45597 | ED11: 45627 | EH11: 45658 | EL11: 45689 | EP11: 45717
B12: 総合計 | D12: 工数 | E12: =SUM(F12:ES12) -> 9 | F12: =F57+F116 -> 0 | J12: =J57+J116 -> 0 | N12: =N57+N116 -> 0 | R12: =R57+R116 -> 0 | V12: =V57+V116 -> 0 | Z12: =Z57+Z116 -> 0 | AD12: =AD57+AD116 -> 0 | AH12: =AH57+AH116 -> 0 | AL12: =AL57+AL116 -> 0 | AP12: =AP57+AP116 -> 0 | AT12: =AT57+AT116 -> 0 | AX12: =AX57+AX116 -> 0 | BB12: =BB57+BB116 -> 0 | BF12: =BF57+BF116 -> 0 | BJ12: =BJ57+BJ116 -> 0 | BN12: =BN57+BN116 -> 0 | BR12: =BR57+BR116 -> 0 | BV12: =BV57+BV116 -> 1.25 | BZ12: =BZ57+BZ116 -> 3.25 | CD12: =CD57+CD116 -> 3.25 | CH12: =CH57+CH116 -> 1.25 | CL12: =CL57+CL116 -> 0 | CP12: =CP57+CP116 -> 0 | CT12: =CT57+CT116 -> 0 | CX12: =CX57+CX116 -> 0 | DB12: =DB57+DB116 -> 0 | DF12: =DF57+DF116 -> 0 | DJ12: =DJ57+DJ116 -> 0 | DN12: =DN57+DN116 -> 0 | DR12: =DR57+DR116 -> 0 | DV12: =DV57+DV116 -> 0 | DZ12: =DZ57+DZ116 -> 0 | ED12: =ED57+ED116 -> 0 | EH12: =EH57+EH116 -> 0 | EL12: =EL57+EL116 -> 0 | EP12: =EP57+EP116 -> 0
D13: 売上金額 | E13: =SUM(F13:ES13) -> 10150000 | F13: =F58+F117 -> 0 | J13: =J58+J117 -> 0 | N13: =N58+N117 -> 0 | R13: =R58+R117 -> 0 | V13: =V58+V117 -> 0 | Z13: =Z58+Z117 -> 0 | AD13: =AD58+AD117 -> 0 | AH13: =AH58+AH117 -> 0 | AL13: =AL58+AL117 -> 0 | AP13: =AP58+AP117 -> 0 | AT13: =AT58+AT117 -> 0 | AX13: =AX58+AX117 -> 0 | BB13: =BB58+BB117 -> 0 | BF13: =BF58+BF117 -> 0 | BJ13: =BJ58+BJ117 -> 0 | BN13: =BN58+BN117 -> 0 | BR13: =BR58+BR117 -> 0 | BV13: =BV58+BV117 -> 1487500 | BZ13: =BZ58+BZ117 -> 3587500 | CD13: =CD58+CD117 -> 3587500 | CH13: =CH58+CH117 -> 1487500 | CL13: =CL58+CL117 -> 0 | CP13: =CP58+CP117 -> 0 | CT13: =CT58+CT117 -> 0 | CX13: =CX58+CX117 -> 0 | DB13: =DB58+DB117 -> 0 | DF13: =DF58+DF117 -> 0 | DJ13: =DJ58+DJ117 -> 0 | DN13: =DN58+DN117 -> 0 | DR13: =DR58+DR117 -> 0 | DV13: =DV58+DV117 -> 0 | DZ13: =DZ58+DZ117 -> 0 | ED13: =ED58+ED117 -> 0 | EH13: =EH58+EH117 -> 0 | EL13: =EL58+EL117 -> 0 | EP13: =EP58+EP117 -> 0
D14: 原価金額 | E14: =SUM(F14:ES14) -> 5220000 | F14: =F59+F118 -> 0 | J14: =J59+J118 -> 0 | N14: =N59+N118 -> 0 | R14: =R59+R118 -> 0 | V14: =V59+V118 -> 0 | Z14: =Z59+Z118 -> 0 | AD14: =AD59+AD118 -> 0 | AH14: =AH59+AH118 -> 0 | AL14: =AL59+AL118 -> 0 | AP14: =AP59+AP118 -> 0 | AT14: =AT59+AT118 -> 0 | AX14: =AX59+AX118 -> 0 | BB14: =BB59+BB118 -> 0 | BF14: =BF59+BF118 -> 0 | BJ14: =BJ59+BJ118 -> 0 | BN14: =BN59+BN118 -> 0 | BR14: =BR59+BR118 -> 0 | BV14: =BV59+BV118 -> 805000 | BZ14: =BZ59+BZ118 -> 1805000 | CD14: =CD59+CD118 -> 1805000 | CH14: =CH59+CH118 -> 805000 | CL14: =CL59+CL118 -> 0 | CP14: =CP59+CP118 -> 0 | CT14: =CT59+CT118 -> 0 | CX14: =CX59+CX118 -> 0 | DB14: =DB59+DB118 -> 0 | DF14: =DF59+DF118 -> 0 | DJ14: =DJ59+DJ118 -> 0 | DN14: =DN59+DN118 -> 0 | DR14: =DR59+DR118 -> 0 | DV14: =DV59+DV118 -> 0 | DZ14: =DZ59+DZ118 -> 0 | ED14: =ED59+ED118 -> 0 | EH14: =EH59+EH118 -> 0 | EL14: =EL59+EL118 -> 0 | EP14: =EP59+EP118 -> 0
D15: 粗利額 | E15: =SUM(F15:ES15) -> 4930000 | F15: =F13-F14 -> 0 | J15: =J13-J14 -> 0 | N15: =N13-N14 -> 0 | R15: =R13-R14 -> 0 | V15: =V13-V14 -> 0 | Z15: =Z13-Z14 -> 0 | AD15: =AD13-AD14 -> 0 | AH15: =AH13-AH14 -> 0 | AL15: =AL13-AL14 -> 0 | AP15: =AP13-AP14 -> 0 | AT15: =AT13-AT14 -> 0 | AX15: =AX13-AX14 -> 0 | BB15: =BB13-BB14 -> 0 | BF15: =BF13-BF14 -> 0 | BJ15: =BJ13-BJ14 -> 0 | BN15: =BN13-BN14 -> 0 | BR15: =BR13-BR14 -> 0 | BV15: =BV13-BV14 -> 682500 | BZ15: =BZ13-BZ14 -> 1782500 | CD15: =CD13-CD14 -> 1782500 | CH15: =CH13-CH14 -> 682500 | CL15: =CL13-CL14 -> 0 | CP15: =CP13-CP14 -> 0 | CT15: =CT13-CT14 -> 0 | CX15: =CX13-CX14 -> 0 | DB15: =DB13-DB14 -> 0 | DF15: =DF13-DF14 -> 0 | DJ15: =DJ13-DJ14 -> 0 | DN15: =DN13-DN14 -> 0 | DR15: =DR13-DR14 -> 0 | DV15: =DV13-DV14 -> 0 | DZ15: =DZ13-DZ14 -> 0 | ED15: =ED13-ED14 -> 0 | EH15: =EH13-EH14 -> 0 | EL15: =EL13-EL14 -> 0 | EP15: =EP13-EP14 -> 0
A17: 【社員・契約社員】 | C17: ※必要に応じて修正すること。
B18: 要員名 | C18: 月額単価 | D18: 内訳 | E18: 合計 | F18: 2026年 | BB18: 2027年 | CX18: 2028年
F19: 1Q | R19: 2Q | AD19: 3Q | AP19: 4Q | BB19: 1Q | BN19: 2Q | BZ19: 3Q | CL19: 4Q | CX19: 1Q | DJ19: 2Q | DV19: 3Q | EH19: 4Q
C20: (上段:売上、下段:原価) | F20: 45017 | J20: 45047 | N20: 45078 | R20: 45108 | V20: 45139 | Z20: 45170 | AD20: 45200 | AH20: 45231 | AL20: 45261 | AP20: 45292 | AT20: 45323 | AX20: 45352 | BB20: 45383 | BF20: 45413 | BJ20: 45444 | BN20: 45474 | BR20: 45505 | BV20: 45536 | BZ20: 45566 | CD20: 45597 | CH20: 45627 | CL20: 45658 | CP20: 45689 | CT20: 45717 | CX20: 45383 | DB20: 45413 | DF20: 45444 | DJ20: 45474 | DN20: 45505 | DR20: 45536 | DV20: 45566 | DZ20: 45597 | ED20: 45627 | EH20: 45658 | EL20: 45689 | EP20: 45717
B21: 福田 | D21: 工数 | E21: =SUM(F21:ES21) -> 2 | BV21: 0.5 | BZ21: 0.5 | CD21: 0.5 | CH21: 0.5
C22: 1400000 | D22: 売上金額 | E22: =SUM(F22:CW22) -> 2800000 | F22: =IFERROR($C22*F21,"") -> 0 | J22: =IFERROR($C22*J21,"") -> 0 | N22: =IFERROR($C22*N21,"") -> 0 | R22: =IFERROR($C22*R21,"") -> 0 | V22: =IFERROR($C22*V21,"") -> 0 | Z22: =IFERROR($C22*Z21,"") -> 0 | AD22: =IFERROR($C22*AD21,"") -> 0 | AH22: =IFERROR($C22*AH21,"") -> 0 | AL22: =IFERROR($C22*AL21,"") -> 0 | AP22: =IFERROR($C22*AP21,"") -> 0 | AT22: =IFERROR($C22*AT21,"") -> 0 | AX22: =IFERROR($C22*AX21,"") -> 0 | BB22: =IFERROR($C22*BB21,"") -> 0 | BF22: =IFERROR($C22*BF21,"") -> 0 | BJ22: =IFERROR($C22*BJ21,"") -> 0 | BN22: =IFERROR($C22*BN21,"") -> 0 | BR22: =IFERROR($C22*BR21,"") -> 0 | BV22: =IFERROR($C22*BV21,"") -> 700000 | BZ22: =IFERROR($C22*BZ21,"") -> 700000 | CD22: =IFERROR($C22*CD21,"") -> 700000 | CH22: =IFERROR($C22*CH21,"") -> 700000 | CL22: =IFERROR($C22*CL21,"") -> 0 | CP22: =IFERROR($C22*CP21,"") -> 0 | CT22: =IFERROR($C22*CT21,"") -> 0 | CX22: =IFERROR($C22*CX21,"") -> 0 | DB22: =IFERROR($C22*DB21,"") -> 0 | DF22: =IFERROR($C22*DF21,"") -> 0 | DJ22: =IFERROR($C22*DJ21,"") -> 0 | DN22: =IFERROR($C22*DN21,"") -> 0 | DR22: =IFERROR($C22*DR21,"") -> 0 | DV22: =IFERROR($C22*DV21,"") -> 0 | DZ22: =IFERROR($C22*DZ21,"") -> 0 | ED22: =IFERROR($C22*ED21,"") -> 0 | EH22: =IFERROR($C22*EH21,"") -> 0 | EL22: =IFERROR($C22*EL21,"") -> 0 | EP22: =IFERROR($C22*EP21,"") -> 0
C23: 600000 | D23: 原価金額 | E23: =SUM(F23:CW23) -> 1200000 | F23: =IFERROR($C23*F21,"") -> 0 | J23: =IFERROR($C23*J21,"") -> 0 | N23: =IFERROR($C23*N21,"") -> 0 | R23: =IFERROR($C23*R21,"") -> 0 | V23: =IFERROR($C23*V21,"") -> 0 | Z23: =IFERROR($C23*Z21,"") -> 0 | AD23: =IFERROR($C23*AD21,"") -> 0 | AH23: =IFERROR($C23*AH21,"") -> 0 | AL23: =IFERROR($C23*AL21,"") -> 0 | AP23: =IFERROR($C23*AP21,"") -> 0 | AT23: =IFERROR($C23*AT21,"") -> 0 | AX23: =IFERROR($C23*AX21,"") -> 0 | BB23: =IFERROR($C23*BB21,"") -> 0 | BF23: =IFERROR($C23*BF21,"") -> 0 | BJ23: =IFERROR($C23*BJ21,"") -> 0 | BN23: =IFERROR($C23*BN21,"") -> 0 | BR23: =IFERROR($C23*BR21,"") -> 0 | BV23: =IFERROR($C23*BV21,"") -> 300000 | BZ23: =IFERROR($C23*BZ21,"") -> 300000 | CD23: =IFERROR($C23*CD21,"") -> 300000 | CH23: =IFERROR($C23*CH21,"") -> 300000 | CL23: =IFERROR($C23*CL21,"") -> 0 | CP23: =IFERROR($C23*CP21,"") -> 0 | CT23: =IFERROR($C23*CT21,"") -> 0 | CX23: =IFERROR($C23*CX21,"") -> 0 | DB23: =IFERROR($C23*DB21,"") -> 0 | DF23: =IFERROR($C23*DF21,"") -> 0 | DJ23: =IFERROR($C23*DJ21,"") -> 0 | DN23: =IFERROR($C23*DN21,"") -> 0 | DR23: =IFERROR($C23*DR21,"") -> 0 | DV23: =IFERROR($C23*DV21,"") -> 0 | DZ23: =IFERROR($C23*DZ21,"") -> 0 | ED23: =IFERROR($C23*ED21,"") -> 0 | EH23: =IFERROR($C23*EH21,"") -> 0 | EL23: =IFERROR($C23*EL21,"") -> 0 | EP23: =IFERROR($C23*EP21,"") -> 0
B24: A | D24: 工数 | E24: =SUM(F24:ES24) -> 2 | BZ24: 1 | CD24: 1
C25: 1050000 | D25: 売上金額 | E25: =SUM(F25:CW25) -> 2100000 | F25: =IFERROR($C25*F24,"") -> 0 | J25: =IFERROR($C25*J24,"") -> 0 | N25: =IFERROR($C25*N24,"") -> 0 | R25: =IFERROR($C25*R24,"") -> 0 | V25: =IFERROR($C25*V24,"") -> 0 | Z25: =IFERROR($C25*Z24,"") -> 0 | AD25: =IFERROR($C25*AD24,"") -> 0 | AH25: =IFERROR($C25*AH24,"") -> 0 | AL25: =IFERROR($C25*AL24,"") -> 0 | AP25: =IFERROR($C25*AP24,"") -> 0 | AT25: =IFERROR($C25*AT24,"") -> 0 | AX25: =IFERROR($C25*AX24,"") -> 0 | BB25: =IFERROR($C25*BB24,"") -> 0 | BF25: =IFERROR($C25*BF24,"") -> 0 | BJ25: =IFERROR($C25*BJ24,"") -> 0 | BN25: =IFERROR($C25*BN24,"") -> 0 | BR25: =IFERROR($C25*BR24,"") -> 0 | BV25: =IFERROR($C25*BV24,"") -> 0 | BZ25: =IFERROR($C25*BZ24,"") -> 1050000 | CD25: =IFERROR($C25*CD24,"") -> 1050000 | CH25: =IFERROR($C25*CH24,"") -> 0 | CL25: =IFERROR($C25*CL24,"") -> 0 | CP25: =IFERROR($C25*CP24,"") -> 0 | CT25: =IFERROR($C25*CT24,"") -> 0 | CX25: =IFERROR($C25*CX24,"") -> 0 | DB25: =IFERROR($C25*DB24,"") -> 0 | DF25: =IFERROR($C25*DF24,"") -> 0 | DJ25: =IFERROR($C25*DJ24,"") -> 0 | DN25: =IFERROR($C25*DN24,"") -> 0 | DR25: =IFERROR($C25*DR24,"") -> 0 | DV25: =IFERROR($C25*DV24,"") -> 0 | DZ25: =IFERROR($C25*DZ24,"") -> 0 | ED25: =IFERROR($C25*ED24,"") -> 0 | EH25: =IFERROR($C25*EH24,"") -> 0 | EL25: =IFERROR($C25*EL24,"") -> 0 | EP25: =IFERROR($C25*EP24,"") -> 0
C26: 500000 | D26: 原価金額 | E26: =SUM(F26:CW26) -> 1000000 | F26: =IFERROR($C26*F24,"") -> 0 | J26: =IFERROR($C26*J24,"") -> 0 | N26: =IFERROR($C26*N24,"") -> 0 | R26: =IFERROR($C26*R24,"") -> 0 | V26: =IFERROR($C26*V24,"") -> 0 | Z26: =IFERROR($C26*Z24,"") -> 0 | AD26: =IFERROR($C26*AD24,"") -> 0 | AH26: =IFERROR($C26*AH24,"") -> 0 | AL26: =IFERROR($C26*AL24,"") -> 0 | AP26: =IFERROR($C26*AP24,"") -> 0 | AT26: =IFERROR($C26*AT24,"") -> 0 | AX26: =IFERROR($C26*AX24,"") -> 0 | BB26: =IFERROR($C26*BB24,"") -> 0 | BF26: =IFERROR($C26*BF24,"") -> 0 | BJ26: =IFERROR($C26*BJ24,"") -> 0 | BN26: =IFERROR($C26*BN24,"") -> 0 | BR26: =IFERROR($C26*BR24,"") -> 0 | BV26: =IFERROR($C26*BV24,"") -> 0 | BZ26: =IFERROR($C26*BZ24,"") -> 500000 | CD26: =IFERROR($C26*CD24,"") -> 500000 | CH26: =IFERROR($C26*CH24,"") -> 0 | CL26: =IFERROR($C26*CL24,"") -> 0 | CP26: =IFERROR($C26*CP24,"") -> 0 | CT26: =IFERROR($C26*CT24,"") -> 0 | CX26: =IFERROR($C26*CX24,"") -> 0 | DB26: =IFERROR($C26*DB24,"") -> 0 | DF26: =IFERROR($C26*DF24,"") -> 0 | DJ26: =IFERROR($C26*DJ24,"") -> 0 | DN26: =IFERROR($C26*DN24,"") -> 0 | DR26: =IFERROR($C26*DR24,"") -> 0 | DV26: =IFERROR($C26*DV24,"") -> 0 | DZ26: =IFERROR($C26*DZ24,"") -> 0 | ED26: =IFERROR($C26*ED24,"") -> 0 | EH26: =IFERROR($C26*EH24,"") -> 0 | EL26: =IFERROR($C26*EL24,"") -> 0 | EP26: =IFERROR($C26*EP24,"") -> 0
B27: B | D27: 工数 | E27: =SUM(F27:ES27) -> 2 | BZ27: 1 | CD27: 1
C28: 1050000 | D28: 売上金額 | E28: =SUM(F28:CW28) -> 2100000 | F28: =IFERROR($C28*F27,"") -> 0 | J28: =IFERROR($C28*J27,"") -> 0 | N28: =IFERROR($C28*N27,"") -> 0 | R28: =IFERROR($C28*R27,"") -> 0 | V28: =IFERROR($C28*V27,"") -> 0 | Z28: =IFERROR($C28*Z27,"") -> 0 | AD28: =IFERROR($C28*AD27,"") -> 0 | AH28: =IFERROR($C28*AH27,"") -> 0 | AL28: =IFERROR($C28*AL27,"") -> 0 | AP28: =IFERROR($C28*AP27,"") -> 0 | AT28: =IFERROR($C28*AT27,"") -> 0 | AX28: =IFERROR($C28*AX27,"") -> 0 | BB28: =IFERROR($C28*BB27,"") -> 0 | BF28: =IFERROR($C28*BF27,"") -> 0 | BJ28: =IFERROR($C28*BJ27,"") -> 0 | BN28: =IFERROR($C28*BN27,"") -> 0 | BR28: =IFERROR($C28*BR27,"") -> 0 | BV28: =IFERROR($C28*BV27,"") -> 0 | BZ28: =IFERROR($C28*BZ27,"") -> 1050000 | CD28: =IFERROR($C28*CD27,"") -> 1050000 | CH28: =IFERROR($C28*CH27,"") -> 0 | CL28: =IFERROR($C28*CL27,"") -> 0 | CP28: =IFERROR($C28*CP27,"") -> 0 | CT28: =IFERROR($C28*CT27,"") -> 0 | CX28: =IFERROR($C28*CX27,"") -> 0 | DB28: =IFERROR($C28*DB27,"") -> 0 | DF28: =IFERROR($C28*DF27,"") -> 0 | DJ28: =IFERROR($C28*DJ27,"") -> 0 | DN28: =IFERROR($C28*DN27,"") -> 0 | DR28: =IFERROR($C28*DR27,"") -> 0 | DV28: =IFERROR($C28*DV27,"") -> 0 | DZ28: =IFERROR($C28*DZ27,"") -> 0 | ED28: =IFERROR($C28*ED27,"") -> 0 | EH28: =IFERROR($C28*EH27,"") -> 0 | EL28: =IFERROR($C28*EL27,"") -> 0 | EP28: =IFERROR($C28*EP27,"") -> 0
C29: 500000 | D29: 原価金額 | E29: =SUM(F29:CW29) -> 1000000 | F29: =IFERROR($C29*F27,"") -> 0 | J29: =IFERROR($C29*J27,"") -> 0 | N29: =IFERROR($C29*N27,"") -> 0 | R29: =IFERROR($C29*R27,"") -> 0 | V29: =IFERROR($C29*V27,"") -> 0 | Z29: =IFERROR($C29*Z27,"") -> 0 | AD29: =IFERROR($C29*AD27,"") -> 0 | AH29: =IFERROR($C29*AH27,"") -> 0 | AL29: =IFERROR($C29*AL27,"") -> 0 | AP29: =IFERROR($C29*AP27,"") -> 0 | AT29: =IFERROR($C29*AT27,"") -> 0 | AX29: =IFERROR($C29*AX27,"") -> 0 | BB29: =IFERROR($C29*BB27,"") -> 0 | BF29: =IFERROR($C29*BF27,"") -> 0 | BJ29: =IFERROR($C29*BJ27,"") -> 0 | BN29: =IFERROR($C29*BN27,"") -> 0 | BR29: =IFERROR($C29*BR27,"") -> 0 | BV29: =IFERROR($C29*BV27,"") -> 0 | BZ29: =IFERROR($C29*BZ27,"") -> 500000 | CD29: =IFERROR($C29*CD27,"") -> 500000 | CH29: =IFERROR($C29*CH27,"") -> 0 | CL29: =IFERROR($C29*CL27,"") -> 0 | CP29: =IFERROR($C29*CP27,"") -> 0 | CT29: =IFERROR($C29*CT27,"") -> 0 | CX29: =IFERROR($C29*CX27,"") -> 0 | DB29: =IFERROR($C29*DB27,"") -> 0 | DF29: =IFERROR($C29*DF27,"") -> 0 | DJ29: =IFERROR($C29*DJ27,"") -> 0 | DN29: =IFERROR($C29*DN27,"") -> 0 | DR29: =IFERROR($C29*DR27,"") -> 0 | DV29: =IFERROR($C29*DV27,"") -> 0 | DZ29: =IFERROR($C29*DZ27,"") -> 0 | ED29: =IFERROR($C29*ED27,"") -> 0 | EH29: =IFERROR($C29*EH27,"") -> 0 | EL29: =IFERROR($C29*EL27,"") -> 0 | EP29: =IFERROR($C29*EP27,"") -> 0
B30: ブリッジ | D30: 工数 | E30: =SUM(F30:ES30) -> 0
C31: 1000000 | D31: 売上金額 | E31: =SUM(F31:CW31) -> 0 | F31: =IFERROR($C31*F30,"") -> 0 | J31: =IFERROR($C31*J30,"") -> 0 | N31: =IFERROR($C31*N30,"") -> 0 | R31: =IFERROR($C31*R30,"") -> 0 | V31: =IFERROR($C31*V30,"") -> 0 | Z31: =IFERROR($C31*Z30,"") -> 0 | AD31: =IFERROR($C31*AD30,"") -> 0 | AH31: =IFERROR($C31*AH30,"") -> 0 | AL31: =IFERROR($C31*AL30,"") -> 0 | AP31: =IFERROR($C31*AP30,"") -> 0 | AT31: =IFERROR($C31*AT30,"") -> 0 | AX31: =IFERROR($C31*AX30,"") -> 0 | BB31: =IFERROR($C31*BB30,"") -> 0 | BF31: =IFERROR($C31*BF30,"") -> 0 | BJ31: =IFERROR($C31*BJ30,"") -> 0 | BN31: =IFERROR($C31*BN30,"") -> 0 | BR31: =IFERROR($C31*BR30,"") -> 0 | BV31: =IFERROR($C31*BV30,"") -> 0 | BZ31: =IFERROR($C31*BZ30,"") -> 0 | CD31: =IFERROR($C31*CD30,"") -> 0 | CH31: =IFERROR($C31*CH30,"") -> 0 | CL31: =IFERROR($C31*CL30,"") -> 0 | CP31: =IFERROR($C31*CP30,"") -> 0 | CT31: =IFERROR($C31*CT30,"") -> 0 | CX31: =IFERROR($C31*CX30,"") -> 0 | DB31: =IFERROR($C31*DB30,"") -> 0 | DF31: =IFERROR($C31*DF30,"") -> 0 | DJ31: =IFERROR($C31*DJ30,"") -> 0 | DN31: =IFERROR($C31*DN30,"") -> 0 | DR31: =IFERROR($C31*DR30,"") -> 0 | DV31: =IFERROR($C31*DV30,"") -> 0 | DZ31: =IFERROR($C31*DZ30,"") -> 0 | ED31: =IFERROR($C31*ED30,"") -> 0 | EH31: =IFERROR($C31*EH30,"") -> 0 | EL31: =IFERROR($C31*EL30,"") -> 0 | EP31: =IFERROR($C31*EP30,"") -> 0
C32: 420000 | D32: 原価金額 | E32: =SUM(F32:CW32) -> 0 | F32: =IFERROR($C32*F30,"") -> 0 | J32: =IFERROR($C32*J30,"") -> 0 | N32: =IFERROR($C32*N30,"") -> 0 | R32: =IFERROR($C32*R30,"") -> 0 | V32: =IFERROR($C32*V30,"") -> 0 | Z32: =IFERROR($C32*Z30,"") -> 0 | AD32: =IFERROR($C32*AD30,"") -> 0 | AH32: =IFERROR($C32*AH30,"") -> 0 | AL32: =IFERROR($C32*AL30,"") -> 0 | AP32: =IFERROR($C32*AP30,"") -> 0 | AT32: =IFERROR($C32*AT30,"") -> 0 | AX32: =IFERROR($C32*AX30,"") -> 0 | BB32: =IFERROR($C32*BB30,"") -> 0 | BF32: =IFERROR($C32*BF30,"") -> 0 | BJ32: =IFERROR($C32*BJ30,"") -> 0 | BN32: =IFERROR($C32*BN30,"") -> 0 | BR32: =IFERROR($C32*BR30,"") -> 0 | BV32: =IFERROR($C32*BV30,"") -> 0 | BZ32: =IFERROR($C32*BZ30,"") -> 0 | CD32: =IFERROR($C32*CD30,"") -> 0 | CH32: =IFERROR($C32*CH30,"") -> 0 | CL32: =IFERROR($C32*CL30,"") -> 0 | CP32: =IFERROR($C32*CP30,"") -> 0 | CT32: =IFERROR($C32*CT30,"") -> 0 | CX32: =IFERROR($C32*CX30,"") -> 0 | DB32: =IFERROR($C32*DB30,"") -> 0 | DF32: =IFERROR($C32*DF30,"") -> 0 | DJ32: =IFERROR($C32*DJ30,"") -> 0 | DN32: =IFERROR($C32*DN30,"") -> 0 | DR32: =IFERROR($C32*DR30,"") -> 0 | DV32: =IFERROR($C32*DV30,"") -> 0 | DZ32: =IFERROR($C32*DZ30,"") -> 0 | ED32: =IFERROR($C32*ED30,"") -> 0 | EH32: =IFERROR($C32*EH30,"") -> 0 | EL32: =IFERROR($C32*EL30,"") -> 0 | EP32: =IFERROR($C32*EP30,"") -> 0
B33: B | D33: 工数 | E33: =SUM(F33:ES33) -> 0
C34: 1000000 | D34: 売上金額 | E34: =SUM(F34:CW34) -> 0 | F34: =IFERROR($C34*F33,"") -> 0 | J34: =IFERROR($C34*J33,"") -> 0 | N34: =IFERROR($C34*N33,"") -> 0 | R34: =IFERROR($C34*R33,"") -> 0 | V34: =IFERROR($C34*V33,"") -> 0 | Z34: =IFERROR($C34*Z33,"") -> 0 | AD34: =IFERROR($C34*AD33,"") -> 0 | DR34: =IFERROR($C34*DR33,"") -> 0 | DV34: =IFERROR($C34*DV33,"") -> 0 | DZ34: =IFERROR($C34*DZ33,"") -> 0 | ED34: =IFERROR($C34*ED33,"") -> 0 | EH34: =IFERROR($C34*EH33,"") -> 0 | EL34: =IFERROR($C34*EL33,"") -> 0 | EP34: =IFERROR($C34*EP33,"") -> 0
C35: 420000 | D35: 原価金額 | E35: =SUM(F35:CW35) -> 0 | F35: =IFERROR($C35*F33,"") -> 0 | J35: =IFERROR($C35*J33,"") -> 0 | N35: =IFERROR($C35*N33,"") -> 0 | R35: =IFERROR($C35*R33,"") -> 0 | V35: =IFERROR($C35*V33,"") -> 0 | Z35: =IFERROR($C35*Z33,"") -> 0 | AD35: =IFERROR($C35*AD33,"") -> 0 | DR35: =IFERROR($C35*DR33,"") -> 0 | DV35: =IFERROR($C35*DV33,"") -> 0 | DZ35: =IFERROR($C35*DZ33,"") -> 0 | ED35: =IFERROR($C35*ED33,"") -> 0 | EH35: =IFERROR($C35*EH33,"") -> 0 | EL35: =IFERROR($C35*EL33,"") -> 0 | EP35: =IFERROR($C35*EP33,"") -> 0
B36: C | D36: 工数 | E36: =SUM(F36:ES36) -> 0
C37: 1000000 | D37: 売上金額 | E37: =SUM(F37:CW37) -> 0 | F37: =IFERROR($C37*F36,"") -> 0 | J37: =IFERROR($C37*J36,"") -> 0 | N37: =IFERROR($C37*N36,"") -> 0 | R37: =IFERROR($C37*R36,"") -> 0 | V37: =IFERROR($C37*V36,"") -> 0 | Z37: =IFERROR($C37*Z36,"") -> 0 | AD37: =IFERROR($C37*AD36,"") -> 0 | DR37: =IFERROR($C37*DR36,"") -> 0 | DV37: =IFERROR($C37*DV36,"") -> 0 | DZ37: =IFERROR($C37*DZ36,"") -> 0 | ED37: =IFERROR($C37*ED36,"") -> 0 | EH37: =IFERROR($C37*EH36,"") -> 0 | EL37: =IFERROR($C37*EL36,"") -> 0 | EP37: =IFERROR($C37*EP36,"") -> 0
C38: 420000 | D38: 原価金額 | E38: =SUM(F38:CW38) -> 0 | F38: =IFERROR($C38*F36,"") -> 0 | J38: =IFERROR($C38*J36,"") -> 0 | N38: =IFERROR($C38*N36,"") -> 0 | R38: =IFERROR($C38*R36,"") -> 0 | V38: =IFERROR($C38*V36,"") -> 0 | Z38: =IFERROR($C38*Z36,"") -> 0 | AD38: =IFERROR($C38*AD36,"") -> 0 | DR38: =IFERROR($C38*DR36,"") -> 0 | DV38: =IFERROR($C38*DV36,"") -> 0 | DZ38: =IFERROR($C38*DZ36,"") -> 0 | ED38: =IFERROR($C38*ED36,"") -> 0 | EH38: =IFERROR($C38*EH36,"") -> 0 | EL38: =IFERROR($C38*EL36,"") -> 0 | EP38: =IFERROR($C38*EP36,"") -> 0
B39: D | D39: 工数 | E39: =SUM(F39:ES39) -> 0
C40: 1000000 | D40: 売上金額 | E40: =SUM(F40:CW40) -> 0 | F40: =IFERROR($C40*F39,"") -> 0 | J40: =IFERROR($C40*J39,"") -> 0 | N40: =IFERROR($C40*N39,"") -> 0 | R40: =IFERROR($C40*R39,"") -> 0 | V40: =IFERROR($C40*V39,"") -> 0 | Z40: =IFERROR($C40*Z39,"") -> 0 | AD40: =IFERROR($C40*AD39,"") -> 0 | DR40: =IFERROR($C40*DR39,"") -> 0 | DV40: =IFERROR($C40*DV39,"") -> 0 | DZ40: =IFERROR($C40*DZ39,"") -> 0 | ED40: =IFERROR($C40*ED39,"") -> 0 | EH40: =IFERROR($C40*EH39,"") -> 0 | EL40: =IFERROR($C40*EL39,"") -> 0 | EP40: =IFERROR($C40*EP39,"") -> 0
C41: 420000 | D41: 原価金額 | E41: =SUM(F41:CW41) -> 0 | F41: =IFERROR($C41*F39,"") -> 0 | J41: =IFERROR($C41*J39,"") -> 0 | N41: =IFERROR($C41*N39,"") -> 0 | R41: =IFERROR($C41*R39,"") -> 0 | V41: =IFERROR($C41*V39,"") -> 0 | Z41: =IFERROR($C41*Z39,"") -> 0 | AD41: =IFERROR($C41*AD39,"") -> 0 | DR41: =IFERROR($C41*DR39,"") -> 0 | DV41: =IFERROR($C41*DV39,"") -> 0 | DZ41: =IFERROR($C41*DZ39,"") -> 0 | ED41: =IFERROR($C41*ED39,"") -> 0 | EH41: =IFERROR($C41*EH39,"") -> 0 | EL41: =IFERROR($C41*EL39,"") -> 0 | EP41: =IFERROR($C41*EP39,"") -> 0
D42: 工数 | E42: =SUM(F42:CW42) -> 0
D43: 売上金額 | E43: =SUM(F43:CW43) -> 0 | F43: =IFERROR($C43*F42,"") -> 0 | J43: =IFERROR($C43*J42,"") -> 0 | N43: =IFERROR($C43*N42,"") -> 0 | R43: =IFERROR($C43*R42,"") -> 0 | V43: =IFERROR($C43*V42,"") -> 0 | Z43: =IFERROR($C43*Z42,"") -> 0 | AD43: =IFERROR($C43*AD42,"") -> 0 | AH43: =IFERROR($C43*AH42,"") -> 0 | AL43: =IFERROR($C43*AL42,"") -> 0 | AP43: =IFERROR($C43*AP42,"") -> 0 | AT43: =IFERROR($C43*AT42,"") -> 0 | AX43: =IFERROR($C43*AX42,"") -> 0 | BB43: =IFERROR($C43*BB42,"") -> 0 | BF43: =IFERROR($C43*BF42,"") -> 0 | BJ43: =IFERROR($C43*BJ42,"") -> 0 | BN43: =IFERROR($C43*BN42,"") -> 0 | BR43: =IFERROR($C43*BR42,"") -> 0 | BV43: =IFERROR($C43*BV42,"") -> 0 | BZ43: =IFERROR($C43*BZ42,"") -> 0 | CD43: =IFERROR($C43*CD42,"") -> 0 | CH43: =IFERROR($C43*CH42,"") -> 0 | CL43: =IFERROR($C43*CL42,"") -> 0 | CP43: =IFERROR($C43*CP42,"") -> 0 | CT43: =IFERROR($C43*CT42,"") -> 0 | CX43: =IFERROR($C43*CX42,"") -> 0 | DB43: =IFERROR($C43*DB42,"") -> 0 | DF43: =IFERROR($C43*DF42,"") -> 0 | DJ43: =IFERROR($C43*DJ42,"") -> 0 | DN43: =IFERROR($C43*DN42,"") -> 0 | DR43: =IFERROR($C43*DR42,"") -> 0 | DV43: =IFERROR($C43*DV42,"") -> 0 | DZ43: =IFERROR($C43*DZ42,"") -> 0 | ED43: =IFERROR($C43*ED42,"") -> 0 | EH43: =IFERROR($C43*EH42,"") -> 0 | EL43: =IFERROR($C43*EL42,"") -> 0 | EP43: =IFERROR($C43*EP42,"") -> 0
D44: 原価金額 | E44: =SUM(F44:CW44) -> 0 | F44: =IFERROR($C44*F42,"") -> 0 | J44: =IFERROR($C44*J42,"") -> 0 | N44: =IFERROR($C44*N42,"") -> 0 | R44: =IFERROR($C44*R42,"") -> 0 | V44: =IFERROR($C44*V42,"") -> 0 | Z44: =IFERROR($C44*Z42,"") -> 0 | AD44: =IFERROR($C44*AD42,"") -> 0 | AH44: =IFERROR($C44*AH42,"") -> 0 | AL44: =IFERROR($C44*AL42,"") -> 0 | AP44: =IFERROR($C44*AP42,"") -> 0 | AT44: =IFERROR($C44*AT42,"") -> 0 | AX44: =IFERROR($C44*AX42,"") -> 0 | BB44: =IFERROR($C44*BB42,"") -> 0 | BF44: =IFERROR($C44*BF42,"") -> 0 | BJ44: =IFERROR($C44*BJ42,"") -> 0 | BN44: =IFERROR($C44*BN42,"") -> 0 | BR44: =IFERROR($C44*BR42,"") -> 0 | BV44: =IFERROR($C44*BV42,"") -> 0 | BZ44: =IFERROR($C44*BZ42,"") -> 0 | CD44: =IFERROR($C44*CD42,"") -> 0 | CH44: =IFERROR($C44*CH42,"") -> 0 | CL44: =IFERROR($C44*CL42,"") -> 0 | CP44: =IFERROR($C44*CP42,"") -> 0 | CT44: =IFERROR($C44*CT42,"") -> 0 | CX44: =IFERROR($C44*CX42,"") -> 0 | DB44: =IFERROR($C44*DB42,"") -> 0 | DF44: =IFERROR($C44*DF42,"") -> 0 | DJ44: =IFERROR($C44*DJ42,"") -> 0 | DN44: =IFERROR($C44*DN42,"") -> 0 | DR44: =IFERROR($C44*DR42,"") -> 0 | DV44: =IFERROR($C44*DV42,"") -> 0 | DZ44: =IFERROR($C44*DZ42,"") -> 0 | ED44: =IFERROR($C44*ED42,"") -> 0 | EH44: =IFERROR($C44*EH42,"") -> 0 | EL44: =IFERROR($C44*EL42,"") -> 0 | EP44: =IFERROR($C44*EP42,"") -> 0
D45: 工数 | E45: =SUM(F45:CW45) -> 0
D46: 売上金額 | E46: =SUM(F46:CW46) -> 0 | F46: =IFERROR($C46*F45,"") -> 0 | J46: =IFERROR($C46*J45,"") -> 0 | N46: =IFERROR($C46*N45,"") -> 0 | R46: =IFERROR($C46*R45,"") -> 0 | V46: =IFERROR($C46*V45,"") -> 0 | Z46: =IFERROR($C46*Z45,"") -> 0 | AD46: =IFERROR($C46*AD45,"") -> 0 | AH46: =IFERROR($C46*AH45,"") -> 0 | AL46: =IFERROR($C46*AL45,"") -> 0 | AP46: =IFERROR($C46*AP45,"") -> 0 | AT46: =IFERROR($C46*AT45,"") -> 0 | AX46: =IFERROR($C46*AX45,"") -> 0 | BB46: =IFERROR($C46*BB45,"") -> 0 | BF46: =IFERROR($C46*BF45,"") -> 0 | BJ46: =IFERROR($C46*BJ45,"") -> 0 | BN46: =IFERROR($C46*BN45,"") -> 0 | BR46: =IFERROR($C46*BR45,"") -> 0 | BV46: =IFERROR($C46*BV45,"") -> 0 | BZ46: =IFERROR($C46*BZ45,"") -> 0 | CD46: =IFERROR($C46*CD45,"") -> 0 | CH46: =IFERROR($C46*CH45,"") -> 0 | CL46: =IFERROR($C46*CL45,"") -> 0 | CP46: =IFERROR($C46*CP45,"") -> 0 | CT46: =IFERROR($C46*CT45,"") -> 0 | CX46: =IFERROR($C46*CX45,"") -> 0 | DB46: =IFERROR($C46*DB45,"") -> 0 | DF46: =IFERROR($C46*DF45,"") -> 0 | DJ46: =IFERROR($C46*DJ45,"") -> 0 | DN46: =IFERROR($C46*DN45,"") -> 0 | DR46: =IFERROR($C46*DR45,"") -> 0 | DV46: =IFERROR($C46*DV45,"") -> 0 | DZ46: =IFERROR($C46*DZ45,"") -> 0 | ED46: =IFERROR($C46*ED45,"") -> 0 | EH46: =IFERROR($C46*EH45,"") -> 0 | EL46: =IFERROR($C46*EL45,"") -> 0 | EP46: =IFERROR($C46*EP45,"") -> 0
D47: 原価金額 | E47: =SUM(F47:CW47) -> 0 | F47: =IFERROR($C47*F45,"") -> 0 | J47: =IFERROR($C47*J45,"") -> 0 | N47: =IFERROR($C47*N45,"") -> 0 | R47: =IFERROR($C47*R45,"") -> 0 | V47: =IFERROR($C47*V45,"") -> 0 | Z47: =IFERROR($C47*Z45,"") -> 0 | AD47: =IFERROR($C47*AD45,"") -> 0 | AH47: =IFERROR($C47*AH45,"") -> 0 | AL47: =IFERROR($C47*AL45,"") -> 0 | AP47: =IFERROR($C47*AP45,"") -> 0 | AT47: =IFERROR($C47*AT45,"") -> 0 | AX47: =IFERROR($C47*AX45,"") -> 0 | BB47: =IFERROR($C47*BB45,"") -> 0 | BF47: =IFERROR($C47*BF45,"") -> 0 | BJ47: =IFERROR($C47*BJ45,"") -> 0 | BN47: =IFERROR($C47*BN45,"") -> 0 | BR47: =IFERROR($C47*BR45,"") -> 0 | BV47: =IFERROR($C47*BV45,"") -> 0 | BZ47: =IFERROR($C47*BZ45,"") -> 0 | CD47: =IFERROR($C47*CD45,"") -> 0 | CH47: =IFERROR($C47*CH45,"") -> 0 | CL47: =IFERROR($C47*CL45,"") -> 0 | CP47: =IFERROR($C47*CP45,"") -> 0 | CT47: =IFERROR($C47*CT45,"") -> 0 | CX47: =IFERROR($C47*CX45,"") -> 0 | DB47: =IFERROR($C47*DB45,"") -> 0 | DF47: =IFERROR($C47*DF45,"") -> 0 | DJ47: =IFERROR($C47*DJ45,"") -> 0 | DN47: =IFERROR($C47*DN45,"") -> 0 | DR47: =IFERROR($C47*DR45,"") -> 0 | DV47: =IFERROR($C47*DV45,"") -> 0 | DZ47: =IFERROR($C47*DZ45,"") -> 0 | ED47: =IFERROR($C47*ED45,"") -> 0 | EH47: =IFERROR($C47*EH45,"") -> 0 | EL47: =IFERROR($C47*EL45,"") -> 0 | EP47: =IFERROR($C47*EP45,"") -> 0
D48: 工数 | E48: =SUM(F48:CW48) -> 0
D49: 売上金額 | E49: =SUM(F49:CW49) -> 0 | F49: =IFERROR($C49*F48,"") -> 0 | J49: =IFERROR($C49*J48,"") -> 0 | N49: =IFERROR($C49*N48,"") -> 0 | R49: =IFERROR($C49*R48,"") -> 0 | V49: =IFERROR($C49*V48,"") -> 0 | Z49: =IFERROR($C49*Z48,"") -> 0 | AD49: =IFERROR($C49*AD48,"") -> 0 | AH49: =IFERROR($C49*AH48,"") -> 0 | AL49: =IFERROR($C49*AL48,"") -> 0 | AP49: =IFERROR($C49*AP48,"") -> 0 | AT49: =IFERROR($C49*AT48,"") -> 0 | AX49: =IFERROR($C49*AX48,"") -> 0 | BB49: =IFERROR($C49*BB48,"") -> 0 | BF49: =IFERROR($C49*BF48,"") -> 0 | BJ49: =IFERROR($C49*BJ48,"") -> 0 | BN49: =IFERROR($C49*BN48,"") -> 0 | BR49: =IFERROR($C49*BR48,"") -> 0 | BV49: =IFERROR($C49*BV48,"") -> 0 | BZ49: =IFERROR($C49*BZ48,"") -> 0 | CD49: =IFERROR($C49*CD48,"") -> 0 | CH49: =IFERROR($C49*CH48,"") -> 0 | CL49: =IFERROR($C49*CL48,"") -> 0 | CP49: =IFERROR($C49*CP48,"") -> 0 | CT49: =IFERROR($C49*CT48,"") -> 0 | CX49: =IFERROR($C49*CX48,"") -> 0 | DB49: =IFERROR($C49*DB48,"") -> 0 | DF49: =IFERROR($C49*DF48,"") -> 0 | DJ49: =IFERROR($C49*DJ48,"") -> 0 | DN49: =IFERROR($C49*DN48,"") -> 0 | DR49: =IFERROR($C49*DR48,"") -> 0 | DV49: =IFERROR($C49*DV48,"") -> 0 | DZ49: =IFERROR($C49*DZ48,"") -> 0 | ED49: =IFERROR($C49*ED48,"") -> 0 | EH49: =IFERROR($C49*EH48,"") -> 0 | EL49: =IFERROR($C49*EL48,"") -> 0 | EP49: =IFERROR($C49*EP48,"") -> 0
D50: 原価金額 | E50: =SUM(F50:CW50) -> 0 | F50: =IFERROR($C50*F48,"") -> 0 | J50: =IFERROR($C50*J48,"") -> 0 | N50: =IFERROR($C50*N48,"") -> 0 | R50: =IFERROR($C50*R48,"") -> 0 | V50: =IFERROR($C50*V48,"") -> 0 | Z50: =IFERROR($C50*Z48,"") -> 0 | AD50: =IFERROR($C50*AD48,"") -> 0 | AH50: =IFERROR($C50*AH48,"") -> 0 | AL50: =IFERROR($C50*AL48,"") -> 0 | AP50: =IFERROR($C50*AP48,"") -> 0 | AT50: =IFERROR($C50*AT48,"") -> 0 | AX50: =IFERROR($C50*AX48,"") -> 0 | BB50: =IFERROR($C50*BB48,"") -> 0 | BF50: =IFERROR($C50*BF48,"") -> 0 | BJ50: =IFERROR($C50*BJ48,"") -> 0 | BN50: =IFERROR($C50*BN48,"") -> 0 | BR50: =IFERROR($C50*BR48,"") -> 0 | BV50: =IFERROR($C50*BV48,"") -> 0 | BZ50: =IFERROR($C50*BZ48,"") -> 0 | CD50: =IFERROR($C50*CD48,"") -> 0 | CH50: =IFERROR($C50*CH48,"") -> 0 | CL50: =IFERROR($C50*CL48,"") -> 0 | CP50: =IFERROR($C50*CP48,"") -> 0 | CT50: =IFERROR($C50*CT48,"") -> 0 | CX50: =IFERROR($C50*CX48,"") -> 0 | DB50: =IFERROR($C50*DB48,"") -> 0 | DF50: =IFERROR($C50*DF48,"") -> 0 | DJ50: =IFERROR($C50*DJ48,"") -> 0 | DN50: =IFERROR($C50*DN48,"") -> 0 | DR50: =IFERROR($C50*DR48,"") -> 0 | DV50: =IFERROR($C50*DV48,"") -> 0 | DZ50: =IFERROR($C50*DZ48,"") -> 0 | ED50: =IFERROR($C50*ED48,"") -> 0 | EH50: =IFERROR($C50*EH48,"") -> 0 | EL50: =IFERROR($C50*EL48,"") -> 0 | EP50: =IFERROR($C50*EP48,"") -> 0
D51: 工数 | E51: =SUM(F51:CW51) -> 0
D52: 売上金額 | E52: =SUM(F52:CW52) -> 0 | F52: =IFERROR($C52*F51,"") -> 0 | J52: =IFERROR($C52*J51,"") -> 0 | N52: =IFERROR($C52*N51,"") -> 0 | R52: =IFERROR($C52*R51,"") -> 0 | V52: =IFERROR($C52*V51,"") -> 0 | Z52: =IFERROR($C52*Z51,"") -> 0 | AD52: =IFERROR($C52*AD51,"") -> 0 | AH52: =IFERROR($C52*AH51,"") -> 0 | AL52: =IFERROR($C52*AL51,"") -> 0 | AP52: =IFERROR($C52*AP51,"") -> 0 | AT52: =IFERROR($C52*AT51,"") -> 0 | AX52: =IFERROR($C52*AX51,"") -> 0 | BB52: =IFERROR($C52*BB51,"") -> 0 | BF52: =IFERROR($C52*BF51,"") -> 0 | BJ52: =IFERROR($C52*BJ51,"") -> 0 | BN52: =IFERROR($C52*BN51,"") -> 0 | BR52: =IFERROR($C52*BR51,"") -> 0 | BV52: =IFERROR($C52*BV51,"") -> 0 | BZ52: =IFERROR($C52*BZ51,"") -> 0 | CD52: =IFERROR($C52*CD51,"") -> 0 | CH52: =IFERROR($C52*CH51,"") -> 0 | CL52: =IFERROR($C52*CL51,"") -> 0 | CP52: =IFERROR($C52*CP51,"") -> 0 | CT52: =IFERROR($C52*CT51,"") -> 0 | CX52: =IFERROR($C52*CX51,"") -> 0 | DB52: =IFERROR($C52*DB51,"") -> 0 | DF52: =IFERROR($C52*DF51,"") -> 0 | DJ52: =IFERROR($C52*DJ51,"") -> 0 | DN52: =IFERROR($C52*DN51,"") -> 0 | DR52: =IFERROR($C52*DR51,"") -> 0 | DV52: =IFERROR($C52*DV51,"") -> 0 | DZ52: =IFERROR($C52*DZ51,"") -> 0 | ED52: =IFERROR($C52*ED51,"") -> 0 | EH52: =IFERROR($C52*EH51,"") -> 0 | EL52: =IFERROR($C52*EL51,"") -> 0 | EP52: =IFERROR($C52*EP51,"") -> 0
D53: 原価金額 | E53: =SUM(F53:CW53) -> 0 | F53: =IFERROR($C53*F51,"") -> 0 | J53: =IFERROR($C53*J51,"") -> 0 | N53: =IFERROR($C53*N51,"") -> 0 | R53: =IFERROR($C53*R51,"") -> 0 | V53: =IFERROR($C53*V51,"") -> 0 | Z53: =IFERROR($C53*Z51,"") -> 0 | AD53: =IFERROR($C53*AD51,"") -> 0 | AH53: =IFERROR($C53*AH51,"") -> 0 | AL53: =IFERROR($C53*AL51,"") -> 0 | AP53: =IFERROR($C53*AP51,"") -> 0 | AT53: =IFERROR($C53*AT51,"") -> 0 | AX53: =IFERROR($C53*AX51,"") -> 0 | BB53: =IFERROR($C53*BB51,"") -> 0 | BF53: =IFERROR($C53*BF51,"") -> 0 | BJ53: =IFERROR($C53*BJ51,"") -> 0 | BN53: =IFERROR($C53*BN51,"") -> 0 | BR53: =IFERROR($C53*BR51,"") -> 0 | BV53: =IFERROR($C53*BV51,"") -> 0 | BZ53: =IFERROR($C53*BZ51,"") -> 0 | CD53: =IFERROR($C53*CD51,"") -> 0 | CH53: =IFERROR($C53*CH51,"") -> 0 | CL53: =IFERROR($C53*CL51,"") -> 0 | CP53: =IFERROR($C53*CP51,"") -> 0 | CT53: =IFERROR($C53*CT51,"") -> 0 | CX53: =IFERROR($C53*CX51,"") -> 0 | DB53: =IFERROR($C53*DB51,"") -> 0 | DF53: =IFERROR($C53*DF51,"") -> 0 | DJ53: =IFERROR($C53*DJ51,"") -> 0 | DN53: =IFERROR($C53*DN51,"") -> 0 | DR53: =IFERROR($C53*DR51,"") -> 0 | DV53: =IFERROR($C53*DV51,"") -> 0 | DZ53: =IFERROR($C53*DZ51,"") -> 0 | ED53: =IFERROR($C53*ED51,"") -> 0 | EH53: =IFERROR($C53*EH51,"") -> 0 | EL53: =IFERROR($C53*EL51,"") -> 0 | EP53: =IFERROR($C53*EP51,"") -> 0
D54: 工数 | E54: =SUM(F54:CW54) -> 0
D55: 売上金額 | E55: =SUM(F55:CW55) -> 0 | F55: =IFERROR($C55*F54,"") -> 0 | J55: =IFERROR($C55*J54,"") -> 0 | N55: =IFERROR($C55*N54,"") -> 0 | R55: =IFERROR($C55*R54,"") -> 0 | V55: =IFERROR($C55*V54,"") -> 0 | Z55: =IFERROR($C55*Z54,"") -> 0 | AD55: =IFERROR($C55*AD54,"") -> 0 | AH55: =IFERROR($C55*AH54,"") -> 0 | AL55: =IFERROR($C55*AL54,"") -> 0 | AP55: =IFERROR($C55*AP54,"") -> 0 | AT55: =IFERROR($C55*AT54,"") -> 0 | AX55: =IFERROR($C55*AX54,"") -> 0 | BB55: =IFERROR($C55*BB54,"") -> 0 | BF55: =IFERROR($C55*BF54,"") -> 0 | BJ55: =IFERROR($C55*BJ54,"") -> 0 | BN55: =IFERROR($C55*BN54,"") -> 0 | BR55: =IFERROR($C55*BR54,"") -> 0 | BV55: =IFERROR($C55*BV54,"") -> 0 | BZ55: =IFERROR($C55*BZ54,"") -> 0 | CD55: =IFERROR($C55*CD54,"") -> 0 | CH55: =IFERROR($C55*CH54,"") -> 0 | CL55: =IFERROR($C55*CL54,"") -> 0 | CP55: =IFERROR($C55*CP54,"") -> 0 | CT55: =IFERROR($C55*CT54,"") -> 0 | CX55: =IFERROR($C55*CX54,"") -> 0 | DB55: =IFERROR($C55*DB54,"") -> 0 | DF55: =IFERROR($C55*DF54,"") -> 0 | DJ55: =IFERROR($C55*DJ54,"") -> 0 | DN55: =IFERROR($C55*DN54,"") -> 0 | DR55: =IFERROR($C55*DR54,"") -> 0 | DV55: =IFERROR($C55*DV54,"") -> 0 | DZ55: =IFERROR($C55*DZ54,"") -> 0 | ED55: =IFERROR($C55*ED54,"") -> 0 | EH55: =IFERROR($C55*EH54,"") -> 0 | EL55: =IFERROR($C55*EL54,"") -> 0 | EP55: =IFERROR($C55*EP54,"") -> 0
D56: 原価金額 | E56: =SUM(F56:CW56) -> 0 | F56: =IFERROR($C56*F54,"") -> 0 | J56: =IFERROR($C56*J54,"") -> 0 | N56: =IFERROR($C56*N54,"") -> 0 | R56: =IFERROR($C56*R54,"") -> 0 | V56: =IFERROR($C56*V54,"") -> 0 | Z56: =IFERROR($C56*Z54,"") -> 0 | AD56: =IFERROR($C56*AD54,"") -> 0 | AH56: =IFERROR($C56*AH54,"") -> 0 | AL56: =IFERROR($C56*AL54,"") -> 0 | AP56: =IFERROR($C56*AP54,"") -> 0 | AT56: =IFERROR($C56*AT54,"") -> 0 | AX56: =IFERROR($C56*AX54,"") -> 0 | BB56: =IFERROR($C56*BB54,"") -> 0 | BF56: =IFERROR($C56*BF54,"") -> 0 | BJ56: =IFERROR($C56*BJ54,"") -> 0 | BN56: =IFERROR($C56*BN54,"") -> 0 | BR56: =IFERROR($C56*BR54,"") -> 0 | BV56: =IFERROR($C56*BV54,"") -> 0 | BZ56: =IFERROR($C56*BZ54,"") -> 0 | CD56: =IFERROR($C56*CD54,"") -> 0 | CH56: =IFERROR($C56*CH54,"") -> 0 | CL56: =IFERROR($C56*CL54,"") -> 0 | CP56: =IFERROR($C56*CP54,"") -> 0 | CT56: =IFERROR($C56*CT54,"") -> 0 | CX56: =IFERROR($C56*CX54,"") -> 0 | DB56: =IFERROR($C56*DB54,"") -> 0 | DF56: =IFERROR($C56*DF54,"") -> 0 | DJ56: =IFERROR($C56*DJ54,"") -> 0 | DN56: =IFERROR($C56*DN54,"") -> 0 | DR56: =IFERROR($C56*DR54,"") -> 0 | DV56: =IFERROR($C56*DV54,"") -> 0 | DZ56: =IFERROR($C56*DZ54,"") -> 0 | ED56: =IFERROR($C56*ED54,"") -> 0 | EH56: =IFERROR($C56*EH54,"") -> 0 | EL56: =IFERROR($C56*EL54,"") -> 0 | EP56: =IFERROR($C56*EP54,"") -> 0
B57: 合 計 | E57: =SUM(F57:CW57) -> 6 | F57: =SUMIF($D21:$D56,"工数",F21:I56) -> 0 | J57: =SUMIF($D21:$D56,"工数",J21:M56) -> 0 | N57: =SUMIF($D21:$D56,"工数",N21:Q56) -> 0 | R57: =SUMIF($D21:$D56,"工数",R21:U56) -> 0 | V57: =SUMIF($D21:$D56,"工数",V21:Y56) -> 0 | Z57: =SUMIF($D21:$D56,"工数",Z21:AC56) -> 0 | AD57: =SUMIF($D21:$D56,"工数",AD21:AG56) -> 0 | AH57: =SUMIF($D21:$D56,"工数",AH21:AK56) -> 0 | AL57: =SUMIF($D21:$D56,"工数",AL21:AO56) -> 0 | AP57: =SUMIF($D21:$D56,"工数",AP21:AS56) -> 0 | AT57: =SUMIF($D21:$D56,"工数",AT21:AW56) -> 0 | AX57: =SUMIF($D21:$D56,"工数",AX21:BA56) -> 0 | BB57: =SUMIF($D21:$D56,"工数",BB21:BE56) -> 0 | BF57: =SUMIF($D21:$D56,"工数",BF21:BI56) -> 0 | BJ57: =SUMIF($D21:$D56,"工数",BJ21:BM56) -> 0 | BN57: =SUMIF($D21:$D56,"工数",BN21:BQ56) -> 0 | BR57: =SUMIF($D21:$D56,"工数",BR21:BU56) -> 0 | BV57: =SUMIF($D21:$D56,"工数",BV21:BY56) -> 0.5 | BZ57: =SUMIF($D21:$D56,"工数",BZ21:CC56) -> 2.5 | CD57: =SUMIF($D21:$D56,"工数",CD21:CG56) -> 2.5 | CH57: =SUMIF($D21:$D56,"工数",CH21:CK56) -> 0.5 | CL57: =SUMIF($D21:$D56,"工数",CL21:CO56) -> 0 | CP57: =SUMIF($D21:$D56,"工数",CP21:CS56) -> 0 | CT57: =SUMIF($D21:$D56,"工数",CT21:CW56) -> 0 | CX57: =SUMIF($D21:$D56,"工数",CX21:DA56) -> 0 | DB57: =SUMIF($D21:$D56,"工数",DB21:DE56) -> 0 | DF57: =SUMIF($D21:$D56,"工数",DF21:DI56) -> 0 | DJ57: =SUMIF($D21:$D56,"工数",DJ21:DM56) -> 0 | DN57: =SUMIF($D21:$D56,"工数",DN21:DQ56) -> 0 | DR57: =SUMIF($D21:$D56,"工数",DR21:DU56) -> 0 | DV57: =SUMIF($D21:$D56,"工数",DV21:DY56) -> 0 | DZ57: =SUMIF($D21:$D56,"工数",DZ21:EC56) -> 0 | ED57: =SUMIF($D21:$D56,"工数",ED21:EG56) -> 0 | EH57: =SUMIF($D21:$D56,"工数",EH21:EK56) -> 0 | EL57: =SUMIF($D21:$D56,"工数",EL21:EO56) -> 0 | EP57: =SUMIF($D21:$D56,"工数",EP21:ES56) -> 0
E58: =SUM(F58:CW58) -> 7000000 | F58: =SUMIF($D21:$D56,"売上金額",F21:I56) -> 0 | J58: =SUMIF($D21:$D56,"売上金額",J21:M56) -> 0 | N58: =SUMIF($D21:$D56,"売上金額",N21:Q56) -> 0 | R58: =SUMIF($D21:$D56,"売上金額",R21:U56) -> 0 | V58: =SUMIF($D21:$D56,"売上金額",V21:Y56) -> 0 | Z58: =SUMIF($D21:$D56,"売上金額",Z21:AC56) -> 0 | AD58: =SUMIF($D21:$D56,"売上金額",AD21:AG56) -> 0 | AH58: =SUMIF($D21:$D56,"売上金額",AH21:AK56) -> 0 | AL58: =SUMIF($D21:$D56,"売上金額",AL21:AO56) -> 0 | AP58: =SUMIF($D21:$D56,"売上金額",AP21:AS56) -> 0 | AT58: =SUMIF($D21:$D56,"売上金額",AT21:AW56) -> 0 | AX58: =SUMIF($D21:$D56,"売上金額",AX21:BA56) -> 0 | BB58: =SUMIF($D21:$D56,"売上金額",BB21:BE56) -> 0 | BF58: =SUMIF($D21:$D56,"売上金額",BF21:BI56) -> 0 | BJ58: =SUMIF($D21:$D56,"売上金額",BJ21:BM56) -> 0 | BN58: =SUMIF($D21:$D56,"売上金額",BN21:BQ56) -> 0 | BR58: =SUMIF($D21:$D56,"売上金額",BR21:BU56) -> 0 | BV58: =SUMIF($D21:$D56,"売上金額",BV21:BY56) -> 700000 | BZ58: =SUMIF($D21:$D56,"売上金額",BZ21:CC56) -> 2800000 | CD58: =SUMIF($D21:$D56,"売上金額",CD21:CG56) -> 2800000 | CH58: =SUMIF($D21:$D56,"売上金額",CH21:CK56) -> 700000 | CL58: =SUMIF($D21:$D56,"売上金額",CL21:CO56) -> 0 | CP58: =SUMIF($D21:$D56,"売上金額",CP21:CS56) -> 0 | CT58: =SUMIF($D21:$D56,"売上金額",CT21:CW56) -> 0 | CX58: =SUMIF($D21:$D56,"売上金額",CX21:DA56) -> 0 | DB58: =SUMIF($D21:$D56,"売上金額",DB21:DE56) -> 0 | DF58: =SUMIF($D21:$D56,"売上金額",DF21:DI56) -> 0 | DJ58: =SUMIF($D21:$D56,"売上金額",DJ21:DM56) -> 0 | DN58: =SUMIF($D21:$D56,"売上金額",DN21:DQ56) -> 0 | DR58: =SUMIF($D21:$D56,"売上金額",DR21:DU56) -> 0 | DV58: =SUMIF($D21:$D56,"売上金額",DV21:DY56) -> 0 | DZ58: =SUMIF($D21:$D56,"売上金額",DZ21:EC56) -> 0 | ED58: =SUMIF($D21:$D56,"売上金額",ED21:EG56) -> 0 | EH58: =SUMIF($D21:$D56,"売上金額",EH21:EK56) -> 0 | EL58: =SUMIF($D21:$D56,"売上金額",EL21:EO56) -> 0 | EP58: =SUMIF($D21:$D56,"売上金額",EP21:ES56) -> 0
E59: =SUM(F59:CW59) -> 3200000 | F59: =SUMIF($D21:$D56,"原価金額",F21:I56) -> 0 | J59: =SUMIF($D21:$D56,"原価金額",J21:M56) -> 0 | N59: =SUMIF($D21:$D56,"原価金額",N21:Q56) -> 0 | R59: =SUMIF($D21:$D56,"原価金額",R21:U56) -> 0 | V59: =SUMIF($D21:$D56,"原価金額",V21:Y56) -> 0 | Z59: =SUMIF($D21:$D56,"原価金額",Z21:AC56) -> 0 | AD59: =SUMIF($D21:$D56,"原価金額",AD21:AG56) -> 0 | AH59: =SUMIF($D21:$D56,"原価金額",AH21:AK56) -> 0 | AL59: =SUMIF($D21:$D56,"原価金額",AL21:AO56) -> 0 | AP59: =SUMIF($D21:$D56,"原価金額",AP21:AS56) -> 0 | AT59: =SUMIF($D21:$D56,"原価金額",AT21:AW56) -> 0 | AX59: =SUMIF($D21:$D56,"原価金額",AX21:BA56) -> 0 | BB59: =SUMIF($D21:$D56,"原価金額",BB21:BE56) -> 0 | BF59: =SUMIF($D21:$D56,"原価金額",BF21:BI56) -> 0 | BJ59: =SUMIF($D21:$D56,"原価金額",BJ21:BM56) -> 0 | BN59: =SUMIF($D21:$D56,"原価金額",BN21:BQ56) -> 0 | BR59: =SUMIF($D21:$D56,"原価金額",BR21:BU56) -> 0 | BV59: =SUMIF($D21:$D56,"原価金額",BV21:BY56) -> 300000 | BZ59: =SUMIF($D21:$D56,"原価金額",BZ21:CC56) -> 1300000 | CD59: =SUMIF($D21:$D56,"原価金額",CD21:CG56) -> 1300000 | CH59: =SUMIF($D21:$D56,"原価金額",CH21:CK56) -> 300000 | CL59: =SUMIF($D21:$D56,"原価金額",CL21:CO56) -> 0 | CP59: =SUMIF($D21:$D56,"原価金額",CP21:CS56) -> 0 | CT59: =SUMIF($D21:$D56,"原価金額",CT21:CW56) -> 0 | CX59: =SUMIF($D21:$D56,"原価金額",CX21:DA56) -> 0 | DB59: =SUMIF($D21:$D56,"原価金額",DB21:DE56) -> 0 | DF59: =SUMIF($D21:$D56,"原価金額",DF21:DI56) -> 0 | DJ59: =SUMIF($D21:$D56,"原価金額",DJ21:DM56) -> 0 | DN59: =SUMIF($D21:$D56,"原価金額",DN21:DQ56) -> 0 | DR59: =SUMIF($D21:$D56,"原価金額",DR21:DU56) -> 0 | DV59: =SUMIF($D21:$D56,"原価金額",DV21:DY56) -> 0 | DZ59: =SUMIF($D21:$D56,"原価金額",DZ21:EC56) -> 0 | ED59: =SUMIF($D21:$D56,"原価金額",ED21:EG56) -> 0 | EH59: =SUMIF($D21:$D56,"原価金額",EH21:EK56) -> 0 | EL59: =SUMIF($D21:$D56,"原価金額",EL21:EO56) -> 0 | EP59: =SUMIF($D21:$D56,"原価金額",EP21:ES56) -> 0
A61: 【BP】 | C61: ※必要に応じて修正すること。
B62: 要員名 | C62: 月額単価 | D62: 内訳 | E62: 合計 | F62: 2026年 | BB62: 2027年 | CX62: 2028年
F63: 1Q | R63: 2Q | AD63: 3Q | AP63: 4Q | BB63: 1Q | BN63: 2Q | BZ63: 3Q | CL63: 4Q | CX63: 1Q | DJ63: 2Q | DV63: 3Q | EH63: 4Q
C64: (上段:売上、下段:原価) | F64: 45017 | J64: 45047 | N64: 45078 | R64: 45108 | V64: 45139 | Z64: 45170 | AD64: 45200 | AH64: 45231 | AL64: 45261 | AP64: 45292 | AT64: 45323 | AX64: 45352 | BB64: 45383 | BF64: 45413 | BJ64: 45444 | BN64: 45474 | BR64: 45505 | BV64: 45536 | BZ64: 45566 | CD64: 45597 | CH64: 45627 | CL64: 45658 | CP64: 45689 | CT64: 45717 | CX64: 45383 | DB64: 45413 | DF64: 45444 | DJ64: 45474 | DN64: 45505 | DR64: 45536 | DV64: 45566 | DZ64: 45597 | ED64: 45627 | EH64: 45658 | EL64: 45689 | EP64: 45717
B65: 五石 | D65: 工数 | E65: =SUM(F65:ES65) -> 2 | BV65: 0.5 | BZ65: 0.5 | CD65: 0.5 | CH65: 0.5 | DR65: =IF(ISERROR(VLOOKUP(RIGHT(CELL("filename",$A$1),LEN(CELL("filename",$A$1))-FIND("]",CELL("filename",$A$1)))&$B65,[2]要員計画!$L:$AJ,((COLUMN()-1)/4)+1,FALSE)),0,VLOOKUP(RIGHT(CELL("filename",$A$1),LEN(CELL("filename",$A$1))-FIND("]",CELL("filename",$A$1)))&$B65,[2]要員計画!$L:$AJ,((COLUMN()-1)/4)+1,FALSE)) -> 0 | DV65: =IF(ISERROR(VLOOKUP(RIGHT(CELL("filename",$A$1),LEN(CELL("filename",$A$1))-FIND("]",CELL("filename",$A$1)))&$B65,[2]要員計画!$L:$AJ,((COLUMN()-1)/4)+1,FALSE)),0,VLOOKUP(RIGHT(CELL("filename",$A$1),LEN(CELL("filename",$A$1))-FIND("]",CELL("filename",$A$1)))&$B65,[2]要員計画!$L:$AJ,((COLUMN()-1)/4)+1,FALSE)) -> 0 | DZ65: =IF(ISERROR(VLOOKUP(RIGHT(CELL("filename",$A$1),LEN(CELL("filename",$A$1))-FIND("]",CELL("filename",$A$1)))&$B65,[2]要員計画!$L:$AJ,((COLUMN()-1)/4)+1,FALSE)),0,VLOOKUP(RIGHT(CELL("filename",$A$1),LEN(CELL("filename",$A$1))-FIND("]",CELL("filename",$A$1)))&$B65,[2]要員計画!$L:$AJ,((COLUMN()-1)/4)+1,FALSE)) -> 0 | ED65: =IF(ISERROR(VLOOKUP(RIGHT(CELL("filename",$A$1),LEN(CELL("filename",$A$1))-FIND("]",CELL("filename",$A$1)))&$B65,[2]要員計画!$L:$AJ,((COLUMN()-1)/4)+1,FALSE)),0,VLOOKUP(RIGHT(CELL("filename",$A$1),LEN(CELL("filename",$A$1))-FIND("]",CELL("filename",$A$1)))&$B65,[2]要員計画!$L:$AJ,((COLUMN()-1)/4)+1,FALSE)) -> 0 | EH65: =IF(ISERROR(VLOOKUP(RIGHT(CELL("filename",$A$1),LEN(CELL("filename",$A$1))-FIND("]",CELL("filename",$A$1)))&$B65,[2]要員計画!$L:$AJ,((COLUMN()-1)/4)+1,FALSE)),0,VLOOKUP(RIGHT(CELL("filename",$A$1),LEN(CELL("filename",$A$1))-FIND("]",CELL("filename",$A$1)))&$B65,[2]要員計画!$L:$AJ,((COLUMN()-1)/4)+1,FALSE)) -> 0 | EL65: =IF(ISERROR(VLOOKUP(RIGHT(CELL("filename",$A$1),LEN(CELL("filename",$A$1))-FIND("]",CELL("filename",$A$1)))&$B65,[2]要員計画!$L:$AJ,((COLUMN()-1)/4)+1,FALSE)),0,VLOOKUP(RIGHT(CELL("filename",$A$1),LEN(CELL("filename",$A$1))-FIND("]",CELL("filename",$A$1)))&$B65,[2]要員計画!$L:$AJ,((COLUMN()-1)/4)+1,FALSE)) -> 0 | EP65: =IF(ISERROR(VLOOKUP(RIGHT(CELL("filename",$A$1),LEN(CELL("filename",$A$1))-FIND("]",CELL("filename",$A$1)))&$B65,[2]要員計画!$L:$AJ,((COLUMN()-1)/4)+1,FALSE)),0,VLOOKUP(RIGHT(CELL("filename",$A$1),LEN(CELL("filename",$A$1))-FIND("]",CELL("filename",$A$1)))&$B65,[2]要員計画!$L:$AJ,((COLUMN()-1)/4)+1,FALSE)) -> 0
C66: 1050000 | D66: 売上金額 | E66: =SUM(F66:CW66) -> 2100000 | F66: =IFERROR($C66*F65,"") -> 0 | J66: =IFERROR($C66*J65,"") -> 0 | N66: =IFERROR($C66*N65,"") -> 0 | R66: =IFERROR($C66*R65,"") -> 0 | V66: =IFERROR($C66*V65,"") -> 0 | Z66: =IFERROR($C66*Z65,"") -> 0 | AD66: =IFERROR($C66*AD65,"") -> 0 | AH66: =IFERROR($C66*AH65,"") -> 0 | AL66: =IFERROR($C66*AL65,"") -> 0 | AP66: =IFERROR($C66*AP65,"") -> 0 | AT66: =IFERROR($C66*AT65,"") -> 0 | AX66: =IFERROR($C66*AX65,"") -> 0 | BB66: =IFERROR($C66*BB65,"") -> 0 | BF66: =IFERROR($C66*BF65,"") -> 0 | BJ66: =IFERROR($C66*BJ65,"") -> 0 | BN66: =IFERROR($C66*BN65,"") -> 0 | BR66: =IFERROR($C66*BR65,"") -> 0 | BV66: =IFERROR($C66*BV65,"") -> 525000 | BZ66: =IFERROR($C66*BZ65,"") -> 525000 | CD66: =IFERROR($C66*CD65,"") -> 525000 | CH66: =IFERROR($C66*CH65,"") -> 525000 | CL66: =IFERROR($C66*CL65,"") -> 0 | CP66: =IFERROR($C66*CP65,"") -> 0 | CT66: =IFERROR($C66*CT65,"") -> 0 | CX66: =IFERROR($C66*CX65,"") -> 0 | DB66: =IFERROR($C66*DB65,"") -> 0 | DF66: =IFERROR($C66*DF65,"") -> 0 | DJ66: =IFERROR($C66*DJ65,"") -> 0 | DN66: =IFERROR($C66*DN65,"") -> 0 | DR66: =IFERROR($C66*DR65,"") -> 0 | DV66: =IFERROR($C66*DV65,"") -> 0 | DZ66: =IFERROR($C66*DZ65,"") -> 0 | ED66: =IFERROR($C66*ED65,"") -> 0 | EH66: =IFERROR($C66*EH65,"") -> 0 | EL66: =IFERROR($C66*EL65,"") -> 0 | EP66: =IFERROR($C66*EP65,"") -> 0
C67: 760000 | D67: 原価金額 | E67: =SUM(F67:CW67) -> 1520000 | F67: =IFERROR($C67*F65,"") -> 0 | J67: =IFERROR($C67*J65,"") -> 0 | N67: =IFERROR($C67*N65,"") -> 0 | R67: =IFERROR($C67*R65,"") -> 0 | V67: =IFERROR($C67*V65,"") -> 0 | Z67: =IFERROR($C67*Z65,"") -> 0 | AD67: =IFERROR($C67*AD65,"") -> 0 | AH67: =IFERROR($C67*AH65,"") -> 0 | AL67: =IFERROR($C67*AL65,"") -> 0 | AP67: =IFERROR($C67*AP65,"") -> 0 | AT67: =IFERROR($C67*AT65,"") -> 0 | AX67: =IFERROR($C67*AX65,"") -> 0 | BB67: =IFERROR($C67*BB65,"") -> 0 | BF67: =IFERROR($C67*BF65,"") -> 0 | BJ67: =IFERROR($C67*BJ65,"") -> 0 | BN67: =IFERROR($C67*BN65,"") -> 0 | BR67: =IFERROR($C67*BR65,"") -> 0 | BV67: =IFERROR($C67*BV65,"") -> 380000 | BZ67: =IFERROR($C67*BZ65,"") -> 380000 | CD67: =IFERROR($C67*CD65,"") -> 380000 | CH67: =IFERROR($C67*CH65,"") -> 380000 | CL67: =IFERROR($C67*CL65,"") -> 0 | CP67: =IFERROR($C67*CP65,"") -> 0 | CT67: =IFERROR($C67*CT65,"") -> 0 | CX67: =IFERROR($C67*CX65,"") -> 0 | DB67: =IFERROR($C67*DB65,"") -> 0 | DF67: =IFERROR($C67*DF65,"") -> 0 | DJ67: =IFERROR($C67*DJ65,"") -> 0 | DN67: =IFERROR($C67*DN65,"") -> 0 | DR67: =IFERROR($C67*DR65,"") -> 0 | DV67: =IFERROR($C67*DV65,"") -> 0 | DZ67: =IFERROR($C67*DZ65,"") -> 0 | ED67: =IFERROR($C67*ED65,"") -> 0 | EH67: =IFERROR($C67*EH65,"") -> 0 | EL67: =IFERROR($C67*EL65,"") -> 0 | EP67: =IFERROR($C67*EP65,"") -> 0
B68: 砂金 | D68: 工数 | E68: =SUM(F68:ES68) -> 1 | BV68: 0.25 | BZ68: 0.25 | CD68: 0.25 | CH68: 0.25 | DR68: =IF(ISERROR(VLOOKUP(RIGHT(CELL("filename",$A$1),LEN(CELL("filename",$A$1))-FIND("]",CELL("filename",$A$1)))&$B68,[2]要員計画!$L:$AJ,((COLUMN()-1)/4)+1,FALSE)),0,VLOOKUP(RIGHT(CELL("filename",$A$1),LEN(CELL("filename",$A$1))-FIND("]",CELL("filename",$A$1)))&$B68,[2]要員計画!$L:$AJ,((COLUMN()-1)/4)+1,FALSE)) -> 0 | DV68: =IF(ISERROR(VLOOKUP(RIGHT(CELL("filename",$A$1),LEN(CELL("filename",$A$1))-FIND("]",CELL("filename",$A$1)))&$B68,[2]要員計画!$L:$AJ,((COLUMN()-1)/4)+1,FALSE)),0,VLOOKUP(RIGHT(CELL("filename",$A$1),LEN(CELL("filename",$A$1))-FIND("]",CELL("filename",$A$1)))&$B68,[2]要員計画!$L:$AJ,((COLUMN()-1)/4)+1,FALSE)) -> 0 | DZ68: =IF(ISERROR(VLOOKUP(RIGHT(CELL("filename",$A$1),LEN(CELL("filename",$A$1))-FIND("]",CELL("filename",$A$1)))&$B68,[2]要員計画!$L:$AJ,((COLUMN()-1)/4)+1,FALSE)),0,VLOOKUP(RIGHT(CELL("filename",$A$1),LEN(CELL("filename",$A$1))-FIND("]",CELL("filename",$A$1)))&$B68,[2]要員計画!$L:$AJ,((COLUMN()-1)/4)+1,FALSE)) -> 0 | ED68: =IF(ISERROR(VLOOKUP(RIGHT(CELL("filename",$A$1),LEN(CELL("filename",$A$1))-FIND("]",CELL("filename",$A$1)))&$B68,[2]要員計画!$L:$AJ,((COLUMN()-1)/4)+1,FALSE)),0,VLOOKUP(RIGHT(CELL("filename",$A$1),LEN(CELL("filename",$A$1))-FIND("]",CELL("filename",$A$1)))&$B68,[2]要員計画!$L:$AJ,((COLUMN()-1)/4)+1,FALSE)) -> 0 | EH68: =IF(ISERROR(VLOOKUP(RIGHT(CELL("filename",$A$1),LEN(CELL("filename",$A$1))-FIND("]",CELL("filename",$A$1)))&$B68,[2]要員計画!$L:$AJ,((COLUMN()-1)/4)+1,FALSE)),0,VLOOKUP(RIGHT(CELL("filename",$A$1),LEN(CELL("filename",$A$1))-FIND("]",CELL("filename",$A$1)))&$B68,[2]要員計画!$L:$AJ,((COLUMN()-1)/4)+1,FALSE)) -> 0 | EL68: =IF(ISERROR(VLOOKUP(RIGHT(CELL("filename",$A$1),LEN(CELL("filename",$A$1))-FIND("]",CELL("filename",$A$1)))&$B68,[2]要員計画!$L:$AJ,((COLUMN()-1)/4)+1,FALSE)),0,VLOOKUP(RIGHT(CELL("filename",$A$1),LEN(CELL("filename",$A$1))-FIND("]",CELL("filename",$A$1)))&$B68,[2]要員計画!$L:$AJ,((COLUMN()-1)/4)+1,FALSE)) -> 0 | EP68: =IF(ISERROR(VLOOKUP(RIGHT(CELL("filename",$A$1),LEN(CELL("filename",$A$1))-FIND("]",CELL("filename",$A$1)))&$B68,[2]要員計画!$L:$AJ,((COLUMN()-1)/4)+1,FALSE)),0,VLOOKUP(RIGHT(CELL("filename",$A$1),LEN(CELL("filename",$A$1))-FIND("]",CELL("filename",$A$1)))&$B68,[2]要員計画!$L:$AJ,((COLUMN()-1)/4)+1,FALSE)) -> 0
C69: 1050000 | D69: 売上金額 | E69: =SUM(F69:CW69) -> 1050000 | F69: =IFERROR($C69*F68,"") -> 0 | J69: =IFERROR($C69*J68,"") -> 0 | N69: =IFERROR($C69*N68,"") -> 0 | R69: =IFERROR($C69*R68,"") -> 0 | V69: =IFERROR($C69*V68,"") -> 0 | Z69: =IFERROR($C69*Z68,"") -> 0 | AD69: =IFERROR($C69*AD68,"") -> 0 | AH69: =IFERROR($C69*AH68,"") -> 0 | AL69: =IFERROR($C69*AL68,"") -> 0 | AP69: =IFERROR($C69*AP68,"") -> 0 | AT69: =IFERROR($C69*AT68,"") -> 0 | AX69: =IFERROR($C69*AX68,"") -> 0 | BB69: =IFERROR($C69*BB68,"") -> 0 | BF69: =IFERROR($C69*BF68,"") -> 0 | BJ69: =IFERROR($C69*BJ68,"") -> 0 | BN69: =IFERROR($C69*BN68,"") -> 0 | BR69: =IFERROR($C69*BR68,"") -> 0 | BV69: =IFERROR($C69*BV68,"") -> 262500 | BZ69: =IFERROR($C69*BZ68,"") -> 262500 | CD69: =IFERROR($C69*CD68,"") -> 262500 | CH69: =IFERROR($C69*CH68,"") -> 262500 | CL69: =IFERROR($C69*CL68,"") -> 0 | CP69: =IFERROR($C69*CP68,"") -> 0 | CT69: =IFERROR($C69*CT68,"") -> 0 | CX69: =IFERROR($C69*CX68,"") -> 0 | DB69: =IFERROR($C69*DB68,"") -> 0 | DF69: =IFERROR($C69*DF68,"") -> 0 | DJ69: =IFERROR($C69*DJ68,"") -> 0 | DN69: =IFERROR($C69*DN68,"") -> 0 | DR69: =IFERROR($C69*DR68,"") -> 0 | DV69: =IFERROR($C69*DV68,"") -> 0 | DZ69: =IFERROR($C69*DZ68,"") -> 0 | ED69: =IFERROR($C69*ED68,"") -> 0 | EH69: =IFERROR($C69*EH68,"") -> 0 | EL69: =IFERROR($C69*EL68,"") -> 0 | EP69: =IFERROR($C69*EP68,"") -> 0
C70: 500000 | D70: 原価金額 | E70: =SUM(F70:CW70) -> 500000 | F70: =IFERROR($C70*F68,"") -> 0 | J70: =IFERROR($C70*J68,"") -> 0 | N70: =IFERROR($C70*N68,"") -> 0 | R70: =IFERROR($C70*R68,"") -> 0 | V70: =IFERROR($C70*V68,"") -> 0 | Z70: =IFERROR($C70*Z68,"") -> 0 | AD70: =IFERROR($C70*AD68,"") -> 0 | AH70: =IFERROR($C70*AH68,"") -> 0 | AL70: =IFERROR($C70*AL68,"") -> 0 | AP70: =IFERROR($C70*AP68,"") -> 0 | AT70: =IFERROR($C70*AT68,"") -> 0 | AX70: =IFERROR($C70*AX68,"") -> 0 | BB70: =IFERROR($C70*BB68,"") -> 0 | BF70: =IFERROR($C70*BF68,"") -> 0 | BJ70: =IFERROR($C70*BJ68,"") -> 0 | BN70: =IFERROR($C70*BN68,"") -> 0 | BR70: =IFERROR($C70*BR68,"") -> 0 | BV70: =IFERROR($C70*BV68,"") -> 125000 | BZ70: =IFERROR($C70*BZ68,"") -> 125000 | CD70: =IFERROR($C70*CD68,"") -> 125000 | CH70: =IFERROR($C70*CH68,"") -> 125000 | CL70: =IFERROR($C70*CL68,"") -> 0 | CP70: =IFERROR($C70*CP68,"") -> 0 | CT70: =IFERROR($C70*CT68,"") -> 0 | CX70: =IFERROR($C70*CX68,"") -> 0 | DB70: =IFERROR($C70*DB68,"") -> 0 | DF70: =IFERROR($C70*DF68,"") -> 0 | DJ70: =IFERROR($C70*DJ68,"") -> 0 | DN70: =IFERROR($C70*DN68,"") -> 0 | DR70: =IFERROR($C70*DR68,"") -> 0 | DV70: =IFERROR($C70*DV68,"") -> 0 | DZ70: =IFERROR($C70*DZ68,"") -> 0 | ED70: =IFERROR($C70*ED68,"") -> 0 | EH70: =IFERROR($C70*EH68,"") -> 0 | EL70: =IFERROR($C70*EL68,"") -> 0 | EP70: =IFERROR($C70*EP68,"") -> 0
B71: 1：PL（オフショア） | D71: 工数 | E71: =SUM(F71:ES71) -> 0 | F71: =IF(ISERROR(VLOOKUP(RIGHT(CELL("filename",$A$1),LEN(CELL("filename",$A$1))-FIND("]",CELL("filename",$A$1)))&$B71,[2]要員計画!$L:$AJ,((COLUMN()-1)/4)+1,FALSE)),0,VLOOKUP(RIGHT(CELL("filename",$A$1),LEN(CELL("filename",$A$1))-FIND("]",CELL("filename",$A$1)))&$B71,[2]要員計画!$L:$AJ,((COLUMN()-1)/4)+1,FALSE)) -> 0 | J71: =IF(ISERROR(VLOOKUP(RIGHT(CELL("filename",$A$1),LEN(CELL("filename",$A$1))-FIND("]",CELL("filename",$A$1)))&$B71,[2]要員計画!$L:$AJ,((COLUMN()-1)/4)+1,FALSE)),0,VLOOKUP(RIGHT(CELL("filename",$A$1),LEN(CELL("filename",$A$1))-FIND("]",CELL("filename",$A$1)))&$B71,[2]要員計画!$L:$AJ,((COLUMN()-1)/4)+1,FALSE)) -> 0 | N71: =IF(ISERROR(VLOOKUP(RIGHT(CELL("filename",$A$1),LEN(CELL("filename",$A$1))-FIND("]",CELL("filename",$A$1)))&$B71,[2]要員計画!$L:$AJ,((COLUMN()-1)/4)+1,FALSE)),0,VLOOKUP(RIGHT(CELL("filename",$A$1),LEN(CELL("filename",$A$1))-FIND("]",CELL("filename",$A$1)))&$B71,[2]要員計画!$L:$AJ,((COLUMN()-1)/4)+1,FALSE)) -> 0 | R71: =IF(ISERROR(VLOOKUP(RIGHT(CELL("filename",$A$1),LEN(CELL("filename",$A$1))-FIND("]",CELL("filename",$A$1)))&$B71,[2]要員計画!$L:$AJ,((COLUMN()-1)/4)+1,FALSE)),0,VLOOKUP(RIGHT(CELL("filename",$A$1),LEN(CELL("filename",$A$1))-FIND("]",CELL("filename",$A$1)))&$B71,[2]要員計画!$L:$AJ,((COLUMN()-1)/4)+1,FALSE)) -> 0 | DR71: =IF(ISERROR(VLOOKUP(RIGHT(CELL("filename",$A$1),LEN(CELL("filename",$A$1))-FIND("]",CELL("filename",$A$1)))&$B71,[2]要員計画!$L:$AJ,((COLUMN()-1)/4)+1,FALSE)),0,VLOOKUP(RIGHT(CELL("filename",$A$1),LEN(CELL("filename",$A$1))-FIND("]",CELL("filename",$A$1)))&$B71,[2]要員計画!$L:$AJ,((COLUMN()-1)/4)+1,FALSE)) -> 0 | DV71: =IF(ISERROR(VLOOKUP(RIGHT(CELL("filename",$A$1),LEN(CELL("filename",$A$1))-FIND("]",CELL("filename",$A$1)))&$B71,[2]要員計画!$L:$AJ,((COLUMN()-1)/4)+1,FALSE)),0,VLOOKUP(RIGHT(CELL("filename",$A$1),LEN(CELL("filename",$A$1))-FIND("]",CELL("filename",$A$1)))&$B71,[2]要員計画!$L:$AJ,((COLUMN()-1)/4)+1,FALSE)) -> 0 | DZ71: =IF(ISERROR(VLOOKUP(RIGHT(CELL("filename",$A$1),LEN(CELL("filename",$A$1))-FIND("]",CELL("filename",$A$1)))&$B71,[2]要員計画!$L:$AJ,((COLUMN()-1)/4)+1,FALSE)),0,VLOOKUP(RIGHT(CELL("filename",$A$1),LEN(CELL("filename",$A$1))-FIND("]",CELL("filename",$A$1)))&$B71,[2]要員計画!$L:$AJ,((COLUMN()-1)/4)+1,FALSE)) -> 0 | ED71: =IF(ISERROR(VLOOKUP(RIGHT(CELL("filename",$A$1),LEN(CELL("filename",$A$1))-FIND("]",CELL("filename",$A$1)))&$B71,[2]要員計画!$L:$AJ,((COLUMN()-1)/4)+1,FALSE)),0,VLOOKUP(RIGHT(CELL("filename",$A$1),LEN(CELL("filename",$A$1))-FIND("]",CELL("filename",$A$1)))&$B71,[2]要員計画!$L:$AJ,((COLUMN()-1)/4)+1,FALSE)) -> 0 | EH71: =IF(ISERROR(VLOOKUP(RIGHT(CELL("filename",$A$1),LEN(CELL("filename",$A$1))-FIND("]",CELL("filename",$A$1)))&$B71,[2]要員計画!$L:$AJ,((COLUMN()-1)/4)+1,FALSE)),0,VLOOKUP(RIGHT(CELL("filename",$A$1),LEN(CELL("filename",$A$1))-FIND("]",CELL("filename",$A$1)))&$B71,[2]要員計画!$L:$AJ,((COLUMN()-1)/4)+1,FALSE)) -> 0 | EL71: =IF(ISERROR(VLOOKUP(RIGHT(CELL("filename",$A$1),LEN(CELL("filename",$A$1))-FIND("]",CELL("filename",$A$1)))&$B71,[2]要員計画!$L:$AJ,((COLUMN()-1)/4)+1,FALSE)),0,VLOOKUP(RIGHT(CELL("filename",$A$1),LEN(CELL("filename",$A$1))-FIND("]",CELL("filename",$A$1)))&$B71,[2]要員計画!$L:$AJ,((COLUMN()-1)/4)+1,FALSE)) -> 0 | EP71: =IF(ISERROR(VLOOKUP(RIGHT(CELL("filename",$A$1),LEN(CELL("filename",$A$1))-FIND("]",CELL("filename",$A$1)))&$B71,[2]要員計画!$L:$AJ,((COLUMN()-1)/4)+1,FALSE)),0,VLOOKUP(RIGHT(CELL("filename",$A$1),LEN(CELL("filename",$A$1))-FIND("]",CELL("filename",$A$1)))&$B71,[2]要員計画!$L:$AJ,((COLUMN()-1)/4)+1,FALSE)) -> 0
C72: 800000 | D72: 売上金額 | E72: =SUM(F72:CW72) -> 0 | F72: =IFERROR($C72*F71,"") -> 0 | J72: =IFERROR($C72*J71,"") -> 0 | N72: =IFERROR($C72*N71,"") -> 0 | R72: =IFERROR($C72*R71,"") -> 0 | V72: =IFERROR($C72*V71,"") -> 0 | Z72: =IFERROR($C72*Z71,"") -> 0 | AD72: =IFERROR($C72*AD71,"") -> 0 | AH72: =IFERROR($C72*AH71,"") -> 0 | AL72: =IFERROR($C72*AL71,"") -> 0 | AP72: =IFERROR($C72*AP71,"") -> 0 | AT72: =IFERROR($C72*AT71,"") -> 0 | AX72: =IFERROR($C72*AX71,"") -> 0 | BB72: =IFERROR($C72*BB71,"") -> 0 | BF72: =IFERROR($C72*BF71,"") -> 0 | BJ72: =IFERROR($C72*BJ71,"") -> 0 | BN72: =IFERROR($C72*BN71,"") -> 0 | BR72: =IFERROR($C72*BR71,"") -> 0 | BV72: =IFERROR($C72*BV71,"") -> 0 | BZ72: =IFERROR($C72*BZ71,"") -> 0 | CD72: =IFERROR($C72*CD71,"") -> 0 | CH72: =IFERROR($C72*CH71,"") -> 0 | CL72: =IFERROR($C72*CL71,"") -> 0 | CP72: =IFERROR($C72*CP71,"") -> 0 | CT72: =IFERROR($C72*CT71,"") -> 0 | CX72: =IFERROR($C72*CX71,"") -> 0 | DB72: =IFERROR($C72*DB71,"") -> 0 | DF72: =IFERROR($C72*DF71,"") -> 0 | DJ72: =IFERROR($C72*DJ71,"") -> 0 | DN72: =IFERROR($C72*DN71,"") -> 0 | DR72: =IFERROR($C72*DR71,"") -> 0 | DV72: =IFERROR($C72*DV71,"") -> 0 | DZ72: =IFERROR($C72*DZ71,"") -> 0 | ED72: =IFERROR($C72*ED71,"") -> 0 | EH72: =IFERROR($C72*EH71,"") -> 0 | EL72: =IFERROR($C72*EL71,"") -> 0 | EP72: =IFERROR($C72*EP71,"") -> 0
C73: 500000 | D73: 原価金額 | E73: =SUM(F73:CW73) -> 0 | F73: =IFERROR($C73*F71,"") -> 0 | J73: =IFERROR($C73*J71,"") -> 0 | N73: =IFERROR($C73*N71,"") -> 0 | R73: =IFERROR($C73*R71,"") -> 0 | V73: =IFERROR($C73*V71,"") -> 0 | Z73: =IFERROR($C73*Z71,"") -> 0 | AD73: =IFERROR($C73*AD71,"") -> 0 | AH73: =IFERROR($C73*AH71,"") -> 0 | AL73: =IFERROR($C73*AL71,"") -> 0 | AP73: =IFERROR($C73*AP71,"") -> 0 | AT73: =IFERROR($C73*AT71,"") -> 0 | AX73: =IFERROR($C73*AX71,"") -> 0 | BB73: =IFERROR($C73*BB71,"") -> 0 | BF73: =IFERROR($C73*BF71,"") -> 0 | BJ73: =IFERROR($C73*BJ71,"") -> 0 | BN73: =IFERROR($C73*BN71,"") -> 0 | BR73: =IFERROR($C73*BR71,"") -> 0 | BV73: =IFERROR($C73*BV71,"") -> 0 | BZ73: =IFERROR($C73*BZ71,"") -> 0 | CD73: =IFERROR($C73*CD71,"") -> 0 | CH73: =IFERROR($C73*CH71,"") -> 0 | CL73: =IFERROR($C73*CL71,"") -> 0 | CP73: =IFERROR($C73*CP71,"") -> 0 | CT73: =IFERROR($C73*CT71,"") -> 0 | CX73: =IFERROR($C73*CX71,"") -> 0 | DB73: =IFERROR($C73*DB71,"") -> 0 | DF73: =IFERROR($C73*DF71,"") -> 0 | DJ73: =IFERROR($C73*DJ71,"") -> 0 | DN73: =IFERROR($C73*DN71,"") -> 0 | DR73: =IFERROR($C73*DR71,"") -> 0 | DV73: =IFERROR($C73*DV71,"") -> 0 | DZ73: =IFERROR($C73*DZ71,"") -> 0 | ED73: =IFERROR($C73*ED71,"") -> 0 | EH73: =IFERROR($C73*EH71,"") -> 0 | EL73: =IFERROR($C73*EL71,"") -> 0 | EP73: =IFERROR($C73*EP71,"") -> 0
B74: 2：コミュニケータ（オフショア） | D74: 工数 | E74: =SUM(F74:ES74) -> 0 | F74: =IF(ISERROR(VLOOKUP(RIGHT(CELL("filename",$A$1),LEN(CELL("filename",$A$1))-FIND("]",CELL("filename",$A$1)))&$B74,[2]要員計画!$L:$AJ,((COLUMN()-1)/4)+1,FALSE)),0,VLOOKUP(RIGHT(CELL("filename",$A$1),LEN(CELL("filename",$A$1))-FIND("]",CELL("filename",$A$1)))&$B74,[2]要員計画!$L:$AJ,((COLUMN()-1)/4)+1,FALSE)) -> 0 | J74: =IF(ISERROR(VLOOKUP(RIGHT(CELL("filename",$A$1),LEN(CELL("filename",$A$1))-FIND("]",CELL("filename",$A$1)))&$B74,[2]要員計画!$L:$AJ,((COLUMN()-1)/4)+1,FALSE)),0,VLOOKUP(RIGHT(CELL("filename",$A$1),LEN(CELL("filename",$A$1))-FIND("]",CELL("filename",$A$1)))&$B74,[2]要員計画!$L:$AJ,((COLUMN()-1)/4)+1,FALSE)) -> 0 | N74: =IF(ISERROR(VLOOKUP(RIGHT(CELL("filename",$A$1),LEN(CELL("filename",$A$1))-FIND("]",CELL("filename",$A$1)))&$B74,[2]要員計画!$L:$AJ,((COLUMN()-1)/4)+1,FALSE)),0,VLOOKUP(RIGHT(CELL("filename",$A$1),LEN(CELL("filename",$A$1))-FIND("]",CELL("filename",$A$1)))&$B74,[2]要員計画!$L:$AJ,((COLUMN()-1)/4)+1,FALSE)) -> 0 | R74: =IF(ISERROR(VLOOKUP(RIGHT(CELL("filename",$A$1),LEN(CELL("filename",$A$1))-FIND("]",CELL("filename",$A$1)))&$B74,[2]要員計画!$L:$AJ,((COLUMN()-1)/4)+1,FALSE)),0,VLOOKUP(RIGHT(CELL("filename",$A$1),LEN(CELL("filename",$A$1))-FIND("]",CELL("filename",$A$1)))&$B74,[2]要員計画!$L:$AJ,((COLUMN()-1)/4)+1,FALSE)) -> 0 | V74: =IF(ISERROR(VLOOKUP(RIGHT(CELL("filename",$A$1),LEN(CELL("filename",$A$1))-FIND("]",CELL("filename",$A$1)))&$B74,[2]要員計画!$L:$AJ,((COLUMN()-1)/4)+1,FALSE)),0,VLOOKUP(RIGHT(CELL("filename",$A$1),LEN(CELL("filename",$A$1))-FIND("]",CELL("filename",$A$1)))&$B74,[2]要員計画!$L:$AJ,((COLUMN()-1)/4)+1,FALSE)) -> 0 | Z74: =IF(ISERROR(VLOOKUP(RIGHT(CELL("filename",$A$1),LEN(CELL("filename",$A$1))-FIND("]",CELL("filename",$A$1)))&$B74,[2]要員計画!$L:$AJ,((COLUMN()-1)/4)+1,FALSE)),0,VLOOKUP(RIGHT(CELL("filename",$A$1),LEN(CELL("filename",$A$1))-FIND("]",CELL("filename",$A$1)))&$B74,[2]要員計画!$L:$AJ,((COLUMN()-1)/4)+1,FALSE)) -> 0 | DR74: =IF(ISERROR(VLOOKUP(RIGHT(CELL("filename",$A$1),LEN(CELL("filename",$A$1))-FIND("]",CELL("filename",$A$1)))&$B74,[2]要員計画!$L:$AJ,((COLUMN()-1)/4)+1,FALSE)),0,VLOOKUP(RIGHT(CELL("filename",$A$1),LEN(CELL("filename",$A$1))-FIND("]",CELL("filename",$A$1)))&$B74,[2]要員計画!$L:$AJ,((COLUMN()-1)/4)+1,FALSE)) -> 0 | DV74: =IF(ISERROR(VLOOKUP(RIGHT(CELL("filename",$A$1),LEN(CELL("filename",$A$1))-FIND("]",CELL("filename",$A$1)))&$B74,[2]要員計画!$L:$AJ,((COLUMN()-1)/4)+1,FALSE)),0,VLOOKUP(RIGHT(CELL("filename",$A$1),LEN(CELL("filename",$A$1))-FIND("]",CELL("filename",$A$1)))&$B74,[2]要員計画!$L:$AJ,((COLUMN()-1)/4)+1,FALSE)) -> 0 | DZ74: =IF(ISERROR(VLOOKUP(RIGHT(CELL("filename",$A$1),LEN(CELL("filename",$A$1))-FIND("]",CELL("filename",$A$1)))&$B74,[2]要員計画!$L:$AJ,((COLUMN()-1)/4)+1,FALSE)),0,VLOOKUP(RIGHT(CELL("filename",$A$1),LEN(CELL("filename",$A$1))-FIND("]",CELL("filename",$A$1)))&$B74,[2]要員計画!$L:$AJ,((COLUMN()-1)/4)+1,FALSE)) -> 0 | ED74: =IF(ISERROR(VLOOKUP(RIGHT(CELL("filename",$A$1),LEN(CELL("filename",$A$1))-FIND("]",CELL("filename",$A$1)))&$B74,[2]要員計画!$L:$AJ,((COLUMN()-1)/4)+1,FALSE)),0,VLOOKUP(RIGHT(CELL("filename",$A$1),LEN(CELL("filename",$A$1))-FIND("]",CELL("filename",$A$1)))&$B74,[2]要員計画!$L:$AJ,((COLUMN()-1)/4)+1,FALSE)) -> 0 | EH74: =IF(ISERROR(VLOOKUP(RIGHT(CELL("filename",$A$1),LEN(CELL("filename",$A$1))-FIND("]",CELL("filename",$A$1)))&$B74,[2]要員計画!$L:$AJ,((COLUMN()-1)/4)+1,FALSE)),0,VLOOKUP(RIGHT(CELL("filename",$A$1),LEN(CELL("filename",$A$1))-FIND("]",CELL("filename",$A$1)))&$B74,[2]要員計画!$L:$AJ,((COLUMN()-1)/4)+1,FALSE)) -> 0 | EL74: =IF(ISERROR(VLOOKUP(RIGHT(CELL("filename",$A$1),LEN(CELL("filename",$A$1))-FIND("]",CELL("filename",$A$1)))&$B74,[2]要員計画!$L:$AJ,((COLUMN()-1)/4)+1,FALSE)),0,VLOOKUP(RIGHT(CELL("filename",$A$1),LEN(CELL("filename",$A$1))-FIND("]",CELL("filename",$A$1)))&$B74,[2]要員計画!$L:$AJ,((COLUMN()-1)/4)+1,FALSE)) -> 0 | EP74: =IF(ISERROR(VLOOKUP(RIGHT(CELL("filename",$A$1),LEN(CELL("filename",$A$1))-FIND("]",CELL("filename",$A$1)))&$B74,[2]要員計画!$L:$AJ,((COLUMN()-1)/4)+1,FALSE)),0,VLOOKUP(RIGHT(CELL("filename",$A$1),LEN(CELL("filename",$A$1))-FIND("]",CELL("filename",$A$1)))&$B74,[2]要員計画!$L:$AJ,((COLUMN()-1)/4)+1,FALSE)) -> 0
C75: 600000 | D75: 売上金額 | E75: =SUM(F75:CW75) -> 0 | F75: =IFERROR($C75*F74,"") -> 0 | J75: =IFERROR($C75*J74,"") -> 0 | N75: =IFERROR($C75*N74,"") -> 0 | R75: =IFERROR($C75*R74,"") -> 0 | V75: =IFERROR($C75*V74,"") -> 0 | Z75: =IFERROR($C75*Z74,"") -> 0 | AD75: =IFERROR($C75*AD74,"") -> 0 | AH75: =IFERROR($C75*AH74,"") -> 0 | AL75: =IFERROR($C75*AL74,"") -> 0 | AP75: =IFERROR($C75*AP74,"") -> 0 | AT75: =IFERROR($C75*AT74,"") -> 0 | AX75: =IFERROR($C75*AX74,"") -> 0 | BB75: =IFERROR($C75*BB74,"") -> 0 | BF75: =IFERROR($C75*BF74,"") -> 0 | BJ75: =IFERROR($C75*BJ74,"") -> 0 | BN75: =IFERROR($C75*BN74,"") -> 0 | BR75: =IFERROR($C75*BR74,"") -> 0 | BV75: =IFERROR($C75*BV74,"") -> 0 | BZ75: =IFERROR($C75*BZ74,"") -> 0 | CD75: =IFERROR($C75*CD74,"") -> 0 | CH75: =IFERROR($C75*CH74,"") -> 0 | CL75: =IFERROR($C75*CL74,"") -> 0 | CP75: =IFERROR($C75*CP74,"") -> 0 | CT75: =IFERROR($C75*CT74,"") -> 0 | CX75: =IFERROR($C75*CX74,"") -> 0 | DB75: =IFERROR($C75*DB74,"") -> 0 | DF75: =IFERROR($C75*DF74,"") -> 0 | DJ75: =IFERROR($C75*DJ74,"") -> 0 | DN75: =IFERROR($C75*DN74,"") -> 0 | DR75: =IFERROR($C75*DR74,"") -> 0 | DV75: =IFERROR($C75*DV74,"") -> 0 | DZ75: =IFERROR($C75*DZ74,"") -> 0 | ED75: =IFERROR($C75*ED74,"") -> 0 | EH75: =IFERROR($C75*EH74,"") -> 0 | EL75: =IFERROR($C75*EL74,"") -> 0 | EP75: =IFERROR($C75*EP74,"") -> 0
C76: 400000 | D76: 原価金額 | E76: =SUM(F76:CW76) -> 0 | F76: =IFERROR($C76*F74,"") -> 0 | J76: =IFERROR($C76*J74,"") -> 0 | N76: =IFERROR($C76*N74,"") -> 0 | R76: =IFERROR($C76*R74,"") -> 0 | V76: =IFERROR($C76*V74,"") -> 0 | Z76: =IFERROR($C76*Z74,"") -> 0 | AD76: =IFERROR($C76*AD74,"") -> 0 | AH76: =IFERROR($C76*AH74,"") -> 0 | AL76: =IFERROR($C76*AL74,"") -> 0 | AP76: =IFERROR($C76*AP74,"") -> 0 | AT76: =IFERROR($C76*AT74,"") -> 0 | AX76: =IFERROR($C76*AX74,"") -> 0 | BB76: =IFERROR($C76*BB74,"") -> 0 | BF76: =IFERROR($C76*BF74,"") -> 0 | BJ76: =IFERROR($C76*BJ74,"") -> 0 | BN76: =IFERROR($C76*BN74,"") -> 0 | BR76: =IFERROR($C76*BR74,"") -> 0 | BV76: =IFERROR($C76*BV74,"") -> 0 | BZ76: =IFERROR($C76*BZ74,"") -> 0 | CD76: =IFERROR($C76*CD74,"") -> 0 | CH76: =IFERROR($C76*CH74,"") -> 0 | CL76: =IFERROR($C76*CL74,"") -> 0 | CP76: =IFERROR($C76*CP74,"") -> 0 | CT76: =IFERROR($C76*CT74,"") -> 0 | CX76: =IFERROR($C76*CX74,"") -> 0 | DB76: =IFERROR($C76*DB74,"") -> 0 | DF76: =IFERROR($C76*DF74,"") -> 0 | DJ76: =IFERROR($C76*DJ74,"") -> 0 | DN76: =IFERROR($C76*DN74,"") -> 0 | DR76: =IFERROR($C76*DR74,"") -> 0 | DV76: =IFERROR($C76*DV74,"") -> 0 | DZ76: =IFERROR($C76*DZ74,"") -> 0 | ED76: =IFERROR($C76*ED74,"") -> 0 | EH76: =IFERROR($C76*EH74,"") -> 0 | EL76: =IFERROR($C76*EL74,"") -> 0 | EP76: =IFERROR($C76*EP74,"") -> 0
B77: 3：PG（オフショア） | D77: 工数 | E77: =SUM(F77:ES77) -> 0 | F77: =IF(ISERROR(VLOOKUP(RIGHT(CELL("filename",$A$1),LEN(CELL("filename",$A$1))-FIND("]",CELL("filename",$A$1)))&$B77,[2]要員計画!$L:$AJ,((COLUMN()-1)/4)+1,FALSE)),0,VLOOKUP(RIGHT(CELL("filename",$A$1),LEN(CELL("filename",$A$1))-FIND("]",CELL("filename",$A$1)))&$B77,[2]要員計画!$L:$AJ,((COLUMN()-1)/4)+1,FALSE)) -> 0 | J77: =IF(ISERROR(VLOOKUP(RIGHT(CELL("filename",$A$1),LEN(CELL("filename",$A$1))-FIND("]",CELL("filename",$A$1)))&$B77,[2]要員計画!$L:$AJ,((COLUMN()-1)/4)+1,FALSE)),0,VLOOKUP(RIGHT(CELL("filename",$A$1),LEN(CELL("filename",$A$1))-FIND("]",CELL("filename",$A$1)))&$B77,[2]要員計画!$L:$AJ,((COLUMN()-1)/4)+1,FALSE)) -> 0 | N77: =IF(ISERROR(VLOOKUP(RIGHT(CELL("filename",$A$1),LEN(CELL("filename",$A$1))-FIND("]",CELL("filename",$A$1)))&$B77,[2]要員計画!$L:$AJ,((COLUMN()-1)/4)+1,FALSE)),0,VLOOKUP(RIGHT(CELL("filename",$A$1),LEN(CELL("filename",$A$1))-FIND("]",CELL("filename",$A$1)))&$B77,[2]要員計画!$L:$AJ,((COLUMN()-1)/4)+1,FALSE)) -> 0 | R77: =IF(ISERROR(VLOOKUP(RIGHT(CELL("filename",$A$1),LEN(CELL("filename",$A$1))-FIND("]",CELL("filename",$A$1)))&$B77,[2]要員計画!$L:$AJ,((COLUMN()-1)/4)+1,FALSE)),0,VLOOKUP(RIGHT(CELL("filename",$A$1),LEN(CELL("filename",$A$1))-FIND("]",CELL("filename",$A$1)))&$B77,[2]要員計画!$L:$AJ,((COLUMN()-1)/4)+1,FALSE)) -> 0 | V77: =IF(ISERROR(VLOOKUP(RIGHT(CELL("filename",$A$1),LEN(CELL("filename",$A$1))-FIND("]",CELL("filename",$A$1)))&$B77,[2]要員計画!$L:$AJ,((COLUMN()-1)/4)+1,FALSE)),0,VLOOKUP(RIGHT(CELL("filename",$A$1),LEN(CELL("filename",$A$1))-FIND("]",CELL("filename",$A$1)))&$B77,[2]要員計画!$L:$AJ,((COLUMN()-1)/4)+1,FALSE)) -> 0 | Z77: =IF(ISERROR(VLOOKUP(RIGHT(CELL("filename",$A$1),LEN(CELL("filename",$A$1))-FIND("]",CELL("filename",$A$1)))&$B77,[2]要員計画!$L:$AJ,((COLUMN()-1)/4)+1,FALSE)),0,VLOOKUP(RIGHT(CELL("filename",$A$1),LEN(CELL("filename",$A$1))-FIND("]",CELL("filename",$A$1)))&$B77,[2]要員計画!$L:$AJ,((COLUMN()-1)/4)+1,FALSE)) -> 0 | DR77: =IF(ISERROR(VLOOKUP(RIGHT(CELL("filename",$A$1),LEN(CELL("filename",$A$1))-FIND("]",CELL("filename",$A$1)))&$B77,[2]要員計画!$L:$AJ,((COLUMN()-1)/4)+1,FALSE)),0,VLOOKUP(RIGHT(CELL("filename",$A$1),LEN(CELL("filename",$A$1))-FIND("]",CELL("filename",$A$1)))&$B77,[2]要員計画!$L:$AJ,((COLUMN()-1)/4)+1,FALSE)) -> 0 | DV77: =IF(ISERROR(VLOOKUP(RIGHT(CELL("filename",$A$1),LEN(CELL("filename",$A$1))-FIND("]",CELL("filename",$A$1)))&$B77,[2]要員計画!$L:$AJ,((COLUMN()-1)/4)+1,FALSE)),0,VLOOKUP(RIGHT(CELL("filename",$A$1),LEN(CELL("filename",$A$1))-FIND("]",CELL("filename",$A$1)))&$B77,[2]要員計画!$L:$AJ,((COLUMN()-1)/4)+1,FALSE)) -> 0 | DZ77: =IF(ISERROR(VLOOKUP(RIGHT(CELL("filename",$A$1),LEN(CELL("filename",$A$1))-FIND("]",CELL("filename",$A$1)))&$B77,[2]要員計画!$L:$AJ,((COLUMN()-1)/4)+1,FALSE)),0,VLOOKUP(RIGHT(CELL("filename",$A$1),LEN(CELL("filename",$A$1))-FIND("]",CELL("filename",$A$1)))&$B77,[2]要員計画!$L:$AJ,((COLUMN()-1)/4)+1,FALSE)) -> 0 | ED77: =IF(ISERROR(VLOOKUP(RIGHT(CELL("filename",$A$1),LEN(CELL("filename",$A$1))-FIND("]",CELL("filename",$A$1)))&$B77,[2]要員計画!$L:$AJ,((COLUMN()-1)/4)+1,FALSE)),0,VLOOKUP(RIGHT(CELL("filename",$A$1),LEN(CELL("filename",$A$1))-FIND("]",CELL("filename",$A$1)))&$B77,[2]要員計画!$L:$AJ,((COLUMN()-1)/4)+1,FALSE)) -> 0 | EH77: =IF(ISERROR(VLOOKUP(RIGHT(CELL("filename",$A$1),LEN(CELL("filename",$A$1))-FIND("]",CELL("filename",$A$1)))&$B77,[2]要員計画!$L:$AJ,((COLUMN()-1)/4)+1,FALSE)),0,VLOOKUP(RIGHT(CELL("filename",$A$1),LEN(CELL("filename",$A$1))-FIND("]",CELL("filename",$A$1)))&$B77,[2]要員計画!$L:$AJ,((COLUMN()-1)/4)+1,FALSE)) -> 0 | EL77: =IF(ISERROR(VLOOKUP(RIGHT(CELL("filename",$A$1),LEN(CELL("filename",$A$1))-FIND("]",CELL("filename",$A$1)))&$B77,[2]要員計画!$L:$AJ,((COLUMN()-1)/4)+1,FALSE)),0,VLOOKUP(RIGHT(CELL("filename",$A$1),LEN(CELL("filename",$A$1))-FIND("]",CELL("filename",$A$1)))&$B77,[2]要員計画!$L:$AJ,((COLUMN()-1)/4)+1,FALSE)) -> 0 | EP77: =IF(ISERROR(VLOOKUP(RIGHT(CELL("filename",$A$1),LEN(CELL("filename",$A$1))-FIND("]",CELL("filename",$A$1)))&$B77,[2]要員計画!$L:$AJ,((COLUMN()-1)/4)+1,FALSE)),0,VLOOKUP(RIGHT(CELL("filename",$A$1),LEN(CELL("filename",$A$1))-FIND("]",CELL("filename",$A$1)))&$B77,[2]要員計画!$L:$AJ,((COLUMN()-1)/4)+1,FALSE)) -> 0
C78: 600000 | D78: 売上金額 | E78: =SUM(F78:CW78) -> 0 | F78: =IFERROR($C78*F77,"") -> 0 | J78: =IFERROR($C78*J77,"") -> 0 | N78: =IFERROR($C78*N77,"") -> 0 | R78: =IFERROR($C78*R77,"") -> 0 | V78: =IFERROR($C78*V77,"") -> 0 | Z78: =IFERROR($C78*Z77,"") -> 0 | AD78: =IFERROR($C78*AD77,"") -> 0 | AH78: =IFERROR($C78*AH77,"") -> 0 | AL78: =IFERROR($C78*AL77,"") -> 0 | AP78: =IFERROR($C78*AP77,"") -> 0 | AT78: =IFERROR($C78*AT77,"") -> 0 | AX78: =IFERROR($C78*AX77,"") -> 0 | BB78: =IFERROR($C78*BB77,"") -> 0 | BF78: =IFERROR($C78*BF77,"") -> 0 | BJ78: =IFERROR($C78*BJ77,"") -> 0 | BN78: =IFERROR($C78*BN77,"") -> 0 | BR78: =IFERROR($C78*BR77,"") -> 0 | BV78: =IFERROR($C78*BV77,"") -> 0 | BZ78: =IFERROR($C78*BZ77,"") -> 0 | CD78: =IFERROR($C78*CD77,"") -> 0 | CH78: =IFERROR($C78*CH77,"") -> 0 | CL78: =IFERROR($C78*CL77,"") -> 0 | CP78: =IFERROR($C78*CP77,"") -> 0 | CT78: =IFERROR($C78*CT77,"") -> 0 | CX78: =IFERROR($C78*CX77,"") -> 0 | DB78: =IFERROR($C78*DB77,"") -> 0 | DF78: =IFERROR($C78*DF77,"") -> 0 | DJ78: =IFERROR($C78*DJ77,"") -> 0 | DN78: =IFERROR($C78*DN77,"") -> 0 | DR78: =IFERROR($C78*DR77,"") -> 0 | DV78: =IFERROR($C78*DV77,"") -> 0 | DZ78: =IFERROR($C78*DZ77,"") -> 0 | ED78: =IFERROR($C78*ED77,"") -> 0 | EH78: =IFERROR($C78*EH77,"") -> 0 | EL78: =IFERROR($C78*EL77,"") -> 0 | EP78: =IFERROR($C78*EP77,"") -> 0
C79: 400000 | D79: 原価金額 | E79: =SUM(F79:CW79) -> 0 | F79: =IFERROR($C79*F77,"") -> 0 | J79: =IFERROR($C79*J77,"") -> 0 | N79: =IFERROR($C79*N77,"") -> 0 | R79: =IFERROR($C79*R77,"") -> 0 | V79: =IFERROR($C79*V77,"") -> 0 | Z79: =IFERROR($C79*Z77,"") -> 0 | AD79: =IFERROR($C79*AD77,"") -> 0 | AH79: =IFERROR($C79*AH77,"") -> 0 | AL79: =IFERROR($C79*AL77,"") -> 0 | AP79: =IFERROR($C79*AP77,"") -> 0 | AT79: =IFERROR($C79*AT77,"") -> 0 | AX79: =IFERROR($C79*AX77,"") -> 0 | BB79: =IFERROR($C79*BB77,"") -> 0 | BF79: =IFERROR($C79*BF77,"") -> 0 | BJ79: =IFERROR($C79*BJ77,"") -> 0 | BN79: =IFERROR($C79*BN77,"") -> 0 | BR79: =IFERROR($C79*BR77,"") -> 0 | BV79: =IFERROR($C79*BV77,"") -> 0 | BZ79: =IFERROR($C79*BZ77,"") -> 0 | CD79: =IFERROR($C79*CD77,"") -> 0 | CH79: =IFERROR($C79*CH77,"") -> 0 | CL79: =IFERROR($C79*CL77,"") -> 0 | CP79: =IFERROR($C79*CP77,"") -> 0 | CT79: =IFERROR($C79*CT77,"") -> 0 | CX79: =IFERROR($C79*CX77,"") -> 0 | DB79: =IFERROR($C79*DB77,"") -> 0 | DF79: =IFERROR($C79*DF77,"") -> 0 | DJ79: =IFERROR($C79*DJ77,"") -> 0 | DN79: =IFERROR($C79*DN77,"") -> 0 | DR79: =IFERROR($C79*DR77,"") -> 0 | DV79: =IFERROR($C79*DV77,"") -> 0 | DZ79: =IFERROR($C79*DZ77,"") -> 0 | ED79: =IFERROR($C79*ED77,"") -> 0 | EH79: =IFERROR($C79*EH77,"") -> 0 | EL79: =IFERROR($C79*EL77,"") -> 0 | EP79: =IFERROR($C79*EP77,"") -> 0
B80: 4：PG（オフショア） | D80: 工数 | E80: =SUM(F80:ES80) -> 0 | F80: =IF(ISERROR(VLOOKUP(RIGHT(CELL("filename",$A$1),LEN(CELL("filename",$A$1))-FIND("]",CELL("filename",$A$1)))&$B80,[2]要員計画!$L:$AJ,((COLUMN()-1)/4)+1,FALSE)),0,VLOOKUP(RIGHT(CELL("filename",$A$1),LEN(CELL("filename",$A$1))-FIND("]",CELL("filename",$A$1)))&$B80,[2]要員計画!$L:$AJ,((COLUMN()-1)/4)+1,FALSE)) -> 0 | J80: =IF(ISERROR(VLOOKUP(RIGHT(CELL("filename",$A$1),LEN(CELL("filename",$A$1))-FIND("]",CELL("filename",$A$1)))&$B80,[2]要員計画!$L:$AJ,((COLUMN()-1)/4)+1,FALSE)),0,VLOOKUP(RIGHT(CELL("filename",$A$1),LEN(CELL("filename",$A$1))-FIND("]",CELL("filename",$A$1)))&$B80,[2]要員計画!$L:$AJ,((COLUMN()-1)/4)+1,FALSE)) -> 0 | N80: =IF(ISERROR(VLOOKUP(RIGHT(CELL("filename",$A$1),LEN(CELL("filename",$A$1))-FIND("]",CELL("filename",$A$1)))&$B80,[2]要員計画!$L:$AJ,((COLUMN()-1)/4)+1,FALSE)),0,VLOOKUP(RIGHT(CELL("filename",$A$1),LEN(CELL("filename",$A$1))-FIND("]",CELL("filename",$A$1)))&$B80,[2]要員計画!$L:$AJ,((COLUMN()-1)/4)+1,FALSE)) -> 0 | R80: =IF(ISERROR(VLOOKUP(RIGHT(CELL("filename",$A$1),LEN(CELL("filename",$A$1))-FIND("]",CELL("filename",$A$1)))&$B80,[2]要員計画!$L:$AJ,((COLUMN()-1)/4)+1,FALSE)),0,VLOOKUP(RIGHT(CELL("filename",$A$1),LEN(CELL("filename",$A$1))-FIND("]",CELL("filename",$A$1)))&$B80,[2]要員計画!$L:$AJ,((COLUMN()-1)/4)+1,FALSE)) -> 0 | V80: =IF(ISERROR(VLOOKUP(RIGHT(CELL("filename",$A$1),LEN(CELL("filename",$A$1))-FIND("]",CELL("filename",$A$1)))&$B80,[2]要員計画!$L:$AJ,((COLUMN()-1)/4)+1,FALSE)),0,VLOOKUP(RIGHT(CELL("filename",$A$1),LEN(CELL("filename",$A$1))-FIND("]",CELL("filename",$A$1)))&$B80,[2]要員計画!$L:$AJ,((COLUMN()-1)/4)+1,FALSE)) -> 0 | Z80: =IF(ISERROR(VLOOKUP(RIGHT(CELL("filename",$A$1),LEN(CELL("filename",$A$1))-FIND("]",CELL("filename",$A$1)))&$B80,[2]要員計画!$L:$AJ,((COLUMN()-1)/4)+1,FALSE)),0,VLOOKUP(RIGHT(CELL("filename",$A$1),LEN(CELL("filename",$A$1))-FIND("]",CELL("filename",$A$1)))&$B80,[2]要員計画!$L:$AJ,((COLUMN()-1)/4)+1,FALSE)) -> 0 | DR80: =IF(ISERROR(VLOOKUP(RIGHT(CELL("filename",$A$1),LEN(CELL("filename",$A$1))-FIND("]",CELL("filename",$A$1)))&$B80,[2]要員計画!$L:$AJ,((COLUMN()-1)/4)+1,FALSE)),0,VLOOKUP(RIGHT(CELL("filename",$A$1),LEN(CELL("filename",$A$1))-FIND("]",CELL("filename",$A$1)))&$B80,[2]要員計画!$L:$AJ,((COLUMN()-1)/4)+1,FALSE)) -> 0 | DV80: =IF(ISERROR(VLOOKUP(RIGHT(CELL("filename",$A$1),LEN(CELL("filename",$A$1))-FIND("]",CELL("filename",$A$1)))&$B80,[2]要員計画!$L:$AJ,((COLUMN()-1)/4)+1,FALSE)),0,VLOOKUP(RIGHT(CELL("filename",$A$1),LEN(CELL("filename",$A$1))-FIND("]",CELL("filename",$A$1)))&$B80,[2]要員計画!$L:$AJ,((COLUMN()-1)/4)+1,FALSE)) -> 0 | DZ80: =IF(ISERROR(VLOOKUP(RIGHT(CELL("filename",$A$1),LEN(CELL("filename",$A$1))-FIND("]",CELL("filename",$A$1)))&$B80,[2]要員計画!$L:$AJ,((COLUMN()-1)/4)+1,FALSE)),0,VLOOKUP(RIGHT(CELL("filename",$A$1),LEN(CELL("filename",$A$1))-FIND("]",CELL("filename",$A$1)))&$B80,[2]要員計画!$L:$AJ,((COLUMN()-1)/4)+1,FALSE)) -> 0 | ED80: =IF(ISERROR(VLOOKUP(RIGHT(CELL("filename",$A$1),LEN(CELL("filename",$A$1))-FIND("]",CELL("filename",$A$1)))&$B80,[2]要員計画!$L:$AJ,((COLUMN()-1)/4)+1,FALSE)),0,VLOOKUP(RIGHT(CELL("filename",$A$1),LEN(CELL("filename",$A$1))-FIND("]",CELL("filename",$A$1)))&$B80,[2]要員計画!$L:$AJ,((COLUMN()-1)/4)+1,FALSE)) -> 0 | EH80: =IF(ISERROR(VLOOKUP(RIGHT(CELL("filename",$A$1),LEN(CELL("filename",$A$1))-FIND("]",CELL("filename",$A$1)))&$B80,[2]要員計画!$L:$AJ,((COLUMN()-1)/4)+1,FALSE)),0,VLOOKUP(RIGHT(CELL("filename",$A$1),LEN(CELL("filename",$A$1))-FIND("]",CELL("filename",$A$1)))&$B80,[2]要員計画!$L:$AJ,((COLUMN()-1)/4)+1,FALSE)) -> 0 | EL80: =IF(ISERROR(VLOOKUP(RIGHT(CELL("filename",$A$1),LEN(CELL("filename",$A$1))-FIND("]",CELL("filename",$A$1)))&$B80,[2]要員計画!$L:$AJ,((COLUMN()-1)/4)+1,FALSE)),0,VLOOKUP(RIGHT(CELL("filename",$A$1),LEN(CELL("filename",$A$1))-FIND("]",CELL("filename",$A$1)))&$B80,[2]要員計画!$L:$AJ,((COLUMN()-1)/4)+1,FALSE)) -> 0 | EP80: =IF(ISERROR(VLOOKUP(RIGHT(CELL("filename",$A$1),LEN(CELL("filename",$A$1))-FIND("]",CELL("filename",$A$1)))&$B80,[2]要員計画!$L:$AJ,((COLUMN()-1)/4)+1,FALSE)),0,VLOOKUP(RIGHT(CELL("filename",$A$1),LEN(CELL("filename",$A$1))-FIND("]",CELL("filename",$A$1)))&$B80,[2]要員計画!$L:$AJ,((COLUMN()-1)/4)+1,FALSE)) -> 0
C81: 600000 | D81: 売上金額 | E81: =SUM(F81:CW81) -> 0 | F81: =IFERROR($C81*F80,"") -> 0 | J81: =IFERROR($C81*J80,"") -> 0 | N81: =IFERROR($C81*N80,"") -> 0 | R81: =IFERROR($C81*R80,"") -> 0 | V81: =IFERROR($C81*V80,"") -> 0 | Z81: =IFERROR($C81*Z80,"") -> 0 | AD81: =IFERROR($C81*AD80,"") -> 0 | AH81: =IFERROR($C81*AH80,"") -> 0 | AL81: =IFERROR($C81*AL80,"") -> 0 | AP81: =IFERROR($C81*AP80,"") -> 0 | AT81: =IFERROR($C81*AT80,"") -> 0 | AX81: =IFERROR($C81*AX80,"") -> 0 | BB81: =IFERROR($C81*BB80,"") -> 0 | BF81: =IFERROR($C81*BF80,"") -> 0 | BJ81: =IFERROR($C81*BJ80,"") -> 0 | BN81: =IFERROR($C81*BN80,"") -> 0 | BR81: =IFERROR($C81*BR80,"") -> 0 | BV81: =IFERROR($C81*BV80,"") -> 0 | BZ81: =IFERROR($C81*BZ80,"") -> 0 | CD81: =IFERROR($C81*CD80,"") -> 0 | CH81: =IFERROR($C81*CH80,"") -> 0 | CL81: =IFERROR($C81*CL80,"") -> 0 | CP81: =IFERROR($C81*CP80,"") -> 0 | CT81: =IFERROR($C81*CT80,"") -> 0 | CX81: =IFERROR($C81*CX80,"") -> 0 | DB81: =IFERROR($C81*DB80,"") -> 0 | DF81: =IFERROR($C81*DF80,"") -> 0 | DJ81: =IFERROR($C81*DJ80,"") -> 0 | DN81: =IFERROR($C81*DN80,"") -> 0 | DR81: =IFERROR($C81*DR80,"") -> 0 | DV81: =IFERROR($C81*DV80,"") -> 0 | DZ81: =IFERROR($C81*DZ80,"") -> 0 | ED81: =IFERROR($C81*ED80,"") -> 0 | EH81: =IFERROR($C81*EH80,"") -> 0 | EL81: =IFERROR($C81*EL80,"") -> 0 | EP81: =IFERROR($C81*EP80,"") -> 0
C82: 400000 | D82: 原価金額 | E82: =SUM(F82:CW82) -> 0 | F82: =IFERROR($C82*F80,"") -> 0 | J82: =IFERROR($C82*J80,"") -> 0 | N82: =IFERROR($C82*N80,"") -> 0 | R82: =IFERROR($C82*R80,"") -> 0 | V82: =IFERROR($C82*V80,"") -> 0 | Z82: =IFERROR($C82*Z80,"") -> 0 | AD82: =IFERROR($C82*AD80,"") -> 0 | AH82: =IFERROR($C82*AH80,"") -> 0 | AL82: =IFERROR($C82*AL80,"") -> 0 | AP82: =IFERROR($C82*AP80,"") -> 0 | AT82: =IFERROR($C82*AT80,"") -> 0 | AX82: =IFERROR($C82*AX80,"") -> 0 | BB82: =IFERROR($C82*BB80,"") -> 0 | BF82: =IFERROR($C82*BF80,"") -> 0 | BJ82: =IFERROR($C82*BJ80,"") -> 0 | BN82: =IFERROR($C82*BN80,"") -> 0 | BR82: =IFERROR($C82*BR80,"") -> 0 | BV82: =IFERROR($C82*BV80,"") -> 0 | BZ82: =IFERROR($C82*BZ80,"") -> 0 | CD82: =IFERROR($C82*CD80,"") -> 0 | CH82: =IFERROR($C82*CH80,"") -> 0 | CL82: =IFERROR($C82*CL80,"") -> 0 | CP82: =IFERROR($C82*CP80,"") -> 0 | CT82: =IFERROR($C82*CT80,"") -> 0 | CX82: =IFERROR($C82*CX80,"") -> 0 | DB82: =IFERROR($C82*DB80,"") -> 0 | DF82: =IFERROR($C82*DF80,"") -> 0 | DJ82: =IFERROR($C82*DJ80,"") -> 0 | DN82: =IFERROR($C82*DN80,"") -> 0 | DR82: =IFERROR($C82*DR80,"") -> 0 | DV82: =IFERROR($C82*DV80,"") -> 0 | DZ82: =IFERROR($C82*DZ80,"") -> 0 | ED82: =IFERROR($C82*ED80,"") -> 0 | EH82: =IFERROR($C82*EH80,"") -> 0 | EL82: =IFERROR($C82*EL80,"") -> 0 | EP82: =IFERROR($C82*EP80,"") -> 0
B83: 7 | D83: 工数 | E83: =SUM(F83:ES83) -> 0 | F83: =IF(ISERROR(VLOOKUP(RIGHT(CELL("filename",$A$1),LEN(CELL("filename",$A$1))-FIND("]",CELL("filename",$A$1)))&$B83,[2]要員計画!$L:$AJ,((COLUMN()-1)/4)+1,FALSE)),0,VLOOKUP(RIGHT(CELL("filename",$A$1),LEN(CELL("filename",$A$1))-FIND("]",CELL("filename",$A$1)))&$B83,[2]要員計画!$L:$AJ,((COLUMN()-1)/4)+1,FALSE)) -> 0 | J83: =IF(ISERROR(VLOOKUP(RIGHT(CELL("filename",$A$1),LEN(CELL("filename",$A$1))-FIND("]",CELL("filename",$A$1)))&$B83,[2]要員計画!$L:$AJ,((COLUMN()-1)/4)+1,FALSE)),0,VLOOKUP(RIGHT(CELL("filename",$A$1),LEN(CELL("filename",$A$1))-FIND("]",CELL("filename",$A$1)))&$B83,[2]要員計画!$L:$AJ,((COLUMN()-1)/4)+1,FALSE)) -> 0 | N83: =IF(ISERROR(VLOOKUP(RIGHT(CELL("filename",$A$1),LEN(CELL("filename",$A$1))-FIND("]",CELL("filename",$A$1)))&$B83,[2]要員計画!$L:$AJ,((COLUMN()-1)/4)+1,FALSE)),0,VLOOKUP(RIGHT(CELL("filename",$A$1),LEN(CELL("filename",$A$1))-FIND("]",CELL("filename",$A$1)))&$B83,[2]要員計画!$L:$AJ,((COLUMN()-1)/4)+1,FALSE)) -> 0 | R83: =IF(ISERROR(VLOOKUP(RIGHT(CELL("filename",$A$1),LEN(CELL("filename",$A$1))-FIND("]",CELL("filename",$A$1)))&$B83,[2]要員計画!$L:$AJ,((COLUMN()-1)/4)+1,FALSE)),0,VLOOKUP(RIGHT(CELL("filename",$A$1),LEN(CELL("filename",$A$1))-FIND("]",CELL("filename",$A$1)))&$B83,[2]要員計画!$L:$AJ,((COLUMN()-1)/4)+1,FALSE)) -> 0 | V83: =IF(ISERROR(VLOOKUP(RIGHT(CELL("filename",$A$1),LEN(CELL("filename",$A$1))-FIND("]",CELL("filename",$A$1)))&$B83,[2]要員計画!$L:$AJ,((COLUMN()-1)/4)+1,FALSE)),0,VLOOKUP(RIGHT(CELL("filename",$A$1),LEN(CELL("filename",$A$1))-FIND("]",CELL("filename",$A$1)))&$B83,[2]要員計画!$L:$AJ,((COLUMN()-1)/4)+1,FALSE)) -> 0 | Z83: =IF(ISERROR(VLOOKUP(RIGHT(CELL("filename",$A$1),LEN(CELL("filename",$A$1))-FIND("]",CELL("filename",$A$1)))&$B83,[2]要員計画!$L:$AJ,((COLUMN()-1)/4)+1,FALSE)),0,VLOOKUP(RIGHT(CELL("filename",$A$1),LEN(CELL("filename",$A$1))-FIND("]",CELL("filename",$A$1)))&$B83,[2]要員計画!$L:$AJ,((COLUMN()-1)/4)+1,FALSE)) -> 0 | DR83: =IF(ISERROR(VLOOKUP(RIGHT(CELL("filename",$A$1),LEN(CELL("filename",$A$1))-FIND("]",CELL("filename",$A$1)))&$B83,[2]要員計画!$L:$AJ,((COLUMN()-1)/4)+1,FALSE)),0,VLOOKUP(RIGHT(CELL("filename",$A$1),LEN(CELL("filename",$A$1))-FIND("]",CELL("filename",$A$1)))&$B83,[2]要員計画!$L:$AJ,((COLUMN()-1)/4)+1,FALSE)) -> 0 | DV83: =IF(ISERROR(VLOOKUP(RIGHT(CELL("filename",$A$1),LEN(CELL("filename",$A$1))-FIND("]",CELL("filename",$A$1)))&$B83,[2]要員計画!$L:$AJ,((COLUMN()-1)/4)+1,FALSE)),0,VLOOKUP(RIGHT(CELL("filename",$A$1),LEN(CELL("filename",$A$1))-FIND("]",CELL("filename",$A$1)))&$B83,[2]要員計画!$L:$AJ,((COLUMN()-1)/4)+1,FALSE)) -> 0 | DZ83: =IF(ISERROR(VLOOKUP(RIGHT(CELL("filename",$A$1),LEN(CELL("filename",$A$1))-FIND("]",CELL("filename",$A$1)))&$B83,[2]要員計画!$L:$AJ,((COLUMN()-1)/4)+1,FALSE)),0,VLOOKUP(RIGHT(CELL("filename",$A$1),LEN(CELL("filename",$A$1))-FIND("]",CELL("filename",$A$1)))&$B83,[2]要員計画!$L:$AJ,((COLUMN()-1)/4)+1,FALSE)) -> 0 | ED83: =IF(ISERROR(VLOOKUP(RIGHT(CELL("filename",$A$1),LEN(CELL("filename",$A$1))-FIND("]",CELL("filename",$A$1)))&$B83,[2]要員計画!$L:$AJ,((COLUMN()-1)/4)+1,FALSE)),0,VLOOKUP(RIGHT(CELL("filename",$A$1),LEN(CELL("filename",$A$1))-FIND("]",CELL("filename",$A$1)))&$B83,[2]要員計画!$L:$AJ,((COLUMN()-1)/4)+1,FALSE)) -> 0 | EH83: =IF(ISERROR(VLOOKUP(RIGHT(CELL("filename",$A$1),LEN(CELL("filename",$A$1))-FIND("]",CELL("filename",$A$1)))&$B83,[2]要員計画!$L:$AJ,((COLUMN()-1)/4)+1,FALSE)),0,VLOOKUP(RIGHT(CELL("filename",$A$1),LEN(CELL("filename",$A$1))-FIND("]",CELL("filename",$A$1)))&$B83,[2]要員計画!$L:$AJ,((COLUMN()-1)/4)+1,FALSE)) -> 0 | EL83: =IF(ISERROR(VLOOKUP(RIGHT(CELL("filename",$A$1),LEN(CELL("filename",$A$1))-FIND("]",CELL("filename",$A$1)))&$B83,[2]要員計画!$L:$AJ,((COLUMN()-1)/4)+1,FALSE)),0,VLOOKUP(RIGHT(CELL("filename",$A$1),LEN(CELL("filename",$A$1))-FIND("]",CELL("filename",$A$1)))&$B83,[2]要員計画!$L:$AJ,((COLUMN()-1)/4)+1,FALSE)) -> 0 | EP83: =IF(ISERROR(VLOOKUP(RIGHT(CELL("filename",$A$1),LEN(CELL("filename",$A$1))-FIND("]",CELL("filename",$A$1)))&$B83,[2]要員計画!$L:$AJ,((COLUMN()-1)/4)+1,FALSE)),0,VLOOKUP(RIGHT(CELL("filename",$A$1),LEN(CELL("filename",$A$1))-FIND("]",CELL("filename",$A$1)))&$B83,[2]要員計画!$L:$AJ,((COLUMN()-1)/4)+1,FALSE)) -> 0
C84: 1000000 | D84: 売上金額 | E84: =SUM(F84:CW84) -> 0 | F84: =IFERROR($C84*F83,"") -> 0 | J84: =IFERROR($C84*J83,"") -> 0 | N84: =IFERROR($C84*N83,"") -> 0 | R84: =IFERROR($C84*R83,"") -> 0 | V84: =IFERROR($C84*V83,"") -> 0 | Z84: =IFERROR($C84*Z83,"") -> 0 | DR84: =IFERROR($C84*DR83,"") -> 0 | DV84: =IFERROR($C84*DV83,"") -> 0 | DZ84: =IFERROR($C84*DZ83,"") -> 0 | ED84: =IFERROR($C84*ED83,"") -> 0 | EH84: =IFERROR($C84*EH83,"") -> 0 | EL84: =IFERROR($C84*EL83,"") -> 0 | EP84: =IFERROR($C84*EP83,"") -> 0
C85: 850000 | D85: 原価金額 | E85: =SUM(F85:CW85) -> 0 | F85: =IFERROR($C85*F83,"") -> 0 | J85: =IFERROR($C85*J83,"") -> 0 | N85: =IFERROR($C85*N83,"") -> 0 | R85: =IFERROR($C85*R83,"") -> 0 | V85: =IFERROR($C85*V83,"") -> 0 | Z85: =IFERROR($C85*Z83,"") -> 0 | DR85: =IFERROR($C85*DR83,"") -> 0 | DV85: =IFERROR($C85*DV83,"") -> 0 | DZ85: =IFERROR($C85*DZ83,"") -> 0 | ED85: =IFERROR($C85*ED83,"") -> 0 | EH85: =IFERROR($C85*EH83,"") -> 0 | EL85: =IFERROR($C85*EL83,"") -> 0 | EP85: =IFERROR($C85*EP83,"") -> 0
B86: 8 | D86: 工数 | E86: =SUM(F86:ES86) -> 0 | DR86: =IF(ISERROR(VLOOKUP(RIGHT(CELL("filename",$A$1),LEN(CELL("filename",$A$1))-FIND("]",CELL("filename",$A$1)))&$B86,[2]要員計画!$L:$AJ,((COLUMN()-1)/4)+1,FALSE)),0,VLOOKUP(RIGHT(CELL("filename",$A$1),LEN(CELL("filename",$A$1))-FIND("]",CELL("filename",$A$1)))&$B86,[2]要員計画!$L:$AJ,((COLUMN()-1)/4)+1,FALSE)) -> 0 | DV86: =IF(ISERROR(VLOOKUP(RIGHT(CELL("filename",$A$1),LEN(CELL("filename",$A$1))-FIND("]",CELL("filename",$A$1)))&$B86,[2]要員計画!$L:$AJ,((COLUMN()-1)/4)+1,FALSE)),0,VLOOKUP(RIGHT(CELL("filename",$A$1),LEN(CELL("filename",$A$1))-FIND("]",CELL("filename",$A$1)))&$B86,[2]要員計画!$L:$AJ,((COLUMN()-1)/4)+1,FALSE)) -> 0 | DZ86: =IF(ISERROR(VLOOKUP(RIGHT(CELL("filename",$A$1),LEN(CELL("filename",$A$1))-FIND("]",CELL("filename",$A$1)))&$B86,[2]要員計画!$L:$AJ,((COLUMN()-1)/4)+1,FALSE)),0,VLOOKUP(RIGHT(CELL("filename",$A$1),LEN(CELL("filename",$A$1))-FIND("]",CELL("filename",$A$1)))&$B86,[2]要員計画!$L:$AJ,((COLUMN()-1)/4)+1,FALSE)) -> 0 | ED86: =IF(ISERROR(VLOOKUP(RIGHT(CELL("filename",$A$1),LEN(CELL("filename",$A$1))-FIND("]",CELL("filename",$A$1)))&$B86,[2]要員計画!$L:$AJ,((COLUMN()-1)/4)+1,FALSE)),0,VLOOKUP(RIGHT(CELL("filename",$A$1),LEN(CELL("filename",$A$1))-FIND("]",CELL("filename",$A$1)))&$B86,[2]要員計画!$L:$AJ,((COLUMN()-1)/4)+1,FALSE)) -> 0 | EH86: =IF(ISERROR(VLOOKUP(RIGHT(CELL("filename",$A$1),LEN(CELL("filename",$A$1))-FIND("]",CELL("filename",$A$1)))&$B86,[2]要員計画!$L:$AJ,((COLUMN()-1)/4)+1,FALSE)),0,VLOOKUP(RIGHT(CELL("filename",$A$1),LEN(CELL("filename",$A$1))-FIND("]",CELL("filename",$A$1)))&$B86,[2]要員計画!$L:$AJ,((COLUMN()-1)/4)+1,FALSE)) -> 0 | EL86: =IF(ISERROR(VLOOKUP(RIGHT(CELL("filename",$A$1),LEN(CELL("filename",$A$1))-FIND("]",CELL("filename",$A$1)))&$B86,[2]要員計画!$L:$AJ,((COLUMN()-1)/4)+1,FALSE)),0,VLOOKUP(RIGHT(CELL("filename",$A$1),LEN(CELL("filename",$A$1))-FIND("]",CELL("filename",$A$1)))&$B86,[2]要員計画!$L:$AJ,((COLUMN()-1)/4)+1,FALSE)) -> 0 | EP86: =IF(ISERROR(VLOOKUP(RIGHT(CELL("filename",$A$1),LEN(CELL("filename",$A$1))-FIND("]",CELL("filename",$A$1)))&$B86,[2]要員計画!$L:$AJ,((COLUMN()-1)/4)+1,FALSE)),0,VLOOKUP(RIGHT(CELL("filename",$A$1),LEN(CELL("filename",$A$1))-FIND("]",CELL("filename",$A$1)))&$B86,[2]要員計画!$L:$AJ,((COLUMN()-1)/4)+1,FALSE)) -> 0
C87: 1000000 | D87: 売上金額 | E87: =SUM(F87:CW87) -> 0 | F87: =IFERROR($C87*F86,"") -> 0 | J87: =IFERROR($C87*J86,"") -> 0 | N87: =IFERROR($C87*N86,"") -> 0 | R87: =IFERROR($C87*R86,"") -> 0 | V87: =IFERROR($C87*V86,"") -> 0 | Z87: =IFERROR($C87*Z86,"") -> 0 | DR87: =IFERROR($C87*DR86,"") -> 0 | DV87: =IFERROR($C87*DV86,"") -> 0 | DZ87: =IFERROR($C87*DZ86,"") -> 0 | ED87: =IFERROR($C87*ED86,"") -> 0 | EH87: =IFERROR($C87*EH86,"") -> 0 | EL87: =IFERROR($C87*EL86,"") -> 0 | EP87: =IFERROR($C87*EP86,"") -> 0
C88: 850000 | D88: 原価金額 | E88: =SUM(F88:CW88) -> 0 | F88: =IFERROR($C88*F86,"") -> 0 | J88: =IFERROR($C88*J86,"") -> 0 | N88: =IFERROR($C88*N86,"") -> 0 | R88: =IFERROR($C88*R86,"") -> 0 | V88: =IFERROR($C88*V86,"") -> 0 | Z88: =IFERROR($C88*Z86,"") -> 0 | DR88: =IFERROR($C88*DR86,"") -> 0 | DV88: =IFERROR($C88*DV86,"") -> 0 | DZ88: =IFERROR($C88*DZ86,"") -> 0 | ED88: =IFERROR($C88*ED86,"") -> 0 | EH88: =IFERROR($C88*EH86,"") -> 0 | EL88: =IFERROR($C88*EL86,"") -> 0 | EP88: =IFERROR($C88*EP86,"") -> 0
B89: 9 | D89: 工数 | E89: =SUM(F89:ES89) -> 0 | DR89: =IF(ISERROR(VLOOKUP(RIGHT(CELL("filename",$A$1),LEN(CELL("filename",$A$1))-FIND("]",CELL("filename",$A$1)))&$B89,[2]要員計画!$L:$AJ,((COLUMN()-1)/4)+1,FALSE)),0,VLOOKUP(RIGHT(CELL("filename",$A$1),LEN(CELL("filename",$A$1))-FIND("]",CELL("filename",$A$1)))&$B89,[2]要員計画!$L:$AJ,((COLUMN()-1)/4)+1,FALSE)) -> 0 | DV89: =IF(ISERROR(VLOOKUP(RIGHT(CELL("filename",$A$1),LEN(CELL("filename",$A$1))-FIND("]",CELL("filename",$A$1)))&$B89,[2]要員計画!$L:$AJ,((COLUMN()-1)/4)+1,FALSE)),0,VLOOKUP(RIGHT(CELL("filename",$A$1),LEN(CELL("filename",$A$1))-FIND("]",CELL("filename",$A$1)))&$B89,[2]要員計画!$L:$AJ,((COLUMN()-1)/4)+1,FALSE)) -> 0 | DZ89: =IF(ISERROR(VLOOKUP(RIGHT(CELL("filename",$A$1),LEN(CELL("filename",$A$1))-FIND("]",CELL("filename",$A$1)))&$B89,[2]要員計画!$L:$AJ,((COLUMN()-1)/4)+1,FALSE)),0,VLOOKUP(RIGHT(CELL("filename",$A$1),LEN(CELL("filename",$A$1))-FIND("]",CELL("filename",$A$1)))&$B89,[2]要員計画!$L:$AJ,((COLUMN()-1)/4)+1,FALSE)) -> 0 | ED89: =IF(ISERROR(VLOOKUP(RIGHT(CELL("filename",$A$1),LEN(CELL("filename",$A$1))-FIND("]",CELL("filename",$A$1)))&$B89,[2]要員計画!$L:$AJ,((COLUMN()-1)/4)+1,FALSE)),0,VLOOKUP(RIGHT(CELL("filename",$A$1),LEN(CELL("filename",$A$1))-FIND("]",CELL("filename",$A$1)))&$B89,[2]要員計画!$L:$AJ,((COLUMN()-1)/4)+1,FALSE)) -> 0 | EH89: =IF(ISERROR(VLOOKUP(RIGHT(CELL("filename",$A$1),LEN(CELL("filename",$A$1))-FIND("]",CELL("filename",$A$1)))&$B89,[2]要員計画!$L:$AJ,((COLUMN()-1)/4)+1,FALSE)),0,VLOOKUP(RIGHT(CELL("filename",$A$1),LEN(CELL("filename",$A$1))-FIND("]",CELL("filename",$A$1)))&$B89,[2]要員計画!$L:$AJ,((COLUMN()-1)/4)+1,FALSE)) -> 0 | EL89: =IF(ISERROR(VLOOKUP(RIGHT(CELL("filename",$A$1),LEN(CELL("filename",$A$1))-FIND("]",CELL("filename",$A$1)))&$B89,[2]要員計画!$L:$AJ,((COLUMN()-1)/4)+1,FALSE)),0,VLOOKUP(RIGHT(CELL("filename",$A$1),LEN(CELL("filename",$A$1))-FIND("]",CELL("filename",$A$1)))&$B89,[2]要員計画!$L:$AJ,((COLUMN()-1)/4)+1,FALSE)) -> 0 | EP89: =IF(ISERROR(VLOOKUP(RIGHT(CELL("filename",$A$1),LEN(CELL("filename",$A$1))-FIND("]",CELL("filename",$A$1)))&$B89,[2]要員計画!$L:$AJ,((COLUMN()-1)/4)+1,FALSE)),0,VLOOKUP(RIGHT(CELL("filename",$A$1),LEN(CELL("filename",$A$1))-FIND("]",CELL("filename",$A$1)))&$B89,[2]要員計画!$L:$AJ,((COLUMN()-1)/4)+1,FALSE)) -> 0
C90: 1000000 | D90: 売上金額 | E90: =SUM(F90:CW90) -> 0 | F90: =IFERROR($C90*F89,"") -> 0 | J90: =IFERROR($C90*J89,"") -> 0 | N90: =IFERROR($C90*N89,"") -> 0 | R90: =IFERROR($C90*R89,"") -> 0 | V90: =IFERROR($C90*V89,"") -> 0 | Z90: =IFERROR($C90*Z89,"") -> 0 | DR90: =IFERROR($C90*DR89,"") -> 0 | DV90: =IFERROR($C90*DV89,"") -> 0 | DZ90: =IFERROR($C90*DZ89,"") -> 0 | ED90: =IFERROR($C90*ED89,"") -> 0 | EH90: =IFERROR($C90*EH89,"") -> 0 | EL90: =IFERROR($C90*EL89,"") -> 0 | EP90: =IFERROR($C90*EP89,"") -> 0
C91: 850000 | D91: 原価金額 | E91: =SUM(F91:CW91) -> 0 | F91: =IFERROR($C91*F89,"") -> 0 | J91: =IFERROR($C91*J89,"") -> 0 | N91: =IFERROR($C91*N89,"") -> 0 | R91: =IFERROR($C91*R89,"") -> 0 | V91: =IFERROR($C91*V89,"") -> 0 | Z91: =IFERROR($C91*Z89,"") -> 0 | DR91: =IFERROR($C91*DR89,"") -> 0 | DV91: =IFERROR($C91*DV89,"") -> 0 | DZ91: =IFERROR($C91*DZ89,"") -> 0 | ED91: =IFERROR($C91*ED89,"") -> 0 | EH91: =IFERROR($C91*EH89,"") -> 0 | EL91: =IFERROR($C91*EL89,"") -> 0 | EP91: =IFERROR($C91*EP89,"") -> 0
B92: 10 | D92: 工数 | E92: =SUM(F92:ES92) -> 0 | F92: =IF(ISERROR(VLOOKUP(RIGHT(CELL("filename",$A$1),LEN(CELL("filename",$A$1))-FIND("]",CELL("filename",$A$1)))&$B92,[2]要員計画!$L:$AJ,((COLUMN()-1)/4)+1,FALSE)),0,VLOOKUP(RIGHT(CELL("filename",$A$1),LEN(CELL("filename",$A$1))-FIND("]",CELL("filename",$A$1)))&$B92,[2]要員計画!$L:$AJ,((COLUMN()-1)/4)+1,FALSE)) -> 0 | J92: =IF(ISERROR(VLOOKUP(RIGHT(CELL("filename",$A$1),LEN(CELL("filename",$A$1))-FIND("]",CELL("filename",$A$1)))&$B92,[2]要員計画!$L:$AJ,((COLUMN()-1)/4)+1,FALSE)),0,VLOOKUP(RIGHT(CELL("filename",$A$1),LEN(CELL("filename",$A$1))-FIND("]",CELL("filename",$A$1)))&$B92,[2]要員計画!$L:$AJ,((COLUMN()-1)/4)+1,FALSE)) -> 0 | N92: =IF(ISERROR(VLOOKUP(RIGHT(CELL("filename",$A$1),LEN(CELL("filename",$A$1))-FIND("]",CELL("filename",$A$1)))&$B92,[2]要員計画!$L:$AJ,((COLUMN()-1)/4)+1,FALSE)),0,VLOOKUP(RIGHT(CELL("filename",$A$1),LEN(CELL("filename",$A$1))-FIND("]",CELL("filename",$A$1)))&$B92,[2]要員計画!$L:$AJ,((COLUMN()-1)/4)+1,FALSE)) -> 0 | R92: =IF(ISERROR(VLOOKUP(RIGHT(CELL("filename",$A$1),LEN(CELL("filename",$A$1))-FIND("]",CELL("filename",$A$1)))&$B92,[2]要員計画!$L:$AJ,((COLUMN()-1)/4)+1,FALSE)),0,VLOOKUP(RIGHT(CELL("filename",$A$1),LEN(CELL("filename",$A$1))-FIND("]",CELL("filename",$A$1)))&$B92,[2]要員計画!$L:$AJ,((COLUMN()-1)/4)+1,FALSE)) -> 0 | V92: =IF(ISERROR(VLOOKUP(RIGHT(CELL("filename",$A$1),LEN(CELL("filename",$A$1))-FIND("]",CELL("filename",$A$1)))&$B92,[2]要員計画!$L:$AJ,((COLUMN()-1)/4)+1,FALSE)),0,VLOOKUP(RIGHT(CELL("filename",$A$1),LEN(CELL("filename",$A$1))-FIND("]",CELL("filename",$A$1)))&$B92,[2]要員計画!$L:$AJ,((COLUMN()-1)/4)+1,FALSE)) -> 0 | Z92: =IF(ISERROR(VLOOKUP(RIGHT(CELL("filename",$A$1),LEN(CELL("filename",$A$1))-FIND("]",CELL("filename",$A$1)))&$B92,[2]要員計画!$L:$AJ,((COLUMN()-1)/4)+1,FALSE)),0,VLOOKUP(RIGHT(CELL("filename",$A$1),LEN(CELL("filename",$A$1))-FIND("]",CELL("filename",$A$1)))&$B92,[2]要員計画!$L:$AJ,((COLUMN()-1)/4)+1,FALSE)) -> 0 | DR92: =IF(ISERROR(VLOOKUP(RIGHT(CELL("filename",$A$1),LEN(CELL("filename",$A$1))-FIND("]",CELL("filename",$A$1)))&$B92,[2]要員計画!$L:$AJ,((COLUMN()-1)/4)+1,FALSE)),0,VLOOKUP(RIGHT(CELL("filename",$A$1),LEN(CELL("filename",$A$1))-FIND("]",CELL("filename",$A$1)))&$B92,[2]要員計画!$L:$AJ,((COLUMN()-1)/4)+1,FALSE)) -> 0 | DV92: =IF(ISERROR(VLOOKUP(RIGHT(CELL("filename",$A$1),LEN(CELL("filename",$A$1))-FIND("]",CELL("filename",$A$1)))&$B92,[2]要員計画!$L:$AJ,((COLUMN()-1)/4)+1,FALSE)),0,VLOOKUP(RIGHT(CELL("filename",$A$1),LEN(CELL("filename",$A$1))-FIND("]",CELL("filename",$A$1)))&$B92,[2]要員計画!$L:$AJ,((COLUMN()-1)/4)+1,FALSE)) -> 0 | DZ92: =IF(ISERROR(VLOOKUP(RIGHT(CELL("filename",$A$1),LEN(CELL("filename",$A$1))-FIND("]",CELL("filename",$A$1)))&$B92,[2]要員計画!$L:$AJ,((COLUMN()-1)/4)+1,FALSE)),0,VLOOKUP(RIGHT(CELL("filename",$A$1),LEN(CELL("filename",$A$1))-FIND("]",CELL("filename",$A$1)))&$B92,[2]要員計画!$L:$AJ,((COLUMN()-1)/4)+1,FALSE)) -> 0 | ED92: =IF(ISERROR(VLOOKUP(RIGHT(CELL("filename",$A$1),LEN(CELL("filename",$A$1))-FIND("]",CELL("filename",$A$1)))&$B92,[2]要員計画!$L:$AJ,((COLUMN()-1)/4)+1,FALSE)),0,VLOOKUP(RIGHT(CELL("filename",$A$1),LEN(CELL("filename",$A$1))-FIND("]",CELL("filename",$A$1)))&$B92,[2]要員計画!$L:$AJ,((COLUMN()-1)/4)+1,FALSE)) -> 0 | EH92: =IF(ISERROR(VLOOKUP(RIGHT(CELL("filename",$A$1),LEN(CELL("filename",$A$1))-FIND("]",CELL("filename",$A$1)))&$B92,[2]要員計画!$L:$AJ,((COLUMN()-1)/4)+1,FALSE)),0,VLOOKUP(RIGHT(CELL("filename",$A$1),LEN(CELL("filename",$A$1))-FIND("]",CELL("filename",$A$1)))&$B92,[2]要員計画!$L:$AJ,((COLUMN()-1)/4)+1,FALSE)) -> 0 | EL92: =IF(ISERROR(VLOOKUP(RIGHT(CELL("filename",$A$1),LEN(CELL("filename",$A$1))-FIND("]",CELL("filename",$A$1)))&$B92,[2]要員計画!$L:$AJ,((COLUMN()-1)/4)+1,FALSE)),0,VLOOKUP(RIGHT(CELL("filename",$A$1),LEN(CELL("filename",$A$1))-FIND("]",CELL("filename",$A$1)))&$B92,[2]要員計画!$L:$AJ,((COLUMN()-1)/4)+1,FALSE)) -> 0 | EP92: =IF(ISERROR(VLOOKUP(RIGHT(CELL("filename",$A$1),LEN(CELL("filename",$A$1))-FIND("]",CELL("filename",$A$1)))&$B92,[2]要員計画!$L:$AJ,((COLUMN()-1)/4)+1,FALSE)),0,VLOOKUP(RIGHT(CELL("filename",$A$1),LEN(CELL("filename",$A$1))-FIND("]",CELL("filename",$A$1)))&$B92,[2]要員計画!$L:$AJ,((COLUMN()-1)/4)+1,FALSE)) -> 0
C93: 1000000 | D93: 売上金額 | E93: =SUM(F93:CW93) -> 0 | F93: =IFERROR($C93*F92,"") -> 0 | J93: =IFERROR($C93*J92,"") -> 0 | N93: =IFERROR($C93*N92,"") -> 0 | R93: =IFERROR($C93*R92,"") -> 0 | V93: =IFERROR($C93*V92,"") -> 0 | Z93: =IFERROR($C93*Z92,"") -> 0 | DR93: =IFERROR($C93*DR92,"") -> 0 | DV93: =IFERROR($C93*DV92,"") -> 0 | DZ93: =IFERROR($C93*DZ92,"") -> 0 | ED93: =IFERROR($C93*ED92,"") -> 0 | EH93: =IFERROR($C93*EH92,"") -> 0 | EL93: =IFERROR($C93*EL92,"") -> 0 | EP93: =IFERROR($C93*EP92,"") -> 0
C94: 850000 | D94: 原価金額 | E94: =SUM(F94:CW94) -> 0 | F94: =IFERROR($C94*F92,"") -> 0 | J94: =IFERROR($C94*J92,"") -> 0 | N94: =IFERROR($C94*N92,"") -> 0 | R94: =IFERROR($C94*R92,"") -> 0 | V94: =IFERROR($C94*V92,"") -> 0 | Z94: =IFERROR($C94*Z92,"") -> 0 | DR94: =IFERROR($C94*DR92,"") -> 0 | DV94: =IFERROR($C94*DV92,"") -> 0 | DZ94: =IFERROR($C94*DZ92,"") -> 0 | ED94: =IFERROR($C94*ED92,"") -> 0 | EH94: =IFERROR($C94*EH92,"") -> 0 | EL94: =IFERROR($C94*EL92,"") -> 0 | EP94: =IFERROR($C94*EP92,"") -> 0
B95: 11 | D95: 工数 | E95: =SUM(F95:ES95) -> 0 | F95: =IF(ISERROR(VLOOKUP(RIGHT(CELL("filename",$A$1),LEN(CELL("filename",$A$1))-FIND("]",CELL("filename",$A$1)))&$B95,[2]要員計画!$L:$AJ,((COLUMN()-1)/4)+1,FALSE)),0,VLOOKUP(RIGHT(CELL("filename",$A$1),LEN(CELL("filename",$A$1))-FIND("]",CELL("filename",$A$1)))&$B95,[2]要員計画!$L:$AJ,((COLUMN()-1)/4)+1,FALSE)) -> 0 | J95: =IF(ISERROR(VLOOKUP(RIGHT(CELL("filename",$A$1),LEN(CELL("filename",$A$1))-FIND("]",CELL("filename",$A$1)))&$B95,[2]要員計画!$L:$AJ,((COLUMN()-1)/4)+1,FALSE)),0,VLOOKUP(RIGHT(CELL("filename",$A$1),LEN(CELL("filename",$A$1))-FIND("]",CELL("filename",$A$1)))&$B95,[2]要員計画!$L:$AJ,((COLUMN()-1)/4)+1,FALSE)) -> 0 | N95: =IF(ISERROR(VLOOKUP(RIGHT(CELL("filename",$A$1),LEN(CELL("filename",$A$1))-FIND("]",CELL("filename",$A$1)))&$B95,[2]要員計画!$L:$AJ,((COLUMN()-1)/4)+1,FALSE)),0,VLOOKUP(RIGHT(CELL("filename",$A$1),LEN(CELL("filename",$A$1))-FIND("]",CELL("filename",$A$1)))&$B95,[2]要員計画!$L:$AJ,((COLUMN()-1)/4)+1,FALSE)) -> 0 | R95: =IF(ISERROR(VLOOKUP(RIGHT(CELL("filename",$A$1),LEN(CELL("filename",$A$1))-FIND("]",CELL("filename",$A$1)))&$B95,[2]要員計画!$L:$AJ,((COLUMN()-1)/4)+1,FALSE)),0,VLOOKUP(RIGHT(CELL("filename",$A$1),LEN(CELL("filename",$A$1))-FIND("]",CELL("filename",$A$1)))&$B95,[2]要員計画!$L:$AJ,((COLUMN()-1)/4)+1,FALSE)) -> 0 | V95: =IF(ISERROR(VLOOKUP(RIGHT(CELL("filename",$A$1),LEN(CELL("filename",$A$1))-FIND("]",CELL("filename",$A$1)))&$B95,[2]要員計画!$L:$AJ,((COLUMN()-1)/4)+1,FALSE)),0,VLOOKUP(RIGHT(CELL("filename",$A$1),LEN(CELL("filename",$A$1))-FIND("]",CELL("filename",$A$1)))&$B95,[2]要員計画!$L:$AJ,((COLUMN()-1)/4)+1,FALSE)) -> 0 | Z95: =IF(ISERROR(VLOOKUP(RIGHT(CELL("filename",$A$1),LEN(CELL("filename",$A$1))-FIND("]",CELL("filename",$A$1)))&$B95,[2]要員計画!$L:$AJ,((COLUMN()-1)/4)+1,FALSE)),0,VLOOKUP(RIGHT(CELL("filename",$A$1),LEN(CELL("filename",$A$1))-FIND("]",CELL("filename",$A$1)))&$B95,[2]要員計画!$L:$AJ,((COLUMN()-1)/4)+1,FALSE)) -> 0 | DR95: =IF(ISERROR(VLOOKUP(RIGHT(CELL("filename",$A$1),LEN(CELL("filename",$A$1))-FIND("]",CELL("filename",$A$1)))&$B95,[2]要員計画!$L:$AJ,((COLUMN()-1)/4)+1,FALSE)),0,VLOOKUP(RIGHT(CELL("filename",$A$1),LEN(CELL("filename",$A$1))-FIND("]",CELL("filename",$A$1)))&$B95,[2]要員計画!$L:$AJ,((COLUMN()-1)/4)+1,FALSE)) -> 0 | DV95: =IF(ISERROR(VLOOKUP(RIGHT(CELL("filename",$A$1),LEN(CELL("filename",$A$1))-FIND("]",CELL("filename",$A$1)))&$B95,[2]要員計画!$L:$AJ,((COLUMN()-1)/4)+1,FALSE)),0,VLOOKUP(RIGHT(CELL("filename",$A$1),LEN(CELL("filename",$A$1))-FIND("]",CELL("filename",$A$1)))&$B95,[2]要員計画!$L:$AJ,((COLUMN()-1)/4)+1,FALSE)) -> 0 | DZ95: =IF(ISERROR(VLOOKUP(RIGHT(CELL("filename",$A$1),LEN(CELL("filename",$A$1))-FIND("]",CELL("filename",$A$1)))&$B95,[2]要員計画!$L:$AJ,((COLUMN()-1)/4)+1,FALSE)),0,VLOOKUP(RIGHT(CELL("filename",$A$1),LEN(CELL("filename",$A$1))-FIND("]",CELL("filename",$A$1)))&$B95,[2]要員計画!$L:$AJ,((COLUMN()-1)/4)+1,FALSE)) -> 0 | ED95: =IF(ISERROR(VLOOKUP(RIGHT(CELL("filename",$A$1),LEN(CELL("filename",$A$1))-FIND("]",CELL("filename",$A$1)))&$B95,[2]要員計画!$L:$AJ,((COLUMN()-1)/4)+1,FALSE)),0,VLOOKUP(RIGHT(CELL("filename",$A$1),LEN(CELL("filename",$A$1))-FIND("]",CELL("filename",$A$1)))&$B95,[2]要員計画!$L:$AJ,((COLUMN()-1)/4)+1,FALSE)) -> 0 | EH95: =IF(ISERROR(VLOOKUP(RIGHT(CELL("filename",$A$1),LEN(CELL("filename",$A$1))-FIND("]",CELL("filename",$A$1)))&$B95,[2]要員計画!$L:$AJ,((COLUMN()-1)/4)+1,FALSE)),0,VLOOKUP(RIGHT(CELL("filename",$A$1),LEN(CELL("filename",$A$1))-FIND("]",CELL("filename",$A$1)))&$B95,[2]要員計画!$L:$AJ,((COLUMN()-1)/4)+1,FALSE)) -> 0 | EL95: =IF(ISERROR(VLOOKUP(RIGHT(CELL("filename",$A$1),LEN(CELL("filename",$A$1))-FIND("]",CELL("filename",$A$1)))&$B95,[2]要員計画!$L:$AJ,((COLUMN()-1)/4)+1,FALSE)),0,VLOOKUP(RIGHT(CELL("filename",$A$1),LEN(CELL("filename",$A$1))-FIND("]",CELL("filename",$A$1)))&$B95,[2]要員計画!$L:$AJ,((COLUMN()-1)/4)+1,FALSE)) -> 0 | EP95: =IF(ISERROR(VLOOKUP(RIGHT(CELL("filename",$A$1),LEN(CELL("filename",$A$1))-FIND("]",CELL("filename",$A$1)))&$B95,[2]要員計画!$L:$AJ,((COLUMN()-1)/4)+1,FALSE)),0,VLOOKUP(RIGHT(CELL("filename",$A$1),LEN(CELL("filename",$A$1))-FIND("]",CELL("filename",$A$1)))&$B95,[2]要員計画!$L:$AJ,((COLUMN()-1)/4)+1,FALSE)) -> 0
C96: 1000000 | D96: 売上金額 | E96: =SUM(F96:CW96) -> 0 | F96: =IFERROR($C96*F95,"") -> 0 | J96: =IFERROR($C96*J95,"") -> 0 | N96: =IFERROR($C96*N95,"") -> 0 | R96: =IFERROR($C96*R95,"") -> 0 | V96: =IFERROR($C96*V95,"") -> 0 | Z96: =IFERROR($C96*Z95,"") -> 0 | DR96: =IFERROR($C96*DR95,"") -> 0 | DV96: =IFERROR($C96*DV95,"") -> 0 | DZ96: =IFERROR($C96*DZ95,"") -> 0 | ED96: =IFERROR($C96*ED95,"") -> 0 | EH96: =IFERROR($C96*EH95,"") -> 0 | EL96: =IFERROR($C96*EL95,"") -> 0 | EP96: =IFERROR($C96*EP95,"") -> 0
C97: 850000 | D97: 原価金額 | E97: =SUM(F97:CW97) -> 0 | F97: =IFERROR($C97*F95,"") -> 0 | J97: =IFERROR($C97*J95,"") -> 0 | N97: =IFERROR($C97*N95,"") -> 0 | R97: =IFERROR($C97*R95,"") -> 0 | V97: =IFERROR($C97*V95,"") -> 0 | Z97: =IFERROR($C97*Z95,"") -> 0 | DR97: =IFERROR($C97*DR95,"") -> 0 | DV97: =IFERROR($C97*DV95,"") -> 0 | DZ97: =IFERROR($C97*DZ95,"") -> 0 | ED97: =IFERROR($C97*ED95,"") -> 0 | EH97: =IFERROR($C97*EH95,"") -> 0 | EL97: =IFERROR($C97*EL95,"") -> 0 | EP97: =IFERROR($C97*EP95,"") -> 0
B98: 12 | D98: 工数 | E98: =SUM(F98:ES98) -> 0 | F98: =IF(ISERROR(VLOOKUP(RIGHT(CELL("filename",$A$1),LEN(CELL("filename",$A$1))-FIND("]",CELL("filename",$A$1)))&$B98,[2]要員計画!$L:$AJ,((COLUMN()-1)/4)+1,FALSE)),0,VLOOKUP(RIGHT(CELL("filename",$A$1),LEN(CELL("filename",$A$1))-FIND("]",CELL("filename",$A$1)))&$B98,[2]要員計画!$L:$AJ,((COLUMN()-1)/4)+1,FALSE)) -> 0 | J98: =IF(ISERROR(VLOOKUP(RIGHT(CELL("filename",$A$1),LEN(CELL("filename",$A$1))-FIND("]",CELL("filename",$A$1)))&$B98,[2]要員計画!$L:$AJ,((COLUMN()-1)/4)+1,FALSE)),0,VLOOKUP(RIGHT(CELL("filename",$A$1),LEN(CELL("filename",$A$1))-FIND("]",CELL("filename",$A$1)))&$B98,[2]要員計画!$L:$AJ,((COLUMN()-1)/4)+1,FALSE)) -> 0 | N98: =IF(ISERROR(VLOOKUP(RIGHT(CELL("filename",$A$1),LEN(CELL("filename",$A$1))-FIND("]",CELL("filename",$A$1)))&$B98,[2]要員計画!$L:$AJ,((COLUMN()-1)/4)+1,FALSE)),0,VLOOKUP(RIGHT(CELL("filename",$A$1),LEN(CELL("filename",$A$1))-FIND("]",CELL("filename",$A$1)))&$B98,[2]要員計画!$L:$AJ,((COLUMN()-1)/4)+1,FALSE)) -> 0 | R98: =IF(ISERROR(VLOOKUP(RIGHT(CELL("filename",$A$1),LEN(CELL("filename",$A$1))-FIND("]",CELL("filename",$A$1)))&$B98,[2]要員計画!$L:$AJ,((COLUMN()-1)/4)+1,FALSE)),0,VLOOKUP(RIGHT(CELL("filename",$A$1),LEN(CELL("filename",$A$1))-FIND("]",CELL("filename",$A$1)))&$B98,[2]要員計画!$L:$AJ,((COLUMN()-1)/4)+1,FALSE)) -> 0 | V98: =IF(ISERROR(VLOOKUP(RIGHT(CELL("filename",$A$1),LEN(CELL("filename",$A$1))-FIND("]",CELL("filename",$A$1)))&$B98,[2]要員計画!$L:$AJ,((COLUMN()-1)/4)+1,FALSE)),0,VLOOKUP(RIGHT(CELL("filename",$A$1),LEN(CELL("filename",$A$1))-FIND("]",CELL("filename",$A$1)))&$B98,[2]要員計画!$L:$AJ,((COLUMN()-1)/4)+1,FALSE)) -> 0 | Z98: =IF(ISERROR(VLOOKUP(RIGHT(CELL("filename",$A$1),LEN(CELL("filename",$A$1))-FIND("]",CELL("filename",$A$1)))&$B98,[2]要員計画!$L:$AJ,((COLUMN()-1)/4)+1,FALSE)),0,VLOOKUP(RIGHT(CELL("filename",$A$1),LEN(CELL("filename",$A$1))-FIND("]",CELL("filename",$A$1)))&$B98,[2]要員計画!$L:$AJ,((COLUMN()-1)/4)+1,FALSE)) -> 0 | AD98: =IF(ISERROR(VLOOKUP(RIGHT(CELL("filename",$A$1),LEN(CELL("filename",$A$1))-FIND("]",CELL("filename",$A$1)))&$B98,[2]要員計画!$L:$AJ,((COLUMN()-1)/4)+1,FALSE)),0,VLOOKUP(RIGHT(CELL("filename",$A$1),LEN(CELL("filename",$A$1))-FIND("]",CELL("filename",$A$1)))&$B98,[2]要員計画!$L:$AJ,((COLUMN()-1)/4)+1,FALSE)) -> 0 | DR98: =IF(ISERROR(VLOOKUP(RIGHT(CELL("filename",$A$1),LEN(CELL("filename",$A$1))-FIND("]",CELL("filename",$A$1)))&$B98,[2]要員計画!$L:$AJ,((COLUMN()-1)/4)+1,FALSE)),0,VLOOKUP(RIGHT(CELL("filename",$A$1),LEN(CELL("filename",$A$1))-FIND("]",CELL("filename",$A$1)))&$B98,[2]要員計画!$L:$AJ,((COLUMN()-1)/4)+1,FALSE)) -> 0 | DV98: =IF(ISERROR(VLOOKUP(RIGHT(CELL("filename",$A$1),LEN(CELL("filename",$A$1))-FIND("]",CELL("filename",$A$1)))&$B98,[2]要員計画!$L:$AJ,((COLUMN()-1)/4)+1,FALSE)),0,VLOOKUP(RIGHT(CELL("filename",$A$1),LEN(CELL("filename",$A$1))-FIND("]",CELL("filename",$A$1)))&$B98,[2]要員計画!$L:$AJ,((COLUMN()-1)/4)+1,FALSE)) -> 0 | DZ98: =IF(ISERROR(VLOOKUP(RIGHT(CELL("filename",$A$1),LEN(CELL("filename",$A$1))-FIND("]",CELL("filename",$A$1)))&$B98,[2]要員計画!$L:$AJ,((COLUMN()-1)/4)+1,FALSE)),0,VLOOKUP(RIGHT(CELL("filename",$A$1),LEN(CELL("filename",$A$1))-FIND("]",CELL("filename",$A$1)))&$B98,[2]要員計画!$L:$AJ,((COLUMN()-1)/4)+1,FALSE)) -> 0 | ED98: =IF(ISERROR(VLOOKUP(RIGHT(CELL("filename",$A$1),LEN(CELL("filename",$A$1))-FIND("]",CELL("filename",$A$1)))&$B98,[2]要員計画!$L:$AJ,((COLUMN()-1)/4)+1,FALSE)),0,VLOOKUP(RIGHT(CELL("filename",$A$1),LEN(CELL("filename",$A$1))-FIND("]",CELL("filename",$A$1)))&$B98,[2]要員計画!$L:$AJ,((COLUMN()-1)/4)+1,FALSE)) -> 0 | EH98: =IF(ISERROR(VLOOKUP(RIGHT(CELL("filename",$A$1),LEN(CELL("filename",$A$1))-FIND("]",CELL("filename",$A$1)))&$B98,[2]要員計画!$L:$AJ,((COLUMN()-1)/4)+1,FALSE)),0,VLOOKUP(RIGHT(CELL("filename",$A$1),LEN(CELL("filename",$A$1))-FIND("]",CELL("filename",$A$1)))&$B98,[2]要員計画!$L:$AJ,((COLUMN()-1)/4)+1,FALSE)) -> 0 | EL98: =IF(ISERROR(VLOOKUP(RIGHT(CELL("filename",$A$1),LEN(CELL("filename",$A$1))-FIND("]",CELL("filename",$A$1)))&$B98,[2]要員計画!$L:$AJ,((COLUMN()-1)/4)+1,FALSE)),0,VLOOKUP(RIGHT(CELL("filename",$A$1),LEN(CELL("filename",$A$1))-FIND("]",CELL("filename",$A$1)))&$B98,[2]要員計画!$L:$AJ,((COLUMN()-1)/4)+1,FALSE)) -> 0 | EP98: =IF(ISERROR(VLOOKUP(RIGHT(CELL("filename",$A$1),LEN(CELL("filename",$A$1))-FIND("]",CELL("filename",$A$1)))&$B98,[2]要員計画!$L:$AJ,((COLUMN()-1)/4)+1,FALSE)),0,VLOOKUP(RIGHT(CELL("filename",$A$1),LEN(CELL("filename",$A$1))-FIND("]",CELL("filename",$A$1)))&$B98,[2]要員計画!$L:$AJ,((COLUMN()-1)/4)+1,FALSE)) -> 0
C99: 1000000 | D99: 売上金額 | E99: =SUM(F99:CW99) -> 0 | F99: =IFERROR($C99*F98,"") -> 0 | J99: =IFERROR($C99*J98,"") -> 0 | N99: =IFERROR($C99*N98,"") -> 0 | R99: =IFERROR($C99*R98,"") -> 0 | V99: =IFERROR($C99*V98,"") -> 0 | Z99: =IFERROR($C99*Z98,"") -> 0 | AD99: =IFERROR($C99*AD98,"") -> 0 | AH99: =IFERROR($C99*AH98,"") -> 0 | AL99: =IFERROR($C99*AL98,"") -> 0 | AP99: =IFERROR($C99*AP98,"") -> 0 | AT99: =IFERROR($C99*AT98,"") -> 0 | AX99: =IFERROR($C99*AX98,"") -> 0 | BB99: =IFERROR($C99*BB98,"") -> 0 | BF99: =IFERROR($C99*BF98,"") -> 0 | BJ99: =IFERROR($C99*BJ98,"") -> 0 | BN99: =IFERROR($C99*BN98,"") -> 0 | BR99: =IFERROR($C99*BR98,"") -> 0 | BV99: =IFERROR($C99*BV98,"") -> 0 | BZ99: =IFERROR($C99*BZ98,"") -> 0 | CD99: =IFERROR($C99*CD98,"") -> 0 | CH99: =IFERROR($C99*CH98,"") -> 0 | CL99: =IFERROR($C99*CL98,"") -> 0 | CP99: =IFERROR($C99*CP98,"") -> 0 | CT99: =IFERROR($C99*CT98,"") -> 0 | CX99: =IFERROR($C99*CX98,"") -> 0 | DB99: =IFERROR($C99*DB98,"") -> 0 | DF99: =IFERROR($C99*DF98,"") -> 0 | DJ99: =IFERROR($C99*DJ98,"") -> 0 | DN99: =IFERROR($C99*DN98,"") -> 0 | DR99: =IFERROR($C99*DR98,"") -> 0 | DV99: =IFERROR($C99*DV98,"") -> 0 | DZ99: =IFERROR($C99*DZ98,"") -> 0 | ED99: =IFERROR($C99*ED98,"") -> 0 | EH99: =IFERROR($C99*EH98,"") -> 0 | EL99: =IFERROR($C99*EL98,"") -> 0 | EP99: =IFERROR($C99*EP98,"") -> 0
C100: 850000 | D100: 原価金額 | E100: =SUM(F100:CW100) -> 0 | F100: =IFERROR($C100*F98,"") -> 0 | J100: =IFERROR($C100*J98,"") -> 0 | N100: =IFERROR($C100*N98,"") -> 0 | R100: =IFERROR($C100*R98,"") -> 0 | V100: =IFERROR($C100*V98,"") -> 0 | Z100: =IFERROR($C100*Z98,"") -> 0 | AD100: =IFERROR($C100*AD98,"") -> 0 | AH100: =IFERROR($C100*AH98,"") -> 0 | AL100: =IFERROR($C100*AL98,"") -> 0 | AP100: =IFERROR($C100*AP98,"") -> 0 | AT100: =IFERROR($C100*AT98,"") -> 0 | AX100: =IFERROR($C100*AX98,"") -> 0 | BB100: =IFERROR($C100*BB98,"") -> 0 | BF100: =IFERROR($C100*BF98,"") -> 0 | BJ100: =IFERROR($C100*BJ98,"") -> 0 | BN100: =IFERROR($C100*BN98,"") -> 0 | BR100: =IFERROR($C100*BR98,"") -> 0 | BV100: =IFERROR($C100*BV98,"") -> 0 | BZ100: =IFERROR($C100*BZ98,"") -> 0 | CD100: =IFERROR($C100*CD98,"") -> 0 | CH100: =IFERROR($C100*CH98,"") -> 0 | CL100: =IFERROR($C100*CL98,"") -> 0 | CP100: =IFERROR($C100*CP98,"") -> 0 | CT100: =IFERROR($C100*CT98,"") -> 0 | CX100: =IFERROR($C100*CX98,"") -> 0 | DB100: =IFERROR($C100*DB98,"") -> 0 | DF100: =IFERROR($C100*DF98,"") -> 0 | DJ100: =IFERROR($C100*DJ98,"") -> 0 | DN100: =IFERROR($C100*DN98,"") -> 0 | DR100: =IFERROR($C100*DR98,"") -> 0 | DV100: =IFERROR($C100*DV98,"") -> 0 | DZ100: =IFERROR($C100*DZ98,"") -> 0 | ED100: =IFERROR($C100*ED98,"") -> 0 | EH100: =IFERROR($C100*EH98,"") -> 0 | EL100: =IFERROR($C100*EL98,"") -> 0 | EP100: =IFERROR($C100*EP98,"") -> 0
B101: 13 | D101: 工数 | E101: =SUM(F101:ES101) -> 0 | F101: =IF(ISERROR(VLOOKUP(RIGHT(CELL("filename",$A$1),LEN(CELL("filename",$A$1))-FIND("]",CELL("filename",$A$1)))&$B101,[2]要員計画!$L:$AJ,((COLUMN()-1)/4)+1,FALSE)),0,VLOOKUP(RIGHT(CELL("filename",$A$1),LEN(CELL("filename",$A$1))-FIND("]",CELL("filename",$A$1)))&$B101,[2]要員計画!$L:$AJ,((COLUMN()-1)/4)+1,FALSE)) -> 0 | J101: =IF(ISERROR(VLOOKUP(RIGHT(CELL("filename",$A$1),LEN(CELL("filename",$A$1))-FIND("]",CELL("filename",$A$1)))&$B101,[2]要員計画!$L:$AJ,((COLUMN()-1)/4)+1,FALSE)),0,VLOOKUP(RIGHT(CELL("filename",$A$1),LEN(CELL("filename",$A$1))-FIND("]",CELL("filename",$A$1)))&$B101,[2]要員計画!$L:$AJ,((COLUMN()-1)/4)+1,FALSE)) -> 0 | N101: =IF(ISERROR(VLOOKUP(RIGHT(CELL("filename",$A$1),LEN(CELL("filename",$A$1))-FIND("]",CELL("filename",$A$1)))&$B101,[2]要員計画!$L:$AJ,((COLUMN()-1)/4)+1,FALSE)),0,VLOOKUP(RIGHT(CELL("filename",$A$1),LEN(CELL("filename",$A$1))-FIND("]",CELL("filename",$A$1)))&$B101,[2]要員計画!$L:$AJ,((COLUMN()-1)/4)+1,FALSE)) -> 0 | R101: =IF(ISERROR(VLOOKUP(RIGHT(CELL("filename",$A$1),LEN(CELL("filename",$A$1))-FIND("]",CELL("filename",$A$1)))&$B101,[2]要員計画!$L:$AJ,((COLUMN()-1)/4)+1,FALSE)),0,VLOOKUP(RIGHT(CELL("filename",$A$1),LEN(CELL("filename",$A$1))-FIND("]",CELL("filename",$A$1)))&$B101,[2]要員計画!$L:$AJ,((COLUMN()-1)/4)+1,FALSE)) -> 0 | V101: =IF(ISERROR(VLOOKUP(RIGHT(CELL("filename",$A$1),LEN(CELL("filename",$A$1))-FIND("]",CELL("filename",$A$1)))&$B101,[2]要員計画!$L:$AJ,((COLUMN()-1)/4)+1,FALSE)),0,VLOOKUP(RIGHT(CELL("filename",$A$1),LEN(CELL("filename",$A$1))-FIND("]",CELL("filename",$A$1)))&$B101,[2]要員計画!$L:$AJ,((COLUMN()-1)/4)+1,FALSE)) -> 0 | Z101: =IF(ISERROR(VLOOKUP(RIGHT(CELL("filename",$A$1),LEN(CELL("filename",$A$1))-FIND("]",CELL("filename",$A$1)))&$B101,[2]要員計画!$L:$AJ,((COLUMN()-1)/4)+1,FALSE)),0,VLOOKUP(RIGHT(CELL("filename",$A$1),LEN(CELL("filename",$A$1))-FIND("]",CELL("filename",$A$1)))&$B101,[2]要員計画!$L:$AJ,((COLUMN()-1)/4)+1,FALSE)) -> 0 | AD101: =IF(ISERROR(VLOOKUP(RIGHT(CELL("filename",$A$1),LEN(CELL("filename",$A$1))-FIND("]",CELL("filename",$A$1)))&$B101,[2]要員計画!$L:$AJ,((COLUMN()-1)/4)+1,FALSE)),0,VLOOKUP(RIGHT(CELL("filename",$A$1),LEN(CELL("filename",$A$1))-FIND("]",CELL("filename",$A$1)))&$B101,[2]要員計画!$L:$AJ,((COLUMN()-1)/4)+1,FALSE)) -> 0 | DR101: =IF(ISERROR(VLOOKUP(RIGHT(CELL("filename",$A$1),LEN(CELL("filename",$A$1))-FIND("]",CELL("filename",$A$1)))&$B101,[2]要員計画!$L:$AJ,((COLUMN()-1)/4)+1,FALSE)),0,VLOOKUP(RIGHT(CELL("filename",$A$1),LEN(CELL("filename",$A$1))-FIND("]",CELL("filename",$A$1)))&$B101,[2]要員計画!$L:$AJ,((COLUMN()-1)/4)+1,FALSE)) -> 0 | DV101: =IF(ISERROR(VLOOKUP(RIGHT(CELL("filename",$A$1),LEN(CELL("filename",$A$1))-FIND("]",CELL("filename",$A$1)))&$B101,[2]要員計画!$L:$AJ,((COLUMN()-1)/4)+1,FALSE)),0,VLOOKUP(RIGHT(CELL("filename",$A$1),LEN(CELL("filename",$A$1))-FIND("]",CELL("filename",$A$1)))&$B101,[2]要員計画!$L:$AJ,((COLUMN()-1)/4)+1,FALSE)) -> 0 | DZ101: =IF(ISERROR(VLOOKUP(RIGHT(CELL("filename",$A$1),LEN(CELL("filename",$A$1))-FIND("]",CELL("filename",$A$1)))&$B101,[2]要員計画!$L:$AJ,((COLUMN()-1)/4)+1,FALSE)),0,VLOOKUP(RIGHT(CELL("filename",$A$1),LEN(CELL("filename",$A$1))-FIND("]",CELL("filename",$A$1)))&$B101,[2]要員計画!$L:$AJ,((COLUMN()-1)/4)+1,FALSE)) -> 0 | ED101: =IF(ISERROR(VLOOKUP(RIGHT(CELL("filename",$A$1),LEN(CELL("filename",$A$1))-FIND("]",CELL("filename",$A$1)))&$B101,[2]要員計画!$L:$AJ,((COLUMN()-1)/4)+1,FALSE)),0,VLOOKUP(RIGHT(CELL("filename",$A$1),LEN(CELL("filename",$A$1))-FIND("]",CELL("filename",$A$1)))&$B101,[2]要員計画!$L:$AJ,((COLUMN()-1)/4)+1,FALSE)) -> 0 | EH101: =IF(ISERROR(VLOOKUP(RIGHT(CELL("filename",$A$1),LEN(CELL("filename",$A$1))-FIND("]",CELL("filename",$A$1)))&$B101,[2]要員計画!$L:$AJ,((COLUMN()-1)/4)+1,FALSE)),0,VLOOKUP(RIGHT(CELL("filename",$A$1),LEN(CELL("filename",$A$1))-FIND("]",CELL("filename",$A$1)))&$B101,[2]要員計画!$L:$AJ,((COLUMN()-1)/4)+1,FALSE)) -> 0 | EL101: =IF(ISERROR(VLOOKUP(RIGHT(CELL("filename",$A$1),LEN(CELL("filename",$A$1))-FIND("]",CELL("filename",$A$1)))&$B101,[2]要員計画!$L:$AJ,((COLUMN()-1)/4)+1,FALSE)),0,VLOOKUP(RIGHT(CELL("filename",$A$1),LEN(CELL("filename",$A$1))-FIND("]",CELL("filename",$A$1)))&$B101,[2]要員計画!$L:$AJ,((COLUMN()-1)/4)+1,FALSE)) -> 0 | EP101: =IF(ISERROR(VLOOKUP(RIGHT(CELL("filename",$A$1),LEN(CELL("filename",$A$1))-FIND("]",CELL("filename",$A$1)))&$B101,[2]要員計画!$L:$AJ,((COLUMN()-1)/4)+1,FALSE)),0,VLOOKUP(RIGHT(CELL("filename",$A$1),LEN(CELL("filename",$A$1))-FIND("]",CELL("filename",$A$1)))&$B101,[2]要員計画!$L:$AJ,((COLUMN()-1)/4)+1,FALSE)) -> 0
C102: 1000000 | D102: 売上金額 | E102: =SUM(F102:CW102) -> 0 | F102: =IFERROR($C102*F101,"") -> 0 | J102: =IFERROR($C102*J101,"") -> 0 | N102: =IFERROR($C102*N101,"") -> 0 | R102: =IFERROR($C102*R101,"") -> 0 | V102: =IFERROR($C102*V101,"") -> 0 | Z102: =IFERROR($C102*Z101,"") -> 0 | AD102: =IFERROR($C102*AD101,"") -> 0 | AH102: =IFERROR($C102*AH101,"") -> 0 | AL102: =IFERROR($C102*AL101,"") -> 0 | AP102: =IFERROR($C102*AP101,"") -> 0 | AT102: =IFERROR($C102*AT101,"") -> 0 | AX102: =IFERROR($C102*AX101,"") -> 0 | BB102: =IFERROR($C102*BB101,"") -> 0 | BF102: =IFERROR($C102*BF101,"") -> 0 | BJ102: =IFERROR($C102*BJ101,"") -> 0 | BN102: =IFERROR($C102*BN101,"") -> 0 | BR102: =IFERROR($C102*BR101,"") -> 0 | BV102: =IFERROR($C102*BV101,"") -> 0 | BZ102: =IFERROR($C102*BZ101,"") -> 0 | CD102: =IFERROR($C102*CD101,"") -> 0 | CH102: =IFERROR($C102*CH101,"") -> 0 | CL102: =IFERROR($C102*CL101,"") -> 0 | CP102: =IFERROR($C102*CP101,"") -> 0 | CT102: =IFERROR($C102*CT101,"") -> 0 | CX102: =IFERROR($C102*CX101,"") -> 0 | DB102: =IFERROR($C102*DB101,"") -> 0 | DF102: =IFERROR($C102*DF101,"") -> 0 | DJ102: =IFERROR($C102*DJ101,"") -> 0 | DN102: =IFERROR($C102*DN101,"") -> 0 | DR102: =IFERROR($C102*DR101,"") -> 0 | DV102: =IFERROR($C102*DV101,"") -> 0 | DZ102: =IFERROR($C102*DZ101,"") -> 0 | ED102: =IFERROR($C102*ED101,"") -> 0 | EH102: =IFERROR($C102*EH101,"") -> 0 | EL102: =IFERROR($C102*EL101,"") -> 0 | EP102: =IFERROR($C102*EP101,"") -> 0
C103: 850000 | D103: 原価金額 | E103: =SUM(F103:CW103) -> 0 | F103: =IFERROR($C103*F101,"") -> 0 | J103: =IFERROR($C103*J101,"") -> 0 | N103: =IFERROR($C103*N101,"") -> 0 | R103: =IFERROR($C103*R101,"") -> 0 | V103: =IFERROR($C103*V101,"") -> 0 | Z103: =IFERROR($C103*Z101,"") -> 0 | AD103: =IFERROR($C103*AD101,"") -> 0 | AH103: =IFERROR($C103*AH101,"") -> 0 | AL103: =IFERROR($C103*AL101,"") -> 0 | AP103: =IFERROR($C103*AP101,"") -> 0 | AT103: =IFERROR($C103*AT101,"") -> 0 | AX103: =IFERROR($C103*AX101,"") -> 0 | BB103: =IFERROR($C103*BB101,"") -> 0 | BF103: =IFERROR($C103*BF101,"") -> 0 | BJ103: =IFERROR($C103*BJ101,"") -> 0 | BN103: =IFERROR($C103*BN101,"") -> 0 | BR103: =IFERROR($C103*BR101,"") -> 0 | BV103: =IFERROR($C103*BV101,"") -> 0 | BZ103: =IFERROR($C103*BZ101,"") -> 0 | CD103: =IFERROR($C103*CD101,"") -> 0 | CH103: =IFERROR($C103*CH101,"") -> 0 | CL103: =IFERROR($C103*CL101,"") -> 0 | CP103: =IFERROR($C103*CP101,"") -> 0 | CT103: =IFERROR($C103*CT101,"") -> 0 | CX103: =IFERROR($C103*CX101,"") -> 0 | DB103: =IFERROR($C103*DB101,"") -> 0 | DF103: =IFERROR($C103*DF101,"") -> 0 | DJ103: =IFERROR($C103*DJ101,"") -> 0 | DN103: =IFERROR($C103*DN101,"") -> 0 | DR103: =IFERROR($C103*DR101,"") -> 0 | DV103: =IFERROR($C103*DV101,"") -> 0 | DZ103: =IFERROR($C103*DZ101,"") -> 0 | ED103: =IFERROR($C103*ED101,"") -> 0 | EH103: =IFERROR($C103*EH101,"") -> 0 | EL103: =IFERROR($C103*EL101,"") -> 0 | EP103: =IFERROR($C103*EP101,"") -> 0
...

Sheet 運転管理(パターン2)
A1: 要員配置計画（運転管理制御システム通信サーバ更新：パターン２）
B2: TOPへ
B3: 受注金額 | C3: 320250000
B4: 売上計上額 | C4: =E13 -> 339412500
B5: 原価金額 | C5: =E14 -> 160455000
B6: 粗利額 | C6: =C3-C5 -> 159795000
B7: 粗利率 | C7: =IF(C3=0,0,C6/C3) -> 0.49896956
F9: 2026年 | BB9: 2027年 | CX9: 2028年
F10: 1Q | R10: 2Q | AD10: 3Q | AP10: 4Q | BB10: 1Q | BN10: 2Q | BZ10: 3Q | CL10: 4Q | CX10: 1Q | DJ10: 2Q | DV10: 3Q | EH10: 4Q
F11: 45017 | J11: 45047 | N11: 45078 | R11: 45108 | V11: 45139 | Z11: 45170 | AD11: 45200 | AH11: 45231 | AL11: 45261 | AP11: 45292 | AT11: 45323 | AX11: 45352 | BB11: 45383 | BF11: 45413 | BJ11: 45444 | BN11: 45474 | BR11: 45505 | BV11: 45536 | BZ11: 45566 | CD11: 45597 | CH11: 45627 | CL11: 45658 | CP11: 45689 | CT11: 45717 | CX11: 45383 | DB11: 45413 | DF11: 45444 | DJ11: 45474 | DN11: 45505 | DR11: 45536 | DV11: 45566 | DZ11: 45597 | ED11: 45627 | EH11: 45658 | EL11: 45689 | EP11: 45717
B12: 総合計 | D12: 工数 | E12: =SUM(F12:ES12) -> 315.75 | F12: =F57+F155 -> 5 | J12: =J57+J155 -> 5 | N12: =N57+N155 -> 9.5 | R12: =R57+R155 -> 9.5 | V12: =V57+V155 -> 10.5 | Z12: =Z57+Z155 -> 19.5 | AD12: =AD57+AD155 -> 24.25 | AH12: =AH57+AH155 -> 22.5 | AL12: =AL57+AL155 -> 22.5 | AP12: =AP57+AP155 -> 22.5 | AT12: =AT57+AT155 -> 22.5 | AX12: =AX57+AX155 -> 22.5 | BB12: =BB57+BB155 -> 24.5 | BF12: =BF57+BF155 -> 24.5 | BJ12: =BJ57+BJ155 -> 19.5 | BN12: =BN57+BN155 -> 19 | BR12: =BR57+BR155 -> 7 | BV12: =BV57+BV155 -> 7 | BZ12: =BZ57+BZ155 -> 7 | CD12: =CD57+CD155 -> 7 | CH12: =CH57+CH155 -> 4.5 | CL12: =CL57+CL155 -> 0 | CP12: =CP57+CP155 -> 0 | CT12: =CT57+CT155 -> 0 | CX12: =CX57+CX155 -> 0 | DB12: =DB57+DB155 -> 0 | DF12: =DF57+DF155 -> 0 | DJ12: =DJ57+DJ155 -> 0 | DN12: =DN57+DN155 -> 0 | DR12: =DR57+DR155 -> 0 | DV12: =DV57+DV155 -> 0 | DZ12: =DZ57+DZ155 -> 0 | ED12: =ED57+ED155 -> 0 | EH12: =EH57+EH155 -> 0 | EL12: =EL57+EL155 -> 0 | EP12: =EP57+EP155 -> 0
D13: 売上金額 | E13: =SUM(F13:ES13) -> 339412500 | F13: =F58+F156 -> 5425000 | J13: =J58+J156 -> 5425000 | N13: =N58+N156 -> 10150000 | R13: =R58+R156 -> 10150000 | V13: =V58+V156 -> 11550000 | Z13: =Z58+Z156 -> 21000000 | AD13: =AD58+AD156 -> 25987500 | AH13: =AH58+AH156 -> 24150000 | AL13: =AL58+AL156 -> 24150000 | AP13: =AP58+AP156 -> 24150000 | AT13: =AT58+AT156 -> 24150000 | AX13: =AX58+AX156 -> 24150000 | BB13: =BB58+BB156 -> 26250000 | BF13: =BF58+BF156 -> 26250000 | BJ13: =BJ58+BJ156 -> 21000000 | BN13: =BN58+BN156 -> 20475000 | BR13: =BR58+BR156 -> 7525000 | BV13: =BV58+BV156 -> 7525000 | BZ13: =BZ58+BZ156 -> 7525000 | CD13: =CD58+CD156 -> 7525000 | CH13: =CH58+CH156 -> 4900000 | CL13: =CL58+CL156 -> 0 | CP13: =CP58+CP156 -> 0 | CT13: =CT58+CT156 -> 0 | CX13: =CX58+CX156 -> 0 | DB13: =DB58+DB156 -> 0 | DF13: =DF58+DF156 -> 0 | DJ13: =DJ58+DJ156 -> 0 | DN13: =DN58+DN156 -> 0 | DR13: =DR58+DR156 -> 0 | DV13: =DV58+DV156 -> 0 | DZ13: =DZ58+DZ156 -> 0 | ED13: =ED58+ED156 -> 0 | EH13: =EH58+EH156 -> 0 | EL13: =EL58+EL156 -> 0 | EP13: =EP58+EP156 -> 0
D14: 原価金額 | E14: =SUM(F14:ES14) -> 160455000 | F14: =F59+F157 -> 2580000 | J14: =J59+J157 -> 2580000 | N14: =N59+N157 -> 5430000 | R14: =R59+R157 -> 5430000 | V14: =V59+V157 -> 6630000 | Z14: =Z59+Z157 -> 9980000 | AD14: =AD59+AD157 -> 11605000 | AH14: =AH59+AH157 -> 10730000 | AL14: =AL59+AL157 -> 10730000 | AP14: =AP59+AP157 -> 10730000 | AT14: =AT59+AT157 -> 10730000 | AX14: =AX59+AX157 -> 10730000 | BB14: =BB59+BB157 -> 11730000 | BF14: =BF59+BF157 -> 11730000 | BJ14: =BJ59+BJ157 -> 9980000 | BN14: =BN59+BN157 -> 9730000 | BR14: =BR59+BR157 -> 4180000 | BV14: =BV59+BV157 -> 4180000 | BZ14: =BZ59+BZ157 -> 4180000 | CD14: =CD59+CD157 -> 4180000 | CH14: =CH59+CH157 -> 2680000 | CL14: =CL59+CL157 -> 0 | CP14: =CP59+CP157 -> 0 | CT14: =CT59+CT157 -> 0 | CX14: =CX59+CX157 -> 0 | DB14: =DB59+DB157 -> 0 | DF14: =DF59+DF157 -> 0 | DJ14: =DJ59+DJ157 -> 0 | DN14: =DN59+DN157 -> 0 | DR14: =DR59+DR157 -> 0 | DV14: =DV59+DV157 -> 0 | DZ14: =DZ59+DZ157 -> 0 | ED14: =ED59+ED157 -> 0 | EH14: =EH59+EH157 -> 0 | EL14: =EL59+EL157 -> 0 | EP14: =EP59+EP157 -> 0
D15: 粗利額 | E15: =SUM(F15:ES15) -> 178957500 | F15: =F13-F14 -> 2845000 | J15: =J13-J14 -> 2845000 | N15: =N13-N14 -> 4720000 | R15: =R13-R14 -> 4720000 | V15: =V13-V14 -> 4920000 | Z15: =Z13-Z14 -> 11020000 | AD15: =AD13-AD14 -> 14382500 | AH15: =AH13-AH14 -> 13420000 | AL15: =AL13-AL14 -> 13420000 | AP15: =AP13-AP14 -> 13420000 | AT15: =AT13-AT14 -> 13420000 | AX15: =AX13-AX14 -> 13420000 | BB15: =BB13-BB14 -> 14520000 | BF15: =BF13-BF14 -> 14520000 | BJ15: =BJ13-BJ14 -> 11020000 | BN15: =BN13-BN14 -> 10745000 | BR15: =BR13-BR14 -> 3345000 | BV15: =BV13-BV14 -> 3345000 | BZ15: =BZ13-BZ14 -> 3345000 | CD15: =CD13-CD14 -> 3345000 | CH15: =CH13-CH14 -> 2220000 | CL15: =CL13-CL14 -> 0 | CP15: =CP13-CP14 -> 0 | CT15: =CT13-CT14 -> 0 | CX15: =CX13-CX14 -> 0 | DB15: =DB13-DB14 -> 0 | DF15: =DF13-DF14 -> 0 | DJ15: =DJ13-DJ14 -> 0 | DN15: =DN13-DN14 -> 0 | DR15: =DR13-DR14 -> 0 | DV15: =DV13-DV14 -> 0 | DZ15: =DZ13-DZ14 -> 0 | ED15: =ED13-ED14 -> 0 | EH15: =EH13-EH14 -> 0 | EL15: =EL13-EL14 -> 0 | EP15: =EP13-EP14 -> 0
A17: 【社員・契約社員】 | C17: ※必要に応じて修正すること。
B18: 要員名 | C18: 月額単価 | D18: 内訳 | E18: 合計 | F18: 2026年 | BB18: 2027年 | CX18: 2028年
F19: 1Q | R19: 2Q | AD19: 3Q | AP19: 4Q | BB19: 1Q | BN19: 2Q | BZ19: 3Q | CL19: 4Q | CX19: 1Q | DJ19: 2Q | DV19: 3Q | EH19: 4Q
C20: (上段:売上、下段:原価) | F20: 45017 | J20: 45047 | N20: 45078 | R20: 45108 | V20: 45139 | Z20: 45170 | AD20: 45200 | AH20: 45231 | AL20: 45261 | AP20: 45292 | AT20: 45323 | AX20: 45352 | BB20: 45383 | BF20: 45413 | BJ20: 45444 | BN20: 45474 | BR20: 45505 | BV20: 45536 | BZ20: 45566 | CD20: 45597 | CH20: 45627 | CL20: 45658 | CP20: 45689 | CT20: 45717 | CX20: 45383 | DB20: 45413 | DF20: 45444 | DJ20: 45474 | DN20: 45505 | DR20: 45536 | DV20: 45566 | DZ20: 45597 | ED20: 45627 | EH20: 45658 | EL20: 45689 | EP20: 45717
B21: 福田 | D21: 工数 | E21: =SUM(F21:ES21) -> 10.5 | F21: 0.5 | J21: 0.5 | N21: 0.5 | R21: 0.5 | V21: 0.5 | Z21: 0.5 | AD21: 0.5 | AH21: 0.5 | AL21: 0.5 | AP21: 0.5 | AT21: 0.5 | AX21: 0.5 | BB21: 0.5 | BF21: 0.5 | BJ21: 0.5 | BN21: 0.5 | BR21: 0.5 | BV21: 0.5 | BZ21: 0.5 | CD21: 0.5 | CH21: 0.5
C22: 1400000 | D22: 売上金額 | E22: =SUM(F22:CW22) -> 14700000 | F22: =IFERROR($C22*F21,"") -> 700000 | J22: =IFERROR($C22*J21,"") -> 700000 | N22: =IFERROR($C22*N21,"") -> 700000 | R22: =IFERROR($C22*R21,"") -> 700000 | V22: =IFERROR($C22*V21,"") -> 700000 | Z22: =IFERROR($C22*Z21,"") -> 700000 | AD22: =IFERROR($C22*AD21,"") -> 700000 | AH22: =IFERROR($C22*AH21,"") -> 700000 | AL22: =IFERROR($C22*AL21,"") -> 700000 | AP22: =IFERROR($C22*AP21,"") -> 700000 | AT22: =IFERROR($C22*AT21,"") -> 700000 | AX22: =IFERROR($C22*AX21,"") -> 700000 | BB22: =IFERROR($C22*BB21,"") -> 700000 | BF22: =IFERROR($C22*BF21,"") -> 700000 | BJ22: =IFERROR($C22*BJ21,"") -> 700000 | BN22: =IFERROR($C22*BN21,"") -> 700000 | BR22: =IFERROR($C22*BR21,"") -> 700000 | BV22: =IFERROR($C22*BV21,"") -> 700000 | BZ22: =IFERROR($C22*BZ21,"") -> 700000 | CD22: =IFERROR($C22*CD21,"") -> 700000 | CH22: =IFERROR($C22*CH21,"") -> 700000 | CL22: =IFERROR($C22*CL21,"") -> 0 | CP22: =IFERROR($C22*CP21,"") -> 0 | CT22: =IFERROR($C22*CT21,"") -> 0 | CX22: =IFERROR($C22*CX21,"") -> 0 | DB22: =IFERROR($C22*DB21,"") -> 0 | DF22: =IFERROR($C22*DF21,"") -> 0 | DJ22: =IFERROR($C22*DJ21,"") -> 0 | DN22: =IFERROR($C22*DN21,"") -> 0 | DR22: =IFERROR($C22*DR21,"") -> 0 | DV22: =IFERROR($C22*DV21,"") -> 0 | DZ22: =IFERROR($C22*DZ21,"") -> 0 | ED22: =IFERROR($C22*ED21,"") -> 0 | EH22: =IFERROR($C22*EH21,"") -> 0 | EL22: =IFERROR($C22*EL21,"") -> 0 | EP22: =IFERROR($C22*EP21,"") -> 0
C23: 600000 | D23: 原価金額 | E23: =SUM(F23:CW23) -> 6300000 | F23: =IFERROR($C23*F21,"") -> 300000 | J23: =IFERROR($C23*J21,"") -> 300000 | N23: =IFERROR($C23*N21,"") -> 300000 | R23: =IFERROR($C23*R21,"") -> 300000 | V23: =IFERROR($C23*V21,"") -> 300000 | Z23: =IFERROR($C23*Z21,"") -> 300000 | AD23: =IFERROR($C23*AD21,"") -> 300000 | AH23: =IFERROR($C23*AH21,"") -> 300000 | AL23: =IFERROR($C23*AL21,"") -> 300000 | AP23: =IFERROR($C23*AP21,"") -> 300000 | AT23: =IFERROR($C23*AT21,"") -> 300000 | AX23: =IFERROR($C23*AX21,"") -> 300000 | BB23: =IFERROR($C23*BB21,"") -> 300000 | BF23: =IFERROR($C23*BF21,"") -> 300000 | BJ23: =IFERROR($C23*BJ21,"") -> 300000 | BN23: =IFERROR($C23*BN21,"") -> 300000 | BR23: =IFERROR($C23*BR21,"") -> 300000 | BV23: =IFERROR($C23*BV21,"") -> 300000 | BZ23: =IFERROR($C23*BZ21,"") -> 300000 | CD23: =IFERROR($C23*CD21,"") -> 300000 | CH23: =IFERROR($C23*CH21,"") -> 300000 | CL23: =IFERROR($C23*CL21,"") -> 0 | CP23: =IFERROR($C23*CP21,"") -> 0 | CT23: =IFERROR($C23*CT21,"") -> 0 | CX23: =IFERROR($C23*CX21,"") -> 0 | DB23: =IFERROR($C23*DB21,"") -> 0 | DF23: =IFERROR($C23*DF21,"") -> 0 | DJ23: =IFERROR($C23*DJ21,"") -> 0 | DN23: =IFERROR($C23*DN21,"") -> 0 | DR23: =IFERROR($C23*DR21,"") -> 0 | DV23: =IFERROR($C23*DV21,"") -> 0 | DZ23: =IFERROR($C23*DZ21,"") -> 0 | ED23: =IFERROR($C23*ED21,"") -> 0 | EH23: =IFERROR($C23*EH21,"") -> 0 | EL23: =IFERROR($C23*EL21,"") -> 0 | EP23: =IFERROR($C23*EP21,"") -> 0
B24: PL | D24: 工数 | E24: =SUM(F24:ES24) -> 20.5 | F24: 1 | J24: 1 | N24: 1 | R24: 1 | V24: 1 | Z24: 1 | AD24: 1 | AH24: 1 | AL24: 1 | AP24: 1 | AT24: 1 | AX24: 1 | BB24: 1 | BF24: 1 | BJ24: 1 | BN24: 1 | BR24: 1 | BV24: 1 | BZ24: 1 | CD24: 1 | CH24: 0.5
C25: 1200000 | D25: 売上金額 | E25: =SUM(F25:CW25) -> 24600000 | F25: =IFERROR($C25*F24,"") -> 1200000 | J25: =IFERROR($C25*J24,"") -> 1200000 | N25: =IFERROR($C25*N24,"") -> 1200000 | R25: =IFERROR($C25*R24,"") -> 1200000 | V25: =IFERROR($C25*V24,"") -> 1200000 | Z25: =IFERROR($C25*Z24,"") -> 1200000 | AD25: =IFERROR($C25*AD24,"") -> 1200000 | AH25: =IFERROR($C25*AH24,"") -> 1200000 | AL25: =IFERROR($C25*AL24,"") -> 1200000 | AP25: =IFERROR($C25*AP24,"") -> 1200000 | AT25: =IFERROR($C25*AT24,"") -> 1200000 | AX25: =IFERROR($C25*AX24,"") -> 1200000 | BB25: =IFERROR($C25*BB24,"") -> 1200000 | BF25: =IFERROR($C25*BF24,"") -> 1200000 | BJ25: =IFERROR($C25*BJ24,"") -> 1200000 | BN25: =IFERROR($C25*BN24,"") -> 1200000 | BR25: =IFERROR($C25*BR24,"") -> 1200000 | BV25: =IFERROR($C25*BV24,"") -> 1200000 | BZ25: =IFERROR($C25*BZ24,"") -> 1200000 | CD25: =IFERROR($C25*CD24,"") -> 1200000 | CH25: =IFERROR($C25*CH24,"") -> 600000 | CL25: =IFERROR($C25*CL24,"") -> 0 | CP25: =IFERROR($C25*CP24,"") -> 0 | CT25: =IFERROR($C25*CT24,"") -> 0 | CX25: =IFERROR($C25*CX24,"") -> 0 | DB25: =IFERROR($C25*DB24,"") -> 0 | DF25: =IFERROR($C25*DF24,"") -> 0 | DJ25: =IFERROR($C25*DJ24,"") -> 0 | DN25: =IFERROR($C25*DN24,"") -> 0 | DR25: =IFERROR($C25*DR24,"") -> 0 | DV25: =IFERROR($C25*DV24,"") -> 0 | DZ25: =IFERROR($C25*DZ24,"") -> 0 | ED25: =IFERROR($C25*ED24,"") -> 0 | EH25: =IFERROR($C25*EH24,"") -> 0 | EL25: =IFERROR($C25*EL24,"") -> 0 | EP25: =IFERROR($C25*EP24,"") -> 0
C26: 600000 | D26: 原価金額 | E26: =SUM(F26:CW26) -> 12300000 | F26: =IFERROR($C26*F24,"") -> 600000 | J26: =IFERROR($C26*J24,"") -> 600000 | N26: =IFERROR($C26*N24,"") -> 600000 | R26: =IFERROR($C26*R24,"") -> 600000 | V26: =IFERROR($C26*V24,"") -> 600000 | Z26: =IFERROR($C26*Z24,"") -> 600000 | AD26: =IFERROR($C26*AD24,"") -> 600000 | AH26: =IFERROR($C26*AH24,"") -> 600000 | AL26: =IFERROR($C26*AL24,"") -> 600000 | AP26: =IFERROR($C26*AP24,"") -> 600000 | AT26: =IFERROR($C26*AT24,"") -> 600000 | AX26: =IFERROR($C26*AX24,"") -> 600000 | BB26: =IFERROR($C26*BB24,"") -> 600000 | BF26: =IFERROR($C26*BF24,"") -> 600000 | BJ26: =IFERROR($C26*BJ24,"") -> 600000 | BN26: =IFERROR($C26*BN24,"") -> 600000 | BR26: =IFERROR($C26*BR24,"") -> 600000 | BV26: =IFERROR($C26*BV24,"") -> 600000 | BZ26: =IFERROR($C26*BZ24,"") -> 600000 | CD26: =IFERROR($C26*CD24,"") -> 600000 | CH26: =IFERROR($C26*CH24,"") -> 300000 | CL26: =IFERROR($C26*CL24,"") -> 0 | CP26: =IFERROR($C26*CP24,"") -> 0 | CT26: =IFERROR($C26*CT24,"") -> 0 | CX26: =IFERROR($C26*CX24,"") -> 0 | DB26: =IFERROR($C26*DB24,"") -> 0 | DF26: =IFERROR($C26*DF24,"") -> 0 | DJ26: =IFERROR($C26*DJ24,"") -> 0 | DN26: =IFERROR($C26*DN24,"") -> 0 | DR26: =IFERROR($C26*DR24,"") -> 0 | DV26: =IFERROR($C26*DV24,"") -> 0 | DZ26: =IFERROR($C26*DZ24,"") -> 0 | ED26: =IFERROR($C26*ED24,"") -> 0 | EH26: =IFERROR($C26*EH24,"") -> 0 | EL26: =IFERROR($C26*EL24,"") -> 0 | EP26: =IFERROR($C26*EP24,"") -> 0
B27: ブリッジ | D27: 工数 | E27: =SUM(F27:ES27) -> 12 | V27: 1 | Z27: 1 | AD27: 1 | AH27: 1 | AL27: 1 | AP27: 1 | AT27: 1 | AX27: 1 | BB27: 1 | BF27: 1 | BJ27: 1 | BN27: 1
C28: 1400000 | D28: 売上金額 | E28: =SUM(F28:CW28) -> 16800000 | F28: =IFERROR($C28*F27,"") -> 0 | J28: =IFERROR($C28*J27,"") -> 0 | N28: =IFERROR($C28*N27,"") -> 0 | R28: =IFERROR($C28*R27,"") -> 0 | V28: =IFERROR($C28*V27,"") -> 1400000 | Z28: =IFERROR($C28*Z27,"") -> 1400000 | AD28: =IFERROR($C28*AD27,"") -> 1400000 | AH28: =IFERROR($C28*AH27,"") -> 1400000 | AL28: =IFERROR($C28*AL27,"") -> 1400000 | AP28: =IFERROR($C28*AP27,"") -> 1400000 | AT28: =IFERROR($C28*AT27,"") -> 1400000 | AX28: =IFERROR($C28*AX27,"") -> 1400000 | BB28: =IFERROR($C28*BB27,"") -> 1400000 | BF28: =IFERROR($C28*BF27,"") -> 1400000 | BJ28: =IFERROR($C28*BJ27,"") -> 1400000 | BN28: =IFERROR($C28*BN27,"") -> 1400000 | BR28: =IFERROR($C28*BR27,"") -> 0 | BV28: =IFERROR($C28*BV27,"") -> 0 | BZ28: =IFERROR($C28*BZ27,"") -> 0 | CD28: =IFERROR($C28*CD27,"") -> 0 | CH28: =IFERROR($C28*CH27,"") -> 0 | CL28: =IFERROR($C28*CL27,"") -> 0 | CP28: =IFERROR($C28*CP27,"") -> 0 | CT28: =IFERROR($C28*CT27,"") -> 0 | CX28: =IFERROR($C28*CX27,"") -> 0 | DB28: =IFERROR($C28*DB27,"") -> 0 | DF28: =IFERROR($C28*DF27,"") -> 0 | DJ28: =IFERROR($C28*DJ27,"") -> 0 | DN28: =IFERROR($C28*DN27,"") -> 0 | DR28: =IFERROR($C28*DR27,"") -> 0 | DV28: =IFERROR($C28*DV27,"") -> 0 | DZ28: =IFERROR($C28*DZ27,"") -> 0 | ED28: =IFERROR($C28*ED27,"") -> 0 | EH28: =IFERROR($C28*EH27,"") -> 0 | EL28: =IFERROR($C28*EL27,"") -> 0 | EP28: =IFERROR($C28*EP27,"") -> 0
C29: 1200000 | D29: 原価金額 | E29: =SUM(F29:CW29) -> 14400000 | F29: =IFERROR($C29*F27,"") -> 0 | J29: =IFERROR($C29*J27,"") -> 0 | N29: =IFERROR($C29*N27,"") -> 0 | R29: =IFERROR($C29*R27,"") -> 0 | V29: =IFERROR($C29*V27,"") -> 1200000 | Z29: =IFERROR($C29*Z27,"") -> 1200000 | AD29: =IFERROR($C29*AD27,"") -> 1200000 | AH29: =IFERROR($C29*AH27,"") -> 1200000 | AL29: =IFERROR($C29*AL27,"") -> 1200000 | AP29: =IFERROR($C29*AP27,"") -> 1200000 | AT29: =IFERROR($C29*AT27,"") -> 1200000 | AX29: =IFERROR($C29*AX27,"") -> 1200000 | BB29: =IFERROR($C29*BB27,"") -> 1200000 | BF29: =IFERROR($C29*BF27,"") -> 1200000 | BJ29: =IFERROR($C29*BJ27,"") -> 1200000 | BN29: =IFERROR($C29*BN27,"") -> 1200000 | BR29: =IFERROR($C29*BR27,"") -> 0 | BV29: =IFERROR($C29*BV27,"") -> 0 | BZ29: =IFERROR($C29*BZ27,"") -> 0 | CD29: =IFERROR($C29*CD27,"") -> 0 | CH29: =IFERROR($C29*CH27,"") -> 0 | CL29: =IFERROR($C29*CL27,"") -> 0 | CP29: =IFERROR($C29*CP27,"") -> 0 | CT29: =IFERROR($C29*CT27,"") -> 0 | CX29: =IFERROR($C29*CX27,"") -> 0 | DB29: =IFERROR($C29*DB27,"") -> 0 | DF29: =IFERROR($C29*DF27,"") -> 0 | DJ29: =IFERROR($C29*DJ27,"") -> 0 | DN29: =IFERROR($C29*DN27,"") -> 0 | DR29: =IFERROR($C29*DR27,"") -> 0 | DV29: =IFERROR($C29*DV27,"") -> 0 | DZ29: =IFERROR($C29*DZ27,"") -> 0 | ED29: =IFERROR($C29*ED27,"") -> 0 | EH29: =IFERROR($C29*EH27,"") -> 0 | EL29: =IFERROR($C29*EL27,"") -> 0 | EP29: =IFERROR($C29*EP27,"") -> 0
B30: PMO | D30: 工数 | E30: =SUM(F30:ES30) -> 20.5 | F30: 1 | J30: 1 | N30: 1 | R30: 1 | V30: 1 | Z30: 1 | AD30: 1 | AH30: 1 | AL30: 1 | AP30: 1 | AT30: 1 | AX30: 1 | BB30: 1 | BF30: 1 | BJ30: 1 | BN30: 1 | BR30: 1 | BV30: 1 | BZ30: 1 | CD30: 1 | CH30: 0.5
C31: 900000 | D31: 売上金額 | E31: =SUM(F31:CW31) -> 18450000 | F31: =IFERROR($C31*F30,"") -> 900000 | J31: =IFERROR($C31*J30,"") -> 900000 | N31: =IFERROR($C31*N30,"") -> 900000 | R31: =IFERROR($C31*R30,"") -> 900000 | V31: =IFERROR($C31*V30,"") -> 900000 | Z31: =IFERROR($C31*Z30,"") -> 900000 | AD31: =IFERROR($C31*AD30,"") -> 900000 | AH31: =IFERROR($C31*AH30,"") -> 900000 | AL31: =IFERROR($C31*AL30,"") -> 900000 | AP31: =IFERROR($C31*AP30,"") -> 900000 | AT31: =IFERROR($C31*AT30,"") -> 900000 | AX31: =IFERROR($C31*AX30,"") -> 900000 | BB31: =IFERROR($C31*BB30,"") -> 900000 | BF31: =IFERROR($C31*BF30,"") -> 900000 | BJ31: =IFERROR($C31*BJ30,"") -> 900000 | BN31: =IFERROR($C31*BN30,"") -> 900000 | BR31: =IFERROR($C31*BR30,"") -> 900000 | BV31: =IFERROR($C31*BV30,"") -> 900000 | BZ31: =IFERROR($C31*BZ30,"") -> 900000 | CD31: =IFERROR($C31*CD30,"") -> 900000 | CH31: =IFERROR($C31*CH30,"") -> 450000 | CL31: =IFERROR($C31*CL30,"") -> 0 | CP31: =IFERROR($C31*CP30,"") -> 0 | CT31: =IFERROR($C31*CT30,"") -> 0 | CX31: =IFERROR($C31*CX30,"") -> 0 | DB31: =IFERROR($C31*DB30,"") -> 0 | DF31: =IFERROR($C31*DF30,"") -> 0 | DJ31: =IFERROR($C31*DJ30,"") -> 0 | DN31: =IFERROR($C31*DN30,"") -> 0 | DR31: =IFERROR($C31*DR30,"") -> 0 | DV31: =IFERROR($C31*DV30,"") -> 0 | DZ31: =IFERROR($C31*DZ30,"") -> 0 | ED31: =IFERROR($C31*ED30,"") -> 0 | EH31: =IFERROR($C31*EH30,"") -> 0 | EL31: =IFERROR($C31*EL30,"") -> 0 | EP31: =IFERROR($C31*EP30,"") -> 0
C32: 300000 | D32: 原価金額 | E32: =SUM(F32:CW32) -> 6150000 | F32: =IFERROR($C32*F30,"") -> 300000 | J32: =IFERROR($C32*J30,"") -> 300000 | N32: =IFERROR($C32*N30,"") -> 300000 | R32: =IFERROR($C32*R30,"") -> 300000 | V32: =IFERROR($C32*V30,"") -> 300000 | Z32: =IFERROR($C32*Z30,"") -> 300000 | AD32: =IFERROR($C32*AD30,"") -> 300000 | AH32: =IFERROR($C32*AH30,"") -> 300000 | AL32: =IFERROR($C32*AL30,"") -> 300000 | AP32: =IFERROR($C32*AP30,"") -> 300000 | AT32: =IFERROR($C32*AT30,"") -> 300000 | AX32: =IFERROR($C32*AX30,"") -> 300000 | BB32: =IFERROR($C32*BB30,"") -> 300000 | BF32: =IFERROR($C32*BF30,"") -> 300000 | BJ32: =IFERROR($C32*BJ30,"") -> 300000 | BN32: =IFERROR($C32*BN30,"") -> 300000 | BR32: =IFERROR($C32*BR30,"") -> 300000 | BV32: =IFERROR($C32*BV30,"") -> 300000 | BZ32: =IFERROR($C32*BZ30,"") -> 300000 | CD32: =IFERROR($C32*CD30,"") -> 300000 | CH32: =IFERROR($C32*CH30,"") -> 150000 | CL32: =IFERROR($C32*CL30,"") -> 0 | CP32: =IFERROR($C32*CP30,"") -> 0 | CT32: =IFERROR($C32*CT30,"") -> 0 | CX32: =IFERROR($C32*CX30,"") -> 0 | DB32: =IFERROR($C32*DB30,"") -> 0 | DF32: =IFERROR($C32*DF30,"") -> 0 | DJ32: =IFERROR($C32*DJ30,"") -> 0 | DN32: =IFERROR($C32*DN30,"") -> 0 | DR32: =IFERROR($C32*DR30,"") -> 0 | DV32: =IFERROR($C32*DV30,"") -> 0 | DZ32: =IFERROR($C32*DZ30,"") -> 0 | ED32: =IFERROR($C32*ED30,"") -> 0 | EH32: =IFERROR($C32*EH30,"") -> 0 | EL32: =IFERROR($C32*EL30,"") -> 0 | EP32: =IFERROR($C32*EP30,"") -> 0
B33: SE1 | D33: 工数 | E33: =SUM(F33:ES33) -> 20.5 | F33: 1 | J33: 1 | N33: 1 | R33: 1 | V33: 1 | Z33: 1 | AD33: 1 | AH33: 1 | AL33: 1 | AP33: 1 | AT33: 1 | AX33: 1 | BB33: 1 | BF33: 1 | BJ33: 1 | BN33: 1 | BR33: 1 | BV33: 1 | BZ33: 1 | CD33: 1 | CH33: 0.5
C34: 1050000 | D34: 売上金額 | E34: =SUM(F34:CW34) -> 21525000 | F34: =IFERROR($C34*F33,"") -> 1050000 | J34: =IFERROR($C34*J33,"") -> 1050000 | N34: =IFERROR($C34*N33,"") -> 1050000 | R34: =IFERROR($C34*R33,"") -> 1050000 | V34: =IFERROR($C34*V33,"") -> 1050000 | Z34: =IFERROR($C34*Z33,"") -> 1050000 | AD34: =IFERROR($C34*AD33,"") -> 1050000 | AH34: =IFERROR($C34*AH33,"") -> 1050000 | AL34: =IFERROR($C34*AL33,"") -> 1050000 | AP34: =IFERROR($C34*AP33,"") -> 1050000 | AT34: =IFERROR($C34*AT33,"") -> 1050000 | AX34: =IFERROR($C34*AX33,"") -> 1050000 | BB34: =IFERROR($C34*BB33,"") -> 1050000 | BF34: =IFERROR($C34*BF33,"") -> 1050000 | BJ34: =IFERROR($C34*BJ33,"") -> 1050000 | BN34: =IFERROR($C34*BN33,"") -> 1050000 | BR34: =IFERROR($C34*BR33,"") -> 1050000 | BV34: =IFERROR($C34*BV33,"") -> 1050000 | BZ34: =IFERROR($C34*BZ33,"") -> 1050000 | CD34: =IFERROR($C34*CD33,"") -> 1050000 | CH34: =IFERROR($C34*CH33,"") -> 525000 | CL34: =IFERROR($C34*CL33,"") -> 0 | CP34: =IFERROR($C34*CP33,"") -> 0 | CT34: =IFERROR($C34*CT33,"") -> 0 | CX34: =IFERROR($C34*CX33,"") -> 0 | DB34: =IFERROR($C34*DB33,"") -> 0 | DF34: =IFERROR($C34*DF33,"") -> 0 | DJ34: =IFERROR($C34*DJ33,"") -> 0 | DN34: =IFERROR($C34*DN33,"") -> 0 | DR34: =IFERROR($C34*DR33,"") -> 0 | DV34: =IFERROR($C34*DV33,"") -> 0 | DZ34: =IFERROR($C34*DZ33,"") -> 0 | ED34: =IFERROR($C34*ED33,"") -> 0 | EH34: =IFERROR($C34*EH33,"") -> 0 | EL34: =IFERROR($C34*EL33,"") -> 0 | EP34: =IFERROR($C34*EP33,"") -> 0
C35: 500000 | D35: 原価金額 | E35: =SUM(F35:CW35) -> 10250000 | F35: =IFERROR($C35*F33,"") -> 500000 | J35: =IFERROR($C35*J33,"") -> 500000 | N35: =IFERROR($C35*N33,"") -> 500000 | R35: =IFERROR($C35*R33,"") -> 500000 | V35: =IFERROR($C35*V33,"") -> 500000 | Z35: =IFERROR($C35*Z33,"") -> 500000 | AD35: =IFERROR($C35*AD33,"") -> 500000 | AH35: =IFERROR($C35*AH33,"") -> 500000 | AL35: =IFERROR($C35*AL33,"") -> 500000 | AP35: =IFERROR($C35*AP33,"") -> 500000 | AT35: =IFERROR($C35*AT33,"") -> 500000 | AX35: =IFERROR($C35*AX33,"") -> 500000 | BB35: =IFERROR($C35*BB33,"") -> 500000 | BF35: =IFERROR($C35*BF33,"") -> 500000 | BJ35: =IFERROR($C35*BJ33,"") -> 500000 | BN35: =IFERROR($C35*BN33,"") -> 500000 | BR35: =IFERROR($C35*BR33,"") -> 500000 | BV35: =IFERROR($C35*BV33,"") -> 500000 | BZ35: =IFERROR($C35*BZ33,"") -> 500000 | CD35: =IFERROR($C35*CD33,"") -> 500000 | CH35: =IFERROR($C35*CH33,"") -> 250000 | CL35: =IFERROR($C35*CL33,"") -> 0 | CP35: =IFERROR($C35*CP33,"") -> 0 | CT35: =IFERROR($C35*CT33,"") -> 0 | CX35: =IFERROR($C35*CX33,"") -> 0 | DB35: =IFERROR($C35*DB33,"") -> 0 | DF35: =IFERROR($C35*DF33,"") -> 0 | DJ35: =IFERROR($C35*DJ33,"") -> 0 | DN35: =IFERROR($C35*DN33,"") -> 0 | DR35: =IFERROR($C35*DR33,"") -> 0 | DV35: =IFERROR($C35*DV33,"") -> 0 | DZ35: =IFERROR($C35*DZ33,"") -> 0 | ED35: =IFERROR($C35*ED33,"") -> 0 | EH35: =IFERROR($C35*EH33,"") -> 0 | EL35: =IFERROR($C35*EL33,"") -> 0 | EP35: =IFERROR($C35*EP33,"") -> 0
B36: SE2 | D36: 工数 | E36: =SUM(F36:ES36) -> 17 | F36: 0.5 | J36: 0.5 | N36: 1 | R36: 1 | V36: 1 | Z36: 1 | AD36: 1 | AH36: 1 | AL36: 1 | AP36: 1 | AT36: 1 | AX36: 1 | BB36: 1 | BF36: 1 | BJ36: 1 | BN36: 0.5 | BR36: 0.5 | BV36: 0.5 | BZ36: 0.5 | CD36: 0.5 | CH36: 0.5
C37: 1050000 | D37: 売上金額 | E37: =SUM(F37:CW37) -> 17850000 | F37: =IFERROR($C37*F36,"") -> 525000 | J37: =IFERROR($C37*J36,"") -> 525000 | N37: =IFERROR($C37*N36,"") -> 1050000 | R37: =IFERROR($C37*R36,"") -> 1050000 | V37: =IFERROR($C37*V36,"") -> 1050000 | Z37: =IFERROR($C37*Z36,"") -> 1050000 | AD37: =IFERROR($C37*AD36,"") -> 1050000 | AH37: =IFERROR($C37*AH36,"") -> 1050000 | AL37: =IFERROR($C37*AL36,"") -> 1050000 | AP37: =IFERROR($C37*AP36,"") -> 1050000 | AT37: =IFERROR($C37*AT36,"") -> 1050000 | AX37: =IFERROR($C37*AX36,"") -> 1050000 | BB37: =IFERROR($C37*BB36,"") -> 1050000 | BF37: =IFERROR($C37*BF36,"") -> 1050000 | BJ37: =IFERROR($C37*BJ36,"") -> 1050000 | BN37: =IFERROR($C37*BN36,"") -> 525000 | BR37: =IFERROR($C37*BR36,"") -> 525000 | BV37: =IFERROR($C37*BV36,"") -> 525000 | BZ37: =IFERROR($C37*BZ36,"") -> 525000 | CD37: =IFERROR($C37*CD36,"") -> 525000 | CH37: =IFERROR($C37*CH36,"") -> 525000 | CL37: =IFERROR($C37*CL36,"") -> 0 | CP37: =IFERROR($C37*CP36,"") -> 0 | CT37: =IFERROR($C37*CT36,"") -> 0 | CX37: =IFERROR($C37*CX36,"") -> 0 | DB37: =IFERROR($C37*DB36,"") -> 0 | DF37: =IFERROR($C37*DF36,"") -> 0 | DJ37: =IFERROR($C37*DJ36,"") -> 0 | DN37: =IFERROR($C37*DN36,"") -> 0 | DR37: =IFERROR($C37*DR36,"") -> 0 | DV37: =IFERROR($C37*DV36,"") -> 0 | DZ37: =IFERROR($C37*DZ36,"") -> 0 | ED37: =IFERROR($C37*ED36,"") -> 0 | EH37: =IFERROR($C37*EH36,"") -> 0 | EL37: =IFERROR($C37*EL36,"") -> 0 | EP37: =IFERROR($C37*EP36,"") -> 0
C38: 500000 | D38: 原価金額 | E38: =SUM(F38:CW38) -> 8500000 | F38: =IFERROR($C38*F36,"") -> 250000 | J38: =IFERROR($C38*J36,"") -> 250000 | N38: =IFERROR($C38*N36,"") -> 500000 | R38: =IFERROR($C38*R36,"") -> 500000 | V38: =IFERROR($C38*V36,"") -> 500000 | Z38: =IFERROR($C38*Z36,"") -> 500000 | AD38: =IFERROR($C38*AD36,"") -> 500000 | AH38: =IFERROR($C38*AH36,"") -> 500000 | AL38: =IFERROR($C38*AL36,"") -> 500000 | AP38: =IFERROR($C38*AP36,"") -> 500000 | AT38: =IFERROR($C38*AT36,"") -> 500000 | AX38: =IFERROR($C38*AX36,"") -> 500000 | BB38: =IFERROR($C38*BB36,"") -> 500000 | BF38: =IFERROR($C38*BF36,"") -> 500000 | BJ38: =IFERROR($C38*BJ36,"") -> 500000 | BN38: =IFERROR($C38*BN36,"") -> 250000 | BR38: =IFERROR($C38*BR36,"") -> 250000 | BV38: =IFERROR($C38*BV36,"") -> 250000 | BZ38: =IFERROR($C38*BZ36,"") -> 250000 | CD38: =IFERROR($C38*CD36,"") -> 250000 | CH38: =IFERROR($C38*CH36,"") -> 250000 | CL38: =IFERROR($C38*CL36,"") -> 0 | CP38: =IFERROR($C38*CP36,"") -> 0 | CT38: =IFERROR($C38*CT36,"") -> 0 | CX38: =IFERROR($C38*CX36,"") -> 0 | DB38: =IFERROR($C38*DB36,"") -> 0 | DF38: =IFERROR($C38*DF36,"") -> 0 | DJ38: =IFERROR($C38*DJ36,"") -> 0 | DN38: =IFERROR($C38*DN36,"") -> 0 | DR38: =IFERROR($C38*DR36,"") -> 0 | DV38: =IFERROR($C38*DV36,"") -> 0 | DZ38: =IFERROR($C38*DZ36,"") -> 0 | ED38: =IFERROR($C38*ED36,"") -> 0 | EH38: =IFERROR($C38*EH36,"") -> 0 | EL38: =IFERROR($C38*EL36,"") -> 0 | EP38: =IFERROR($C38*EP36,"") -> 0
B39: SE3 | D39: 工数 | E39: =SUM(F39:ES39) -> 9 | N39: 1 | R39: 1 | V39: 1 | Z39: 1 | AD39: 1 | BB39: 1 | BF39: 1 | BJ39: 1 | BN39: 1
C40: 1050000 | D40: 売上金額 | E40: =SUM(F40:CW40) -> 9450000 | F40: =IFERROR($C40*F39,"") -> 0 | J40: =IFERROR($C40*J39,"") -> 0 | N40: =IFERROR($C40*N39,"") -> 1050000 | R40: =IFERROR($C40*R39,"") -> 1050000 | V40: =IFERROR($C40*V39,"") -> 1050000 | Z40: =IFERROR($C40*Z39,"") -> 1050000 | AD40: =IFERROR($C40*AD39,"") -> 1050000 | AH40: =IFERROR($C40*AH39,"") -> 0 | AL40: =IFERROR($C40*AL39,"") -> 0 | AP40: =IFERROR($C40*AP39,"") -> 0 | AT40: =IFERROR($C40*AT39,"") -> 0 | AX40: =IFERROR($C40*AX39,"") -> 0 | BB40: =IFERROR($C40*BB39,"") -> 1050000 | BF40: =IFERROR($C40*BF39,"") -> 1050000 | BJ40: =IFERROR($C40*BJ39,"") -> 1050000 | BN40: =IFERROR($C40*BN39,"") -> 1050000 | BR40: =IFERROR($C40*BR39,"") -> 0 | BV40: =IFERROR($C40*BV39,"") -> 0 | BZ40: =IFERROR($C40*BZ39,"") -> 0 | CD40: =IFERROR($C40*CD39,"") -> 0 | CH40: =IFERROR($C40*CH39,"") -> 0 | CL40: =IFERROR($C40*CL39,"") -> 0 | CP40: =IFERROR($C40*CP39,"") -> 0 | CT40: =IFERROR($C40*CT39,"") -> 0 | CX40: =IFERROR($C40*CX39,"") -> 0 | DB40: =IFERROR($C40*DB39,"") -> 0 | DF40: =IFERROR($C40*DF39,"") -> 0 | DJ40: =IFERROR($C40*DJ39,"") -> 0 | DN40: =IFERROR($C40*DN39,"") -> 0 | DR40: =IFERROR($C40*DR39,"") -> 0 | DV40: =IFERROR($C40*DV39,"") -> 0 | DZ40: =IFERROR($C40*DZ39,"") -> 0 | ED40: =IFERROR($C40*ED39,"") -> 0 | EH40: =IFERROR($C40*EH39,"") -> 0 | EL40: =IFERROR($C40*EL39,"") -> 0 | EP40: =IFERROR($C40*EP39,"") -> 0
C41: 500000 | D41: 原価金額 | E41: =SUM(F41:CW41) -> 4500000 | F41: =IFERROR($C41*F39,"") -> 0 | J41: =IFERROR($C41*J39,"") -> 0 | N41: =IFERROR($C41*N39,"") -> 500000 | R41: =IFERROR($C41*R39,"") -> 500000 | V41: =IFERROR($C41*V39,"") -> 500000 | Z41: =IFERROR($C41*Z39,"") -> 500000 | AD41: =IFERROR($C41*AD39,"") -> 500000 | AH41: =IFERROR($C41*AH39,"") -> 0 | AL41: =IFERROR($C41*AL39,"") -> 0 | AP41: =IFERROR($C41*AP39,"") -> 0 | AT41: =IFERROR($C41*AT39,"") -> 0 | AX41: =IFERROR($C41*AX39,"") -> 0 | BB41: =IFERROR($C41*BB39,"") -> 500000 | BF41: =IFERROR($C41*BF39,"") -> 500000 | BJ41: =IFERROR($C41*BJ39,"") -> 500000 | BN41: =IFERROR($C41*BN39,"") -> 500000 | BR41: =IFERROR($C41*BR39,"") -> 0 | BV41: =IFERROR($C41*BV39,"") -> 0 | BZ41: =IFERROR($C41*BZ39,"") -> 0 | CD41: =IFERROR($C41*CD39,"") -> 0 | CH41: =IFERROR($C41*CH39,"") -> 0 | CL41: =IFERROR($C41*CL39,"") -> 0 | CP41: =IFERROR($C41*CP39,"") -> 0 | CT41: =IFERROR($C41*CT39,"") -> 0 | CX41: =IFERROR($C41*CX39,"") -> 0 | DB41: =IFERROR($C41*DB39,"") -> 0 | DF41: =IFERROR($C41*DF39,"") -> 0 | DJ41: =IFERROR($C41*DJ39,"") -> 0 | DN41: =IFERROR($C41*DN39,"") -> 0 | DR41: =IFERROR($C41*DR39,"") -> 0 | DV41: =IFERROR($C41*DV39,"") -> 0 | DZ41: =IFERROR($C41*DZ39,"") -> 0 | ED41: =IFERROR($C41*ED39,"") -> 0 | EH41: =IFERROR($C41*EH39,"") -> 0 | EL41: =IFERROR($C41*EL39,"") -> 0 | EP41: =IFERROR($C41*EP39,"") -> 0
B42: SE4 | D42: 工数 | E42: =SUM(F42:ES42) -> 9 | N42: 1 | R42: 1 | V42: 1 | Z42: 1 | AD42: 1 | BB42: 1 | BF42: 1 | BJ42: 1 | BN42: 1
C43: 1050000 | D43: 売上金額 | E43: =SUM(F43:CW43) -> 9450000 | F43: =IFERROR($C43*F42,"") -> 0 | J43: =IFERROR($C43*J42,"") -> 0 | N43: =IFERROR($C43*N42,"") -> 1050000 | R43: =IFERROR($C43*R42,"") -> 1050000 | V43: =IFERROR($C43*V42,"") -> 1050000 | Z43: =IFERROR($C43*Z42,"") -> 1050000 | AD43: =IFERROR($C43*AD42,"") -> 1050000 | AH43: =IFERROR($C43*AH42,"") -> 0 | AL43: =IFERROR($C43*AL42,"") -> 0 | AP43: =IFERROR($C43*AP42,"") -> 0 | AT43: =IFERROR($C43*AT42,"") -> 0 | AX43: =IFERROR($C43*AX42,"") -> 0 | BB43: =IFERROR($C43*BB42,"") -> 1050000 | BF43: =IFERROR($C43*BF42,"") -> 1050000 | BJ43: =IFERROR($C43*BJ42,"") -> 1050000 | BN43: =IFERROR($C43*BN42,"") -> 1050000 | BR43: =IFERROR($C43*BR42,"") -> 0 | BV43: =IFERROR($C43*BV42,"") -> 0 | BZ43: =IFERROR($C43*BZ42,"") -> 0 | CD43: =IFERROR($C43*CD42,"") -> 0 | CH43: =IFERROR($C43*CH42,"") -> 0 | CL43: =IFERROR($C43*CL42,"") -> 0 | CP43: =IFERROR($C43*CP42,"") -> 0 | CT43: =IFERROR($C43*CT42,"") -> 0 | CX43: =IFERROR($C43*CX42,"") -> 0 | DB43: =IFERROR($C43*DB42,"") -> 0 | DF43: =IFERROR($C43*DF42,"") -> 0 | DJ43: =IFERROR($C43*DJ42,"") -> 0 | DN43: =IFERROR($C43*DN42,"") -> 0 | DR43: =IFERROR($C43*DR42,"") -> 0 | DV43: =IFERROR($C43*DV42,"") -> 0 | DZ43: =IFERROR($C43*DZ42,"") -> 0 | ED43: =IFERROR($C43*ED42,"") -> 0 | EH43: =IFERROR($C43*EH42,"") -> 0 | EL43: =IFERROR($C43*EL42,"") -> 0 | EP43: =IFERROR($C43*EP42,"") -> 0
C44: 500000 | D44: 原価金額 | E44: =SUM(F44:CW44) -> 4500000 | F44: =IFERROR($C44*F42,"") -> 0 | J44: =IFERROR($C44*J42,"") -> 0 | N44: =IFERROR($C44*N42,"") -> 500000 | R44: =IFERROR($C44*R42,"") -> 500000 | V44: =IFERROR($C44*V42,"") -> 500000 | Z44: =IFERROR($C44*Z42,"") -> 500000 | AD44: =IFERROR($C44*AD42,"") -> 500000 | AH44: =IFERROR($C44*AH42,"") -> 0 | AL44: =IFERROR($C44*AL42,"") -> 0 | AP44: =IFERROR($C44*AP42,"") -> 0 | AT44: =IFERROR($C44*AT42,"") -> 0 | AX44: =IFERROR($C44*AX42,"") -> 0 | BB44: =IFERROR($C44*BB42,"") -> 500000 | BF44: =IFERROR($C44*BF42,"") -> 500000 | BJ44: =IFERROR($C44*BJ42,"") -> 500000 | BN44: =IFERROR($C44*BN42,"") -> 500000 | BR44: =IFERROR($C44*BR42,"") -> 0 | BV44: =IFERROR($C44*BV42,"") -> 0 | BZ44: =IFERROR($C44*BZ42,"") -> 0 | CD44: =IFERROR($C44*CD42,"") -> 0 | CH44: =IFERROR($C44*CH42,"") -> 0 | CL44: =IFERROR($C44*CL42,"") -> 0 | CP44: =IFERROR($C44*CP42,"") -> 0 | CT44: =IFERROR($C44*CT42,"") -> 0 | CX44: =IFERROR($C44*CX42,"") -> 0 | DB44: =IFERROR($C44*DB42,"") -> 0 | DF44: =IFERROR($C44*DF42,"") -> 0 | DJ44: =IFERROR($C44*DJ42,"") -> 0 | DN44: =IFERROR($C44*DN42,"") -> 0 | DR44: =IFERROR($C44*DR42,"") -> 0 | DV44: =IFERROR($C44*DV42,"") -> 0 | DZ44: =IFERROR($C44*DZ42,"") -> 0 | ED44: =IFERROR($C44*ED42,"") -> 0 | EH44: =IFERROR($C44*EH42,"") -> 0 | EL44: =IFERROR($C44*EL42,"") -> 0 | EP44: =IFERROR($C44*EP42,"") -> 0
D45: 工数 | E45: =SUM(F45:CW45) -> 0
D46: 売上金額 | E46: =SUM(F46:CW46) -> 0 | F46: =IFERROR($C46*F45,"") -> 0 | J46: =IFERROR($C46*J45,"") -> 0 | N46: =IFERROR($C46*N45,"") -> 0 | R46: =IFERROR($C46*R45,"") -> 0 | V46: =IFERROR($C46*V45,"") -> 0 | Z46: =IFERROR($C46*Z45,"") -> 0 | AD46: =IFERROR($C46*AD45,"") -> 0 | AH46: =IFERROR($C46*AH45,"") -> 0 | AL46: =IFERROR($C46*AL45,"") -> 0 | AP46: =IFERROR($C46*AP45,"") -> 0 | AT46: =IFERROR($C46*AT45,"") -> 0 | AX46: =IFERROR($C46*AX45,"") -> 0 | BB46: =IFERROR($C46*BB45,"") -> 0 | BF46: =IFERROR($C46*BF45,"") -> 0 | BJ46: =IFERROR($C46*BJ45,"") -> 0 | BN46: =IFERROR($C46*BN45,"") -> 0 | BR46: =IFERROR($C46*BR45,"") -> 0 | BV46: =IFERROR($C46*BV45,"") -> 0 | BZ46: =IFERROR($C46*BZ45,"") -> 0 | CD46: =IFERROR($C46*CD45,"") -> 0 | CH46: =IFERROR($C46*CH45,"") -> 0 | CL46: =IFERROR($C46*CL45,"") -> 0 | CP46: =IFERROR($C46*CP45,"") -> 0 | CT46: =IFERROR($C46*CT45,"") -> 0 | CX46: =IFERROR($C46*CX45,"") -> 0 | DB46: =IFERROR($C46*DB45,"") -> 0 | DF46: =IFERROR($C46*DF45,"") -> 0 | DJ46: =IFERROR($C46*DJ45,"") -> 0 | DN46: =IFERROR($C46*DN45,"") -> 0 | DR46: =IFERROR($C46*DR45,"") -> 0 | DV46: =IFERROR($C46*DV45,"") -> 0 | DZ46: =IFERROR($C46*DZ45,"") -> 0 | ED46: =IFERROR($C46*ED45,"") -> 0 | EH46: =IFERROR($C46*EH45,"") -> 0 | EL46: =IFERROR($C46*EL45,"") -> 0 | EP46: =IFERROR($C46*EP45,"") -> 0
D47: 原価金額 | E47: =SUM(F47:CW47) -> 0 | F47: =IFERROR($C47*F45,"") -> 0 | J47: =IFERROR($C47*J45,"") -> 0 | N47: =IFERROR($C47*N45,"") -> 0 | R47: =IFERROR($C47*R45,"") -> 0 | V47: =IFERROR($C47*V45,"") -> 0 | Z47: =IFERROR($C47*Z45,"") -> 0 | AD47: =IFERROR($C47*AD45,"") -> 0 | AH47: =IFERROR($C47*AH45,"") -> 0 | AL47: =IFERROR($C47*AL45,"") -> 0 | AP47: =IFERROR($C47*AP45,"") -> 0 | AT47: =IFERROR($C47*AT45,"") -> 0 | AX47: =IFERROR($C47*AX45,"") -> 0 | BB47: =IFERROR($C47*BB45,"") -> 0 | BF47: =IFERROR($C47*BF45,"") -> 0 | BJ47: =IFERROR($C47*BJ45,"") -> 0 | BN47: =IFERROR($C47*BN45,"") -> 0 | BR47: =IFERROR($C47*BR45,"") -> 0 | BV47: =IFERROR($C47*BV45,"") -> 0 | BZ47: =IFERROR($C47*BZ45,"") -> 0 | CD47: =IFERROR($C47*CD45,"") -> 0 | CH47: =IFERROR($C47*CH45,"") -> 0 | CL47: =IFERROR($C47*CL45,"") -> 0 | CP47: =IFERROR($C47*CP45,"") -> 0 | CT47: =IFERROR($C47*CT45,"") -> 0 | CX47: =IFERROR($C47*CX45,"") -> 0 | DB47: =IFERROR($C47*DB45,"") -> 0 | DF47: =IFERROR($C47*DF45,"") -> 0 | DJ47: =IFERROR($C47*DJ45,"") -> 0 | DN47: =IFERROR($C47*DN45,"") -> 0 | DR47: =IFERROR($C47*DR45,"") -> 0 | DV47: =IFERROR($C47*DV45,"") -> 0 | DZ47: =IFERROR($C47*DZ45,"") -> 0 | ED47: =IFERROR($C47*ED45,"") -> 0 | EH47: =IFERROR($C47*EH45,"") -> 0 | EL47: =IFERROR($C47*EL45,"") -> 0 | EP47: =IFERROR($C47*EP45,"") -> 0
D48: 工数 | E48: =SUM(F48:CW48) -> 0
D49: 売上金額 | E49: =SUM(F49:CW49) -> 0 | F49: =IFERROR($C49*F48,"") -> 0 | J49: =IFERROR($C49*J48,"") -> 0 | N49: =IFERROR($C49*N48,"") -> 0 | R49: =IFERROR($C49*R48,"") -> 0 | V49: =IFERROR($C49*V48,"") -> 0 | Z49: =IFERROR($C49*Z48,"") -> 0 | AD49: =IFERROR($C49*AD48,"") -> 0 | AH49: =IFERROR($C49*AH48,"") -> 0 | AL49: =IFERROR($C49*AL48,"") -> 0 | AP49: =IFERROR($C49*AP48,"") -> 0 | AT49: =IFERROR($C49*AT48,"") -> 0 | AX49: =IFERROR($C49*AX48,"") -> 0 | BB49: =IFERROR($C49*BB48,"") -> 0 | BF49: =IFERROR($C49*BF48,"") -> 0 | BJ49: =IFERROR($C49*BJ48,"") -> 0 | BN49: =IFERROR($C49*BN48,"") -> 0 | BR49: =IFERROR($C49*BR48,"") -> 0 | BV49: =IFERROR($C49*BV48,"") -> 0 | BZ49: =IFERROR($C49*BZ48,"") -> 0 | CD49: =IFERROR($C49*CD48,"") -> 0 | CH49: =IFERROR($C49*CH48,"") -> 0 | CL49: =IFERROR($C49*CL48,"") -> 0 | CP49: =IFERROR($C49*CP48,"") -> 0 | CT49: =IFERROR($C49*CT48,"") -> 0 | CX49: =IFERROR($C49*CX48,"") -> 0 | DB49: =IFERROR($C49*DB48,"") -> 0 | DF49: =IFERROR($C49*DF48,"") -> 0 | DJ49: =IFERROR($C49*DJ48,"") -> 0 | DN49: =IFERROR($C49*DN48,"") -> 0 | DR49: =IFERROR($C49*DR48,"") -> 0 | DV49: =IFERROR($C49*DV48,"") -> 0 | DZ49: =IFERROR($C49*DZ48,"") -> 0 | ED49: =IFERROR($C49*ED48,"") -> 0 | EH49: =IFERROR($C49*EH48,"") -> 0 | EL49: =IFERROR($C49*EL48,"") -> 0 | EP49: =IFERROR($C49*EP48,"") -> 0
D50: 原価金額 | E50: =SUM(F50:CW50) -> 0 | F50: =IFERROR($C50*F48,"") -> 0 | J50: =IFERROR($C50*J48,"") -> 0 | N50: =IFERROR($C50*N48,"") -> 0 | R50: =IFERROR($C50*R48,"") -> 0 | V50: =IFERROR($C50*V48,"") -> 0 | Z50: =IFERROR($C50*Z48,"") -> 0 | AD50: =IFERROR($C50*AD48,"") -> 0 | AH50: =IFERROR($C50*AH48,"") -> 0 | AL50: =IFERROR($C50*AL48,"") -> 0 | AP50: =IFERROR($C50*AP48,"") -> 0 | AT50: =IFERROR($C50*AT48,"") -> 0 | AX50: =IFERROR($C50*AX48,"") -> 0 | BB50: =IFERROR($C50*BB48,"") -> 0 | BF50: =IFERROR($C50*BF48,"") -> 0 | BJ50: =IFERROR($C50*BJ48,"") -> 0 | BN50: =IFERROR($C50*BN48,"") -> 0 | BR50: =IFERROR($C50*BR48,"") -> 0 | BV50: =IFERROR($C50*BV48,"") -> 0 | BZ50: =IFERROR($C50*BZ48,"") -> 0 | CD50: =IFERROR($C50*CD48,"") -> 0 | CH50: =IFERROR($C50*CH48,"") -> 0 | CL50: =IFERROR($C50*CL48,"") -> 0 | CP50: =IFERROR($C50*CP48,"") -> 0 | CT50: =IFERROR($C50*CT48,"") -> 0 | CX50: =IFERROR($C50*CX48,"") -> 0 | DB50: =IFERROR($C50*DB48,"") -> 0 | DF50: =IFERROR($C50*DF48,"") -> 0 | DJ50: =IFERROR($C50*DJ48,"") -> 0 | DN50: =IFERROR($C50*DN48,"") -> 0 | DR50: =IFERROR($C50*DR48,"") -> 0 | DV50: =IFERROR($C50*DV48,"") -> 0 | DZ50: =IFERROR($C50*DZ48,"") -> 0 | ED50: =IFERROR($C50*ED48,"") -> 0 | EH50: =IFERROR($C50*EH48,"") -> 0 | EL50: =IFERROR($C50*EL48,"") -> 0 | EP50: =IFERROR($C50*EP48,"") -> 0
D51: 工数 | E51: =SUM(F51:CW51) -> 0
D52: 売上金額 | E52: =SUM(F52:CW52) -> 0 | F52: =IFERROR($C52*F51,"") -> 0 | J52: =IFERROR($C52*J51,"") -> 0 | N52: =IFERROR($C52*N51,"") -> 0 | R52: =IFERROR($C52*R51,"") -> 0 | V52: =IFERROR($C52*V51,"") -> 0 | Z52: =IFERROR($C52*Z51,"") -> 0 | AD52: =IFERROR($C52*AD51,"") -> 0 | AH52: =IFERROR($C52*AH51,"") -> 0 | AL52: =IFERROR($C52*AL51,"") -> 0 | AP52: =IFERROR($C52*AP51,"") -> 0 | AT52: =IFERROR($C52*AT51,"") -> 0 | AX52: =IFERROR($C52*AX51,"") -> 0 | BB52: =IFERROR($C52*BB51,"") -> 0 | BF52: =IFERROR($C52*BF51,"") -> 0 | BJ52: =IFERROR($C52*BJ51,"") -> 0 | BN52: =IFERROR($C52*BN51,"") -> 0 | BR52: =IFERROR($C52*BR51,"") -> 0 | BV52: =IFERROR($C52*BV51,"") -> 0 | BZ52: =IFERROR($C52*BZ51,"") -> 0 | CD52: =IFERROR($C52*CD51,"") -> 0 | CH52: =IFERROR($C52*CH51,"") -> 0 | CL52: =IFERROR($C52*CL51,"") -> 0 | CP52: =IFERROR($C52*CP51,"") -> 0 | CT52: =IFERROR($C52*CT51,"") -> 0 | CX52: =IFERROR($C52*CX51,"") -> 0 | DB52: =IFERROR($C52*DB51,"") -> 0 | DF52: =IFERROR($C52*DF51,"") -> 0 | DJ52: =IFERROR($C52*DJ51,"") -> 0 | DN52: =IFERROR($C52*DN51,"") -> 0 | DR52: =IFERROR($C52*DR51,"") -> 0 | DV52: =IFERROR($C52*DV51,"") -> 0 | DZ52: =IFERROR($C52*DZ51,"") -> 0 | ED52: =IFERROR($C52*ED51,"") -> 0 | EH52: =IFERROR($C52*EH51,"") -> 0 | EL52: =IFERROR($C52*EL51,"") -> 0 | EP52: =IFERROR($C52*EP51,"") -> 0
D53: 原価金額 | E53: =SUM(F53:CW53) -> 0 | F53: =IFERROR($C53*F51,"") -> 0 | J53: =IFERROR($C53*J51,"") -> 0 | N53: =IFERROR($C53*N51,"") -> 0 | R53: =IFERROR($C53*R51,"") -> 0 | V53: =IFERROR($C53*V51,"") -> 0 | Z53: =IFERROR($C53*Z51,"") -> 0 | AD53: =IFERROR($C53*AD51,"") -> 0 | AH53: =IFERROR($C53*AH51,"") -> 0 | AL53: =IFERROR($C53*AL51,"") -> 0 | AP53: =IFERROR($C53*AP51,"") -> 0 | AT53: =IFERROR($C53*AT51,"") -> 0 | AX53: =IFERROR($C53*AX51,"") -> 0 | BB53: =IFERROR($C53*BB51,"") -> 0 | BF53: =IFERROR($C53*BF51,"") -> 0 | BJ53: =IFERROR($C53*BJ51,"") -> 0 | BN53: =IFERROR($C53*BN51,"") -> 0 | BR53: =IFERROR($C53*BR51,"") -> 0 | BV53: =IFERROR($C53*BV51,"") -> 0 | BZ53: =IFERROR($C53*BZ51,"") -> 0 | CD53: =IFERROR($C53*CD51,"") -> 0 | CH53: =IFERROR($C53*CH51,"") -> 0 | CL53: =IFERROR($C53*CL51,"") -> 0 | CP53: =IFERROR($C53*CP51,"") -> 0 | CT53: =IFERROR($C53*CT51,"") -> 0 | CX53: =IFERROR($C53*CX51,"") -> 0 | DB53: =IFERROR($C53*DB51,"") -> 0 | DF53: =IFERROR($C53*DF51,"") -> 0 | DJ53: =IFERROR($C53*DJ51,"") -> 0 | DN53: =IFERROR($C53*DN51,"") -> 0 | DR53: =IFERROR($C53*DR51,"") -> 0 | DV53: =IFERROR($C53*DV51,"") -> 0 | DZ53: =IFERROR($C53*DZ51,"") -> 0 | ED53: =IFERROR($C53*ED51,"") -> 0 | EH53: =IFERROR($C53*EH51,"") -> 0 | EL53: =IFERROR($C53*EL51,"") -> 0 | EP53: =IFERROR($C53*EP51,"") -> 0
D54: 工数 | E54: =SUM(F54:CW54) -> 0
D55: 売上金額 | E55: =SUM(F55:CW55) -> 0 | F55: =IFERROR($C55*F54,"") -> 0 | J55: =IFERROR($C55*J54,"") -> 0 | N55: =IFERROR($C55*N54,"") -> 0 | R55: =IFERROR($C55*R54,"") -> 0 | V55: =IFERROR($C55*V54,"") -> 0 | Z55: =IFERROR($C55*Z54,"") -> 0 | AD55: =IFERROR($C55*AD54,"") -> 0 | AH55: =IFERROR($C55*AH54,"") -> 0 | AL55: =IFERROR($C55*AL54,"") -> 0 | AP55: =IFERROR($C55*AP54,"") -> 0 | AT55: =IFERROR($C55*AT54,"") -> 0 | AX55: =IFERROR($C55*AX54,"") -> 0 | BB55: =IFERROR($C55*BB54,"") -> 0 | BF55: =IFERROR($C55*BF54,"") -> 0 | BJ55: =IFERROR($C55*BJ54,"") -> 0 | BN55: =IFERROR($C55*BN54,"") -> 0 | BR55: =IFERROR($C55*BR54,"") -> 0 | BV55: =IFERROR($C55*BV54,"") -> 0 | BZ55: =IFERROR($C55*BZ54,"") -> 0 | CD55: =IFERROR($C55*CD54,"") -> 0 | CH55: =IFERROR($C55*CH54,"") -> 0 | CL55: =IFERROR($C55*CL54,"") -> 0 | CP55: =IFERROR($C55*CP54,"") -> 0 | CT55: =IFERROR($C55*CT54,"") -> 0 | CX55: =IFERROR($C55*CX54,"") -> 0 | DB55: =IFERROR($C55*DB54,"") -> 0 | DF55: =IFERROR($C55*DF54,"") -> 0 | DJ55: =IFERROR($C55*DJ54,"") -> 0 | DN55: =IFERROR($C55*DN54,"") -> 0 | DR55: =IFERROR($C55*DR54,"") -> 0 | DV55: =IFERROR($C55*DV54,"") -> 0 | DZ55: =IFERROR($C55*DZ54,"") -> 0 | ED55: =IFERROR($C55*ED54,"") -> 0 | EH55: =IFERROR($C55*EH54,"") -> 0 | EL55: =IFERROR($C55*EL54,"") -> 0 | EP55: =IFERROR($C55*EP54,"") -> 0
D56: 原価金額 | E56: =SUM(F56:CW56) -> 0 | F56: =IFERROR($C56*F54,"") -> 0 | J56: =IFERROR($C56*J54,"") -> 0 | N56: =IFERROR($C56*N54,"") -> 0 | R56: =IFERROR($C56*R54,"") -> 0 | V56: =IFERROR($C56*V54,"") -> 0 | Z56: =IFERROR($C56*Z54,"") -> 0 | AD56: =IFERROR($C56*AD54,"") -> 0 | AH56: =IFERROR($C56*AH54,"") -> 0 | AL56: =IFERROR($C56*AL54,"") -> 0 | AP56: =IFERROR($C56*AP54,"") -> 0 | AT56: =IFERROR($C56*AT54,"") -> 0 | AX56: =IFERROR($C56*AX54,"") -> 0 | BB56: =IFERROR($C56*BB54,"") -> 0 | BF56: =IFERROR($C56*BF54,"") -> 0 | BJ56: =IFERROR($C56*BJ54,"") -> 0 | BN56: =IFERROR($C56*BN54,"") -> 0 | BR56: =IFERROR($C56*BR54,"") -> 0 | BV56: =IFERROR($C56*BV54,"") -> 0 | BZ56: =IFERROR($C56*BZ54,"") -> 0 | CD56: =IFERROR($C56*CD54,"") -> 0 | CH56: =IFERROR($C56*CH54,"") -> 0 | CL56: =IFERROR($C56*CL54,"") -> 0 | CP56: =IFERROR($C56*CP54,"") -> 0 | CT56: =IFERROR($C56*CT54,"") -> 0 | CX56: =IFERROR($C56*CX54,"") -> 0 | DB56: =IFERROR($C56*DB54,"") -> 0 | DF56: =IFERROR($C56*DF54,"") -> 0 | DJ56: =IFERROR($C56*DJ54,"") -> 0 | DN56: =IFERROR($C56*DN54,"") -> 0 | DR56: =IFERROR($C56*DR54,"") -> 0 | DV56: =IFERROR($C56*DV54,"") -> 0 | DZ56: =IFERROR($C56*DZ54,"") -> 0 | ED56: =IFERROR($C56*ED54,"") -> 0 | EH56: =IFERROR($C56*EH54,"") -> 0 | EL56: =IFERROR($C56*EL54,"") -> 0 | EP56: =IFERROR($C56*EP54,"") -> 0
B57: 合 計 | E57: =SUM(F57:CW57) -> 119 | F57: =SUMIF($D21:$D56,"工数",F21:I56) -> 4 | J57: =SUMIF($D21:$D56,"工数",J21:M56) -> 4 | N57: =SUMIF($D21:$D56,"工数",N21:Q56) -> 6.5 | R57: =SUMIF($D21:$D56,"工数",R21:U56) -> 6.5 | V57: =SUMIF($D21:$D56,"工数",V21:Y56) -> 7.5 | Z57: =SUMIF($D21:$D56,"工数",Z21:AC56) -> 7.5 | AD57: =SUMIF($D21:$D56,"工数",AD21:AG56) -> 7.5 | AH57: =SUMIF($D21:$D56,"工数",AH21:AK56) -> 5.5 | AL57: =SUMIF($D21:$D56,"工数",AL21:AO56) -> 5.5 | AP57: =SUMIF($D21:$D56,"工数",AP21:AS56) -> 5.5 | AT57: =SUMIF($D21:$D56,"工数",AT21:AW56) -> 5.5 | AX57: =SUMIF($D21:$D56,"工数",AX21:BA56) -> 5.5 | BB57: =SUMIF($D21:$D56,"工数",BB21:BE56) -> 7.5 | BF57: =SUMIF($D21:$D56,"工数",BF21:BI56) -> 7.5 | BJ57: =SUMIF($D21:$D56,"工数",BJ21:BM56) -> 7.5 | BN57: =SUMIF($D21:$D56,"工数",BN21:BQ56) -> 7 | BR57: =SUMIF($D21:$D56,"工数",BR21:BU56) -> 4 | BV57: =SUMIF($D21:$D56,"工数",BV21:BY56) -> 4 | BZ57: =SUMIF($D21:$D56,"工数",BZ21:CC56) -> 4 | CD57: =SUMIF($D21:$D56,"工数",CD21:CG56) -> 4 | CH57: =SUMIF($D21:$D56,"工数",CH21:CK56) -> 2.5 | CL57: =SUMIF($D21:$D56,"工数",CL21:CO56) -> 0 | CP57: =SUMIF($D21:$D56,"工数",CP21:CS56) -> 0 | CT57: =SUMIF($D21:$D56,"工数",CT21:CW56) -> 0 | CX57: =SUMIF($D21:$D56,"工数",CX21:DA56) -> 0 | DB57: =SUMIF($D21:$D56,"工数",DB21:DE56) -> 0 | DF57: =SUMIF($D21:$D56,"工数",DF21:DI56) -> 0 | DJ57: =SUMIF($D21:$D56,"工数",DJ21:DM56) -> 0 | DN57: =SUMIF($D21:$D56,"工数",DN21:DQ56) -> 0 | DR57: =SUMIF($D21:$D56,"工数",DR21:DU56) -> 0 | DV57: =SUMIF($D21:$D56,"工数",DV21:DY56) -> 0 | DZ57: =SUMIF($D21:$D56,"工数",DZ21:EC56) -> 0 | ED57: =SUMIF($D21:$D56,"工数",ED21:EG56) -> 0 | EH57: =SUMIF($D21:$D56,"工数",EH21:EK56) -> 0 | EL57: =SUMIF($D21:$D56,"工数",EL21:EO56) -> 0 | EP57: =SUMIF($D21:$D56,"工数",EP21:ES56) -> 0
E58: =SUM(F58:CW58) -> 132825000 | F58: =SUMIF($D21:$D56,"売上金額",F21:I56) -> 4375000 | J58: =SUMIF($D21:$D56,"売上金額",J21:M56) -> 4375000 | N58: =SUMIF($D21:$D56,"売上金額",N21:Q56) -> 7000000 | R58: =SUMIF($D21:$D56,"売上金額",R21:U56) -> 7000000 | V58: =SUMIF($D21:$D56,"売上金額",V21:Y56) -> 8400000 | Z58: =SUMIF($D21:$D56,"売上金額",Z21:AC56) -> 8400000 | AD58: =SUMIF($D21:$D56,"売上金額",AD21:AG56) -> 8400000 | AH58: =SUMIF($D21:$D56,"売上金額",AH21:AK56) -> 6300000 | AL58: =SUMIF($D21:$D56,"売上金額",AL21:AO56) -> 6300000 | AP58: =SUMIF($D21:$D56,"売上金額",AP21:AS56) -> 6300000 | AT58: =SUMIF($D21:$D56,"売上金額",AT21:AW56) -> 6300000 | AX58: =SUMIF($D21:$D56,"売上金額",AX21:BA56) -> 6300000 | BB58: =SUMIF($D21:$D56,"売上金額",BB21:BE56) -> 8400000 | BF58: =SUMIF($D21:$D56,"売上金額",BF21:BI56) -> 8400000 | BJ58: =SUMIF($D21:$D56,"売上金額",BJ21:BM56) -> 8400000 | BN58: =SUMIF($D21:$D56,"売上金額",BN21:BQ56) -> 7875000 | BR58: =SUMIF($D21:$D56,"売上金額",BR21:BU56) -> 4375000 | BV58: =SUMIF($D21:$D56,"売上金額",BV21:BY56) -> 4375000 | BZ58: =SUMIF($D21:$D56,"売上金額",BZ21:CC56) -> 4375000 | CD58: =SUMIF($D21:$D56,"売上金額",CD21:CG56) -> 4375000 | CH58: =SUMIF($D21:$D56,"売上金額",CH21:CK56) -> 2800000 | CL58: =SUMIF($D21:$D56,"売上金額",CL21:CO56) -> 0 | CP58: =SUMIF($D21:$D56,"売上金額",CP21:CS56) -> 0 | CT58: =SUMIF($D21:$D56,"売上金額",CT21:CW56) -> 0 | CX58: =SUMIF($D21:$D56,"売上金額",CX21:DA56) -> 0 | DB58: =SUMIF($D21:$D56,"売上金額",DB21:DE56) -> 0 | DF58: =SUMIF($D21:$D56,"売上金額",DF21:DI56) -> 0 | DJ58: =SUMIF($D21:$D56,"売上金額",DJ21:DM56) -> 0 | DN58: =SUMIF($D21:$D56,"売上金額",DN21:DQ56) -> 0 | DR58: =SUMIF($D21:$D56,"売上金額",DR21:DU56) -> 0 | DV58: =SUMIF($D21:$D56,"売上金額",DV21:DY56) -> 0 | DZ58: =SUMIF($D21:$D56,"売上金額",DZ21:EC56) -> 0 | ED58: =SUMIF($D21:$D56,"売上金額",ED21:EG56) -> 0 | EH58: =SUMIF($D21:$D56,"売上金額",EH21:EK56) -> 0 | EL58: =SUMIF($D21:$D56,"売上金額",EL21:EO56) -> 0 | EP58: =SUMIF($D21:$D56,"売上金額",EP21:ES56) -> 0
E59: =SUM(F59:CW59) -> 66900000 | F59: =SUMIF($D21:$D56,"原価金額",F21:I56) -> 1950000 | J59: =SUMIF($D21:$D56,"原価金額",J21:M56) -> 1950000 | N59: =SUMIF($D21:$D56,"原価金額",N21:Q56) -> 3200000 | R59: =SUMIF($D21:$D56,"原価金額",R21:U56) -> 3200000 | V59: =SUMIF($D21:$D56,"原価金額",V21:Y56) -> 4400000 | Z59: =SUMIF($D21:$D56,"原価金額",Z21:AC56) -> 4400000 | AD59: =SUMIF($D21:$D56,"原価金額",AD21:AG56) -> 4400000 | AH59: =SUMIF($D21:$D56,"原価金額",AH21:AK56) -> 3400000 | AL59: =SUMIF($D21:$D56,"原価金額",AL21:AO56) -> 3400000 | AP59: =SUMIF($D21:$D56,"原価金額",AP21:AS56) -> 3400000 | AT59: =SUMIF($D21:$D56,"原価金額",AT21:AW56) -> 3400000 | AX59: =SUMIF($D21:$D56,"原価金額",AX21:BA56) -> 3400000 | BB59: =SUMIF($D21:$D56,"原価金額",BB21:BE56) -> 4400000 | BF59: =SUMIF($D21:$D56,"原価金額",BF21:BI56) -> 4400000 | BJ59: =SUMIF($D21:$D56,"原価金額",BJ21:BM56) -> 4400000 | BN59: =SUMIF($D21:$D56,"原価金額",BN21:BQ56) -> 4150000 | BR59: =SUMIF($D21:$D56,"原価金額",BR21:BU56) -> 1950000 | BV59: =SUMIF($D21:$D56,"原価金額",BV21:BY56) -> 1950000 | BZ59: =SUMIF($D21:$D56,"原価金額",BZ21:CC56) -> 1950000 | CD59: =SUMIF($D21:$D56,"原価金額",CD21:CG56) -> 1950000 | CH59: =SUMIF($D21:$D56,"原価金額",CH21:CK56) -> 1250000 | CL59: =SUMIF($D21:$D56,"原価金額",CL21:CO56) -> 0 | CP59: =SUMIF($D21:$D56,"原価金額",CP21:CS56) -> 0 | CT59: =SUMIF($D21:$D56,"原価金額",CT21:CW56) -> 0 | CX59: =SUMIF($D21:$D56,"原価金額",CX21:DA56) -> 0 | DB59: =SUMIF($D21:$D56,"原価金額",DB21:DE56) -> 0 | DF59: =SUMIF($D21:$D56,"原価金額",DF21:DI56) -> 0 | DJ59: =SUMIF($D21:$D56,"原価金額",DJ21:DM56) -> 0 | DN59: =SUMIF($D21:$D56,"原価金額",DN21:DQ56) -> 0 | DR59: =SUMIF($D21:$D56,"原価金額",DR21:DU56) -> 0 | DV59: =SUMIF($D21:$D56,"原価金額",DV21:DY56) -> 0 | DZ59: =SUMIF($D21:$D56,"原価金額",DZ21:EC56) -> 0 | ED59: =SUMIF($D21:$D56,"原価金額",ED21:EG56) -> 0 | EH59: =SUMIF($D21:$D56,"原価金額",EH21:EK56) -> 0 | EL59: =SUMIF($D21:$D56,"原価金額",EL21:EO56) -> 0 | EP59: =SUMIF($D21:$D56,"原価金額",EP21:ES56) -> 0
A61: 【BP】 | C61: ※必要に応じて修正すること。
B62: 要員名 | C62: 月額単価 | D62: 内訳 | E62: 合計 | F62: 2026年 | BB62: 2027年 | CX62: 2028年
F63: 1Q | R63: 2Q | AD63: 3Q | AP63: 4Q | BB63: 1Q | BN63: 2Q | BZ63: 3Q | CL63: 4Q | CX63: 1Q | DJ63: 2Q | DV63: 3Q | EH63: 4Q
C64: (上段:売上、下段:原価) | F64: 45017 | J64: 45047 | N64: 45078 | R64: 45108 | V64: 45139 | Z64: 45170 | AD64: 45200 | AH64: 45231 | AL64: 45261 | AP64: 45292 | AT64: 45323 | AX64: 45352 | BB64: 45383 | BF64: 45413 | BJ64: 45444 | BN64: 45474 | BR64: 45505 | BV64: 45536 | BZ64: 45566 | CD64: 45597 | CH64: 45627 | CL64: 45658 | CP64: 45689 | CT64: 45717 | CX64: 45383 | DB64: 45413 | DF64: 45444 | DJ64: 45474 | DN64: 45505 | DR64: 45536 | DV64: 45566 | DZ64: 45597 | ED64: 45627 | EH64: 45658 | EL64: 45689 | EP64: 45717
B65: 五石 | D65: 工数 | E65: =SUM(F65:ES65) -> 10.5 | F65: 0.5 | J65: 0.5 | N65: 0.5 | R65: 0.5 | V65: 0.5 | Z65: 0.5 | AD65: 0.5 | AH65: 0.5 | AL65: 0.5 | AP65: 0.5 | AT65: 0.5 | AX65: 0.5 | BB65: 0.5 | BF65: 0.5 | BJ65: 0.5 | BN65: 0.5 | BR65: 0.5 | BV65: 0.5 | BZ65: 0.5 | CD65: 0.5 | CH65: 0.5 | DR65: =IF(ISERROR(VLOOKUP(RIGHT(CELL("filename",$A$1),LEN(CELL("filename",$A$1))-FIND("]",CELL("filename",$A$1)))&$B65,[2]要員計画!$L:$AJ,((COLUMN()-1)/4)+1,FALSE)),0,VLOOKUP(RIGHT(CELL("filename",$A$1),LEN(CELL("filename",$A$1))-FIND("]",CELL("filename",$A$1)))&$B65,[2]要員計画!$L:$AJ,((COLUMN()-1)/4)+1,FALSE)) -> 0 | DV65: =IF(ISERROR(VLOOKUP(RIGHT(CELL("filename",$A$1),LEN(CELL("filename",$A$1))-FIND("]",CELL("filename",$A$1)))&$B65,[2]要員計画!$L:$AJ,((COLUMN()-1)/4)+1,FALSE)),0,VLOOKUP(RIGHT(CELL("filename",$A$1),LEN(CELL("filename",$A$1))-FIND("]",CELL("filename",$A$1)))&$B65,[2]要員計画!$L:$AJ,((COLUMN()-1)/4)+1,FALSE)) -> 0 | DZ65: =IF(ISERROR(VLOOKUP(RIGHT(CELL("filename",$A$1),LEN(CELL("filename",$A$1))-FIND("]",CELL("filename",$A$1)))&$B65,[2]要員計画!$L:$AJ,((COLUMN()-1)/4)+1,FALSE)),0,VLOOKUP(RIGHT(CELL("filename",$A$1),LEN(CELL("filename",$A$1))-FIND("]",CELL("filename",$A$1)))&$B65,[2]要員計画!$L:$AJ,((COLUMN()-1)/4)+1,FALSE)) -> 0 | ED65: =IF(ISERROR(VLOOKUP(RIGHT(CELL("filename",$A$1),LEN(CELL("filename",$A$1))-FIND("]",CELL("filename",$A$1)))&$B65,[2]要員計画!$L:$AJ,((COLUMN()-1)/4)+1,FALSE)),0,VLOOKUP(RIGHT(CELL("filename",$A$1),LEN(CELL("filename",$A$1))-FIND("]",CELL("filename",$A$1)))&$B65,[2]要員計画!$L:$AJ,((COLUMN()-1)/4)+1,FALSE)) -> 0 | EH65: =IF(ISERROR(VLOOKUP(RIGHT(CELL("filename",$A$1),LEN(CELL("filename",$A$1))-FIND("]",CELL("filename",$A$1)))&$B65,[2]要員計画!$L:$AJ,((COLUMN()-1)/4)+1,FALSE)),0,VLOOKUP(RIGHT(CELL("filename",$A$1),LEN(CELL("filename",$A$1))-FIND("]",CELL("filename",$A$1)))&$B65,[2]要員計画!$L:$AJ,((COLUMN()-1)/4)+1,FALSE)) -> 0 | EL65: =IF(ISERROR(VLOOKUP(RIGHT(CELL("filename",$A$1),LEN(CELL("filename",$A$1))-FIND("]",CELL("filename",$A$1)))&$B65,[2]要員計画!$L:$AJ,((COLUMN()-1)/4)+1,FALSE)),0,VLOOKUP(RIGHT(CELL("filename",$A$1),LEN(CELL("filename",$A$1))-FIND("]",CELL("filename",$A$1)))&$B65,[2]要員計画!$L:$AJ,((COLUMN()-1)/4)+1,FALSE)) -> 0 | EP65: =IF(ISERROR(VLOOKUP(RIGHT(CELL("filename",$A$1),LEN(CELL("filename",$A$1))-FIND("]",CELL("filename",$A$1)))&$B65,[2]要員計画!$L:$AJ,((COLUMN()-1)/4)+1,FALSE)),0,VLOOKUP(RIGHT(CELL("filename",$A$1),LEN(CELL("filename",$A$1))-FIND("]",CELL("filename",$A$1)))&$B65,[2]要員計画!$L:$AJ,((COLUMN()-1)/4)+1,FALSE)) -> 0
C66: 1050000 | D66: 売上金額 | E66: =SUM(F66:CW66) -> 11025000 | F66: =IFERROR($C66*F65,"") -> 525000 | J66: =IFERROR($C66*J65,"") -> 525000 | N66: =IFERROR($C66*N65,"") -> 525000 | R66: =IFERROR($C66*R65,"") -> 525000 | V66: =IFERROR($C66*V65,"") -> 525000 | Z66: =IFERROR($C66*Z65,"") -> 525000 | AD66: =IFERROR($C66*AD65,"") -> 525000 | AH66: =IFERROR($C66*AH65,"") -> 525000 | AL66: =IFERROR($C66*AL65,"") -> 525000 | AP66: =IFERROR($C66*AP65,"") -> 525000 | AT66: =IFERROR($C66*AT65,"") -> 525000 | AX66: =IFERROR($C66*AX65,"") -> 525000 | BB66: =IFERROR($C66*BB65,"") -> 525000 | BF66: =IFERROR($C66*BF65,"") -> 525000 | BJ66: =IFERROR($C66*BJ65,"") -> 525000 | BN66: =IFERROR($C66*BN65,"") -> 525000 | BR66: =IFERROR($C66*BR65,"") -> 525000 | BV66: =IFERROR($C66*BV65,"") -> 525000 | BZ66: =IFERROR($C66*BZ65,"") -> 525000 | CD66: =IFERROR($C66*CD65,"") -> 525000 | CH66: =IFERROR($C66*CH65,"") -> 525000 | CL66: =IFERROR($C66*CL65,"") -> 0 | CP66: =IFERROR($C66*CP65,"") -> 0 | CT66: =IFERROR($C66*CT65,"") -> 0 | CX66: =IFERROR($C66*CX65,"") -> 0 | DB66: =IFERROR($C66*DB65,"") -> 0 | DF66: =IFERROR($C66*DF65,"") -> 0 | DJ66: =IFERROR($C66*DJ65,"") -> 0 | DN66: =IFERROR($C66*DN65,"") -> 0 | DR66: =IFERROR($C66*DR65,"") -> 0 | DV66: =IFERROR($C66*DV65,"") -> 0 | DZ66: =IFERROR($C66*DZ65,"") -> 0 | ED66: =IFERROR($C66*ED65,"") -> 0 | EH66: =IFERROR($C66*EH65,"") -> 0 | EL66: =IFERROR($C66*EL65,"") -> 0 | EP66: =IFERROR($C66*EP65,"") -> 0
C67: 760000 | D67: 原価金額 | E67: =SUM(F67:CW67) -> 7980000 | F67: =IFERROR($C67*F65,"") -> 380000 | J67: =IFERROR($C67*J65,"") -> 380000 | N67: =IFERROR($C67*N65,"") -> 380000 | R67: =IFERROR($C67*R65,"") -> 380000 | V67: =IFERROR($C67*V65,"") -> 380000 | Z67: =IFERROR($C67*Z65,"") -> 380000 | AD67: =IFERROR($C67*AD65,"") -> 380000 | AH67: =IFERROR($C67*AH65,"") -> 380000 | AL67: =IFERROR($C67*AL65,"") -> 380000 | AP67: =IFERROR($C67*AP65,"") -> 380000 | AT67: =IFERROR($C67*AT65,"") -> 380000 | AX67: =IFERROR($C67*AX65,"") -> 380000 | BB67: =IFERROR($C67*BB65,"") -> 380000 | BF67: =IFERROR($C67*BF65,"") -> 380000 | BJ67: =IFERROR($C67*BJ65,"") -> 380000 | BN67: =IFERROR($C67*BN65,"") -> 380000 | BR67: =IFERROR($C67*BR65,"") -> 380000 | BV67: =IFERROR($C67*BV65,"") -> 380000 | BZ67: =IFERROR($C67*BZ65,"") -> 380000 | CD67: =IFERROR($C67*CD65,"") -> 380000 | CH67: =IFERROR($C67*CH65,"") -> 380000 | CL67: =IFERROR($C67*CL65,"") -> 0 | CP67: =IFERROR($C67*CP65,"") -> 0 | CT67: =IFERROR($C67*CT65,"") -> 0 | CX67: =IFERROR($C67*CX65,"") -> 0 | DB67: =IFERROR($C67*DB65,"") -> 0 | DF67: =IFERROR($C67*DF65,"") -> 0 | DJ67: =IFERROR($C67*DJ65,"") -> 0 | DN67: =IFERROR($C67*DN65,"") -> 0 | DR67: =IFERROR($C67*DR65,"") -> 0 | DV67: =IFERROR($C67*DV65,"") -> 0 | DZ67: =IFERROR($C67*DZ65,"") -> 0 | ED67: =IFERROR($C67*ED65,"") -> 0 | EH67: =IFERROR($C67*EH65,"") -> 0 | EL67: =IFERROR($C67*EL65,"") -> 0 | EP67: =IFERROR($C67*EP65,"") -> 0
B68: 砂金 | D68: 工数 | E68: =SUM(F68:ES68) -> 10.25 | F68: 0.5 | J68: 0.5 | N68: 0.5 | R68: 0.5 | V68: 0.5 | Z68: 0.5 | AD68: 0.25 | AH68: 0.5 | AL68: 0.5 | AP68: 0.5 | AT68: 0.5 | AX68: 0.5 | BB68: 0.5 | BF68: 0.5 | BJ68: 0.5 | BN68: 0.5 | BR68: 0.5 | BV68: 0.5 | BZ68: 0.5 | CD68: 0.5 | CH68: 0.5 | DR68: =IF(ISERROR(VLOOKUP(RIGHT(CELL("filename",$A$1),LEN(CELL("filename",$A$1))-FIND("]",CELL("filename",$A$1)))&$B68,[2]要員計画!$L:$AJ,((COLUMN()-1)/4)+1,FALSE)),0,VLOOKUP(RIGHT(CELL("filename",$A$1),LEN(CELL("filename",$A$1))-FIND("]",CELL("filename",$A$1)))&$B68,[2]要員計画!$L:$AJ,((COLUMN()-1)/4)+1,FALSE)) -> 0 | DV68: =IF(ISERROR(VLOOKUP(RIGHT(CELL("filename",$A$1),LEN(CELL("filename",$A$1))-FIND("]",CELL("filename",$A$1)))&$B68,[2]要員計画!$L:$AJ,((COLUMN()-1)/4)+1,FALSE)),0,VLOOKUP(RIGHT(CELL("filename",$A$1),LEN(CELL("filename",$A$1))-FIND("]",CELL("filename",$A$1)))&$B68,[2]要員計画!$L:$AJ,((COLUMN()-1)/4)+1,FALSE)) -> 0 | DZ68: =IF(ISERROR(VLOOKUP(RIGHT(CELL("filename",$A$1),LEN(CELL("filename",$A$1))-FIND("]",CELL("filename",$A$1)))&$B68,[2]要員計画!$L:$AJ,((COLUMN()-1)/4)+1,FALSE)),0,VLOOKUP(RIGHT(CELL("filename",$A$1),LEN(CELL("filename",$A$1))-FIND("]",CELL("filename",$A$1)))&$B68,[2]要員計画!$L:$AJ,((COLUMN()-1)/4)+1,FALSE)) -> 0 | ED68: =IF(ISERROR(VLOOKUP(RIGHT(CELL("filename",$A$1),LEN(CELL("filename",$A$1))-FIND("]",CELL("filename",$A$1)))&$B68,[2]要員計画!$L:$AJ,((COLUMN()-1)/4)+1,FALSE)),0,VLOOKUP(RIGHT(CELL("filename",$A$1),LEN(CELL("filename",$A$1))-FIND("]",CELL("filename",$A$1)))&$B68,[2]要員計画!$L:$AJ,((COLUMN()-1)/4)+1,FALSE)) -> 0 | EH68: =IF(ISERROR(VLOOKUP(RIGHT(CELL("filename",$A$1),LEN(CELL("filename",$A$1))-FIND("]",CELL("filename",$A$1)))&$B68,[2]要員計画!$L:$AJ,((COLUMN()-1)/4)+1,FALSE)),0,VLOOKUP(RIGHT(CELL("filename",$A$1),LEN(CELL("filename",$A$1))-FIND("]",CELL("filename",$A$1)))&$B68,[2]要員計画!$L:$AJ,((COLUMN()-1)/4)+1,FALSE)) -> 0 | EL68: =IF(ISERROR(VLOOKUP(RIGHT(CELL("filename",$A$1),LEN(CELL("filename",$A$1))-FIND("]",CELL("filename",$A$1)))&$B68,[2]要員計画!$L:$AJ,((COLUMN()-1)/4)+1,FALSE)),0,VLOOKUP(RIGHT(CELL("filename",$A$1),LEN(CELL("filename",$A$1))-FIND("]",CELL("filename",$A$1)))&$B68,[2]要員計画!$L:$AJ,((COLUMN()-1)/4)+1,FALSE)) -> 0 | EP68: =IF(ISERROR(VLOOKUP(RIGHT(CELL("filename",$A$1),LEN(CELL("filename",$A$1))-FIND("]",CELL("filename",$A$1)))&$B68,[2]要員計画!$L:$AJ,((COLUMN()-1)/4)+1,FALSE)),0,VLOOKUP(RIGHT(CELL("filename",$A$1),LEN(CELL("filename",$A$1))-FIND("]",CELL("filename",$A$1)))&$B68,[2]要員計画!$L:$AJ,((COLUMN()-1)/4)+1,FALSE)) -> 0
C69: 1050000 | D69: 売上金額 | E69: =SUM(F69:CW69) -> 10762500 | F69: =IFERROR($C69*F68,"") -> 525000 | J69: =IFERROR($C69*J68,"") -> 525000 | N69: =IFERROR($C69*N68,"") -> 525000 | R69: =IFERROR($C69*R68,"") -> 525000 | V69: =IFERROR($C69*V68,"") -> 525000 | Z69: =IFERROR($C69*Z68,"") -> 525000 | AD69: =IFERROR($C69*AD68,"") -> 262500 | AH69: =IFERROR($C69*AH68,"") -> 525000 | AL69: =IFERROR($C69*AL68,"") -> 525000 | AP69: =IFERROR($C69*AP68,"") -> 525000 | AT69: =IFERROR($C69*AT68,"") -> 525000 | AX69: =IFERROR($C69*AX68,"") -> 525000 | BB69: =IFERROR($C69*BB68,"") -> 525000 | BF69: =IFERROR($C69*BF68,"") -> 525000 | BJ69: =IFERROR($C69*BJ68,"") -> 525000 | BN69: =IFERROR($C69*BN68,"") -> 525000 | BR69: =IFERROR($C69*BR68,"") -> 525000 | BV69: =IFERROR($C69*BV68,"") -> 525000 | BZ69: =IFERROR($C69*BZ68,"") -> 525000 | CD69: =IFERROR($C69*CD68,"") -> 525000 | CH69: =IFERROR($C69*CH68,"") -> 525000 | CL69: =IFERROR($C69*CL68,"") -> 0 | CP69: =IFERROR($C69*CP68,"") -> 0 | CT69: =IFERROR($C69*CT68,"") -> 0 | CX69: =IFERROR($C69*CX68,"") -> 0 | DB69: =IFERROR($C69*DB68,"") -> 0 | DF69: =IFERROR($C69*DF68,"") -> 0 | DJ69: =IFERROR($C69*DJ68,"") -> 0 | DN69: =IFERROR($C69*DN68,"") -> 0 | DR69: =IFERROR($C69*DR68,"") -> 0 | DV69: =IFERROR($C69*DV68,"") -> 0 | DZ69: =IFERROR($C69*DZ68,"") -> 0 | ED69: =IFERROR($C69*ED68,"") -> 0 | EH69: =IFERROR($C69*EH68,"") -> 0 | EL69: =IFERROR($C69*EL68,"") -> 0 | EP69: =IFERROR($C69*EP68,"") -> 0
C70: 500000 | D70: 原価金額 | E70: =SUM(F70:CW70) -> 5125000 | F70: =IFERROR($C70*F68,"") -> 250000 | J70: =IFERROR($C70*J68,"") -> 250000 | N70: =IFERROR($C70*N68,"") -> 250000 | R70: =IFERROR($C70*R68,"") -> 250000 | V70: =IFERROR($C70*V68,"") -> 250000 | Z70: =IFERROR($C70*Z68,"") -> 250000 | AD70: =IFERROR($C70*AD68,"") -> 125000 | AH70: =IFERROR($C70*AH68,"") -> 250000 | AL70: =IFERROR($C70*AL68,"") -> 250000 | AP70: =IFERROR($C70*AP68,"") -> 250000 | AT70: =IFERROR($C70*AT68,"") -> 250000 | AX70: =IFERROR($C70*AX68,"") -> 250000 | BB70: =IFERROR($C70*BB68,"") -> 250000 | BF70: =IFERROR($C70*BF68,"") -> 250000 | BJ70: =IFERROR($C70*BJ68,"") -> 250000 | BN70: =IFERROR($C70*BN68,"") -> 250000 | BR70: =IFERROR($C70*BR68,"") -> 250000 | BV70: =IFERROR($C70*BV68,"") -> 250000 | BZ70: =IFERROR($C70*BZ68,"") -> 250000 | CD70: =IFERROR($C70*CD68,"") -> 250000 | CH70: =IFERROR($C70*CH68,"") -> 250000 | CL70: =IFERROR($C70*CL68,"") -> 0 | CP70: =IFERROR($C70*CP68,"") -> 0 | CT70: =IFERROR($C70*CT68,"") -> 0 | CX70: =IFERROR($C70*CX68,"") -> 0 | DB70: =IFERROR($C70*DB68,"") -> 0 | DF70: =IFERROR($C70*DF68,"") -> 0 | DJ70: =IFERROR($C70*DJ68,"") -> 0 | DN70: =IFERROR($C70*DN68,"") -> 0 | DR70: =IFERROR($C70*DR68,"") -> 0 | DV70: =IFERROR($C70*DV68,"") -> 0 | DZ70: =IFERROR($C70*DZ68,"") -> 0 | ED70: =IFERROR($C70*ED68,"") -> 0 | EH70: =IFERROR($C70*EH68,"") -> 0 | EL70: =IFERROR($C70*EL68,"") -> 0 | EP70: =IFERROR($C70*EP68,"") -> 0
B71: 国内BP１ | D71: 工数 | E71: =SUM(F71:ES71) -> 18.5 | N71: 1 | R71: 1 | V71: 1 | Z71: 1 | AD71: 1 | AH71: 1 | AL71: 1 | AP71: 1 | AT71: 1 | AX71: 1 | BB71: 1 | BF71: 1 | BJ71: 1 | BN71: 1 | BR71: 1 | BV71: 1 | BZ71: 1 | CD71: 1 | CH71: 0.5 | DR71: =IF(ISERROR(VLOOKUP(RIGHT(CELL("filename",$A$1),LEN(CELL("filename",$A$1))-FIND("]",CELL("filename",$A$1)))&$B71,[2]要員計画!$L:$AJ,((COLUMN()-1)/4)+1,FALSE)),0,VLOOKUP(RIGHT(CELL("filename",$A$1),LEN(CELL("filename",$A$1))-FIND("]",CELL("filename",$A$1)))&$B71,[2]要員計画!$L:$AJ,((COLUMN()-1)/4)+1,FALSE)) -> 0 | DV71: =IF(ISERROR(VLOOKUP(RIGHT(CELL("filename",$A$1),LEN(CELL("filename",$A$1))-FIND("]",CELL("filename",$A$1)))&$B71,[2]要員計画!$L:$AJ,((COLUMN()-1)/4)+1,FALSE)),0,VLOOKUP(RIGHT(CELL("filename",$A$1),LEN(CELL("filename",$A$1))-FIND("]",CELL("filename",$A$1)))&$B71,[2]要員計画!$L:$AJ,((COLUMN()-1)/4)+1,FALSE)) -> 0 | DZ71: =IF(ISERROR(VLOOKUP(RIGHT(CELL("filename",$A$1),LEN(CELL("filename",$A$1))-FIND("]",CELL("filename",$A$1)))&$B71,[2]要員計画!$L:$AJ,((COLUMN()-1)/4)+1,FALSE)),0,VLOOKUP(RIGHT(CELL("filename",$A$1),LEN(CELL("filename",$A$1))-FIND("]",CELL("filename",$A$1)))&$B71,[2]要員計画!$L:$AJ,((COLUMN()-1)/4)+1,FALSE)) -> 0 | ED71: =IF(ISERROR(VLOOKUP(RIGHT(CELL("filename",$A$1),LEN(CELL("filename",$A$1))-FIND("]",CELL("filename",$A$1)))&$B71,[2]要員計画!$L:$AJ,((COLUMN()-1)/4)+1,FALSE)),0,VLOOKUP(RIGHT(CELL("filename",$A$1),LEN(CELL("filename",$A$1))-FIND("]",CELL("filename",$A$1)))&$B71,[2]要員計画!$L:$AJ,((COLUMN()-1)/4)+1,FALSE)) -> 0 | EH71: =IF(ISERROR(VLOOKUP(RIGHT(CELL("filename",$A$1),LEN(CELL("filename",$A$1))-FIND("]",CELL("filename",$A$1)))&$B71,[2]要員計画!$L:$AJ,((COLUMN()-1)/4)+1,FALSE)),0,VLOOKUP(RIGHT(CELL("filename",$A$1),LEN(CELL("filename",$A$1))-FIND("]",CELL("filename",$A$1)))&$B71,[2]要員計画!$L:$AJ,((COLUMN()-1)/4)+1,FALSE)) -> 0 | EL71: =IF(ISERROR(VLOOKUP(RIGHT(CELL("filename",$A$1),LEN(CELL("filename",$A$1))-FIND("]",CELL("filename",$A$1)))&$B71,[2]要員計画!$L:$AJ,((COLUMN()-1)/4)+1,FALSE)),0,VLOOKUP(RIGHT(CELL("filename",$A$1),LEN(CELL("filename",$A$1))-FIND("]",CELL("filename",$A$1)))&$B71,[2]要員計画!$L:$AJ,((COLUMN()-1)/4)+1,FALSE)) -> 0 | EP71: =IF(ISERROR(VLOOKUP(RIGHT(CELL("filename",$A$1),LEN(CELL("filename",$A$1))-FIND("]",CELL("filename",$A$1)))&$B71,[2]要員計画!$L:$AJ,((COLUMN()-1)/4)+1,FALSE)),0,VLOOKUP(RIGHT(CELL("filename",$A$1),LEN(CELL("filename",$A$1))-FIND("]",CELL("filename",$A$1)))&$B71,[2]要員計画!$L:$AJ,((COLUMN()-1)/4)+1,FALSE)) -> 0
C72: 1050000 | D72: 売上金額 | E72: =SUM(F72:CW72) -> 19425000 | F72: =IFERROR($C72*F71,"") -> 0 | J72: =IFERROR($C72*J71,"") -> 0 | N72: =IFERROR($C72*N71,"") -> 1050000 | R72: =IFERROR($C72*R71,"") -> 1050000 | V72: =IFERROR($C72*V71,"") -> 1050000 | Z72: =IFERROR($C72*Z71,"") -> 1050000 | AD72: =IFERROR($C72*AD71,"") -> 1050000 | AH72: =IFERROR($C72*AH71,"") -> 1050000 | AL72: =IFERROR($C72*AL71,"") -> 1050000 | AP72: =IFERROR($C72*AP71,"") -> 1050000 | AT72: =IFERROR($C72*AT71,"") -> 1050000 | AX72: =IFERROR($C72*AX71,"") -> 1050000 | BB72: =IFERROR($C72*BB71,"") -> 1050000 | BF72: =IFERROR($C72*BF71,"") -> 1050000 | BJ72: =IFERROR($C72*BJ71,"") -> 1050000 | BN72: =IFERROR($C72*BN71,"") -> 1050000 | BR72: =IFERROR($C72*BR71,"") -> 1050000 | BV72: =IFERROR($C72*BV71,"") -> 1050000 | BZ72: =IFERROR($C72*BZ71,"") -> 1050000 | CD72: =IFERROR($C72*CD71,"") -> 1050000 | CH72: =IFERROR($C72*CH71,"") -> 525000 | CL72: =IFERROR($C72*CL71,"") -> 0 | CP72: =IFERROR($C72*CP71,"") -> 0 | CT72: =IFERROR($C72*CT71,"") -> 0 | CX72: =IFERROR($C72*CX71,"") -> 0 | DB72: =IFERROR($C72*DB71,"") -> 0 | DF72: =IFERROR($C72*DF71,"") -> 0 | DJ72: =IFERROR($C72*DJ71,"") -> 0 | DN72: =IFERROR($C72*DN71,"") -> 0 | DR72: =IFERROR($C72*DR71,"") -> 0 | DV72: =IFERROR($C72*DV71,"") -> 0 | DZ72: =IFERROR($C72*DZ71,"") -> 0 | ED72: =IFERROR($C72*ED71,"") -> 0 | EH72: =IFERROR($C72*EH71,"") -> 0 | EL72: =IFERROR($C72*EL71,"") -> 0 | EP72: =IFERROR($C72*EP71,"") -> 0
C73: 800000 | D73: 原価金額 | E73: =SUM(F73:CW73) -> 14800000 | F73: =IFERROR($C73*F71,"") -> 0 | J73: =IFERROR($C73*J71,"") -> 0 | N73: =IFERROR($C73*N71,"") -> 800000 | R73: =IFERROR($C73*R71,"") -> 800000 | V73: =IFERROR($C73*V71,"") -> 800000 | Z73: =IFERROR($C73*Z71,"") -> 800000 | AD73: =IFERROR($C73*AD71,"") -> 800000 | AH73: =IFERROR($C73*AH71,"") -> 800000 | AL73: =IFERROR($C73*AL71,"") -> 800000 | AP73: =IFERROR($C73*AP71,"") -> 800000 | AT73: =IFERROR($C73*AT71,"") -> 800000 | AX73: =IFERROR($C73*AX71,"") -> 800000 | BB73: =IFERROR($C73*BB71,"") -> 800000 | BF73: =IFERROR($C73*BF71,"") -> 800000 | BJ73: =IFERROR($C73*BJ71,"") -> 800000 | BN73: =IFERROR($C73*BN71,"") -> 800000 | BR73: =IFERROR($C73*BR71,"") -> 800000 | BV73: =IFERROR($C73*BV71,"") -> 800000 | BZ73: =IFERROR($C73*BZ71,"") -> 800000 | CD73: =IFERROR($C73*CD71,"") -> 800000 | CH73: =IFERROR($C73*CH71,"") -> 400000 | CL73: =IFERROR($C73*CL71,"") -> 0 | CP73: =IFERROR($C73*CP71,"") -> 0 | CT73: =IFERROR($C73*CT71,"") -> 0 | CX73: =IFERROR($C73*CX71,"") -> 0 | DB73: =IFERROR($C73*DB71,"") -> 0 | DF73: =IFERROR($C73*DF71,"") -> 0 | DJ73: =IFERROR($C73*DJ71,"") -> 0 | DN73: =IFERROR($C73*DN71,"") -> 0 | DR73: =IFERROR($C73*DR71,"") -> 0 | DV73: =IFERROR($C73*DV71,"") -> 0 | DZ73: =IFERROR($C73*DZ71,"") -> 0 | ED73: =IFERROR($C73*ED71,"") -> 0 | EH73: =IFERROR($C73*EH71,"") -> 0 | EL73: =IFERROR($C73*EL71,"") -> 0 | EP73: =IFERROR($C73*EP71,"") -> 0
B74: 国内BP2 | D74: 工数 | E74: =SUM(F74:ES74) -> 18.5 | N74: 1 | R74: 1 | V74: 1 | Z74: 1 | AD74: 1 | AH74: 1 | AL74: 1 | AP74: 1 | AT74: 1 | AX74: 1 | BB74: 1 | BF74: 1 | BJ74: 1 | BN74: 1 | BR74: 1 | BV74: 1 | BZ74: 1 | CD74: 1 | CH74: 0.5 | DR74: =IF(ISERROR(VLOOKUP(RIGHT(CELL("filename",$A$1),LEN(CELL("filename",$A$1))-FIND("]",CELL("filename",$A$1)))&$B74,[2]要員計画!$L:$AJ,((COLUMN()-1)/4)+1,FALSE)),0,VLOOKUP(RIGHT(CELL("filename",$A$1),LEN(CELL("filename",$A$1))-FIND("]",CELL("filename",$A$1)))&$B74,[2]要員計画!$L:$AJ,((COLUMN()-1)/4)+1,FALSE)) -> 0 | DV74: =IF(ISERROR(VLOOKUP(RIGHT(CELL("filename",$A$1),LEN(CELL("filename",$A$1))-FIND("]",CELL("filename",$A$1)))&$B74,[2]要員計画!$L:$AJ,((COLUMN()-1)/4)+1,FALSE)),0,VLOOKUP(RIGHT(CELL("filename",$A$1),LEN(CELL("filename",$A$1))-FIND("]",CELL("filename",$A$1)))&$B74,[2]要員計画!$L:$AJ,((COLUMN()-1)/4)+1,FALSE)) -> 0 | DZ74: =IF(ISERROR(VLOOKUP(RIGHT(CELL("filename",$A$1),LEN(CELL("filename",$A$1))-FIND("]",CELL("filename",$A$1)))&$B74,[2]要員計画!$L:$AJ,((COLUMN()-1)/4)+1,FALSE)),0,VLOOKUP(RIGHT(CELL("filename",$A$1),LEN(CELL("filename",$A$1))-FIND("]",CELL("filename",$A$1)))&$B74,[2]要員計画!$L:$AJ,((COLUMN()-1)/4)+1,FALSE)) -> 0 | ED74: =IF(ISERROR(VLOOKUP(RIGHT(CELL("filename",$A$1),LEN(CELL("filename",$A$1))-FIND("]",CELL("filename",$A$1)))&$B74,[2]要員計画!$L:$AJ,((COLUMN()-1)/4)+1,FALSE)),0,VLOOKUP(RIGHT(CELL("filename",$A$1),LEN(CELL("filename",$A$1))-FIND("]",CELL("filename",$A$1)))&$B74,[2]要員計画!$L:$AJ,((COLUMN()-1)/4)+1,FALSE)) -> 0 | EH74: =IF(ISERROR(VLOOKUP(RIGHT(CELL("filename",$A$1),LEN(CELL("filename",$A$1))-FIND("]",CELL("filename",$A$1)))&$B74,[2]要員計画!$L:$AJ,((COLUMN()-1)/4)+1,FALSE)),0,VLOOKUP(RIGHT(CELL("filename",$A$1),LEN(CELL("filename",$A$1))-FIND("]",CELL("filename",$A$1)))&$B74,[2]要員計画!$L:$AJ,((COLUMN()-1)/4)+1,FALSE)) -> 0 | EL74: =IF(ISERROR(VLOOKUP(RIGHT(CELL("filename",$A$1),LEN(CELL("filename",$A$1))-FIND("]",CELL("filename",$A$1)))&$B74,[2]要員計画!$L:$AJ,((COLUMN()-1)/4)+1,FALSE)),0,VLOOKUP(RIGHT(CELL("filename",$A$1),LEN(CELL("filename",$A$1))-FIND("]",CELL("filename",$A$1)))&$B74,[2]要員計画!$L:$AJ,((COLUMN()-1)/4)+1,FALSE)) -> 0 | EP74: =IF(ISERROR(VLOOKUP(RIGHT(CELL("filename",$A$1),LEN(CELL("filename",$A$1))-FIND("]",CELL("filename",$A$1)))&$B74,[2]要員計画!$L:$AJ,((COLUMN()-1)/4)+1,FALSE)),0,VLOOKUP(RIGHT(CELL("filename",$A$1),LEN(CELL("filename",$A$1))-FIND("]",CELL("filename",$A$1)))&$B74,[2]要員計画!$L:$AJ,((COLUMN()-1)/4)+1,FALSE)) -> 0
C75: 1050000 | D75: 売上金額 | E75: =SUM(F75:CW75) -> 19425000 | F75: =IFERROR($C75*F74,"") -> 0 | J75: =IFERROR($C75*J74,"") -> 0 | N75: =IFERROR($C75*N74,"") -> 1050000 | R75: =IFERROR($C75*R74,"") -> 1050000 | V75: =IFERROR($C75*V74,"") -> 1050000 | Z75: =IFERROR($C75*Z74,"") -> 1050000 | AD75: =IFERROR($C75*AD74,"") -> 1050000 | AH75: =IFERROR($C75*AH74,"") -> 1050000 | AL75: =IFERROR($C75*AL74,"") -> 1050000 | AP75: =IFERROR($C75*AP74,"") -> 1050000 | AT75: =IFERROR($C75*AT74,"") -> 1050000 | AX75: =IFERROR($C75*AX74,"") -> 1050000 | BB75: =IFERROR($C75*BB74,"") -> 1050000 | BF75: =IFERROR($C75*BF74,"") -> 1050000 | BJ75: =IFERROR($C75*BJ74,"") -> 1050000 | BN75: =IFERROR($C75*BN74,"") -> 1050000 | BR75: =IFERROR($C75*BR74,"") -> 1050000 | BV75: =IFERROR($C75*BV74,"") -> 1050000 | BZ75: =IFERROR($C75*BZ74,"") -> 1050000 | CD75: =IFERROR($C75*CD74,"") -> 1050000 | CH75: =IFERROR($C75*CH74,"") -> 525000 | CL75: =IFERROR($C75*CL74,"") -> 0 | CP75: =IFERROR($C75*CP74,"") -> 0 | CT75: =IFERROR($C75*CT74,"") -> 0 | CX75: =IFERROR($C75*CX74,"") -> 0 | DB75: =IFERROR($C75*DB74,"") -> 0 | DF75: =IFERROR($C75*DF74,"") -> 0 | DJ75: =IFERROR($C75*DJ74,"") -> 0 | DN75: =IFERROR($C75*DN74,"") -> 0 | DR75: =IFERROR($C75*DR74,"") -> 0 | DV75: =IFERROR($C75*DV74,"") -> 0 | DZ75: =IFERROR($C75*DZ74,"") -> 0 | ED75: =IFERROR($C75*ED74,"") -> 0 | EH75: =IFERROR($C75*EH74,"") -> 0 | EL75: =IFERROR($C75*EL74,"") -> 0 | EP75: =IFERROR($C75*EP74,"") -> 0
C76: 800000 | D76: 原価金額 | E76: =SUM(F76:CW76) -> 14800000 | F76: =IFERROR($C76*F74,"") -> 0 | J76: =IFERROR($C76*J74,"") -> 0 | N76: =IFERROR($C76*N74,"") -> 800000 | R76: =IFERROR($C76*R74,"") -> 800000 | V76: =IFERROR($C76*V74,"") -> 800000 | Z76: =IFERROR($C76*Z74,"") -> 800000 | AD76: =IFERROR($C76*AD74,"") -> 800000 | AH76: =IFERROR($C76*AH74,"") -> 800000 | AL76: =IFERROR($C76*AL74,"") -> 800000 | AP76: =IFERROR($C76*AP74,"") -> 800000 | AT76: =IFERROR($C76*AT74,"") -> 800000 | AX76: =IFERROR($C76*AX74,"") -> 800000 | BB76: =IFERROR($C76*BB74,"") -> 800000 | BF76: =IFERROR($C76*BF74,"") -> 800000 | BJ76: =IFERROR($C76*BJ74,"") -> 800000 | BN76: =IFERROR($C76*BN74,"") -> 800000 | BR76: =IFERROR($C76*BR74,"") -> 800000 | BV76: =IFERROR($C76*BV74,"") -> 800000 | BZ76: =IFERROR($C76*BZ74,"") -> 800000 | CD76: =IFERROR($C76*CD74,"") -> 800000 | CH76: =IFERROR($C76*CH74,"") -> 400000 | CL76: =IFERROR($C76*CL74,"") -> 0 | CP76: =IFERROR($C76*CP74,"") -> 0 | CT76: =IFERROR($C76*CT74,"") -> 0 | CX76: =IFERROR($C76*CX74,"") -> 0 | DB76: =IFERROR($C76*DB74,"") -> 0 | DF76: =IFERROR($C76*DF74,"") -> 0 | DJ76: =IFERROR($C76*DJ74,"") -> 0 | DN76: =IFERROR($C76*DN74,"") -> 0 | DR76: =IFERROR($C76*DR74,"") -> 0 | DV76: =IFERROR($C76*DV74,"") -> 0 | DZ76: =IFERROR($C76*DZ74,"") -> 0 | ED76: =IFERROR($C76*ED74,"") -> 0 | EH76: =IFERROR($C76*EH74,"") -> 0 | EL76: =IFERROR($C76*EL74,"") -> 0 | EP76: =IFERROR($C76*EP74,"") -> 0
B77: 1：PL（オフショア） | D77: 工数 | E77: =SUM(F77:ES77) -> 11 | F77: =IF(ISERROR(VLOOKUP(RIGHT(CELL("filename",$A$1),LEN(CELL("filename",$A$1))-FIND("]",CELL("filename",$A$1)))&$B77,[2]要員計画!$L:$AJ,((COLUMN()-1)/4)+1,FALSE)),0,VLOOKUP(RIGHT(CELL("filename",$A$1),LEN(CELL("filename",$A$1))-FIND("]",CELL("filename",$A$1)))&$B77,[2]要員計画!$L:$AJ,((COLUMN()-1)/4)+1,FALSE)) -> 0 | J77: =IF(ISERROR(VLOOKUP(RIGHT(CELL("filename",$A$1),LEN(CELL("filename",$A$1))-FIND("]",CELL("filename",$A$1)))&$B77,[2]要員計画!$L:$AJ,((COLUMN()-1)/4)+1,FALSE)),0,VLOOKUP(RIGHT(CELL("filename",$A$1),LEN(CELL("filename",$A$1))-FIND("]",CELL("filename",$A$1)))&$B77,[2]要員計画!$L:$AJ,((COLUMN()-1)/4)+1,FALSE)) -> 0 | N77: =IF(ISERROR(VLOOKUP(RIGHT(CELL("filename",$A$1),LEN(CELL("filename",$A$1))-FIND("]",CELL("filename",$A$1)))&$B77,[2]要員計画!$L:$AJ,((COLUMN()-1)/4)+1,FALSE)),0,VLOOKUP(RIGHT(CELL("filename",$A$1),LEN(CELL("filename",$A$1))-FIND("]",CELL("filename",$A$1)))&$B77,[2]要員計画!$L:$AJ,((COLUMN()-1)/4)+1,FALSE)) -> 0 | Z77: 1 | AD77: 1 | AH77: 1 | AL77: 1 | AP77: 1 | AT77: 1 | AX77: 1 | BB77: 1 | BF77: 1 | BJ77: 1 | BN77: 1 | DR77: =IF(ISERROR(VLOOKUP(RIGHT(CELL("filename",$A$1),LEN(CELL("filename",$A$1))-FIND("]",CELL("filename",$A$1)))&$B77,[2]要員計画!$L:$AJ,((COLUMN()-1)/4)+1,FALSE)),0,VLOOKUP(RIGHT(CELL("filename",$A$1),LEN(CELL("filename",$A$1))-FIND("]",CELL("filename",$A$1)))&$B77,[2]要員計画!$L:$AJ,((COLUMN()-1)/4)+1,FALSE)) -> 0 | DV77: =IF(ISERROR(VLOOKUP(RIGHT(CELL("filename",$A$1),LEN(CELL("filename",$A$1))-FIND("]",CELL("filename",$A$1)))&$B77,[2]要員計画!$L:$AJ,((COLUMN()-1)/4)+1,FALSE)),0,VLOOKUP(RIGHT(CELL("filename",$A$1),LEN(CELL("filename",$A$1))-FIND("]",CELL("filename",$A$1)))&$B77,[2]要員計画!$L:$AJ,((COLUMN()-1)/4)+1,FALSE)) -> 0 | DZ77: =IF(ISERROR(VLOOKUP(RIGHT(CELL("filename",$A$1),LEN(CELL("filename",$A$1))-FIND("]",CELL("filename",$A$1)))&$B77,[2]要員計画!$L:$AJ,((COLUMN()-1)/4)+1,FALSE)),0,VLOOKUP(RIGHT(CELL("filename",$A$1),LEN(CELL("filename",$A$1))-FIND("]",CELL("filename",$A$1)))&$B77,[2]要員計画!$L:$AJ,((COLUMN()-1)/4)+1,FALSE)) -> 0 | ED77: =IF(ISERROR(VLOOKUP(RIGHT(CELL("filename",$A$1),LEN(CELL("filename",$A$1))-FIND("]",CELL("filename",$A$1)))&$B77,[2]要員計画!$L:$AJ,((COLUMN()-1)/4)+1,FALSE)),0,VLOOKUP(RIGHT(CELL("filename",$A$1),LEN(CELL("filename",$A$1))-FIND("]",CELL("filename",$A$1)))&$B77,[2]要員計画!$L:$AJ,((COLUMN()-1)/4)+1,FALSE)) -> 0 | EH77: =IF(ISERROR(VLOOKUP(RIGHT(CELL("filename",$A$1),LEN(CELL("filename",$A$1))-FIND("]",CELL("filename",$A$1)))&$B77,[2]要員計画!$L:$AJ,((COLUMN()-1)/4)+1,FALSE)),0,VLOOKUP(RIGHT(CELL("filename",$A$1),LEN(CELL("filename",$A$1))-FIND("]",CELL("filename",$A$1)))&$B77,[2]要員計画!$L:$AJ,((COLUMN()-1)/4)+1,FALSE)) -> 0 | EL77: =IF(ISERROR(VLOOKUP(RIGHT(CELL("filename",$A$1),LEN(CELL("filename",$A$1))-FIND("]",CELL("filename",$A$1)))&$B77,[2]要員計画!$L:$AJ,((COLUMN()-1)/4)+1,FALSE)),0,VLOOKUP(RIGHT(CELL("filename",$A$1),LEN(CELL("filename",$A$1))-FIND("]",CELL("filename",$A$1)))&$B77,[2]要員計画!$L:$AJ,((COLUMN()-1)/4)+1,FALSE)) -> 0 | EP77: =IF(ISERROR(VLOOKUP(RIGHT(CELL("filename",$A$1),LEN(CELL("filename",$A$1))-FIND("]",CELL("filename",$A$1)))&$B77,[2]要員計画!$L:$AJ,((COLUMN()-1)/4)+1,FALSE)),0,VLOOKUP(RIGHT(CELL("filename",$A$1),LEN(CELL("filename",$A$1))-FIND("]",CELL("filename",$A$1)))&$B77,[2]要員計画!$L:$AJ,((COLUMN()-1)/4)+1,FALSE)) -> 0
C78: 1050000 | D78: 売上金額 | E78: =SUM(F78:CW78) -> 11550000 | F78: =IFERROR($C78*F77,"") -> 0 | J78: =IFERROR($C78*J77,"") -> 0 | N78: =IFERROR($C78*N77,"") -> 0 | R78: =IFERROR($C78*R77,"") -> 0 | V78: =IFERROR($C78*V77,"") -> 0 | Z78: =IFERROR($C78*Z77,"") -> 1050000 | AD78: =IFERROR($C78*AD77,"") -> 1050000 | AH78: =IFERROR($C78*AH77,"") -> 1050000 | AL78: =IFERROR($C78*AL77,"") -> 1050000 | AP78: =IFERROR($C78*AP77,"") -> 1050000 | AT78: =IFERROR($C78*AT77,"") -> 1050000 | AX78: =IFERROR($C78*AX77,"") -> 1050000 | BB78: =IFERROR($C78*BB77,"") -> 1050000 | BF78: =IFERROR($C78*BF77,"") -> 1050000 | BJ78: =IFERROR($C78*BJ77,"") -> 1050000 | BN78: =IFERROR($C78*BN77,"") -> 1050000 | BR78: =IFERROR($C78*BR77,"") -> 0 | BV78: =IFERROR($C78*BV77,"") -> 0 | BZ78: =IFERROR($C78*BZ77,"") -> 0 | CD78: =IFERROR($C78*CD77,"") -> 0 | CH78: =IFERROR($C78*CH77,"") -> 0 | CL78: =IFERROR($C78*CL77,"") -> 0 | CP78: =IFERROR($C78*CP77,"") -> 0 | CT78: =IFERROR($C78*CT77,"") -> 0 | CX78: =IFERROR($C78*CX77,"") -> 0 | DB78: =IFERROR($C78*DB77,"") -> 0 | DF78: =IFERROR($C78*DF77,"") -> 0 | DJ78: =IFERROR($C78*DJ77,"") -> 0 | DN78: =IFERROR($C78*DN77,"") -> 0 | DR78: =IFERROR($C78*DR77,"") -> 0 | DV78: =IFERROR($C78*DV77,"") -> 0 | DZ78: =IFERROR($C78*DZ77,"") -> 0 | ED78: =IFERROR($C78*ED77,"") -> 0 | EH78: =IFERROR($C78*EH77,"") -> 0 | EL78: =IFERROR($C78*EL77,"") -> 0 | EP78: =IFERROR($C78*EP77,"") -> 0
C79: 400000 | D79: 原価金額 | E79: =SUM(F79:CW79) -> 4400000 | F79: =IFERROR($C79*F77,"") -> 0 | J79: =IFERROR($C79*J77,"") -> 0 | N79: =IFERROR($C79*N77,"") -> 0 | R79: =IFERROR($C79*R77,"") -> 0 | V79: =IFERROR($C79*V77,"") -> 0 | Z79: =IFERROR($C79*Z77,"") -> 400000 | AD79: =IFERROR($C79*AD77,"") -> 400000 | AH79: =IFERROR($C79*AH77,"") -> 400000 | AL79: =IFERROR($C79*AL77,"") -> 400000 | AP79: =IFERROR($C79*AP77,"") -> 400000 | AT79: =IFERROR($C79*AT77,"") -> 400000 | AX79: =IFERROR($C79*AX77,"") -> 400000 | BB79: =IFERROR($C79*BB77,"") -> 400000 | BF79: =IFERROR($C79*BF77,"") -> 400000 | BJ79: =IFERROR($C79*BJ77,"") -> 400000 | BN79: =IFERROR($C79*BN77,"") -> 400000 | BR79: =IFERROR($C79*BR77,"") -> 0 | BV79: =IFERROR($C79*BV77,"") -> 0 | BZ79: =IFERROR($C79*BZ77,"") -> 0 | CD79: =IFERROR($C79*CD77,"") -> 0 | CH79: =IFERROR($C79*CH77,"") -> 0 | CL79: =IFERROR($C79*CL77,"") -> 0 | CP79: =IFERROR($C79*CP77,"") -> 0 | CT79: =IFERROR($C79*CT77,"") -> 0 | CX79: =IFERROR($C79*CX77,"") -> 0 | DB79: =IFERROR($C79*DB77,"") -> 0 | DF79: =IFERROR($C79*DF77,"") -> 0 | DJ79: =IFERROR($C79*DJ77,"") -> 0 | DN79: =IFERROR($C79*DN77,"") -> 0 | DR79: =IFERROR($C79*DR77,"") -> 0 | DV79: =IFERROR($C79*DV77,"") -> 0 | DZ79: =IFERROR($C79*DZ77,"") -> 0 | ED79: =IFERROR($C79*ED77,"") -> 0 | EH79: =IFERROR($C79*EH77,"") -> 0 | EL79: =IFERROR($C79*EL77,"") -> 0 | EP79: =IFERROR($C79*EP77,"") -> 0
B80: 2：コミュニケータ（オフショア） | D80: 工数 | E80: =SUM(F80:ES80) -> 11 | F80: =IF(ISERROR(VLOOKUP(RIGHT(CELL("filename",$A$1),LEN(CELL("filename",$A$1))-FIND("]",CELL("filename",$A$1)))&$B80,[2]要員計画!$L:$AJ,((COLUMN()-1)/4)+1,FALSE)),0,VLOOKUP(RIGHT(CELL("filename",$A$1),LEN(CELL("filename",$A$1))-FIND("]",CELL("filename",$A$1)))&$B80,[2]要員計画!$L:$AJ,((COLUMN()-1)/4)+1,FALSE)) -> 0 | J80: =IF(ISERROR(VLOOKUP(RIGHT(CELL("filename",$A$1),LEN(CELL("filename",$A$1))-FIND("]",CELL("filename",$A$1)))&$B80,[2]要員計画!$L:$AJ,((COLUMN()-1)/4)+1,FALSE)),0,VLOOKUP(RIGHT(CELL("filename",$A$1),LEN(CELL("filename",$A$1))-FIND("]",CELL("filename",$A$1)))&$B80,[2]要員計画!$L:$AJ,((COLUMN()-1)/4)+1,FALSE)) -> 0 | N80: =IF(ISERROR(VLOOKUP(RIGHT(CELL("filename",$A$1),LEN(CELL("filename",$A$1))-FIND("]",CELL("filename",$A$1)))&$B80,[2]要員計画!$L:$AJ,((COLUMN()-1)/4)+1,FALSE)),0,VLOOKUP(RIGHT(CELL("filename",$A$1),LEN(CELL("filename",$A$1))-FIND("]",CELL("filename",$A$1)))&$B80,[2]要員計画!$L:$AJ,((COLUMN()-1)/4)+1,FALSE)) -> 0 | Z80: 1 | AD80: 1 | AH80: 1 | AL80: 1 | AP80: 1 | AT80: 1 | AX80: 1 | BB80: 1 | BF80: 1 | BJ80: 1 | BN80: 1 | DR80: =IF(ISERROR(VLOOKUP(RIGHT(CELL("filename",$A$1),LEN(CELL("filename",$A$1))-FIND("]",CELL("filename",$A$1)))&$B80,[2]要員計画!$L:$AJ,((COLUMN()-1)/4)+1,FALSE)),0,VLOOKUP(RIGHT(CELL("filename",$A$1),LEN(CELL("filename",$A$1))-FIND("]",CELL("filename",$A$1)))&$B80,[2]要員計画!$L:$AJ,((COLUMN()-1)/4)+1,FALSE)) -> 0 | DV80: =IF(ISERROR(VLOOKUP(RIGHT(CELL("filename",$A$1),LEN(CELL("filename",$A$1))-FIND("]",CELL("filename",$A$1)))&$B80,[2]要員計画!$L:$AJ,((COLUMN()-1)/4)+1,FALSE)),0,VLOOKUP(RIGHT(CELL("filename",$A$1),LEN(CELL("filename",$A$1))-FIND("]",CELL("filename",$A$1)))&$B80,[2]要員計画!$L:$AJ,((COLUMN()-1)/4)+1,FALSE)) -> 0 | DZ80: =IF(ISERROR(VLOOKUP(RIGHT(CELL("filename",$A$1),LEN(CELL("filename",$A$1))-FIND("]",CELL("filename",$A$1)))&$B80,[2]要員計画!$L:$AJ,((COLUMN()-1)/4)+1,FALSE)),0,VLOOKUP(RIGHT(CELL("filename",$A$1),LEN(CELL("filename",$A$1))-FIND("]",CELL("filename",$A$1)))&$B80,[2]要員計画!$L:$AJ,((COLUMN()-1)/4)+1,FALSE)) -> 0 | ED80: =IF(ISERROR(VLOOKUP(RIGHT(CELL("filename",$A$1),LEN(CELL("filename",$A$1))-FIND("]",CELL("filename",$A$1)))&$B80,[2]要員計画!$L:$AJ,((COLUMN()-1)/4)+1,FALSE)),0,VLOOKUP(RIGHT(CELL("filename",$A$1),LEN(CELL("filename",$A$1))-FIND("]",CELL("filename",$A$1)))&$B80,[2]要員計画!$L:$AJ,((COLUMN()-1)/4)+1,FALSE)) -> 0 | EH80: =IF(ISERROR(VLOOKUP(RIGHT(CELL("filename",$A$1),LEN(CELL("filename",$A$1))-FIND("]",CELL("filename",$A$1)))&$B80,[2]要員計画!$L:$AJ,((COLUMN()-1)/4)+1,FALSE)),0,VLOOKUP(RIGHT(CELL("filename",$A$1),LEN(CELL("filename",$A$1))-FIND("]",CELL("filename",$A$1)))&$B80,[2]要員計画!$L:$AJ,((COLUMN()-1)/4)+1,FALSE)) -> 0 | EL80: =IF(ISERROR(VLOOKUP(RIGHT(CELL("filename",$A$1),LEN(CELL("filename",$A$1))-FIND("]",CELL("filename",$A$1)))&$B80,[2]要員計画!$L:$AJ,((COLUMN()-1)/4)+1,FALSE)),0,VLOOKUP(RIGHT(CELL("filename",$A$1),LEN(CELL("filename",$A$1))-FIND("]",CELL("filename",$A$1)))&$B80,[2]要員計画!$L:$AJ,((COLUMN()-1)/4)+1,FALSE)) -> 0 | EP80: =IF(ISERROR(VLOOKUP(RIGHT(CELL("filename",$A$1),LEN(CELL("filename",$A$1))-FIND("]",CELL("filename",$A$1)))&$B80,[2]要員計画!$L:$AJ,((COLUMN()-1)/4)+1,FALSE)),0,VLOOKUP(RIGHT(CELL("filename",$A$1),LEN(CELL("filename",$A$1))-FIND("]",CELL("filename",$A$1)))&$B80,[2]要員計画!$L:$AJ,((COLUMN()-1)/4)+1,FALSE)) -> 0
C81: 1050000 | D81: 売上金額 | E81: =SUM(F81:CW81) -> 11550000 | F81: =IFERROR($C81*F80,"") -> 0 | J81: =IFERROR($C81*J80,"") -> 0 | N81: =IFERROR($C81*N80,"") -> 0 | R81: =IFERROR($C81*R80,"") -> 0 | V81: =IFERROR($C81*V80,"") -> 0 | Z81: =IFERROR($C81*Z80,"") -> 1050000 | AD81: =IFERROR($C81*AD80,"") -> 1050000 | AH81: =IFERROR($C81*AH80,"") -> 1050000 | AL81: =IFERROR($C81*AL80,"") -> 1050000 | AP81: =IFERROR($C81*AP80,"") -> 1050000 | AT81: =IFERROR($C81*AT80,"") -> 1050000 | AX81: =IFERROR($C81*AX80,"") -> 1050000 | BB81: =IFERROR($C81*BB80,"") -> 1050000 | BF81: =IFERROR($C81*BF80,"") -> 1050000 | BJ81: =IFERROR($C81*BJ80,"") -> 1050000 | BN81: =IFERROR($C81*BN80,"") -> 1050000 | BR81: =IFERROR($C81*BR80,"") -> 0 | BV81: =IFERROR($C81*BV80,"") -> 0 | BZ81: =IFERROR($C81*BZ80,"") -> 0 | CD81: =IFERROR($C81*CD80,"") -> 0 | CH81: =IFERROR($C81*CH80,"") -> 0 | CL81: =IFERROR($C81*CL80,"") -> 0 | CP81: =IFERROR($C81*CP80,"") -> 0 | CT81: =IFERROR($C81*CT80,"") -> 0 | CX81: =IFERROR($C81*CX80,"") -> 0 | DB81: =IFERROR($C81*DB80,"") -> 0 | DF81: =IFERROR($C81*DF80,"") -> 0 | DJ81: =IFERROR($C81*DJ80,"") -> 0 | DN81: =IFERROR($C81*DN80,"") -> 0 | DR81: =IFERROR($C81*DR80,"") -> 0 | DV81: =IFERROR($C81*DV80,"") -> 0 | DZ81: =IFERROR($C81*DZ80,"") -> 0 | ED81: =IFERROR($C81*ED80,"") -> 0 | EH81: =IFERROR($C81*EH80,"") -> 0 | EL81: =IFERROR($C81*EL80,"") -> 0 | EP81: =IFERROR($C81*EP80,"") -> 0
C82: 400000 | D82: 原価金額 | E82: =SUM(F82:CW82) -> 4400000 | F82: =IFERROR($C82*F80,"") -> 0 | J82: =IFERROR($C82*J80,"") -> 0 | N82: =IFERROR($C82*N80,"") -> 0 | R82: =IFERROR($C82*R80,"") -> 0 | V82: =IFERROR($C82*V80,"") -> 0 | Z82: =IFERROR($C82*Z80,"") -> 400000 | AD82: =IFERROR($C82*AD80,"") -> 400000 | AH82: =IFERROR($C82*AH80,"") -> 400000 | AL82: =IFERROR($C82*AL80,"") -> 400000 | AP82: =IFERROR($C82*AP80,"") -> 400000 | AT82: =IFERROR($C82*AT80,"") -> 400000 | AX82: =IFERROR($C82*AX80,"") -> 400000 | BB82: =IFERROR($C82*BB80,"") -> 400000 | BF82: =IFERROR($C82*BF80,"") -> 400000 | BJ82: =IFERROR($C82*BJ80,"") -> 400000 | BN82: =IFERROR($C82*BN80,"") -> 400000 | BR82: =IFERROR($C82*BR80,"") -> 0 | BV82: =IFERROR($C82*BV80,"") -> 0 | BZ82: =IFERROR($C82*BZ80,"") -> 0 | CD82: =IFERROR($C82*CD80,"") -> 0 | CH82: =IFERROR($C82*CH80,"") -> 0 | CL82: =IFERROR($C82*CL80,"") -> 0 | CP82: =IFERROR($C82*CP80,"") -> 0 | CT82: =IFERROR($C82*CT80,"") -> 0 | CX82: =IFERROR($C82*CX80,"") -> 0 | DB82: =IFERROR($C82*DB80,"") -> 0 | DF82: =IFERROR($C82*DF80,"") -> 0 | DJ82: =IFERROR($C82*DJ80,"") -> 0 | DN82: =IFERROR($C82*DN80,"") -> 0 | DR82: =IFERROR($C82*DR80,"") -> 0 | DV82: =IFERROR($C82*DV80,"") -> 0 | DZ82: =IFERROR($C82*DZ80,"") -> 0 | ED82: =IFERROR($C82*ED80,"") -> 0 | EH82: =IFERROR($C82*EH80,"") -> 0 | EL82: =IFERROR($C82*EL80,"") -> 0 | EP82: =IFERROR($C82*EP80,"") -> 0
B83: 3：PL（オフショア） | D83: 工数 | E83: =SUM(F83:ES83) -> 11 | F83: =IF(ISERROR(VLOOKUP(RIGHT(CELL("filename",$A$1),LEN(CELL("filename",$A$1))-FIND("]",CELL("filename",$A$1)))&$B83,[2]要員計画!$L:$AJ,((COLUMN()-1)/4)+1,FALSE)),0,VLOOKUP(RIGHT(CELL("filename",$A$1),LEN(CELL("filename",$A$1))-FIND("]",CELL("filename",$A$1)))&$B83,[2]要員計画!$L:$AJ,((COLUMN()-1)/4)+1,FALSE)) -> 0 | J83: =IF(ISERROR(VLOOKUP(RIGHT(CELL("filename",$A$1),LEN(CELL("filename",$A$1))-FIND("]",CELL("filename",$A$1)))&$B83,[2]要員計画!$L:$AJ,((COLUMN()-1)/4)+1,FALSE)),0,VLOOKUP(RIGHT(CELL("filename",$A$1),LEN(CELL("filename",$A$1))-FIND("]",CELL("filename",$A$1)))&$B83,[2]要員計画!$L:$AJ,((COLUMN()-1)/4)+1,FALSE)) -> 0 | N83: =IF(ISERROR(VLOOKUP(RIGHT(CELL("filename",$A$1),LEN(CELL("filename",$A$1))-FIND("]",CELL("filename",$A$1)))&$B83,[2]要員計画!$L:$AJ,((COLUMN()-1)/4)+1,FALSE)),0,VLOOKUP(RIGHT(CELL("filename",$A$1),LEN(CELL("filename",$A$1))-FIND("]",CELL("filename",$A$1)))&$B83,[2]要員計画!$L:$AJ,((COLUMN()-1)/4)+1,FALSE)) -> 0 | Z83: 1 | AD83: 1 | AH83: 1 | AL83: 1 | AP83: 1 | AT83: 1 | AX83: 1 | BB83: 1 | BF83: 1 | BJ83: 1 | BN83: 1 | DR83: =IF(ISERROR(VLOOKUP(RIGHT(CELL("filename",$A$1),LEN(CELL("filename",$A$1))-FIND("]",CELL("filename",$A$1)))&$B83,[2]要員計画!$L:$AJ,((COLUMN()-1)/4)+1,FALSE)),0,VLOOKUP(RIGHT(CELL("filename",$A$1),LEN(CELL("filename",$A$1))-FIND("]",CELL("filename",$A$1)))&$B83,[2]要員計画!$L:$AJ,((COLUMN()-1)/4)+1,FALSE)) -> 0 | DV83: =IF(ISERROR(VLOOKUP(RIGHT(CELL("filename",$A$1),LEN(CELL("filename",$A$1))-FIND("]",CELL("filename",$A$1)))&$B83,[2]要員計画!$L:$AJ,((COLUMN()-1)/4)+1,FALSE)),0,VLOOKUP(RIGHT(CELL("filename",$A$1),LEN(CELL("filename",$A$1))-FIND("]",CELL("filename",$A$1)))&$B83,[2]要員計画!$L:$AJ,((COLUMN()-1)/4)+1,FALSE)) -> 0 | DZ83: =IF(ISERROR(VLOOKUP(RIGHT(CELL("filename",$A$1),LEN(CELL("filename",$A$1))-FIND("]",CELL("filename",$A$1)))&$B83,[2]要員計画!$L:$AJ,((COLUMN()-1)/4)+1,FALSE)),0,VLOOKUP(RIGHT(CELL("filename",$A$1),LEN(CELL("filename",$A$1))-FIND("]",CELL("filename",$A$1)))&$B83,[2]要員計画!$L:$AJ,((COLUMN()-1)/4)+1,FALSE)) -> 0 | ED83: =IF(ISERROR(VLOOKUP(RIGHT(CELL("filename",$A$1),LEN(CELL("filename",$A$1))-FIND("]",CELL("filename",$A$1)))&$B83,[2]要員計画!$L:$AJ,((COLUMN()-1)/4)+1,FALSE)),0,VLOOKUP(RIGHT(CELL("filename",$A$1),LEN(CELL("filename",$A$1))-FIND("]",CELL("filename",$A$1)))&$B83,[2]要員計画!$L:$AJ,((COLUMN()-1)/4)+1,FALSE)) -> 0 | EH83: =IF(ISERROR(VLOOKUP(RIGHT(CELL("filename",$A$1),LEN(CELL("filename",$A$1))-FIND("]",CELL("filename",$A$1)))&$B83,[2]要員計画!$L:$AJ,((COLUMN()-1)/4)+1,FALSE)),0,VLOOKUP(RIGHT(CELL("filename",$A$1),LEN(CELL("filename",$A$1))-FIND("]",CELL("filename",$A$1)))&$B83,[2]要員計画!$L:$AJ,((COLUMN()-1)/4)+1,FALSE)) -> 0 | EL83: =IF(ISERROR(VLOOKUP(RIGHT(CELL("filename",$A$1),LEN(CELL("filename",$A$1))-FIND("]",CELL("filename",$A$1)))&$B83,[2]要員計画!$L:$AJ,((COLUMN()-1)/4)+1,FALSE)),0,VLOOKUP(RIGHT(CELL("filename",$A$1),LEN(CELL("filename",$A$1))-FIND("]",CELL("filename",$A$1)))&$B83,[2]要員計画!$L:$AJ,((COLUMN()-1)/4)+1,FALSE)) -> 0 | EP83: =IF(ISERROR(VLOOKUP(RIGHT(CELL("filename",$A$1),LEN(CELL("filename",$A$1))-FIND("]",CELL("filename",$A$1)))&$B83,[2]要員計画!$L:$AJ,((COLUMN()-1)/4)+1,FALSE)),0,VLOOKUP(RIGHT(CELL("filename",$A$1),LEN(CELL("filename",$A$1))-FIND("]",CELL("filename",$A$1)))&$B83,[2]要員計画!$L:$AJ,((COLUMN()-1)/4)+1,FALSE)) -> 0
C84: 1050000 | D84: 売上金額 | E84: =SUM(F84:CW84) -> 11550000 | F84: =IFERROR($C84*F83,"") -> 0 | J84: =IFERROR($C84*J83,"") -> 0 | N84: =IFERROR($C84*N83,"") -> 0 | R84: =IFERROR($C84*R83,"") -> 0 | V84: =IFERROR($C84*V83,"") -> 0 | Z84: =IFERROR($C84*Z83,"") -> 1050000 | AD84: =IFERROR($C84*AD83,"") -> 1050000 | AH84: =IFERROR($C84*AH83,"") -> 1050000 | AL84: =IFERROR($C84*AL83,"") -> 1050000 | AP84: =IFERROR($C84*AP83,"") -> 1050000 | AT84: =IFERROR($C84*AT83,"") -> 1050000 | AX84: =IFERROR($C84*AX83,"") -> 1050000 | BB84: =IFERROR($C84*BB83,"") -> 1050000 | BF84: =IFERROR($C84*BF83,"") -> 1050000 | BJ84: =IFERROR($C84*BJ83,"") -> 1050000 | BN84: =IFERROR($C84*BN83,"") -> 1050000 | BR84: =IFERROR($C84*BR83,"") -> 0 | BV84: =IFERROR($C84*BV83,"") -> 0 | BZ84: =IFERROR($C84*BZ83,"") -> 0 | CD84: =IFERROR($C84*CD83,"") -> 0 | CH84: =IFERROR($C84*CH83,"") -> 0 | CL84: =IFERROR($C84*CL83,"") -> 0 | CP84: =IFERROR($C84*CP83,"") -> 0 | CT84: =IFERROR($C84*CT83,"") -> 0 | CX84: =IFERROR($C84*CX83,"") -> 0 | DB84: =IFERROR($C84*DB83,"") -> 0 | DF84: =IFERROR($C84*DF83,"") -> 0 | DJ84: =IFERROR($C84*DJ83,"") -> 0 | DN84: =IFERROR($C84*DN83,"") -> 0 | DR84: =IFERROR($C84*DR83,"") -> 0 | DV84: =IFERROR($C84*DV83,"") -> 0 | DZ84: =IFERROR($C84*DZ83,"") -> 0 | ED84: =IFERROR($C84*ED83,"") -> 0 | EH84: =IFERROR($C84*EH83,"") -> 0 | EL84: =IFERROR($C84*EL83,"") -> 0 | EP84: =IFERROR($C84*EP83,"") -> 0
