Workbook

Sheet 社員工数
A1: 社員工数入力（単位：時間） | D1: 小数点以下は受発注システムに入力ができない仕様となってます
A3: 見積番号 | D3: 案件名 | E3: 次世代研SWANシステム 縮小版共通基盤移行
A4: 受注番号 | B4: - | D4: 契約金額 | G4: 社員工数 | H4: =AF59 -> 138 | J4: 外注費金額 | K4: =外注費・経費!K4 -> 3234000 | M4: 経費金額 | N4: 0
A6: 区分 | B6: 社員番号 | C6: 氏名 | D6: 見積工数 | AF6: 合計
D7: 2025年度1Q | G7: 2025年度2Q | J7: 2025年度3Q | M7: 2025年度4Q | P7: 2026年度1Q | S7: 2026年度2Q | V7: 2026年度3Q | Y7: 2026年度4Q | AB7: 2027年度1Q | AE7: それ以降
D8: 44287 | E8: 44317 | F8: 44348 | G8: 44378 | H8: 44409 | I8: 44440 | J8: 44470 | K8: 44501 | L8: 44531 | M8: 44562 | N8: 44593 | O8: 44621 | P8: 44287 | Q8: 44317 | R8: 44348 | S8: 44378 | T8: 44409 | U8: 44440 | V8: 44470 | W8: 44501 | X8: 44531 | Y8: 44562 | Z8: 44593 | AA8: 44621 | AB8: 44287 | AC8: 44317 | AD8: 44348
A9: 入社済社員 | B9: 638 | C9: 高木義尚 | J9: 10 | K9: 64 | L9: 64 | AF9: =SUM(D9:AE9) -> 138
AF10: =SUM(D10:AE10) -> 0
AF11: =SUM(D11:AE11) -> 0
AF12: =SUM(D12:AE12) -> 0
AF13: =SUM(D13:AE13) -> 0
AF14: =SUM(D14:AE14) -> 0
AF15: =SUM(D15:AE15) -> 0
AF16: =SUM(D16:AE16) -> 0
AF17: =SUM(D17:AE17) -> 0
AF18: =SUM(D18:AE18) -> 0
AF19: =SUM(D19:AE19) -> 0
AF20: =SUM(D20:AE20) -> 0
AF21: =SUM(D21:AE21) -> 0
... AF58: =SUM(D58:AE58) -> 0
A59: 合計 | D59: =SUM(D9:D58) -> 0 | E59: =SUM(E9:E58) -> 0 | F59: =SUM(F9:F58) -> 0 | G59: =SUM(G9:G58) -> 0 | H59: =SUM(H9:H58) -> 0 | I59: =SUM(I9:I58) -> 0 | J59: =SUM(J9:J58) -> 10 | K59: =SUM(K9:K58) -> 64 | ... AF59: =SUM(AF9:AF58) -> 138

Sheet 外注費・経費
A1: 外注費・経費（単位：円）
A3: 見積番号 | D3: 案件名 | E3: =社員工数!E3 -> 次世代研SWANシステム 縮小版共通基盤移行
A4: 受注番号 | B4: - | D4: 契約金額 | E4: =社員工数!E4 -> 0 | G4: 社員工数 | H4: =社員工数!H4 -> 138 | J4: 外注費金額 | K4: =AF59 -> 3234000 | M4: 経費金額 | N4: =SUMIF(A:A,"経費",AF:AF) -> 0
A6: 区分 | B6: BPID | C6: 氏名 | D6: 見積金額 | AF6: 合計
D7: 2025年度1Q | G7: 2025年度2Q | J7: 2025年度3Q | M7: 2025年度4Q | P7: 2026年度1Q | S7: 2026年度2Q | V7: 2026年度3Q | Y7: 2026年度4Q | AB7: 2027年度1Q | AE7: それ以降
D8: 44287 | E8: 44317 | F8: 44348 | G8: 44378 | H8: 44409 | I8: 44440 | J8: 44470 | K8: 44501 | L8: 44531 | M8: 44562 | N8: 44593 | O8: 44621 | P8: 44287 | Q8: 44317 | R8: 44348 | S8: 44378 | T8: 44409 | U8: 44440 | V8: 44470 | W8: 44501 | X8: 44531 | Y8: 44562 | Z8: 44593 | AA8: 44621 | AB8: 44287 | AC8: 44317 | AD8: 44348
A9: BP | C9: 篠塚正裕 | K9: =810000*0.2 -> 162000 | L9: =810000*0.2 -> 162000 | AF9: =SUM(D9:AE9) -> 324000
A10: BP | C10: 木村清一 | J10: =42500/5*1 -> 8500 | K10: =42500/5*4 -> 34000 | L10: 42500 | AF10: =SUM(D10:AE10) -> 85000
A11: BP | C11: 王志鵬 | J11: =750000/5*1 -> 150000 | K11: =750000/5*4 -> 600000 | L11: 375000 | AF11: =SUM(D11:AE11) -> 1125000
A12: BP | C12: 高鑫 | J12: =850000/5*1 -> 170000 | K12: =850000/5*4 -> 680000 | L12: 850000 | AF12: =SUM(D12:AE12) -> 1700000
AF13: =SUM(D13:AE13) -> 0
AF14: =SUM(D14:AE14) -> 0
AF15: =SUM(D15:AE15) -> 0
AF16: =SUM(D16:AE16) -> 0
AF17: =SUM(D17:AE17) -> 0
AF18: =SUM(D18:AE18) -> 0
AF19: =SUM(D19:AE19) -> 0
AF20: =SUM(D20:AE20) -> 0
AF21: =SUM(D21:AE21) -> 0
AF22: =SUM(D22:AE22) -> 0
AF23: =SUM(D23:AE23) -> 0
AF24: =SUM(D24:AE24) -> 0
... AF58: =SUM(D58:AE58) -> 0
A59: 合計 | D59: =SUM(D9:D58) -> 0 | E59: =SUM(E9:E58) -> 0 | F59: =SUM(F9:F58) -> 0 | G59: =SUM(G9:G58) -> 0 | H59: =SUM(H9:H58) -> 0 | I59: =SUM(I9:I58) -> 0 | J59: =SUM(J9:J58) -> 328500 | K59: =SUM(K9:K58) -> 1476000 | ... AF59: =SUM(AF9:AF58) -> 3234000

Sheet 外注費・経費 (実行予算)
A1: 外注費・経費（単位：円）
A3: 見積番号 | D3: 案件名 | E3: =社員工数!E3 -> 次世代研SWANシステム 縮小版共通基盤移行
A4: 受注番号 | B4: - | D4: 契約金額 | E4: =社員工数!E4 -> 0 | G4: 社員工数 | H4: =社員工数!H4 -> 138 | J4: 外注費金額 | K4: =AF59 -> 3751440 | M4: 経費金額 | N4: =SUMIF(A:A,"経費",AF:AF) -> 0
A6: 区分 | B6: BPID | C6: 氏名 | D6: 見積金額 | AF6: 合計
D7: 2025年度1Q | G7: 2025年度2Q | J7: 2025年度3Q | M7: 2025年度4Q | P7: 2026年度1Q | S7: 2026年度2Q | V7: 2026年度3Q | Y7: 2026年度4Q | AB7: 2027年度1Q | AE7: それ以降
D8: 44287 | E8: 44317 | F8: 44348 | G8: 44378 | H8: 44409 | I8: 44440 | J8: 44470 | K8: 44501 | L8: 44531 | M8: 44562 | N8: 44593 | O8: 44621 | P8: 44287 | Q8: 44317 | R8: 44348 | S8: 44378 | T8: 44409 | U8: 44440 | V8: 44470 | W8: 44501 | X8: 44531 | Y8: 44562 | Z8: 44593 | AA8: 44621 | AB8: 44287 | AC8: 44317 | AD8: 44348
A9: BP | C9: 篠塚正裕 | K9: =外注費・経費!K9*1.16 -> 187920 | L9: =外注費・経費!L9*1.16 -> 187920 | AF9: =SUM(D9:AE9) -> 375840
A10: BP | C10: 木村清一 | J10: =外注費・経費!J10*1.16 -> 9860 | K10: =外注費・経費!K10*1.16 -> 39440 | L10: =外注費・経費!L10*1.16 -> 49300 | AF10: =SUM(D10:AE10) -> 98600
A11: BP | C11: 王志鵬 | J11: =外注費・経費!J11*1.16 -> 174000 | K11: =外注費・経費!K11*1.16 -> 696000 | L11: =外注費・経費!L11*1.16 -> 435000 | AF11: =SUM(D11:AE11) -> 1305000
A12: BP | C12: 高鑫 | J12: =外注費・経費!J12*1.16 -> 197200 | K12: =外注費・経費!K12*1.16 -> 788800 | L12: =外注費・経費!L12*1.16 -> 986000 | AF12: =SUM(D12:AE12) -> 1972000
AF13: =SUM(D13:AE13) -> 0
AF14: =SUM(D14:AE14) -> 0
AF15: =SUM(D15:AE15) -> 0
AF16: =SUM(D16:AE16) -> 0
AF17: =SUM(D17:AE17) -> 0
AF18: =SUM(D18:AE18) -> 0
AF19: =SUM(D19:AE19) -> 0
AF20: =SUM(D20:AE20) -> 0
AF21: =SUM(D21:AE21) -> 0
AF22: =SUM(D22:AE22) -> 0
AF23: =SUM(D23:AE23) -> 0
AF24: =SUM(D24:AE24) -> 0
... AF58: =SUM(D58:AE58) -> 0
A59: 合計 | D59: =SUM(D9:D58) -> 0 | E59: =SUM(E9:E58) -> 0 | F59: =SUM(F9:F58) -> 0 | G59: =SUM(G9:G58) -> 0 | H59: =SUM(H9:H58) -> 0 | I59: =SUM(I9:I58) -> 0 | J59: =SUM(J9:J58) -> 381060 | K59: =SUM(K9:K58) -> 1712160 | ... AF59: =SUM(AF9:AF58) -> 3751440

Sheet リストマスタ
A1: No | B1: 消費税 | C1: 見積有効期限 | D1: 作業形態 | E1: 作業場所 | F1: 支払条件 | G1: 摘要 | H1: 契約区分 | J1: 単位 | K1: 社員区分 | L1: 経費区分
B2: 税率 | H2: No | I2: 契約名
A3: 1 | B3: 0.1 | C3: 見積年月日より一ヶ月後 | D3: 準委任契約 | E3: 貴社内 | F3: 検収後翌月15日払い（但し、金融機関休業日の場合はその前営業日） | G3: ﾌﾟﾛｸﾞﾗﾏ | H3: 1 | I3: 固定契約 | J3: 人月 | K3: 入社済社員 | L3: BP
A4: 2 | E4: 弊社内 | F4: 検収後翌月末日払い（但し、金融機関休業日の場合はその翌営業日） | G4: ｼｽﾃﾑｴﾝｼﾞﾆｱ | H4: 2 | I4: 変動契約 | J4: 人日 | K4: 計画要員（等級1） | L4: 経費
A5: 3 | F5: 検収後翌々月10日払い（但し、金融機関休業日の場合はその翌営業日） | G5: ｵﾍﾟﾚｰﾀ | H5: 3 | I5: 時間契約 | J5: 時給 | K5: 計画要員（等級2）
A6: 4 | K6: 計画要員（等級3）
A7: 5 | K7: 計画要員（等級4）
A8: 6 | K8: 計画要員（等級5）
A9: 7 | K9: 計画要員（等級6）
A10: 8 | K10: 計画要員（等級7）
A11: 9 | K11: 計画要員（等級8）
A12: 10 | K12: 計画要員（等級9）
A13: 11
